Workbook
Name addlogo: INDEX(#REF!,MATCH(#REF!,#REF!,0))

Sheet TONGQUAN
A1: Kỳ báo cáo: | C1: Tại ngày 30 tháng 06 năm 2020 / As at 30 Jun 2020
C2: Quý II năm 2020 / Quarter II 2020
A4: Thông tin chung:
C5: Tên Công ty quản lý quỹ: | D5: Công ty Cổ phần Quản lý Quỹ Đầu tư Việt Nam
C6: Fund Management Company: | D6: Vietnam Investment Fund Management Joint Stock Company
C7: Tên ngân hàng giám sát: | D7: Ngân hàng TNHH Một thành viên Standard Chartered (Việt Nam)
C8: Supervising bank: | D8: Standard Chartered Bank (Vietnam) Limited
C9: Tên Quỹ: | D9: Quỹ Đầu tư Doanh nghiệp hàng đầu Việt Nam
C10: Fund name: | D10: Vietnam Blue Chip Fund(VFMVF4)
C11: Ngày lập báo cáo: | D11: Ngày 06 tháng 07 năm 2020
C12: Reporting Date: | D12: 06 Jul 2020
A14: Người ký báo cáo:
C16: Đại diện có thẩm quyền của Ngân hàng giám sát | F16: Đại diện có thẩm quyền của Công ty quản lý Quỹ
C17: Authorised Representative of Supervisory Bank | F17: Authorised Representative of Fund Management Company
C19: Ngân hàng TNHH MTV Standard Chartered (Việt Nam) | F19: =D5 -> Công ty Cổ phần Quản lý Quỹ Đầu tư Việt Nam
C20: Bùi Thị Huyền Trang | F20: Trần Thanh Tân
C21: Cán bộ Quản lý Nghiệp vụ Dịch vụ Chứng khoán | F21: Tổng Giám đốc
B34: STT | C34: Nội dung | D34: Tên sheet
B35: A | C35: BÁO CÁO CHUNG VỀ HOẠT ĐỘNG ĐẦU TƯ CỦA QUỸ
B36: A.I | C36: Báo cáo về tài sản | D36: 06027
B37: A.II | C37: Báo cáo kết quả hoạt động | D37: 06028
B38: A.III | C38: Báo cáo danh mục đầu tư | D38: 06029
B39: A.IV | C39: Báo cáo hoạt động vay, giao dịch mua bán lại | D39: 06026
B40: A.V | C40: Một số chỉ tiêu khác | D40: 06030
B41: A.VI | C41: Thống kê phí giao dịch | D41: 06031
B42: 5 | C42: Báo cáo thay đổi giá trị tài sản ròng, giao dịch chứng chỉ quỹ | D42: 06129
B43: 6 | C43: Báo cáo thu nhập giữa niên độ | D43: 06203
B44: 7 | C44: Báo cáo tình hình tài chính giữa niên độ | D44: 06105
B45: 8 | C45: Báo cáo thay đổi giá trị tài sản ròng, giao dịch chứng chỉ quỹ giữa niên độ | D45: 06107
B46: 9 | C46: Báo cáo danh mục đầu tư | D46: 06108
B47: 10 | C47: Báo cáo lưu chuyển tiền tệ | D47: 06262
B48: 11 | C48: Báo cáo thu nhập | D48: 06104
B49: 12 | C49: Báo cáo về tài sản của quỹ | D49: 06126
B50: B | C50: BÁO CÁO TÌNH HÌNH TỰ DOANH ĐẦU TƯ GIÁN TIẾP RA NƯỚC NGOÀI CỦA QUỸ | D50: Không có

Sheet BCthunhap
A1: Mẫu số B01g - QM. Báo cáo thu nhập Template B01g - QM. Statement of Comprehensive Income
A2: (Ban hành kèm theo Thông tư 198/2012/TT-BTC ngày 15 tháng 11 năm 2012 về chế độ kế toán áp dụng đối với quỹ mở) (Issued in association with Circular 198/2012/TT-BTC dated 15 Nov 2012 on the Accounting Policies for Open-Ended Fund)
A3: BÁO CÁO THU NHẬP STATEMENT OF COMPREHENSIVE INCOME
A5: =TONGQUAN!C2 -> Quý II năm 2020 / Quarter II 2020
A7: Tên Công ty quản lý quỹ: | D7: =TONGQUAN!D5 -> Công ty Cổ phần Quản lý Quỹ Đầu tư Việt Nam
A8: Fund Management Company: | D8: =TONGQUAN!D6 -> Vietnam Investment Fund Management Joint Stock Company
A9: Tên ngân hàng giám sát: | D9: =TONGQUAN!D7 -> Ngân hàng TNHH Một thành viên Standard Chartered (Việt Nam)
A10: Supervising bank: | D10: =TONGQUAN!D8 -> Standard Chartered Bank (Vietnam) Limited
A11: Tên Quỹ: | D11: =TONGQUAN!D9 -> Quỹ Đầu tư Doanh nghiệp hàng đầu Việt Nam
A12: Fund name: | D12: =TONGQUAN!D10 -> Vietnam Blue Chip Fund(VFMVF4)
A13: Ngày lập báo cáo: | D13: =TONGQUAN!D11 -> Ngày 06 tháng 07 năm 2020
A14: Reporting Date: | D14: =TONGQUAN!D12 -> 06 Jul 2020
A16: Chỉ tiêu Indicator | B16: Mã số Code | C16: Thuyết minh Note | D16: Năm 2020 Year 2020 | F16: Năm 2019 Year 2019
D17: =BCKetQuaHoatDong_06028!D18 -> Quý II năm 2020 Quarter II 2020 | E17: Số lũy kế Year-to-date | F17: Quý II năm 2019 Quarter II 2019 | G17: Số lũy kế Year-to-date
A18: I. THU NHẬP, DOANH THU HOẠT ĐỘNG ĐẦU TƯ Investment income | B18: 01 | D18: 91926242003 | E18: -97247010645 | F18: -6468367683 | G18: 39833212143
A19: 1.1. Cổ tức được chia Dividend income | B19: 02 | D19: 1673700000 | E19: 2081200000 | F19: 6348205000 | G19: 7547205000
A20: 1.2. Tiền lãi được nhận Interest income | B20: 03 | D20: 203123503 | E20: 444683755 | F20: 213396817 | G20: 1490454360
A21: Lãi tiền gửi ngân hàng Interest income from bank deposits | B21: 03.1 | D21: 203123503 | E21: 444683755 | F21: 213396817 | G21: 237095456
A22: Lãi chứng chỉ tiền gửi Interest income from Certificates of Deposit | B22: 03.2 | D22: 0 | E22: 0 | F22: 0 | G22: 929523288
A23: Lãi trái phiếu Interest income from bonds | B23: 03.3 | D23: 0 | E23: 0 | F23: 0 | G23: 323835616
A24: Tiền lãi hợp đồng mua lại đảo ngược được nhận Reverse repo contract interest received | B24: 03.4 | D24: 0 | E24: 0 | F24: 0 | G24: 0
A25: 1.3. Lãi (lỗ) bán các khoản đầu tư Realized gain (losses) from disposal investments | B25: 04 | D25: -9574059758 | E25: -44439213945 | F25: -19147228770 | G25: -36105615007
A26: 1.4. Chênh lệch tăng, giảm đánh giá lại các khoản đầu tư chưa thực hiện Unrealized gain (losses) from investment revaluation | B26: 05 | D26: 99623478258 | E26: -55333680455 | F26: 6117259270 | G26: 66901167790
A27: 1.5. Doanh thu khác Other income | B27: 06 | D27: 0 | E27: 0 | F27: 0 | G27: 0
A28: 1.6. Chênh lệch lãi, lỗ tỷ giá hối đoái đã và chưa thực hiện Realized and unrealized gain (losses) from foreign exchange | B28: 07 | D28: 0 | E28: 0 | F28: 0 | G28: 0
A29: 1.7. Doanh thu khác về đầu tư Other investment income | B29: 08 | D29: 0 | E29: 0 | F29: 0 | G29: 0
... A77: VIII. LỢI NHUẬN KẾ TOÁN SAU THUẾ TNDN PROFIT AFTER TAX (41=30-40) | B77: 41 | D77: 89373950354 | E77: -103327609059 | F77: -11205262934 | G77: 29592793859
A80: Người lập: | B80: Người duyệt:
A93: _______________________________________________ | B93: ___________________________________________ | F93: _____________________________
A94: Phạm Thị Như Thảo | B94: Nguyễn Minh Đăng Khánh | F94: Trần Thanh Tân
A95: Kế toán Quỹ | B95: Phó Tổng Giám đốc kiêm Giám đốc Tài chính | F95: Tổng Giám đốc

Sheet BCtinhhinhtaichinh
A1: Mẫu số B02g - QM. Báo cáo tình hình tài chính Template B02g - QM. Statement of Financial Position
A2: (Ban hành kèm theo Thông tư 198/2012/TT-BTC ngày 15 tháng 11 năm 2012 về chế độ kế toán áp dụng đối với quỹ mở) (Issued in association with Circular 198/2012/TT-BTC dated 15 Nov 2012 on the Accounting Policies for Open-Ended Fund)
A3: BÁO CÁO TÌNH HÌNH TÀI CHÍNH STATEMENT OF FINANCIAL POSITION
A5: =TONGQUAN!C1 -> Tại ngày 30 tháng 06 năm 2020 / As at 30 Jun 2020
A7: Tên Công ty quản lý quỹ: | C7: =TONGQUAN!D5 -> Công ty Cổ phần Quản lý Quỹ Đầu tư Việt Nam
A8: Fund Management Company: | C8: =TONGQUAN!D6 -> Vietnam Investment Fund Management Joint Stock Company
A9: Tên ngân hàng giám sát: | C9: =TONGQUAN!D7 -> Ngân hàng TNHH Một thành viên Standard Chartered (Việt Nam)
A10: Supervising bank: | C10: =TONGQUAN!D8 -> Standard Chartered Bank (Vietnam) Limited
A11: Tên Quỹ: | C11: =TONGQUAN!D9 -> Quỹ Đầu tư Doanh nghiệp hàng đầu Việt Nam
A12: Fund name: | C12: =TONGQUAN!D10 -> Vietnam Blue Chip Fund(VFMVF4)
A13: Ngày lập báo cáo: | C13: =TONGQUAN!D11 -> Ngày 06 tháng 07 năm 2020
A14: Reporting Date: | C14: =TONGQUAN!D12 -> 06 Jul 2020
A16: STT No. | B16: Chỉ tiêu Indicator | C16: Mã số Code | D16: Thuyết minh Note | E16: =BCTaiSan_06027!D18 -> Ngày 30 tháng 06 năm 2020 As at 30 Jun 2020 | F16: =BCTaiSan_06027!E18 -> Ngày 31 tháng 03 năm 2020 As at 31 Mar 2020
A17: I | B17: I. TÀI SẢN ASSETS | C17: I
A18: 1 | B18: 1.Tiền gửi ngân hàng và tương đương tiền Cash at bank and cash equivalent | C18: 110 | E18: 13504541103 | F18: 51265696867
A19: 1.1 | B19: 1.1. Tiền gửi ngân hàng Cash at bank | C19: 111 | E19: 8504541103 | F19: 36265696867
B20: Tiền gửi của nhà đầu tư cho hoạt động mua chứng chỉ quỹ Cash at bank for Fund's subscription | C20: 111.1 | E20: 8000000 | F20: 7000000
B21: Tiền phải trả cho Nhà đầu tư về mua lại Chứng chỉ quỹ Cash at bank for Fund's redemption | C21: 111.2 | E21: 14789498 | F21: 584312861
B22: Tiền gửi ngân hàng cho hoạt động của Quỹ Cash at bank for Fund's operation | C22: 111.3 | E22: 8481669359 | F22: 11750871898
B23: Tiền gửi ký quỹ cho hoạt động đầu tư chứng khoán phái sinh Margin account for trading derivatives | C23: 111.4 | E23: 82246 | F23: 23923512108
A24: 1.2 | B24: 1.2. Tiền gửi có kỳ hạn dưới ba (03) tháng Deposit with term less than three (03) months | C24: 112 | E24: 5000000000 | F24: 15000000000
A25: 2 | B25: 2. Các khoản đầu tư thuần Net Investments | C25: 120 | E25: 418780070000 | F25: 279586497500
A26: 2.1 | B26: 2.1. Các khoản đầu tư Investments | C26: 121 | E26: 418780070000 | F26: 279586497500
B27: Cổ phiếu niêm yết Listed Shares | C27: 121.1 | E27: 418780070000 | F27: 279586497500
B28: Cổ phiếu chưa niêm yết Unlisted Shares | C28: 121.2 | E28: 0 | F28: 0
B29: Trái phiếu niêm yết Listed Bonds | C29: 121.3 | E29: 0 | F29: 0
B30: Trái phiếu chưa niêm yết Unlisted Bonds | C30: 121.4 | E30: 0 | F30: 0
B31: Chứng chỉ tiền gửi Certificates of Deposit | C31: 121.5 | E31: 0 | F31: 0
B32: Hợp đồng tiền gửi có kỳ hạn trên ba (03) tháng Deposits with term over three (03) months | C32: 121.6 | E32: 0 | F32: 0
B33: Quyền mua chứng khoán Investment - Rights | C33: 121.7 | E33: 0 | F33: 0
B34: Hợp đồng tương lai chỉ số Index future contracts | C34: 121.8 | E34: 0 | F34: 0
B35: Đầu tư khác Other Investments | C35: 121.9 | E35: 0 | F35: 0
B36: Hợp đồng mua lại đảo ngược Reverse repo contracts | C36: 121.10 | E36: 0 | F36: 0
A37: 2.2 | B37: 2.2. Dự phòng giảm giá tài sản nhận thế chấp Impairment of devaluation of pledged assets | C37: 122 | E37: 0 | F37: 0
A38: 3 | B38: 3. Các khoản phải thu Receivables | C38: 130 | E38: 249315068 | F38: 360616437
A39: 3.1 | B39: 3.1 Phải thu về bán các khoản đầu tư Receivables from investments sold but not yet settled | C39: 131 | E39: 0 | F39: 0
B40: Trong đó: Phải thu khó đòi về bán các khoản đầu tư In which: Overdue receivables from selling investments | C40: 132 | E40: 0 | F40: 0
A41: 3.2 | B41: 3.2. Phải thu và dự thu cổ tức, tiền lãi các khoản đầu tư Dividend and interest receivables | C41: 133 | E41: 249315068 | F41: 360616437
A42: 3.2.1 | B42: 3.2.1. Phải thu cổ tức, tiền lãi đến ngày nhận Dividend and interest receivables on or after payment date | C42: 134 | E42: 0 | F42: 0
B43: Phải thu cổ tức Dividend receivables | C43: 134.1 | E43: 0 | F43: 0
B44: Phải thu trái tức Coupon receivables | C44: 134.2 | E44: 0 | F44: 0
B45: Phải thu lãi tiền gửi có kỳ hạn dưới 3 tháng Interest receivables from deposit with term less than three (03) months | C45: 134.3 | E45: 0 | F45: 0
B46: Phải thu lãi tiền gửi có kỳ hạn trên 3 tháng Interest receivables from deposit with term more than three (03) months | C46: 134.4 | E46: 0 | F46: 0
B47: Phải thu lãi chứng chỉ tiền gửi Interest receivables from Certificates of Deposit | C47: 134.5 | E47: 0 | F47: 0
B48: Trong đó: Phải thu khó đòi về cổ tức, tiền lãi đến ngày nhận nhưng chưa nhận được In which: Overdue receivables from dividend, interest income | C48: 135 | E48: 0 | F48: 0
A49: 3.2.2 | B49: 3.2.2.Dự thu cổ tức, tiền lãi chưa đến ngày nhận Dividend and interest receivables before payment date | C49: 136 | E49: 249315068 | F49: 360616437
B50: Dự thu cổ tức Dividend receivables | C50: 136.1 | E50: 240000000 | F50: 345000000
B51: Dự thu lãi trái phiếu Interest accrual from bonds | C51: 136.2 | E51: 0 | F51: 0
B52: Dự thu lãi tiền gửi có kỳ hạn dưới 3 tháng Interest accrual from deposits with term less than three (03) months | C52: 136.3 | E52: 9315068 | F52: 15616437
B53: Dự thu lãi tiền gửi có kỳ hạn trên 3 tháng Interest accrual from deposit with term more than three (03) months | C53: 136.4 | E53: 0 | F53: 0
B54: Dự thu lãi chứng chỉ tiền gửi Interest accrual from Certificates of Deposit | C54: 136.5 | E54: 0 | F54: 0
B55: Dự thu lãi hợp đồng mua lại đảo ngược Interest receivables from reverse repo contracts | C55: 136.6 | E55: 0 | F55: 0
A56: 3.3 | B56: 3.3. Các khoản phải thu khác Other receivables | C56: 137 | E56: 0 | F56: 0
B57: Phải thu cho khoản cổ phiếu hạn chế chờ mua Receivable from AP/Investors on securities on hold of buying | C57: 137.1 | E57: 0 | F57: 0
B58: Các tài sản khác Other assets | C58: 137.2 | E58: 0 | F58: 0
B59: Các khoản khác Others | C59: 137.3 | E59: 0 | F59: 0
A60: 3.4 | B60: 3.4. Dự phòng nợ phải thu khó đòi Provision for doubtful debt | C60: 138 | E60: 0 | F60: 0
B61: TỔNG TÀI SẢN TOTAL ASSETS | C61: 100 | E61: 432533926171 | F61: 331212810804
A62: II | B62: II. NỢ PHẢI TRẢ TOTAL LIABILITIES | C62: II
A63: 1 | B63: 1. Vay ngắn hạn Short-term loans | C63: 311 | E63: 0 | F63: 0
B64: Gốc hợp đồng repo Repo contracts - Principal | C64: 311.1 | E64: 0 | F64: 0
B65: Vay ngắn hạn Short-term loans | C65: 311.2 | E65: 0 | F65: 0
A66: 2 | B66: 2. Phải trả về mua các khoản đầu tư Payables for securities bought but not yet settled | C66: 312 | E66: 4476492000 | F66: 0
A67: 3 | B67: 3. Phải trả phí cho các Đại lý phân phối, Công ty quản lý quỹ về mua bán Chứng chỉ quỹ Subscription and Redemption fee payable to distributors and fund management company | C67: 313 | E67: 51478829 | F67: 603503865
B68: Phải trả phí cho các Đại lý phân phối về mua bán Chứng chỉ quỹ Subscription and Redemption fee payable to distributors | C68: 313.1 | E68: 36689000 | F68: 4421926
B69: Phải trả phí cho Công ty quản lý quỹ về mua bán Chứng chỉ quỹ Subscription and Redemption fee payable to fund management company | C69: 313.2 | E69: 14789829 | F69: 599081939
A70: 4 | B70: 4. Thuế và các khoản phải nộp Nhà nước Tax payables and obligations to the State Budget | C70: 314 | E70: 2266631 | F70: 60041380
A71: 5 | B71: 5.Phải trả thu nhập cho Nhà đầu tư Profit distribution payables | C71: 315 | E71: 83000000 | F71: 83000000
A72: 6 | B72: 6. Chi phí phải trả Expense Accruals | C72: 316 | E72: 177918438 | F72: 297685726
B73: Phí giao dịch Transaction fee | C73: 316.1 | E73: 6714738 | F73: 0
B74: Phải trả phí môi giới Brokerage fee payables | C74: 316.1.1 | E74: 6714738 | F74: 0
B75: Phải trả phí giao dịch thanh toán bù trừ chứng khoán Clearing Settlement Fee payables | C75: 316.1.2 | E75: 0 | F75: 0
B76: Trích trước phí kiểm toán Accrued expense for audit fee | C76: 316.2 | E76: 84784154 | F76: 212892077
B77: Trích trước phí họp đại hội thường niên Accrued expense for Annual General meeting | C77: 316.3 | E77: 35386313 | F77: 36744033
B78: Trích trước phí báo cáo thường niên Accrued expense for Annual report | C78: 316.4 | E78: 33066000 | F78: 33066000
B79: Trích trước thù lao ban đại diện quỹ Accrued expense for Remuneration Payable to Fund's Board of Representatives | C79: 316.5 | E79: 17967233 | F79: 14983616
B80: Trích trước phí quản lý niêm yết hàng năm tại SGDCK Accrued expense for annual listing fee at HOSE | C80: 316.6 | E80: 0 | F80: 0
B81: Trích trước lãi vay ngắn hạn của hợp đồng vay và hợp đồng repo Accrued Interest Expense of short-term loan contracts and repo contracts | C81: 316.7 | E81: 0 | F81: 0
A82: 7 | B82: 7. Phải trả cho Nhà đầu tư về mua Chứng chỉ quỹ Subscription payables to investors | C82: 317 | E82: 52095900 | F82: 86095900
B83: Phải trả cho nhà đầu tư chờ mua chứng chỉ quỹ Subscription Pending allotment | C83: 317.1 | E83: 52095900 | F83: 86095900
B84: Phải trả nhà đầu tư trên tài sản giữ hộ Payables to investors for investment bought on behalf | C84: 317.2 | E84: 0 | F84: 0
A85: 8 | B85: 8. Phải trả cho Nhà đầu tư về mua lại Chứng chỉ quỹ Redemption payables to investors | C85: 318 | E85: 82912784 | F85: 1132371244
A86: 9 | B86: 9. Phải trả dịch vụ quản lý Quỹ mở Fund management related service expense payable | C86: 319 | E86: 780199454 | F86: 831021029
B87: Trích trước phải trả phí quản lý Accrued expense for Management fee | C87: 319.1 | E87: 707895540 | F87: 749309010
B88: Trích trước phí lưu ký tài sản Quỹ mở Accrued expense for Custodian fee | C88: 319.2 | E88: 23900000 | F88: 32600000
B89: Phí dịch vụ lưu ký - bảo quản tài sản Custodian service - Safe Custody Fee | C89: 319.2.1 | E89: 22000000 | F89: 22000000
B90: Phí dịch vụ lưu ký - giao dịch chứng khoán Custodian service - Transaction fee | C90: 319.2.2 | E90: 1900000 | F90: 10600000
B91: Phí dịch vụ lưu ký cho chứng khoán cơ sở, phí quản lý vị thế và tài sản phái sinh trả cho VSD Custodian service - Depository fee, Position and Margin management fee paid to VSD | C91: 319.2.3 | E91: 0 | F91: 0
B92: Trích trước phí quản trị quỹ Accrued expense for Fund administration fee | C92: 319.3 | E92: 12103914 | F92: 12812019
B93: Trích trước phí giám sát Accrued expense for Supervising fee | C93: 319.4 | E93: 25300000 | F93: 25300000
B94: Trích trước phí dịch vụ đại lý chuyển nhượng Accrued expense for Tranfer agency fee | C94: 319.5 | E94: 11000000 | F94: 11000000
B95: Dự chi phí cung cấp dịch vụ tính giá trị tài sản ròng tham chiếu (iNAV) cho HOSE Accrued expense for payable to HOSE for iNAV calculation | C95: 319.6 | E95: 0 | F95: 0
B96: Dự chi phí cấp quyền sử dụng chỉ số cho HOSE Accrued expense for payable to HOSE for Index usage | C96: 319.7 | E96: 0 | F96: 0
A97: 10 | B97: 10. Phải trả, phải nộp khác Other payables | C97: 320 | E97: 37054239 | F97: 37054239
B98: Phải trả phí báo giá Price feed fee payable | C98: 320.1 | E98: 0 | F98: 0
B99: Trích trước phí công tác, họp của ban đại diện Accrued expense for Fund's Board of Representatives travelling, meeting | C99: 320.2 | E99: 37054239 | F99: 37054239
B100: Trích trước phí quản lý thường niên trả cho UBCKNN Accrued expense for Annual Fee paid to SSC | C100: 320.3 | E100: 0 | F100: 0
B101: Phí Ngân hàng S2B S2B Bank charge | C101: 320.4 | E101: 0 | F101: 0
B102: Phải trả khác Other payables | C102: 320.5 | E102: 0 | F102: 0
B103: TỔNG NỢ PHẢI TRẢ TOTAL LIABILITIES | C103: 300 | E103: 5743418275 | F103: 3130773383
...

Sheet BCLCGT_06262
A1: Mẫu số B05g - QM. Báo cáo lưu chuyển tiền tệ Template B05g - QM. Cash flow statement
A2: (Ban hành kèm theo Thông tư 198/2012/TT-BTC ngày 15 tháng 11 năm 2012 về chế độ kế toán áp dụng đối với quỹ mở) (Issued in association with Circular 198/2012/TT-BTC dated 15 Nov 2012 on the Accounting Policies for Open-Ended Fund)
A3: BÁO CÁO LƯU CHUYỂN TIỀN TỆ CASH FLOW STATEMENT
A4: =TONGQUAN!C2 -> Quý II năm 2020 / Quarter II 2020
A7: Tên Công ty quản lý quỹ: | B7: =TONGQUAN!D5 -> Công ty Cổ phần Quản lý Quỹ Đầu tư Việt Nam
A8: Fund Management Company: | B8: =TONGQUAN!D6 -> Vietnam Investment Fund Management Joint Stock Company
A9: Tên ngân hàng giám sát: | B9: =TONGQUAN!D7 -> Ngân hàng TNHH Một thành viên Standard Chartered (Việt Nam)
A10: Supervising bank: | B10: =TONGQUAN!D8 -> Standard Chartered Bank (Vietnam) Limited
A11: Tên Quỹ: | B11: =TONGQUAN!D9 -> Quỹ Đầu tư Doanh nghiệp hàng đầu Việt Nam
A12: Fund name: | B12: =TONGQUAN!D10 -> Vietnam Blue Chip Fund(VFMVF4)
A13: Ngày lập báo cáo: | B13: =TONGQUAN!D11 -> Ngày 06 tháng 07 năm 2020
A14: Reporting Date: | B14: =TONGQUAN!D12 -> 06 Jul 2020
A17: Chỉ tiêu Indicator | B17: Mã số Code | C17: Thuyết minh Note | D17: =BCKetQuaHoatDong_06028!D18 -> Quý II năm 2020 Quarter II 2020 | E17: =BCKetQuaHoatDong_06028!E18 -> Quý I năm 2020 Quarter I 2020
A18: I. Lưu chuyển tiền từ hoạt động đầu tư Cash flow from investing activities | B18: I
A19: 1. Lợi nhuận trước Thuế thu nhập doanh nghiệp Profit before income tax | B19: 01 | D19: 89373950354 | E19: -192701559413
A20: 2. Điều chỉnh cho các khoản tăng giá trị tài sản ròng từ các hoạt động đầu tư Adjustment for NAV increase from investing activities | B20: 02 | D20: -99752943901 | E20: 154999550790
A21: (- Lãi) hoặc (+ lỗ) chênh lệch tỷ giá hối đoái/ đánh giá lại các khoản đầu tư chưa thực hiện Unreliased (Gain) or Loss from FX valuation/Investment revaluation | B21: 03 | D21: -99623478258 | E21: 154957158713
A22: (+) Chi phí trích trước Increase of Accrued Expenses | B22: 04 | D22: -129465643 | E22: 42392077
A23: 3. Lợi nhuận từ hoạt động đầu tư trước thay đổi vốn lưu động Profit from investing activities before changes in working capital | B23: 05 | D23: -10378993547 | E23: -37702008623
A24: (-) Tăng, (+) giảm đầu tư (Increase), Decrease Investments | B24: 20 | D24: -39570094242 | E24: 138161393787
A25: (-) Tăng, (+) giảm phải thu bán chứng khoán đầu tư (Increase), Decrease in Receivables from investments sold but not yet settled | B25: 06 | D25: 0 | E25: 860897000
A26: (-) Tăng, (+) giảm dự thu phải thu tiền lãi các khoản đầu tư (Increase), Decrease in Dividend and interest receivables | B26: 07 | D26: 111301369 | E26: 1683303562
A27: (-) Tăng, (+) giảm các khoản phải thu khác (Increase), Decrease in other receivables | B27: 08 | D27: 0 | E27: 0
A28: (+) Tăng, (-) giảm vay ngắn hạn Increase, (Decrease) in Short-term Loans | B28: 09 | D28: 0 | E28: 0
A29: (+) Tăng, (-) giảm phải trả cho người bán (Decrease), Increase in payables for securities purchased but not yet settled | B29: 10 | D29: 4476492000 | E29: -1560750000
A30: (+) Tăng, (-) giảm phải trả các Đại lý phân phối Chứng chỉ quỹ, Công ty Quản lý Quỹ (Decrease)/increase in subscription and redemption fee payable to distributors and Fund Management Company | B30: 11 | D30: -552025036 | E30: 519396804
... A38: Lưu chuyển tiền thuần từ hoạt động đầu tư (1+2+3) Net Cash flow from Investing activities | B38: 19 | D38: -47095675885 | E38: 101682539040
A39: II. Lưu chuyển tiền từ hoạt động tài chính Cash flow from financing activities | B39: II
A40: 1. Tiền thu từ phát hành Chứng chỉ quỹ mở Receipts from subscriptions | B40: 31 | D40: 17059020369 | E40: 25096350158
A41: 2. Tiền chi mua lại Chứng chỉ quỹ mở Payments for redemptions | B41: 32 | D41: -7724500248 | E41: -122282601242
A42: 3. Tiền vay gốc Principal of borrowings | B42: 33 | D42: 0 | E42: 0
A43: 4. Tiền chi trả nợ gốc vay Payment of Principal borrowings | B43: 34 | D43: 0 | E43: 0
A44: 5. Tiền chi trả cổ tức, tiền lãi cho nhà đầu tư Dividend, profit distribution paid to investors | B44: 35 | D44: 0 | E44: 0
A45: Lưu chuyển tiền thuần từ hoạt động tài chính (1-2+3-4-5) Net cash outflows from financing activities | B45: 30 | D45: 9334520121 | E45: -97186251084
A46: III. Tăng/giảm tiền thuần trong kỳ Net Increase/Decrease in cash and cash equivalent for the period | B46: 40 | D46: -37761155764 | E46: 4496287956
A47: IV. Tiền và các khoản tương đương tiền đầu kỳ Cash and cash equivalents at the beginning of period | B47: 50 | D47: 51265696867 | E47: 46769408911
A48: Tiền gửi ngân hàng đầu kỳ: Cash at bank of the beginning of period: | B48: 51 | D48: 51265696867 | E48: 46769408911
A49: -Tiền gửi ngân hàng và tương đương tiền cho hoạt động của Quỹ Cash at bank and cash equivalent for Fund's operation | B49: 52 | D49: 50674384006 | E49: 46742616131
A50: Tiền gửi không kỳ hạn Demand deposit | B50: 52.1 | D50: 11750871898 | E50: 26742616131
A51: Tiền gửi có kỳ hạn dưới ba (03) tháng Deposits with term under three (03) months | B51: 52.2 | D51: 15000000000 | E51: 20000000000
... A64: Khác Others | B64: 80 | D64: 0 | E64: 0
A67: Người lập: | C67: Người duyệt:
A78: _______________________________ | B78: _______________________________________ | E78: ______________________
A79: Phạm Thị Như Thảo | B79: Nguyễn Minh Đăng Khánh | E79: Trần Thanh Tân
A80: Kế toán Quỹ | B80: Phó Tổng Giám đốc kiêm Giám đốc Tài chính | E80: Tổng Giám đốc

Sheet BCTaiSan_06027
A1: Phụ lục số 03. Mẫu báo cáo hoạt động đầu tư của quỹ mở Appendix 03. Report on Open ended Fund's Investment Activities
A2: (Ban hành kèm theo Thông tư số 91/2019/TT-BTC ngày 31 tháng 12 năm 2019 của Bộ trưởng Bộ Tài chính sửa đổi, bổ sung một số Thông tư quy định về chế độ báo cáo và thủ tục hành chính áp dụng với công ty quản lý quỹ, quỹ đầu tư chứng khoán và công ty đầu tư chứng khoán) (Issued in association with Circular 91/2019/TT-BTC dated 31 December 2019 of the Minister of Finance on amending and supplementing several Circulars on the reporting regime and administrative procedures applicable to fund management company, investment fund and investment company)
A3: BÁO CÁO HOẠT ĐỘNG ĐẦU TƯ CỦA QUỸ MỞ REPORT ON OPEN ENDED FUND'S INVESTMENT ACTIVITIES
A5: =TONGQUAN!C1 -> Tại ngày 30 tháng 06 năm 2020 / As at 30 Jun 2020
A7: Tên Công ty quản lý quỹ: | C7: =TONGQUAN!D5 -> Công ty Cổ phần Quản lý Quỹ Đầu tư Việt Nam
A8: Fund Management Company: | C8: =TONGQUAN!D6 -> Vietnam Investment Fund Management Joint Stock Company
A9: Tên ngân hàng giám sát: | C9: =TONGQUAN!D7 -> Ngân hàng TNHH Một thành viên Standard Chartered (Việt Nam)
A10: Supervising bank: | C10: =TONGQUAN!D8 -> Standard Chartered Bank (Vietnam) Limited
A11: Tên Quỹ: | C11: =TONGQUAN!D9 -> Quỹ Đầu tư Doanh nghiệp hàng đầu Việt Nam
A12: Fund name: | C12: =TONGQUAN!D10 -> Vietnam Blue Chip Fund(VFMVF4)
A13: Ngày lập báo cáo: | C13: =TONGQUAN!D11 -> Ngày 06 tháng 07 năm 2020
A14: Reporting Date: | C14: =TONGQUAN!D12 -> 06 Jul 2020
A16: A. | B16: BÁO CÁO CHUNG VỀ HOẠT ĐỘNG ĐẦU TƯ CỦA QUỸ/GENERAL INFORMATION ON FUND'S INVESTMENT ACTIVITIES
A17: I | B17: BÁO CÁO VỀ TÀI SẢN / ASSET REPORT
A18: STT No | B18: Nội dung Indicator | C18: Mã chỉ tiêu Code | D18: Ngày 30 tháng 06 năm 2020 As at 30 Jun 2020 | E18: Ngày 31 tháng 03 năm 2020 As at 31 Mar 2020 | F18: %/cùng kỳ năm trước %/against last year
A19: I | B19: TÀI SẢN ASSETS | C19: 2200
A20: I.1 | B20: Tiền và các khoản tương đương tiền Cash and Cash Equivalents | C20: 2201 | D20: 13504541103 | E20: 51265696867 | F20: 0.2548239
B21: Tiền Cash | C21: 2202 | D21: 0 | E21: 0
B22: Tiền gửi ngân hàng Cash at bank | C22: 2203 | D22: 8504541103 | E22: 36265696867 | F22: 0.25774787
B23: Tiền gửi của nhà đầu tư cho hoạt động mua chứng chỉ quỹ Cash at bank for Fund's subscription | C23: 2203.1 | D23: 8000000 | E23: 7000000 | F23: 0.66666667
B24: Tiền phải trả cho Nhà đầu tư về mua lại chứng chỉ quỹ Cash at bank for Fund's redemption | C24: 2203.2 | D24: 14789498 | E24: 584312861 | F24: 0.0046042276
B25: Tiền gửi ngân hàng cho hoạt động của Quỹ Cash at bank for Fund's operation | C25: 2203.3 | D25: 8481669359 | E25: 11750871898 | F25: 0.28489295
B26: Tiền gửi ký quỹ cho hoạt động đầu tư chứng khoán phái sinh Margin account for trading derivatives | C26: 2203.4 | D26: 82246 | E26: 23923512108
B27: Các khoản tương đương tiền Cash Equivalents | C27: 2204 | D27: 5000000000 | E27: 15000000000 | F27: 0.25
A28: I.2 | B28: Các khoản đầu tư (kê chi tiết) Investments | C28: 2205 | D28: 418780070000 | E28: 279586497500 | F28: 0.57528409
B29: Cổ phiếu niêm yết Listed shares | C29: 2205.1 | D29: 418780070000 | E29: 279586497500 | F29: 0.57528409
B30: Cổ phiếu chưa niêm yết Unlisted shares | C30: 2205.2 | D30: 0 | E30: 0
B31: Trái phiếu Bonds | C31: 2205.3 | D31: 0 | E31: 0
B32: Chứng chỉ tiền gửi Certificates of Deposit | C32: 2205.4 | D32: 0 | E32: 0
B33: Hợp đồng tiền gửi có kỳ hạn trên ba (03) tháng Deposits with term over three (03) months | C33: 2205.5 | D33: 0 | E33: 0
B34: Quyền mua chứng khoán Investment - Rights | C34: 2205.6 | D34: 0 | E34: 0
B35: Hợp đồng tương lai chỉ số Index future contracts | C35: 2205.7 | D35: 0 | E35: 0
B36: Đầu tư khác Other investments | C36: 2205.8 | D36: 0 | E36: 0
B37: Hợp đồng mua lại đảo ngược Reverse repo contracts | C37: 2205.9 | D37: 0 | E37: 0
A38: I.3 | B38: Phải thu cổ tức, trái tức Dividend, Coupon receivables | C38: 2206 | D38: 240000000 | E38: 345000000 | F38: 0.41958042
B39: Phải thu cổ tức Dividend receivables | C39: 2206.1 | D39: 240000000 | E39: 345000000 | F39: 0.41958042
B40: Phải thu trái tức Coupon receivables | C40: 2206.2 | D40: 0 | E40: 0
A41: I.4 | B41: Lãi được nhận Interest receivables | C41: 2207 | D41: 9315068 | E41: 15616437 | F41: 0.18181817
B42: Phải thu lãi tiền gửi Interest receivable from bank deposits | C42: 2207.1 | D42: 9315068 | E42: 15616437 | F42: 0.18181817
B43: Phải thu lãi chứng chỉ tiền gửi Interest receivable from Certificates of Deposit | C43: 2207.2 | D43: 0 | E43: 0
B44: Phải thu lãi hợp đồng mua lại đảo ngược Interest receivable from reverse repo contracts | C44: 2207.3 | D44: 0 | E44: 0
A45: I.5 | B45: Tiền bán chứng khoán chờ thu Securities Trading Receivables | C45: 2208 | D45: 0 | E45: 0 | F45: 0
A46: I.6 | B46: Các khoản phải thu khác Other Receivables | C46: 2210 | D46: 0 | E46: 0
B47: Dự phòng giảm giá tài sản nhận thế chấp Impairment of devaluation of pledged assets | C47: 2210.1 | D47: 0 | E47: 0
B48: Dự phòng nợ phải thu khó đòi Provision for doubtful debt | C48: 2210.2 | D48: 0 | E48: 0
B49: Các khoản phải thu khác Other Receivables | C49: 2210.3 | D49: 0 | E49: 0
A50: I.7 | B50: Các tài sản khác Other Assets | C50: 2211 | D50: 0 | E50: 0
A51: I.8 | B51: TỔNG TÀI SẢN TOTAL ASSETS | C51: 2212 | D51: 432533926171 | E51: 331212810804 | F51: 0.55259919
A52: II | B52: NỢ LIABILITIES | C52: 2213
A53: II.1 | B53: Tiền phải thanh toán mua chứng khoán Securities Trading Payables | C53: 2214 | D53: 4476492000 | E53: 0 | F53: 1.3952578
A54: II.2 | B54: Các khoản phải trả khác Other Payables | C54: 2215 | D54: 1266926275 | E54: 3130773383 | F54: 0.15410136
B55: Phải trả nhà đầu tư Payables to investors | C55: 2215.1 | D55: 135008684 | E55: 1218467144 | F55: 0.021302522
B56: Phải trả cho nhà đầu tư chờ mua chứng chỉ quỹ Subscription Pending allotment | C56: 2215.1.1 | D56: 52095900 | E56: 86095900 | F56: 0.77298322
B57: Phải trả nhà đầu tư trên tài sản giữ hộ Payables to investors for investment bought on behalf | C57: 2215.1.2 | D57: 0 | E57: 0
B58: Phải trả nhà đầu tư trên cổ tức đã thu Payables to investors for collected dividend | C58: 2215.1.3 | D58: 0 | E58: 0
B59: Phải trả cho Nhà đầu tư về mua lại chứng chỉ quỹ Redemption payable to investors | C59: 2215.1.4 | D59: 82912784 | E59: 1132371244 | F59: 0.013223119
B60: Thuế và các khoản phải nộp Nhà nước Tax payables and obligations to the State Budget | C60: 2215.2 | D60: 2266631 | E60: 60041380 | F60: 0.11376259
B61: Phải trả phí phát hành, mua lại chứng chỉ quỹ cho Đại lý phân phối và Công ty quản lý quỹ Subscription and Redemption fee payable to distributors and Fund Management Company | C61: 2215.3 | D61: 51478829 | E61: 603503865 | F61: 0.22797966
B62: Phải trả thu nhập cho nhà đầu tư Income payable to investors | C62: 2215.4 | D62: 83000000 | E62: 83000000 | F62: 1
B63: Phải trả thù lao Ban đại diện quỹ Remuneration Payable to Fund's Board of Representatives | C63: 2215.5 | D63: 17967233 | E63: 14983616 | F63: 0.80073685
B64: Phải trả phí quản lý cho công ty quản lý quỹ Management fee payable | C64: 2215.6 | D64: 707895540 | E64: 749309010 | F64: 0.58094692
B65: Phải trả phí quản trị quỹ Fund Administration fee payable | C65: 2215.7 | D65: 12103914 | E65: 12812019 | F65: 0.58094697
B66: Phải trả phí giám sát Supervisory service fee payable | C66: 2215.8 | D66: 25300000 | E66: 25300000 | F66: 0.91073583
B67: Phí giao dịch Transaction fee | C67: 2215.9 | D67: 6714738 | E67: 0 | F67: 1.0261627
B68: Phải trả phí môi giới Brokerage fee payable | C68: 2215.9.1 | D68: 6714738 | E68: 0 | F68: 1.0261627
B69: Phải trả phí phát hành thanh toán bù trừ chứng khoán Clearing Settlement fee payable | C69: 2215.9.2 | D69: 0 | E69: 0
B70: Trích trước phí lưu ký tài sản Quỹ mở Accrued expense for Custodian fee | C70: 2215.10 | D70: 23900000 | E70: 32600000 | F70: 0.75265385
B71: Phí lưu ký - bảo quản tài sản Custodian service - Safe Custody Fee | C71: 2215.10.1 | D71: 22000000 | E71: 22000000 | F71: 0.8711386
B72: Phí lưu ký - giao dịch chứng khoán Custodian service - Transaction fee | C72: 2215.10.2 | D72: 1900000 | E72: 10600000 | F72: 0.29230769
B73: Phí lưu ký cho chứng khoán cơ sở, phí quản lý vị thế và tài sản phái sinh trả cho VSD Custodian service - Depository fee, Position and Margin management fee paid to VSD | C73: 2215.10.3 | D73: 0 | E73: 0
B74: Phải trả phí kiểm toán Audit fee payable | C74: 2215.11 | D74: 84784154 | E74: 212892077 | F74: 1.0027778
B75: Phải trả phí họp đại hội thường niên General meeting expense payable | C75: 2215.12 | D75: 35386313 | E75: 36744033 | F75: 0.64379612
B76: Phải trả phí báo cáo thường niên Annual report fee payable | C76: 2215.13 | D76: 33066000 | E76: 33066000 | F76: 0.66849798
B77: Phải trả phí dịch vụ đại lý chuyển nhượng Transfer Agency fee payable | C77: 2215.14 | D77: 11000000 | E77: 11000000 | F77: 1
B78: Dự chi phí tính giá trị tài sản ròng tham chiếu (iNAV) cho HOSE Service fee payable to HOSE for calculating iNAV | C78: 2215.15 | D78: 0 | E78: 0
B79: Dự chi phí cấp quyền sử dụng chỉ số cho HOSE Authorising index service fee payable to HOSE | C79: 2215.16 | D79: 0 | E79: 0
B80: Phải trả khác Other payables | C80: 2215.17 | D80: 37054239 | E80: 37054239 | F80: 1.3663098
B81: Phải trả phí báo giá Price feed fee payable | C81: 2215.17.1 | D81: 0 | E81: 0 | F81: 0
B82: Trích trước phí công tác, họp của ban đại diện Accrued expense for Fund's Board of Representatives travelling, meeting | C82: 2215.17.2 | D82: 37054239 | E82: 37054239 | F82: 2.3297315
B83: Trích trước phí quản lý thường niên trả UBCKNN Accrued expense for Annual Management Fee pay to SSC | C83: 2215.17.3 | D83: 0 | E83: 0
B84: Phải trả khác Other payables | C84: 2215.17.4 | D84: 0 | E84: 0
B85: Vay ngắn hạn - hợp đồng repo Short-term loans - Repo contracts | C85: 2215.18 | D85: 0 | E85: 0
B86: Gốc hợp đồng repo Principal of repo contracts | C86: 2215.18.1 | D86: 0 | E86: 0
B87: Trích trước lãi vay ngắn hạn Accrued Interest Expense | C87: 2215.18.2 | D87: 0 | E87: 0
B88: Gốc vay ngắn hạn Principal of Short-term loans | C88: 2215.18.3 | D88: 0 | E88: 0
A89: II.3 | B89: TỔNG NỢ TOTAL LIABILITIES | C89: 2216 | D89: 5743418275 | E89: 3130773383 | F89: 0.50249752
B90: Tài sản ròng của Quỹ ( = I.8 - II.3) Net Asset Value ( = I.8 - II.3) | C90: 2217 | D90: 426790507896 | E90: 328082037421 | F90: 0.55334164
B91: Tổng số đơn vị quỹ Total Outstanding Fund Certificates | C91: 2218 | D91: 28492998 | E91: 27868601 | F91: 0.6145365
B92: Giá trị tài sản ròng trên một đơn vị quỹ Net Asset Value per Fund Certificate | C92: 2219 | D92: 14978.78 | E92: 11772.46 | F92: 0.90042085
A94: Đại diện có thẩm quyền của Ngân hàng giám sát | E94: Đại diện có thẩm quyền của Công ty quản lý Quỹ
A95: Authorised Representative of Supervisory Bank | E95: Authorised Representative of Fund Management Company
A103: Ngân hàng TNHH MTV Standard Chartered (Việt Nam) | E103: Công ty Cổ phần Quản lý Quỹ Đầu tư Việt Nam
A104: Bùi Thị Huyền Trang | E104: Trần Thanh Tân
A105: Cán bộ Quản lý Nghiệp vụ Dịch vụ Chứng khoán | E105: Tổng Giám đốc

Sheet BCKetQuaHoatDong_06028
A1: Phụ lục số 03. Mẫu báo cáo hoạt động đầu tư của quỹ mở Appendix 03. Report on Open ended Fund's Investment Activities
A2: (Ban hành kèm theo Thông tư số 91/2019/TT-BTC ngày 31 tháng 12 năm 2019 của Bộ trưởng Bộ Tài chính sửa đổi, bổ sung một số Thông tư quy định về chế độ báo cáo và thủ tục hành chính áp dụng với công ty quản lý quỹ, quỹ đầu tư chứng khoán và công ty đầu tư chứng khoán) (Issued in association with Circular 91/2019/TT-BTC dated 31 December 2019 of the Minister of Finance on amending and supplementing several Circulars on the reporting regime and administrative procedures applicable to fund management company, investment fund and investment company)
A3: BÁO CÁO HOẠT ĐỘNG ĐẦU TƯ CỦA QUỸ MỞ REPORT ON OPEN ENDED FUND'S INVESTMENT ACTIVITIES
A5: =TONGQUAN!C2 -> Quý II năm 2020 / Quarter II 2020
A7: Tên Công ty quản lý quỹ: | C7: =TONGQUAN!D5 -> Công ty Cổ phần Quản lý Quỹ Đầu tư Việt Nam
A8: Fund Management Company: | C8: =TONGQUAN!D6 -> Vietnam Investment Fund Management Joint Stock Company
A9: Tên ngân hàng giám sát: | C9: =TONGQUAN!D7 -> Ngân hàng TNHH Một thành viên Standard Chartered (Việt Nam)
A10: Supervising bank: | C10: =TONGQUAN!D8 -> Standard Chartered Bank (Vietnam) Limited
A11: Tên Quỹ: | C11: =TONGQUAN!D9 -> Quỹ Đầu tư Doanh nghiệp hàng đầu Việt Nam
A12: Fund name: | C12: =TONGQUAN!D10 -> Vietnam Blue Chip Fund(VFMVF4)
A13: Ngày lập báo cáo: | C13: =TONGQUAN!D11 -> Ngày 06 tháng 07 năm 2020
A14: Reporting Date: | C14: =TONGQUAN!D12 -> 06 Jul 2020
A16: A. | B16: BÁO CÁO CHUNG VỀ HOẠT ĐỘNG ĐẦU TƯ CỦA QUỸ/GENERAL INFORMATION ON FUND'S INVESTMENT ACTIVITIES
A17: II | B17: BÁO CÁO KẾT QUẢ HOẠT ĐỘNG / PROFIT AND LOSS REPORT
A18: STT No | B18: Nội dung Indicator | C18: Mã chỉ tiêu Code | D18: Quý II năm 2020 Quarter II 2020 | E18: Quý I năm 2020 Quarter I 2020 | F18: Lũy kế từ đầu năm Accumulated from beginning of year
A19: I | B19: Thu nhập từ hoạt động đầu tư Income from Investment Activities | C19: 2220 | D19: 1876823503 | E19: 649060252 | F19: 2525883755
A20: 1 | B20: Cổ tức, trái tức được nhận Dividend income, interest income from bonds | C20: 2221 | D20: 1673700000 | E20: 407500000 | F20: 2081200000
B21: Cổ tức được nhận Dividends income | C21: 2221.1 | D21: 1673700000 | E21: 407500000 | F21: 2081200000
B22: Trái tức được nhận Interest income from bonds | C22: 2221.2 | D22: 0 | E22: 0 | F22: 0
A23: 2 | B23: Lãi được nhận Interest income | C23: 2222 | D23: 203123503 | E23: 241560252 | F23: 444683755
B24: Lãi tiền gửi ngân hàng Interest income from bank deposits | C24: 2222.1 | D24: 203123503 | E24: 241560252 | F24: 444683755
B25: Lãi chứng chỉ tiền gửi Interest income from Certificates of Deposit | C25: 2222.2 | D25: 0 | E25: 0 | F25: 0
B26: Lãi hợp đồng mua lại đảo ngược Interest income from reverse repo contracts | C26: 2222.3 | D26: 0 | E26: 0 | F26: 0
A27: 3 | B27: Các khoản thu nhập khác Other incomes | C27: 2223 | D27: 0 | E27: 0 | F27: 0
B28: Thu nhập khác về đầu tư Other investment incomes | C28: 2223.1 | D28: 0 | E28: 0 | F28: 0
B29: Thu nhập khác Other incomes | C29: 2223.2 | D29: 0 | E29: 0 | F29: 0
B30: Chi phí dự phòng nợ phải thu khó đòi về cổ tức, tiền lãi và xử lý tổn thất nợ phải thu khó đòi về cổ tức, tiền lãi Provision expense for bad debts from dividends, interest income and written off bad debts from dividends, interest income | C30: 2223.3 | D30: 0 | E30: 0 | F30: 0
A31: II | B31: Chi phí Expenses | C31: 2224 | D31: 2552291649 | E31: 3528306765 | F31: 6080598414
A32: 1 | B32: Phí quản lý trả cho Công ty quản lý quỹ Management Fee paid to Fund Management Company | C32: 2225 | D32: 1989134194 | E32: 2695771205 | F32: 4684905399
A33: 2 | B33: Phí lưu ký, giám sát trả cho Ngân hàng Giám sát/VSD Custody fee, Supervising fee paid to Supervising Bank/VSD | C33: 2226 | D33: 192098803 | E33: 191279422 | F33: 383378225
B34: Phí dịch vụ lưu ký - bảo quản tài sản Custodian service - Safe Custody Fee | C34: 2226.1 | D34: 66000000 | E34: 66000000 | F34: 132000000
B35: Phí dịch vụ lưu ký - giao dịch chứng khoán Custodian service - Transaction fee | C35: 2226.2 | D35: 11000000 | E35: 20200000 | F35: 31200000
B36: Phí dịch vụ lưu ký cho chứng khoán cơ sở, phí quản lý vị thế và tài sản phái sinh trả cho VSD Custodian service - Depository fee, Position and Margin management fee paid to VSD | C36: 2226.3 | D36: 39198803 | E36: 29179422 | F36: 68378225
B37: Phí giám sát Supervisory fee | C37: 2226.4 | D37: 75900000 | E37: 75900000 | F37: 151800000
A38: 3 | B38: Chi phí dịch vụ quản trị quỹ, chi phí dịch vụ đại lý chuyển nhượng và các chi phí khác mà công ty quản lý quỹ trả cho tổ chức cung cấp dịch vụ có liên quan Fund Administration Fee, Transfer Agency Fee and other fees paid to relevant Fund's service providers | C38: 2227 | D38: 67011106 | E38: 79093497 | F38: 146104603
B39: Chi phí quản trị Quỹ Fund Administration Fee | C39: 2227.1 | D39: 34011106 | E39: 46093497 | F39: 80104603
B40: Chi phí dịch vụ Đại lý Chuyển nhượng Transfer Agency Fee | C40: 2227.2 | D40: 33000000 | E40: 33000000 | F40: 66000000
A41: 4 | B41: Chi phí kiểm toán trả cho tổ chức kiểm toán Audit fee | C41: 2228 | D41: 45641516 | E41: 42392077 | F41: 88033593
A42: 5 | B42: Chi phí dịch vụ tư vấn pháp lý, dịch vụ báo giá và các dịch vụ hợp lý khác, thù lao trả cho ban đại diện quỹ Legal consultancy expenses, price feed fee, other valid expenses, remuneration paid to Fund's Board of Representatives | C42: 2229 | D42: 38983617 | E42: 47083616 | F42: 86067233
B43: Thù lao Ban đại diện Quỹ Remuneration of Fund's Board of Representatives | C43: 2229.1 | D43: 38983617 | E43: 38983616 | F43: 77967233
B44: Chi phí cung cấp báo giá chứng khoán Price feed fee | C44: 2229.2 | D44: 0 | E44: 8100000 | F44: 8100000
B45: Chi phí dịch vụ tư vấn pháp lý Legal consultancy expenses | C45: 2229.3 | D45: 0 | E45: 0 | F45: 0
A46: 6 | B46: Chi phí dự thảo, in ấn, gửi bản cáo bạch, bản cáo bạch tóm tắt, báo cáo tài chính, xác nhận giao dịch, sao kê tài khoản và các tài liệu khác cho nhà đầu tư; chi phí công bố thông tin của quỹ; chi phí tổ chức họp đại hội nhà đầu tư, ban đại diện quỹ Fee for drafting, printing, distribution of prospectus, summarised prospectus, financial statements, transaction confirmations, account statements and other documents to investors; information disclosure fee; fee for organising annual general meeting, board of representatives meeting | C46: 2230 | D46: 0 | E46: 0 | F46: 0
B47: Chi phí họp Đại hội Quỹ Meeting expenses | C47: 2230.1 | D47: 0 | E47: 0 | F47: 0
B48: Chi phí báo cáo thường niên Annual report expenses | C48: 2230.2 | D48: 0 | E48: 0 | F48: 0
B49: Chi phí họp, công tác của Ban đại diện Fund's Board of Representatives meeting, travelling expenses | C49: 2230.3 | D49: 0 | E49: 0 | F49: 0
B50: Chi phí công bố thông tin của Quỹ Expenses of information disclosure of the Fund | C50: 2230.4 | D50: 0 | E50: 0 | F50: 0
B51: Phí thiết kế, in ấn, gửi thư… Designing, printing, posting... expenses | C51: 2230.5 | D51: 0 | E51: 0 | F51: 0
A52: 7 | B52: Chi phí liên quan đến thực hiện các giao dịch tài sản của Quỹ Expenses related to execution of Fund’s asset transactions | C52: 2231 | D52: 213953490 | E52: 462691027 | F52: 676644517
B53: Chi phí môi giới Brokerage fee | C53: 2231.1 | D53: 212114680 | E53: 461329720 | F53: 673444400
B54: Chi phí thanh toán bù trừ Clearing settlement fee | C54: 2231.2 | D54: 1838810 | E54: 1361307 | F54: 3200117
B55: Chi phí khác Other Expenses | C55: 2231.3 | D55: 0 | E55: 0 | F55: 0
A56: 8 | B56: Các loại phí, chi phí khác Other fees, expenses | C56: 2232 | D56: 5468923 | E56: 9995921 | F56: 15464844
B57: Chi phí thiết lập Quỹ Set up Expenses | C57: 2232.1 | D57: 0 | E57: 0 | F57: 0
B58: Phí niêm yết, đăng ký chứng khoán Listing, registration fees | C58: 2232.2 | D58: 0 | E58: 0 | F58: 0
B59: Phí quản lý thường niên trả cho UBCKNN Annual management fee paid to SSC | C59: 2232.3 | D59: 0 | E59: 0 | F59: 0
B60: Phí ngân hàng Bank charges | C60: 2232.4 | D60: 5468923 | E60: 8895921 | F60: 14364844
B61: Chi phí lãi vay Borrowing expense | C61: 2232.5 | D61: 0 | E61: 0 | F61: 0
B62: Chi phí khác Other Expenses | C62: 2232.6 | D62: 0 | E62: 0 | F62: 0
B63: Phí thực hiện quyền trả cho VSD Fee paid to VSD for getting the list of investors | C63: 2232.7 | D63: 0 | E63: 1100000 | F63: 1100000
A64: III | B64: Thu nhập ròng từ hoạt động đầu tư (= I - II) Net Income from Investment Activities (= I - II) | C64: 2233 | D64: -675468146 | E64: -2879246513 | F64: -3554714659
A65: IV | B65: Lãi / (lỗ) từ hoạt động đầu tư Gain / (Loss) from Investment Activities | C65: 2234 | D65: 90049418500 | E65: -189822312900 | F65: -99772894400
A66: 1 | B66: Lãi (lỗ) thực tế phát sinh từ hoạt động đầu tư Realised Gain / (Loss) from disposal of investment | C66: 2235 | D66: -9574059758 | E66: -34865154187 | F66: -44439213945
A67: 2 | B67: Thay đổi về giá trị của các khoản đầu tư trong kỳ Unrealised Gain / (Loss) due to market price | C67: 2236 | D67: 99623478258 | E67: -154957158713 | F67: -55333680455
A68: V | B68: Thay đổi của giá trị tài sản ròng của Quỹ do các hoạt động đầu tư trong kỳ (III + IV) Change of Net Asset Value of the Fund due to investment activities during the period (= III + IV) | C68: 2237 | D68: 89373950354 | E68: -192701559413 | F68: -103327609059
A69: VI | B69: Giá trị tài sản ròng đầu kỳ Net Asset Value at the beginning of period | C69: 2238 | D69: 328082037421 | E69: 617969847918 | F69: 617969847918
A70: VII | B70: Thay đổi giá trị tài sản ròng của Quỹ trong kỳ Change of Net Asset Value of the Fund during the period | C70: 2239 | D70: 98708470475 | E70: -289887810497 | F70: -191179340022
B71: Trong đó: Of which: | C71: 2240
A72: 1 | B72: Thay đổi giá trị tài sản ròng của Quỹ do các hoạt động liên quan đến đầu tư của Quỹ trong kỳ Change of Net Asset Value due to investment related activities during the period | C72: 2239.1 | D72: 89373950354 | E72: -192701559413 | F72: -103327609059
A73: 2 | B73: Thay đổi giá trị tài sản ròng của Quỹ do việc phân phối thu nhập của Quỹ cho các nhà đầu tư trong kỳ Change of Net Asset Value due to profit distribution to investors during the period | C73: 2239.2 | D73: 0 | E73: 0 | F73: 0
A74: 3 | B74: Thay đổi giá trị tài sản ròng do phát hành thêm Chứng chỉ Quỹ Change of Net Asset Value due to subscription during the period | C74: 2239.3 | D74: 17059020369 | E74: 25096350158 | F74: 42155370527
A75: 4 | B75: Thay đổi giá trị tài sản ròng do mua lại Chứng chỉ Quỹ Change of Net Asset Value due to redemption during the period | C75: 2239.4 | D75: -7724500248 | E75: -122282601242 | F75: -130007101490
A76: VIII | B76: Giá trị tài sản ròng cuối kỳ Net Asset Value at the end of period | C76: 2243 | D76: 426790507896 | E76: 328082037421 | F76: 426790507896
A77: IX | B77: Lợi nhuận bình quân năm (chỉ áp dụng đối với báo cáo năm) Average annual profit (only applicable to annual report) | C77: 2244
B78: Tỷ suất lợi nhuận bình quân năm (chỉ áp dụng đối với báo cáo năm) Average annual rate of return (only applicable to annual report) | C78: 2245
A81: =TONGQUAN!C16 -> Đại diện có thẩm quyền của Ngân hàng giám sát | D81: =TONGQUAN!F16 -> Đại diện có thẩm quyền của Công ty quản lý Quỹ
A82: =TONGQUAN!C17 -> Authorised Representative of Supervisory Bank | D82: =TONGQUAN!F17 -> Authorised Representative of Fund Management Company
A90: =TONGQUAN!C19 -> Ngân hàng TNHH MTV Standard Chartered (Việt Nam) | D90: =TONGQUAN!F19 -> Công ty Cổ phần Quản lý Quỹ Đầu tư Việt Nam
A91: =TONGQUAN!C20 -> Bùi Thị Huyền Trang | D91: =TONGQUAN!F20 -> Trần Thanh Tân
A92: =TONGQUAN!C21 -> Cán bộ Quản lý Nghiệp vụ Dịch vụ Chứng khoán | D92: =TONGQUAN!F21 -> Tổng Giám đốc

Sheet BCDanhMucDauTu_06029
A1: Phụ lục số 03. Mẫu báo cáo hoạt động đầu tư của quỹ mở Appendix 03. Report on Open ended Fund's Investment Activities
A2: (Ban hành kèm theo Thông tư số 91/2019/TT-BTC ngày 31 tháng 12 năm 2019 của Bộ trưởng Bộ Tài chính sửa đổi, bổ sung một số Thông tư quy định về chế độ báo cáo và thủ tục hành chính áp dụng với công ty quản lý quỹ, quỹ đầu tư chứng khoán và công ty đầu tư chứng khoán) (Issued in association with Circular 91/2019/TT-BTC dated 31 December 2019 of the Minister of Finance on amending and supplementing several Circulars on the reporting regime and administrative procedures applicable to fund management company, investment fund and investment company)
A3: BÁO CÁO HOẠT ĐỘNG ĐẦU TƯ CỦA QUỸ MỞ REPORT ON OPEN ENDED FUND'S INVESTMENT ACTIVITIES
A5: =TONGQUAN!C1 -> Tại ngày 30 tháng 06 năm 2020 / As at 30 Jun 2020
A7: Tên Công ty quản lý quỹ: | C7: =TONGQUAN!D5 -> Công ty Cổ phần Quản lý Quỹ Đầu tư Việt Nam
A8: Fund Management Company: | C8: =TONGQUAN!D6 -> Vietnam Investment Fund Management Joint Stock Company
A9: Tên ngân hàng giám sát: | C9: =TONGQUAN!D7 -> Ngân hàng TNHH Một thành viên Standard Chartered (Việt Nam)
A10: Supervising bank: | C10: =TONGQUAN!D8 -> Standard Chartered Bank (Vietnam) Limited
A11: Tên Quỹ: | C11: =TONGQUAN!D9 -> Quỹ Đầu tư Doanh nghiệp hàng đầu Việt Nam
A12: Fund name: | C12: =TONGQUAN!D10 -> Vietnam Blue Chip Fund(VFMVF4)
A13: Ngày lập báo cáo: | C13: =TONGQUAN!D11 -> Ngày 06 tháng 07 năm 2020
A14: Reporting Date: | C14: =TONGQUAN!D12 -> 06 Jul 2020
A16: A. | B16: BÁO CÁO CHUNG VỀ HOẠT ĐỘNG ĐẦU TƯ CỦA QUỸ/GENERAL INFORMATION ON FUND'S INVESTMENT ACTIVITIES
A17: III | B17: BÁO CÁO DANH MỤC ĐẦU TƯ / INVESTMENT PORTFOLIO REPORT
A18: STT No. | B18: Loại Category | C18: Mã chỉ tiêu Code | D18: Số Lượng Quantity | E18: Giá thị trường hoặc giá trị hợp lý tại ngày báo cáo Market price | F18: Tổng giá trị (Đồng) Value (VND) | G18: Tỷ lệ % Tổng giá trị tài sản của Quỹ % of total asset
A19: I | B19: CỔ PHIẾU NIÊM YẾT LISTED SHARES | C19: 2246
A20: 1 | B20: ACB | C20: 2246.1 | D20: 400000 | E20: 22800 | F20: 9120000000 | G20: 0.021085051
A21: 2 | B21: ACV | C21: 2246.2 | D21: 70000 | E21: 58300 | F21: 4081000000 | G21: 0.009435098
A22: 3 | B22: BID | C22: 2246.3 | D22: 768000 | E22: 37900 | F22: 29107200000 | G22: 0.067294606
A23: 4 | B23: BMP | C23: 2246.4 | D23: 85000 | E23: 51900 | F23: 4411500000 | G23: 0.0101992
A24: 5 | B24: BVH | C24: 2246.5 | D24: 10 | E24: 45500 | F24: 455000 | G24: 1.0519406e-06
A25: 6 | B25: CTD | C25: 2246.6 | D25: 10 | E25: 69600 | F25: 696000 | G25: 1.6091223e-06
A26: 7 | B26: CTG | C26: 2246.7 | D26: 615000 | E26: 21550 | F26: 13253250000 | G26: 0.030640949
A27: 8 | B27: DXG | C27: 2246.8 | D27: 750000 | E27: 11200 | F27: 8400000000 | G27: 0.019420442
A28: 9 | B28: EIB | C28: 2246.9 | D28: 55010 | E28: 17800 | F28: 979178000 | G28: 0.0022638178
A29: 10 | B29: FPT | C29: 2246.10 | D29: 874000 | E29: 45650 | F29: 39898100000 | G29: 0.092242706
A30: 11 | B30: GAS | C30: 2246.11 | D30: 240000 | E30: 69000 | F30: 16560000000 | G30: 0.038286014
A31: 12 | B31: HDB | C31: 2246.12 | D31: 37010 | E31: 24800 | F31: 917848000 | G31: 0.0021220255
... A64: 45 | B64: VRE | C64: 2246.45 | D64: 250000 | E64: 24800 | F64: 6200000000 | G64: 0.014334136
B65: TỔNG TOTAL | C65: 2247 | F65: 418780070000 | G65: 0.96820167
A66: II | B66: CỔ PHIẾU CHƯA NIÊM YẾT UNLISTED SHARES | C66: 2248
B67: TỔNG TOTAL | C67: 2249 | D67: 0 | F67: 0 | G67: 0
B68: TỔNG CÁC LOẠI CỔ PHIẾU TOTAL SHARES | C68: 2250 | F68: 418780070000 | G68: 0.96820167
A69: III | B69: TRÁI PHIẾU BONDS | C69: 2251
A70: 1 | B70: Trái phiếu niêm yết Listed bonds | C70: 2251.1 | D70: 0 | F70: 0 | G70: 0
A71: 2 | B71: Trái phiếu chưa niêm yết Unlisted Bonds | C71: 2251.2 | D71: 0 | F71: 0 | G71: 0
B72: TỔNG TOTAL | C72: 2252 | D72: 0 | F72: 0 | G72: 0
A73: IV | B73: CÁC LOẠI CHỨNG KHOÁN KHÁC OTHER SECURITIES | C73: 2253
A74: 1 | B74: Quyền mua chứng khoán Investment - Rights | C74: 2253.1 | D74: 0 | F74: 0 | G74: 0
A75: 2 | B75: Chi tiết loại hợp đồng phái sinh(*) Index future contracts | C75: 2253.2 | D75: 0 | F75: 0 | G75: 0
B76: TỔNG TOTAL | C76: 2254 | F76: 0 | G76: 0
B77: TỔNG CÁC LOẠI CHỨNG KHOÁN TOTAL TYPES OF SECURITIES | C77: 2255 | F77: 418780070000 | G77: 0.96820167
A78: V | B78: CÁC TÀI SẢN KHÁC OTHER ASSETS | C78: 2256
A79: 1 | B79: Cổ tức được nhận Dividend receivables | C79: 2256.1 | F79: 240000000 | G79: 0.00055486977
A80: 2 | B80: Lãi trái phiếu được nhận Coupon receivables | C80: 2256.2 | F80: 0 | G80: 0
A81: 3 | B81: Lãi tiền gửi và chứng chỉ tiền gửi được nhận Interest receivables from bank deposits and certificates of deposit | C81: 2256.3 | F81: 9315068 | G81: 2.153604e-05
A82: 4 | B82: Tiền bán chứng khoán chờ thu Outstanding Settlement of sales transactions | C82: 2256.4 | F82: 0 | G82: 0
A83: 5 | B83: Phải thu cho khoản cổ phiếu hạn chế chờ mua Receivable from AP/Investors on securities on hold of buying | C83: 2256.5 | F83: 0 | G83: 0
A84: 6 | B84: Phải thu khác Other receivables | C84: 2256.6 | F84: 0 | G84: 0
A85: 7 | B85: Tài sản khác Other assets | C85: 2256.7 | F85: 0 | G85: 0
B86: TỔNG TOTAL | C86: 2257 | F86: 249315068 | G86: 0.00057640581
A87: VI | B87: TIỀN CASH | C87: 2258
A88: 1 | B88: Tiền gửi Ngân hàng Cash at bank | C88: 2259 | F88: 13504541103 | G88: 0.031221923
A89: 1.1 | B89: Tiền gửi ngân hàng Cash at Bank | C89: 2259.1 | F89: 8504541103 | G89: 0.019662137
A90: 1.2 | B90: Các khoản tương đương tiền Cash Equivalents | C90: 2259.2 | F90: 5000000000 | G90: 0.011559787
A91: 1.3 | B91: Tiền gửi có kỳ hạn trên 3 tháng Deposits with term over three (03) months | C91: 2259.3 | F91: 0 | G91: 0
A92: 2 | B92: Chứng chỉ tiền gửi Certificates of deposit | C92: 2260 | F92: 0 | G92: 0
A93: 3 | B93: Công cụ chuyển nhượng… Transferable instruments… | C93: 2261 | F93: 0 | G93: 0
B94: TỔNG TOTAL | C94: 2262 | F94: 13504541103 | G94: 0.031221923
A95: VII | B95: Tổng giá trị danh mục Total value of portfolio | C95: 2263 | F95: 432533926171 | G95: 1
A97: Đại diện có thẩm quyền của Ngân hàng giám sát | E97: Đại diện có thẩm quyền của Công ty quản lý Quỹ
A98: Authorised Representative of Supervisory Bank | E98: Authorised Representative of Fund Management Company
A107: Ngân hàng TNHH MTV Standard Chartered (Việt Nam) | E107: Công ty Cổ phần Quản lý Quỹ Đầu tư Việt Nam
A108: Bùi Thị Huyền Trang | E108: Trần Thanh Tân
A109: Cán bộ Quản lý Nghiệp vụ Dịch vụ Chứng khoán | E109: Tổng Giám đốc

Sheet BCHoatDongVay_06026
A1: Phụ lục số 03. Mẫu báo cáo hoạt động đầu tư của quỹ mở Appendix 03. Report on Open ended Fund's Investment Activities
A2: (Ban hành kèm theo Thông tư số 91/2019/TT-BTC ngày 31 tháng 12 năm 2019 của Bộ trưởng Bộ Tài chính sửa đổi, bổ sung một số Thông tư quy định về chế độ báo cáo và thủ tục hành chính áp dụng với công ty quản lý quỹ, quỹ đầu tư chứng khoán và công ty đầu tư chứng khoán) (Issued in association with Circular 91/2019/TT-BTC dated 31 December 2019 of the Minister of Finance on amending and supplementing several Circulars on the reporting regime and administrative procedures applicable to fund management company, investment fund and investment company)
A3: BÁO CÁO HOẠT ĐỘNG ĐẦU TƯ CỦA QUỸ MỞ REPORT ON OPEN ENDED FUND'S INVESTMENT ACTIVITIES
A5: =TONGQUAN!C2 -> Quý II năm 2020 / Quarter II 2020
A7: Tên Công ty quản lý quỹ: | G7: =TONGQUAN!D5 -> Công ty Cổ phần Quản lý Quỹ Đầu tư Việt Nam
A8: Fund Management Company: | G8: =TONGQUAN!D6 -> Vietnam Investment Fund Management Joint Stock Company
A9: Tên ngân hàng giám sát: | G9: =TONGQUAN!D7 -> Ngân hàng TNHH Một thành viên Standard Chartered (Việt Nam)
A10: Supervising bank: | G10: =TONGQUAN!D8 -> Standard Chartered Bank (Vietnam) Limited
A11: Tên Quỹ: | G11: =TONGQUAN!D9 -> Quỹ Đầu tư Doanh nghiệp hàng đầu Việt Nam
A12: Fund name: | G12: =TONGQUAN!D10 -> Vietnam Blue Chip Fund(VFMVF4)
A13: Ngày lập báo cáo: | G13: =TONGQUAN!D11 -> Ngày 06 tháng 07 năm 2020
A14: Reporting Date: | G14: =TONGQUAN!D12 -> 06 Jul 2020
A15: A. | B15: BÁO CÁO CHUNG VỀ HOẠT ĐỘNG ĐẦU TƯ CỦA QUỸ/GENERAL INFORMATION ON FUND'S INVESTMENT ACTIVITIES
A16: IV | B16: BÁO CÁO HOẠT ĐỘNG VAY, GIAO DỊCH MUA BÁN LẠI / REPORT ON BORROWING OPERATION, REPO/REVERSE REPO TRANSACTIONS
A17: STT No. | B17: Nội dung hoạt động (nêu chi tiết theo mục tiêu và đối tác) Description | C17: Mã chỉ tiêu Code | D17: Đối tác Counterparty | E17: Mục tiêu/Tài sản đảm bảo Collateral | F17: Kỳ hạn Term | G17: Giá trị khoản vay hoặc khoản cho vay Amount | H17: Thời điểm giao dịch As at transaction date | J17: Thời điểm báo cáo As at reporting date
H18: Ngày tháng năm Date | I18: Tỷ lệ giá trị hợp đồng/giá trị tài sản ròng của quỹ Balance/NAV | J18: Ngày tháng năm Date | K18: Tỷ lệ giá trị hợp đồng/giá trị tài sản ròng của quỹ Balance/NAV
A19: 1 | B19: Các khoản vay tiền (nêu chi tiết từng hợp đồng) Borrowings (detail by each contract) | C19: 2287
A20: I | B20: Tổng giá trị các khoản vay tiền/giá trị tài sản ròng Borrowings/NAV | C20: 2288
A21: 2 | B21: Hợp đồng Repo (nêu chi tiết từng hợp đồng) Repo contract (detail by each contract) | C21: 2289
A22: II | B22: Tổng giá trị các hợp đồng Repo/giá trị tài sản ròng Total value of Repo contracts/NAV | C22: 2290
A23: A | B23: Tổng giá trị các khoản vay/giá trị tài sản ròng (=I+II) Total Borrowings, Repo/NAV (=I+II) | C23: 2291
A24: 3 | B24: Cho vay chứng khoán (nêu chi tiết từng hợp đồng) Securities lending (detail by each contract) | C24: 2292
A25: III | B25: Tổng giá trị các hợp đồng/giá trị tài sản ròng Total contract value/NAV | C25: 2293
A26: 4 | B26: Hợp đồng Reverse Repo (nêu chi tiết từng hợp đồng) Reverse Repo contract (Detail by each contract) | C26: 2295
A27: IV | B27: Tổng giá trị các hợp đồng/giá trị tài sản ròng Total contract value/NAV | C27: 2296
A28: B | B28: Tổng giá trị các khoản cho vay/giá trị tài sản ròng (=III + IV) Total Loans/NAV (=III + IV) | C28: 2297
A33: Đại diện có thẩm quyền của Ngân hàng giám sát | I33: Đại diện có thẩm quyền của Công ty quản lý Quỹ
A34: Authorised Representative of Supervisory Bank | I34: Authorised Representative of Fund Management Company
A44: Ngân hàng TNHH MTV Standard Chartered (Việt Nam) | I44: =TONGQUAN!F19 -> Công ty Cổ phần Quản lý Quỹ Đầu tư Việt Nam
A45: =TONGQUAN!C20 -> Bùi Thị Huyền Trang | I45: =TONGQUAN!F20 -> Trần Thanh Tân
A46: =TONGQUAN!C21 -> Cán bộ Quản lý Nghiệp vụ Dịch vụ Chứng khoán | I46: =TONGQUAN!F21 -> Tổng Giám đốc

Sheet Khac_06030
A1: Phụ lục số 03. Mẫu báo cáo hoạt động đầu tư của quỹ mở Appendix 03. Report on Open ended Fund's Investment Activities
A2: (Ban hành kèm theo Thông tư số 91/2019/TT-BTC ngày 31 tháng 12 năm 2019 của Bộ trưởng Bộ Tài chính sửa đổi, bổ sung một số Thông tư quy định về chế độ báo cáo và thủ tục hành chính áp dụng với công ty quản lý quỹ, quỹ đầu tư chứng khoán và công ty đầu tư chứng khoán) (Issued in association with Circular 91/2019/TT-BTC dated 31 December 2019 of the Minister of Finance on amending and supplementing several Circulars on the reporting regime and administrative procedures applicable to fund management company, investment fund and investment company)
A3: BÁO CÁO HOẠT ĐỘNG ĐẦU TƯ CỦA QUỸ MỞ REPORT ON OPEN ENDED FUND'S INVESTMENT ACTIVITIES
A5: =TONGQUAN!C2 -> Quý II năm 2020 / Quarter II 2020
A7: Tên Công ty quản lý quỹ: | C7: =TONGQUAN!D5 -> Công ty Cổ phần Quản lý Quỹ Đầu tư Việt Nam
A8: Fund Management Company: | C8: =TONGQUAN!D6 -> Vietnam Investment Fund Management Joint Stock Company
A9: Tên ngân hàng giám sát: | C9: =TONGQUAN!D7 -> Ngân hàng TNHH Một thành viên Standard Chartered (Việt Nam)
A10: Supervising bank: | C10: =TONGQUAN!D8 -> Standard Chartered Bank (Vietnam) Limited
A11: Tên Quỹ: | C11: =TONGQUAN!D9 -> Quỹ Đầu tư Doanh nghiệp hàng đầu Việt Nam
A12: Fund name: | C12: =TONGQUAN!D10 -> Vietnam Blue Chip Fund(VFMVF4)
A13: Ngày lập báo cáo: | C13: =TONGQUAN!D11 -> Ngày 06 tháng 07 năm 2020
A14: Reporting Date: | C14: =TONGQUAN!D12 -> 06 Jul 2020
A16: A. | B16: BÁO CÁO CHUNG VỀ HOẠT ĐỘNG ĐẦU TƯ CỦA QUỸ/GENERAL INFORMATION ON FUND'S INVESTMENT ACTIVITIES
A17: V | B17: MỘT SỐ CHỈ TIÊU KHÁC / OTHER INDICATORS
A18: STT No | B18: Chỉ tiêu Indicators | C18: Mã chỉ tiêu Code | D18: =BCKetQuaHoatDong_06028!D18 -> Quý II năm 2020 Quarter II 2020 | E18: =BCKetQuaHoatDong_06028!E18 -> Quý I năm 2020 Quarter I 2020
A19: I | B19: CÁC CHỈ TIÊU VỀ HIỆU QUẢ HOẠT ĐỘNG INVESTMENT PERFORMANCE INDICATORS | C19: 2264
A20: 1 | B20: Tỷ lệ phí quản lý trả cho công ty quản lý quỹ/Giá trị tài sản ròng trung bình trong kỳ (%) Management fee paid to the fund management company/Average NAV (%) | C20: 2265 | D20: 0.019196624 | E20: 0.019196799
A21: 2 | B21: Tỷ lệ phí lưu ký, giám sát trả cho Ngân hàng Giám sát/Giá trị tài sản ròng trung bình trong kỳ (%) Custody and supervising fees paid to the Supervisory Bank/Average NAV (%) | C21: 2266 | D21: 0.0014755987 | E21: 0.0011543269
A22: 3 | B22: Tỷ lệ chi phí dịch vụ quản trị quỹ, chi phí dịch vụ đại lý chuyển nhượng và các chi phí khác mà công ty quản lý quỹ trả cho tổ chức cung cấp dịch vụ có liên quan/Giá trị tài sản ròng của quỹ trung bình trong kỳ (%) Fund admin fee, transfer agency fee and other fees paid to relating services providers by the fund management company/Average NAV (%) | C22: 22661 | D22: 0.0010250046 | E22: 0.00077101999
A23: 4 | B23: Chi phí kiểm toán trả cho tổ chức kiểm toán (nếu phát sinh)/Giá trị tài sản ròng trung bình trong kỳ (%) Auditing fee paid to auditing organizations (if any)/Average NAV (%) | C23: 2267 | D23: 0.00044047456 | E23: 0.00030187732
A24: 5 | B24: Chi phí dịch vụ tư vấn pháp lý, dịch vụ báo giá và các dịch vụ hợp lý khác, thù lao trả cho ban đại diện quỹ/Giá trị tài sản ròng trung bình trong kỳ (%) Legal consultancy, price quotation and other appropriate service fees; remunerations paid to the Board of Representatives/Average NAV (%) | C24: 2268 | D24: 0.00037622089 | E24: 0.00033528614
A25: 6 | B25: Tỷ lệ chi phí hoạt động/Giá trị tài sản ròng trung bình trong kỳ (%) Operating expense/Average NAV (%) | C25: 2269 | D25: 0.024631512 | E25: 0.025125351
A26: 7 | B26: Tốc độ vòng quay danh mục trong kỳ (%) = (Tổng giá trị danh mục mua vào + tổng giá trị danh mục bán ra) x 100%/ (2 x Giá trị tài sản ròng trung bình trong kỳ) Portfolio turnover rate (%) = (Total value of purchase transactions + total value of sales transactions) x 100%/ (2 x Average NAV) (**) | C26: 2270 | D26: 0.72693854 | E26: 1.2542411
A27: II | B27: CÁC CHỈ TIÊU KHÁC OTHER INDICATORS | C27: 2272
A28: 1 | B28: Quy mô quỹ đầu kỳ (tính theo mệnh giá chứng chỉ quỹ) Fund scale at the beginning of the period (based on par value of fund certificate) | C28: 2273 | D28: 278686005700 | E28: 352404067800
B29: Tổng giá trị chứng chỉ quỹ đang lưu hành đầu kỳ Total value of outstanding Fund Certificate at the beginning of period | C29: 2274 | D29: 278686005700 | E29: 352404067800
B30: Tổng số lượng đơn vị quỹ đang lưu hành đầu kỳ Total number of outstanding Fund Certificate at the beginning of period | C30: 2275 | D30: 27868601 | E30: 35240407
A31: 2 | B31: Thay đổi quy mô quỹ trong kỳ (tính theo mệnh giá chứng chỉ quỹ) Change of Fund scale during the period (based on par value of fund certificate) | C31: 2276 | D31: 6243976300 | E31: -73718062100
B32: Thay đổi số lượng chứng chỉ quỹ trong kỳ Change of Number of Fund Certificates during the period | C32: 2276.1 | D32: 624397.63 | E32: -7371806.2
B33: Thay đổi giá trị vốn trong kỳ (theo mệnh giá) Change in capital amount during the period (based on par value) | C33: 2276.2 | D33: 6243976300 | E33: -73718062100
B34: Số lượng đơn vị quỹ phát hành thêm trong kỳ Number of Fund Certificates subscribed during the period | C34: 2277 | D34: 1141672.3 | E34: 1464878.6
B35: Giá trị vốn huy động thêm trong kỳ (theo mệnh giá) Net subscription amount during the period (based on par value) | C35: 2278 | D35: 11416722700 | E35: 14648785700
B36: Số lượng đơn vị quỹ mua lại trong kỳ Number of Fund Certificates redeemed during the period | C36: 22781 | D36: -517274.64 | E36: -8836684.8
B37: Giá trị vốn phải thanh toán trong kỳ khi đáp ứng lệnh của nhà đầu tư (theo mệnh giá) Net redemption amount during the period (based on par value) | C37: 22782 | D37: -5172746400 | E37: -88366847800
A38: 3 | B38: Quy mô quỹ cuối kỳ (tính theo mệnh giá chứng chỉ quỹ) Fund scale at the end of the period (based on par value) | C38: 2279 | D38: 284929982000 | E38: 278686005700
B39: Tổng giá trị chứng chỉ quỹ đang lưu hành cuối kỳ Total value of outstanding Fund Certificate at the end of the period | C39: 2280 | D39: 284929982000 | E39: 278686005700
B40: Tổng số lượng đơn vị quỹ đang lưu hành cuối kỳ Total number of outstanding Fund Certificate at the end of the period | C40: 2281 | D40: 28492998 | E40: 27868601
A41: 4 | B41: Tỷ lệ nắm giữ chứng chỉ quỹ của công ty quản lý quỹ và người có liên quan cuối kỳ Fund Management Company and related parties' ownership ratio at the end of the period | C41: 2282 | D41: 0.00080203037 | E41: 0.00074976531
A42: 5 | B42: Tỷ lệ nắm giữ chứng chỉ quỹ của 10 nhà đầu tư lớn nhất cuối kỳ Top 10 investors' ownership ratio at the end of the period | C42: 2283 | D42: 0.4512 | E42: 0.4474
A43: 6 | B43: Tỷ lệ nắm giữ chứng chỉ quỹ của nhà đầu tư nước ngoài cuối kỳ Foreign investors' ownership ratio at the end of the period | C43: 2284 | D43: 0.2489 | E43: 0.2538
A44: 7 | B44: Số nhà đầu tư tham gia vào quỹ, kể cả giao dịch ký danh Number of investors of the Fund at the end of the period | C44: 22841 | D44: 2045 | E44: 2023
A45: 8 | B45: Giá trị tài sản ròng trên một đơn vị quỹ cuối kỳ Net asset value per Fund Certificate at the end of period | C45: 2285 | D45: 14978.78 | E45: 11772.46
A46: Ghi chú / Notes:
A47: Các chỉ tiêu từ 1 đến 7 của "Chỉ tiêu về hiệu quả hoạt động" đã được điều chỉnh để phản ánh số liệu trên cơ sở hoạt động tròn năm bằng cách nhân các chỉ tiêu này với 12 (đối với báo cáo tháng), 4 (đối với báo cáo quý), 2 (đối với báo cáo bán niên), 1 (đối với báo cáo năm). All Indicator starting from number 1 to 7 of "Investment performance indicators" are annualized to reflect a rate that is based on a full year operation by multiplying these indicators with 12 (monthly report) or 4 (quarterly report) or 2 (semi-annual report) or 1 (annual report).
A48: (**) Không tính đến giá trị cam kết của các hợp đồng tương lai chỉ số. Excluding the committed value of the Index Futures contracts.
A50: =TONGQUAN!C16 -> Đại diện có thẩm quyền của Ngân hàng giám sát | D50: =TONGQUAN!F16 -> Đại diện có thẩm quyền của Công ty quản lý Quỹ
A51: =TONGQUAN!C17 -> Authorised Representative of Supervisory Bank | D51: =TONGQUAN!F17 -> Authorised Representative of Fund Management Company
A61: =TONGQUAN!C19 -> Ngân hàng TNHH MTV Standard Chartered (Việt Nam) | D61: =TONGQUAN!F19 -> Công ty Cổ phần Quản lý Quỹ Đầu tư Việt Nam
A62: =TONGQUAN!C20 -> Bùi Thị Huyền Trang | D62: =TONGQUAN!F20 -> Trần Thanh Tân
A63: =TONGQUAN!C21 -> Cán bộ Quản lý Nghiệp vụ Dịch vụ Chứng khoán | D63: =TONGQUAN!F21 -> Tổng Giám đốc

Sheet GiaTriTaiSanRong_06129
A1: Phụ lục 26. Mẫu báo cáo thay đổi giá trị tài sản ròng, giao dịch chứng chỉ quỹ Appendix 26. Report on change of Net Asset Value, trading of Fund Certificate
A2: (Ban hành kèm theo Thông tư 183/2011/TT-BTC ngày 16 tháng 12 năm 2011 hướng dẫn về việc thành lập và quản lý quỹ mở) (Issued in association with Circular 183/2011/TT-BTC dated 16 December 2011 guiding establishment and management of the Open-Ended Fund)
A3: BÁO CÁO THAY ĐỔI GIÁ TRỊ TÀI SẢN RÒNG, GIAO DỊCH CHỨNG CHỈ QUỸ REPORT ON CHANGE OF NET ASSET VALUE, TRADING OF FUND CERTIFICATE
A5: =TONGQUAN!C2 -> Quý II năm 2020 / Quarter II 2020
A7: Tên Công ty quản lý quỹ: | D7: =TONGQUAN!D5 -> Công ty Cổ phần Quản lý Quỹ Đầu tư Việt Nam
A8: Fund Management Company: | D8: =TONGQUAN!D6 -> Vietnam Investment Fund Management Joint Stock Company
A9: Tên ngân hàng giám sát: | D9: =TONGQUAN!D7 -> Ngân hàng TNHH Một thành viên Standard Chartered (Việt Nam)
A10: Supervising bank: | D10: =TONGQUAN!D8 -> Standard Chartered Bank (Vietnam) Limited
A11: Tên Quỹ: | D11: =TONGQUAN!D9 -> Quỹ Đầu tư Doanh nghiệp hàng đầu Việt Nam
A12: Fund name: | D12: =TONGQUAN!D10 -> Vietnam Blue Chip Fund(VFMVF4)
A13: Ngày lập báo cáo: | D13: =TONGQUAN!D11 -> Ngày 06 tháng 07 năm 2020
A14: Reporting Date: | D14: =TONGQUAN!D12 -> 06 Jul 2020
A18: STT No | C18: Nội dung Item | D18: Mã số Code | E18: =BCKetQuaHoatDong_06028!D18 -> Quý II năm 2020 Quarter II 2020 | F18: =BCKetQuaHoatDong_06028!E18 -> Quý I năm 2020 Quarter I 2020
A19: I | C19: I. Giá trị tài sản ròng của Quỹ mở (NAV) đầu kỳ Net Asset Value (NAV) at the beginning of period | D19: 4060 | E19: 328082037421 | F19: 617969847918
A20: II | C20: II. Thay đổi NAV so với kỳ trước (= II.1 + II.2), trong đó: Change of NAV during the period (= II.1 + II.2), of which: | D20: 4061 | E20: 89373950354 | F20: -192701559413
B21: II.1 | C21: II.1 Thay đổi NAV do biến động thị trường và hoạt động giao dịch của Quỹ mở trong kỳ Changes of NAV due to market fluctuation and the fund's investment during the period | D21: 4062 | E21: 89373950354 | F21: -192701559413
B22: II.2 | C22: II.2 Thay đổi NAV do phân chia Lợi nhuận/Tài sản của Quỹ mở cho Nhà đầu tư trong kỳ Change of NAV due to profit/asset distribution to investors during the period | D22: 4063 | E22: 0 | F22: 0
A23: III | C23: III. Thay đổi NAV do mua lại, phát hành thêm Chứng chỉ quỹ (= III.1 + III.2) Change of NAV due to redemption, subscription of Fund Certificate (= III.1 + III.2) | D23: 4064 | E23: 9334520121 | F23: -97186251084
B24: III.1 | C24: III.1 Khoản thu từ việc phát hành bổ sung Chứng chỉ quỹ Increase from Subscription of Fund Certificate | D24: 4065 | E24: 17059020369 | F24: 25096350158
B25: III.2 | C25: III.2 Khoản thanh toán từ việc mua lại Chứng chỉ quỹ Decrease from Redemption of Fund Certificate | D25: 4066 | E25: -7724500248 | F25: -122282601242
A26: IV | C26: IV. Giá trị tài sản ròng của Quỹ mở cuối kỳ (= I + II + III) NAV at the end of period (= I + II + III) | D26: 4067 | E26: 426790507896 | F26: 328082037421
A27: V | C27: V. Giá trị tài sản ròng trên một đơn vị quỹ cuối kỳ NAV per unit at the end of period | D27: 4067.1 | E27: 14978.78 | F27: 11772.46
A30: =TONGQUAN!C16 -> Đại diện có thẩm quyền của Ngân hàng giám sát | E30: =TONGQUAN!F16 -> Đại diện có thẩm quyền của Công ty quản lý Quỹ
A31: =TONGQUAN!C17 -> Authorised Representative of Supervisory Bank | E31: =TONGQUAN!F17 -> Authorised Representative of Fund Management Company
A41: =TONGQUAN!C19 -> Ngân hàng TNHH MTV Standard Chartered (Việt Nam) | E41: =TONGQUAN!F19 -> Công ty Cổ phần Quản lý Quỹ Đầu tư Việt Nam
A42: =TONGQUAN!C20 -> Bùi Thị Huyền Trang | E42: =TONGQUAN!F20 -> Trần Thanh Tân
A43: =TONGQUAN!C21 -> Cán bộ Quản lý Nghiệp vụ Dịch vụ Chứng khoán | E43: =TONGQUAN!F21 -> Tổng Giám đốc
