Workbook
Name addlogo: INDEX(#REF!,MATCH(#REF!,#REF!,0))

Sheet TONGQUAN
A1: Kỳ báo cáo: | C1: Tại ngày 31 tháng 07 năm 2022 / As at 31 Jul 2022
C2: Tháng 07 năm 2022 / Jul 2022
A4: Thông tin chung:
C5: Tên Công ty quản lý quỹ: | D5: Công ty Cổ phần Quản lý Quỹ Đầu tư Dragon Capital Việt Nam
C6: Fund Management Company: | D6: Dragon Capital Vietfund Management Joint Stock Company
C7: Tên ngân hàng giám sát: | D7: Ngân hàng TNHH Một thành viên Standard Chartered (Việt Nam)
C8: Supervising bank: | D8: Standard Chartered Bank (Vietnam) Limited
C9: Tên Quỹ: | D9: Quỹ Đầu tư Chứng khoán Năng động DC
C10: Fund name: | D10: DC Dynamic Securities Fund(VFMVF1)
C11: Ngày lập báo cáo: | D11: Ngày 01 tháng 08 năm 2022
C12: Reporting Date: | D12: 01 Aug 2022
A14: Người ký báo cáo:
C16: Đại diện có thẩm quyền của Ngân hàng giám sát | F16: Đại diện có thẩm quyền của Công ty quản lý Quỹ
C17: Authorised Representative of Supervisory Bank | F17: Authorised Representative of Fund Management Company
C19: Ngân hàng TNHH MTV Standard Chartered (Việt Nam) | F19: =D5 -> Công ty Cổ phần Quản lý Quỹ Đầu tư Dragon Capital Việt Nam
C20: Trịnh Hoài Nam | F20: Nguyễn Minh Đăng Khánh
C21: Phó phòng Dịch vụ Quản trị và Giám sát Quỹ | F21: Giám đốc điều hành Nghiệp vụ hỗ trợ đầu tư
B34: STT | C34: Nội dung | D34: Tên sheet
B35: 1 | C35: Báo cáo về tài sản của quỹ | D35: 06027
B36: 2 | C36: Báo cáo kết quả hoạt động | D36: 06028
B37: 3 | C37: Báo cáo danh mục đầu tư của quỹ | D37: 06029
B38: 4 | C38: Một số chỉ tiêu khác | D38: 06030
B39: 5 | C39: Báo cáo thay đổi giá trị tài sản ròng, giao dịch chứng chỉ quỹ | D39: 06129
B40: 6 | C40: Báo cáo thu nhập giữa niên độ | D40: 06203
B41: 7 | C41: Báo cáo tình hình tài chính giữa niên độ | D41: 06105
B42: 8 | C42: Báo cáo thay đổi giá trị tài sản ròng, giao dịch chứng chỉ quỹ giữa niên độ | D42: 06107
B43: 9 | C43: Báo cáo danh mục đầu tư | D43: 06108
B44: 10 | C44: Báo cáo lưu chuyển tiền tệ | D44: 06262
B45: 11 | C45: Báo cáo thu nhập | D45: 06104
B46: 12 | C46: Báo cáo về tài sản của quỹ | D46: 06126

Sheet BCthunhap
A1: Mẫu số B01g - QM. Báo cáo thu nhập Template B01g - QM. Statement of Comprehensive Income
A2: (Ban hành kèm theo Thông tư 198/2012/TT-BTC ngày 15 tháng 11 năm 2012 về chế độ kế toán áp dụng đối với quỹ mở) (Issued in association with Circular 198/2012/TT-BTC dated 15 Nov 2012 on the Accounting Policies for Open-Ended Fund)
A3: BÁO CÁO THU NHẬP STATEMENT OF COMPREHENSIVE INCOME
A5: =TONGQUAN!C2 -> Tháng 07 năm 2022 / Jul 2022
A7: Tên Công ty quản lý quỹ: | D7: =TONGQUAN!D5 -> Công ty Cổ phần Quản lý Quỹ Đầu tư Dragon Capital Việt Nam
A8: Fund Management Company: | D8: =TONGQUAN!D6 -> Dragon Capital Vietfund Management Joint Stock Company
A9: Tên ngân hàng giám sát: | D9: =TONGQUAN!D7 -> Ngân hàng TNHH Một thành viên Standard Chartered (Việt Nam)
A10: Supervising bank: | D10: =TONGQUAN!D8 -> Standard Chartered Bank (Vietnam) Limited
A11: Tên Quỹ: | D11: =TONGQUAN!D9 -> Quỹ Đầu tư Chứng khoán Năng động DC
A12: Fund name: | D12: =TONGQUAN!D10 -> DC Dynamic Securities Fund(VFMVF1)
A13: Ngày lập báo cáo: | D13: =TONGQUAN!D11 -> Ngày 01 tháng 08 năm 2022
A14: Reporting Date: | D14: =TONGQUAN!D12 -> 01 Aug 2022
A16: Chỉ tiêu Indicator | B16: Mã số Code | C16: Thuyết minh Note | D16: Năm 2022 Year 2022 | F16: Năm 2021 Year 2021
D17: =BCKetQuaHoatDong_06028!D18 -> Tháng 07 năm 2022 Jul 2022 | E17: Số lũy kế Year-to-date | F17: Tháng 07 năm 2021 Jul 2021 | G17: Số lũy kế Year-to-date
A18: I. THU NHẬP, DOANH THU HOẠT ĐỘNG ĐẦU TƯ Investment income | B18: 01 | D18: -14939385873 | E18: -429717885070 | F18: -13099594865 | G18: 200773185202
A19: 1.1. Cổ tức được chia Dividend income | B19: 02 | D19: 2937160000 | E19: 9928292500 | F19: 735280000 | G19: 4241863418
A20: 1.2. Tiền lãi được nhận Interest income | B20: 03 | D20: 1590327272 | E20: 10206130379 | F20: 660869085 | G20: 3572725912
A21: Lãi tiền gửi ngân hàng Interest income from bank deposits | B21: 03.1 | D21: 22224578 | E21: 1028198843 | F21: 12204701 | G21: 52890297
A22: Lãi chứng chỉ tiền gửi Interest income from Certificates of Deposit | B22: 03.2 | D22: 66458904 | E22: 706698630 | F22: 139075343 | G22: 2158739724
A23: Lãi trái phiếu Interest income from bonds | B23: 03.3 | D23: 1501643790 | E23: 8471232906 | F23: 509589041 | G23: 1361095891
A24: Tiền lãi hợp đồng mua lại đảo ngược được nhận Reverse repo contract interest received | B24: 03.4 | D24: 0 | E24: 0 | F24: 0 | G24: 0
A25: 1.3. Lãi (lỗ) bán các khoản đầu tư Realized gain (losses) from disposal investments | B25: 04 | D25: -56005984946 | E25: -223721190383 | F25: 39446220636 | G25: 119193067591
A26: 1.4. Chênh lệch tăng, giảm đánh giá lại các khoản đầu tư chưa thực hiện Unrealized gain (losses) from investment revaluation | B26: 05 | D26: 36539111801 | E26: -226131117566 | F26: -53941964586 | G26: 73765528281
A27: 1.5. Doanh thu khác Other income | B27: 06 | D27: 0 | E27: 0 | F27: 0 | G27: 0
A28: 1.6. Chênh lệch lãi, lỗ tỷ giá hối đoái đã và chưa thực hiện Realized and unrealized gain (losses) from foreign exchange | B28: 07 | D28: 0 | E28: 0 | F28: 0 | G28: 0
A29: 1.7. Doanh thu khác về đầu tư Other investment income | B29: 08 | D29: 0 | E29: 0 | F29: 0 | G29: 0
... A77: VIII. LỢI NHUẬN KẾ TOÁN SAU THUẾ TNDN PROFIT AFTER TAX (41=30-40) | B77: 41 | D77: -19608724457 | E77: -458051190817 | F77: -14978575973 | G77: 190674815145
A80: Người lập: | B80: Người duyệt:
A93: _______________________________________________ | B93: ___________________________________________ | F93: _____________________________
A94: Nguyễn Thu Ngọc | B94: Phạm Thanh Dũng | F94: Nguyễn Minh Đăng Khánh
A95: Kế toán Quỹ | B95: Kế toán Trưởng | F95: Giám đốc điều hành Nghiệp vụ hỗ trợ đầu tư

Sheet BCtinhhinhtaichinh
A1: Mẫu số B02g - QM. Báo cáo tình hình tài chính Template B02g - QM. Statement of Financial Position
A2: (Ban hành kèm theo Thông tư 198/2012/TT-BTC ngày 15 tháng 11 năm 2012 về chế độ kế toán áp dụng đối với quỹ mở) (Issued in association with Circular 198/2012/TT-BTC dated 15 Nov 2012 on the Accounting Policies for Open-Ended Fund)
A3: BÁO CÁO TÌNH HÌNH TÀI CHÍNH STATEMENT OF FINANCIAL POSITION
A5: =TONGQUAN!C1 -> Tại ngày 31 tháng 07 năm 2022 / As at 31 Jul 2022
A7: Tên Công ty quản lý quỹ: | C7: =TONGQUAN!D5 -> Công ty Cổ phần Quản lý Quỹ Đầu tư Dragon Capital Việt Nam
A8: Fund Management Company: | C8: =TONGQUAN!D6 -> Dragon Capital Vietfund Management Joint Stock Company
A9: Tên ngân hàng giám sát: | C9: =TONGQUAN!D7 -> Ngân hàng TNHH Một thành viên Standard Chartered (Việt Nam)
A10: Supervising bank: | C10: =TONGQUAN!D8 -> Standard Chartered Bank (Vietnam) Limited
A11: Tên Quỹ: | C11: =TONGQUAN!D9 -> Quỹ Đầu tư Chứng khoán Năng động DC
A12: Fund name: | C12: =TONGQUAN!D10 -> DC Dynamic Securities Fund(VFMVF1)
A13: Ngày lập báo cáo: | C13: =TONGQUAN!D11 -> Ngày 01 tháng 08 năm 2022
A14: Reporting Date: | C14: =TONGQUAN!D12 -> 01 Aug 2022
A16: STT No. | B16: Chỉ tiêu Indicator | C16: Mã số Code | D16: Thuyết minh Note | E16: =BCTaiSan_06027!D18 -> Ngày 31 tháng 07 năm 2022 As at 31 Jul 2022 | F16: =BCTaiSan_06027!E18 -> Ngày 30 tháng 06 năm 2022 As at 30 Jun 2022
A17: I | B17: I. TÀI SẢN ASSETS | C17: I
A18: 1 | B18: 1.Tiền gửi ngân hàng và tương đương tiền Cash at bank and cash equivalent | C18: 110 | E18: 189101074987 | F18: 118659866954
A19: 1.1 | B19: 1.1. Tiền gửi ngân hàng Cash at bank | C19: 111 | E19: 189101074987 | F19: 118659866954
B20: Tiền gửi của nhà đầu tư cho hoạt động mua chứng chỉ quỹ Cash at bank for Fund's subscription | C20: 111.1 | E20: 0 | F20: 0
B21: Tiền phải trả cho Nhà đầu tư về mua lại Chứng chỉ quỹ Cash at bank for Fund's redemption | C21: 111.2 | E21: 719033789 | F21: 1118154682
B22: Tiền gửi ngân hàng cho hoạt động của Quỹ Cash at bank for Fund's operation | C22: 111.3 | E22: 188382041198 | F22: 117541712272
B23: Tiền gửi ký quỹ cho hoạt động đầu tư chứng khoán phái sinh Margin account for trading derivatives | C23: 111.4 | E23: 0 | F23: 0
A24: 1.2 | B24: 1.2. Tiền gửi có kỳ hạn dưới ba (03) tháng Deposit with term less than three (03) months | C24: 112 | E24: 0 | F24: 0
A25: 2 | B25: 2. Các khoản đầu tư thuần Net Investments | C25: 120 | E25: 1401393395550 | F25: 1470911463400
A26: 2.1 | B26: 2.1. Các khoản đầu tư Investments | C26: 121 | E26: 1401393395550 | F26: 1470911463400
B27: Cổ phiếu niêm yết Listed Shares | C27: 121.1 | E27: 1271337570950 | F27: 1291055638800
B28: Cổ phiếu chưa niêm yết Unlisted Shares | C28: 121.2 | E28: 0 | F28: 0
B29: Trái phiếu niêm yết Listed Bonds | C29: 121.3 | E29: 30062400000 | F29: 79862400000
B30: Trái phiếu chưa niêm yết Unlisted Bonds | C30: 121.4 | E30: 89993424600 | F30: 89993424600
B31: Chứng chỉ tiền gửi Certificates of Deposit | C31: 121.5 | E31: 10000000000 | F31: 10000000000
B32: Hợp đồng tiền gửi có kỳ hạn trên ba (03) tháng Deposits with term over three (03) months | C32: 121.6 | E32: 0 | F32: 0
B33: Quyền mua chứng khoán Investment - Rights | C33: 121.7 | E33: 0 | F33: 0
B34: Hợp đồng tương lai chỉ số Index future contracts | C34: 121.8 | E34: 0 | F34: 0
B35: Đầu tư khác Other Investments | C35: 121.9 | E35: 0 | F35: 0
B36: Hợp đồng mua lại đảo ngược Reverse repo contracts | C36: 121.10 | E36: 0 | F36: 0
A37: 2.2 | B37: 2.2. Dự phòng giảm giá tài sản nhận thế chấp Impairment of devaluation of pledged assets | C37: 122 | E37: 0 | F37: 0
A38: 3 | B38: 3. Các khoản phải thu Receivables | C38: 130 | E38: 88255697740 | F38: 47664359841
A39: 3.1 | B39: 3.1 Phải thu về bán các khoản đầu tư Receivables from investments sold but not yet settled | C39: 131 | E39: 83396335000 | F39: 41850102600
B40: Trong đó: Phải thu khó đòi về bán các khoản đầu tư In which: Overdue receivables from selling investments | C40: 132 | E40: 0 | F40: 0
A41: 3.2 | B41: 3.2. Phải thu và dự thu cổ tức, tiền lãi các khoản đầu tư Dividend and interest receivables | C41: 133 | E41: 5725762740 | F41: 6680657241
A42: 3.2.1 | B42: 3.2.1. Phải thu cổ tức, tiền lãi đến ngày nhận Dividend and interest receivables on or after payment date | C42: 134 | E42: 866400000 | F42: 866400000
B43: Phải thu cổ tức Dividend receivables | C43: 134.1 | E43: 866400000 | F43: 866400000
B44: Phải thu trái tức Coupon receivables | C44: 134.2 | E44: 0 | F44: 0
B45: Phải thu lãi tiền gửi có kỳ hạn dưới 3 tháng Interest receivables from deposit with term less than three (03) months | C45: 134.3 | E45: 0 | F45: 0
B46: Phải thu lãi tiền gửi có kỳ hạn trên 3 tháng Interest receivables from deposit with term more than three (03) months | C46: 134.4 | E46: 0 | F46: 0
B47: Phải thu lãi chứng chỉ tiền gửi Interest receivables from Certificates of Deposit | C47: 134.5 | E47: 0 | F47: 0
B48: Trong đó: Phải thu khó đòi về cổ tức, tiền lãi đến ngày nhận nhưng chưa nhận được In which: Overdue receivables from dividend, interest income | C48: 135 | E48: 866400000 | F48: 866400000
A49: 3.2.2 | B49: 3.2.2.Dự thu cổ tức, tiền lãi chưa đến ngày nhận Dividend and interest receivables before payment date | C49: 136 | E49: 4859362740 | F49: 5814257241
B50: Dự thu cổ tức Dividend receivables | C50: 136.1 | E50: 2474760000 | F50: 2335154500
B51: Dự thu lãi trái phiếu Interest accrual from bonds | C51: 136.2 | E51: 2118767124 | F51: 3279726029
B52: Dự thu lãi tiền gửi có kỳ hạn dưới 3 tháng Interest accrual from deposits with term less than three (03) months | C52: 136.3 | E52: 0 | F52: 0
B53: Dự thu lãi tiền gửi có kỳ hạn trên 3 tháng Interest accrual from deposit with term more than three (03) months | C53: 136.4 | E53: 0 | F53: 0
B54: Dự thu lãi chứng chỉ tiền gửi Interest accrual from Certificates of Deposit | C54: 136.5 | E54: 265835616 | F54: 199376712
B55: Dự thu lãi hợp đồng mua lại đảo ngược Interest receivables from reverse repo contracts | C55: 136.6 | E55: 0 | F55: 0
A56: 3.3 | B56: 3.3. Các khoản phải thu khác Other receivables | C56: 137 | E56: 0 | F56: 0
B57: Phải thu cho khoản cổ phiếu hạn chế chờ mua Receivable from AP/Investors on securities on hold of buying | C57: 137.1 | E57: 0 | F57: 0
B58: Các tài sản khác Other assets | C58: 137.2 | E58: 0 | F58: 0
B59: Các khoản khác Others | C59: 137.3 | E59: 0 | F59: 0
A60: 3.4 | B60: 3.4. Dự phòng nợ phải thu khó đòi Provision for doubtful debt | C60: 138 | E60: -866400000 | F60: -866400000
B61: TỔNG TÀI SẢN TOTAL ASSETS | C61: 100 | E61: 1678750168277 | F61: 1637235690195
A62: II | B62: II. NỢ PHẢI TRẢ TOTAL LIABILITIES | C62: II
A63: 1 | B63: 1. Vay ngắn hạn Short-term loans | C63: 311 | E63: 0 | F63: 0
B64: Gốc hợp đồng repo Repo contracts - Principal | C64: 311.1 | E64: 0 | F64: 0
B65: Vay ngắn hạn Short-term loans | C65: 311.2 | E65: 0 | F65: 0
A66: 2 | B66: 2. Phải trả về mua các khoản đầu tư Payables for securities bought but not yet settled | C66: 312 | E66: 129590415000 | F66: 67553225000
A67: 3 | B67: 3. Phải trả phí cho các Đại lý phân phối, Công ty quản lý quỹ về mua bán Chứng chỉ quỹ Subscription and Redemption fee payable to distributors and fund management company | C67: 313 | E67: 498829721 | F67: 364202705
B68: Phải trả phí cho các Đại lý phân phối về mua bán Chứng chỉ quỹ Subscription and Redemption fee payable to distributors | C68: 313.1 | E68: 6835448 | F68: 6835448
B69: Phải trả phí cho Công ty quản lý quỹ về mua bán Chứng chỉ quỹ Subscription and Redemption fee payable to fund management company | C69: 313.2 | E69: 491994273 | F69: 357367257
A70: 4 | B70: 4. Thuế và các khoản phải nộp Nhà nước Tax payables and obligations to the State Budget | C70: 314 | E70: 17156187 | F70: 13315654
A71: 5 | B71: 5.Phải trả thu nhập cho Nhà đầu tư Profit distribution payables | C71: 315 | E71: 39925000 | F71: 39925000
A72: 6 | B72: 6. Chi phí phải trả Expense Accruals | C72: 316 | E72: 395744036 | F72: 300024871
B73: Phí giao dịch Transaction fee | C73: 316.1 | E73: 267738269 | F73: 189240157
B74: Phải trả phí môi giới Brokerage fee payables | C74: 316.1.1 | E74: 267738269 | F74: 189240157
B75: Phải trả phí giao dịch thanh toán bù trừ chứng khoán Clearing Settlement Fee payables | C75: 316.1.2 | E75: 0 | F75: 0
B76: Trích trước phí kiểm toán Accrued expense for audit fee | C76: 316.2 | E76: 107557028 | F76: 91055511
B77: Trích trước phí họp đại hội thường niên Accrued expense for Annual General meeting | C77: 316.3 | E77: 0 | F77: 0
B78: Trích trước phí báo cáo thường niên Accrued expense for Annual report | C78: 316.4 | E78: 0 | F78: 0
B79: Trích trước thù lao ban đại diện quỹ Accrued expense for Remuneration Payable to Fund's Board of Representatives | C79: 316.5 | E79: 20448739 | F79: 19729203
B80: Trích trước phí quản lý niêm yết hàng năm tại SGDCK Accrued expense for annual listing fee at HOSE | C80: 316.6 | E80: 0 | F80: 0
B81: Trích trước lãi vay ngắn hạn của hợp đồng vay và hợp đồng repo Accrued Interest Expense of short-term loan contracts and repo contracts | C81: 316.7 | E81: 0 | F81: 0
A82: 7 | B82: 7. Phải trả cho Nhà đầu tư về mua Chứng chỉ quỹ Subscription payables to investors | C82: 317 | E82: 1158156289 | F82: 2944693215
B83: Phải trả cho nhà đầu tư chờ mua chứng chỉ quỹ Subscription Pending allotment | C83: 317.1 | E83: 1158156289 | F83: 2944693215
B84: Phải trả nhà đầu tư trên tài sản giữ hộ Payables to investors for investment bought on behalf | C84: 317.2 | E84: 0 | F84: 0
A85: 8 | B85: 8. Phải trả cho Nhà đầu tư về mua lại Chứng chỉ quỹ Redemption payables to investors | C85: 318 | E85: 15170468046 | F85: 1408685339
A86: 9 | B86: 9. Phải trả dịch vụ quản lý Quỹ mở Fund management related service expense payable | C86: 319 | E86: 2703222421 | F86: 2756275170
B87: Trích trước phải trả phí quản lý Accrued expense for Management fee | C87: 319.1 | E87: 2510663947 | F87: 2562833656
B88: Trích trước phí lưu ký tài sản Quỹ mở Accrued expense for Custodian fee | C88: 319.2 | E88: 87300798 | F88: 88470948
B89: Phí dịch vụ lưu ký - bảo quản tài sản Custodian service - Safe Custody Fee | C89: 319.2.1 | E89: 51500798 | F89: 52570948
B90: Phí dịch vụ lưu ký - giao dịch chứng khoán Custodian service - Transaction fee | C90: 319.2.2 | E90: 35800000 | F90: 35900000
B91: Phí dịch vụ lưu ký cho chứng khoán cơ sở, phí quản lý vị thế và tài sản phái sinh trả cho VSD Custodian service - Depository fee, Position and Margin management fee paid to VSD | C91: 319.2.3 | E91: 0 | F91: 0
B92: Trích trước phí quản trị quỹ Accrued expense for Fund administration fee | C92: 319.3 | E92: 35406798 | F92: 36142524
B93: Trích trước phí giám sát Accrued expense for Supervising fee | C93: 319.4 | E93: 56650878 | F93: 57828042
B94: Trích trước phí dịch vụ đại lý chuyển nhượng Accrued expense for Tranfer agency fee | C94: 319.5 | E94: 13200000 | F94: 11000000
B95: Dự chi phí cung cấp dịch vụ tính giá trị tài sản ròng tham chiếu (iNAV) cho HOSE Accrued expense for payable to HOSE for iNAV calculation | C95: 319.6 | E95: 0 | F95: 0
B96: Dự chi phí cấp quyền sử dụng chỉ số cho HOSE Accrued expense for payable to HOSE for Index usage | C96: 319.7 | E96: 0 | F96: 0
A97: 10 | B97: 10. Phải trả, phải nộp khác Other payables | C97: 320 | E97: 176482966 | F97: 176482966
B98: Phải trả phí báo giá Price feed fee payable | C98: 320.1 | E98: 0 | F98: 0
B99: Trích trước phí công tác, họp của ban đại diện Accrued expense for Fund's Board of Representatives travelling, meeting | C99: 320.2 | E99: 0 | F99: 0
B100: Trích trước phí quản lý thường niên trả cho UBCKNN Accrued expense for Annual Fee paid to SSC | C100: 320.3 | E100: 0 | F100: 0
B101: Phí Ngân hàng S2B S2B Bank charge | C101: 320.4 | E101: 0 | F101: 0
B102: Phải trả khác Other payables | C102: 320.5 | E102: 176482966 | F102: 176482966
B103: TỔNG NỢ PHẢI TRẢ TOTAL LIABILITIES | C103: 300 | E103: 149750399666 | F103: 75556829920
...

Sheet BCTaiSan_06027
A1: Phụ lục XXVI. Mẫu báo cáo về hoạt động của Quỹ Appendix XXVI. Report on Fund's Operation
A2: (Ban hành kèm theo Thông tư số 98/2020/TT-BTC ngày 16 tháng 11 năm 2020 của Bộ trưởng Bộ Tài Chính về hướng dẫn hoạt động và quản lý quỹ đầu tư chứng khoán) (Issued in association with Circular 98/2020/TT-BTC dated 16 November 2020 of the Minister of Finance on guiding the operation and management of the securities investment funds)
A3: BÁO CÁO VỀ HOẠT ĐỘNG ĐẦU TƯ REPORT ON INVESTMENT ACTIVITIES
A5: Tại ngày 31 tháng 07 năm 2022 / As at 31 Jul 2022
A7: Tên Công ty quản lý quỹ: | C7: Công ty Cổ phần Quản lý Quỹ Đầu tư Dragon Capital Việt Nam
A8: Fund Management Company: | C8: Dragon Capital Vietfund Management Joint Stock Company
A9: Tên ngân hàng giám sát: | C9: Ngân hàng TNHH Một thành viên Standard Chartered (Việt Nam)
A10: Supervising bank: | C10: Standard Chartered Bank (Vietnam) Limited
A11: Tên Quỹ: | C11: Quỹ Đầu tư Chứng khoán Năng động DC
A12: Fund name: | C12: DC Dynamic Securities Fund(VFMVF1)
A13: Ngày lập báo cáo: | C13: Ngày 01 tháng 08 năm 2022
A14: Reporting Date: | C14: 01 Aug 2022
A16: A. | B16: BÁO CÁO CHUNG VỀ HOẠT ĐỘNG ĐẦU TƯ CỦA QUỸ/GENERAL INFORMATION ON FUND'S INVESTMENT ACTIVITIES
A17: I | B17: BÁO CÁO VỀ TÀI SẢN / ASSET REPORT
A18: STT No | B18: Nội dung Indicator | C18: Mã chỉ tiêu Code | D18: Ngày 31 tháng 07 năm 2022 As at 31 Jul 2022 | E18: Ngày 30 tháng 06 năm 2022 As at 30 Jun 2022 | F18: %/cùng kỳ năm trước %/against last year
A19: I | B19: TÀI SẢN ASSETS
A20: I.1 | B20: Tiền và các khoản tương đương tiền Cash and Cash Equivalents | D20: 189101074987 | E20: 118659866954 | F20: 3.0340988
B21: Tiền gửi ngân hàng Cash at bank | D21: 189101074987 | E21: 118659866954 | F21: 3.0340988
B22: Tiền gửi của nhà đầu tư cho hoạt động mua chứng chỉ quỹ Cash at bank for Fund's subscription | D22: 0 | E22: 0
B23: Tiền phải trả cho Nhà đầu tư về mua lại chứng chỉ quỹ Cash at bank for Fund's redemption | D23: 719033789 | E23: 1118154682 | F23: 4.5588939
B24: Tiền gửi ngân hàng cho hoạt động của Quỹ Cash at bank for Fund's operation | D24: 188382041198 | E24: 117541712272 | F24: 3.0302303
B25: Tiền gửi ký quỹ cho hoạt động đầu tư chứng khoán phái sinh Margin account for trading derivatives | D25: 0 | E25: 0
B26: Tiền, tương đương tiền Cash, cash equivalents | D26: 0 | E26: 0
A27: I.2 | B27: Các khoản đầu tư (kê chi tiết) Investments | D27: 1401393395550 | E27: 1470911463400 | F27: 1.7481488
B28: Cổ phiếu niêm yết Listed shares | D28: 1271337570950 | E28: 1291055638800 | F28: 1.7376289
B29: Cổ phiếu chưa niêm yết Unlisted shares | D29: 0 | E29: 0
B30: Trái phiếu Bonds | D30: 120055824600 | E30: 169855824600 | F30: 2.4014323
B31: Chứng chỉ tiền gửi Certificates of Deposit | D31: 10000000000 | E31: 10000000000 | F31: 0.5
B32: Hợp đồng tiền gửi có kỳ hạn trên ba (03) tháng Deposits with term over three (03) months | D32: 0 | E32: 0
B33: Quyền mua chứng khoán Investment - Rights | D33: 0 | E33: 0
B34: Hợp đồng tương lai chỉ số Index future contracts | D34: 0 | E34: 0
B35: Đầu tư khác Other investments | D35: 0 | E35: 0
B36: Hợp đồng mua lại đảo ngược Reverse repo contracts | D36: 0 | E36: 0
A37: I.3 | B37: Thu từ cho thuê bất động sản đầu tư (không áp dụng) Receivables from rental of investment property (not applicable)
A38: I.4 | B38: Cổ tức, trái tức được nhận Dividend, Coupon receivables | D38: 5459927124 | E38: 6481280529 | F38: 2.2065338
B39: Phải thu cổ tức Dividend receivables | D39: 3341160000 | E39: 3201554500 | F39: 3.0188522
B40: Phải thu trái tức Coupon receivables | D40: 2118767124 | E40: 3279726029 | F40: 1.5491787
A41: I.5 | B41: Lãi được nhận Interest receivables | D41: 265835616 | E41: 199376712 | F41: 0.53774108
B42: Phải thu lãi tiền gửi Interest receivable from bank deposits | D42: 0 | E42: 0
B43: Phải thu lãi chứng chỉ tiền gửi Interest receivable from Certificates of Deposit | D43: 265835616 | E43: 199376712 | F43: 0.53774108
B44: Phải thu lãi hợp đồng mua lại đảo ngược Interest receivable from reverse repo contracts | D44: 0 | E44: 0
A45: I.6 | B45: Tiền bán bất động sản chờ thu (không áp dụng) Real Estate Proceeds Receivables (not applicale)
A46: I.7 | B46: Tiền bán chứng khoán chờ thu Securities Trading Receivables | D46: 83396335000 | E46: 41850102600
A47: I.8 | B47: Các khoản phải thu khác Other Receivables | D47: -866400000 | E47: -866400000 | F47: 1
B48: Dự phòng giảm giá tài sản nhận thế chấp Impairment of devaluation of pledged assets | D48: 0 | E48: 0
B49: Dự phòng nợ phải thu khó đòi Provision for doubtful debt | D49: -866400000 | E49: -866400000 | F49: 1
B50: Các khoản phải thu khác Other Receivables | D50: 0 | E50: 0
A51: I.9 | B51: Các tài sản khác Other Assets | D51: 0 | E51: 0
A52: I.10 | B52: TỔNG TÀI SẢN TOTAL ASSETS | D52: 1678750168277 | E52: 1637235690195 | F52: 1.9383496
A53: II | B53: NỢ LIABILITIES
A54: II.1 | B54: Tiền phải thanh toán mua bất động sản (không áp dụng) Real Estate Trading Payables (not applicable)
A55: II.2 | B55: Tiền phải thanh toán mua chứng khoán Securities Trading Payables | D55: 129590415000 | E55: 67553225000 | F55: 45.153455
A56: II.3 | B56: Các khoản phải trả khác Other Payables | D56: 20159984666 | E56: 8003604920 | F56: 2.9748501
B57: Phải trả nhà đầu tư Payables to investors | D57: 16328624335 | E57: 4353378554 | F57: 3.6844567
B58: Phải trả cho nhà đầu tư chờ mua chứng chỉ quỹ Subscription Pending allotment | D58: 1158156289 | E58: 2944693215 | F58: 0.30024024
B59: Phải trả nhà đầu tư trên tài sản giữ hộ Payables to investors for investment bought on behalf | D59: 0 | E59: 0
B60: Phải trả nhà đầu tư trên cổ tức đã thu Payables to investors for collected dividend | D60: 0 | E60: 0
B61: Phải trả cho Nhà đầu tư về mua lại chứng chỉ quỹ Redemption payable to investors | D61: 15170468046 | E61: 1408685339 | F61: 26.414336
B62: Thuế và các khoản phải nộp Nhà nước Tax payables and obligations to the State Budget | D62: 17156187 | E62: 13315654 | F62: 0.18786678
B63: Phải trả phí phát hành, mua lại chứng chỉ quỹ cho Đại lý phân phối và Công ty quản lý quỹ Subscription and Redemption fee payable to distributors and Fund Management Company | D63: 498829721 | E63: 364202705 | F63: 1.3449301
B64: Phải trả thu nhập cho nhà đầu tư Income payable to investors | D64: 39925000 | E64: 39925000 | F64: 1
B65: Phải trả thù lao Ban đại diện quỹ Remuneration Payable to Fund's Board of Representatives | D65: 20448739 | E65: 19729203 | F65: 0.76091239
B66: Phải trả phí quản lý cho công ty quản lý quỹ Management fee payable | D66: 2510663947 | E66: 2562833656 | F66: 1.7957969
B67: Phải trả phí quản trị quỹ Fund Administration fee payable | D67: 35406798 | E67: 36142524 | F67: 1.795797
B68: Phải trả phí giám sát Supervisory service fee payable | D68: 56650878 | E68: 57828042 | F68: 1.7957969
B69: Phí giao dịch Transaction fee | D69: 267738269 | E69: 189240157 | F69: 9.0942099
B70: Phải trả phí môi giới Brokerage fee payable | D70: 267738269 | E70: 189240157 | F70: 9.0942099
B71: Phải trả phí phát hành thanh toán bù trừ chứng khoán Clearing Settlement fee payable | D71: 0 | E71: 0
B72: Trích trước phí lưu ký tài sản Quỹ mở Accrued expense for Custodian fee | D72: 87300798 | E72: 88470948 | F72: 1.9685329
B73: Phí lưu ký - bảo quản tài sản Custodian service - Safe Custody Fee | D73: 51500798 | E73: 52570948 | F73: 1.4366374
B74: Phí lưu ký - giao dịch chứng khoán Custodian service - Transaction fee | D74: 35800000 | E74: 35900000 | F74: 4.2117647
B75: Phí lưu ký cho chứng khoán cơ sở, phí quản lý vị thế và tài sản phái sinh trả cho VSD Custodian service - Depository fee, Position and Margin management fee paid to VSD | D75: 0 | E75: 0
B76: Phải trả phí kiểm toán Audit fee payable | D76: 107557028 | E76: 91055511 | F76: 1.0202795
B77: Phải trả phí họp đại hội thường niên General meeting expense payable | D77: 0 | E77: 0
B78: Phải trả phí báo cáo thường niên Annual report fee payable | D78: 0 | E78: 0
B79: Phải trả phí dịch vụ đại lý chuyển nhượng Transfer Agency fee payable | D79: 13200000 | E79: 11000000 | F79: 1.2
B80: Dự chi phí tính giá trị tài sản ròng tham chiếu (iNAV) cho HOSE Service fee payable to HOSE for calculating iNAV | D80: 0 | E80: 0
B81: Dự chi phí cấp quyền sử dụng chỉ số cho HOSE Authorising index service fee payable to HOSE | D81: 0 | E81: 0
B82: Phải trả khác Other payables | D82: 176482966 | E82: 176482966 | F82: 1
B83: Phải trả phí báo giá Price feed fee payable | D83: 0 | E83: 0
B84: Trích trước phí công tác, họp của ban đại diện Accrued expense for Fund's Board of Representatives travelling, meeting | D84: 0 | E84: 0
B85: Trích trước phí quản lý thường niên trả UBCKNN Accrued expense for Annual Management Fee pay to SSC | D85: 0 | E85: 0
B86: Phải trả khác Other payables | D86: 176482966 | E86: 176482966 | F86: 1
B87: Vay ngắn hạn - hợp đồng repo Short-term loans - Repo contracts | D87: 0 | E87: 0
B88: Gốc hợp đồng repo Principal of repo contracts | D88: 0 | E88: 0
B89: Trích trước lãi vay ngắn hạn Accrued Interest Expense | D89: 0 | E89: 0
B90: Gốc vay ngắn hạn Principal of Short-term loans | D90: 0 | E90: 0
A91: II.4 | B91: TỔNG NỢ TOTAL LIABILITIES | D91: 149750399666 | E91: 75556829920 | F91: 15.523313
B92: Tài sản ròng của Quỹ ( = I.10 - II.4) Net Asset Value ( = I.10 - II.4) | D92: 1528999768611 | E92: 1561678860275 | F92: 1.7853281
B93: Tổng số chứng chỉ quỹ đang lưu hành Total Outstanding Fund Certificates | D93: 25562665 | E93: 25785278 | F93: 2.0255659
B94: Giá trị tài sản ròng trên một chứng chỉ quỹ Net Asset Value per Fund Certificate | D94: 59813.78 | E94: 60564.74 | F94: 0.88139717
A96: Đại diện có thẩm quyền của Ngân hàng giám sát | E96: Đại diện có thẩm quyền của Công ty quản lý Quỹ
A97: Authorised Representative of Supervisory Bank | E97: Authorised Representative of Fund Management Company
A105: Ngân hàng TNHH MTV Standard Chartered (Việt Nam) | E105: Công ty Cổ phần Quản lý Quỹ Đầu tư Dragon Capital Việt Nam
A106: Trịnh Hoài Nam | E106: Nguyễn Minh Đăng Khánh
A107: Phó phòng Dịch vụ Quản trị và Giám sát Quỹ | E107: Giám đốc điều hành Nghiệp vụ hỗ trợ đầu tư

Sheet BCKetQuaHoatDong_06028
A1: Phụ lục XXVI. Mẫu báo cáo về hoạt động của Quỹ Appendix XXVI. Report on Fund's Operation
A2: (Ban hành kèm theo Thông tư số 98/2020/TT-BTC ngày 16 tháng 11 năm 2020 của Bộ trưởng Bộ Tài Chính về hướng dẫn hoạt động và quản lý quỹ đầu tư chứng khoán) (Issued in association with Circular 98/2020/TT-BTC dated 16 November 2020 of the Minister of Finance on guiding the operation and management of the securities investment funds)
A3: BÁO CÁO VỀ HOẠT ĐỘNG ĐẦU TƯ REPORT ON INVESTMENT ACTIVITIES
A5: Tháng 07 năm 2022 / Jul 2022
A7: Tên Công ty quản lý quỹ: | C7: Công ty Cổ phần Quản lý Quỹ Đầu tư Dragon Capital Việt Nam
A8: Fund Management Company: | C8: Dragon Capital Vietfund Management Joint Stock Company
A9: Tên ngân hàng giám sát: | C9: Ngân hàng TNHH Một thành viên Standard Chartered (Việt Nam)
A10: Supervising bank: | C10: Standard Chartered Bank (Vietnam) Limited
A11: Tên Quỹ: | C11: Quỹ Đầu tư Chứng khoán Năng động DC
A12: Fund name: | C12: DC Dynamic Securities Fund(VFMVF1)
A13: Ngày lập báo cáo: | C13: Ngày 01 tháng 08 năm 2022
A14: Reporting Date: | C14: 01 Aug 2022
A16: A. | B16: BÁO CÁO CHUNG VỀ HOẠT ĐỘNG ĐẦU TƯ CỦA QUỸ/GENERAL INFORMATION ON FUND'S INVESTMENT ACTIVITIES
A17: II | B17: BÁO CÁO KẾT QUẢ HOẠT ĐỘNG / PROFIT AND LOSS REPORT
A18: STT No | B18: Nội dung Indicator | C18: Mã chỉ tiêu Code | D18: Tháng 07 năm 2022 Jul 2022 | E18: Tháng 06 năm 2022 Jun 2022 | F18: Lũy kế từ đầu năm Accumulated from beginning of year
A19: I | B19: Thu nhập từ hoạt động đầu tư Income from Investment Activities | D19: 4527487272 | E19: 5778917619 | F19: 20134422879
A20: 1 | B20: Thu từ bất động sản cho thuê (không áp dụng) Income from rental property (not applicable)
A21: 2 | B21: Cổ tức, trái tức được nhận Dividend income, interest income from bonds | D21: 4438803790 | E21: 5691951625 | F21: 18399525406
B22: Cổ tức được nhận Dividends income | D22: 2937160000 | E22: 4163184500 | F22: 9928292500
B23: Trái tức được nhận Interest income from bonds | D23: 1501643790 | E23: 1528767125 | F23: 8471232906
A24: 3 | B24: Lãi được nhận Interest income | D24: 88683482 | E24: 86965994 | F24: 1734897473
B25: Lãi tiền gửi ngân hàng Interest income from bank deposits | D25: 22224578 | E25: 22650926 | F25: 1028198843
B26: Lãi chứng chỉ tiền gửi Interest income from Certificates of Deposit | D26: 66458904 | E26: 64315068 | F26: 706698630
B27: Lãi hợp đồng mua lại đảo ngược Interest income from reverse repo contracts | D27: 0 | E27: 0 | F27: 0
A28: 4 | B28: Các khoản thu nhập khác Other incomes | D28: 0 | E28: 0 | F28: 0
B29: Thu nhập khác về đầu tư Other investment incomes | D29: 0 | E29: 0 | F29: 0
B30: Thu nhập khác Other incomes | D30: 0 | E30: 0 | F30: 0
B31: Chi phí dự phòng nợ phải thu khó đòi về cổ tức, tiền lãi và xử lý tổn thất nợ phải thu khó đòi về cổ tức, tiền lãi Provision expense for bad debts from dividends, interest income and written off bad debts from dividends, interest income | D31: 0 | E31: 0 | F31: 0
A32: II | B32: Chi phí Expenses | D32: 4669338584 | E32: 5216351986 | F32: 28333305747
A33: 1 | B33: Chi phí quản lý trả cho Công ty quản lý quỹ Management Fee paid to Fund Management Company | D33: 2510663947 | E33: 2562833656 | F33: 18994474631
A34: 2 | B34: Chi phí lưu ký, giám sát trả cho Ngân hàng Giám sát/VSD Custody fee, Supervising fee paid to Supervising Bank/VSD | D34: 151138053 | E34: 153352081 | F34: 978239083
B35: Chi phí dịch vụ lưu ký - bảo quản tài sản Custodian service - Safe Custody Fee | D35: 51500798 | E35: 52570948 | F35: 389630247
B36: Chi phí dịch vụ lưu ký - giao dịch chứng khoán Custodian service - Transaction fee | D36: 33200000 | E36: 33700000 | F36: 104600000
B37: Chi phí dịch vụ lưu ký cho chứng khoán cơ sở, phí quản lý vị thế và tài sản phái sinh trả cho VSD Custodian service - Depository fee, Position and Margin management fee paid to VSD | D37: 9786377 | E37: 9253091 | F37: 55415562
B38: Chi phí giám sát Supervisory fee | D38: 56650878 | E38: 57828042 | F38: 428593274
A39: 3 | B39: Chi phí quản trị quỹ và các chi phí khác mà công ty quản lý quỹ trả cho tổ chức cung cấp dịch vụ có liên quan Fund Administration Fee, and other fees paid to relevant Fund's service providers | D39: 48606798 | E39: 47142524 | F39: 347070794
B40: Chi phí quản trị Quỹ Fund Administration Fee | D40: 35406798 | E40: 36142524 | F40: 267870794
B41: Chi phí dịch vụ Đại lý Chuyển nhượng Transfer Agency Fee | D41: 13200000 | E41: 11000000 | F41: 79200000
A42: 4 | B42: Chi phí dịch vụ quản lý bất động sản (không áp dụng) Real Estate Management Service fee (not applicable)
A43: 5 | B43: Chi phí dịch vụ định giá bất động sản (không áp dụng) Real estate valuation service fees (not applicable)
A44: 6 | B44: Chi phí kiểm toán trả cho tổ chức kiểm toán Audit fee | D44: 16501517 | E44: 15969210 | F44: 108499028
A45: 7 | B45: Chi phí dịch vụ tư vấn pháp lý, dịch vụ báo giá và các dịch vụ hợp lý khác, thù lao trả cho ban đại diện quỹ Legal consultancy expenses, price feed fee, other valid expenses, remuneration paid to Fund's Board of Representatives | D45: 57952869 | E45: 12696326 | F45: 191648738
B46: Thù lao Ban đại diện Quỹ Remuneration of Fund's Board of Representatives | D46: 12719536 | E46: 12696326 | F46: 117448739
B47: Chi phí cung cấp báo giá chứng khoán Price feed fee | D47: 45233333 | E47: 0 | F47: 74199999
B48: Chi phí dịch vụ tư vấn pháp lý Legal consultancy expenses | D48: 0 | E48: 0 | F48: 0
A49: 8 | B49: Chi phí dự thảo, in ấn, gửi bản cáo bạch, bản cáo bạch tóm tắt, báo cáo tài chính, xác nhận giao dịch, sao kê tài khoản và các tài liệu khác cho nhà đầu tư; chi phí công bố thông tin của quỹ; chi phí tổ chức họp đại hội nhà đầu tư, ban đại diện quỹ Fee for drafting, printing, distribution of prospectus, summarised prospectus, financial statements, transaction confirmations, account statements and other documents to investors; information disclosure fee; fee for organising annual general meeting, board of representatives meeting | D49: 0 | E49: 2326968 | F49: 35094216
B50: Chi phí họp Đại hội Quỹ Meeting expenses | D50: 0 | E50: 2326968 | F50: 35094216
B51: Chi phí báo cáo thường niên Annual report expenses | D51: 0 | E51: 0 | F51: 0
B52: Chi phí họp, công tác của Ban đại diện Fund's Board of Representatives meeting, travelling expenses | D52: 0 | E52: 0 | F52: 0
B53: Chi phí công bố thông tin của Quỹ Expenses of information disclosure of the Fund | D53: 0 | E53: 0 | F53: 0
B54: Chi phí thiết kế, in ấn, gửi thư… Designing, printing, posting... expenses | D54: 0 | E54: 0 | F54: 0
A55: 9 | B55: Chi phí liên quan đến thực hiện các giao dịch tài sản của Quỹ Expenses related to execution of Fund’s asset transactions | D55: 1878264800 | E55: 2411028471 | F55: 7627115232
B56: Chi phí môi giới Brokerage fee | D56: 1872123750 | E56: 2408972041 | F56: 7613216232
B57: Chi phí thanh toán bù trừ Clearing settlement fee | D57: 6141050 | E57: 2056430 | F57: 13899000
B58: Chi phí khác Other Expenses | D58: 0 | E58: 0 | F58: 0
A59: 10 | B59: Các loại chi phí khác Other expenses | D59: 6210600 | E59: 11002750 | F59: 51164025
B60: Chi phí thiết lập Quỹ Set up Expenses | D60: 0 | E60: 0 | F60: 0
B61: Phí niêm yết, đăng ký chứng khoán Listing, registration fees | D61: 0 | E61: 0 | F61: 0
B62: Phí quản lý thường niên trả cho UBCKNN Annual management fee paid to SSC | D62: 0 | E62: 0 | F62: 0
B63: Phí ngân hàng Bank charges | D63: 6210600 | E63: 11002750 | F63: 50064025
B64: Chi phí lãi vay Borrowing expense | D64: 0 | E64: 0 | F64: 0
B65: Chi phí khác Other Expenses | D65: 0 | E65: 0 | F65: 0
B66: Phí thực hiện quyền trả cho VSD Fee paid to VSD for getting the list of investors | D66: 0 | E66: 0 | F66: 1100000
A67: III | B67: Thu nhập ròng từ hoạt động đầu tư (= I - II) Net Income from Investment Activities (= I - II) | D67: -141851312 | E67: 562565633 | F67: -8198882868
A68: IV | B68: Lãi / (lỗ) từ hoạt động đầu tư Gain / (Loss) from Investment Activities | D68: -19466873145 | E68: -91935427050 | F68: -449852307949
A69: 1 | B69: Lãi (lỗ) thực tế phát sinh từ hoạt động đầu tư hoặc chuyển nhượng bất động sản Realised Gain / (Loss) from disposal of investment or real estate transfer | D69: -56005984946 | E69: -85220772842 | F69: -223721190383
A70: 2 | B70: Thay đổi về giá trị của các khoản đầu tư trong kỳ Unrealised Gain / (Loss) due to market price | D70: 36539111801 | E70: -6714654208 | F70: -226131117566
A71: V | B71: Thay đổi của giá trị tài sản ròng của Quỹ do các hoạt động đầu tư trong kỳ (III + IV) Change of Net Asset Value of the Fund due to investment activities during the period (= III + IV) | D71: -19608724457 | E71: -91372861417 | F71: -458051190817
A72: VI | B72: Giá trị tài sản ròng đầu kỳ Net Asset Value at the beginning of period | D72: 1561678860275 | E72: 1620610632855 | F72: 1641867480749
A73: VII | B73: Thay đổi giá trị tài sản ròng của Quỹ trong kỳ Change of Net Asset Value of the Fund during the period | D73: -32679091664 | E73: -58931772580 | F73: -112867712138
B74: Trong đó: Of which:
A75: 1 | B75: Thay đổi giá trị tài sản ròng của Quỹ do các hoạt động đầu tư của Quỹ trong kỳ Change of Net Asset Value due to investment activities during the period | D75: -19608724457 | E75: -91372861417 | F75: -458051190817
A76: 2 | B76: Thay đổi giá trị tài sản ròng của Quỹ do việc chi trả lợi tức/ cổ tức của Quỹ cho các nhà đầu tư trong kỳ Change of Net Asset Value due to dividends payment to investors during the period | D76: 0 | E76: 0 | F76: 0
A77: 3 | B77: Thay đổi giá trị tài sản ròng do phát hành thêm/mua lại chứng chỉ quỹ Change of Net Asset Value due to subscription/redemption during the period | D77: -13070367207 | E77: 32441088837 | F77: 345183478679
B78: Thay đổi giá trị tài sản ròng do phát hành thêm Chứng chỉ Quỹ Change of Net Asset Value due to subscription during the period | D78: 24361788681 | E78: 51855917042 | F78: 623977676265
B79: Thay đổi giá trị tài sản ròng do mua lại Chứng chỉ Quỹ Change of Net Asset Value due to redemption during the period | D79: -37432155888 | E79: -19414828205 | F79: -278794197586
A80: VIII | B80: Giá trị tài sản ròng cuối kỳ Net Asset Value at the end of period | D80: 1528999768611 | E80: 1561678860275 | F80: 1528999768611
A81: IX | B81: Lợi nhuận bình quân năm (chỉ áp dụng đối với báo cáo năm) Average annual profit (only applicable to annual report) | D81: 0 | E81: 0 | F81: 0
B82: Tỷ suất lợi nhuận bình quân năm (chỉ áp dụng đối với báo cáo năm) Average annual rate of return (only applicable to annual report) | D82: 0 | E82: 0 | F82: 0
A85: Đại diện có thẩm quyền của Ngân hàng giám sát | D85: Đại diện có thẩm quyền của Công ty quản lý Quỹ
A86: Authorised Representative of Supervisory Bank | D86: Authorised Representative of Fund Management Company
A94: Ngân hàng TNHH MTV Standard Chartered (Việt Nam) | D94: Công ty Cổ phần Quản lý Quỹ Đầu tư Dragon Capital Việt Nam
A95: Trịnh Hoài Nam | D95: Nguyễn Minh Đăng Khánh
A96: Phó phòng Dịch vụ Quản trị và Giám sát Quỹ | D96: Giám đốc điều hành Nghiệp vụ hỗ trợ đầu tư

Sheet BCDanhMucDauTu_06029
A1: Phụ lục XXVI. Mẫu báo cáo về hoạt động của Quỹ Appendix XXVI. Report on Fund's Operation
A2: (Ban hành kèm theo Thông tư số 98/2020/TT-BTC ngày 16 tháng 11 năm 2020 của Bộ trưởng Bộ Tài chính về hướng dẫn hoạt động và quản lý quỹ đầu tư chứng khoán) (Issued in association with Circular 98/2020/TT-BTC dated 16 November 2020 of the Minister of Finance on guiding the operation and management of the securities investment funds)
A3: BÁO CÁO VỀ HOẠT ĐỘNG ĐẦU TƯ REPORT ON INVESTMENT ACTIVITIES
A5: Tại ngày 31 tháng 07 năm 2022 / As at 31 Jul 2022
A7: Tên Công ty quản lý quỹ: | C7: Công ty Cổ phần Quản lý Quỹ Đầu tư Dragon Capital Việt Nam
A8: Fund Management Company: | C8: Dragon Capital Vietfund Management Joint Stock Company
A9: Tên ngân hàng giám sát: | C9: Ngân hàng TNHH Một thành viên Standard Chartered (Việt Nam)
A10: Supervising bank: | C10: Standard Chartered Bank (Vietnam) Limited
A11: Tên Quỹ: | C11: Quỹ Đầu tư Chứng khoán Năng động DC
A12: Fund name: | C12: DC Dynamic Securities Fund(VFMVF1)
A13: Ngày lập báo cáo: | C13: Ngày 01 tháng 08 năm 2022
A14: Reporting Date: | C14: 01 Aug 2022
A16: A. | B16: BÁO CÁO CHUNG VỀ HOẠT ĐỘNG ĐẦU TƯ CỦA QUỸ/GENERAL INFORMATION ON FUND'S INVESTMENT ACTIVITIES
A17: III | B17: BÁO CÁO DANH MỤC ĐẦU TƯ / INVESTMENT PORTFOLIO REPORT
A18: STT No. | B18: Loại Category | C18: Mã chỉ tiêu Code | D18: Số Lượng Quantity | E18: Giá thị trường hoặc giá trị hợp lý tại ngày báo cáo Market price | F18: Tổng giá trị (Đồng) Value (VND) | G18: Tỷ lệ % Tổng giá trị tài sản của Quỹ % of total asset
A19: I | B19: BẤT ĐỘNG SẢN ĐẦU TƯ (KHÔNG ÁP DỤNG) REAL ESTATE INVESTMENT (NOT APPLICABLE)
A20: II | B20: CỔ PHIẾU NIÊM YẾT, ĐĂNG KÝ GIAO DỊCH, CHỨNG CHỈ QUỸ NIÊM YẾT SHARES LISTED, SHARES REGISTERED FOR TRADING, LISTED FUND CERTIFICATES
A21: 1 | B21: ACB | D21: 662677 | E21: 24600 | F21: 16301854200 | G21: 0.0097107089
A22: 2 | B22: BID | D22: 526800 | E22: 37300 | F22: 19649640000 | G22: 0.011704922
A23: 3 | B23: BWE | D23: 150000 | E23: 47700 | F23: 7155000000 | G23: 0.0042620993
A24: 4 | B24: CTD | D24: 196800 | E24: 60300 | F24: 11867040000 | G24: 0.0070689732
A25: 5 | B25: CTG | D25: 396800 | E25: 27200 | F25: 10792960000 | G25: 0.0064291639
A26: 6 | B26: DGC | D26: 212900 | E26: 89300 | F26: 19011970000 | G26: 0.011325074
A27: 7 | B27: DGW | D27: 257200 | E27: 58600 | F27: 15071920000 | G27: 0.0089780602
A28: 8 | B28: DPG | D28: 400000 | E28: 44250 | F28: 17700000000 | G28: 0.010543558
A29: 9 | B29: DXG | D29: 1101500 | E29: 24800 | F29: 27317200000 | G29: 0.016272344
A30: 10 | B30: FPT | D30: 615700 | E30: 83500 | F30: 51410950000 | G30: 0.030624539
A31: 11 | B31: FRT | D31: 226000 | E31: 72000 | F31: 16272000000 | G31: 0.0096929253
A32: 12 | B32: GAS | D32: 566800 | E32: 107500 | F32: 60931000000 | G32: 0.036295454
... A67: 47 | B67: VSH | D67: 399900 | E67: 39300 | F67: 15716070000 | G67: 0.0093617682
B68: TỔNG TOTAL | F68: 1271337570950 | G68: 0.75731195
A69: III | B69: CỔ PHIẾU CHƯA NIÊM YẾT, ĐĂNG KÝ GIAO DỊCH, CHỨNG CHỈ QUỸ KHÔNG NIÊM YẾT SHARES UNLISTED, UNREGISTERED FOR TRADING, UNLISTED FUND CERTIFICATES
B70: TỔNG TOTAL | D70: 0 | F70: 0 | G70: 0
B71: TỔNG CÁC LOẠI CỔ PHIẾU TOTAL SHARES | F71: 1271337570950 | G71: 0.75731195
A72: IV | B72: TRÁI PHIẾU BONDS
A73: 1 | B73: Trái phiếu niêm yết Listed bonds | F73: 30062400000 | G73: 0.017907608
A74: 1.1 | B74: CII121029 | D74: 300000 | E74: 100208 | F74: 30062400000 | G74: 0.017907608
A75: 2 | B75: Trái phiếu chưa niêm yết Unlisted Bonds | F75: 89993424600 | G75: 0.053607396
A76: 2.1 | B76: DAT XANH GROUP JSC 12% 18 Mar 2023 | D76: 200 | E76: 99967123 | F76: 19993424600 | G76: 0.011909708
A77: 2.2 | B77: KDH TRADING & INV JSC 12% 14/06/2025 | D77: 30 | E77: 1000000000 | F77: 30000000000 | G77: 0.017870438
A78: 2.3 | B78: PDR BOND 12 PCT 02 DEC 2023 | D78: 200 | E78: 100000000 | F78: 20000000000 | G78: 0.011913625
A79: 2.4 | B79: PHAT DAT REAL ESTATE 13% 24/09/2023 | D79: 200 | E79: 100000000 | F79: 20000000000 | G79: 0.011913625
B80: TỔNG TOTAL | F80: 120055824600 | G80: 0.071515004
A81: V | B81: CÁC LOẠI CHỨNG KHOÁN KHÁC OTHER SECURITIES
A82: 1 | B82: Quyền mua chứng khoán Investment - Rights | D82: 0 | F82: 0 | G82: 0
A83: 2 | B83: Chi tiết loại hợp đồng phái sinh(*) Index future contracts | D83: 0 | F83: 0 | G83: 0
B84: TỔNG TOTAL | F84: 0 | G84: 0
B85: TỔNG CÁC LOẠI CHỨNG KHOÁN TOTAL TYPES OF SECURITIES | F85: 1391393395550 | G85: 0.82882696
A86: VI | B86: CÁC TÀI SẢN KHÁC OTHER ASSETS
A87: 1 | B87: Cổ tức được nhận Dividend receivables | F87: 3341160000 | G87: 0.0019902664
A88: 2 | B88: Lãi trái phiếu được nhận Coupon receivables | F88: 2118767124 | G88: 0.0012621099
A89: 3 | B89: Lãi tiền gửi và chứng chỉ tiền gửi được nhận Interest receivables from bank deposits and certificates of deposit | F89: 265835616 | G89: 0.00015835329
A90: 4 | B90: Tiền bán chứng khoán chờ thu Outstanding Settlement of sales transactions | F90: 83396335000 | G90: 0.049677633
A91: 5 | B91: Phải thu cho khoản cổ phiếu hạn chế chờ mua Receivable from AP/Investors on securities on hold of buying | F91: 0 | G91: 0
A92: 6 | B92: Phải thu khác Other receivables | F92: -866400000 | G92: -0.00051609824
A93: 7 | B93: Tài sản khác Other assets | F93: 0 | G93: 0
B94: TỔNG TOTAL | F94: 88255697740 | G94: 0.052572264
A95: VII | B95: TIỀN CASH
A96: 1 | B96: Tiền, tương đương tiền Cash, Cash Equivalents | F96: 189101074987 | G96: 0.11264396
A97: 1.1 | B97: Tiền gửi ngân hàng Cash at Bank | F97: 189101074987 | G97: 0.11264396
A98: 1.2 | B98: Các khoản tương đương tiền Cash Equivalents | F98: 0 | G98: 0
A99: 2 | B99: Tiền gửi ngân hàng có kỳ hạn trên 3 tháng Deposits with term over three (03) months | F99: 0 | G99: 0
A100: 3 | B100: Chứng chỉ tiền gửi Certificates of deposit | F100: 10000000000 | G100: 0.0059568125
A101: 4 | B101: Công cụ chuyển nhượng… Transferable instruments… | F101: 0 | G101: 0
B102: TỔNG TOTAL | F102: 199101074987 | G102: 0.11860078
A103: VIII | B103: Tổng giá trị danh mục Total value of portfolio | F103: 1678750168277 | G103: 1
A105: Đại diện có thẩm quyền của Ngân hàng giám sát | E105: Đại diện có thẩm quyền của Công ty quản lý Quỹ
A106: Authorised Representative of Supervisory Bank | E106: Authorised Representative of Fund Management Company
A115: Ngân hàng TNHH MTV Standard Chartered (Việt Nam) | E115: Công ty Cổ phần Quản lý Quỹ Đầu tư Dragon Capital Việt Nam
A116: Trịnh Hoài Nam | E116: Nguyễn Minh Đăng Khánh
A117: Phó phòng Dịch vụ Quản trị và Giám sát Quỹ | E117: Giám đốc điều hành Nghiệp vụ hỗ trợ đầu tư

Sheet BCHoatDongVay_06026
A1: Phụ lục XXVI. Mẫu báo cáo về hoạt động của Quỹ Appendix XXVI. Report on Fund's Operation
A2: (Ban hành kèm theo Thông tư số 98/2020/TT-BTC ngày 16 tháng 11 năm 2020 của Bộ trưởng Bộ Tài Chính về hướng dẫn hoạt động và quản lý quỹ đầu tư chứng khoán) (Issued in association with Circular 98/2020/TT-BTC dated 16 November 2020 of the Minister of Finance on guiding the operation and management of the securities investment funds)
A3: BÁO CÁO VỀ HOẠT ĐỘNG ĐẦU TƯ REPORT ON INVESTMENT ACTIVITIES
A5: =TONGQUAN!C2 -> Tháng 07 năm 2022 / Jul 2022
A7: Tên Công ty quản lý quỹ: | G7: =TONGQUAN!D5 -> Công ty Cổ phần Quản lý Quỹ Đầu tư Dragon Capital Việt Nam
A8: Fund Management Company: | G8: =TONGQUAN!D6 -> Dragon Capital Vietfund Management Joint Stock Company
A9: Tên ngân hàng giám sát: | G9: =TONGQUAN!D7 -> Ngân hàng TNHH Một thành viên Standard Chartered (Việt Nam)
A10: Supervising bank: | G10: =TONGQUAN!D8 -> Standard Chartered Bank (Vietnam) Limited
A11: Tên Quỹ: | G11: =TONGQUAN!D9 -> Quỹ Đầu tư Chứng khoán Năng động DC
A12: Fund name: | G12: =TONGQUAN!D10 -> DC Dynamic Securities Fund(VFMVF1)
A13: Ngày lập báo cáo: | G13: =TONGQUAN!D11 -> Ngày 01 tháng 08 năm 2022
A14: Reporting Date: | G14: =TONGQUAN!D12 -> 01 Aug 2022
A15: A. | B15: BÁO CÁO CHUNG VỀ HOẠT ĐỘNG ĐẦU TƯ CỦA QUỸ/GENERAL INFORMATION ON FUND'S INVESTMENT ACTIVITIES
A16: IV | B16: BÁO CÁO HOẠT ĐỘNG VAY, GIAO DỊCH MUA BÁN LẠI / REPORT ON BORROWING OPERATION, REPO/REVERSE REPO TRANSACTIONS
A17: STT No. | B17: Nội dung hoạt động (nêu chi tiết theo mục tiêu và đối tác) Description | C17: Mã chỉ tiêu Code | D17: Đối tác Counterparty | E17: Mục tiêu/Tài sản đảm bảo Collateral | F17: Kỳ hạn Term | G17: Giá trị khoản vay hoặc khoản cho vay Amount | H17: Thời điểm giao dịch As at transaction date | J17: Thời điểm báo cáo As at reporting date
H18: Ngày tháng năm Date | I18: Tỷ lệ giá trị hợp đồng/giá trị tài sản ròng của quỹ Balance/NAV | J18: Ngày tháng năm Date | K18: Tỷ lệ giá trị hợp đồng/giá trị tài sản ròng của quỹ Balance/NAV
A19: 1 | B19: Các khoản vay tiền (nêu chi tiết từng hợp đồng) Borrowings (detail by each contract)
A20: I | B20: Tổng giá trị các khoản vay tiền/giá trị tài sản ròng Borrowings/NAV
A21: 2 | B21: Hợp đồng Repo (nêu chi tiết từng hợp đồng) Repo contract (detail by each contract)
A22: II | B22: Tổng giá trị các hợp đồng Repo/giá trị tài sản ròng Total value of Repo contracts/NAV
A23: A | B23: Tổng giá trị các khoản vay/giá trị tài sản ròng (=I+II) Total Borrowings, Repo/NAV (=I+II)
A24: 3 | B24: Cho vay chứng khoán (nêu chi tiết từng hợp đồng) Securities lending (detail by each contract)
A25: III | B25: Tổng giá trị các hợp đồng/giá trị tài sản ròng Total contract value/NAV
A26: 4 | B26: Hợp đồng Reverse Repo (nêu chi tiết từng hợp đồng) Reverse Repo contract (Detail by each contract)
A27: IV | B27: Tổng giá trị các hợp đồng/giá trị tài sản ròng Total contract value/NAV
A28: B | B28: Tổng giá trị các khoản cho vay/giá trị tài sản ròng (=III + IV) Total Loans/NAV (=III + IV)
A33: Đại diện có thẩm quyền của Ngân hàng giám sát | I33: Đại diện có thẩm quyền của Công ty quản lý Quỹ
A34: Authorised Representative of Supervisory Bank | I34: Authorised Representative of Fund Management Company
A44: Ngân hàng TNHH MTV Standard Chartered (Việt Nam) | I44: =TONGQUAN!F19 -> Công ty Cổ phần Quản lý Quỹ Đầu tư Dragon Capital Việt Nam
A45: =TONGQUAN!C20 -> Trịnh Hoài Nam | I45: =TONGQUAN!F20 -> Nguyễn Minh Đăng Khánh
A46: =TONGQUAN!C21 -> Phó phòng Dịch vụ Quản trị và Giám sát Quỹ | I46: =TONGQUAN!F21 -> Giám đốc điều hành Nghiệp vụ hỗ trợ đầu tư

Sheet Khac_06030
A1: Phụ lục XXVI. Mẫu báo cáo về hoạt động của Quỹ Appendix XXVI. Report on Fund's Operation
A2: (Ban hành kèm theo Thông tư số 98/2020/TT-BTC ngày 16 tháng 11 năm 2020 của Bộ trưởng Bộ Tài chính về hướng dẫn hoạt động và quản lý quỹ đầu tư chứng khoán) (Issued in association with Circular 98/2020/TT-BTC dated 16 November 2020 of the Minister of Finance on guiding the operation and management of the securities investment funds)
A3: BÁO CÁO VỀ HOẠT ĐỘNG ĐẦU TƯ REPORT ON INVESTMENT ACTIVITIES
A5: Tháng 07 năm 2022 / Jul 2022
A7: Tên Công ty quản lý quỹ: | C7: Công ty Cổ phần Quản lý Quỹ Đầu tư Dragon Capital Việt Nam
A8: Fund Management Company: | C8: Dragon Capital Vietfund Management Joint Stock Company
A9: Tên ngân hàng giám sát: | C9: Ngân hàng TNHH Một thành viên Standard Chartered (Việt Nam)
A10: Supervising bank: | C10: Standard Chartered Bank (Vietnam) Limited
A11: Tên Quỹ: | C11: Quỹ Đầu tư Chứng khoán Năng động DC
A12: Fund name: | C12: DC Dynamic Securities Fund(VFMVF1)
A13: Ngày lập báo cáo: | C13: Ngày 01 tháng 08 năm 2022
A14: Reporting Date: | C14: 01 Aug 2022
A16: A. | B16: BÁO CÁO CHUNG VỀ HOẠT ĐỘNG ĐẦU TƯ CỦA QUỸ/GENERAL INFORMATION ON FUND'S INVESTMENT ACTIVITIES
A17: V | B17: MỘT SỐ CHỈ TIÊU KHÁC / OTHER INDICATORS
A18: STT No | B18: Chỉ tiêu Indicators | C18: Mã chỉ tiêu Code | D18: Tháng 07 năm 2022 Jul 2022 | E18: Tháng 06 năm 2022 Jun 2022
A19: I | B19: CÁC CHỈ TIÊU VỀ HIỆU QUẢ HOẠT ĐỘNG INVESTMENT PERFORMANCE INDICATORS
A20: 1 | B20: Tỷ lệ giá dịch vụ quản lý quỹ trả cho công ty quản lý quỹ/Giá trị tài sản ròng trung bình trong kỳ (%) Management fee paid to the fund management company/Average NAV (%) | D20: 0.019876187 | E20: 0.019234837
A21: 2 | B21: Tỷ lệ giá dịch vụ lưu ký, giám sát trả cho Ngân hàng Giám sát/Giá trị tài sản ròng trung bình trong kỳ (%) Custody and supervising fees paid to the Supervisory Bank/Average NAV (%) | D21: 0.0011190396 | E21: 0.0010815062
A22: 3 | B22: Tỷ lệ chi phí dịch vụ quản trị quỹ, và các chi phí khác mà công ty quản lý quỹ trả cho tổ chức cung cấp dịch vụ có liên quan/Giá trị tài sản ròng của quỹ trung bình trong kỳ (%) Fund admin fee, and other fees paid to relating services providers by the fund management company/Average NAV (%) | D22: 0.00046228157 | E22: 0.00042326604
A23: 4 | B23: Chi phí kiểm toán trả cho tổ chức kiểm toán (nếu phát sinh)/Giá trị tài sản ròng trung bình trong kỳ (%) Auditing fee paid to auditing organizations (if any)/Average NAV (%) | D23: 0.00013063765 | E23: 0.00011985372
A24: 5 | B24: Chi phí trả cho tổ chức quản lý bất động sản/ Giá trị tài sản ròng trung bình trong kỳ (%) (không áp dụng) Fee paid to Real Estate management organisation/ Average NAV (%) (not applicable)
A25: 6 | B25: Chi phí trả cho doanh nghiệp thẩm định giá bất động sản/Giá trị tài sản ròng trung bình trong kỳ (%) (không áp dụng) Fee paid to Real Estate valuation service provider/ Average NAV (%) (not applicable)
A26: 7 | B26: Chi phí dịch vụ tư vấn pháp lý, dịch vụ báo giá và các dịch vụ hợp lý khác, thù lao trả cho ban đại diện quỹ/Giá trị tài sản ròng trung bình trong kỳ (%) Legal consultancy, price quotation and other appropriate service fees; remunerations paid to the Board of Representatives/Average NAV (%) | D26: 0.0004587958 | E26: 9.5289742e-05
A27: 8 | B27: Tỷ lệ chi phí /Giá trị tài sản ròng trung bình trong kỳ (%) Expense/Average NAV (%) | D27: 0.036965779 | E27: 0.039150289
A28: 9 | B28: Tốc độ vòng quay danh mục trong kỳ (%) = (Tổng giá trị mua vào + tổng giá trị bán ra) x 100%/ (2 x Giá trị tài sản ròng trung bình trong kỳ) Portfolio turnover rate (%) = (Total value of purchase transactions + total value of sales transactions) x 100%/ (2 x Average NAV) (**) | D28: 6.0501778 | E28: 6.4666664
A29: 10 | B29: Tỷ lệ thu nhập (tính cả thu nhập từ lãi, cổ tức, trái tức, chênh lệch giá)/ Giá trị tài sản ròng (không áp dụng) Income (including interest income, dividend, coupon income and unrealised gain)/ Average NAV (%) (not applicable)
A30: II | B30: CÁC CHỈ TIÊU KHÁC OTHER INDICATORS
A31: 1 | B31: Quy mô quỹ đầu kỳ (theo mệnh giá) Fund scale at the beginning of the period (based on par value) | D31: 257852775500 | E31: 252649777600
B32: Tổng giá trị chứng chỉ quỹ đang lưu hành đầu kỳ (theo mệnh giá) Total value of outstanding Fund Certificate at the beginning of period (based on par value) | D32: 257852775500 | E32: 252649777600
B33: Tổng số lượng chứng chỉ quỹ đang lưu hành đầu kỳ Total number of outstanding Fund Certificate at the beginning of period | D33: 25785278 | E33: 25264978
A34: 2 | B34: Thay đổi quy mô quỹ trong kỳ (theo mệnh giá) Change of Fund scale during the period (based on par value) | D34: -2226121100 | E34: 5202997900
B35: Thay đổi số lượng chứng chỉ quỹ trong kỳ Change of Number of Fund Certificates during the period | D35: -222612.11 | E35: 520299.79
B36: Thay đổi giá trị vốn trong kỳ (theo mệnh giá) Change in capital amount during the period (based on par value) | D36: -2226121100 | E36: 5202997900
B37: Số lượng chứng chỉ quỹ phát hành thêm trong kỳ Number of Fund Certificates subscribed during the period | D37: 415796.87 | E37: 827815.92
B38: Giá trị vốn huy động thêm trong kỳ (theo mệnh giá) Net subscription amount during the period (based on par value) | D38: 4157968700 | E38: 8278159200
B39: Số lượng chứng chỉ quỹ mua lại trong kỳ Number of Fund Certificates redeemed during the period | D39: -638408.98 | E39: -307516.13
B40: Giá trị vốn phải thanh toán trong kỳ khi đáp ứng lệnh của nhà đầu tư (theo mệnh giá) Net redemption amount during the period (based on par value) | D40: -6384089800 | E40: -3075161300
A41: 3 | B41: Quy mô quỹ cuối kỳ (theo mệnh giá) Fund scale at the end of the period (based on par value) | D41: 255626654400 | E41: 257852775500
B42: Tổng giá trị thị trường của quỹ đang lưu hành cuối kỳ (theo mệnh giá) Total value of outstanding Fund Certificate at the end of the period (based on par value) | D42: 255626654400 | E42: 257852775500
B43: Tổng số lượng chứng chỉ quỹ đang lưu hành cuối kỳ Total number of outstanding Fund Certificate at the end of the period | D43: 25562665 | E43: 25785278
A44: 4 | B44: Tỷ lệ nắm giữ chứng chỉ quỹ của công ty quản lý quỹ và người có liên quan cuối kỳ Fund Management Company and related parties' ownership ratio at the end of the period | D44: 0.0013524204 | E44: 0.0013064847
A45: 5 | B45: Tỷ lệ nắm giữ chứng chỉ quỹ của 10 nhà đầu tư lớn nhất cuối kỳ Top 10 investors' ownership ratio at the end of the period | D45: 0.2856 | E45: 0.2921
A46: 6 | B46: Tỷ lệ nắm giữ chứng chỉ quỹ của nhà đầu tư nước ngoài cuối kỳ Foreign investors' ownership ratio at the end of the period | D46: 0.1172 | E46: 0.1169
A47: 7 | B47: Giá trị tài sản ròng trên một đơn vị quỹ cuối kỳ Net asset value per Fund Certificate at the end of period | D47: 59813.78 | E47: 60564.74
A48: 8 | B48: Giá trị thị trường trên một chứng chỉ quỹ/cổ phiếu cuối kỳ (không áp dụng) Market price per fund certificates at the end of period (not applicable)
A49: 9 | B49: Số nhà đầu tư tham gia vào quỹ, kể cả giao dịch ký danh Number of investors of the Fund at the end of the period | D49: 18796 | E49: 18153
A50: Ghi chú / Notes:
A51: Các chỉ tiêu từ 1 đến 10 của "Chỉ tiêu về hiệu quả hoạt động" đã được điều chỉnh để phản ánh số liệu trên cơ sở hoạt động tròn năm bằng cách nhân các chỉ tiêu này với 12 (đối với báo cáo tháng), 4 (đối với báo cáo quý), 2 (đối với báo cáo bán niên), 1 (đối với báo cáo năm). All Indicator starting from number 1 to 10 of "Investment performance indicators" are annualized to reflect a rate that is based on a full year operation by multiplying these indicators with 12 (monthly report) or 4 (quarterly report) or 2 (semi-annual report) or 1 (annual report).
A52: (**) Không tính đến giá trị cam kết của các hợp đồng tương lai chỉ số. Excluding the committed value of the Index Futures contracts.
A54: Đại diện có thẩm quyền của Ngân hàng giám sát | D54: Đại diện có thẩm quyền của Công ty quản lý Quỹ
A55: Authorised Representative of Supervisory Bank | D55: Authorised Representative of Fund Management Company
A65: Ngân hàng TNHH MTV Standard Chartered (Việt Nam) | D65: Công ty Cổ phần Quản lý Quỹ Đầu tư Dragon Capital Việt Nam
A66: Trịnh Hoài Nam | D66: Nguyễn Minh Đăng Khánh
A67: Phó phòng Dịch vụ Quản trị và Giám sát Quỹ | D67: Giám đốc điều hành Nghiệp vụ hỗ trợ đầu tư
