Workbook
Name addlogo: INDEX(#REF!,MATCH(#REF!,#REF!,0))

Sheet TONGQUAN
A1: Kỳ báo cáo: | C1: Tại ngày 31 tháng 12 năm 2023 / As at 31 Dec 2023
C2: Năm 2023 / Year 2023
A4: Thông tin chung:
C5: Tên Công ty quản lý quỹ: | D5: Công ty Cổ phần Quản lý Quỹ Đầu tư Dragon Capital Việt Nam
C6: Fund Management Company: | D6: Dragon Capital Vietfund Management Joint Stock Company
C7: Tên ngân hàng giám sát: | D7: Ngân hàng TNHH Một thành viên Standard Chartered (Việt Nam)
C8: Supervising bank: | D8: Standard Chartered Bank (Vietnam) Limited
C9: Tên Quỹ: | D9: Quỹ Đầu tư Chứng khoán Năng động DC
C10: Fund name: | D10: DC Dynamic Securities Fund(DCDS)
C11: Ngày lập báo cáo: | D11: Ngày 08 tháng 03 năm 2024
C12: Reporting Date: | D12: 08 Mar 2024
A14: Người ký báo cáo:
C16: Đại diện có thẩm quyền của Ngân hàng giám sát | F16: Đại diện có thẩm quyền của Công ty quản lý Quỹ
C17: Authorised Representative of Supervisory Bank | F17: Authorised Representative of Fund Management Company
C19: Ngân hàng TNHH MTV Standard Chartered (Việt Nam) | F19: Công ty Cổ phần Quản lý Quỹ Đầu tư Dragon Capital Việt Nam
C20: Vũ Quang Phan | F20: Lê Hoàng Anh
C21: Phó phòng Dịch vụ nghiệp vụ Giám sát Quỹ | F21: Quyền Giám đốc nghiệp vụ hỗ trợ đầu tư

Sheet BCThuNhap_06104
A1: Mẫu số B01 - QM Báo cáo thu nhập Template B01 - QM Statement of Comprehensive Income
A2: (Ban hành kèm theo Thông tư 198/2012/TT-BTC ngày 15 tháng 11 năm 2012 về chế độ kế toán áp dụng đối với quỹ mở) (Issued in association with Circular 198/2012/TT-BTC dated 15 Nov 2012 on the Accounting Policies for Open-Ended Fund)
A3: BÁO CÁO THU NHẬP STATEMENT OF COMPREHENSIVE INCOME
A5: =TONGQUAN!C2 -> Năm 2023 / Year 2023
A7: Tên Công ty quản lý quỹ: | B7: =TONGQUAN!D5 -> Công ty Cổ phần Quản lý Quỹ Đầu tư Dragon Capital Việt Nam
A8: Fund Management Company: | B8: =TONGQUAN!D6 -> Dragon Capital Vietfund Management Joint Stock Company
A9: Tên ngân hàng giám sát: | B9: =TONGQUAN!D7 -> Ngân hàng TNHH Một thành viên Standard Chartered (Việt Nam)
A10: Supervising bank: | B10: =TONGQUAN!D8 -> Standard Chartered Bank (Vietnam) Limited
A11: Tên Quỹ: | B11: =TONGQUAN!D9 -> Quỹ Đầu tư Chứng khoán Năng động DC
A12: Fund name: | B12: =TONGQUAN!D10 -> DC Dynamic Securities Fund(DCDS)
A13: Ngày lập báo cáo: | B13: =TONGQUAN!D11 -> Ngày 08 tháng 03 năm 2024
A14: Reporting Date: | B14: =TONGQUAN!D12 -> 08 Mar 2024
A16: Chỉ tiêu Indicator | B16: Mã số Code | C16: Thuyết minh Note | D16: Năm 2023 Year 2023 | E16: Năm 2022 Year 2022
A18: I. THU NHẬP, DOANH THU HOẠT ĐỘNG ĐẦU TƯ Investment income | B18: 01 | D18: 372465575175 | E18: -613132069233
A19: 1.1. Cổ tức được chia Dividend income | B19: 02 | D19: 21446287000 | E19: 17365202500
A20: 1.2. Tiền lãi được nhận Interest income | B20: 03 | D20: 5741875933 | E20: 17530222986
A21: Lãi tiền gửi ngân hàng Interest income from bank deposits | B21: 03.1 | D21: 252478465 | E21: 1192606383
A22: Lãi công cụ thị trường tiền tệ Interest income from Money market instruments | B22: 03.2 | D22: 0 | E22: 835328767
A23: Lãi trái phiếu Interest income from bonds | B23: 03.3 | D23: 5489397468 | E23: 15502287836
A24: Tiền lãi hợp đồng mua lại đảo ngược được nhận Reverse repo contract interest received | B24: 03.4 | D24: 0 | E24: 0
A25: 1.3. Lãi (lỗ) bán các khoản đầu tư Realized gain (losses) from disposal investments | B25: 04 | D25: 202459819566 | E25: -449654427803
A26: 1.4. Chênh lệch tăng, giảm đánh giá lại các khoản đầu tư chưa thực hiện Unrealized gain (losses) from investment revaluation | B26: 05 | D26: 142817592676 | E26: -198373066916
A27: 1.5. Doanh thu khác Other income | B27: 06 | D27: 0 | E27: 0
A28: 1.6. Chênh lệch lãi, lỗ tỷ giá hối đoái đã và chưa thực hiện Realized and unrealized gain (losses) from foreign exchange | B28: 07 | D28: 0 | E28: 0
A29: 1.7. Doanh thu khác về đầu tư Other investment income | B29: 08 | D29: 0 | E29: 0
... A77: VIII. LỢI NHUẬN KẾ TOÁN SAU THUẾ TNDN PROFIT AFTER TAX (41=30-40) | B77: 41 | D77: 326760799108 | E77: -665811825559
A80: Người lập: | B80: Người duyệt:
A90: _________________________________ | B90: _________________________________ | E90: ________________________
A91: Nguyễn Thu Ngọc | B91: Ninh Thị Tuệ Minh | E91: Lê Hoàng Anh
A92: Kế toán Quỹ | B92: Trưởng phòng Kế toán Quỹ | E92: Quyền Giám đốc nghiệp vụ hỗ trợ đầu tư

Sheet BCTinhHinhTaiChinh_06105
A1: Mẫu số B02 - QM. Báo cáo tình hình tài chính Template B02 - QM. Statement of Financial Position
A2: (Ban hành kèm theo Thông tư 198/2012/TT-BTC ngày 15 tháng 11 năm 2012 về chế độ kế toán áp dụng đối với quỹ mở) (Issued in association with Circular 198/2012/TT-BTC dated 15 Nov 2012 on the Accounting Policies for Open-Ended Fund)
A3: BÁO CÁO TÌNH HÌNH TÀI CHÍNH STATEMENT OF FINANCIAL POSITION
A5: =TONGQUAN!C1 -> Tại ngày 31 tháng 12 năm 2023 / As at 31 Dec 2023
A7: Tên Công ty quản lý quỹ: | C7: =TONGQUAN!D5 -> Công ty Cổ phần Quản lý Quỹ Đầu tư Dragon Capital Việt Nam
A8: Fund Management Company: | C8: =TONGQUAN!D6 -> Dragon Capital Vietfund Management Joint Stock Company
A9: Tên ngân hàng giám sát: | C9: =TONGQUAN!D7 -> Ngân hàng TNHH Một thành viên Standard Chartered (Việt Nam)
A10: Supervising bank: | C10: =TONGQUAN!D8 -> Standard Chartered Bank (Vietnam) Limited
A11: Tên Quỹ: | C11: =TONGQUAN!D9 -> Quỹ Đầu tư Chứng khoán Năng động DC
A12: Fund name: | C12: =TONGQUAN!D10 -> DC Dynamic Securities Fund(DCDS)
A13: Ngày lập báo cáo: | C13: =TONGQUAN!D11 -> Ngày 08 tháng 03 năm 2024
A14: Reporting Date: | C14: =TONGQUAN!D12 -> 08 Mar 2024
A16: STT No. | B16: Chỉ tiêu Indicator | C16: Mã số Code | D16: Thuyết minh Note | E16: =BCTaiSan_06027!D18 -> Ngày 31 tháng 12 năm 2023 As at 31 Dec 2023 | F16: =BCTaiSan_06027!E18 -> Ngày 31 tháng 12 năm 2022 As at 31 Dec 2022
A17: I | B17: I. TÀI SẢN ASSETS | C17: I
A18: 1 | B18: 1.Tiền gửi ngân hàng và tương đương tiền Cash at bank and cash equivalent | C18: 110 | E18: 59838686129 | F18: 75921669347
A19: 1.1 | B19: 1.1. Tiền gửi ngân hàng Cash at bank | C19: 111 | E19: 59838686129 | F19: 75921669347
B20: Tiền gửi của nhà đầu tư cho hoạt động mua chứng chỉ quỹ Cash at bank for Fund's subscription | C20: 111.1 | E20: 1448301386 | F20: 747083745
B21: Tiền phải trả cho Nhà đầu tư về mua lại Chứng chỉ quỹ Cash at bank for Fund's redemption | C21: 111.2 | E21: 136051360 | F21: 128376390
B22: Tiền gửi ngân hàng cho hoạt động của Quỹ Cash at bank for Fund's operation | C22: 111.3 | E22: 58254333383 | F22: 75046209212
B23: Tiền gửi ký quỹ cho hoạt động đầu tư chứng khoán phái sinh Margin account for trading derivatives | C23: 111.4 | E23: 0 | F23: 0
A24: 1.2 | B24: 1.2. Tiền gửi có kỳ hạn dưới ba (03) tháng Deposit with term less than three (03) months | C24: 112 | E24: 0 | F24: 0
A25: 2 | B25: 2. Các khoản đầu tư thuần Net Investments | C25: 120 | E25: 1469077080000 | F25: 1210013434960
A26: 2.1 | B26: 2.1. Các khoản đầu tư Investments | C26: 121 | E26: 1469077080000 | F26: 1210013434960
B27: Cổ phiếu, chứng chỉ quỹ niêm yết Listed Shares, fund certificates | C27: 121.1 | E27: 1451817016000 | F27: 1049565668100
B28: Cổ phiếu, chứng chỉ quỹ chưa niêm yết Unlisted Shares, fund certifictes | C28: 121.2 | E28: 0 | F28: 0
B29: Trái phiếu niêm yết Listed Bonds | C29: 121.3 | E29: 0 | F29: 49408300000
B30: Trái phiếu chưa niêm yết Unlisted Bonds | C30: 121.4 | E30: 15155514000 | F30: 111039466860
B31: Công cụ thị trường tiền tệ Money market instruments | C31: 121.5 | E31: 0 | F31: 0
B32: Hợp đồng tiền gửi có kỳ hạn trên ba (03) tháng Deposits with term over three (03) months | C32: 121.6 | E32: 0 | F32: 0
B33: Quyền mua chứng khoán Investment - Rights | C33: 121.7 | E33: 2104550000 | F33: 0
B34: Hợp đồng tương lai chỉ số Index future contracts | C34: 121.8 | E34: 0 | F34: 0
B35: Đầu tư khác Other Investments | C35: 121.9 | E35: 0 | F35: 0
B36: Hợp đồng mua lại đảo ngược Reverse repo contracts | C36: 121.10 | E36: 0 | F36: 0
A37: 2.2 | B37: 2.2. Dự phòng giảm giá tài sản nhận thế chấp Impairment of devaluation of pledged assets | C37: 122 | E37: 0 | F37: 0
A38: 3 | B38: 3. Các khoản phải thu Receivables | C38: 130 | E38: 30655997123 | F38: 42108315411
A39: 3.1 | B39: 3.1 Phải thu về bán các khoản đầu tư Receivables from investments sold but not yet settled | C39: 131 | E39: 28573030000 | F39: 36621925000
B40: Trong đó: Phải thu khó đòi về bán các khoản đầu tư In which: Overdue receivables from selling investments | C40: 132 | E40: 0 | F40: 0
A41: 3.2 | B41: 3.2. Phải thu và dự thu cổ tức, tiền lãi các khoản đầu tư Dividend and interest receivables | C41: 133 | E41: 2949367123 | F41: 6352790411
A42: 3.2.1 | B42: 3.2.1. Phải thu cổ tức, tiền lãi đến ngày nhận Dividend and interest receivables on or after payment date | C42: 134 | E42: 866400000 | F42: 866400000
B43: Phải thu cổ tức Dividend receivables | C43: 134.1 | E43: 866400000 | F43: 866400000
B44: Phải thu trái tức Coupon receivables | C44: 134.2 | E44: 0 | F44: 0
B45: Phải thu lãi tiền gửi có kỳ hạn dưới 3 tháng Interest receivables from deposit with term less than three (03) months | C45: 134.3 | E45: 0 | F45: 0
B46: Phải thu lãi tiền gửi có kỳ hạn trên 3 tháng Interest receivables from deposit with term more than three (03) months | C46: 134.4 | E46: 0 | F46: 0
B47: Phải thu lãi công cụ thị trường tiền tệ Interest receivables from Money market instruments | C47: 134.5 | E47: 0 | F47: 0
B48: Trong đó: Phải thu khó đòi về cổ tức, tiền lãi đến ngày nhận nhưng chưa nhận được In which: Overdue receivables from dividend, interest income | C48: 135 | E48: 866400000 | F48: 866400000
A49: 3.2.2 | B49: 3.2.2.Dự thu cổ tức, tiền lãi chưa đến ngày nhận Dividend and interest receivables before payment date | C49: 136 | E49: 2082967123 | F49: 5486390411
B50: Dự thu cổ tức Dividend receivables | C50: 136.1 | E50: 1994200000 | F50: 2830500000
B51: Dự thu lãi trái phiếu Interest accrual from bonds | C51: 136.2 | E51: 88767123 | F51: 2655890411
B52: Dự thu lãi tiền gửi có kỳ hạn dưới 3 tháng Interest accrual from deposits with term less than three (03) months | C52: 136.3 | E52: 0 | F52: 0
B53: Dự thu lãi tiền gửi có kỳ hạn trên 3 tháng Interest accrual from deposit with term more than three (03) months | C53: 136.4 | E53: 0 | F53: 0
B54: Dự thu lãi công cụ thị trường tiền tệ Interest accrual from Money market instruments | C54: 136.5 | E54: 0 | F54: 0
B55: Dự thu lãi hợp đồng mua lại đảo ngược Interest receivables from reverse repo contracts | C55: 136.6 | E55: 0 | F55: 0
A56: 3.3 | B56: 3.3. Các khoản phải thu khác Other receivables | C56: 137 | E56: 0 | F56: 0
B57: Phải thu cho khoản cổ phiếu hạn chế chờ mua Receivable from AP/Investors on securities on hold of buying | C57: 137.1 | E57: 0 | F57: 0
B58: Các tài sản khác Other assets | C58: 137.2 | E58: 0 | F58: 0
B59: Các khoản khác Others | C59: 137.3 | E59: 0 | F59: 0
A60: 3.4 | B60: 3.4. Dự phòng nợ phải thu khó đòi Provision for doubtful debt | C60: 138 | E60: -866400000 | F60: -866400000
B61: TỔNG TÀI SẢN TOTAL ASSETS | C61: 100 | E61: 1559571763252 | F61: 1328043419718
A62: II | B62: II. NỢ PHẢI TRẢ TOTAL LIABILITIES | C62: II
A63: 1 | B63: 1. Vay ngắn hạn Short-term loans | C63: 311 | E63: 0 | F63: 0
B64: Gốc hợp đồng repo Repo contracts - Principal | C64: 311.1 | E64: 0 | F64: 0
B65: Vay ngắn hạn Short-term loans | C65: 311.2 | E65: 0 | F65: 0
A66: 2 | B66: 2. Phải trả về mua các khoản đầu tư Payables for securities bought but not yet settled | C66: 312 | E66: 43686305000 | F66: 52333345000
A67: 3 | B67: 3. Phải trả phí cho các Đại lý phân phối, Công ty quản lý quỹ về mua bán Chứng chỉ quỹ Subscription and Redemption fee payable to distributors and fund management company | C67: 313 | E67: 210829151 | F67: 309689895
B68: Phải trả phí cho các Đại lý phân phối về mua bán Chứng chỉ quỹ Subscription and Redemption fee payable to distributors | C68: 313.1 | E68: 6835448 | F68: 6835448
B69: Phải trả phí cho Công ty quản lý quỹ về mua bán Chứng chỉ quỹ Subscription and Redemption fee payable to fund management company | C69: 313.2 | E69: 203993703 | F69: 302854447
A70: 4 | B70: 4. Thuế và các khoản phải nộp Nhà nước Tax payables and obligations to the State Budget | C70: 314 | E70: 24333177 | F70: 9310080
A71: 5 | B71: 5.Phải trả thu nhập cho Nhà đầu tư Profit distribution payables | C71: 315 | E71: 39925000 | F71: 39925000
A72: 6 | B72: 6. Chi phí phải trả Expense Accruals | C72: 316 | E72: 260004523 | F72: 371568430
B73: Phí giao dịch Transaction fee | C73: 316.1 | E73: 133524523 | F73: 158568430
B74: Phải trả phí môi giới Brokerage fee payables | C74: 316.1.1 | E74: 133524523 | F74: 158568430
B75: Phải trả phí giao dịch thanh toán bù trừ chứng khoán Clearing Settlement Fee payables | C75: 316.1.2 | E75: 0 | F75: 0
B76: Trích trước phí kiểm toán Accrued expense for audit fee | C76: 316.2 | E76: 102480000 | F76: 189000000
B77: Trích trước phí họp đại hội thường niên Accrued expense for Annual General meeting | C77: 316.3 | E77: 0 | F77: 0
B78: Trích trước phí báo cáo thường niên Accrued expense for Annual report | C78: 316.4 | E78: 0 | F78: 0
B79: Trích trước thù lao ban đại diện quỹ Accrued expense for Remuneration Payable to Fund's Board of Representatives | C79: 316.5 | E79: 24000000 | F79: 24000000
B80: Trích trước phí quản lý niêm yết hàng năm tại SGDCK Accrued expense for annual listing fee at HOSE | C80: 316.6 | E80: 0 | F80: 0
B81: Trích trước lãi vay ngắn hạn của hợp đồng vay và hợp đồng repo Accrued Interest Expense of short-term loan contracts and repo contracts | C81: 316.7 | E81: 0 | F81: 0
A82: 7 | B82: 7. Phải trả cho Nhà đầu tư về mua Chứng chỉ quỹ Subscription payables to investors | C82: 317 | E82: 1448301386 | F82: 747083745
B83: Phải trả cho nhà đầu tư chờ mua chứng chỉ quỹ Subscription Pending allotment | C83: 317.1 | E83: 1448301386 | F83: 747083745
B84: Phải trả nhà đầu tư trên tài sản giữ hộ Payables to investors for investment bought on behalf | C84: 317.2 | E84: 0 | F84: 0
A85: 8 | B85: 8. Phải trả cho Nhà đầu tư về mua lại Chứng chỉ quỹ Redemption payables to investors | C85: 318 | E85: 4628656017 | F85: 10348162724
A86: 9 | B86: 9. Phải trả dịch vụ quản lý Quỹ mở Fund management related service expense payable | C86: 319 | E86: 2656313886 | F86: 2350637319
B87: Trích trước phải trả phí quản lý Accrued expense for Management fee | C87: 319.1 | E87: 2448036416 | F87: 2150379709
B88: Trích trước phí lưu ký tài sản Quỹ mở Accrued expense for Custodian fee | C88: 319.2 | E88: 105316133 | F88: 108210352
B89: Phí dịch vụ lưu ký - bảo quản tài sản Custodian service - Safe Custody Fee | C89: 319.2.1 | E89: 50216133 | F89: 44110352
B90: Phí dịch vụ lưu ký - giao dịch chứng khoán Custodian service - Transaction fee | C90: 319.2.2 | E90: 44100000 | F90: 64100000
B91: Phí dịch vụ lưu ký cho chứng khoán cơ sở, phí quản lý vị thế và tài sản phái sinh trả cho VSDC Custodian service - Depository fee, Position and Margin management fee paid to VSDC | C91: 319.2.3 | E91: 11000000 | F91: 0
B92: Trích trước phí quản trị quỹ Accrued expense for Fund administration fee | C92: 319.3 | E92: 34523592 | F92: 30325868
B93: Trích trước phí giám sát Accrued expense for Supervising fee | C93: 319.4 | E93: 55237745 | F93: 48521390
B94: Trích trước phí dịch vụ đại lý chuyển nhượng Accrued expense for Tranfer agency fee | C94: 319.5 | E94: 13200000 | F94: 13200000
B95: Dự chi phí cung cấp dịch vụ tính giá trị tài sản ròng tham chiếu (iNAV) cho HOSE Accrued expense for payable to HOSE for iNAV calculation | C95: 319.6 | E95: 0 | F95: 0
B96: Dự chi phí cấp quyền sử dụng chỉ số cho HOSE Accrued expense for payable to HOSE for Index usage | C96: 319.7 | E96: 0 | F96: 0
A97: 10 | B97: 10. Phải trả, phải nộp khác Other payables | C97: 320 | E97: 207174216 | F97: 227852829
B98: Phải trả phí báo giá Price feed fee payable | C98: 320.1 | E98: 23500000 | F98: 0
B99: Trích trước phí công tác, họp của ban đại diện Accrued expense for Fund's Board of Representatives travelling, meeting | C99: 320.2 | E99: 0 | F99: 0
B100: Trích trước phí quản lý thường niên trả cho UBCKNN Accrued expense for Annual Fee paid to SSC | C100: 320.3 | E100: 0 | F100: 0
B101: Phí Ngân hàng S2B S2B Bank charge | C101: 320.4 | E101: 7191250 | F101: 0
B102: Phải trả khác Other payables | C102: 320.5 | E102: 176482966 | F102: 227852829
B103: TỔNG NỢ PHẢI TRẢ TOTAL LIABILITIES | C103: 300 | E103: 53161842356 | F103: 66737575022
...

Sheet GTTSRong_06107
A1: Mẫu số B03 - QM. Mẫu báo cáo thay đổi giá trị tài sản ròng, giao dịch chứng chỉ quỹ Template B03 - QM. Report on change of Net Asset Value, trading of Fund Certificate
A2: (Ban hành kèm theo Thông tư 198/2012/TT-BTC ngày 15 tháng 11 năm 2012 về chế độ kế toán áp dụng đối với quỹ mở) (Issued in association with Circular 198/2012/TT-BTC dated 15 Nov 2012 on the Accounting Policies for Open-Ended Fund)
A3: BÁO CÁO THAY ĐỔI GIÁ TRỊ TÀI SẢN RÒNG, GIAO DỊCH CHỨNG CHỈ QUỸ REPORT ON CHANGE OF NET ASSET VALUE, TRADING OF FUND CERTIFICATE
A5: =TONGQUAN!C2 -> Năm 2023 / Year 2023
A7: Tên Công ty quản lý quỹ: | D7: =TONGQUAN!D5 -> Công ty Cổ phần Quản lý Quỹ Đầu tư Dragon Capital Việt Nam
A8: Fund Management Company: | D8: =TONGQUAN!D6 -> Dragon Capital Vietfund Management Joint Stock Company
A9: Tên ngân hàng giám sát: | D9: =TONGQUAN!D7 -> Ngân hàng TNHH Một thành viên Standard Chartered (Việt Nam)
A10: Supervising bank: | D10: =TONGQUAN!D8 -> Standard Chartered Bank (Vietnam) Limited
A11: Tên Quỹ: | D11: =TONGQUAN!D9 -> Quỹ Đầu tư Chứng khoán Năng động DC
A12: Fund name: | D12: =TONGQUAN!D10 -> DC Dynamic Securities Fund(DCDS)
A13: Ngày lập báo cáo: | D13: =TONGQUAN!D11 -> Ngày 08 tháng 03 năm 2024
A14: Reporting Date: | D14: =TONGQUAN!D12 -> 08 Mar 2024
A18: STT No | C18: Nội dung Item | D18: Mã số Code | E18: =BCKetQuaHoatDong_06028!D18 -> Năm 2023 Year 2023 | F18: =BCKetQuaHoatDong_06028!E18 -> Năm 2022 Year 2022
A19: I | C19: I. Giá trị tài sản ròng của Quỹ mở (NAV) đầu kỳ Net Asset Value (NAV) at the beginning of period | D19: 4060 | E19: 1261305844696 | F19: 1641867480749
A20: II | C20: II. Thay đổi NAV so với kỳ trước (= II.1 + II.2), trong đó: Change of NAV during the period (= II.1 + II.2), of which: | D20: 4061 | E20: 326760799108 | F20: -665811825559
B21: II.1 | C21: II.1 Thay đổi NAV do biến động thị trường và hoạt động giao dịch của Quỹ mở trong kỳ Changes of NAV due to market fluctuation and the fund's investment during the period | D21: 4062 | E21: 326760799108 | F21: -665811825559
B22: II.2 | C22: II.2 Thay đổi NAV do phân chia Lợi nhuận/Tài sản của Quỹ mở cho Nhà đầu tư trong kỳ Change of NAV due to profit/asset distribution to investors during the period | D22: 4063 | E22: 0 | F22: 0
A23: III | C23: III. Thay đổi NAV do mua lại, phát hành thêm Chứng chỉ quỹ (= III.1 + III.2) Change of NAV due to redemption, subscription of Fund Certificate (= III.1 + III.2) | D23: 4064 | E23: -81656722908 | F23: 285250189506
B24: III.1 | C24: III.1 Khoản thu từ việc phát hành bổ sung Chứng chỉ quỹ Increase from Subscription of Fund Certificate | D24: 4065 | E24: 263340163689 | F24: 734385200678
B25: III.2 | C25: III.2 Khoản thanh toán từ việc mua lại Chứng chỉ quỹ Decrease from Redemption of Fund Certificate | D25: 4066 | E25: -344996886597 | F25: -449135011172
A26: IV | C26: IV. Giá trị tài sản ròng của Quỹ mở cuối kỳ (= I + II + III) NAV at the end of period (= I + II + III) | D26: 4067 | E26: 1506409920896 | F26: 1261305844696
A27: V | C27: V. Giá trị tài sản ròng trên một đơn vị quỹ cuối kỳ NAV per unit at the end of period | D27: 4067.1 | E27: 65722.27 | F27: 51531.77
A30: Người lập: | D30: Người duyệt:
A39: ____________________________________ | D39: _____________________________ | F39: ________________________
A40: Nguyễn Thu Ngọc | D40: Ninh Thị Tuệ Minh | F40: Lê Hoàng Anh
A41: Kế toán Quỹ | D41: Trưởng phòng Kế toán Quỹ | F41: Quyền Giám đốc nghiệp vụ hỗ trợ đầu tư

Sheet BCDMDT_06108
A1: Mẫu số B04 - QM. Mẫu báo cáo danh mục đầu tư Template B04 - QM. Statement of investment portfolio
A2: (Ban hành kèm theo Thông tư 198/2012/TT-BTC ngày 15 tháng 11 năm 2012 về chế độ kế toán áp dụng đối với quỹ mở) (Issued in association with Circular 198/2012/TT-BTC dated 15 Nov 2012 on the Accounting Policies for Open-Ended Fund)
A3: BÁO CÁO DANH MỤC ĐẦU TƯ CỦA QUỸ STATEMENT OF INVESTMENT PORTFOLIO
A4: =TONGQUAN!C1 -> Tại ngày 31 tháng 12 năm 2023 / As at 31 Dec 2023
A6: Tên Công ty quản lý quỹ: | C6: =TONGQUAN!D5 -> Công ty Cổ phần Quản lý Quỹ Đầu tư Dragon Capital Việt Nam
A7: Fund Management Company: | C7: =TONGQUAN!D6 -> Dragon Capital Vietfund Management Joint Stock Company
A8: Tên ngân hàng giám sát: | C8: =TONGQUAN!D7 -> Ngân hàng TNHH Một thành viên Standard Chartered (Việt Nam)
A9: Supervising bank: | C9: =TONGQUAN!D8 -> Standard Chartered Bank (Vietnam) Limited
A10: Tên Quỹ: | C10: =TONGQUAN!D9 -> Quỹ Đầu tư Chứng khoán Năng động DC
A11: Fund name: | C11: =TONGQUAN!D10 -> DC Dynamic Securities Fund(DCDS)
A12: Ngày lập báo cáo: | C12: =TONGQUAN!D11 -> Ngày 08 tháng 03 năm 2024
A13: Reporting Date: | C13: =TONGQUAN!D12 -> 08 Mar 2024
A16: STT/No. | B16: Loại Category | C16: Mã chỉ tiêu Code | D16: Số Lượng Quantity | E16: Giá thị trường hoặc giá trị hợp lý tại ngày báo cáo Market price | F16: Tổng giá trị (Đồng) Value (VND) | G16: Tỷ lệ % Tổng giá trị tài sản của Quỹ % of total asset
A17: I | B17: CỔ PHIẾU NIÊM YẾT, ĐĂNG KÝ GIAO DỊCH, CHỨNG CHỈ QUỸ NIÊM YẾT SHARES LISTED, SHARES REGISTERED FOR TRADING, LISTED FUND CERTIFICATES | C17: 4030
A18: ... | B18: ... | C18: ... | D18: ... | E18: ... | F18: ... | G18: ...
A19: 1 | B19: BID | C19: 4030.1 | D19: 115738 | E19: 43400 | F19: 5023029200 | G19: 0.0032
A20: 2 | B20: BSI | C20: 4030.2 | D20: 48800 | E20: 47500 | F20: 2318000000 | G20: 0.0015
A21: 3 | B21: CTD | C21: 4030.3 | D21: 536800 | E21: 68800 | F21: 36931840000 | G21: 0.0237
A22: 4 | B22: CTG | C22: 4030.4 | D22: 526026 | E22: 27100 | F22: 14255304600 | G22: 0.0091
A23: 5 | B23: DCM | C23: 4030.5 | D23: 798000 | E23: 32400 | F23: 25855200000 | G23: 0.0166
A24: 6 | B24: DGC | C24: 4030.6 | D24: 716800 | E24: 94400 | F24: 67665920000 | G24: 0.0434
A25: 7 | B25: DGW | C25: 4030.7 | D25: 726800 | E25: 52300 | F25: 38011640000 | G25: 0.0244
A26: 8 | B26: DHC | C26: 4030.8 | D26: 117000 | E26: 38000 | F26: 4446000000 | G26: 0.0029
A27: 9 | B27: DIG | C27: 4030.9 | D27: 656800 | E27: 26750 | F27: 17569400000 | G27: 0.0113
A28: 10 | B28: DPG | C28: 4030.10 | D28: 576800 | E28: 39650 | F28: 22870120000 | G28: 0.0147
A29: 11 | B29: DRC | C29: 4030.11 | D29: 281600 | E29: 26500 | F29: 7462400000 | G29: 0.0048
A30: 12 | B30: DXG | C30: 4030.12 | D30: 1511000 | E30: 19350 | F30: 29237850000 | G30: 0.0187
... A73: 55 | B73: VTP | C73: 4030.55 | D73: 572568 | E73: 56900 | F73: 32579119200 | G73: 0.0209
B74: TỔNG TOTAL | C74: 4031 | F74: 1451817016000 | G74: 0.931
A75: II | B75: CỔ PHIẾU CHƯA NIÊM YẾT, ĐĂNG KÝ GIAO DỊCH, CHỨNG CHỈ QUỸ KHÔNG NIÊM YẾT SHARES UNLISTED, UNREGISTERED FOR TRADING, UNLISTED FUND CERTIFICATES | C75: 4032
B76: TỔNG TOTAL | C76: 4033 | F76: 0
B77: TỔNG CÁC LOẠI CỔ PHIẾU, CHỨNG CHỈ QUỸ TOTAL SHARES, FUND CERTIFICATES | C77: 4034 | F77: 1451817016000 | G77: 0.931
A78: III | B78: TRÁI PHIẾU BONDS | C78: 4035
A79: ... | B79: ... | C79: ... | D79: ... | E79: ... | F79: ...
A80: 1 | B80: Trái phiếu niêm yết Listed bonds | C80: 4035.1 | F80: 0
A81: 2 | B81: Trái phiếu không niêm yết Unlisted bonds | C81: 4035.2 | F81: 15155514000 | G81: 0.0097
A82: 2.1 | B82: KDH12101 | C82: 4035.2.1 | D82: 15 | E82: 1010367600 | F82: 15155514000 | G82: 0.0097
B83: TỔNG TOTAL | C83: 4036 | F83: 15155514000 | G83: 0.0097
A84: IV | B84: CÁC LOẠI CHỨNG KHOÁN KHÁC OTHER SECURITIES | C84: 4037
A85: ... | B85: ... | C85: ... | D85: ... | E85: ... | F85: ...
A86: 1 | B86: Quyền mua Rights | C86: 4037.1 | F86: 2104550000 | G86: 0.0013
A87: 1.1 | B87: DAT XANH GROUP JSC -RIGHTS | C87: 4037.1.1 | D87: 1718000 | E87: 1225 | F87: 2104550000 | G87: 0.0013
A88: 2 | B88: Chi tiết loại hợp đồng phái sinh(*) Index future contracts | C88: 4037.2 | F88: 0 | G88: 0
B89: TỔNG TOTAL | C89: 4038 | F89: 2104550000 | G89: 0.0013
B90: TỔNG CÁC LOẠI CHỨNG KHOÁN TOTAL TYPES OF SECURITIES | C90: 4039 | F90: 1469077080000
A91: V | B91: CÁC TÀI SẢN KHÁC OTHER ASSETS | C91: 4040
A92: ... | B92: ... | C92: ... | D92: ... | E92: ... | F92: ...
A93: 1 | B93: Cổ tức được nhận Dividend receivables | C93: 4040.1 | F93: 2860600000 | G93: 0.0018
A94: 2 | B94: Lãi trái phiếu được nhận Coupon receivables | C94: 4040.2 | F94: 88767123 | G94: 0.0001
A95: 3 | B95: Lãi tiền gửi và chứng chỉ tiền gửi được nhận Interest receivables from bank deposits and certificates of deposit | C95: 4040.3 | F95: 0 | G95: 0
A96: 4 | B96: Tiền bán chứng khoán chờ thu Outstanding Settlement of sales transactions | C96: 4040.4 | F96: 28573030000 | G96: 0.0183
A97: 5 | B97: Phải thu cho khoản cổ phiếu hạn chế chờ mua Receivable from AP/Investors on securities on hold of buying | C97: 4040.5 | F97: 0 | G97: 0
A98: 6 | B98: Phải thu khác Other receivables | C98: 4040.6 | F98: -866400000 | G98: -0.0006
A99: 7 | B99: Tài sản khác Other assets | C99: 4040.7 | F99: 0 | G99: 0
B100: TỔNG TOTAL | C100: 4041 | F100: 30655997123 | G100: 0.0196
A101: VI | B101: TIỀN CASH | C101: 4042
A102: 1 | B102: Tiền gửi Ngân hàng Cash at bank | C102: 4043 | F102: 59838686129 | G102: 0.0384
A103: ... | B103: ... | C103: ... | D103: ... | E103: ... | F103: ...
A104: 1.1 | B104: Tiền gửi ngân hàng Cash at Bank | C104: 4043.1 | F104: 59838686129 | G104: 0.0384
A105: 1.2 | B105: Các khoản tương đương tiền Cash Equivalents | C105: 4043.2 | F105: 0 | G105: 0
A106: 1.3 | B106: Tiền gửi có kỳ hạn trên 3 tháng Deposits with term over three (03) months | C106: 4043.3 | F106: 0 | G106: 0
A107: 2 | B107: Công cụ thị trường tiền tệ Money market instruments | C107: 4044 | F107: 0 | G107: 0
A108: ... | B108: ... | C108: ... | D108: ... | E108: ... | F108: ...
A109: 3 | B109: Công cụ chuyển nhượng… Transferable instruments… | C109: 4045 | F109: 0 | G109: 0
A110: ... | B110: ... | C110: ... | D110: ... | E110: ... | F110: ...
B111: TỔNG TOTAL | C111: 4046 | F111: 59838686129 | G111: 0.0384
A112: VII | B112: Tổng giá trị danh mục Total value of portfolio | C112: 4047 | F112: 1559571763252 | G112: 1
B114: Người lập: | C114: Người duyệt:
B126: __________________________________ | C126: ______________________________________ | F126: _____________________________
B127: Nguyễn Thu Ngọc | C127: Ninh Thị Tuệ Minh | F127: Lê Hoàng Anh
B128: Kế toán Quỹ | C128: Trưởng phòng Kế toán Quỹ | F128: Quyền Giám đốc nghiệp vụ hỗ trợ đầu tư

Sheet BCLCGT_06262
A1: Mẫu số B05 - QM. Báo cáo lưu chuyển tiền tệ Template B05 - QM. Cash flow statement
A2: (Ban hành kèm theo Thông tư 198/2012/TT-BTC ngày 15 tháng 11 năm 2012 về chế độ kế toán áp dụng đối với quỹ mở) (Issued in association with Circular 198/2012/TT-BTC dated 15 Nov 2012 on the Accounting Policies for Open-Ended Fund)
A3: BÁO CÁO LƯU CHUYỂN TIỀN TỆ CASH FLOW STATEMENT
A4: =TONGQUAN!C2 -> Năm 2023 / Year 2023
A7: Tên Công ty quản lý quỹ: | B7: =TONGQUAN!D5 -> Công ty Cổ phần Quản lý Quỹ Đầu tư Dragon Capital Việt Nam
A8: Fund Management Company: | B8: =TONGQUAN!D6 -> Dragon Capital Vietfund Management Joint Stock Company
A9: Tên ngân hàng giám sát: | B9: =TONGQUAN!D7 -> Ngân hàng TNHH Một thành viên Standard Chartered (Việt Nam)
A10: Supervising bank: | B10: =TONGQUAN!D8 -> Standard Chartered Bank (Vietnam) Limited
A11: Tên Quỹ: | B11: =TONGQUAN!D9 -> Quỹ Đầu tư Chứng khoán Năng động DC
A12: Fund name: | B12: =TONGQUAN!D10 -> DC Dynamic Securities Fund(DCDS)
A13: Ngày lập báo cáo: | B13: =TONGQUAN!D11 -> Ngày 08 tháng 03 năm 2024
A14: Reporting Date: | B14: =TONGQUAN!D12 -> 08 Mar 2024
A17: Chỉ tiêu Indicator | B17: Mã số Code | C17: Thuyết minh Note | D17: =BCKetQuaHoatDong_06028!D18 -> Năm 2023 Year 2023 | E17: =BCKetQuaHoatDong_06028!E18 -> Năm 2022 Year 2022
A18: I. Lưu chuyển tiền từ hoạt động đầu tư Cash flow from investing activities | B18: I
A19: 1. Lợi nhuận trước Thuế thu nhập doanh nghiệp Profit before income tax | B19: 01 | D19: 326760799108 | E19: -665811825559
A20: 2. Điều chỉnh cho các khoản tăng giá trị tài sản ròng từ các hoạt động đầu tư Adjustment for NAV increase from investing activities | B20: 02 | D20: -142880612676 | E20: 198358491916
A21: (- Lãi) hoặc (+ lỗ) chênh lệch tỷ giá hối đoái/ đánh giá lại các khoản đầu tư chưa thực hiện Unreliased (Gain) or Loss from FX valuation/Investment revaluation | B21: 03 | D21: -142817592676 | E21: 198373066916
A22: (+) Chi phí trích trước Increase of Accrued Expenses | B22: 04 | D22: -63020000 | E22: -14575000
A23: 3. Lợi nhuận từ hoạt động đầu tư trước thay đổi vốn lưu động Profit from investing activities before changes in working capital | B23: 05 | D23: 183880186432 | E23: -467453333643
A24: (-) Tăng, (+) giảm đầu tư (Increase), Decrease Investments | B24: 20 | D24: -116246052364 | E24: 62423110024
A25: (-) Tăng, (+) giảm phải thu bán chứng khoán đầu tư (Increase), Decrease in Receivables from investments sold but not yet settled | B25: 06 | D25: 8048895000 | E25: -17934475000
A26: (-) Tăng, (+) giảm dự thu phải thu tiền lãi các khoản đầu tư (Increase), Decrease in Dividend and interest receivables | B26: 07 | D26: 3403423288 | E26: -3651411753
A27: (-) Tăng, (+) giảm các khoản phải thu khác (Increase), Decrease in other receivables | B27: 08 | D27: 0 | E27: 24200
A28: (+) Tăng, (-) giảm vay ngắn hạn Increase, (Decrease) in Short-term Loans | B28: 09 | D28: 0 | E28: 0
A29: (+) Tăng, (-) giảm phải trả cho người bán (Decrease), Increase in payables for securities purchased but not yet settled | B29: 10 | D29: -8647040000 | E29: 33721725000
A30: (+) Tăng, (-) giảm phải trả các Đại lý phân phối Chứng chỉ quỹ, Công ty Quản lý Quỹ (Decrease)/increase in subscription and redemption fee payable to distributors and Fund Management Company | B30: 11 | D30: -98860744 | E30: -1176620106
... A38: Lưu chuyển tiền thuần từ hoạt động đầu tư (1+2+3) Net Cash flow from Investing activities | B38: 19 | D38: 65573739690 | E38: -392527457124
A39: II. Lưu chuyển tiền từ hoạt động tài chính Cash flow from financing activities | B39: II
A40: 1. Tiền thu từ phát hành Chứng chỉ quỹ mở Receipts from subscriptions | B40: 31 | D40: 263340163689 | E40: 734385200678
A41: 2. Tiền chi mua lại Chứng chỉ quỹ mở Payments for redemptions | B41: 32 | D41: -344996886597 | E41: -449135011172
A42: 3. Tiền vay gốc Principal of borrowings | B42: 33 | D42: 0 | E42: 0
A43: 4. Tiền chi trả nợ gốc vay Payment of Principal borrowings | B43: 34 | D43: 0 | E43: 0
A44: 5. Tiền chi trả cổ tức, tiền lãi cho nhà đầu tư Dividend, profit distribution paid to investors | B44: 35 | D44: 0 | E44: 0
A45: Lưu chuyển tiền thuần từ hoạt động tài chính (1-2+3-4-5) Net cash outflows from financing activities | B45: 30 | D45: -81656722908 | E45: 285250189506
A46: III. Tăng/giảm tiền thuần trong kỳ Net Increase/Decrease in cash and cash equivalent for the period | B46: 40 | D46: -16082983218 | E46: -107277267618
A47: IV. Tiền và các khoản tương đương tiền đầu kỳ Cash and cash equivalents at the beginning of period | B47: 50 | D47: 75921669347 | E47: 183198936965
A48: Tiền gửi ngân hàng đầu kỳ: Cash at bank of the beginning of period: | B48: 51 | D48: 75921669347 | E48: 183198936965
A49: -Tiền gửi ngân hàng và tương đương tiền cho hoạt động của Quỹ Cash at bank and cash equivalent for Fund's operation | B49: 52 | D49: 75046209212 | E49: 183101471378
A50: Tiền gửi không kỳ hạn Demand deposit | B50: 52.1 | D50: 75046209212 | E50: 103101471378
A51: Tiền gửi có kỳ hạn dưới ba (03) tháng Deposits with term under three (03) months | B51: 52.2 | D51: 0 | E51: 80000000000
... A64: Khác Others | B64: 80 | D64: 0 | E64: 0
A67: Người lập: | C67: Người duyệt:
A78: _______________________________ | B78: _______________________________________ | E78: ______________________
A79: Nguyễn Thu Ngọc | B79: Ninh Thị Tuệ Minh | E79: Lê Hoàng Anh
A80: Kế toán Quỹ | B80: Trưởng phòng Kế toán Quỹ | E80: Quyền Giám đốc nghiệp vụ hỗ trợ đầu tư

Sheet BCTaiSan_06027
A1: Phụ lục XXVI. Mẫu báo cáo về hoạt động của Quỹ Appendix XXVI. Report on Fund's Operation
A2: (Ban hành kèm theo Thông tư số 98/2020/TT-BTC ngày 16 tháng 11 năm 2020 của Bộ trưởng Bộ Tài Chính về hướng dẫn hoạt động và quản lý quỹ đầu tư chứng khoán) (Issued in association with Circular 98/2020/TT-BTC dated 16 November 2020 of the Minister of Finance on guiding the operation and management of the securities investment funds)
A3: BÁO CÁO HOẠT ĐỘNG ĐẦU TƯ CỦA QUỸ MỞ REPORT ON OPEN ENDED FUND'S INVESTMENT ACTIVITIES
A5: =TONGQUAN!C1 -> Tại ngày 31 tháng 12 năm 2023 / As at 31 Dec 2023
A7: Tên Công ty quản lý quỹ: | C7: =TONGQUAN!D5 -> Công ty Cổ phần Quản lý Quỹ Đầu tư Dragon Capital Việt Nam
A8: Fund Management Company: | C8: =TONGQUAN!D6 -> Dragon Capital Vietfund Management Joint Stock Company
A9: Tên ngân hàng giám sát: | C9: =TONGQUAN!D7 -> Ngân hàng TNHH Một thành viên Standard Chartered (Việt Nam)
A10: Supervising bank: | C10: =TONGQUAN!D8 -> Standard Chartered Bank (Vietnam) Limited
A11: Tên Quỹ: | C11: =TONGQUAN!D9 -> Quỹ Đầu tư Chứng khoán Năng động DC
A12: Fund name: | C12: =TONGQUAN!D10 -> DC Dynamic Securities Fund(DCDS)
A13: Ngày lập báo cáo: | C13: =TONGQUAN!D11 -> Ngày 08 tháng 03 năm 2024
A14: Reporting Date: | C14: =TONGQUAN!D12 -> 08 Mar 2024
A16: A. | B16: BÁO CÁO CHUNG VỀ HOẠT ĐỘNG ĐẦU TƯ CỦA QUỸ/GENERAL INFORMATION ON FUND'S INVESTMENT ACTIVITIES
A17: I | B17: BÁO CÁO VỀ TÀI SẢN / ASSET REPORT
A18: STT No | B18: Nội dung Indicator | C18: Mã chỉ tiêu Code | D18: Ngày 31 tháng 12 năm 2023 As at 31 Dec 2023 | E18: Ngày 31 tháng 12 năm 2022 As at 31 Dec 2022 | F18: %/cùng kỳ năm trước %/against last year
A19: I | B19: TÀI SẢN ASSETS | C19: 2200
A20: I.1 | B20: Tiền và các khoản tương đương tiền Cash and Cash Equivalents | C20: 2201 | D20: 59838686129 | E20: 75921669347 | F20: 0.78816347
B21: Tiền Cash | C21: 2202
A22: ... | B22: ... | C22: ... | D22: ... | E22: ... | F22: ...
B23: Tiền gửi ngân hàng Cash at bank | C23: 2203 | D23: 59838686129 | E23: 75921669347 | F23: 0.78816347
A24: ... | B24: ... | C24: ... | D24: ... | E24: ... | F24: ...
B25: Tiền gửi của nhà đầu tư cho hoạt động mua chứng chỉ quỹ Cash at bank for Fund's subscription | C25: 2203.1 | D25: 1448301386 | E25: 747083745 | F25: 1.9386065
B26: Tiền phải trả cho Nhà đầu tư về mua lại chứng chỉ quỹ Cash at bank for Fund's redemption | C26: 2203.2 | D26: 136051360 | E26: 128376390 | F26: 1.0597849
B27: Tiền gửi ngân hàng cho hoạt động của Quỹ Cash at bank for Fund's operation | C27: 2203.3 | D27: 58254333383 | E27: 75046209212 | F27: 0.77624618
B28: Tiền gửi ký quỹ cho hoạt động đầu tư chứng khoán phái sinh Margin account for trading derivatives | C28: 2203.4 | D28: 0 | E28: 0
B29: Tiền, tương đương tiền Cash, cash equivalents | C29: 2203.5 | D29: 0 | E29: 0
A30: I.2 | B30: Các khoản đầu tư (kê chi tiết) Investments | C30: 2205 | D30: 1469077080000 | E30: 1210013434960 | F30: 1.2140998
A31: ... | B31: ... | C31: ... | D31: ... | E31: ... | F31: ...
B32: Cổ phiếu, chứng chỉ quỹ niêm yết Listed Shares, fund certificates | C32: 2205.1 | D32: 1451817016000 | E32: 1049565668100 | F32: 1.3832551
B33: Cổ phiếu, chứng chỉ quỹ chưa niêm yết Unlisted Shares, fund certifictes | C33: 2205.2 | D33: 0 | E33: 0
B34: Trái phiếu Bonds | C34: 2205.3 | D34: 15155514000 | E34: 160447766860 | F34: 0.094457619
B35: Công cụ thị trường tiền tệ Money market instruments | C35: 2205.4 | D35: 0 | E35: 0
B36: Hợp đồng tiền gửi có kỳ hạn trên ba (03) tháng Deposits with term over three (03) months | C36: 2205.5 | D36: 0 | E36: 0
B37: Quyền mua chứng khoán Investment - Rights | C37: 2205.6 | D37: 2104550000 | E37: 0
B38: Hợp đồng tương lai chỉ số Index future contracts | C38: 2205.7 | D38: 0 | E38: 0
B39: Đầu tư khác Other investments | C39: 2205.8 | D39: 0 | E39: 0
B40: Hợp đồng mua lại đảo ngược Reverse repo contracts | C40: 2205.9 | D40: 0 | E40: 0
A41: I.3 | B41: Thu từ cho thuê bất động sản đầu tư (không áp dụng) Receivables from rental of investment property (not applicable) | C41: 2220 | D41: 0 | E41: 0
A42: ... | B42: ... | C42: ... | D42: ... | E42: ... | F42: ...
A43: I.4 | B43: Cổ tức, trái tức được nhận Dividend, Coupon receivables | C43: 2206 | D43: 2949367123 | E43: 6352790411 | F43: 0.46426325
A44: ... | B44: ... | C44: ... | D44: ... | E44: ... | F44: ...
B45: Phải thu cổ tức Dividend receivables | C45: 2206.1 | D45: 2860600000 | E45: 3696900000 | F45: 0.77378344
B46: Phải thu trái tức Coupon receivables | C46: 2206.2 | D46: 88767123 | E46: 2655890411 | F46: 0.033422736
A47: I.5 | B47: Lãi được nhận Interest receivables | C47: 2207 | D47: 0 | E47: 0
A48: ... | B48: ... | C48: ... | D48: ... | E48: ... | F48: ...
B49: Phải thu lãi tiền gửi Interest receivable from bank deposits | C49: 2207.1 | D49: 0 | E49: 0
B50: Phải thu lãi công cụ thị trường tiền tệ Interest receivable from Money market instruments | C50: 2207.2 | D50: 0 | E50: 0
B51: Phải thu lãi hợp đồng mua lại đảo ngược Interest receivable from reverse repo contracts | C51: 2207.3 | D51: 0 | E51: 0
A52: I.6 | B52: Tiền bán bất động sản chờ thu (không áp dụng) Real Estate Proceeds Receivables (not applicale) | C52: 2221 | D52: 0 | E52: 0
A53: ... | B53: ... | C53: ... | D53: ... | E53: ... | F53: ...
A54: I.7 | B54: Tiền bán chứng khoán chờ thu Securities Trading Receivables | C54: 2208 | D54: 28573030000 | E54: 36621925000 | F54: 0.7802165
A55: ... | B55: ... | C55: ... | D55: ... | E55: ... | F55: ...
A56: I.8 | B56: Các khoản phải thu khác Other Receivables | C56: 2210 | D56: -866400000 | E56: -866400000 | F56: 1
A57: ... | B57: ... | C57: ... | D57: ... | E57: ... | F57: ...
B58: Dự phòng giảm giá tài sản nhận thế chấp Impairment of devaluation of pledged assets | C58: 2210.1 | D58: 0 | E58: 0
B59: Dự phòng nợ phải thu khó đòi Provision for doubtful debt | C59: 2210.2 | D59: -866400000 | E59: -866400000 | F59: 1
B60: Các khoản phải thu khác Other Receivables | C60: 2210.3 | D60: 0 | E60: 0
A61: I.9 | B61: Các tài sản khác Other Assets | C61: 2211 | D61: 0 | E61: 0
A62: ... | B62: ... | C62: ... | D62: ... | E62: ... | F62: ...
A63: I.10 | B63: TỔNG TÀI SẢN TOTAL ASSETS | C63: 2212 | D63: 1559571763252 | E63: 1328043419718 | F63: 1.1743379
A64: II | B64: NỢ LIABILITIES | C64: 2213
A65: II.1 | B65: Tiền phải thanh toán mua bất động sản (không áp dụng) Real Estate Trading Payables (not applicable) | C65: 2222 | D65: 0 | E65: 0
A66: ... | B66: ... | C66: ... | D66: ... | E66: ... | F66: ...
A67: II.2 | B67: Tiền phải thanh toán mua chứng khoán Securities Trading Payables | C67: 2214 | D67: 43686305000 | E67: 52333345000 | F67: 0.83476997
A68: ... | B68: ... | C68: ... | D68: ... | E68: ... | F68: ...
A69: II.3 | B69: Các khoản phải trả khác Other Payables | C69: 2215 | D69: 9475537356 | E69: 14404230022 | F69: 0.65783019
A70: ... | B70: ... | C70: ... | D70: ... | E70: ... | F70: ...
B71: Phải trả nhà đầu tư Payables to investors | C71: 2215.1 | D71: 6076957403 | E71: 11095246469 | F71: 0.54770819
B72: Phải trả cho nhà đầu tư chờ mua chứng chỉ quỹ Subscription Pending allotment | C72: 2215.1.1 | D72: 1448301386 | E72: 747083745 | F72: 1.9386065
B73: Phải trả nhà đầu tư trên tài sản giữ hộ Payables to investors for investment bought on behalf | C73: 2215.1.2 | D73: 0 | E73: 0
B74: Phải trả nhà đầu tư trên cổ tức đã thu Payables to investors for collected dividend | C74: 2215.1.3 | D74: 0 | E74: 0
B75: Phải trả cho Nhà đầu tư về mua lại chứng chỉ quỹ Redemption payable to investors | C75: 2215.1.4 | D75: 4628656017 | E75: 10348162724 | F75: 0.44729254
B76: Thuế và các khoản phải nộp Nhà nước Tax payables and obligations to the State Budget | C76: 2215.2 | D76: 24333177 | E76: 9310080 | F76: 2.6136378
B77: Phải trả phí phát hành, mua lại chứng chỉ quỹ cho Đại lý phân phối và Công ty quản lý quỹ Subscription and Redemption fee payable to distributors and Fund Management Company | C77: 2215.3 | D77: 210829151 | E77: 309689895 | F77: 0.68077504
B78: Phải trả thu nhập cho nhà đầu tư Income payable to investors | C78: 2215.4 | D78: 39925000 | E78: 39925000 | F78: 1
B79: Phải trả thù lao Ban đại diện quỹ Remuneration Payable to Fund's Board of Representatives | C79: 2215.5 | D79: 24000000 | E79: 24000000 | F79: 1
B80: Phải trả phí quản lý cho công ty quản lý quỹ Management fee payable | C80: 2215.6 | D80: 2448036416 | E80: 2150379709 | F80: 1.1384205
B81: Phải trả phí quản trị quỹ Fund Administration fee payable | C81: 2215.7 | D81: 34523592 | E81: 30325868 | F81: 1.1384206
B82: Phải trả phí giám sát Supervisory service fee payable | C82: 2215.8 | D82: 55237745 | E82: 48521390 | F82: 1.1384205
B83: Phí giao dịch Transaction fee | C83: 2215.9 | D83: 133524523 | E83: 158568430 | F83: 0.84206246
B84: Phải trả phí môi giới Brokerage fee payable | C84: 2215.9.1 | D84: 133524523 | E84: 158568430 | F84: 0.84206246
B85: Phải trả phí phát hành thanh toán bù trừ chứng khoán Clearing Settlement fee payable | C85: 2215.9.2 | D85: 0 | E85: 0
B86: Trích trước phí lưu ký tài sản Quỹ mở Accrued expense for Custodian fee | C86: 2215.10 | D86: 105316133 | E86: 108210352 | F86: 0.97325377
B87: Phí lưu ký - bảo quản tài sản Custodian service - Safe Custody Fee | C87: 2215.10.1 | D87: 50216133 | E87: 44110352 | F87: 1.1384206
B88: Phí lưu ký - giao dịch chứng khoán Custodian service - Transaction fee | C88: 2215.10.2 | D88: 44100000 | E88: 64100000 | F88: 0.68798752
B89: Phí lưu ký cho chứng khoán cơ sở, phí quản lý vị thế và tài sản phái sinh trả cho VSDC Custodian service - Depository fee, Position and Margin management fee paid to VSDC | C89: 2215.10.3 | D89: 11000000 | E89: 0
B90: Phải trả phí kiểm toán Audit fee payable | C90: 2215.11 | D90: 102480000 | E90: 189000000 | F90: 0.54222222
B91: Phải trả phí họp đại hội thường niên General meeting expense payable | C91: 2215.12 | D91: 0 | E91: 0
B92: Phải trả phí báo cáo thường niên Annual report fee payable | C92: 2215.13 | D92: 0 | E92: 0
B93: Phải trả phí dịch vụ đại lý chuyển nhượng Transfer Agency fee payable | C93: 2215.14 | D93: 13200000 | E93: 13200000 | F93: 1
B94: Dự chi phí tính giá trị tài sản ròng tham chiếu (iNAV) cho HOSE Service fee payable to HOSE for calculating iNAV | C94: 2215.15 | D94: 0 | E94: 0
B95: Dự chi phí cấp quyền sử dụng chỉ số cho HOSE Authorising index service fee payable to HOSE | C95: 2215.16 | D95: 0 | E95: 0
B96: Phải trả khác Other payables | C96: 2215.17 | D96: 207174216 | E96: 227852829 | F96: 0.90924575
B97: Phải trả phí báo giá Price feed fee payable | C97: 2215.17.1 | D97: 23500000 | E97: 0
B98: Trích trước phí công tác, họp của ban đại diện Accrued expense for Fund's Board of Representatives travelling, meeting | C98: 2215.17.2 | D98: 0 | E98: 0
B99: Trích trước phí quản lý thường niên trả UBCKNN Accrued expense for Annual Management Fee pay to SSC | C99: 2215.17.3 | D99: 0 | E99: 0
B100: Phải trả khác Other payables | C100: 2215.17.4 | D100: 183674216 | E100: 227852829 | F100: 0.806109
B101: Vay ngắn hạn - hợp đồng repo Short-term loans - Repo contracts | C101: 2215.18 | D101: 0 | E101: 0
B102: Gốc hợp đồng repo Principal of repo contracts | C102: 2215.18.1 | D102: 0 | E102: 0
B103: Trích trước lãi vay ngắn hạn Accrued Interest Expense | C103: 2215.18.2 | D103: 0 | E103: 0
...

Sheet BCKetQuaHoatDong_06028
A1: Phụ lục XXVI. Mẫu báo cáo về hoạt động của Quỹ Appendix XXVI. Report on Fund's Operation
A2: (Ban hành kèm theo Thông tư số 98/2020/TT-BTC ngày 16 tháng 11 năm 2020 của Bộ trưởng Bộ Tài Chính về hướng dẫn hoạt động và quản lý quỹ đầu tư chứng khoán) (Issued in association with Circular 98/2020/TT-BTC dated 16 November 2020 of the Minister of Finance on guiding the operation and management of the securities investment funds)
A3: BÁO CÁO HOẠT ĐỘNG ĐẦU TƯ CỦA QUỸ MỞ REPORT ON OPEN ENDED FUND'S INVESTMENT ACTIVITIES
A5: =TONGQUAN!C2 -> Năm 2023 / Year 2023
A7: Tên Công ty quản lý quỹ: | C7: =TONGQUAN!D5 -> Công ty Cổ phần Quản lý Quỹ Đầu tư Dragon Capital Việt Nam
A8: Fund Management Company: | C8: =TONGQUAN!D6 -> Dragon Capital Vietfund Management Joint Stock Company
A9: Tên ngân hàng giám sát: | C9: =TONGQUAN!D7 -> Ngân hàng TNHH Một thành viên Standard Chartered (Việt Nam)
A10: Supervising bank: | C10: =TONGQUAN!D8 -> Standard Chartered Bank (Vietnam) Limited
A11: Tên Quỹ: | C11: =TONGQUAN!D9 -> Quỹ Đầu tư Chứng khoán Năng động DC
A12: Fund name: | C12: =TONGQUAN!D10 -> DC Dynamic Securities Fund(DCDS)
A13: Ngày lập báo cáo: | C13: =TONGQUAN!D11 -> Ngày 08 tháng 03 năm 2024
A14: Reporting Date: | C14: =TONGQUAN!D12 -> 08 Mar 2024
A16: A. | B16: BÁO CÁO CHUNG VỀ HOẠT ĐỘNG ĐẦU TƯ CỦA QUỸ/GENERAL INFORMATION ON FUND'S INVESTMENT ACTIVITIES
A17: II | B17: BÁO CÁO KẾT QUẢ HOẠT ĐỘNG / PROFIT AND LOSS REPORT
A18: STT No | B18: Nội dung Indicator | C18: Mã chỉ tiêu Code | D18: Năm 2023 Year 2023 | E18: Năm 2022 Year 2022 | F18: Lũy kế từ đầu năm Accumulated from beginning of year
A19: I | B19: Thu nhập từ hoạt động đầu tư Income from Investment Activities | C19: 2220 | D19: 27188162933 | E19: 34895425486 | F19: 27188162933
A20: 1 | B20: Thu từ bất động sản cho thuê (không áp dụng) Income from rental property (not applicable) | C20: 2223 | D20: 0 | E20: 0 | F20: 0
A21: ... | B21: ... | C21: ... | D21: ... | E21: … | F21: …
A22: 2 | B22: Cổ tức, trái tức được nhận Dividend income, interest income from bonds | C22: 2221 | D22: 26935684468 | E22: 32867490336 | F22: 26935684468
A23: ... | B23: ... | C23: ... | D23: ... | E23: … | F23: …
B24: Cổ tức được nhận Dividends income | C24: 2221.1 | D24: 21446287000 | E24: 17365202500 | F24: 21446287000
B25: Trái tức được nhận Interest income from bonds | C25: 2221.2 | D25: 5489397468 | E25: 15502287836 | F25: 5489397468
A26: 3 | B26: Lãi được nhận Interest income | C26: 2222 | D26: 252478465 | E26: 2027935150 | F26: 252478465
A27: ... | B27: ... | C27: ... | D27: ... | E27: ... | F27: ...
B28: Lãi tiền gửi ngân hàng Interest income from bank deposits | C28: 2222.1 | D28: 252478465 | E28: 1192606383 | F28: 252478465
B29: Lãi công cụ thị trường tiền tệ Interest income from Money market instruments | C29: 2222.2 | D29: 0 | E29: 835328767 | F29: 0
B30: Lãi hợp đồng mua lại đảo ngược Interest income from reverse repo contracts | C30: 2222.3 | D30: 0 | E30: 0 | F30: 0
A31: 4 | B31: Các khoản thu nhập khác Other incomes | C31: 2223 | D31: 0 | E31: 0 | F31: 0
A32: ... | B32: ... | C32: ... | D32: ... | E32: ... | F32: ...
B33: Thu nhập khác về đầu tư Other investment incomes | C33: 2223.1 | D33: 0 | E33: 0 | F33: 0
B34: Thu nhập khác Other incomes | C34: 2223.2 | D34: 0 | E34: 0 | F34: 0
B35: Chi phí dự phòng nợ phải thu khó đòi về cổ tức, tiền lãi và xử lý tổn thất nợ phải thu khó đòi về cổ tức, tiền lãi Provision expense for bad debts from dividends, interest income and written off bad debts from dividends, interest income | C35: 2223.3 | D35: 0 | E35: 0 | F35: 0
A36: II | B36: Chi phí Expenses | C36: 2224 | D36: 45704776067 | E36: 52679756326 | F36: 45704776067
A37: 1 | B37: Chi phí quản lý trả cho Công ty quản lý quỹ Management Fee paid to Fund Management Company | C37: 2225 | D37: 26545352339 | E37: 30361846097 | F37: 26545352339
A38: ... | B38: ... | C38: ... | D38: ... | E38: ... | F38: ...
A39: 2 | B39: Chi phí lưu ký, giám sát trả cho Ngân hàng Giám sát/VSDC Custody fee, Supervising fee paid to Supervising Bank/VSDC | C39: 2226 | D39: 1743724364 | E39: 1752733314 | F39: 1743724364
A40: ... | B40: ... | C40: ... | D40: ... | E40: ... | F40: ...
B41: Chi phí dịch vụ lưu ký - bảo quản tài sản Custodian service - Safe Custody Fee | C41: 2226.1 | D41: 544661766 | E41: 622807094 | F41: 544661766
B42: Chi phí dịch vụ lưu ký - giao dịch chứng khoán Custodian service - Transaction fee | C42: 2226.2 | D42: 465615000 | E42: 349015000 | F42: 465615000
B43: Chi phí dịch vụ lưu ký cho chứng khoán cơ sở, phí quản lý vị thế và tài sản phái sinh trả cho VSDC Custodian service - Depository fee, Position and Margin management fee paid to VSDC | C43: 2226.3 | D43: 134319658 | E43: 95823407 | F43: 134319658
B44: Chi phí giám sát Supervisory fee | C44: 2226.4 | D44: 599127940 | E44: 685087813 | F44: 599127940
A45: 3 | B45: Chi phí quản trị quỹ và các chi phí khác mà công ty quản lý quỹ trả cho tổ chức cung cấp dịch vụ có liên quan Fund Administration Fee, and other fees paid to relevant Fund's service providers | C45: 2227 | D45: 532854969 | E45: 573379880 | F45: 532854969
A46: ... | B46: ... | C46: ... | D46: ... | E46: ... | F46: ...
B47: Chi phí quản trị Quỹ Fund Administration Fee | C47: 2227.1 | D47: 374454969 | E47: 428179880 | F47: 374454969
B48: Chi phí dịch vụ Đại lý Chuyển nhượng Transfer Agency Fee | C48: 2227.2 | D48: 158400000 | E48: 145200000 | F48: 158400000
A49: 4 | B49: Chi phí dịch vụ quản lý bất động sản (không áp dụng) Real Estate Management Service fee (not applicable) | C49: 2231 | D49: 0 | E49: 0 | F49: 0
A50: ... | B50: ... | C50: ... | D50: ... | E50: ... | F50: ...
A51: 5 | B51: Chi phí dịch vụ định giá bất động sản (không áp dụng) Real estate valuation service fees (not applicable) | C51: 2232 | D51: 0 | E51: 0 | F51: 0
A52: ... | B52: ... | C52: ... | D52: ... | E52: ... | F52: ...
A53: 6 | B53: Chi phí kiểm toán trả cho tổ chức kiểm toán Audit fee | C53: 2228 | D53: 207137469 | E53: 189942000 | F53: 207137469
A54: ... | B54: ... | C54: ... | D54: ... | E54: ... | F54: ...
A55: 7 | B55: Chi phí dịch vụ tư vấn pháp lý, dịch vụ báo giá và các dịch vụ hợp lý khác, thù lao trả cho ban đại diện quỹ Legal consultancy expenses, price feed fee, other valid expenses, remuneration paid to Fund's Board of Representatives | C55: 2229 | D55: 250000000 | E55: 317633332 | F55: 250000000
A56: ... | B56: ... | C56: ... | D56: ... | E56: ... | F56: ...
B57: Thù lao Ban đại diện Quỹ Remuneration of Fund's Board of Representatives | C57: 2229.1 | D57: 156000000 | E57: 181000000 | F57: 156000000
B58: Chi phí cung cấp báo giá chứng khoán Price feed fee | C58: 2229.2 | D58: 94000000 | E58: 136633332 | F58: 94000000
B59: Chi phí dịch vụ tư vấn pháp lý Legal consultancy expenses | C59: 2229.3 | D59: 0 | E59: 0 | F59: 0
A60: 8 | B60: Chi phí dự thảo, in ấn, gửi bản cáo bạch, bản cáo bạch tóm tắt, báo cáo tài chính, xác nhận giao dịch, sao kê tài khoản và các tài liệu khác cho nhà đầu tư; chi phí công bố thông tin của quỹ; chi phí tổ chức họp đại hội nhà đầu tư, ban đại diện quỹ Fee for drafting, printing, distribution of prospectus, summarised prospectus, financial statements, transaction confirmations, account statements and other documents to investors; information disclosure fee; fee for organising annual general meeting, board of representatives meeting | C60: 2230 | D60: 27950952 | E60: 35094216 | F60: 27950952
A61: ... | B61: ... | C61: ... | D61: ... | E61: ... | F61: ...
B62: Chi phí họp Đại hội Quỹ Meeting expenses | C62: 2230.1 | D62: 27950952 | E62: 35094216 | F62: 27950952
B63: Chi phí báo cáo thường niên Annual report expenses | C63: 2230.2 | D63: 0 | E63: 0 | F63: 0
B64: Chi phí họp, công tác của Ban đại diện Fund's Board of Representatives meeting, travelling expenses | C64: 2230.3 | D64: 0 | E64: 0 | F64: 0
B65: Chi phí công bố thông tin của Quỹ Expenses of information disclosure of the Fund | C65: 2230.4 | D65: 0 | E65: 0 | F65: 0
B66: Chi phí thiết kế, in ấn, gửi thư… Designing, printing, posting... expenses | C66: 2230.5 | D66: 0 | E66: 0 | F66: 0
A67: 9 | B67: Chi phí liên quan đến thực hiện các giao dịch tài sản của Quỹ Expenses related to execution of Fund’s asset transactions | C67: 2231 | D67: 16285754924 | E67: 19348708287 | F67: 16285754924
A68: ... | B68: ... | C68: ... | D68: ... | E68: ... | F68: ...
B69: Chi phí môi giới Brokerage fee | C69: 2231.1 | D69: 16195631005 | E69: 19285488371 | F69: 16195631005
B70: Chi phí thanh toán bù trừ Clearing settlement fee | C70: 2231.2 | D70: 67623919 | E70: 53219916 | F70: 67623919
B71: Chi phí khác Other Expenses | C71: 2231.3 | D71: 22500000 | E71: 10000000 | F71: 22500000
A72: 10 | B72: Các loại chi phí khác Other expenses | C72: 2232 | D72: 112001050 | E72: 100419200 | F72: 112001050
A73: ... | B73: ... | C73: ... | D73: ... | E73: ... | F73: ...
B74: Chi phí thiết lập Quỹ Set up Expenses | C74: 2232.1 | D74: 0 | E74: 0 | F74: 0
B75: Phí niêm yết, đăng ký chứng khoán Listing, registration fees | C75: 2232.2 | D75: 0 | E75: 0 | F75: 0
B76: Phí quản lý thường niên trả cho UBCKNN Annual management fee paid to SSC | C76: 2232.3 | D76: 12500000 | E76: 7500000 | F76: 12500000
B77: Phí ngân hàng Bank charges | C77: 2232.4 | D77: 98401050 | E77: 91819200 | F77: 98401050
B78: Chi phí lãi vay Borrowing expense | C78: 2232.5 | D78: 0 | E78: 0 | F78: 0
B79: Chi phí khác Other Expenses | C79: 2232.6 | D79: 0 | E79: 0 | F79: 0
B80: Phí thực hiện quyền trả cho VSDC Fee paid to VSDC for getting the list of investors | C80: 2232.7 | D80: 1100000 | E80: 1100000 | F80: 1100000
A81: III | B81: Thu nhập ròng từ hoạt động đầu tư (= I - II) Net Income from Investment Activities (= I - II) | C81: 2233 | D81: -18516613134 | E81: -17784330840 | F81: -18516613134
A82: IV | B82: Lãi / (lỗ) từ hoạt động đầu tư Gain / (Loss) from Investment Activities | C82: 2234 | D82: 345277412242 | E82: -648027494719 | F82: 345277412242
A83: 1 | B83: Lãi (lỗ) thực tế phát sinh từ hoạt động đầu tư hoặc chuyển nhượng bất động sản Realised Gain / (Loss) from disposal of investment or real estate transfer | C83: 2235 | D83: 202459819566 | E83: -449654427803 | F83: 202459819566
A84: 2 | B84: Thay đổi về giá trị của các khoản đầu tư trong kỳ Unrealised Gain / (Loss) due to market price | C84: 2236 | D84: 142817592676 | E84: -198373066916 | F84: 142817592676
A85: V | B85: Thay đổi của giá trị tài sản ròng của Quỹ do các hoạt động đầu tư trong kỳ (III + IV) Change of Net Asset Value of the Fund due to investment activities during the period (= III + IV) | C85: 2237 | D85: 326760799108 | E85: -665811825559 | F85: 326760799108
A86: VI | B86: Giá trị tài sản ròng đầu kỳ Net Asset Value at the beginning of period | C86: 2238 | D86: 1261305844696 | E86: 1641867480749 | F86: 1261305844696
A87: VII | B87: Thay đổi giá trị tài sản ròng của Quỹ trong kỳ, Trong đó Change of Net Asset Value of the Fund during the period, of which | C87: 2239 | D87: 245104076200 | E87: -380561636053 | F87: 245104076200
A88: 1 | B88: Thay đổi giá trị tài sản ròng của Quỹ do các hoạt động đầu tư của Quỹ trong kỳ Change of Net Asset Value due to investment activities during the period | C88: 2239.1 | D88: 326760799108 | E88: -665811825559 | F88: 326760799108
A89: 2 | B89: Thay đổi giá trị tài sản ròng của Quỹ do việc chi trả lợi tức/ cổ tức của Quỹ cho các nhà đầu tư trong kỳ Change of Net Asset Value due to dividends payment to investors during the period | C89: 2239.2 | D89: 0 | E89: 0 | F89: 0
A90: 3 | B90: Thay đổi giá trị tài sản ròng do phát hành thêm/mua lại chứng chỉ quỹ Change of Net Asset Value due to subscription/redemption during the period | C90: 2239.3 | D90: -81656722908 | E90: 285250189506 | F90: -81656722908
B91: Thay đổi giá trị tài sản ròng do phát hành thêm Chứng chỉ Quỹ Change of Net Asset Value due to subscription during the period | C91: 2239.3.1 | D91: 263340163689 | E91: 734385200678 | F91: 263340163689
B92: Thay đổi giá trị tài sản ròng do mua lại Chứng chỉ Quỹ Change of Net Asset Value due to redemption during the period | C92: 2239.3.2 | D92: -344996886597 | E92: -449135011172 | F92: -344996886597
A93: VIII | B93: Giá trị tài sản ròng cuối kỳ Net Asset Value at the end of period | C93: 2243 | D93: 1506409920896 | E93: 1261305844696 | F93: 1506409920896
A94: IX | B94: Lợi nhuận bình quân năm (chỉ áp dụng đối với báo cáo năm) Average annual profit (only applicable to annual report) | C94: 2244 | D94: 326760799108 | E94: -665811825559 | F94: 326760799108
B95: Tỷ suất lợi nhuận bình quân năm (chỉ áp dụng đối với báo cáo năm) Average annual rate of return (only applicable to annual report) | C95: 2245 | D95: 0.24000046 | E95: -0.42766661 | F95: 0.24000046
A97: Đại diện có thẩm quyền của Ngân hàng giám sát | D97: Đại diện có thẩm quyền của Công ty quản lý Quỹ
A98: Authorised Representative of Supervisory Bank | D98: Authorised Representative of Fund Management Company
A105: =TONGQUAN!C19 -> Ngân hàng TNHH MTV Standard Chartered (Việt Nam) | D105: =TONGQUAN!F19 -> Công ty Cổ phần Quản lý Quỹ Đầu tư Dragon Capital Việt Nam
A106: =TONGQUAN!C20 -> Vũ Quang Phan | D106: =TONGQUAN!F20 -> Lê Hoàng Anh
A107: Phó phòng Dịch vụ nghiệp vụ Giám sát Quỹ | D107: =TONGQUAN!F21 -> Quyền Giám đốc nghiệp vụ hỗ trợ đầu tư

Sheet BCDanhMucDauTu_06029
A1: Phụ lục XXVI. Mẫu báo cáo về hoạt động của Quỹ Appendix XXVI. Report on Fund's Operation
A2: (Ban hành kèm theo Thông tư số 98/2020/TT-BTC ngày 16 tháng 11 năm 2020 của Bộ trưởng Bộ Tài Chính về hướng dẫn hoạt động và quản lý quỹ đầu tư chứng khoán) (Issued in association with Circular 98/2020/TT-BTC dated 16 November 2020 of the Minister of Finance on guiding the operation and management of the securities investment funds)
A3: BÁO CÁO HOẠT ĐỘNG ĐẦU TƯ CỦA QUỸ MỞ REPORT ON OPEN ENDED FUND'S INVESTMENT ACTIVITIES
A5: =TONGQUAN!C1 -> Tại ngày 31 tháng 12 năm 2023 / As at 31 Dec 2023
A7: Tên Công ty quản lý quỹ: | C7: =TONGQUAN!D5 -> Công ty Cổ phần Quản lý Quỹ Đầu tư Dragon Capital Việt Nam
A8: Fund Management Company: | C8: =TONGQUAN!D6 -> Dragon Capital Vietfund Management Joint Stock Company
A9: Tên ngân hàng giám sát: | C9: =TONGQUAN!D7 -> Ngân hàng TNHH Một thành viên Standard Chartered (Việt Nam)
A10: Supervising bank: | C10: =TONGQUAN!D8 -> Standard Chartered Bank (Vietnam) Limited
A11: Tên Quỹ: | C11: =TONGQUAN!D9 -> Quỹ Đầu tư Chứng khoán Năng động DC
A12: Fund name: | C12: =TONGQUAN!D10 -> DC Dynamic Securities Fund(DCDS)
A13: Ngày lập báo cáo: | C13: =TONGQUAN!D11 -> Ngày 08 tháng 03 năm 2024
A14: Reporting Date: | C14: =TONGQUAN!D12 -> 08 Mar 2024
A16: A. | B16: BÁO CÁO CHUNG VỀ HOẠT ĐỘNG ĐẦU TƯ CỦA QUỸ/GENERAL INFORMATION ON FUND'S INVESTMENT ACTIVITIES
A17: III | B17: BÁO CÁO DANH MỤC ĐẦU TƯ / INVESTMENT PORTFOLIO REPORT
A18: STT No. | B18: Loại Category | C18: Mã chỉ tiêu Code | D18: Số Lượng Quantity | E18: Giá thị trường hoặc giá trị hợp lý tại ngày báo cáo Market price | F18: Tổng giá trị (Đồng) Value (VND) | G18: Tỷ lệ % Tổng giá trị tài sản của Quỹ % of total asset
A19: I | B19: BẤT ĐỘNG SẢN ĐẦU TƯ (KHÔNG ÁP DỤNG) REAL ESTATE INVESTMENT (NOT APPLICABLE)
B21: TỔNG TOTAL | C21: 2264
A22: II | B22: CỔ PHIẾU NIÊM YẾT, ĐĂNG KÝ GIAO DỊCH, CHỨNG CHỈ QUỸ NIÊM YẾT SHARES LISTED, SHARES REGISTERED FOR TRADING, LISTED FUND CERTIFICATES | C22: 2246
A24: 1 | B24: BID | C24: 2246.1 | D24: 115738 | E24: 43400 | F24: 5023029200 | G24: 0.0032
A25: 2 | B25: BSI | C25: 2246.2 | D25: 48800 | E25: 47500 | F25: 2318000000 | G25: 0.0015
A26: 3 | B26: CTD | C26: 2246.3 | D26: 536800 | E26: 68800 | F26: 36931840000 | G26: 0.0237
A27: 4 | B27: CTG | C27: 2246.4 | D27: 526026 | E27: 27100 | F27: 14255304600 | G27: 0.0091
A28: 5 | B28: DCM | C28: 2246.5 | D28: 798000 | E28: 32400 | F28: 25855200000 | G28: 0.0166
A29: 6 | B29: DGC | C29: 2246.6 | D29: 716800 | E29: 94400 | F29: 67665920000 | G29: 0.0434
A30: 7 | B30: DGW | C30: 2246.7 | D30: 726800 | E30: 52300 | F30: 38011640000 | G30: 0.0244
A31: 8 | B31: DHC | C31: 2246.8 | D31: 117000 | E31: 38000 | F31: 4446000000 | G31: 0.0029
A32: 9 | B32: DIG | C32: 2246.9 | D32: 656800 | E32: 26750 | F32: 17569400000 | G32: 0.0113
A33: 10 | B33: DPG | C33: 2246.10 | D33: 576800 | E33: 39650 | F33: 22870120000 | G33: 0.0147
A34: 11 | B34: DRC | C34: 2246.11 | D34: 281600 | E34: 26500 | F34: 7462400000 | G34: 0.0048
A35: 12 | B35: DXG | C35: 2246.12 | D35: 1511000 | E35: 19350 | F35: 29237850000 | G35: 0.0187
... A78: 55 | B78: VTP | C78: 2246.55 | D78: 572568 | E78: 56900 | F78: 32579119200 | G78: 0.0209
B79: TỔNG TOTAL | C79: 2247 | F79: 1451817016000 | G79: 0.931
A80: III | B80: CỔ PHIẾU CHƯA NIÊM YẾT, ĐĂNG KÝ GIAO DỊCH, CHỨNG CHỈ QUỸ KHÔNG NIÊM YẾT SHARES UNLISTED, UNREGISTERED FOR TRADING, UNLISTED FUND CERTIFICATES | C80: 2248
B82: TỔNG TOTAL | C82: 2249 | F82: 0 | G82: 0
A83: IV | B83: TRÁI PHIẾU BONDS | C83: 2251
A85: 1 | B85: Trái phiếu niêm yết Listed bonds | C85: 2251.1 | F85: 0 | G85: 0
A86: 2 | B86: Trái phiếu chưa niêm yết Unlisted Bonds | C86: 2251.2 | F86: 15155514000 | G86: 0.0097
A87: 2.1 | B87: KDH12101 | C87: 2251.2.1 | D87: 15 | E87: 1010367600 | F87: 15155514000 | G87: 0.0097
B88: TỔNG TOTAL | C88: 2252 | F88: 15155514000 | G88: 0.0097
A89: V | B89: CÁC LOẠI CHỨNG KHOÁN KHÁC OTHER SECURITIES | C89: 2253
A91: 1 | B91: Quyền mua chứng khoán Investment - Rights | C91: 2253.1 | F91: 2104550000 | G91: 0.0013
A92: 1.1 | B92: DAT XANH GROUP JSC -RIGHTS | C92: 2253.1.1 | D92: 1718000 | E92: 1225 | F92: 2104550000 | G92: 0.0013
A93: 2 | B93: Chi tiết loại hợp đồng phái sinh(*) Index future contracts | C93: 2253.2 | F93: 0 | G93: 0
B94: TỔNG TOTAL | C94: 2254 | F94: 2104550000 | G94: 0.0013
B95: TỔNG CÁC LOẠI CHỨNG KHOÁN TOTAL TYPES OF SECURITIES | C95: 2255 | F95: 1469077080000 | G95: 0.942
A96: VI | B96: CÁC TÀI SẢN KHÁC OTHER ASSETS | C96: 2256
A98: 1 | B98: Cổ tức được nhận Dividend receivables | C98: 2256.1 | F98: 2860600000 | G98: 0.0018
A99: 2 | B99: Lãi trái phiếu được nhận Coupon receivables | C99: 2256.2 | F99: 88767123 | G99: 0.0001
A100: 3 | B100: Lãi tiền gửi và công cụ thị trường tiền tệ được nhận Interest receivables from bank deposits and Money market instruments | C100: 2256.3 | F100: 0 | G100: 0
A101: 4 | B101: Tiền bán chứng khoán chờ thu Outstanding Settlement of sales transactions | C101: 2256.4 | F101: 28573030000 | G101: 0.0183
A102: 5 | B102: Phải thu cho khoản cổ phiếu hạn chế chờ mua Receivable from AP/Investors on securities on hold of buying | C102: 2256.5 | F102: 0 | G102: 0
A103: 6 | B103: Phải thu khác Other receivables | C103: 2256.6 | F103: -866400000 | G103: -0.0006
A104: 7 | B104: Tài sản khác Other assets | C104: 2256.7 | F104: 0 | G104: 0
B105: TỔNG TOTAL | C105: 2257 | F105: 30655997123 | G105: 0.0196
A106: VII | B106: TIỀN CASH | C106: 2258
A107: 1 | B107: Tiền, tương đương tiền Cash, Cash Equivalent | C107: 2259 | F107: 59838686129 | G107: 0.0384
A109: 1.1 | B109: Tiền gửi ngân hàng Cash at Bank | C109: 2259.1 | F109: 59838686129 | G109: 0.0384
A110: 1.2 | B110: Các khoản tương đương tiền Cash Equivalents | C110: 2259.2 | F110: 0 | G110: 0
A111: 2 | B111: Tiền gửi ngân hàng có kỳ hạn trên 3 tháng Deposits with term over three (03) months | C111: 2260 | F111: 0 | G111: 0
A113: 3 | B113: Công cụ thị trường tiền tệ Money market instruments | C113: 2261.1 | F113: 0 | G113: 0
B114: TỔNG TOTAL | C114: 2262 | F114: 59838686129 | G114: 0.0384
A115: VIII | B115: Tổng giá trị danh mục Total value of portfolio | C115: 2263 | F115: 1559571763252 | G115: 1
A117: Đại diện có thẩm quyền của Ngân hàng giám sát | E117: Đại diện có thẩm quyền của Công ty quản lý Quỹ
A118: Authorised Representative of Supervisory Bank | E118: Authorised Representative of Fund Management Company
A127: Ngân hàng TNHH MTV Standard Chartered (Việt Nam) | E127: Công ty Cổ phần Quản lý Quỹ Đầu tư Dragon Capital Việt Nam
A128: Vũ Quang Phan | E128: Lê Hoàng Anh
A129: Phó phòng Dịch vụ nghiệp vụ Giám sát Quỹ | E129: Quyền Giám đốc nghiệp vụ hỗ trợ đầu tư

Sheet Khac_06030
A1: Phụ lục XXVI. Mẫu báo cáo về hoạt động của Quỹ Appendix XXVI. Report on Fund's Operation
A2: (Ban hành kèm theo Thông tư số 98/2020/TT-BTC ngày 16 tháng 11 năm 2020 của Bộ trưởng Bộ Tài Chính về hướng dẫn hoạt động và quản lý quỹ đầu tư chứng khoán) (Issued in association with Circular 98/2020/TT-BTC dated 16 November 2020 of the Minister of Finance on guiding the operation and management of the securities investment funds)
A3: BÁO CÁO HOẠT ĐỘNG ĐẦU TƯ CỦA QUỸ MỞ REPORT ON OPEN ENDED FUND'S INVESTMENT ACTIVITIES
A5: =TONGQUAN!C2 -> Năm 2023 / Year 2023
A7: Tên Công ty quản lý quỹ: | C7: =TONGQUAN!D5 -> Công ty Cổ phần Quản lý Quỹ Đầu tư Dragon Capital Việt Nam
A8: Fund Management Company: | C8: =TONGQUAN!D6 -> Dragon Capital Vietfund Management Joint Stock Company
A9: Tên ngân hàng giám sát: | C9: =TONGQUAN!D7 -> Ngân hàng TNHH Một thành viên Standard Chartered (Việt Nam)
A10: Supervising bank: | C10: =TONGQUAN!D8 -> Standard Chartered Bank (Vietnam) Limited
A11: Tên Quỹ: | C11: =TONGQUAN!D9 -> Quỹ Đầu tư Chứng khoán Năng động DC
A12: Fund name: | C12: =TONGQUAN!D10 -> DC Dynamic Securities Fund(DCDS)
A13: Ngày lập báo cáo: | C13: =TONGQUAN!D11 -> Ngày 08 tháng 03 năm 2024
A14: Reporting Date: | C14: =TONGQUAN!D12 -> 08 Mar 2024
A16: A. | B16: BÁO CÁO CHUNG VỀ HOẠT ĐỘNG ĐẦU TƯ CỦA QUỸ/GENERAL INFORMATION ON FUND'S INVESTMENT ACTIVITIES
A17: V | B17: MỘT SỐ CHỈ TIÊU KHÁC / OTHER INDICATORS
A18: STT No | B18: Chỉ tiêu Indicators | C18: Mã chỉ tiêu Code | D18: Năm 2023 Year 2023 | E18: Năm 2022 Year 2022
A19: I | B19: CÁC CHỈ TIÊU VỀ HIỆU QUẢ HOẠT ĐỘNG INVESTMENT PERFORMANCE INDICATORS | C19: 2264
A20: 1 | B20: Tỷ lệ giá dịch vụ quản lý quỹ trả cho công ty quản lý quỹ/Giá trị tài sản ròng trung bình trong kỳ (%) Management fee paid to the fund management company/Average NAV (%) | C20: 2265 | D20: 0.019497127 | E20: 0.019502128
A21: 2 | B21: Tỷ lệ giá dịch vụ lưu ký, giám sát trả cho Ngân hàng Giám sát/Giá trị tài sản ròng trung bình trong kỳ (%) Custody and supervising fees paid to the Supervisory Bank/Average NAV (%) | C21: 2266 | D21: 0.0011820814 | E21: 0.0010642722
A22: 3 | B22: Tỷ lệ chi phí dịch vụ quản trị quỹ, và các chi phí khác mà công ty quản lý quỹ trả cho tổ chức cung cấp dịch vụ có liên quan/Giá trị tài sản ròng của quỹ trung bình trong kỳ (%) Fund admin fee, and other fees paid to relating services providers by the fund management company/Average NAV (%) | C22: 22661 | D22: 0.00049002885 | E22: 0.00042984502
A23: 4 | B23: Chi phí kiểm toán trả cho tổ chức kiểm toán (nếu phát sinh)/Giá trị tài sản ròng trung bình trong kỳ (%) Auditing fee paid to auditing organizations (if any)/Average NAV (%) | C23: 2267 | D23: 0.00015213908 | E23: 0.00012200422
A24: 5 | B24: Chi phí trả cho tổ chức quản lý bất động sản/ Giá trị tài sản ròng trung bình trong kỳ (%) (không áp dụng) Fee paid to Real Estate management organisation/ Average NAV (%) (not applicable) | C24: 2286
A25: 6 | B25: Chi phí trả cho doanh nghiệp thẩm định giá bất động sản/Giá trị tài sản ròng trung bình trong kỳ (%) (không áp dụng) Fee paid to Real Estate valuation service provider/ Average NAV (%) (not applicable) | C25: 2287
A26: 7 | B26: Chi phí dịch vụ tư vấn pháp lý, dịch vụ báo giá và các dịch vụ hợp lý khác, thù lao trả cho ban đại diện quỹ/Giá trị tài sản ròng trung bình trong kỳ (%) Legal consultancy, price quotation and other appropriate service fees; remunerations paid to the Board of Representatives/Average NAV (%) | C26: 2268 | D26: 0.00018362091 | E26: 0.00020402337
A27: 8 | B27: Tỷ lệ chi phí /Giá trị tài sản ròng trung bình trong kỳ (%) Expense/Average NAV (%) | C27: 2269 | D27: 0.02160779 | E27: 0.033837448
A28: 9 | B28: Tốc độ vòng quay danh mục trong kỳ (%)/Portfolio turnover rate (%) | C28: 2270 | D28: 4.4416021 | E28: 4.7136996
A29: 10 | B29: Tỷ lệ thu nhập (tính cả thu nhập từ lãi, cổ tức, trái tức, chênh lệch giá)/ Giá trị tài sản ròng (không áp dụng) Income (including interest income, dividend, coupon income and unrealised gain)/ Average NAV (%) (not applicable) | C29: 2287
A30: II | B30: CÁC CHỈ TIÊU KHÁC OTHER INDICATORS | C30: 2272
A31: 1 | B31: Quy mô quỹ đầu kỳ (tính theo mệnh giá chứng chỉ quỹ) Fund scale at the beginning of the period (based on par value of fund certificate) | C31: 2273 | D31: 244762721400 | E31: 209030821100
B32: Tổng giá trị chứng chỉ quỹ đang lưu hành đầu kỳ Total value of outstanding Fund Certificate at the beginning of period | C32: 2274 | D32: 244762721400 | E32: 209030821100
B33: Tổng số lượng chứng chỉ quỹ đang lưu hành đầu kỳ Total number of outstanding Fund Certificate at the beginning of period | C33: 2275 | D33: 24476272 | E33: 20903082
A34: 2 | B34: Thay đổi quy mô quỹ trong kỳ (tính theo mệnh giá chứng chỉ quỹ) Change of Fund scale during the period (based on par value of fund certificate) | C34: 2276 | D34: -15554296300 | E34: 35731900300
B35: Thay đổi số lượng chứng chỉ quỹ trong kỳ Change of Number of Fund Certificates during the period | C35: 22761 | D35: -1555429.6 | E35: 3573190
B36: Thay đổi giá trị vốn trong kỳ (theo mệnh giá) Change in capital amount during the period (based on par value) | C36: 22762 | D36: -15554296300 | E36: 35731900300
B37: Số lượng chứng chỉ quỹ phát hành thêm trong kỳ Number of Fund Certificates subscribed during the period | C37: 2277 | D37: 4308044.8 | E37: 10562254
B38: Giá trị vốn huy động thêm trong kỳ (theo mệnh giá) Net subscription amount during the period (based on par value) | C38: 2278 | D38: 43080447800 | E38: 105622541400
B39: Số lượng chứng chỉ quỹ mua lại trong kỳ Number of Fund Certificates redeemed during the period | C39: 22781 | D39: -5863474.4 | E39: -6989064.1
B40: Giá trị vốn phải thanh toán trong kỳ khi đáp ứng lệnh của nhà đầu tư (theo mệnh giá) Net redemption amount during the period (based on par value) | C40: 22782 | D40: -58634744100 | E40: -69890641100
A41: 3 | B41: Quy mô quỹ cuối kỳ (tính theo mệnh giá chứng chỉ quỹ) Fund scale at the end of the period (based on par value) | C41: 2279 | D41: 229208425100 | E41: 244762721400
B42: Tổng giá trị thị trường của quỹ đang lưu hành cuối kỳ (theo mệnh giá) Total value of outstanding Fund Certificate at the end of the period (based on par value) | C42: 2280 | D42: 229208425100 | E42: 244762721400
B43: Tổng số lượng chứng chỉ quỹ đang lưu hành cuối kỳ Total number of outstanding Fund Certificate at the end of the period | C43: 2281 | D43: 22920843 | E43: 24476272
A44: 4 | B44: Tỷ lệ nắm giữ chứng chỉ quỹ của công ty quản lý quỹ và người có liên quan cuối kỳ Fund Management Company and related parties' ownership ratio at the end of the period | C44: 2282 | D44: 0.0033308038 | E44: 0.00095601119
A45: 5 | B45: Tỷ lệ nắm giữ chứng chỉ quỹ của 10 nhà đầu tư lớn nhất cuối kỳ Top 10 investors' ownership ratio at the end of the period | C45: 2283 | D45: 0.2228 | E45: 0.2527
A46: 6 | B46: Tỷ lệ nắm giữ chứng chỉ quỹ của nhà đầu tư nước ngoài cuối kỳ Foreign investors' ownership ratio at the end of the period | C46: 2284 | D46: 0.138 | E46: 0.12275621
A47: 7 | B47: Số nhà đầu tư tham gia vào quỹ, kể cả giao dịch ký danh Number of investors of the Fund at the end of the period | C47: 22841 | D47: 26096 | E47: 22003
A48: 8 | B48: Giá trị tài sản ròng trên một đơn vị quỹ cuối kỳ Net asset value per Fund Certificate at the end of period | C48: 2285 | D48: 65722.27 | E48: 51531.77
A49: 9 | B49: Giá trị thị trường trên một chứng chỉ quỹ/cổ phiếu cuối kỳ (không áp dụng) Market price per fund certificates at the end of period (not applicable) | C49: 2288
A50: Ghi chú: Note:
A51: (*) Bắt đầu từ năm 2023, chỉ tiêu Tỷ lệ chi phí /Giá trị tài sản ròng trung bình trong kỳ (%) được tính trên cơ sở Tỷ lệ chi phí hoạt động/ Giá trị tài sản ròng trung bình trong kỳ (%). Since 2023, Item Expense/Average NAV (%) is calculated based on Operating Expense/Average NAV for reporting period.
A52: (**) Các chỉ tiêu từ 1 đến 7 của "Chỉ tiêu về hiệu quả hoạt động" đã được điều chỉnh để phản ánh số liệu trên cơ sở hoạt động tròn năm bằng cách nhân các chỉ tiêu này với 12 (đối với báo cáo tháng), 4 (đối với báo cáo quý), 2 (đối với báo cáo bán niên), 1 (đối với báo cáo năm). All Indicator starting from number 1 to 7 of "Investment performance indicators" are annualized to reflect a rate that is based on a full year operation by multiplying these indicators with 12 (monthly report) or 4 (quarterly report) or 2 (semi-annual report) or 1 (annual report). (***) Không tính đến giá trị cam kết của các hợp đồng tương lai chỉ số. Excluding the committed value of the Index Futures contracts.
A53: =TONGQUAN!C16 -> Đại diện có thẩm quyền của Ngân hàng giám sát | D53: =TONGQUAN!F16 -> Đại diện có thẩm quyền của Công ty quản lý Quỹ
A54: =TONGQUAN!C17 -> Authorised Representative of Supervisory Bank | D54: =TONGQUAN!F17 -> Authorised Representative of Fund Management Company
A64: =TONGQUAN!C19 -> Ngân hàng TNHH MTV Standard Chartered (Việt Nam) | D64: =TONGQUAN!F19 -> Công ty Cổ phần Quản lý Quỹ Đầu tư Dragon Capital Việt Nam
A65: =TONGQUAN!C20 -> Vũ Quang Phan | D65: =TONGQUAN!F20 -> Lê Hoàng Anh
A66: Phó phòng Dịch vụ nghiệp vụ Giám sát Quỹ | D66: =TONGQUAN!F21 -> Quyền Giám đốc nghiệp vụ hỗ trợ đầu tư

Sheet ThongKePhiGiaoDich_06145
A1: Phụ lục XXVI. Mẫu báo cáo về hoạt động của Quỹ Appendix XXVI. Report on Fund's Operation
A2: (Ban hành kèm theo Thông tư số 98/2020/TT-BTC ngày 16 tháng 11 năm 2020 của Bộ trưởng Bộ Tài Chính về hướng dẫn hoạt động và quản lý quỹ đầu tư chứng khoán) (Issued in association with Circular 98/2020/TT-BTC dated 16 November 2020 of the Minister of Finance on guiding the operation and management of the securities investment funds)
A3: BÁO CÁO VỀ HOẠT ĐỘNG ĐẦU TƯ REPORT ON INVESTMENT ACTIVITIES
A5: Năm 2023 / Year 2023
A7: Tên Công ty quản lý quỹ: | D7: Công ty Cổ phần Quản lý Quỹ Đầu tư Dragon Capital Việt Nam
A8: Fund Management Company | D8: Dragon Capital Vietfund Management Joint Stock Company
A9: Tên ngân hàng giám sát: | D9: Ngân hàng TNHH Một thành viên Standard Chartered (Việt Nam)
A10: Supervising bank: | D10: Standard Chartered Bank (Vietnam) Limited
A11: Tên Quỹ: | D11: Quỹ Đầu tư Chứng khoán Năng động DC
A12: Fund name: | D12: DC Dynamic Securities Fund(DCDS)
A13: Ngày lập báo cáo: | D13: Ngày 08 tháng 03 năm 2024
A14: Reporting Date: | D14: 08 Mar 2024
A16: A. | B16: BÁO CÁO CHUNG VỀ HOẠT ĐỘNG ĐẦU TƯ CỦA QUỸ/GENERAL INFORMATION ON FUND'S INVESTMENT ACTIVITIES
A17: VI | B17: THỐNG KÊ PHÍ GIAO DỊCH /REPORT ON BROKER FEE
A18: Số thứ tự No. | B18: Tên (mã) các công ty chứng khoán (có giá trị giao dịch vượt quá 5% tổng giá trị giao dịch kỳ báo cáo) Name (code) of securities companies (with transaction value exceeding 5% of the Fund’s total transaction value for the year) | C18: Quan hệ với công ty quản lý quỹ Relationship with the Fund Management Company | D18: Tỷ lệ giao dịch của quỹ/công ty tại từng công ty chứng khoán | G18: Giá dịch vụ giao dịch bình quân Average transaction fee rate | H18: Giá dịch vụ giao dịch bình quân trên thị trường Market average transaction fee rate
D19: Giá trị giao dịch trong kỳ báo cáo của quỹ Fund’s transaction value for the year with each securities company | E19: Tổng giá trị giao dịch trong kỳ báo cáo của quỹ Fund’s total transaction value for the year | F19: Tỷ lệ giao dịch của quỹ qua công ty chứng khoán trong kỳ báo cáo Percentage of the Fund’s total transaction value for the year
A20: (1) | B20: (2) | C20: (3) | D20: (4) | E20: (5) | F20: (6) = (4)/(5)% | G20: (7) | H20: (8)
A21: ... | B21: ... | C21: ... | D21: ... | E21: ... | F21: ... | G21: ... | H21: ...
A22: 1 | B22: Giao dịch chứng khoán không niêm yết Unlisted securities trading | C22: Không/No | D22: 136140576590 | E22: 12105504931135 | F22: 0.011246171
A23: 2 | B23: Công ty Cổ phần Chứng khoán Vietcap Vietcap Securities Joint Stock Company | C23: Không/No | D23: 1233595092150 | E23: 12105504931135 | F23: 0.10190365 | G23: 0.0015 | H23: 0.00% - 0.45%
A24: 3 | B24: Công ty Cổ phần Chứng khoán SSI SSI Securities Corporation | C24: Không/No | D24: 911717778000 | E24: 12105504931135 | F24: 0.075314312 | G24: 0.0015 | H24: 0.00% - 0.45%
A25: 4 | B25: Công ty cổ phần chứng khoán Thành phố Hồ Chí Minh Ho Chi Minh City Securities Corporation | C25: Không/No | D25: 2779604721100 | E25: 12105504931135 | F25: 0.22961493 | G25: 0.001499 | H25: 0.00% - 0.45%
A26: 5 | B26: Công ty cổ phần chứng khoán Rồng Việt Viet Dragon Securities Corporation | C26: Không/No | D26: 894385462000 | E26: 12105504931135 | F26: 0.073882541 | G26: 0.0015 | H26: 0.00% - 0.45%
A27: 6 | B27: Công ty cổ phần chứng khoán Bảo Việt Bao Viet Securities Joint Stock Company | C27: Không/No | D27: 4170778654150 | E27: 12105504931135 | F27: 0.3445357 | G27: 0.0015 | H27: 0.00% - 0.45%
A28: 7 | B28: Công ty cổ phần chứng khoán KIS Việt Nam KIS Vietnam Securities Corporation | C28: Không/No | D28: 1979282647145 | E28: 12105504931135 | F28: 0.16350269 | G28: 0.000612 | H28: 0.00% - 0.45%
B29: Tổng/Total | D29: 12105504931135 | E29: 12105504931135 | F29: 1
A32: Giao dịch chứng khoán không niêm yết bao gồm cổ phiếu chưa niêm yết, trái phiếu chưa niêm yết, chứng chỉ tiền gửi và giao dịch ngoài sàn. Unlisted securities trading includes unlisted equities, unlisted bonds. certificates of deposits and trade off exchange.
A35: Đại diện có thẩm quyền của Ngân hàng giám sát | G35: Đại diện có thẩm quyền của Công ty quản lý Quỹ
A36: Authorised Representative of Supervisory Bank | G36: Authorised Representative of Fund Management Company
A48: Ngân hàng TNHH MTV Standard Chartered (Việt Nam) | G48: Công ty Cổ phần Quản lý Quỹ Đầu tư Dragon Capital Việt Nam
A49: Vũ Quang Phan | G49: Lê Hoàng Anh
A50: Phó phòng Dịch vụ nghiệp vụ Giám sát Quỹ | G50: Quyền Giám đốc nghiệp vụ hỗ trợ đầu tư

Sheet BCHoatDongVay_06026
A1: Phụ lục XXVI. Mẫu báo cáo về hoạt động của Quỹ Appendix XXVI. Report on Fund's Operation
A2: (Ban hành kèm theo Thông tư số 98/2020/TT-BTC ngày 16 tháng 11 năm 2020 của Bộ trưởng Bộ Tài Chính về hướng dẫn hoạt động và quản lý quỹ đầu tư chứng khoán) (Issued in association with Circular 98/2020/TT-BTC dated 16 November 2020 of the Minister of Finance on guiding the operation and management of the securities investment funds)
A3: BÁO CÁO HOẠT ĐỘNG ĐẦU TƯ CỦA QUỸ MỞ REPORT ON OPEN ENDED FUND'S INVESTMENT ACTIVITIES
A5: =TONGQUAN!C2 -> Năm 2023 / Year 2023
A7: Tên Công ty quản lý quỹ: | G7: =TONGQUAN!D5 -> Công ty Cổ phần Quản lý Quỹ Đầu tư Dragon Capital Việt Nam
A8: Fund Management Company: | G8: =TONGQUAN!D6 -> Dragon Capital Vietfund Management Joint Stock Company
A9: Tên ngân hàng giám sát: | G9: =TONGQUAN!D7 -> Ngân hàng TNHH Một thành viên Standard Chartered (Việt Nam)
A10: Supervising bank: | G10: =TONGQUAN!D8 -> Standard Chartered Bank (Vietnam) Limited
A11: Tên Quỹ: | G11: =TONGQUAN!D9 -> Quỹ Đầu tư Chứng khoán Năng động DC
A12: Fund name: | G12: =TONGQUAN!D10 -> DC Dynamic Securities Fund(DCDS)
A13: Ngày lập báo cáo: | G13: =TONGQUAN!D11 -> Ngày 08 tháng 03 năm 2024
A14: Reporting Date: | G14: =TONGQUAN!D12 -> 08 Mar 2024
A15: A. | B15: BÁO CÁO CHUNG VỀ HOẠT ĐỘNG ĐẦU TƯ CỦA QUỸ/GENERAL INFORMATION ON FUND'S INVESTMENT ACTIVITIES
A16: IV | B16: BÁO CÁO HOẠT ĐỘNG VAY, GIAO DỊCH MUA BÁN LẠI / REPORT ON BORROWING OPERATION, REPO/REVERSE REPO TRANSACTIONS
A17: STT No. | B17: Nội dung hoạt động (nên chi tiết theo mục tiêu và đối tác) Description | C17: Đối tác Counterparty | D17: Mục tiêu/ Tài sản đảm bảo Collateral | E17: Kỳ hạn Term | F17: Giá trị khoản vay hoặc khoản cho vay Amount | G17: Thời điểm giao dịch As at transaction date | I17: Thời điểm báo cáo As at reporting date
G18: Ngày tháng năm Date | H18: Tỷ lệ giá trị hợp đồng/giá trị tài sản ròng của quỹ/công ty (%) Balance/NAV (%) | I18: Ngày tháng năm Date | J18: Tỷ lệ giá trị hợp đồng/ giá trị tài sản ròng của quỹ/ công ty (%) Balance/NAV (%)
A19: 1 | B19: Các khoản vay tiền (nêu chi tiết từng hợp đồng)
A20: ... | B20: ... | C20: ... | D20: ... | E20: ... | F20: ... | G20: ... | H20: ... | I20: ... | J20: ...
A21: I | B21: Tổng giá trị các khoản vay tiền/giá trị tài sản ròng | F21: 0 | H21: 0 | J21: 0
A22: 2 | B22: Hợp đồng Repo (nêu chi tiết từng hợp đồng)
A23: ... | B23: ... | C23: ... | D23: ... | E23: ... | F23: ... | G23: ... | H23: ... | I23: ... | J23: ...
A24: II | B24: Tổng giá trị các hợp đồng Repo/giá trị tài sản ròng | F24: 0 | H24: 0 | J24: 0
A25: A | B25: Tổng giá trị các khoản vay/giá trị tài sản ròng (=I+II) | F25: 0 | H25: 0 | J25: 0
A26: 3 | B26: Cho vay chứng khoán (nêu chi tiết từng hợp đồng)
A27: ... | B27: ... | C27: ... | D27: ... | E27: ... | F27: ... | G27: ... | H27: ... | I27: ... | J27: ...
A28: III | B28: Tổng giá trị các hợp đồng/giá trị tài sản ròng | F28: 0 | H28: 0 | J28: 0
A29: 4 | B29: Hợp đồng Reverse Repo (nêu chi tiết từng hợp đồng)
A30: ... | B30: ... | C30: ... | D30: ... | E30: ... | F30: ... | G30: ... | H30: ... | I30: ... | J30: ...
A31: IV | B31: Tổng giá trị các hợp đồng/ giá trị tài sản ròng | F31: 0 | H31: 0 | J31: 0
A32: B | B32: Tổng giá trị các khoản cho vay/giá trị tài sản ròng (=III + IV) | F32: 0 | H32: 0 | J32: 0
A33: Đại diện có thẩm quyền của Ngân hàng giám sát | I33: Đại diện có thẩm quyền của Công ty quản lý Quỹ
A34: Authorised Representative of Supervisory Bank | I34: Authorised Representative of Fund Management Company
A40: Ngân hàng TNHH MTV Standard Chartered (Việt Nam) | I40: Công ty Cổ phần Quản lý Quỹ Đầu tư Dragon Capital Việt Nam
A41: Vũ Quang Phan | I41: Lê Hoàng Anh
A42: Phó phòng Dịch vụ nghiệp vụ Giám sát Quỹ | I42: Quyền Giám đốc nghiệp vụ hỗ trợ đầu tư
