Workbook
Name addlogo: INDEX(LogoFMS!$C$3:$C$76,MATCH(LogoFMS!$D$1,LogoFMS!$A$3:$A$76,0))

Sheet TONGQUAN
A1: Kỳ báo cáo: | C1: Tại ngày 30 tháng 09 năm 2024 / As at 30 Sep 2024
C2: Quý III năm 2024 / Quarter III 2024
A4: Thông tin chung:
C5: Tên Công ty quản lý quỹ: | D5: Công ty Cổ phần Quản lý Quỹ Đầu tư Dragon Capital Việt Nam
C6: Fund Management Company: | D6: Dragon Capital Vietfund Management Joint Stock Company
C7: Tên ngân hàng giám sát: | D7: Ngân hàng TNHH Một thành viên Standard Chartered (Việt Nam)
C8: Supervising bank: | D8: Standard Chartered Bank (Vietnam) Limited
C9: Tên Quỹ: | D9: Quỹ Đầu tư Chứng khoán Năng động DC
C10: Fund name: | D10: DC Dynamic Securities Fund (DCDS)
C11: Ngày lập báo cáo: | D11: Ngày 07 tháng 10 năm 2024
C12: Reporting Date: | D12: 07 Oct 2024
A14: Người ký báo cáo:
C16: Đại diện có thẩm quyền của Ngân hàng giám sát | F16: Đại diện có thẩm quyền của Công ty quản lý Quỹ
C17: Authorised Representative of Supervisory Bank | F17: Authorised Representative of Fund Management Company
C19: Ngân hàng TNHH MTV Standard Chartered (Việt Nam) | F19: =D5 -> Công ty Cổ phần Quản lý Quỹ Đầu tư Dragon Capital Việt Nam
C20: Vũ Quang Phan | F20: Lê Hoàng Anh
C21: Phó phòng Dịch vụ nghiệp vụ giám sát Quỹ | F21: Quyền Giám đốc nghiệp vụ hỗ trợ đầu tư

Sheet BCTaiSan_06027
A1: Phụ lục XXVI. Mẫu báo cáo về hoạt động của Quỹ Appendix XXVI. Report on Fund's Operation
A2: (Ban hành kèm theo Thông tư số 98/2020/TT-BTC ngày 16 tháng 11 năm 2020 của Bộ trưởng Bộ Tài Chính về hướng dẫn hoạt động và quản lý quỹ đầu tư chứng khoán) (Issued in association with Circular 98/2020/TT-BTC dated 16 November 2020 of the Minister of Finance on guiding the operation and management of the securities investment funds)
A3: BÁO CÁO HOẠT ĐỘNG ĐẦU TƯ CỦA QUỸ MỞ REPORT ON OPEN ENDED FUND'S INVESTMENT ACTIVITIES
A5: =TONGQUAN!C1 -> Tại ngày 30 tháng 09 năm 2024 / As at 30 Sep 2024
A7: Tên Công ty quản lý quỹ: | C7: =TONGQUAN!D5 -> Công ty Cổ phần Quản lý Quỹ Đầu tư Dragon Capital Việt Nam
A8: Fund Management Company: | C8: =TONGQUAN!D6 -> Dragon Capital Vietfund Management Joint Stock Company
A9: Tên ngân hàng giám sát: | C9: =TONGQUAN!D7 -> Ngân hàng TNHH Một thành viên Standard Chartered (Việt Nam)
A10: Supervising bank: | C10: =TONGQUAN!D8 -> Standard Chartered Bank (Vietnam) Limited
A11: Tên Quỹ: | C11: =TONGQUAN!D9 -> Quỹ Đầu tư Chứng khoán Năng động DC
A12: Fund name: | C12: =TONGQUAN!D10 -> DC Dynamic Securities Fund (DCDS)
A13: Ngày lập báo cáo: | C13: =TONGQUAN!D11 -> Ngày 07 tháng 10 năm 2024
A14: Reporting Date: | C14: =TONGQUAN!D12 -> 07 Oct 2024
A16: A. | B16: BÁO CÁO CHUNG VỀ HOẠT ĐỘNG ĐẦU TƯ CỦA QUỸ/GENERAL INFORMATION ON FUND'S INVESTMENT ACTIVITIES
A17: I | B17: BÁO CÁO VỀ TÀI SẢN / ASSET REPORT
A18: STT No | B18: Nội dung Indicator | C18: Mã chỉ tiêu Code | D18: Ngày 30 tháng 09 năm 2024 As at 30 Sep 2024 | E18: Ngày 30 tháng 06 năm 2024 As at 30 Jun 2024 | F18: %/cùng kỳ năm trước %/against last year
A19: I | B19: TÀI SẢN ASSETS | C19: 2200
A20: I.1 | B20: Tiền và các khoản tương đương tiền Cash and Cash Equivalents | C20: 2201 | D20: 58966760393 | E20: 128013039383 | F20: 1.11824
B21: Tiền Cash | C21: 2202
A22: ... | B22: ... | C22: ... | D22: ... | E22: ... | F22: ...
B23: Tiền gửi ngân hàng Cash at bank | C23: 2203 | D23: 58966760393 | E23: 128013039383 | F23: 1.11824
A24: ... | B24: ... | C24: ... | D24: ... | E24: ... | F24: ...
B25: Tiền gửi của nhà đầu tư cho hoạt động mua chứng chỉ quỹ Cash at bank for Fund's subscription | C25: 2203.1 | D25: 8253542436 | E25: 25116978132 | F25: 3.5063492
B26: Tiền phải trả cho Nhà đầu tư về mua lại chứng chỉ quỹ Cash at bank for Fund's redemption | C26: 2203.2 | D26: 151980129 | E26: 158380272 | F26: 0.30780636
B27: Tiền gửi ngân hàng cho hoạt động của Quỹ Cash at bank for Fund's operation | C27: 2203.3 | D27: 50561237828 | E27: 102737680979 | F27: 1.0135739
B28: Tiền gửi ký quỹ cho hoạt động đầu tư chứng khoán phái sinh Margin account for trading derivatives | C28: 2203.4 | D28: 0 | E28: 0
B29: Tiền, tương đương tiền Cash, cash equivalents | C29: 2203.5 | D29: 0 | E29: 0
A30: I.2 | B30: Các khoản đầu tư (kê chi tiết) Investments | C30: 2205 | D30: 2536149865950 | E30: 1900572223600 | F30: 1.7901436
A31: ... | B31: ... | C31: ... | D31: ... | E31: ... | F31: ...
B32: Cổ phiếu, chứng chỉ quỹ niêm yết Listed Shares, fund certificates | C32: 2205.1 | D32: 2535160693950 | E32: 1900572223600 | F32: 1.8344589
B33: Cổ phiếu, chứng chỉ quỹ chưa niêm yết Unlisted Shares, fund certifictes | C33: 2205.2 | D33: 0 | E33: 0
B34: Trái phiếu Bonds | C34: 2205.3 | D34: 0 | E34: 0 | F34: 0
B35: Công cụ thị trường tiền tệ Money market instruments | C35: 2205.4 | D35: 0 | E35: 0
B36: Hợp đồng tiền gửi có kỳ hạn trên ba (03) tháng Deposits with term over three (03) months | C36: 2205.5 | D36: 0 | E36: 0
B37: Quyền mua chứng khoán Investment - Rights | C37: 2205.6 | D37: 989172000 | E37: 0
B38: Hợp đồng tương lai chỉ số Index future contracts | C38: 2205.7 | D38: 0 | E38: 0
B39: Đầu tư khác Other investments | C39: 2205.8 | D39: 0 | E39: 0
B40: Hợp đồng mua lại đảo ngược Reverse repo contracts | C40: 2205.9 | D40: 0 | E40: 0
A41: I.3 | B41: Thu từ cho thuê bất động sản đầu tư (không áp dụng) Receivables from rental of investment property (not applicable) | C41: 2220 | D41: 0 | E41: 0
A42: ... | B42: ... | C42: ... | D42: ... | E42: ... | F42: ...
A43: I.4 | B43: Cổ tức, trái tức được nhận Dividend, Coupon receivables | C43: 2206 | D43: 5195706000 | E43: 4913060000 | F43: 1.2575927
A44: ... | B44: ... | C44: ... | D44: ... | E44: ... | F44: ...
B45: Phải thu cổ tức Dividend receivables | C45: 2206.1 | D45: 5195706000 | E45: 4913060000 | F45: 1.7268768
B46: Phải thu trái tức Coupon receivables | C46: 2206.2 | D46: 0 | E46: 0 | F46: 0
A47: I.5 | B47: Lãi được nhận Interest receivables | C47: 2207 | D47: 0 | E47: 0
A48: ... | B48: ... | C48: ... | D48: ... | E48: ... | F48: ...
B49: Phải thu lãi tiền gửi Interest receivable from bank deposits | C49: 2207.1 | D49: 0 | E49: 0
B50: Phải thu lãi công cụ thị trường tiền tệ Interest receivable from Money market instruments | C50: 2207.2 | D50: 0 | E50: 0
B51: Phải thu lãi hợp đồng mua lại đảo ngược Interest receivable from reverse repo contracts | C51: 2207.3 | D51: 0 | E51: 0
A52: I.6 | B52: Tiền bán bất động sản chờ thu (không áp dụng) Real Estate Proceeds Receivables (not applicale) | C52: 2221 | D52: 0 | E52: 0
A53: ... | B53: ... | C53: ... | D53: ... | E53: ... | F53: ...
A54: I.7 | B54: Tiền bán chứng khoán chờ thu Securities Trading Receivables | C54: 2208 | D54: 48528246100 | E54: 43306359800 | F54: 1.4294363
A55: ... | B55: ... | C55: ... | D55: ... | E55: ... | F55: ...
A56: I.8 | B56: Các khoản phải thu khác Other Receivables | C56: 2210 | D56: -866400000 | E56: -866351600 | F56: 1
A57: ... | B57: ... | C57: ... | D57: ... | E57: ... | F57: ...
B58: Dự phòng giảm giá tài sản nhận thế chấp Impairment of devaluation of pledged assets | C58: 2210.1 | D58: 0 | E58: 0
B59: Dự phòng nợ phải thu khó đòi Provision for doubtful debt | C59: 2210.2 | D59: -866400000 | E59: -866400000 | F59: 1
B60: Các khoản phải thu khác Other Receivables | C60: 2210.3 | D60: 0 | E60: 48400
A61: I.9 | B61: Các tài sản khác Other Assets | C61: 2211 | D61: 36454571 | E61: 47259108 | F61: 3.0762902
A62: ... | B62: ... | C62: ... | D62: ... | E62: ... | F62: ...
A63: I.10 | B63: TỔNG TÀI SẢN TOTAL ASSETS | C63: 2212 | D63: 2648010633014 | E63: 2075985590291 | F63: 1.7575046
A64: II | B64: NỢ LIABILITIES | C64: 2213
A65: II.1 | B65: Tiền phải thanh toán mua bất động sản (không áp dụng) Real Estate Trading Payables (not applicable) | C65: 2222 | D65: 0 | E65: 0
A66: ... | B66: ... | C66: ... | D66: ... | E66: ... | F66: ...
A67: II.2 | B67: Tiền phải thanh toán mua chứng khoán Securities Trading Payables | C67: 2214 | D67: 47045700000 | E67: 65419005000 | F67: 1.3902112
A68: ... | B68: ... | C68: ... | D68: ... | E68: ... | F68: ...
A69: II.3 | B69: Các khoản phải trả khác Other Payables | C69: 2215 | D69: 81140010559 | E69: 37278526187 | F69: 11.377169
A70: ... | B70: ... | C70: ... | D70: ... | E70: ... | F70: ...
B71: Phải trả nhà đầu tư Payables to investors | C71: 2215.1 | D71: 75946595660 | E71: 32673080526 | F71: 20.080029
B72: Phải trả cho nhà đầu tư chờ mua chứng chỉ quỹ Subscription Pending allotment | C72: 2215.1.1 | D72: 8253542436 | E72: 25116978132 | F72: 3.5063492
B73: Phải trả nhà đầu tư trên tài sản giữ hộ Payables to investors for investment bought on behalf | C73: 2215.1.2 | D73: 0 | E73: 0
B74: Phải trả nhà đầu tư trên cổ tức đã thu Payables to investors for collected dividend | C74: 2215.1.3 | D74: 0 | E74: 0
B75: Phải trả cho Nhà đầu tư về mua lại chứng chỉ quỹ Redemption payable to investors | C75: 2215.1.4 | D75: 67693053224 | E75: 7556102394 | F75: 47.393787
B76: Thuế và các khoản phải nộp Nhà nước Tax payables and obligations to the State Budget | C76: 2215.2 | D76: 125701915 | E76: 158879648 | F76: 4.5102872
B77: Phải trả phí phát hành, mua lại chứng chỉ quỹ cho Đại lý phân phối và Công ty quản lý quỹ Subscription and Redemption fee payable to distributors and Fund Management Company | C77: 2215.3 | D77: 325061456 | E77: 437404346 | F77: 1.3619853
B78: Phải trả thu nhập cho nhà đầu tư Income payable to investors | C78: 2215.4 | D78: 39925000 | E78: 39925000 | F78: 1
B79: Phải trả thù lao Ban đại diện quỹ Remuneration Payable to Fund's Board of Representatives | C79: 2215.5 | D79: 19248634 | E79: 16232240 | F79: 0.91767915
B80: Phải trả phí quản lý cho công ty quản lý quỹ Management fee payable | C80: 2215.6 | D80: 3926981906 | E80: 3187386361 | F80: 1.6086917
B81: Phải trả phí quản trị quỹ Fund Administration fee payable | C81: 2215.7 | D81: 55380513 | E81: 44950321 | F81: 1.6086916
B82: Phải trả phí giám sát Supervisory service fee payable | C82: 2215.8 | D82: 88608823 | E82: 71920514 | F82: 1.6086918
B83: Phí giao dịch Transaction fee | C83: 2215.9 | D83: 151294122 | E83: 187002435 | F83: 1.1929796
B84: Phải trả phí môi giới Brokerage fee payable | C84: 2215.9.1 | D84: 151294122 | E84: 187002435 | F84: 1.1929796
B85: Phải trả phí phát hành thanh toán bù trừ chứng khoán Clearing Settlement fee payable | C85: 2215.9.2 | D85: 0 | E85: 0
B86: Trích trước phí lưu ký tài sản Quỹ mở Accrued expense for Custodian fee | C86: 2215.10 | D86: 157453475 | E86: 130682282 | F86: 1.76569
B87: Phí lưu ký - bảo quản tài sản Custodian service - Safe Custody Fee | C87: 2215.10.1 | D87: 80553475 | E87: 65382282 | F87: 1.6086917
B88: Phí lưu ký - giao dịch chứng khoán Custodian service - Transaction fee | C88: 2215.10.2 | D88: 65900000 | E88: 54300000 | F88: 2.3451957
B89: Phí lưu ký cho chứng khoán cơ sở, phí quản lý vị thế và tài sản phái sinh trả cho VSDC Custodian service - Depository fee, Position and Margin management fee paid to VSDC | C89: 2215.10.3 | D89: 11000000 | E89: 11000000 | F89: 1
B90: Phải trả phí kiểm toán Audit fee payable | C90: 2215.11 | D90: 51880000 | E90: 100100000 | F90: 1.0458251
B91: Phải trả phí họp đại hội thường niên General meeting expense payable | C91: 2215.12 | D91: 25381335 | E91: 5758790
B92: Phải trả phí báo cáo thường niên Annual report fee payable | C92: 2215.13 | D92: 0 | E92: 0
B93: Phải trả phí dịch vụ đại lý chuyển nhượng Transfer Agency fee payable | C93: 2215.14 | D93: 13200000 | E93: 13200000 | F93: 1
B94: Dự chi phí tính giá trị tài sản ròng tham chiếu (iNAV) cho HOSE Service fee payable to HOSE for calculating iNAV | C94: 2215.15 | D94: 0 | E94: 0
B95: Dự chi phí cấp quyền sử dụng chỉ số cho HOSE Authorising index service fee payable to HOSE | C95: 2215.16 | D95: 0 | E95: 0
B96: Phải trả khác Other payables | C96: 2215.17 | D96: 213297720 | E96: 212003724 | F96: 1.0024152
B97: Phải trả phí báo giá Price feed fee payable | C97: 2215.17.1 | D97: 23500000 | E97: 23500000 | F97: 1
B98: Trích trước phí công tác, họp của ban đại diện Accrued expense for Fund's Board of Representatives travelling, meeting | C98: 2215.17.2 | D98: 0 | E98: 0
B99: Trích trước phí quản lý thường niên trả UBCKNN Accrued expense for Annual Management Fee pay to SSC | C99: 2215.17.3 | D99: 5614754 | E99: 3729508 | F99: 1.0009207
B100: Phải trả khác Other payables | C100: 2215.17.4 | D100: 184182966 | E100: 184774216 | F100: 1.0027698
B101: Vay ngắn hạn - hợp đồng repo Short-term loans - Repo contracts | C101: 2215.18 | D101: 0 | E101: 0
B102: Gốc hợp đồng repo Principal of repo contracts | C102: 2215.18.1 | D102: 0 | E102: 0
B103: Trích trước lãi vay ngắn hạn Accrued Interest Expense | C103: 2215.18.2 | D103: 0 | E103: 0
...

Sheet BCKetQuaHoatDong_06028
A1: Phụ lục XXVI. Mẫu báo cáo về hoạt động của Quỹ Appendix XXVI. Report on Fund's Operation
A2: (Ban hành kèm theo Thông tư số 98/2020/TT-BTC ngày 16 tháng 11 năm 2020 của Bộ trưởng Bộ Tài Chính về hướng dẫn hoạt động và quản lý quỹ đầu tư chứng khoán) (Issued in association with Circular 98/2020/TT-BTC dated 16 November 2020 of the Minister of Finance on guiding the operation and management of the securities investment funds)
A3: BÁO CÁO HOẠT ĐỘNG ĐẦU TƯ CỦA QUỸ MỞ REPORT ON OPEN ENDED FUND'S INVESTMENT ACTIVITIES
A5: Quý III năm 2024 / Quarter III 2024
A7: Tên Công ty quản lý quỹ: | C7: Công ty Cổ phần Quản lý Quỹ Đầu tư Dragon Capital Việt Nam
A8: Fund Management Company: | C8: Dragon Capital Vietfund Management Joint Stock Company
A9: Tên ngân hàng giám sát: | C9: Ngân hàng TNHH Một thành viên Standard Chartered (Việt Nam)
A10: Supervising bank: | C10: Standard Chartered Bank (Vietnam) Limited
A11: Tên Quỹ: | C11: Quỹ Đầu tư Chứng khoán Năng động DC
A12: Fund name: | C12: DC Dynamic Securities Fund (DCDS)
A13: Ngày lập báo cáo: | C13: Ngày 07 tháng 10 năm 2024
A14: Reporting Date: | C14: 07 Oct 2024
A16: A. | B16: BÁO CÁO CHUNG VỀ HOẠT ĐỘNG ĐẦU TƯ CỦA QUỸ/GENERAL INFORMATION ON FUND'S INVESTMENT ACTIVITIES
A17: II | B17: BÁO CÁO KẾT QUẢ HOẠT ĐỘNG / PROFIT AND LOSS REPORT
A18: STT No | B18: Nội dung Indicator | C18: Mã chỉ tiêu Code | D18: Quý III năm 2024 Quarter III 2024 | E18: Quý II năm 2024 Quarter II 2024 | F18: Lũy kế từ đầu năm Accumulated from beginning of year
A19: I | B19: Thu nhập từ hoạt động đầu tư Income from Investment Activities | C19: 2220 | D19: 9522369569 | E19: 17538739958 | F19: 29158759707
A20: 1 | B20: Thu từ bất động sản cho thuê (không áp dụng) Income from rental property (not applicable) | C20: 2223 | D20: 0 | E20: 0 | F20: 0
A21: ... | B21: ... | C21: ... | D21: ... | E21: … | F21: …
A22: 2 | B22: Cổ tức, trái tức được nhận Dividend income, interest income from bonds | C22: 2221 | D22: 9435931600 | E22: 17484376500 | F22: 28977347862
A23: ... | B23: ... | C23: ... | D23: ... | E23: … | F23: …
B24: Cổ tức được nhận Dividends income | C24: 2221.1 | D24: 9435931600 | E24: 17484376500 | F24: 28932964300
B25: Trái tức được nhận Interest income from bonds | C25: 2221.2 | D25: 0 | E25: 0 | F25: 44383562
A26: 3 | B26: Lãi được nhận Interest income | C26: 2222 | D26: 86437969 | E26: 54363458 | F26: 181411845
A27: ... | B27: ... | C27: ... | D27: ... | E27: ... | F27: ...
B28: Lãi tiền gửi ngân hàng Interest income from bank deposits | C28: 2222.1 | D28: 86437969 | E28: 54363458 | F28: 181411845
B29: Lãi công cụ thị trường tiền tệ Interest income from Money market instruments | C29: 2222.2 | D29: 0 | E29: 0 | F29: 0
B30: Lãi hợp đồng mua lại đảo ngược Interest income from reverse repo contracts | C30: 2222.3 | D30: 0 | E30: 0 | F30: 0
A31: 4 | B31: Các khoản thu nhập khác Other incomes | C31: 2223 | D31: 0 | E31: 0 | F31: 0
A32: ... | B32: ... | C32: ... | D32: ... | E32: ... | F32: ...
B33: Thu nhập khác về đầu tư Other investment incomes | C33: 2223.1 | D33: 0 | E33: 0 | F33: 0
B34: Thu nhập khác Other incomes | C34: 2223.2 | D34: 0 | E34: 0 | F34: 0
B35: Chi phí dự phòng nợ phải thu khó đòi về cổ tức, tiền lãi và xử lý tổn thất nợ phải thu khó đòi về cổ tức, tiền lãi Provision expense for bad debts from dividends, interest income and written off bad debts from dividends, interest income | C35: 2223.3 | D35: 0 | E35: 0 | F35: 0
A36: II | B36: Chi phí Expenses | C36: 2224 | D36: 18412829999 | E36: 15017581534 | F36: 45879279923
A37: 1 | B37: Chi phí quản lý trả cho Công ty quản lý quỹ Management Fee paid to Fund Management Company | C37: 2225 | D37: 11136941564 | E37: 9122657386 | F37: 28057296839
A38: ... | B38: ... | C38: ... | D38: ... | E38: ... | F38: ...
A39: 2 | B39: Chi phí lưu ký, giám sát trả cho Ngân hàng Giám sát/VSDC Custody fee, Supervising fee paid to Supervising Bank/VSDC | C39: 2226 | D39: 711067185 | E39: 561502426 | F39: 1741526013
A40: ... | B40: ... | C40: ... | D40: ... | E40: ... | F40: ...
B41: Chi phí dịch vụ lưu ký - bảo quản tài sản Custodian service - Safe Custody Fee | C41: 2226.1 | D41: 228450085 | E41: 187131429 | F41: 575534294
B42: Chi phí dịch vụ lưu ký - giao dịch chứng khoán Custodian service - Transaction fee | C42: 2226.2 | D42: 194515000 | E42: 136215000 | F42: 431530000
B43: Chi phí dịch vụ lưu ký cho chứng khoán cơ sở, phí quản lý vị thế và tài sản phái sinh trả cho VSDC Custodian service - Depository fee, Position and Margin management fee paid to VSDC | C43: 2226.3 | D43: 36807006 | E43: 32311418 | F43: 101373991
B44: Chi phí giám sát Supervisory fee | C44: 2226.4 | D44: 251295094 | E44: 205844579 | F44: 633087728
A45: 3 | B45: Chi phí quản trị quỹ và các chi phí khác mà công ty quản lý quỹ trả cho tổ chức cung cấp dịch vụ có liên quan Fund Administration Fee, and other fees paid to relevant Fund's service providers | C45: 2227 | D45: 196659432 | E45: 168252864 | F45: 514479830
A46: ... | B46: ... | C46: ... | D46: ... | E46: ... | F46: ...
B47: Chi phí quản trị Quỹ Fund Administration Fee | C47: 2227.1 | D47: 157059432 | E47: 128652864 | F47: 395679830
B48: Chi phí dịch vụ Đại lý Chuyển nhượng Transfer Agency Fee | C48: 2227.2 | D48: 39600000 | E48: 39600000 | F48: 118800000
A49: 4 | B49: Chi phí dịch vụ quản lý bất động sản (không áp dụng) Real Estate Management Service fee (not applicable) | C49: 2231 | D49: 0 | E49: 0 | F49: 0
A50: ... | B50: ... | C50: ... | D50: ... | E50: ... | F50: ...
A51: 5 | B51: Chi phí dịch vụ định giá bất động sản (không áp dụng) Real estate valuation service fees (not applicable) | C51: 2232 | D51: 0 | E51: 0 | F51: 0
A52: ... | B52: ... | C52: ... | D52: ... | E52: ... | F52: ...
A53: 6 | B53: Chi phí kiểm toán trả cho tổ chức kiểm toán Audit fee | C53: 2228 | D53: 50600000 | E53: 50050000 | F53: 149189475
A54: ... | B54: ... | C54: ... | D54: ... | E54: ... | F54: ...
A55: 7 | B55: Chi phí dịch vụ tư vấn pháp lý, dịch vụ báo giá và các dịch vụ hợp lý khác, thù lao trả cho ban đại diện quỹ Legal consultancy expenses, price feed fee, other valid expenses, remuneration paid to Fund's Board of Representatives | C55: 2229 | D55: 73320948 | E55: 71435746 | F55: 218144080
A56: ... | B56: ... | C56: ... | D56: ... | E56: ... | F56: ...
B57: Thù lao Ban đại diện Quỹ Remuneration of Fund's Board of Representatives | C57: 2229.1 | D57: 39016394 | E57: 37248633 | F57: 115248634
B58: Chi phí cung cấp báo giá chứng khoán Price feed fee | C58: 2229.2 | D58: 23500000 | E58: 23500000 | F58: 70500000
B59: Chi phí dịch vụ tư vấn pháp lý Legal consultancy expenses | C59: 2229.3 | D59: 10804554 | E59: 10687113 | F59: 32395446
A60: 8 | B60: Chi phí dự thảo, in ấn, gửi bản cáo bạch, bản cáo bạch tóm tắt, báo cáo tài chính, xác nhận giao dịch, sao kê tài khoản và các tài liệu khác cho nhà đầu tư; chi phí công bố thông tin của quỹ; chi phí tổ chức họp đại hội nhà đầu tư, ban đại diện quỹ Fee for drafting, printing, distribution of prospectus, summarised prospectus, financial statements, transaction confirmations, account statements and other documents to investors; information disclosure fee; fee for organising annual general meeting, board of representatives meeting | C60: 2230 | D60: 53906672 | E60: 49928790 | F60: 103835462
A61: ... | B61: ... | C61: ... | D61: ... | E61: ... | F61: ...
B62: Chi phí họp Đại hội Quỹ Meeting expenses | C62: 2230.1 | D62: 53906672 | E62: 49928790 | F62: 103835462
B63: Chi phí báo cáo thường niên Annual report expenses | C63: 2230.2 | D63: 0 | E63: 0 | F63: 0
B64: Chi phí họp, công tác của Ban đại diện Fund's Board of Representatives meeting, travelling expenses | C64: 2230.3 | D64: 0 | E64: 0 | F64: 0
B65: Chi phí công bố thông tin của Quỹ Expenses of information disclosure of the Fund | C65: 2230.4 | D65: 0 | E65: 0 | F65: 0
B66: Chi phí thiết kế, in ấn, gửi thư… Designing, printing, posting... expenses | C66: 2230.5 | D66: 0 | E66: 0 | F66: 0
A67: 9 | B67: Chi phí liên quan đến thực hiện các giao dịch tài sản của Quỹ Expenses related to execution of Fund’s asset transactions | C67: 2231 | D67: 6160601852 | E67: 4965593518 | F67: 15007947420
A68: ... | B68: ... | C68: ... | D68: ... | E68: ... | F68: ...
B69: Chi phí môi giới Brokerage fee | C69: 2231.1 | D69: 6142103244 | E69: 4951880670 | F69: 14963027304
B70: Chi phí thanh toán bù trừ Clearing settlement fee | C70: 2231.2 | D70: 18498608 | E70: 13712848 | F70: 44920116
B71: Chi phí khác Other Expenses | C71: 2231.3 | D71: 0 | E71: 0 | F71: 0
A72: 10 | B72: Các loại chi phí khác Other expenses | C72: 2232 | D72: 29732346 | E72: 28160804 | F72: 86860804
A73: ... | B73: ... | C73: ... | D73: ... | E73: ... | F73: ...
B74: Chi phí thiết lập Quỹ Set up Expenses | C74: 2232.1 | D74: 0 | E74: 0 | F74: 0
B75: Phí niêm yết, đăng ký chứng khoán Listing, registration fees | C75: 2232.2 | D75: 0 | E75: 0 | F75: 0
B76: Phí quản lý thường niên trả cho UBCKNN Annual management fee paid to SSC | C76: 2232.3 | D76: 1885246 | E76: 1864754 | F76: 5614754
B77: Phí ngân hàng Bank charges | C77: 2232.4 | D77: 24025100 | E77: 25196050 | F77: 76324050
B78: Chi phí lãi vay Borrowing expense | C78: 2232.5 | D78: 0 | E78: 0 | F78: 0
B79: Chi phí khác Other Expenses | C79: 2232.6 | D79: 3822000 | E79: 0 | F79: 3822000
B80: Phí thực hiện quyền trả cho VSDC Fee paid to VSDC for getting the list of investors | C80: 2232.7 | D80: 0 | E80: 1100000 | F80: 1100000
A81: III | B81: Thu nhập ròng từ hoạt động đầu tư (= I - II) Net Income from Investment Activities (= I - II) | C81: 2233 | D81: -8890460430 | E81: 2521158424 | F81: -16720520216
A82: IV | B82: Lãi / (lỗ) từ hoạt động đầu tư Gain / (Loss) from Investment Activities | C82: 2234 | D82: 64964357850 | E82: 81703239650 | F82: 399575302655
A83: 1 | B83: Lãi (lỗ) thực tế phát sinh từ hoạt động đầu tư hoặc chuyển nhượng bất động sản Realised Gain / (Loss) from disposal of investment or real estate transfer | C83: 2235 | D83: 26012636096 | E83: 141161158133 | F83: 279911200339
A84: 2 | B84: Thay đổi về giá trị của các khoản đầu tư trong kỳ Unrealised Gain / (Loss) due to market price | C84: 2236 | D84: 38951721754 | E84: -59457918483 | F84: 119664102316
A85: V | B85: Thay đổi của giá trị tài sản ròng của Quỹ do các hoạt động đầu tư trong kỳ (III + IV) Change of Net Asset Value of the Fund due to investment activities during the period (= III + IV) | C85: 2237 | D85: 56073897420 | E85: 84224398074 | F85: 382854782439
A86: VI | B86: Giá trị tài sản ròng đầu kỳ Net Asset Value at the beginning of period | C86: 2238 | D86: 1973288059104 | E86: 1790107106040 | F86: 1506409920896
A87: VII | B87: Thay đổi giá trị tài sản ròng của Quỹ trong kỳ, Trong đó Change of Net Asset Value of the Fund during the period, of which | C87: 2239 | D87: 546536863351 | E87: 183180953064 | F87: 1013415001559
A88: 1 | B88: Thay đổi giá trị tài sản ròng của Quỹ do các hoạt động đầu tư của Quỹ trong kỳ Change of Net Asset Value due to investment activities during the period | C88: 2239.1 | D88: 56073897420 | E88: 84224398074 | F88: 382854782439
A89: 2 | B89: Thay đổi giá trị tài sản ròng của Quỹ do việc chi trả lợi tức/ cổ tức của Quỹ cho các nhà đầu tư trong kỳ Change of Net Asset Value due to dividends payment to investors during the period | C89: 2239.2 | D89: 0 | E89: 0 | F89: 0
A90: 3 | B90: Thay đổi giá trị tài sản ròng do phát hành thêm/mua lại chứng chỉ quỹ Change of Net Asset Value due to subscription/redemption during the period | C90: 2239.3 | D90: 490462965931 | E90: 98956554990 | F90: 630560219120
B91: Thay đổi giá trị tài sản ròng do phát hành thêm Chứng chỉ Quỹ Change of Net Asset Value due to subscription during the period | C91: 2239.3.1 | D91: 869806044900 | E91: 496010237277 | F91: 1583724932508
B92: Thay đổi giá trị tài sản ròng do mua lại Chứng chỉ Quỹ Change of Net Asset Value due to redemption during the period | C92: 2239.3.2 | D92: -379343078969 | E92: -397053682287 | F92: -953164713388
A93: VIII | B93: Giá trị tài sản ròng cuối kỳ Net Asset Value at the end of period | C93: 2243 | D93: 2519824922455 | E93: 1973288059104 | F93: 2519824922455
A94: IX | B94: Lợi nhuận bình quân năm (chỉ áp dụng đối với báo cáo năm) Average annual profit (only applicable to annual report) | C94: 2244 | D94: 0 | E94: 0 | F94: 0
B95: Tỷ suất lợi nhuận bình quân năm (chỉ áp dụng đối với báo cáo năm) Average annual rate of return (only applicable to annual report) | C95: 2245 | D95: 0 | E95: 0 | F95: 0
A97: Đại diện có thẩm quyền của Ngân hàng giám sát | E97: Đại diện có thẩm quyền của Công ty quản lý Quỹ
A98: Authorised Representative of Supervisory Bank | E98: Authorised Representative of Fund Management Company
A105: Ngân hàng TNHH MTV Standard Chartered (Việt Nam) | E105: Công ty Cổ phần Quản lý Quỹ Đầu tư Dragon Capital Việt Nam
A106: Vũ Quang Phan | E106: Lê Hoàng Anh
A107: Phó phòng Dịch vụ nghiệp vụ giám sát Quỹ | E107: Quyền Giám đốc nghiệp vụ hỗ trợ đầu tư

Sheet BCDanhMucDauTu_06029
A1: Phụ lục XXVI. Mẫu báo cáo về hoạt động của Quỹ Appendix XXVI. Report on Fund's Operation
A2: (Ban hành kèm theo Thông tư số 98/2020/TT-BTC ngày 16 tháng 11 năm 2020 của Bộ trưởng Bộ Tài Chính về hướng dẫn hoạt động và quản lý quỹ đầu tư chứng khoán) (Issued in association with Circular 98/2020/TT-BTC dated 16 November 2020 of the Minister of Finance on guiding the operation and management of the securities investment funds)
A3: BÁO CÁO HOẠT ĐỘNG ĐẦU TƯ CỦA QUỸ MỞ REPORT ON OPEN ENDED FUND'S INVESTMENT ACTIVITIES
A5: Tại ngày 30 tháng 09 năm 2024 / As at 30 Sep 2024
A7: Tên Công ty quản lý quỹ: | C7: Công ty Cổ phần Quản lý Quỹ Đầu tư Dragon Capital Việt Nam
A8: Fund Management Company: | C8: Dragon Capital Vietfund Management Joint Stock Company
A9: Tên ngân hàng giám sát: | C9: Ngân hàng TNHH Một thành viên Standard Chartered (Việt Nam)
A10: Supervising bank: | C10: Standard Chartered Bank (Vietnam) Limited
A11: Tên Quỹ: | C11: Quỹ Đầu tư Chứng khoán Năng động DC
A12: Fund name: | C12: DC Dynamic Securities Fund (DCDS)
A13: Ngày lập báo cáo: | C13: Ngày 07 tháng 10 năm 2024
A14: Reporting Date: | C14: 07 Oct 2024
A16: A. | B16: BÁO CÁO CHUNG VỀ HOẠT ĐỘNG ĐẦU TƯ CỦA QUỸ/GENERAL INFORMATION ON FUND'S INVESTMENT ACTIVITIES
A17: III | B17: BÁO CÁO DANH MỤC ĐẦU TƯ / INVESTMENT PORTFOLIO REPORT
A18: STT No. | B18: Loại Category | C18: Mã chỉ tiêu Code | D18: Số Lượng Quantity | E18: Giá thị trường hoặc giá trị hợp lý tại ngày báo cáo Market price | F18: Tổng giá trị (Đồng) Value (VND) | G18: Tỷ lệ % Tổng giá trị tài sản của Quỹ % of total asset
A19: I | B19: BẤT ĐỘNG SẢN ĐẦU TƯ (KHÔNG ÁP DỤNG) REAL ESTATE INVESTMENT (NOT APPLICABLE)
B21: TỔNG TOTAL | C21: 2264
A22: II | B22: CỔ PHIẾU NIÊM YẾT, ĐĂNG KÝ GIAO DỊCH, CHỨNG CHỈ QUỸ NIÊM YẾT SHARES LISTED, SHARES REGISTERED FOR TRADING, LISTED FUND CERTIFICATES | C22: 2246
A24: 1 | B24: ACB | C24: 2246.1 | D24: 4357835 | E24: 25750 | F24: 112214251250 | G24: 0.042376813
A25: 2 | B25: ACV | C25: 2246.2 | D25: 141100 | E25: 103800 | F25: 14646180000 | G25: 0.0055310125
A26: 3 | B26: BAF | C26: 2246.3 | D26: 488000 | E26: 21450 | F26: 10467600000 | G26: 0.0039530053
A27: 4 | B27: BID | C27: 2246.4 | D27: 305300 | E27: 49700 | F27: 15173410000 | G27: 0.0057301167
A28: 5 | B28: BMP | C28: 2246.5 | D28: 116800 | E28: 118600 | F28: 13852480000 | G28: 0.0052312781
A29: 6 | B29: BWE | C29: 2246.6 | D29: 167400 | E29: 45400 | F29: 7599960000 | G29: 0.002870064
A30: 7 | B30: CTD | C30: 2246.7 | D30: 143000 | E30: 63800 | F30: 9123400000 | G30: 0.0034453789
A31: 8 | B31: CTG | C31: 2246.8 | D31: 4288226 | E31: 36950 | F31: 158449950700 | G31: 0.059837354
A32: 9 | B32: CTR | C32: 2246.9 | D32: 90800 | E32: 126400 | F32: 11477120000 | G32: 0.0043342424
A33: 10 | B33: DBC | C33: 2246.10 | D33: 1047866 | E33: 29000 | F33: 30388114000 | G33: 0.011475828
A34: 11 | B34: DCM | C34: 2246.11 | D34: 766800 | E34: 38500 | F34: 29521800000 | G34: 0.011148671
A35: 12 | B35: DGC | C35: 2246.12 | D35: 636800 | E35: 115500 | F35: 73550400000 | G35: 0.027775719
... A83: 60 | B83: VTP | C83: 2246.60 | D83: 296800 | E83: 78600 | F83: 23328480000 | G83: 0.0088098136
B84: TỔNG TOTAL | C84: 2247 | F84: 2535160693950 | G84: 0.95738312
A85: III | B85: CỔ PHIẾU CHƯA NIÊM YẾT, ĐĂNG KÝ GIAO DỊCH, CHỨNG CHỈ QUỸ KHÔNG NIÊM YẾT SHARES UNLISTED, UNREGISTERED FOR TRADING, UNLISTED FUND CERTIFICATES | C85: 2248
B87: TỔNG TOTAL | C87: 2249 | F87: 0 | G87: 0
A88: IV | B88: TRÁI PHIẾU BONDS | C88: 2251
A90: 1 | B90: Trái phiếu niêm yết Listed bonds | C90: 2251.1 | F90: 0 | G90: 0
A91: 2 | B91: Trái phiếu chưa niêm yết Unlisted Bonds | C91: 2251.2 | F91: 0 | G91: 0
B92: TỔNG TOTAL | C92: 2252 | F92: 0 | G92: 0
A93: V | B93: CÁC LOẠI CHỨNG KHOÁN KHÁC OTHER SECURITIES | C93: 2253
A95: 1 | B95: Quyền mua chứng khoán Investment - Rights | C95: 2253.1 | F95: 989172000 | G95: 0.00037355288
A96: 1.1 | B96: SSI SECURITIES CORP | C96: 2253.1.1 | D96: 766800 | E96: 1290 | F96: 989172000 | G96: 0.00037355288
A97: 2 | B97: Chi tiết loại hợp đồng phái sinh(*) Index future contracts | C97: 2253.2 | F97: 0 | G97: 0
B98: TỔNG TOTAL | C98: 2254 | F98: 989172000 | G98: 0.00037355288
B99: TỔNG CÁC LOẠI CHỨNG KHOÁN TOTAL TYPES OF SECURITIES | C99: 2255 | F99: 2536149865950 | G99: 0.95775668
A100: VI | B100: CÁC TÀI SẢN KHÁC OTHER ASSETS | C100: 2256
A102: 1 | B102: Cổ tức được nhận Dividend receivables | C102: 2256.1 | F102: 5195706000 | G102: 0.0019621167
A103: 2 | B103: Lãi trái phiếu được nhận Coupon receivables | C103: 2256.2 | F103: 0 | G103: 0
A104: 3 | B104: Lãi tiền gửi và công cụ thị trường tiền tệ được nhận Interest receivables from bank deposits and Money market instruments | C104: 2256.3 | F104: 0 | G104: 0
A105: 4 | B105: Tiền bán chứng khoán chờ thu Outstanding Settlement of sales transactions | C105: 2256.4 | F105: 48528246100 | G105: 0.018326303
A106: 5 | B106: Phải thu cho khoản cổ phiếu hạn chế chờ mua Receivable from AP/Investors on securities on hold of buying | C106: 2256.5 | F106: 0 | G106: 0
A107: 6 | B107: Phải thu khác Other receivables | C107: 2256.6 | F107: -866400000 | G107: -0.00032718902
A108: 7 | B108: Tài sản khác Other assets | C108: 2256.7 | F108: 36454571 | G108: 1.3766777e-05
B109: TỔNG TOTAL | C109: 2257 | F109: 52894006671 | G109: 0.019974998
A110: VII | B110: TIỀN CASH | C110: 2258
A111: 1 | B111: Tiền, tương đương tiền Cash, Cash Equivalent | C111: 2259 | F111: 58966760393 | G111: 0.022268325
A113: 1.1 | B113: Tiền gửi ngân hàng Cash at Bank | C113: 2259.1 | F113: 58966760393 | G113: 0.022268325
A114: 1.2 | B114: Các khoản tương đương tiền Cash Equivalents | C114: 2259.2 | F114: 0 | G114: 0
A115: 2 | B115: Tiền gửi ngân hàng có kỳ hạn trên 3 tháng Deposits with term over three (03) months | C115: 2260 | F115: 0 | G115: 0
A117: 3 | B117: Công cụ thị trường tiền tệ Money market instruments | C117: 2261.1 | F117: 0 | G117: 0
B118: TỔNG TOTAL | C118: 2262 | F118: 58966760393 | G118: 0.022268325
A119: VIII | B119: Tổng giá trị danh mục Total value of portfolio | C119: 2263 | F119: 2648010633014 | G119: 1
A121: Đại diện có thẩm quyền của Ngân hàng giám sát | E121: Đại diện có thẩm quyền của Công ty quản lý Quỹ
A122: Authorised Representative of Supervisory Bank | E122: Authorised Representative of Fund Management Company
A131: Ngân hàng TNHH MTV Standard Chartered (Việt Nam) | E131: Công ty Cổ phần Quản lý Quỹ Đầu tư Dragon Capital Việt Nam
A132: Vũ Quang Phan | E132: Lê Hoàng Anh
A133: Phó phòng Dịch vụ nghiệp vụ giám sát Quỹ | E133: Quyền Giám đốc nghiệp vụ hỗ trợ đầu tư

Sheet BCThuNhap_06203
A1: Mẫu số B01 - QM Báo cáo thu nhập Template B01 - QM Statement of Comprehensive Income
A2: (Ban hành kèm theo Thông tư 198/2012/TT-BTC ngày 15 tháng 11 năm 2012 về chế độ kế toán áp dụng đối với quỹ mở) (Issued in association with Circular 198/2012/TT-BTC dated 15 Nov 2012 on the Accounting Policies for Open-Ended Fund)
A3: BÁO CÁO THU NHẬP STATEMENT OF COMPREHENSIVE INCOME
A5: =TONGQUAN!C2 -> Quý III năm 2024 / Quarter III 2024
A7: Tên Công ty quản lý quỹ: | D7: =TONGQUAN!D5 -> Công ty Cổ phần Quản lý Quỹ Đầu tư Dragon Capital Việt Nam
A8: Fund Management Company: | D8: =TONGQUAN!D6 -> Dragon Capital Vietfund Management Joint Stock Company
A9: Tên ngân hàng giám sát: | D9: =TONGQUAN!D7 -> Ngân hàng TNHH Một thành viên Standard Chartered (Việt Nam)
A10: Supervising bank: | D10: =TONGQUAN!D8 -> Standard Chartered Bank (Vietnam) Limited
A11: Tên Quỹ: | D11: =TONGQUAN!D9 -> Quỹ Đầu tư Chứng khoán Năng động DC
A12: Fund name: | D12: =TONGQUAN!D10 -> DC Dynamic Securities Fund (DCDS)
A13: Ngày lập báo cáo: | D13: =TONGQUAN!D11 -> Ngày 07 tháng 10 năm 2024
A14: Reporting Date: | D14: =TONGQUAN!D12 -> 07 Oct 2024
A16: Chỉ tiêu Indicator | B16: Mã số Code | C16: Thuyết minh Note | D16: Năm 2024 Year 2024 | F16: Năm 2023 Year 2023
D17: =BCKetQuaHoatDong_06028!D18 -> Quý III năm 2024 Quarter III 2024 | E17: Số lũy kế Year-to-date | F17: Quý III năm 2023 Quarter III 2023 | G17: Số lũy kế Year-to-date
A18: I. THU NHẬP, DOANH THU HOẠT ĐỘNG ĐẦU TƯ Investment income | B18: 01 | D18: 74486727419 | E18: 428734062362 | F18: 143622984274 | G18: 342046521513
A19: 1.1. Cổ tức được chia Dividend income | B19: 02 | D19: 9435931600 | E19: 28932964300 | F19: 7489910000 | G19: 15116750000
A20: 1.2. Tiền lãi được nhận Interest income | B20: 03 | D20: 86437969 | E20: 225795407 | F20: 767709555 | G20: 5075035803
A21: Lãi tiền gửi ngân hàng Interest income from bank deposits | B21: 03.1 | D21: 86437969 | E21: 181411845 | F21: 45572569 | G21: 204816417
A22: Lãi công cụ thị trường tiền tệ Interest income from Money market instruments | B22: 03.2 | D22: 0 | E22: 0 | F22: 0 | G22: 0
A23: Lãi trái phiếu Interest income from bonds | B23: 03.3 | D23: 0 | E23: 44383562 | F23: 722136986 | G23: 4870219386
A24: Tiền lãi hợp đồng mua lại đảo ngược được nhận Reverse repo contract interest received | B24: 03.4 | D24: 0 | E24: 0 | F24: 0 | G24: 0
A25: 1.3. Lãi (lỗ) bán các khoản đầu tư Realized gain (losses) from disposal investments | B25: 04 | D25: 26012636096 | E25: 279911200339 | F25: 104057909216 | G25: 169078991963
A26: 1.4. Chênh lệch tăng, giảm đánh giá lại các khoản đầu tư chưa thực hiện Unrealized gain (losses) from investment revaluation | B26: 05 | D26: 38951721754 | E26: 119664102316 | F26: 31307455503 | G26: 152775743747
A27: 1.5. Doanh thu khác Other income | B27: 06 | D27: 0 | E27: 0 | F27: 0 | G27: 0
A28: 1.6. Chênh lệch lãi, lỗ tỷ giá hối đoái đã và chưa thực hiện Realized and unrealized gain (losses) from foreign exchange | B28: 07 | D28: 0 | E28: 0 | F28: 0 | G28: 0
A29: 1.7. Doanh thu khác về đầu tư Other investment income | B29: 08 | D29: 0 | E29: 0 | F29: 0 | G29: 0
... A77: VIII. LỢI NHUẬN KẾ TOÁN SAU THUẾ TNDN PROFIT AFTER TAX (41=30-40) | B77: 41 | D77: 56073897420 | E77: 382854782439 | F77: 132654321739 | G77: 308700096339
A80: Người lập: | B80: Người duyệt:
A93: _______________________________________________ | B93: ___________________________________________ | F93: _______________________________________
A94: Nguyễn Kiều Trúc Ly | B94: Ninh Thị Tuệ Minh | F94: Lê Hoàng Anh
A95: Kế toán Quỹ | B95: Trưởng phòng Kế toán Quỹ | F95: Quyền Giám đốc nghiệp vụ hỗ trợ đầu tư

Sheet Khac_06030
A1: Phụ lục XXVI. Mẫu báo cáo về hoạt động của Quỹ Appendix XXVI. Report on Fund's Operation
A2: (Ban hành kèm theo Thông tư số 98/2020/TT-BTC ngày 16 tháng 11 năm 2020 của Bộ trưởng Bộ Tài Chính về hướng dẫn hoạt động và quản lý quỹ đầu tư chứng khoán) (Issued in association with Circular 98/2020/TT-BTC dated 16 November 2020 of the Minister of Finance on guiding the operation and management of the securities investment funds)
A3: BÁO CÁO HOẠT ĐỘNG ĐẦU TƯ CỦA QUỸ MỞ REPORT ON OPEN ENDED FUND'S INVESTMENT ACTIVITIES
A5: =TONGQUAN!C2 -> Quý III năm 2024 / Quarter III 2024
A7: Tên Công ty quản lý quỹ: | C7: =TONGQUAN!D5 -> Công ty Cổ phần Quản lý Quỹ Đầu tư Dragon Capital Việt Nam
A8: Fund Management Company: | C8: =TONGQUAN!D6 -> Dragon Capital Vietfund Management Joint Stock Company
A9: Tên ngân hàng giám sát: | C9: =TONGQUAN!D7 -> Ngân hàng TNHH Một thành viên Standard Chartered (Việt Nam)
A10: Supervising bank: | C10: =TONGQUAN!D8 -> Standard Chartered Bank (Vietnam) Limited
A11: Tên Quỹ: | C11: =TONGQUAN!D9 -> Quỹ Đầu tư Chứng khoán Năng động DC
A12: Fund name: | C12: =TONGQUAN!D10 -> DC Dynamic Securities Fund (DCDS)
A13: Ngày lập báo cáo: | C13: =TONGQUAN!D11 -> Ngày 07 tháng 10 năm 2024
A14: Reporting Date: | C14: =TONGQUAN!D12 -> 07 Oct 2024
A16: A. | B16: BÁO CÁO CHUNG VỀ HOẠT ĐỘNG ĐẦU TƯ CỦA QUỸ/GENERAL INFORMATION ON FUND'S INVESTMENT ACTIVITIES
A17: V | B17: MỘT SỐ CHỈ TIÊU KHÁC / OTHER INDICATORS
A18: STT No | B18: Chỉ tiêu Indicators | C18: Mã chỉ tiêu Code | D18: Quý III năm 2024 Quarter III 2024 | E18: Quý II năm 2024 Quarter II 2024
A19: I | B19: CÁC CHỈ TIÊU VỀ HIỆU QUẢ HOẠT ĐỘNG INVESTMENT PERFORMANCE INDICATORS | C19: 2264
A20: 1 | B20: Tỷ lệ giá dịch vụ quản lý quỹ trả cho công ty quản lý quỹ/Giá trị tài sản ròng trung bình trong kỳ (%) Management fee paid to the fund management company/Average NAV (%) | C20: 2265 | D20: 0.019608629 | E20: 0.019395561
A21: 2 | B21: Tỷ lệ giá dịch vụ lưu ký, giám sát trả cho Ngân hàng Giám sát/Giá trị tài sản ròng trung bình trong kỳ (%) Custody and supervising fees paid to the Supervisory Bank/Average NAV (%) | C21: 2266 | D21: 0.0011871588 | E21: 0.001125106
A22: 3 | B22: Tỷ lệ chi phí dịch vụ quản trị quỹ, và các chi phí khác mà công ty quản lý quỹ trả cho tổ chức cung cấp dịch vụ có liên quan/Giá trị tài sản ròng của quỹ trung bình trong kỳ (%) Fund admin fee, and other fees paid to relating services providers by the fund management company/Average NAV (%) | C22: 22661 | D22: 0.00041106051 | E22: 0.00042641706
A23: 4 | B23: Chi phí kiểm toán trả cho tổ chức kiểm toán (nếu phát sinh)/Giá trị tài sản ròng trung bình trong kỳ (%) Auditing fee paid to auditing organizations (if any)/Average NAV (%) | C23: 2267 | D23: 8.9090585e-05 | E23: 0.00010641064
A24: 5 | B24: Chi phí trả cho tổ chức quản lý bất động sản/ Giá trị tài sản ròng trung bình trong kỳ (%) (không áp dụng) Fee paid to Real Estate management organisation/ Average NAV (%) (not applicable) | C24: 2286
A25: 6 | B25: Chi phí trả cho doanh nghiệp thẩm định giá bất động sản/Giá trị tài sản ròng trung bình trong kỳ (%) (không áp dụng) Fee paid to Real Estate valuation service provider/ Average NAV (%) (not applicable) | C25: 2287
A26: 7 | B26: Chi phí dịch vụ tư vấn pháp lý, dịch vụ báo giá và các dịch vụ hợp lý khác, thù lao trả cho ban đại diện quỹ/Giá trị tài sản ròng trung bình trong kỳ (%) Legal consultancy, price quotation and other appropriate service fees; remunerations paid to the Board of Representatives/Average NAV (%) | C26: 2268 | D26: 0.00012909498 | E26: 0.00015187859
A27: 8 | B27: Tỷ lệ chi phí /Giá trị tài sản ròng trung bình trong kỳ (%) Expense/Average NAV (%) | C27: 2269 | D27: 0.021455055 | E27: 0.021488824
A28: 9 | B28: Tốc độ vòng quay danh mục trong kỳ (%)/Portfolio turnover rate (%) | C28: 2270 | D28: 3.7473534 | E28: 3.6132804
A29: 10 | B29: Tỷ lệ thu nhập (tính cả thu nhập từ lãi, cổ tức, trái tức, chênh lệch giá)/ Giá trị tài sản ròng (không áp dụng) Income (including interest income, dividend, coupon income and unrealised gain)/ Average NAV (%) (not applicable) | C29: 2287
A30: II | B30: CÁC CHỈ TIÊU KHÁC OTHER INDICATORS | C30: 2272
A31: 1 | B31: Quy mô quỹ đầu kỳ (tính theo mệnh giá chứng chỉ quỹ) Fund scale at the beginning of the period (based on par value of fund certificate) | C31: 2273 | D31: 248164255000 | E31: 234760300500
B32: Tổng giá trị chứng chỉ quỹ đang lưu hành đầu kỳ Total value of outstanding Fund Certificate at the beginning of period | C32: 2274 | D32: 248164255000 | E32: 234760300500
B33: Tổng số lượng chứng chỉ quỹ đang lưu hành đầu kỳ Total number of outstanding Fund Certificate at the beginning of period | C33: 2275 | D33: 24816426 | E33: 23476030
A34: 2 | B34: Thay đổi quy mô quỹ trong kỳ (tính theo mệnh giá chứng chỉ quỹ) Change of Fund scale during the period (based on par value of fund certificate) | C34: 2276 | D34: 62685745500 | E34: 13403954500
B35: Thay đổi số lượng chứng chỉ quỹ trong kỳ Change of Number of Fund Certificates during the period | C35: 22761 | D35: 6268574.5 | E35: 1340395.4
B36: Thay đổi giá trị vốn trong kỳ (theo mệnh giá) Change in capital amount during the period (based on par value) | C36: 22762 | D36: 62685745500 | E36: 13403954500
B37: Số lượng chứng chỉ quỹ phát hành thêm trong kỳ Number of Fund Certificates subscribed during the period | C37: 2277 | D37: 10988546 | E37: 6407318.2
B38: Giá trị vốn huy động thêm trong kỳ (theo mệnh giá) Net subscription amount during the period (based on par value) | C38: 2278 | D38: 109885459500 | E38: 64073181700
B39: Số lượng chứng chỉ quỹ mua lại trong kỳ Number of Fund Certificates redeemed during the period | C39: 22781 | D39: -4719971.4 | E39: -5066922.7
B40: Giá trị vốn phải thanh toán trong kỳ khi đáp ứng lệnh của nhà đầu tư (theo mệnh giá) Net redemption amount during the period (based on par value) | C40: 22782 | D40: -47199714000 | E40: -50669227200
A41: 3 | B41: Quy mô quỹ cuối kỳ (tính theo mệnh giá chứng chỉ quỹ) Fund scale at the end of the period (based on par value) | C41: 2279 | D41: 310850000500 | E41: 248164255000
B42: Tổng giá trị thị trường của quỹ đang lưu hành cuối kỳ (theo mệnh giá) Total value of outstanding Fund Certificate at the end of the period (based on par value) | C42: 2280 | D42: 310850000500 | E42: 248164255000
B43: Tổng số lượng chứng chỉ quỹ đang lưu hành cuối kỳ Total number of outstanding Fund Certificate at the end of the period | C43: 2281 | D43: 31085000 | E43: 24816426
A44: 4 | B44: Tỷ lệ nắm giữ chứng chỉ quỹ của công ty quản lý quỹ và người có liên quan cuối kỳ Fund Management Company and related parties' ownership ratio at the end of the period | C44: 2282 | D44: 0.0512 | E44: 0.0030880958
A45: 5 | B45: Tỷ lệ nắm giữ chứng chỉ quỹ của 10 nhà đầu tư lớn nhất cuối kỳ Top 10 investors' ownership ratio at the end of the period | C45: 2283 | D45: 0.2079 | E45: 0.1849
A46: 6 | B46: Tỷ lệ nắm giữ chứng chỉ quỹ của nhà đầu tư nước ngoài cuối kỳ Foreign investors' ownership ratio at the end of the period | C46: 2284 | D46: 0.1662 | E46: 0.1376
A47: 7 | B47: Số nhà đầu tư tham gia vào quỹ, kể cả giao dịch ký danh Number of investors of the Fund at the end of the period | C47: 22841 | D47: 33484 | E47: 31311
A48: 8 | B48: Giá trị tài sản ròng trên một đơn vị quỹ cuối kỳ Net asset value per Fund Certificate at the end of period | C48: 2285 | D48: 81062.4 | E48: 79515.4
A49: 9 | B49: Giá trị thị trường trên một chứng chỉ quỹ/cổ phiếu cuối kỳ (không áp dụng) Market price per fund certificates at the end of period (not applicable) | C49: 2288
A50: Ghi chú: Note:
A51: (*) Các chỉ tiêu từ 1 đến 7 của "Chỉ tiêu về hiệu quả hoạt động" đã được điều chỉnh để phản ánh số liệu trên cơ sở hoạt động tròn năm bằng cách nhân các chỉ tiêu này với 12 (đối với báo cáo tháng), 4 (đối với báo cáo quý), 2 (đối với báo cáo bán niên), 1 (đối với báo cáo năm). All Indicator starting from number 1 to 7 of "Investment performance indicators" are annualized to reflect a rate that is based on a full year operation by multiplying these indicators with 12 (monthly report) or 4 (quarterly report) or 2 (semi-annual report) or 1 (annual report). (**) Không tính đến giá trị cam kết của các hợp đồng tương lai chỉ số. Excluding the committed value of the Index Futures contracts.
A52: =TONGQUAN!C16 -> Đại diện có thẩm quyền của Ngân hàng giám sát | D52: =TONGQUAN!F16 -> Đại diện có thẩm quyền của Công ty quản lý Quỹ
A53: =TONGQUAN!C17 -> Authorised Representative of Supervisory Bank | D53: =TONGQUAN!F17 -> Authorised Representative of Fund Management Company
A63: =TONGQUAN!C19 -> Ngân hàng TNHH MTV Standard Chartered (Việt Nam) | D63: =TONGQUAN!F19 -> Công ty Cổ phần Quản lý Quỹ Đầu tư Dragon Capital Việt Nam
A64: =TONGQUAN!C20 -> Vũ Quang Phan | D64: =TONGQUAN!F20 -> Lê Hoàng Anh
A65: =TONGQUAN!C21 -> Phó phòng Dịch vụ nghiệp vụ giám sát Quỹ | D65: =TONGQUAN!F21 -> Quyền Giám đốc nghiệp vụ hỗ trợ đầu tư

Sheet BCTinhHinhTaiChinh_06105
A1: Mẫu số B02 - QM. Báo cáo tình hình tài chính Template B02 - QM. Statement of Financial Position
A2: (Ban hành kèm theo Thông tư 198/2012/TT-BTC ngày 15 tháng 11 năm 2012 về chế độ kế toán áp dụng đối với quỹ mở) (Issued in association with Circular 198/2012/TT-BTC dated 15 Nov 2012 on the Accounting Policies for Open-Ended Fund)
A3: BÁO CÁO TÌNH HÌNH TÀI CHÍNH STATEMENT OF FINANCIAL POSITION
A5: =TONGQUAN!C1 -> Tại ngày 30 tháng 09 năm 2024 / As at 30 Sep 2024
A7: Tên Công ty quản lý quỹ: | C7: =TONGQUAN!D5 -> Công ty Cổ phần Quản lý Quỹ Đầu tư Dragon Capital Việt Nam
A8: Fund Management Company: | C8: =TONGQUAN!D6 -> Dragon Capital Vietfund Management Joint Stock Company
A9: Tên ngân hàng giám sát: | C9: =TONGQUAN!D7 -> Ngân hàng TNHH Một thành viên Standard Chartered (Việt Nam)
A10: Supervising bank: | C10: =TONGQUAN!D8 -> Standard Chartered Bank (Vietnam) Limited
A11: Tên Quỹ: | C11: =TONGQUAN!D9 -> Quỹ Đầu tư Chứng khoán Năng động DC
A12: Fund name: | C12: =TONGQUAN!D10 -> DC Dynamic Securities Fund (DCDS)
A13: Ngày lập báo cáo: | C13: =TONGQUAN!D11 -> Ngày 07 tháng 10 năm 2024
A14: Reporting Date: | C14: =TONGQUAN!D12 -> 07 Oct 2024
A16: STT No. | B16: Chỉ tiêu Indicator | C16: Mã số Code | D16: Thuyết minh Note | E16: =BCTaiSan_06027!D18 -> Ngày 30 tháng 09 năm 2024 As at 30 Sep 2024 | F16: =BCTaiSan_06027!E18 -> Ngày 30 tháng 06 năm 2024 As at 30 Jun 2024
A17: I | B17: I. TÀI SẢN ASSETS | C17: I
A18: 1 | B18: 1.Tiền gửi ngân hàng và tương đương tiền Cash at bank and cash equivalent | C18: 110 | E18: 58966760393 | F18: 128013039383
A19: 1.1 | B19: 1.1. Tiền gửi ngân hàng Cash at bank | C19: 111 | E19: 58966760393 | F19: 128013039383
B20: Tiền gửi của nhà đầu tư cho hoạt động mua chứng chỉ quỹ Cash at bank for Fund's subscription | C20: 111.1 | E20: 8253542436 | F20: 25116978132
B21: Tiền phải trả cho Nhà đầu tư về mua lại Chứng chỉ quỹ Cash at bank for Fund's redemption | C21: 111.2 | E21: 151980129 | F21: 158380272
B22: Tiền gửi ngân hàng cho hoạt động của Quỹ Cash at bank for Fund's operation | C22: 111.3 | E22: 50561237828 | F22: 102737680979
B23: Tiền gửi ký quỹ cho hoạt động đầu tư chứng khoán phái sinh Margin account for trading derivatives | C23: 111.4 | E23: 0 | F23: 0
A24: 1.2 | B24: 1.2. Tiền gửi có kỳ hạn dưới ba (03) tháng Deposit with term less than three (03) months | C24: 112 | E24: 0 | F24: 0
A25: 2 | B25: 2. Các khoản đầu tư thuần Net Investments | C25: 120 | E25: 2536149865950 | F25: 1900572223600
A26: 2.1 | B26: 2.1. Các khoản đầu tư Investments | C26: 121 | E26: 2536149865950 | F26: 1900572223600
B27: Cổ phiếu, chứng chỉ quỹ niêm yết Listed Shares, fund certificates | C27: 121.1 | E27: 2535160693950 | F27: 1900572223600
B28: Cổ phiếu, chứng chỉ quỹ chưa niêm yết Unlisted Shares, fund certifictes | C28: 121.2 | E28: 0 | F28: 0
B29: Trái phiếu niêm yết Listed Bonds | C29: 121.3 | E29: 0 | F29: 0
B30: Trái phiếu chưa niêm yết Unlisted Bonds | C30: 121.4 | E30: 0 | F30: 0
B31: Công cụ thị trường tiền tệ Money market instruments | C31: 121.5 | E31: 0 | F31: 0
B32: Hợp đồng tiền gửi có kỳ hạn trên ba (03) tháng Deposits with term over three (03) months | C32: 121.6 | E32: 0 | F32: 0
B33: Quyền mua chứng khoán Investment - Rights | C33: 121.7 | E33: 989172000 | F33: 0
B34: Hợp đồng tương lai chỉ số Index future contracts | C34: 121.8 | E34: 0 | F34: 0
B35: Đầu tư khác Other Investments | C35: 121.9 | E35: 0 | F35: 0
B36: Hợp đồng mua lại đảo ngược Reverse repo contracts | C36: 121.10 | E36: 0 | F36: 0
A37: 2.2 | B37: 2.2. Dự phòng giảm giá tài sản nhận thế chấp Impairment of devaluation of pledged assets | C37: 122 | E37: 0 | F37: 0
A38: 3 | B38: 3. Các khoản phải thu Receivables | C38: 130 | E38: 52894006671 | F38: 47400327308
A39: 3.1 | B39: 3.1 Phải thu về bán các khoản đầu tư Receivables from investments sold but not yet settled | C39: 131 | E39: 48528246100 | F39: 43306359800
B40: Trong đó: Phải thu khó đòi về bán các khoản đầu tư In which: Overdue receivables from selling investments | C40: 132 | E40: 0 | F40: 0
A41: 3.2 | B41: 3.2. Phải thu và dự thu cổ tức, tiền lãi các khoản đầu tư Dividend and interest receivables | C41: 133 | E41: 5195706000 | F41: 4913060000
A42: 3.2.1 | B42: 3.2.1. Phải thu cổ tức, tiền lãi đến ngày nhận Dividend and interest receivables on or after payment date | C42: 134 | E42: 866400000 | F42: 866400000
B43: Phải thu cổ tức Dividend receivables | C43: 134.1 | E43: 866400000 | F43: 866400000
B44: Phải thu trái tức Coupon receivables | C44: 134.2 | E44: 0 | F44: 0
B45: Phải thu lãi tiền gửi có kỳ hạn dưới 3 tháng Interest receivables from deposit with term less than three (03) months | C45: 134.3 | E45: 0 | F45: 0
B46: Phải thu lãi tiền gửi có kỳ hạn trên 3 tháng Interest receivables from deposit with term more than three (03) months | C46: 134.4 | E46: 0 | F46: 0
B47: Phải thu lãi công cụ thị trường tiền tệ Interest receivables from Money market instruments | C47: 134.5 | E47: 0 | F47: 0
B48: Trong đó: Phải thu khó đòi về cổ tức, tiền lãi đến ngày nhận nhưng chưa nhận được In which: Overdue receivables from dividend, interest income | C48: 135 | E48: 866400000 | F48: 866400000
A49: 3.2.2 | B49: 3.2.2.Dự thu cổ tức, tiền lãi chưa đến ngày nhận Dividend and interest receivables before payment date | C49: 136 | E49: 4329306000 | F49: 4046660000
B50: Dự thu cổ tức Dividend receivables | C50: 136.1 | E50: 4329306000 | F50: 4046660000
B51: Dự thu lãi trái phiếu Interest accrual from bonds | C51: 136.2 | E51: 0 | F51: 0
B52: Dự thu lãi tiền gửi có kỳ hạn dưới 3 tháng Interest accrual from deposits with term less than three (03) months | C52: 136.3 | E52: 0 | F52: 0
B53: Dự thu lãi tiền gửi có kỳ hạn trên 3 tháng Interest accrual from deposit with term more than three (03) months | C53: 136.4 | E53: 0 | F53: 0
B54: Dự thu lãi công cụ thị trường tiền tệ Interest accrual from Money market instruments | C54: 136.5 | E54: 0 | F54: 0
B55: Dự thu lãi hợp đồng mua lại đảo ngược Interest receivables from reverse repo contracts | C55: 136.6 | E55: 0 | F55: 0
A56: 3.3 | B56: 3.3. Các khoản phải thu khác Other receivables | C56: 137 | E56: 36454571 | F56: 47307508
B57: Phải thu cho khoản cổ phiếu hạn chế chờ mua Receivable from AP/Investors on securities on hold of buying | C57: 137.1 | E57: 0 | F57: 0
B58: Các tài sản khác Other assets | C58: 137.2 | E58: 36454571 | F58: 47259108
B59: Các khoản khác Others | C59: 137.3 | E59: 0 | F59: 48400
A60: 3.4 | B60: 3.4. Dự phòng nợ phải thu khó đòi Provision for doubtful debt | C60: 138 | E60: -866400000 | F60: -866400000
B61: TỔNG TÀI SẢN TOTAL ASSETS | C61: 100 | E61: 2648010633014 | F61: 2075985590291
A62: II | B62: II. NỢ PHẢI TRẢ TOTAL LIABILITIES | C62: II
A63: 1 | B63: 1. Vay ngắn hạn Short-term loans | C63: 311 | E63: 0 | F63: 0
B64: Gốc hợp đồng repo Repo contracts - Principal | C64: 311.1 | E64: 0 | F64: 0
B65: Vay ngắn hạn Short-term loans | C65: 311.2 | E65: 0 | F65: 0
A66: 2 | B66: 2. Phải trả về mua các khoản đầu tư Payables for securities bought but not yet settled | C66: 312 | E66: 47045700000 | F66: 65419005000
A67: 3 | B67: 3. Phải trả phí cho các Đại lý phân phối, Công ty quản lý quỹ về mua bán Chứng chỉ quỹ Subscription and Redemption fee payable to distributors and fund management company | C67: 313 | E67: 325061456 | F67: 437404346
B68: Phải trả phí cho các Đại lý phân phối về mua bán Chứng chỉ quỹ Subscription and Redemption fee payable to distributors | C68: 313.1 | E68: 6835448 | F68: 6835448
B69: Phải trả phí cho Công ty quản lý quỹ về mua bán Chứng chỉ quỹ Subscription and Redemption fee payable to fund management company | C69: 313.2 | E69: 318226008 | F69: 430568898
A70: 4 | B70: 4. Thuế và các khoản phải nộp Nhà nước Tax payables and obligations to the State Budget | C70: 314 | E70: 125701915 | F70: 158879648
A71: 5 | B71: 5.Phải trả thu nhập cho Nhà đầu tư Profit distribution payables | C71: 315 | E71: 39925000 | F71: 39925000
A72: 6 | B72: 6. Chi phí phải trả Expense Accruals | C72: 316 | E72: 247804091 | F72: 309093465
B73: Phí giao dịch Transaction fee | C73: 316.1 | E73: 151294122 | F73: 187002435
B74: Phải trả phí môi giới Brokerage fee payables | C74: 316.1.1 | E74: 151294122 | F74: 187002435
B75: Phải trả phí giao dịch thanh toán bù trừ chứng khoán Clearing Settlement Fee payables | C75: 316.1.2 | E75: 0 | F75: 0
B76: Trích trước phí kiểm toán Accrued expense for audit fee | C76: 316.2 | E76: 51880000 | F76: 100100000
B77: Trích trước phí họp đại hội thường niên Accrued expense for Annual General meeting | C77: 316.3 | E77: 25381335 | F77: 5758790
B78: Trích trước phí báo cáo thường niên Accrued expense for Annual report | C78: 316.4 | E78: 0 | F78: 0
B79: Trích trước thù lao ban đại diện quỹ Accrued expense for Remuneration Payable to Fund's Board of Representatives | C79: 316.5 | E79: 19248634 | F79: 16232240
B80: Trích trước phí quản lý niêm yết hàng năm tại SGDCK Accrued expense for annual listing fee at HOSE | C80: 316.6 | E80: 0 | F80: 0
B81: Trích trước lãi vay ngắn hạn của hợp đồng vay và hợp đồng repo Accrued Interest Expense of short-term loan contracts and repo contracts | C81: 316.7 | E81: 0 | F81: 0
A82: 7 | B82: 7. Phải trả cho Nhà đầu tư về mua Chứng chỉ quỹ Subscription payables to investors | C82: 317 | E82: 8253542436 | F82: 25116978132
B83: Phải trả cho nhà đầu tư chờ mua chứng chỉ quỹ Subscription Pending allotment | C83: 317.1 | E83: 8253542436 | F83: 25116978132
B84: Phải trả nhà đầu tư trên tài sản giữ hộ Payables to investors for investment bought on behalf | C84: 317.2 | E84: 0 | F84: 0
A85: 8 | B85: 8. Phải trả cho Nhà đầu tư về mua lại Chứng chỉ quỹ Redemption payables to investors | C85: 318 | E85: 67693053224 | F85: 7556102394
A86: 9 | B86: 9. Phải trả dịch vụ quản lý Quỹ mở Fund management related service expense payable | C86: 319 | E86: 4241624717 | F86: 3448139478
B87: Trích trước phải trả phí quản lý Accrued expense for Management fee | C87: 319.1 | E87: 3926981906 | F87: 3187386361
B88: Trích trước phí lưu ký tài sản Quỹ mở Accrued expense for Custodian fee | C88: 319.2 | E88: 157453475 | F88: 130682282
B89: Phí dịch vụ lưu ký - bảo quản tài sản Custodian service - Safe Custody Fee | C89: 319.2.1 | E89: 80553475 | F89: 65382282
B90: Phí dịch vụ lưu ký - giao dịch chứng khoán Custodian service - Transaction fee | C90: 319.2.2 | E90: 65900000 | F90: 54300000
B91: Phí dịch vụ lưu ký cho chứng khoán cơ sở, phí quản lý vị thế và tài sản phái sinh trả cho VSDC Custodian service - Depository fee, Position and Margin management fee paid to VSDC | C91: 319.2.3 | E91: 11000000 | F91: 11000000
B92: Trích trước phí quản trị quỹ Accrued expense for Fund administration fee | C92: 319.3 | E92: 55380513 | F92: 44950321
B93: Trích trước phí giám sát Accrued expense for Supervising fee | C93: 319.4 | E93: 88608823 | F93: 71920514
B94: Trích trước phí dịch vụ đại lý chuyển nhượng Accrued expense for Tranfer agency fee | C94: 319.5 | E94: 13200000 | F94: 13200000
B95: Dự chi phí cung cấp dịch vụ tính giá trị tài sản ròng tham chiếu (iNAV) cho HOSE Accrued expense for payable to HOSE for iNAV calculation | C95: 319.6 | E95: 0 | F95: 0
B96: Dự chi phí cấp quyền sử dụng chỉ số cho HOSE Accrued expense for payable to HOSE for Index usage | C96: 319.7 | E96: 0 | F96: 0
A97: 10 | B97: 10. Phải trả, phải nộp khác Other payables | C97: 320 | E97: 213297720 | F97: 212003724
B98: Phải trả phí báo giá Price feed fee payable | C98: 320.1 | E98: 23500000 | F98: 23500000
B99: Trích trước phí công tác, họp của ban đại diện Accrued expense for Fund's Board of Representatives travelling, meeting | C99: 320.2 | E99: 0 | F99: 0
B100: Trích trước phí quản lý thường niên trả cho UBCKNN Accrued expense for Annual Fee paid to SSC | C100: 320.3 | E100: 5614754 | F100: 3729508
B101: Phí Ngân hàng S2B S2B Bank charge | C101: 320.4 | E101: 7700000 | F101: 8291250
B102: Phải trả khác Other payables | C102: 320.5 | E102: 176482966 | F102: 176482966
B103: TỔNG NỢ PHẢI TRẢ TOTAL LIABILITIES | C103: 300 | E103: 128185710559 | F103: 102697531187
...

Sheet BCLCGT_06262
A1: Mẫu số B05 - QM. Báo cáo lưu chuyển tiền tệ Template B05 - QM. Cash flow statement
A2: (Ban hành kèm theo Thông tư 198/2012/TT-BTC ngày 15 tháng 11 năm 2012 về chế độ kế toán áp dụng đối với quỹ mở) (Issued in association with Circular 198/2012/TT-BTC dated 15 Nov 2012 on the Accounting Policies for Open-Ended Fund)
A3: BÁO CÁO LƯU CHUYỂN TIỀN TỆ CASH FLOW STATEMENT
A4: =TONGQUAN!C2 -> Quý III năm 2024 / Quarter III 2024
A7: Tên Công ty quản lý quỹ: | B7: =TONGQUAN!D5 -> Công ty Cổ phần Quản lý Quỹ Đầu tư Dragon Capital Việt Nam
A8: Fund Management Company: | B8: =TONGQUAN!D6 -> Dragon Capital Vietfund Management Joint Stock Company
A9: Tên ngân hàng giám sát: | B9: =TONGQUAN!D7 -> Ngân hàng TNHH Một thành viên Standard Chartered (Việt Nam)
A10: Supervising bank: | B10: =TONGQUAN!D8 -> Standard Chartered Bank (Vietnam) Limited
A11: Tên Quỹ: | B11: =TONGQUAN!D9 -> Quỹ Đầu tư Chứng khoán Năng động DC
A12: Fund name: | B12: =TONGQUAN!D10 -> DC Dynamic Securities Fund (DCDS)
A13: Ngày lập báo cáo: | B13: =TONGQUAN!D11 -> Ngày 07 tháng 10 năm 2024
A14: Reporting Date: | B14: =TONGQUAN!D12 -> 07 Oct 2024
A17: Chỉ tiêu Indicator | B17: Mã số Code | C17: Thuyết minh Note | D17: =BCKetQuaHoatDong_06028!D18 -> Quý III năm 2024 Quarter III 2024 | E17: =BCKetQuaHoatDong_06028!E18 -> Quý II năm 2024 Quarter II 2024
A18: I. Lưu chuyển tiền từ hoạt động đầu tư Cash flow from investing activities | B18: I
A19: 1. Lợi nhuận trước Thuế thu nhập doanh nghiệp Profit before income tax | B19: 01 | D19: 56073897420 | E19: 84224398074
A20: 2. Điều chỉnh cho các khoản tăng giá trị tài sản ròng từ các hoạt động đầu tư Adjustment for NAV increase from investing activities | B20: 02 | D20: -38978433963 | E20: 59515592027
A21: (- Lãi) hoặc (+ lỗ) chênh lệch tỷ giá hối đoái/ đánh giá lại các khoản đầu tư chưa thực hiện Unreliased (Gain) or Loss from FX valuation/Investment revaluation | B21: 03 | D21: -38951721754 | E21: 59457918483
A22: (+) Chi phí trích trước Increase of Accrued Expenses | B22: 04 | D22: -26712209 | E22: 57673544
A23: 3. Lợi nhuận từ hoạt động đầu tư trước thay đổi vốn lưu động Profit from investing activities before changes in working capital | B23: 05 | D23: 17095463457 | E23: 143739990101
A24: (-) Tăng, (+) giảm đầu tư (Increase), Decrease Investments | B24: 20 | D24: -596625920596 | E24: -188568936433
A25: (-) Tăng, (+) giảm phải thu bán chứng khoán đầu tư (Increase), Decrease in Receivables from investments sold but not yet settled | B25: 06 | D25: -5221886300 | E25: -9266409800
A26: (-) Tăng, (+) giảm dự thu phải thu tiền lãi các khoản đầu tư (Increase), Decrease in Dividend and interest receivables | B26: 07 | D26: -282646000 | E26: -3491760000
A27: (-) Tăng, (+) giảm các khoản phải thu khác (Increase), Decrease in other receivables | B27: 08 | D27: 10852937 | E27: 10638713
A28: (+) Tăng, (-) giảm vay ngắn hạn Increase, (Decrease) in Short-term Loans | B28: 09 | D28: 0 | E28: 0
A29: (+) Tăng, (-) giảm phải trả cho người bán (Decrease), Increase in payables for securities purchased but not yet settled | B29: 10 | D29: -18373305000 | E29: 31473010000
A30: (+) Tăng, (-) giảm phải trả các Đại lý phân phối Chứng chỉ quỹ, Công ty Quản lý Quỹ (Decrease)/increase in subscription and redemption fee payable to distributors and Fund Management Company | B30: 11 | D30: -112342890 | E30: 44400507
... A38: Lưu chuyển tiền thuần từ hoạt động đầu tư (1+2+3) Net Cash flow from Investing activities | B38: 19 | D38: -559509244921 | E38: -10774882098
A39: II. Lưu chuyển tiền từ hoạt động tài chính Cash flow from financing activities | B39: II
A40: 1. Tiền thu từ phát hành Chứng chỉ quỹ mở Receipts from subscriptions | B40: 31 | D40: 869806044900 | E40: 496010237277
A41: 2. Tiền chi mua lại Chứng chỉ quỹ mở Payments for redemptions | B41: 32 | D41: -379343078969 | E41: -397053682287
A42: 3. Tiền vay gốc Principal of borrowings | B42: 33 | D42: 0 | E42: 0
A43: 4. Tiền chi trả nợ gốc vay Payment of Principal borrowings | B43: 34 | D43: 0 | E43: 0
A44: 5. Tiền chi trả cổ tức, tiền lãi cho nhà đầu tư Dividend, profit distribution paid to investors | B44: 35 | D44: 0 | E44: 0
A45: Lưu chuyển tiền thuần từ hoạt động tài chính (1-2+3-4-5) Net cash outflows from financing activities | B45: 30 | D45: 490462965931 | E45: 98956554990
A46: III. Tăng/giảm tiền thuần trong kỳ Net Increase/Decrease in cash and cash equivalent for the period | B46: 40 | D46: -69046278990 | E46: 88181672892
A47: IV. Tiền và các khoản tương đương tiền đầu kỳ Cash and cash equivalents at the beginning of period | B47: 50 | D47: 128013039383 | E47: 39831366491
A48: Tiền gửi ngân hàng đầu kỳ: Cash at bank of the beginning of period: | B48: 51 | D48: 128013039383 | E48: 39831366491
A49: -Tiền gửi ngân hàng và tương đương tiền cho hoạt động của Quỹ Cash at bank and cash equivalent for Fund's operation | B49: 52 | D49: 102737680979 | E49: 34723879362
A50: Tiền gửi không kỳ hạn Demand deposit | B50: 52.1 | D50: 102737680979 | E50: 34723879362
A51: Tiền gửi có kỳ hạn dưới ba (03) tháng Deposits with term under three (03) months | B51: 52.2 | D51: 0 | E51: 0
... A64: Khác Others | B64: 80 | D64: 0 | E64: 0
A67: Người lập: | C67: Người duyệt:
A78: _______________________________ | B78: _______________________________________ | E78: ___________________________________
A79: Nguyễn Kiều Trúc Ly | B79: Ninh Thị Tuệ Minh | E79: Lê Hoàng Anh
A80: Kế toán Quỹ | B80: Trưởng phòng Kế toán Quỹ | E80: Quyền Giám đốc nghiệp vụ hỗ trợ đầu tư

Sheet BCHoatDongVay_06026
A1: Phụ lục XXVI. Mẫu báo cáo về hoạt động của Quỹ Appendix XXVI. Report on Fund's Operation
A2: (Ban hành kèm theo Thông tư số 98/2020/TT-BTC ngày 16 tháng 11 năm 2020 của Bộ trưởng Bộ Tài Chính về hướng dẫn hoạt động và quản lý quỹ đầu tư chứng khoán) (Issued in association with Circular 98/2020/TT-BTC dated 16 November 2020 of the Minister of Finance on guiding the operation and management of the securities investment funds)
A3: BÁO CÁO HOẠT ĐỘNG ĐẦU TƯ CỦA QUỸ MỞ REPORT ON OPEN ENDED FUND'S INVESTMENT ACTIVITIES
A5: =TONGQUAN!C2 -> Quý III năm 2024 / Quarter III 2024
A7: Tên Công ty quản lý quỹ: | G7: =TONGQUAN!D5 -> Công ty Cổ phần Quản lý Quỹ Đầu tư Dragon Capital Việt Nam
A8: Fund Management Company: | G8: =TONGQUAN!D6 -> Dragon Capital Vietfund Management Joint Stock Company
A9: Tên ngân hàng giám sát: | G9: =TONGQUAN!D7 -> Ngân hàng TNHH Một thành viên Standard Chartered (Việt Nam)
A10: Supervising bank: | G10: =TONGQUAN!D8 -> Standard Chartered Bank (Vietnam) Limited
A11: Tên Quỹ: | G11: =TONGQUAN!D9 -> Quỹ Đầu tư Chứng khoán Năng động DC
A12: Fund name: | G12: =TONGQUAN!D10 -> DC Dynamic Securities Fund (DCDS)
A13: Ngày lập báo cáo: | G13: =TONGQUAN!D11 -> Ngày 07 tháng 10 năm 2024
A14: Reporting Date: | G14: =TONGQUAN!D12 -> 07 Oct 2024
A15: A. | B15: BÁO CÁO CHUNG VỀ HOẠT ĐỘNG ĐẦU TƯ CỦA QUỸ/GENERAL INFORMATION ON FUND'S INVESTMENT ACTIVITIES
A16: IV | B16: BÁO CÁO HOẠT ĐỘNG VAY, GIAO DỊCH MUA BÁN LẠI / REPORT ON BORROWING OPERATION, REPO/REVERSE REPO TRANSACTIONS
A17: STT No. | B17: Nội dung hoạt động (nên chi tiết theo mục tiêu và đối tác) Description | C17: Đối tác Counterparty | D17: Mục tiêu/ Tài sản đảm bảo Collateral | E17: Kỳ hạn Term | F17: Giá trị khoản vay hoặc khoản cho vay Amount | G17: Thời điểm giao dịch As at transaction date | I17: Thời điểm báo cáo As at reporting date
G18: Ngày tháng năm Date | H18: Tỷ lệ giá trị hợp đồng/giá trị tài sản ròng của quỹ/công ty (%) Balance/NAV (%) | I18: Ngày tháng năm Date | J18: Tỷ lệ giá trị hợp đồng/ giá trị tài sản ròng của quỹ/ công ty (%) Balance/NAV (%)
A19: 1 | B19: Các khoản vay tiền (nêu chi tiết từng hợp đồng)
A20: ... | B20: ... | C20: ... | D20: ... | E20: ... | F20: ... | G20: ... | H20: ... | I20: ... | J20: ...
A21: I | B21: Tổng giá trị các khoản vay tiền/giá trị tài sản ròng | F21: 0 | H21: 0 | J21: 0
A22: 2 | B22: Hợp đồng Repo (nêu chi tiết từng hợp đồng)
A23: ... | B23: ... | C23: ... | D23: ... | E23: ... | F23: ... | G23: ... | H23: ... | I23: ... | J23: ...
A24: II | B24: Tổng giá trị các hợp đồng Repo/giá trị tài sản ròng | F24: 0 | H24: 0 | J24: 0
A25: A | B25: Tổng giá trị các khoản vay/giá trị tài sản ròng (=I+II) | F25: 0 | H25: 0 | J25: 0
A26: 3 | B26: Cho vay chứng khoán (nêu chi tiết từng hợp đồng)
A27: ... | B27: ... | C27: ... | D27: ... | E27: ... | F27: ... | G27: ... | H27: ... | I27: ... | J27: ...
A28: III | B28: Tổng giá trị các hợp đồng/giá trị tài sản ròng | F28: 0 | H28: 0 | J28: 0
A29: 4 | B29: Hợp đồng Reverse Repo (nêu chi tiết từng hợp đồng)
A30: ... | B30: ... | C30: ... | D30: ... | E30: ... | F30: ... | G30: ... | H30: ... | I30: ... | J30: ...
A31: IV | B31: Tổng giá trị các hợp đồng/ giá trị tài sản ròng | F31: 0 | H31: 0 | J31: 0
A32: B | B32: Tổng giá trị các khoản cho vay/giá trị tài sản ròng (=III + IV) | F32: 0 | H32: 0 | J32: 0
A33: Đại diện có thẩm quyền của Ngân hàng giám sát | I33: Đại diện có thẩm quyền của Công ty quản lý Quỹ
A34: Authorised Representative of Supervisory Bank | I34: Authorised Representative of Fund Management Company
A44: Ngân hàng TNHH MTV Standard Chartered (Việt Nam) | I44: Công ty Cổ phần Quản lý Quỹ Đầu tư Dragon Capital Việt Nam
A45: Vũ Quang Phan | I45: Lê Hoàng Anh
A46: Phó phòng Dịch vụ nghiệp vụ giám sát Quỹ | I46: Quyền Giám đốc nghiệp vụ hỗ trợ đầu tư

Sheet LogoFMS
D1: VFMVF1
A2: FUNDCODE | B2: FUNDNAME | C2: LOGO
A3: VFMVSF | B3: Quỹ Đầu Tư Cổ Phiếu Việt Nam Chọn Lọc
A4: VFMVF1 | B4: Quỹ Đầu tư Chứng khoán Năng động DC
A5: VFMVF4 | B5: Quỹ Đầu tư Doanh nghiệp Hàng đầu DC
A6: VFMVFA | B6: Quỹ Đầu tư Năng Động Việt Nam
A7: VFMVFB | B7: Quỹ Đầu tư Trái phiếu DC
A8: VFMVFC | B8: Quỹ Đầu tư Trái phiếu Gia tăng Thu nhập Cố định DC
A9: TCEF1 | B9: Quỹ Đầu tư Cổ phiếu Techcom
A10: TCBF | B10: Quỹ Đầu tư Cổ phiếu Techcom
A11: MBEF1 | B11: Quỹ Đầu tư JAPAN ASIA MB CAPITAL
A12: MBVF | B12: Quỹ Đầu tư Giá trị MB Capital
A13: SSISCA | B13: Quỹ Đầu tư Lợi thế Cạnh tranh Bền vững SSI
A14: VCBBCF | B14: Quỹ Đầu tư Cổ Phiếu Hàng Đầu VCBF
... A52: VCBMGF | B52: Quỹ Đầu Tư Cổ phiếu Tăng trưởng VCBF
A53: AM33
A54: AM34
A55: AM35
A56: AM36 | B56: Tổng công ty cổ phần bảo hiểm Petrolimex - PJICO EQUITY PORTFOLIO 04
A57: AM37
A58: AM38
A59: AM39
A60: AM40
A61: AM41
A62: AM42
A63: AM43
A64: AM44
A65: AM45
A66: AM46
A67: AM47
A68: AM48
... A70: AM50
A71: VMPF | B71: Quỹ Đầu Tư Cổ Phiếu Hiệu Suất Thị Trường Việt Nam VinaCapital (VinaCapital-VMPF)
A72: ENF
A73: EVESG
A74: UVDIF
A75: VDEF
A76: VCBAIF
