Workbook
Name addlogo: INDEX(LogoFMS!$C$3:$C$76,MATCH(LogoFMS!$D$1,LogoFMS!$A$3:$A$76,0))

Sheet TONGQUAN
A1: Kỳ báo cáo: | C1: Tại ngày 31 tháng 01 năm 2025 / As at 31 Jan 2025
C2: Tháng 01 năm 2025 / Jan 2025
A4: Thông tin chung:
C5: Tên Công ty quản lý quỹ: | D5: Công ty Cổ phần Quản lý Quỹ Đầu tư Dragon Capital Việt Nam
C6: Fund Management Company: | D6: Dragon Capital Vietfund Management Joint Stock Company
C7: Tên ngân hàng giám sát: | D7: Ngân hàng TNHH Một thành viên Standard Chartered (Việt Nam)
C8: Supervising bank: | D8: Standard Chartered Bank (Vietnam) Limited
C9: Tên Quỹ: | D9: Quỹ Đầu tư Trái phiếu DC
C10: Fund name: | D10: DC Bond Fund (DCBF)
C11: Ngày lập báo cáo: | D11: Ngày 03 tháng 02 năm 2025
C12: Reporting Date: | D12: 03 Feb 2025
A14: Người ký báo cáo:
C16: Đại diện có thẩm quyền của Ngân hàng giám sát | F16: Đại diện có thẩm quyền của Công ty quản lý Quỹ
C17: Authorised Representative of Supervisory Bank | F17: Authorised Representative of Fund Management Company
C19: Ngân hàng TNHH MTV Standard Chartered (Việt Nam) | F19: =D5 -> Công ty Cổ phần Quản lý Quỹ Đầu tư Dragon Capital Việt Nam
C20: Vũ Quang Phan | F20: Lê Hoàng Anh
C21: Phó phòng Dịch vụ nghiệp vụ giám sát Quỹ | F21: Quyền Giám đốc nghiệp vụ hỗ trợ đầu tư

Sheet BCHoatDongVay_06026
A1: Phụ lục XXVI. Mẫu báo cáo về hoạt động của Quỹ Appendix XXVI. Report on Fund's Operation
A2: (Ban hành kèm theo Thông tư số 98/2020/TT-BTC ngày 16 tháng 11 năm 2020 của Bộ trưởng Bộ Tài Chính về hướng dẫn hoạt động và quản lý quỹ đầu tư chứng khoán) (Issued in association with Circular 98/2020/TT-BTC dated 16 November 2020 of the Minister of Finance on guiding the operation and management of the securities investment funds)
A3: BÁO CÁO HOẠT ĐỘNG ĐẦU TƯ CỦA QUỸ MỞ REPORT ON OPEN ENDED FUND'S INVESTMENT ACTIVITIES
A5: =TONGQUAN!C2 -> Tháng 01 năm 2025 / Jan 2025
A7: Tên Công ty quản lý quỹ: | G7: =TONGQUAN!D5 -> Công ty Cổ phần Quản lý Quỹ Đầu tư Dragon Capital Việt Nam
A8: Fund Management Company: | G8: =TONGQUAN!D6 -> Dragon Capital Vietfund Management Joint Stock Company
A9: Tên ngân hàng giám sát: | G9: =TONGQUAN!D7 -> Ngân hàng TNHH Một thành viên Standard Chartered (Việt Nam)
A10: Supervising bank: | G10: =TONGQUAN!D8 -> Standard Chartered Bank (Vietnam) Limited
A11: Tên Quỹ: | G11: =TONGQUAN!D9 -> Quỹ Đầu tư Trái phiếu DC
A12: Fund name: | G12: =TONGQUAN!D10 -> DC Bond Fund (DCBF)
A13: Ngày lập báo cáo: | G13: =TONGQUAN!D11 -> Ngày 03 tháng 02 năm 2025
A14: Reporting Date: | G14: =TONGQUAN!D12 -> 03 Feb 2025
A15: A. | B15: BÁO CÁO CHUNG VỀ HOẠT ĐỘNG ĐẦU TƯ CỦA QUỸ/GENERAL INFORMATION ON FUND'S INVESTMENT ACTIVITIES
A16: IV | B16: BÁO CÁO HOẠT ĐỘNG VAY, GIAO DỊCH MUA BÁN LẠI / REPORT ON BORROWING OPERATION, REPO/REVERSE REPO TRANSACTIONS
A17: STT No. | B17: Nội dung hoạt động (nên chi tiết theo mục tiêu và đối tác) Description | C17: Đối tác Counterparty | D17: Mục tiêu/ Tài sản đảm bảo Collateral | E17: Kỳ hạn Term | F17: Giá trị khoản vay hoặc khoản cho vay Amount | G17: Thời điểm giao dịch As at transaction date | I17: Thời điểm báo cáo As at reporting date
G18: Ngày tháng năm Date | H18: Tỷ lệ giá trị hợp đồng/giá trị tài sản ròng của quỹ/công ty (%) Balance/NAV (%) | I18: Ngày tháng năm Date | J18: Tỷ lệ giá trị hợp đồng/ giá trị tài sản ròng của quỹ/ công ty (%) Balance/NAV (%)
A19: 1 | B19: Các khoản vay tiền (nêu chi tiết từng hợp đồng)
A20: ... | B20: ... | C20: ... | D20: ... | E20: ... | F20: ... | G20: ... | H20: ... | I20: ... | J20: ...
A21: I | B21: Tổng giá trị các khoản vay tiền/giá trị tài sản ròng | F21: 0 | H21: 0 | J21: 0
A22: 2 | B22: Hợp đồng Repo (nêu chi tiết từng hợp đồng)
A23: ... | B23: ... | C23: ... | D23: ... | E23: ... | F23: ... | G23: ... | H23: ... | I23: ... | J23: ...
A24: II | B24: Tổng giá trị các hợp đồng Repo/giá trị tài sản ròng | F24: 0 | H24: 0 | J24: 0
A25: A | B25: Tổng giá trị các khoản vay/giá trị tài sản ròng (=I+II) | F25: 0 | H25: 0 | J25: 0
A26: 3 | B26: Cho vay chứng khoán (nêu chi tiết từng hợp đồng)
A27: ... | B27: ... | C27: ... | D27: ... | E27: ... | F27: ... | G27: ... | H27: ... | I27: ... | J27: ...
A28: III | B28: Tổng giá trị các hợp đồng/giá trị tài sản ròng | F28: 0 | H28: 0 | J28: 0
A29: 4 | B29: Hợp đồng Reverse Repo (nêu chi tiết từng hợp đồng)
A30: ... | B30: ... | C30: ... | D30: ... | E30: ... | F30: ... | G30: ... | H30: ... | I30: ... | J30: ...
A31: IV | B31: Tổng giá trị các hợp đồng/ giá trị tài sản ròng | F31: 0 | H31: 0 | J31: 0
A32: B | B32: Tổng giá trị các khoản cho vay/giá trị tài sản ròng (=III + IV) | F32: 0 | H32: 0 | J32: 0
A33: Đại diện có thẩm quyền của Ngân hàng giám sát | I33: Đại diện có thẩm quyền của Công ty quản lý Quỹ
A34: Authorised Representative of Supervisory Bank | I34: Authorised Representative of Fund Management Company
A42: Ngân hàng TNHH MTV Standard Chartered (Việt Nam) | I42: Công ty Cổ phần Quản lý Quỹ Đầu tư Dragon Capital Việt Nam
A43: Vũ Quang Phan | I43: Lê Hoàng Anh
A44: Phó phòng Dịch vụ nghiệp vụ giám sát Quỹ | I44: Quyền Giám đốc nghiệp vụ hỗ trợ đầu tư

Sheet BCTaiSan_06027
A1: Phụ lục XXVI. Mẫu báo cáo về hoạt động của Quỹ Appendix XXVI. Report on Fund's Operation
A2: (Ban hành kèm theo Thông tư số 98/2020/TT-BTC ngày 16 tháng 11 năm 2020 của Bộ trưởng Bộ Tài Chính về hướng dẫn hoạt động và quản lý quỹ đầu tư chứng khoán) (Issued in association with Circular 98/2020/TT-BTC dated 16 November 2020 of the Minister of Finance on guiding the operation and management of the securities investment funds)
A3: BÁO CÁO HOẠT ĐỘNG ĐẦU TƯ CỦA QUỸ MỞ REPORT ON OPEN ENDED FUND'S INVESTMENT ACTIVITIES
A5: =TONGQUAN!C1 -> Tại ngày 31 tháng 01 năm 2025 / As at 31 Jan 2025
A7: Tên Công ty quản lý quỹ: | C7: =TONGQUAN!D5 -> Công ty Cổ phần Quản lý Quỹ Đầu tư Dragon Capital Việt Nam
A8: Fund Management Company: | C8: =TONGQUAN!D6 -> Dragon Capital Vietfund Management Joint Stock Company
A9: Tên ngân hàng giám sát: | C9: =TONGQUAN!D7 -> Ngân hàng TNHH Một thành viên Standard Chartered (Việt Nam)
A10: Supervising bank: | C10: =TONGQUAN!D8 -> Standard Chartered Bank (Vietnam) Limited
A11: Tên Quỹ: | C11: =TONGQUAN!D9 -> Quỹ Đầu tư Trái phiếu DC
A12: Fund name: | C12: =TONGQUAN!D10 -> DC Bond Fund (DCBF)
A13: Ngày lập báo cáo: | C13: =TONGQUAN!D11 -> Ngày 03 tháng 02 năm 2025
A14: Reporting Date: | C14: =TONGQUAN!D12 -> 03 Feb 2025
A16: A. | B16: BÁO CÁO CHUNG VỀ HOẠT ĐỘNG ĐẦU TƯ CỦA QUỸ/GENERAL INFORMATION ON FUND'S INVESTMENT ACTIVITIES
A17: I | B17: BÁO CÁO VỀ TÀI SẢN / ASSET REPORT
A18: STT No | B18: Nội dung Indicator | C18: Mã chỉ tiêu Code | D18: Ngày 31 tháng 01 năm 2025 As at 31 Jan 2025 | E18: Ngày 31 tháng 12 năm 2024 As at 31 Dec 2024 | F18: %/cùng kỳ năm trước %/against last year
A19: I | B19: TÀI SẢN ASSETS | C19: 2200
A20: I.1 | B20: Tiền và các khoản tương đương tiền Cash and Cash Equivalents | C20: 2201 | D20: 162739470657 | E20: 260940922040 | F20: 1.5809258
B21: Tiền Cash | C21: 2202
A22: ... | B22: ... | C22: ... | D22: ... | E22: ... | F22: ...
B23: Tiền gửi ngân hàng Cash at bank | C23: 2203 | D23: 162739470657 | E23: 260940922040 | F23: 1.5809258
A24: ... | B24: ... | C24: ... | D24: ... | E24: ... | F24: ...
B25: Tiền gửi của nhà đầu tư cho hoạt động mua chứng chỉ quỹ Cash at bank for Fund's subscription | C25: 2203.1 | D25: 1114420907 | E25: 9923142711 | F25: 0.038859656
B26: Tiền phải trả cho Nhà đầu tư về cổ tức và mua lại chứng chỉ quỹ Cash at bank for Fund's dividend payment and redemption | C26: 2203.2 | D26: 4991136 | E26: 4391073 | F26: 0.50972162
B27: Tiền gửi ngân hàng cho hoạt động của Quỹ Cash at bank for Fund's operation | C27: 2203.3 | D27: 620058614 | E27: 2213388256 | F27: 0.21151881
B28: Tiền gửi ký quỹ cho hoạt động đầu tư chứng khoán phái sinh Margin account for trading derivatives | C28: 2203.4 | D28: 0 | E28: 0
B29: Tiền, tương đương tiền Cash, cash equivalents | C29: 2203.5 | D29: 161000000000 | E29: 248800000000 | F29: 2.2574313
A30: I.2 | B30: Các khoản đầu tư (kê chi tiết) Investments | C30: 2205 | D30: 1480776952181 | E30: 1383107257612 | F30: 3.2126466
A31: ... | B31: ... | C31: ... | D31: ... | E31: ... | F31: ...
B32: Cổ phiếu, chứng chỉ quỹ niêm yết Listed Shares, fund certificates | C32: 2205.1 | D32: 0 | E32: 0
B33: Cổ phiếu, chứng chỉ quỹ chưa niêm yết Unlisted Shares, fund certifictes | C33: 2205.2 | D33: 0 | E33: 0
B34: Trái phiếu Bonds | C34: 2205.3 | D34: 1054554046578 | E34: 956884352009 | F34: 2.4759369
B35: Công cụ thị trường tiền tệ Money market instruments | C35: 2205.4 | D35: 265122905603 | E35: 265122905603 | F35: 7.5749402
B36: Hợp đồng tiền gửi có kỳ hạn trên ba (03) tháng Deposits with term over three (03) months | C36: 2205.5 | D36: 161100000000 | E36: 161100000000
B37: Quyền mua chứng khoán Investment - Rights | C37: 2205.6 | D37: 0 | E37: 0
B38: Hợp đồng tương lai chỉ số Index future contracts | C38: 2205.7 | D38: 0 | E38: 0
B39: Đầu tư khác Other investments | C39: 2205.8 | D39: 0 | E39: 0
B40: Hợp đồng mua lại đảo ngược Reverse repo contracts | C40: 2205.9 | D40: 0 | E40: 0
A41: I.3 | B41: Thu từ cho thuê bất động sản đầu tư (không áp dụng) Receivables from rental of investment property (not applicable) | C41: 2220 | D41: 0 | E41: 0
A42: ... | B42: ... | C42: ... | D42: ... | E42: ... | F42: ...
A43: I.4 | B43: Cổ tức, trái tức được nhận Dividend, Coupon receivables | C43: 2206 | D43: 36142849246 | E43: 30288039815 | F43: 2.0484235
A44: ... | B44: ... | C44: ... | D44: ... | E44: ... | F44: ...
B45: Phải thu cổ tức Dividend receivables | C45: 2206.1 | D45: 0 | E45: 0
B46: Phải thu trái tức Coupon receivables | C46: 2206.2 | D46: 36142849246 | E46: 30288039815 | F46: 2.0484235
A47: I.5 | B47: Lãi được nhận Interest receivables | C47: 2207 | D47: 12944287808 | E47: 13444436440 | F47: 114.53886
A48: ... | B48: ... | C48: ... | D48: ... | E48: ... | F48: ...
B49: Phải thu lãi tiền gửi Interest receivable from bank deposits | C49: 2207.1 | D49: 4757027535 | E49: 3842326851 | F49: 42.093048
B50: Phải thu lãi công cụ thị trường tiền tệ Interest receivable from Money market instruments | C50: 2207.2 | D50: 8187260273 | E50: 9602109589
B51: Phải thu lãi hợp đồng mua lại đảo ngược Interest receivable from reverse repo contracts | C51: 2207.3 | D51: 0 | E51: 0
A52: I.6 | B52: Tiền bán bất động sản chờ thu (không áp dụng) Real Estate Proceeds Receivables (not applicale) | C52: 2221 | D52: 0 | E52: 0
A53: ... | B53: ... | C53: ... | D53: ... | E53: ... | F53: ...
A54: I.7 | B54: Tiền bán chứng khoán chờ thu Securities Trading Receivables | C54: 2208 | D54: 0 | E54: 0
A55: ... | B55: ... | C55: ... | D55: ... | E55: ... | F55: ...
A56: I.8 | B56: Các khoản phải thu khác Other Receivables | C56: 2210 | D56: 0 | E56: 0
A57: ... | B57: ... | C57: ... | D57: ... | E57: ... | F57: ...
B58: Dự phòng giảm giá tài sản nhận thế chấp Impairment of devaluation of pledged assets | C58: 2210.1 | D58: 0 | E58: 0
B59: Dự phòng nợ phải thu khó đòi Provision for doubtful debt | C59: 2210.2 | D59: 0 | E59: 0
B60: Các khoản phải thu khác Other Receivables | C60: 2210.3 | D60: 0 | E60: 0
A61: I.9 | B61: Các tài sản khác Other Assets | C61: 2211 | D61: 0 | E61: 0
A62: ... | B62: ... | C62: ... | D62: ... | E62: ... | F62: ...
A63: I.10 | B63: TỔNG TÀI SẢN TOTAL ASSETS | C63: 2212 | D63: 1692603559892 | E63: 1687780655907 | F63: 2.9101647
A64: II | B64: NỢ LIABILITIES | C64: 2213
A65: II.1 | B65: Tiền phải thanh toán mua bất động sản (không áp dụng) Real Estate Trading Payables (not applicable) | C65: 2222 | D65: 0 | E65: 0
A66: ... | B66: ... | C66: ... | D66: ... | E66: ... | F66: ...
A67: II.2 | B67: Tiền phải thanh toán mua chứng khoán Securities Trading Payables | C67: 2214 | D67: 0 | E67: 0
A68: ... | B68: ... | C68: ... | D68: ... | E68: ... | F68: ...
A69: II.3 | B69: Các khoản phải trả khác Other Payables | C69: 2215 | D69: 6254402891 | E69: 39206607425 | F69: 0.20605497
A70: ... | B70: ... | C70: ... | D70: ... | E70: ... | F70: ...
B71: Phải trả nhà đầu tư Payables to investors | C71: 2215.1 | D71: 3591754541 | E71: 36492948218 | F71: 0.12194824
B72: Phải trả cho nhà đầu tư chờ mua chứng chỉ quỹ Subscription Pending allotment | C72: 2215.1.1 | D72: 1114420907 | E72: 9923142711 | F72: 0.038859656
B73: Phải trả nhà đầu tư trên tài sản giữ hộ Payables to investors for investment bought on behalf | C73: 2215.1.2 | D73: 0 | E73: 0
B74: Phải trả nhà đầu tư trên cổ tức đã thu Payables to investors for collected dividend | C74: 2215.1.3 | D74: 0 | E74: 0
B75: Phải trả cho Nhà đầu tư về mua lại chứng chỉ quỹ Redemption payable to investors | C75: 2215.1.4 | D75: 2477333634 | E75: 26569805507 | F75: 3.1965143
B76: Thuế và các khoản phải nộp Nhà nước Tax payables and obligations to the State Budget | C76: 2215.2 | D76: 72785573 | E76: 137193084 | F76: 35.403334
B77: Phải trả phí phát hành, mua lại chứng chỉ quỹ cho Đại lý phân phối và Công ty quản lý quỹ Subscription and Redemption fee payable to distributors and Fund Management Company | C77: 2215.3 | D77: 367542413 | E77: 405658375 | F77: 35.885493
B78: Phải trả thu nhập cho nhà đầu tư Income payable to investors | C78: 2215.4 | D78: 0 | E78: 0
B79: Phải trả thù lao Ban đại diện quỹ Remuneration Payable to Fund's Board of Representatives | C79: 2215.5 | D79: 6509589 | E79: 12000000 | F79: 1.0002139
B80: Phải trả phí quản lý cho công ty quản lý quỹ Management fee payable | C80: 2215.6 | D80: 1708862226 | E80: 1650065860 | F80: 3.3648248
B81: Phải trả phí quản trị quỹ Fund Administration fee payable | C81: 2215.7 | D81: 46993711 | E81: 45376811 | F81: 3.3648247
B82: Phải trả phí giám sát Supervisory service fee payable | C82: 2215.8 | D82: 62658281 | E82: 60502415 | F82: 3.364825
B83: Phí giao dịch Transaction fee | C83: 2215.9 | D83: 192537125 | E83: 192537125 | F83: 1
B84: Phải trả phí môi giới Brokerage fee payable | C84: 2215.9.1 | D84: 192537125 | E84: 192537125 | F84: 1
B85: Phải trả phí phát hành thanh toán bù trừ chứng khoán Clearing Settlement fee payable | C85: 2215.9.2 | D85: 0 | E85: 0
B86: Trích trước phí lưu ký tài sản Quỹ mở Accrued expense for Custodian fee | C86: 2215.10 | D86: 51091815 | E86: 49976921 | F86: 2.7352998
B87: Phí lưu ký - bảo quản tài sản Custodian service - Safe Custody Fee | C87: 2215.10.1 | D87: 49841815 | E87: 48126921 | F87: 2.9442218
B88: Phí lưu ký - giao dịch chứng khoán Custodian service - Transaction fee | C88: 2215.10.2 | D88: 500000 | E88: 1100000 | F88: 0.5
B89: Phí lưu ký cho chứng khoán cơ sở, phí quản lý vị thế và tài sản phái sinh trả cho VSDC Custodian service - Depository fee, Position and Margin management fee paid to VSDC | C89: 2215.10.3 | D89: 750000 | E89: 750000 | F89: 1
B90: Phải trả phí kiểm toán Audit fee payable | C90: 2215.11 | D90: 86905479 | E90: 74480000 | F90: 0.95037125
B91: Phải trả phí họp đại hội thường niên General meeting expense payable | C91: 2215.12 | D91: 42983485 | E91: 39618616
B92: Phải trả phí báo cáo thường niên Annual report fee payable | C92: 2215.13 | D92: 0 | E92: 0
B93: Phải trả phí dịch vụ đại lý chuyển nhượng Transfer Agency fee payable | C93: 2215.14 | D93: 11000000 | E93: 11000000 | F93: 1
B94: Dự chi phí tính giá trị tài sản ròng tham chiếu (iNAV) cho HOSE Service fee payable to HOSE for calculating iNAV | C94: 2215.15 | D94: 0 | E94: 0
B95: Dự chi phí cấp quyền sử dụng chỉ số cho HOSE Authorising index service fee payable to HOSE | C95: 2215.16 | D95: 0 | E95: 0
B96: Phải trả khác Other payables | C96: 2215.17 | D96: 12778653 | E96: 35250000 | F96: 0.47225555
B97: Phải trả phí báo giá Price feed fee payable | C97: 2215.17.1 | D97: 12141667 | E97: 35250000 | F97: 1.5166666
B98: Trích trước phí công tác, họp của ban đại diện Accrued expense for Fund's Board of Representatives travelling, meeting | C98: 2215.17.2 | D98: 0 | E98: 0
B99: Trích trước phí quản lý thường niên trả UBCKNN Accrued expense for Annual Management Fee pay to SSC | C99: 2215.17.3 | D99: 636986 | E99: 0 | F99: 0.078299538
B100: Phải trả khác Other payables | C100: 2215.17.4 | D100: 0 | E100: 0 | F100: 0
B101: Vay ngắn hạn - hợp đồng repo Short-term loans - Repo contracts | C101: 2215.18 | D101: 0 | E101: 0
B102: Gốc hợp đồng repo Principal of repo contracts | C102: 2215.18.1 | D102: 0 | E102: 0
B103: Trích trước lãi vay ngắn hạn Accrued Interest Expense | C103: 2215.18.2 | D103: 0 | E103: 0
...

Sheet BCKetQuaHoatDong_06028
A1: Phụ lục XXVI. Mẫu báo cáo về hoạt động của Quỹ Appendix XXVI. Report on Fund's Operation
A2: (Ban hành kèm theo Thông tư số 98/2020/TT-BTC ngày 16 tháng 11 năm 2020 của Bộ trưởng Bộ Tài Chính về hướng dẫn hoạt động và quản lý quỹ đầu tư chứng khoán) (Issued in association with Circular 98/2020/TT-BTC dated 16 November 2020 of the Minister of Finance on guiding the operation and management of the securities investment funds)
A3: BÁO CÁO HOẠT ĐỘNG ĐẦU TƯ CỦA QUỸ MỞ REPORT ON OPEN ENDED FUND'S INVESTMENT ACTIVITIES
A5: =TONGQUAN!C2 -> Tháng 01 năm 2025 / Jan 2025
A7: Tên Công ty quản lý quỹ: | C7: =TONGQUAN!D5 -> Công ty Cổ phần Quản lý Quỹ Đầu tư Dragon Capital Việt Nam
A8: Fund Management Company: | C8: =TONGQUAN!D6 -> Dragon Capital Vietfund Management Joint Stock Company
A9: Tên ngân hàng giám sát: | C9: =TONGQUAN!D7 -> Ngân hàng TNHH Một thành viên Standard Chartered (Việt Nam)
A10: Supervising bank: | C10: =TONGQUAN!D8 -> Standard Chartered Bank (Vietnam) Limited
A11: Tên Quỹ: | C11: =TONGQUAN!D9 -> Quỹ Đầu tư Trái phiếu DC
A12: Fund name: | C12: =TONGQUAN!D10 -> DC Bond Fund (DCBF)
A13: Ngày lập báo cáo: | C13: =TONGQUAN!D11 -> Ngày 03 tháng 02 năm 2025
A14: Reporting Date: | C14: =TONGQUAN!D12 -> 03 Feb 2025
A16: A. | B16: BÁO CÁO CHUNG VỀ HOẠT ĐỘNG ĐẦU TƯ CỦA QUỸ/GENERAL INFORMATION ON FUND'S INVESTMENT ACTIVITIES
A17: II | B17: BÁO CÁO KẾT QUẢ HOẠT ĐỘNG / PROFIT AND LOSS REPORT
A18: STT No | B18: Nội dung Indicator | C18: Mã chỉ tiêu Code | D18: Tháng 01 năm 2025 Jan 2025 | E18: Tháng 12 năm 2024 Dec 2024 | F18: Lũy kế từ đầu năm Accumulated from beginning of year
A19: I | B19: Thu nhập từ hoạt động đầu tư Income from Investment Activities | C19: 2220 | D19: 11300234028 | E19: 10832961716 | F19: 11300234028
A20: 1 | B20: Thu từ bất động sản cho thuê (không áp dụng) Income from rental property (not applicable) | C20: 2223 | D20: 0 | E20: 0 | F20: 0
A21: ... | B21: ... | C21: ... | D21: ... | E21: … | F21: …
A22: 2 | B22: Cổ tức, trái tức được nhận Dividend income, interest income from bonds | C22: 2221 | D22: 8242672705 | E22: 7749155913 | F22: 8242672705
A23: ... | B23: ... | C23: ... | D23: ... | E23: … | F23: …
B24: Cổ tức được nhận Dividends income | C24: 2221.1 | D24: 0 | E24: 0 | F24: 0
B25: Trái tức được nhận Interest income from bonds | C25: 2221.2 | D25: 8242672705 | E25: 7749155913 | F25: 8242672705
A26: 3 | B26: Lãi được nhận Interest income | C26: 2222 | D26: 3057561323 | E26: 3083805803 | F26: 3057561323
A27: ... | B27: ... | C27: ... | D27: ... | E27: ... | F27: ...
B28: Lãi tiền gửi ngân hàng Interest income from bank deposits | C28: 2222.1 | D28: 1509150365 | E28: 1472655119 | F28: 1509150365
B29: Lãi công cụ thị trường tiền tệ Interest income from Money market instruments | C29: 2222.2 | D29: 1548410958 | E29: 1611150684 | F29: 1548410958
B30: Lãi hợp đồng mua lại đảo ngược Interest income from reverse repo contracts | C30: 2222.3 | D30: 0 | E30: 0 | F30: 0
A31: 4 | B31: Các khoản thu nhập khác Other incomes | C31: 2223 | D31: 0 | E31: 0 | F31: 0
A32: ... | B32: ... | C32: ... | D32: ... | E32: ... | F32: ...
B33: Thu nhập khác về đầu tư Other investment incomes | C33: 2223.1 | D33: 0 | E33: 0 | F33: 0
B34: Thu nhập khác Other incomes | C34: 2223.2 | D34: 0 | E34: 0 | F34: 0
B35: Chi phí dự phòng nợ phải thu khó đòi về cổ tức, tiền lãi và xử lý tổn thất nợ phải thu khó đòi về cổ tức, tiền lãi Provision expense for bad debts from dividends, interest income and written off bad debts from dividends, interest income | C35: 2223.3 | D35: 0 | E35: 0 | F35: 0
A36: II | B36: Chi phí Expenses | C36: 2224 | D36: 1937332277 | E36: 1954948016 | F36: 1937332277
A37: 1 | B37: Chi phí quản lý trả cho Công ty quản lý quỹ Management Fee paid to Fund Management Company | C37: 2225 | D37: 1708862226 | E37: 1650065860 | F37: 1708862226
A38: ... | B38: ... | C38: ... | D38: ... | E38: ... | F38: ...
A39: 2 | B39: Chi phí lưu ký, giám sát trả cho Ngân hàng Giám sát/VSDC Custody fee, Supervising fee paid to Supervising Bank/VSDC | C39: 2226 | D39: 116555410 | E39: 111379944 | F39: 116555410
A40: ... | B40: ... | C40: ... | D40: ... | E40: ... | F40: ...
B41: Chi phí dịch vụ lưu ký - bảo quản tài sản Custodian service - Safe Custody Fee | C41: 2226.1 | D41: 49841815 | E41: 48126921 | F41: 49841815
B42: Chi phí dịch vụ lưu ký - giao dịch chứng khoán Custodian service - Transaction fee | C42: 2226.2 | D42: 2800000 | E42: 1300000 | F42: 2800000
B43: Chi phí dịch vụ lưu ký cho chứng khoán cơ sở, phí quản lý vị thế và tài sản phái sinh trả cho VSDC Custodian service - Depository fee, Position and Margin management fee paid to VSDC | C43: 2226.3 | D43: 1255314 | E43: 1450608 | F43: 1255314
B44: Chi phí giám sát Supervisory fee | C44: 2226.4 | D44: 62658281 | E44: 60502415 | F44: 62658281
A45: 3 | B45: Chi phí quản trị quỹ và các chi phí khác mà công ty quản lý quỹ trả cho tổ chức cung cấp dịch vụ có liên quan Fund Administration Fee, and other fees paid to relevant Fund's service providers | C45: 2227 | D45: 57993711 | E45: 56376811 | F45: 57993711
A46: ... | B46: ... | C46: ... | D46: ... | E46: ... | F46: ...
B47: Chi phí quản trị Quỹ Fund Administration Fee | C47: 2227.1 | D47: 46993711 | E47: 45376811 | F47: 46993711
B48: Chi phí dịch vụ Đại lý Chuyển nhượng Transfer Agency Fee | C48: 2227.2 | D48: 11000000 | E48: 11000000 | F48: 11000000
A49: 4 | B49: Chi phí dịch vụ quản lý bất động sản (không áp dụng) Real Estate Management Service fee (not applicable) | D49: 0 | E49: 0 | F49: 0
A50: ... | B50: ... | C50: ... | D50: ... | E50: ... | F50: ...
A51: 5 | B51: Chi phí dịch vụ định giá bất động sản (không áp dụng) Real estate valuation service fees (not applicable) | D51: 0 | E51: 0 | F51: 0
A52: ... | B52: ... | C52: ... | D52: ... | E52: ... | F52: ...
A53: 6 | B53: Chi phí kiểm toán trả cho tổ chức kiểm toán Audit fee | C53: 2228 | D53: 12425479 | E53: 11813303 | F53: 12425479
A54: ... | B54: ... | C54: ... | D54: ... | E54: ... | F54: ...
A55: 7 | B55: Chi phí dịch vụ tư vấn pháp lý, dịch vụ báo giá và các dịch vụ hợp lý khác, thù lao trả cho ban đại diện quỹ Legal consultancy expenses, price feed fee, other valid expenses, remuneration paid to Fund's Board of Representatives | C55: 2229 | D55: 18651256 | E55: 22070048 | F55: 18651256
A56: ... | B56: ... | C56: ... | D56: ... | E56: ... | F56: ...
B57: Thù lao Ban đại diện Quỹ Remuneration of Fund's Board of Representatives | C57: 2229.1 | D57: 6509589 | E57: 6508197 | F57: 6509589
B58: Chi phí cung cấp báo giá chứng khoán Price feed fee | C58: 2229.2 | D58: 12141667 | E58: 11877717 | F58: 12141667
B59: Chi phí dịch vụ tư vấn pháp lý Legal consultancy expenses | C59: 2229.3 | D59: 0 | E59: 3684134 | F59: 0
A60: 8 | B60: Chi phí dự thảo, in ấn, gửi bản cáo bạch, bản cáo bạch tóm tắt, báo cáo tài chính, xác nhận giao dịch, sao kê tài khoản và các tài liệu khác cho nhà đầu tư; chi phí công bố thông tin của quỹ; chi phí tổ chức họp đại hội nhà đầu tư, ban đại diện quỹ Fee for drafting, printing, distribution of prospectus, summarised prospectus, financial statements, transaction confirmations, account statements and other documents to investors; information disclosure fee; fee for organising annual general meeting, board of representatives meeting | C60: 2230 | D60: 3364869 | E60: 14463673 | F60: 3364869
A61: ... | B61: ... | C61: ... | D61: ... | E61: ... | F61: ...
B62: Chi phí họp Đại hội Quỹ Meeting expenses | C62: 2230.1 | D62: 3364869 | E62: 14463673 | F62: 3364869
B63: Chi phí báo cáo thường niên Annual report expenses | C63: 2230.2 | D63: 0 | E63: 0 | F63: 0
B64: Chi phí họp, công tác của Ban đại diện Fund's Board of Representatives meeting, travelling expenses | C64: 2230.3 | D64: 0 | E64: 0 | F64: 0
B65: Chi phí công bố thông tin của Quỹ Expenses of information disclosure of the Fund | C65: 2230.4 | D65: 0 | E65: 0 | F65: 0
B66: Chi phí thiết kế, in ấn, gửi thư… Designing, printing, posting... expenses | C66: 2230.5 | D66: 0 | E66: 0 | F66: 0
A67: 9 | B67: Chi phí liên quan đến thực hiện các giao dịch tài sản của Quỹ Expenses related to execution of Fund’s asset transactions | C67: 2231 | D67: 17303440 | E67: 85706631 | F67: 17303440
A68: ... | B68: ... | C68: ... | D68: ... | E68: ... | F68: ...
B69: Chi phí môi giới Brokerage fee | C69: 2231.1 | D69: 16669302 | E69: 85256631 | F69: 16669302
B70: Chi phí thanh toán bù trừ Clearing settlement fee | C70: 2231.2 | D70: 634138 | E70: 450000 | F70: 634138
B71: Chi phí khác Other Expenses | C71: 2231.3 | D71: 0 | E71: 0 | F71: 0
A72: 10 | B72: Các loại chi phí khác Other expenses | C72: 2232 | D72: 2175886 | E72: 3071746 | F72: 2175886
A73: ... | B73: ... | C73: ... | D73: ... | E73: ... | F73: ...
B74: Chi phí thiết lập Quỹ Set up Expenses | C74: 2232.1 | D74: 0 | E74: 0 | F74: 0
B75: Phí niêm yết, đăng ký chứng khoán Listing, registration fees | C75: 2232.2 | D75: 0 | E75: 0 | F75: 0
B76: Phí quản lý thường niên trả cho UBCKNN Annual management fee paid to SSC | C76: 2232.3 | D76: 636986 | E76: 635246 | F76: 636986
B77: Phí ngân hàng Bank charges | C77: 2232.4 | D77: 1538900 | E77: 2436500 | F77: 1538900
B78: Chi phí lãi vay Borrowing expense | C78: 2232.5 | D78: 0 | E78: 0 | F78: 0
B79: Chi phí khác Other Expenses | C79: 2232.6 | D79: 0 | E79: 0 | F79: 0
B80: Phí thực hiện quyền trả cho VSDC Fee paid to VSDC for getting the list of investors | C80: 2232.7 | D80: 0 | E80: 0 | F80: 0
A81: III | B81: Thu nhập ròng từ hoạt động đầu tư (= I - II) Net Income from Investment Activities (= I - II) | C81: 2233 | D81: 9362901751 | E81: 8878013700 | F81: 9362901751
A82: IV | B82: Lãi / (lỗ) từ hoạt động đầu tư Gain / (Loss) from Investment Activities | C82: 2234 | D82: -1403376355 | E82: 225500161 | F82: -1403376355
A83: 1 | B83: Lãi (lỗ) thực tế phát sinh từ hoạt động đầu tư hoặc chuyển nhượng bất động sản Realised Gain / (Loss) from disposal of investment or real estate transfer | C83: 2235 | D83: 15160000 | E83: 1211063828 | F83: 15160000
A84: 2 | B84: Thay đổi về giá trị của các khoản đầu tư trong kỳ Unrealised Gain / (Loss) due to market price | C84: 2236 | D84: -1418536355 | E84: -985563667 | F84: -1418536355
A85: V | B85: Thay đổi của giá trị tài sản ròng của Quỹ do các hoạt động đầu tư trong kỳ (III + IV) Change of Net Asset Value of the Fund due to investment activities during the period (= III + IV) | C85: 2237 | D85: 7959525396 | E85: 9103513861 | F85: 7959525396
A86: VI | B86: Giá trị tài sản ròng đầu kỳ Net Asset Value at the beginning of period | C86: 2238 | D86: 1648574048482 | E86: 1633591480269 | F86: 1648574048482
A87: VII | B87: Thay đổi giá trị tài sản ròng của Quỹ trong kỳ, Trong đó Change of Net Asset Value of the Fund during the period, of which | C87: 2239 | D87: 37775108519 | E87: 14982568213 | F87: 37775108519
A88: 1 | B88: Thay đổi giá trị tài sản ròng của Quỹ do các hoạt động đầu tư của Quỹ trong kỳ Change of Net Asset Value due to investment activities during the period | C88: 2239.1 | D88: 7959525396 | E88: 9103513861 | F88: 7959525396
A89: 2 | B89: Thay đổi giá trị tài sản ròng của Quỹ do việc chi trả lợi tức/ cổ tức của Quỹ cho các nhà đầu tư trong kỳ Change of Net Asset Value due to dividends payment to investors during the period | C89: 2239.2 | D89: 0 | E89: 0 | F89: 0
A90: 3 | B90: Thay đổi giá trị tài sản ròng do phát hành thêm/mua lại chứng chỉ quỹ Change of Net Asset Value due to subscription/redemption during the period | C90: 2239.3 | D90: 29815583123 | E90: 5879054352 | F90: 29815583123
B91: Thay đổi giá trị tài sản ròng do phát hành thêm Chứng chỉ Quỹ Change of Net Asset Value due to subscription during the period | C91: 2239.3.1 | D91: 102603986527 | E91: 143294899607 | F91: 102603986527
B92: Thay đổi giá trị tài sản ròng do mua lại Chứng chỉ Quỹ Change of Net Asset Value due to redemption during the period | C92: 2239.3.2 | D92: -72788403404 | E92: -137415845255 | F92: -72788403404
A93: VIII | B93: Giá trị tài sản ròng cuối kỳ Net Asset Value at the end of period | C93: 2243 | D93: 1686349157001 | E93: 1648574048482 | F93: 1686349157001
A94: IX | B94: Lợi nhuận bình quân năm (chỉ áp dụng đối với báo cáo năm) Average annual profit (only applicable to annual report) | C94: 2244 | D94: 0 | E94: 0 | F94: 0
B95: Tỷ suất lợi nhuận bình quân năm (chỉ áp dụng đối với báo cáo năm) Average annual rate of return (only applicable to annual report) | C95: 2245 | D95: 0 | E95: 0 | F95: 0
A97: Đại diện có thẩm quyền của Ngân hàng giám sát | E97: Đại diện có thẩm quyền của Công ty quản lý Quỹ
A98: Authorised Representative of Supervisory Bank | E98: Authorised Representative of Fund Management Company
A105: =TONGQUAN!C19 -> Ngân hàng TNHH MTV Standard Chartered (Việt Nam) | E105: Công ty Cổ phần Quản lý Quỹ Đầu tư Dragon Capital Việt Nam
A106: =TONGQUAN!C20 -> Vũ Quang Phan | E106: Lê Hoàng Anh
A107: =TONGQUAN!C21 -> Phó phòng Dịch vụ nghiệp vụ giám sát Quỹ | E107: Quyền Giám đốc nghiệp vụ hỗ trợ đầu tư

Sheet BCDanhMucDauTu_06029
A1: Phụ lục XXVI. Mẫu báo cáo về hoạt động của Quỹ Appendix XXVI. Report on Fund's Operation
A2: (Ban hành kèm theo Thông tư số 98/2020/TT-BTC ngày 16 tháng 11 năm 2020 của Bộ trưởng Bộ Tài Chính về hướng dẫn hoạt động và quản lý quỹ đầu tư chứng khoán) (Issued in association with Circular 98/2020/TT-BTC dated 16 November 2020 of the Minister of Finance on guiding the operation and management of the securities investment funds)
A3: BÁO CÁO HOẠT ĐỘNG ĐẦU TƯ CỦA QUỸ MỞ REPORT ON OPEN ENDED FUND'S INVESTMENT ACTIVITIES
A5: =TONGQUAN!C1 -> Tại ngày 31 tháng 01 năm 2025 / As at 31 Jan 2025
A7: Tên Công ty quản lý quỹ: | C7: =TONGQUAN!D5 -> Công ty Cổ phần Quản lý Quỹ Đầu tư Dragon Capital Việt Nam
A8: Fund Management Company: | C8: =TONGQUAN!D6 -> Dragon Capital Vietfund Management Joint Stock Company
A9: Tên ngân hàng giám sát: | C9: =TONGQUAN!D7 -> Ngân hàng TNHH Một thành viên Standard Chartered (Việt Nam)
A10: Supervising bank: | C10: =TONGQUAN!D8 -> Standard Chartered Bank (Vietnam) Limited
A11: Tên Quỹ: | C11: =TONGQUAN!D9 -> Quỹ Đầu tư Trái phiếu DC
A12: Fund name: | C12: =TONGQUAN!D10 -> DC Bond Fund (DCBF)
A13: Ngày lập báo cáo: | C13: =TONGQUAN!D11 -> Ngày 03 tháng 02 năm 2025
A14: Reporting Date: | C14: =TONGQUAN!D12 -> 03 Feb 2025
A16: A. | B16: BÁO CÁO CHUNG VỀ HOẠT ĐỘNG ĐẦU TƯ CỦA QUỸ/GENERAL INFORMATION ON FUND'S INVESTMENT ACTIVITIES
A17: III | B17: BÁO CÁO DANH MỤC ĐẦU TƯ / INVESTMENT PORTFOLIO REPORT
A18: STT No. | B18: Loại Category | C18: Mã chỉ tiêu Code | D18: Số Lượng Quantity | E18: Giá thị trường hoặc giá trị hợp lý tại ngày báo cáo Market price | F18: Tổng giá trị (Đồng) Value (VND) | G18: Tỷ lệ % Tổng giá trị tài sản của Quỹ % of total asset
A19: I | B19: BẤT ĐỘNG SẢN ĐẦU TƯ (KHÔNG ÁP DỤNG) REAL ESTATE INVESTMENT (NOT APPLICABLE)
B21: TỔNG TOTAL | C21: 2264
A22: II | B22: CỔ PHIẾU NIÊM YẾT, ĐĂNG KÝ GIAO DỊCH, CHỨNG CHỈ QUỸ NIÊM YẾT SHARES LISTED, SHARES REGISTERED FOR TRADING, LISTED FUND CERTIFICATES | C22: 2246
B24: TỔNG TOTAL | C24: 2247
A25: III | B25: CỔ PHIẾU CHƯA NIÊM YẾT, ĐĂNG KÝ GIAO DỊCH, CHỨNG CHỈ QUỸ KHÔNG NIÊM YẾT SHARES UNLISTED, UNREGISTERED FOR TRADING, UNLISTED FUND CERTIFICATES | C25: 2248
B27: TỔNG TOTAL | C27: 2249 | F27: 0 | G27: 0
A28: IV | B28: TRÁI PHIẾU BONDS | C28: 2251
A30: 1 | B30: Trái phiếu niêm yết Listed bonds | C30: 2251.1 | F30: 894010461508 | G30: 0.52818657
A31: 1.1 | B31: BAF122029 | C31: 2251.1.1 | D31: 390000 | E31: 100492.19 | F31: 39191953710 | G31: 0.023154834
A32: 1.2 | B32: BAF123020 | C32: 2251.1.2 | D32: 452357 | E32: 100711.39 | F32: 45557504056 | G32: 0.026915638
A33: 1.3 | B33: CII124021 | C33: 2251.1.3 | D33: 993 | E33: 99996998 | F33: 99297019014 | G33: 0.058665255
A34: 1.4 | B34: HDB124006 | C34: 2251.1.4 | D34: 100000 | E34: 100418.79 | F34: 10041878800 | G34: 0.0059328002
A35: 1.5 | B35: HDB124018 | C35: 2251.1.5 | D35: 1000000 | E35: 99807.273 | F35: 99807273000 | G35: 0.058966716
A36: 1.6 | B36: MML121021 | C36: 2251.1.6 | D36: 400230 | E36: 99950.705 | F36: 40003270662 | G36: 0.023634164
A37: 1.7 | B37: MSN123008 | C37: 2251.1.7 | D37: 1050000 | E37: 99658.655 | F37: 104641587750 | G37: 0.061822857
A38: 1.8 | B38: MSN123009 | C38: 2251.1.8 | D38: 250000 | E38: 100042.11 | F38: 25010527500 | G38: 0.014776365
A39: 1.9 | B39: TCX124013 | C39: 2251.1.9 | D39: 363794 | E39: 99415.538 | F39: 36166776231 | G39: 0.021367541
A40: 1.10 | B40: TNG122017 | C40: 2251.1.10 | D40: 1100000 | E40: 100972.2 | F40: 111069422200 | G40: 0.065620459
A41: 1.11 | B41: VBA122001 | C41: 2251.1.11 | D41: 220480 | E41: 98103.165 | F41: 21629785819 | G41: 0.012779003
A42: 1.12 | B42: VIC123028 | C42: 2251.1.12 | D42: 380000 | E42: 99213.767 | F42: 37701231460 | G42: 0.022274106
... A45: 1.15 | B45: VRE12007 | C45: 2251.1.15 | D45: 200000 | E45: 100016.75 | F45: 20003349800 | G45: 0.011818095
A46: 2 | B46: Trái phiếu chưa niêm yết Unlisted Bonds | C46: 2251.2 | F46: 160543585070 | G46: 0.094850081
A47: 2.1 | B47: CII12403 | C47: 2251.2.1 | D47: 360 | E47: 99963194 | F47: 35986749840 | G47: 0.021261181
A48: 2.2 | B48: KBC12401 | C48: 2251.2.2 | D48: 83 | E48: 993643810 | F48: 82472436230 | G48: 0.048725194
A49: 2.3 | B49: KDH12101 | C49: 2251.2.3 | D49: 35 | E49: 1002411400 | F49: 35084399000 | G49: 0.020728066
A50: 2.4 | B50: KDH12202 | C50: 2251.2.4 | D50: 7 | E50: 1000000000 | F50: 7000000000 | G50: 0.0041356406
B51: TỔNG TOTAL | C51: 2252 | F51: 1054554046578 | G51: 0.62303665
A52: V | B52: CÁC LOẠI CHỨNG KHOÁN KHÁC OTHER SECURITIES | C52: 2253
A54: 1 | B54: Quyền mua chứng khoán Investment - Rights | C54: 2253.1 | F54: 0 | G54: 0
A55: 2 | B55: Chi tiết loại hợp đồng phái sinh(*) Index future contracts | C55: 2253.2 | F55: 0 | G55: 0
B56: TỔNG TOTAL | C56: 2254 | F56: 0 | G56: 0
B57: TỔNG CÁC LOẠI CHỨNG KHOÁN TOTAL TYPES OF SECURITIES | C57: 2255 | F57: 1054554046578 | G57: 0.62303665
A58: VI | B58: CÁC TÀI SẢN KHÁC OTHER ASSETS | C58: 2256
A60: 1 | B60: Cổ tức được nhận Dividend receivables | C60: 2256.1 | F60: 0 | G60: 0
A61: 2 | B61: Lãi trái phiếu được nhận Coupon receivables | C61: 2256.2 | F61: 36142849246 | G61: 0.021353405
A62: 3 | B62: Lãi tiền gửi và công cụ thị trường tiền tệ được nhận Interest receivables from bank deposits and Money market instruments | C62: 2256.3 | F62: 12944287808 | G62: 0.0076475603
A63: 4 | B63: Tiền bán chứng khoán chờ thu Outstanding Settlement of sales transactions | C63: 2256.4 | F63: 0 | G63: 0
A64: 5 | B64: Phải thu cho khoản cổ phiếu hạn chế chờ mua Receivable from AP/Investors on securities on hold of buying | C64: 2256.5 | F64: 0 | G64: 0
A65: 6 | B65: Phải thu khác Other receivables | C65: 2256.6 | F65: 0 | G65: 0
A66: 7 | B66: Tài sản khác Other assets | C66: 2256.7 | F66: 0 | G66: 0
B67: TỔNG TOTAL | C67: 2257 | F67: 49087137054 | G67: 0.029000965
A68: VII | B68: TIỀN CASH | C68: 2258
A69: 1 | B69: Tiền, tương đương tiền Cash, Cash Equivalent | C69: 2259 | F69: 162739470657 | G69: 0.096147423
A71: 1.1 | B71: Tiền gửi ngân hàng Cash at Bank | C71: 2259.1 | F71: 1739470657 | G71: 0.0010276894
A72: 1.2 | B72: Các khoản tương đương tiền Cash Equivalents | C72: 2259.2 | F72: 161000000000 | G72: 0.095119734
A73: 2 | B73: Tiền gửi ngân hàng có kỳ hạn trên 3 tháng Deposits with term over three (03) months | C73: 2260 | F73: 161100000000 | G73: 0.095178814
A75: 3 | B75: Công cụ thị trường tiền tệ Money market instruments | C75: 2261.1 | F75: 265122905603 | G75: 0.15663615
B76: TỔNG TOTAL | C76: 2262 | F76: 588962376260 | G76: 0.34796239
A77: VIII | B77: Tổng giá trị danh mục Total value of portfolio | C77: 2263 | F77: 1692603559892 | G77: 1
A79: Đại diện có thẩm quyền của Ngân hàng giám sát | E79: Đại diện có thẩm quyền của Công ty quản lý Quỹ
A80: Authorised Representative of Supervisory Bank | E80: Authorised Representative of Fund Management Company
A89: Ngân hàng TNHH MTV Standard Chartered (Việt Nam) | E89: Công ty Cổ phần Quản lý Quỹ Đầu tư Dragon Capital Việt Nam
A90: Vũ Quang Phan | E90: Lê Hoàng Anh
A91: Phó phòng Dịch vụ nghiệp vụ giám sát Quỹ | E91: Quyền Giám đốc nghiệp vụ hỗ trợ đầu tư

Sheet Khac_06030
A1: Phụ lục XXVI. Mẫu báo cáo về hoạt động của Quỹ Appendix XXVI. Report on Fund's Operation
A2: (Ban hành kèm theo Thông tư số 98/2020/TT-BTC ngày 16 tháng 11 năm 2020 của Bộ trưởng Bộ Tài Chính về hướng dẫn hoạt động và quản lý quỹ đầu tư chứng khoán) (Issued in association with Circular 98/2020/TT-BTC dated 16 November 2020 of the Minister of Finance on guiding the operation and management of the securities investment funds)
A3: BÁO CÁO HOẠT ĐỘNG ĐẦU TƯ CỦA QUỸ MỞ REPORT ON OPEN ENDED FUND'S INVESTMENT ACTIVITIES
A5: =TONGQUAN!C2 -> Tháng 01 năm 2025 / Jan 2025
A7: Tên Công ty quản lý quỹ: | C7: =TONGQUAN!D5 -> Công ty Cổ phần Quản lý Quỹ Đầu tư Dragon Capital Việt Nam
A8: Fund Management Company: | C8: =TONGQUAN!D6 -> Dragon Capital Vietfund Management Joint Stock Company
A9: Tên ngân hàng giám sát: | C9: =TONGQUAN!D7 -> Ngân hàng TNHH Một thành viên Standard Chartered (Việt Nam)
A10: Supervising bank: | C10: =TONGQUAN!D8 -> Standard Chartered Bank (Vietnam) Limited
A11: Tên Quỹ: | C11: =TONGQUAN!D9 -> Quỹ Đầu tư Trái phiếu DC
A12: Fund name: | C12: =TONGQUAN!D10 -> DC Bond Fund (DCBF)
A13: Ngày lập báo cáo: | C13: =TONGQUAN!D11 -> Ngày 03 tháng 02 năm 2025
A14: Reporting Date: | C14: =TONGQUAN!D12 -> 03 Feb 2025
A16: A. | B16: BÁO CÁO CHUNG VỀ HOẠT ĐỘNG ĐẦU TƯ CỦA QUỸ/GENERAL INFORMATION ON FUND'S INVESTMENT ACTIVITIES
A17: V | B17: MỘT SỐ CHỈ TIÊU KHÁC / OTHER INDICATORS
A18: STT No | B18: Chỉ tiêu Indicators | C18: Mã chỉ tiêu Code | D18: Tháng 01 năm 2025 Jan 2025 | E18: Tháng 12 năm 2024 Dec 2024
A19: I | B19: CÁC CHỈ TIÊU VỀ HIỆU QUẢ HOẠT ĐỘNG INVESTMENT PERFORMANCE INDICATORS | C19: 2264
A20: 1 | B20: Tỷ lệ giá dịch vụ quản lý quỹ trả cho công ty quản lý quỹ/Giá trị tài sản ròng trung bình trong kỳ (%) Management fee paid to the fund management company/Average NAV (%) | C20: 2265 | D20: 0.012232339 | E20: 0.012198485
A21: 2 | B21: Tỷ lệ giá dịch vụ lưu ký, giám sát trả cho Ngân hàng Giám sát/Giá trị tài sản ròng trung bình trong kỳ (%) Custody and supervising fees paid to the Supervisory Bank/Average NAV (%) | C21: 2266 | D21: 0.00082533851 | E21: 0.00081267747
A22: 3 | B22: Tỷ lệ chi phí dịch vụ quản trị quỹ, và các chi phí khác mà công ty quản lý quỹ trả cho tổ chức cung cấp dịch vụ có liên quan/Giá trị tài sản ròng của quỹ trung bình trong kỳ (%) Fund admin fee, and other fees paid to relating services providers by the fund management company/Average NAV (%) | C22: 22661 | D22: 0.00042411502 | E22: 0.00042750227
A23: 4 | B23: Chi phí kiểm toán trả cho tổ chức kiểm toán (nếu phát sinh)/Giá trị tài sản ròng trung bình trong kỳ (%) Auditing fee paid to auditing organizations (if any)/Average NAV (%) | C23: 2267 | D23: 8.894378e-05 | E23: 8.7332514e-05
A24: 5 | B24: Chi phí trả cho tổ chức quản lý bất động sản/ Giá trị tài sản ròng trung bình trong kỳ (%) (không áp dụng) Fee paid to Real Estate management organisation/ Average NAV (%) (not applicable) | C24: 2286
A25: 6 | B25: Chi phí trả cho doanh nghiệp thẩm định giá bất động sản/Giá trị tài sản ròng trung bình trong kỳ (%) (không áp dụng) Fee paid to Real Estate valuation service provider/ Average NAV (%) (not applicable)
A26: 7 | B26: Chi phí dịch vụ tư vấn pháp lý, dịch vụ báo giá và các dịch vụ hợp lý khác, thù lao trả cho ban đại diện quỹ/Giá trị tài sản ròng trung bình trong kỳ (%) Legal consultancy, price quotation and other appropriate service fees; remunerations paid to the Board of Representatives/Average NAV (%) | C26: 2268 | D26: 0.00013350899 | E26: 0.00016315782
A27: 8 | B27: Tỷ lệ chi phí /Giá trị tài sản ròng trung bình trong kỳ (%) Expense/Average NAV (%) | C27: 2269 | D27: 0.013485285 | E27: 0.013595906
A28: 9 | B28: Tốc độ vòng quay danh mục trong kỳ (%)/Portfolio turnover rate (%) | C28: 2270 | D28: 0.80455157 | E28: 1.7853931
A29: 10 | B29: Tỷ lệ thu nhập (tính cả thu nhập từ lãi, cổ tức, trái tức, chênh lệch giá)/ Giá trị tài sản ròng (không áp dụng) Income (including interest income, dividend, coupon income and unrealised gain)/ Average NAV (%) (not applicable) | C29: 2287
A30: II | B30: CÁC CHỈ TIÊU KHÁC OTHER INDICATORS | C30: 2272
A31: 1 | B31: Quy mô quỹ đầu kỳ (tính theo mệnh giá chứng chỉ quỹ) Fund scale at the beginning of the period (based on par value of fund certificate) | C31: 2273 | D31: 607878516100 | E31: 605747837800
B32: Tổng giá trị chứng chỉ quỹ đang lưu hành đầu kỳ Total value of outstanding Fund Certificate at the beginning of period | C32: 2274 | D32: 607878516100 | E32: 605747837800
B33: Tổng số lượng chứng chỉ quỹ đang lưu hành đầu kỳ Total number of outstanding Fund Certificate at the beginning of period | C33: 2275 | D33: 60787852 | E33: 60574784
A34: 2 | B34: Thay đổi quy mô quỹ trong kỳ (tính theo mệnh giá chứng chỉ quỹ) Change of Fund scale during the period (based on par value of fund certificate) | C34: 2276 | D34: 10985301200 | E34: 2130678300
B35: Thay đổi số lượng chứng chỉ quỹ trong kỳ Change of Number of Fund Certificates during the period | C35: 22761 | D35: 1098530.1 | E35: 213067.83
B36: Thay đổi giá trị vốn trong kỳ (theo mệnh giá) Change in capital amount during the period (based on par value) | C36: 22762 | D36: 10985301200 | E36: 2130678300
B37: Số lượng chứng chỉ quỹ phát hành thêm trong kỳ Number of Fund Certificates subscribed during the period | C37: 2277 | D37: 3778254.6 | E37: 5296415.9
B38: Giá trị vốn huy động thêm trong kỳ (theo mệnh giá) Net subscription amount during the period (based on par value) | C38: 2278 | D38: 37782546500 | E38: 52964158700
B39: Số lượng chứng chỉ quỹ mua lại trong kỳ Number of Fund Certificates redeemed during the period | C39: 22781 | D39: -2679724.5 | E39: -5083348
B40: Giá trị vốn phải thanh toán trong kỳ khi đáp ứng lệnh của nhà đầu tư (theo mệnh giá) Net redemption amount during the period (based on par value) | C40: 22782 | D40: -26797245300 | E40: -50833480400
A41: 3 | B41: Quy mô quỹ cuối kỳ (tính theo mệnh giá chứng chỉ quỹ) Fund scale at the end of the period (based on par value) | C41: 2279 | D41: 618863817300 | E41: 607878516100
B42: Tổng giá trị thị trường của quỹ đang lưu hành cuối kỳ (theo mệnh giá) Total value of outstanding Fund Certificate at the end of the period (based on par value) | C42: 2280 | D42: 618863817300 | E42: 607878516100
B43: Tổng số lượng chứng chỉ quỹ đang lưu hành cuối kỳ Total number of outstanding Fund Certificate at the end of the period | C43: 2281 | D43: 61886382 | E43: 60787852
A44: 4 | B44: Tỷ lệ nắm giữ chứng chỉ quỹ của công ty quản lý quỹ và người có liên quan cuối kỳ Fund Management Company and related parties' ownership ratio at the end of the period | C44: 2282 | D44: 6.7723623e-05 | E44: 6.8947493e-05
A45: 5 | B45: Tỷ lệ nắm giữ chứng chỉ quỹ của 10 nhà đầu tư lớn nhất cuối kỳ Top 10 investors' ownership ratio at the end of the period | C45: 2283 | D45: 0.2709 | E45: 0.2831
A46: 6 | B46: Tỷ lệ nắm giữ chứng chỉ quỹ của nhà đầu tư nước ngoài cuối kỳ Foreign investors' ownership ratio at the end of the period (***) | C46: 2284 | D46: 0.0083 | E46: 0.0081
A47: 7 | B47: Số nhà đầu tư tham gia vào quỹ, kể cả giao dịch ký danh Number of investors of the Fund at the end of the period | C47: 22841 | D47: 11919 | E47: 11859
A48: 8 | B48: Giá trị tài sản ròng trên một đơn vị quỹ cuối kỳ Net asset value per Fund Certificate at the end of period | C48: 2285 | D48: 27249.11 | E48: 27120.12
A49: 9 | B49: Giá trị thị trường trên một chứng chỉ quỹ/cổ phiếu cuối kỳ (không áp dụng) Market price per fund certificates at the end of period (not applicable) | C49: 2288
A50: Ghi chú: Note:
A51: (*) Các chỉ tiêu từ 1 đến 7 của "Chỉ tiêu về hiệu quả hoạt động" đã được điều chỉnh để phản ánh số liệu trên cơ sở hoạt động tròn năm bằng cách nhân các chỉ tiêu này với 12 (đối với báo cáo tháng), 4 (đối với báo cáo quý), 2 (đối với báo cáo bán niên), 1 (đối với báo cáo năm). All Indicator starting from number 1 to 7 of "Investment performance indicators" are annualized to reflect a rate that is based on a full year operation by multiplying these indicators with 12 (monthly report) or 4 (quarterly report) or 2 (semi-annual report) or 1 (annual report). (**) Không tính đến giá trị cam kết của các hợp đồng tương lai chỉ số. Excluding the committed value of the Index Futures contracts.
A52: (***) Hiện tại Công ty Cổ phần Quản lý Quỹ Đầu tư Dragon Capital Việt Nam ("DCVFM") đang làm thủ tục cập nhật lên trên hệ thống Đại lý chuyển nhượng (“VSD”) từ hình thức Nhà đầu tư trong nước thành hình thức doanh nghiệp thành lập trong nước có vốn đầu tư nước ngoài. Vì vậy, chỉ tiêu “Tỷ lệ sở hữu nước ngoài” được trình bày ở trên vẫn tính toán dựa trên báo cáo từ VSD với dữ liệu DCVFM là nhà đầu tư trong nước. Dragon Capital Vietfund Management Joint Stock Company ("DCVFM") is updating Company's information from Local coporation to Foreign Direct Investment corporation in Vietnam Securites Depository ("VSD") system. Therefore, above Foreign Investors' Ownership Ratio is still calculated based on VSD's report which records DCVFM is Local coporation.
A53: =TONGQUAN!C16 -> Đại diện có thẩm quyền của Ngân hàng giám sát | D53: =TONGQUAN!F16 -> Đại diện có thẩm quyền của Công ty quản lý Quỹ
A54: =TONGQUAN!C17 -> Authorised Representative of Supervisory Bank | D54: =TONGQUAN!F17 -> Authorised Representative of Fund Management Company
A64: =TONGQUAN!C19 -> Ngân hàng TNHH MTV Standard Chartered (Việt Nam) | D64: =TONGQUAN!F19 -> Công ty Cổ phần Quản lý Quỹ Đầu tư Dragon Capital Việt Nam
A65: =TONGQUAN!C20 -> Vũ Quang Phan | D65: =TONGQUAN!F20 -> Lê Hoàng Anh
A66: =TONGQUAN!C21 -> Phó phòng Dịch vụ nghiệp vụ giám sát Quỹ | D66: =TONGQUAN!F21 -> Quyền Giám đốc nghiệp vụ hỗ trợ đầu tư

Sheet LogoFMS
D1: VFMVFB
A2: FUNDCODE | B2: FUNDNAME | C2: LOGO
A3: VFMVSF | B3: Quỹ Đầu Tư Cổ Phiếu Việt Nam Chọn Lọc
A4: VFMVF1 | B4: Quỹ Đầu tư Chứng khoán Năng động DC
A5: VFMVF4 | B5: Quỹ Đầu tư Doanh nghiệp Hàng đầu DC
A6: VFMVFA | B6: Quỹ Đầu tư Năng Động Việt Nam
A7: VFMVFB | B7: Quỹ Đầu tư Trái phiếu DC
A8: VFMVFC | B8: Quỹ Đầu tư Trái phiếu Gia tăng Thu nhập Cố định DC
A9: TCEF1 | B9: Quỹ Đầu tư Cổ phiếu Techcom
A10: TCBF | B10: Quỹ Đầu tư Cổ phiếu Techcom
A11: MBEF1 | B11: Quỹ Đầu tư JAPAN ASIA MB CAPITAL
A12: MBVF | B12: Quỹ Đầu tư Giá trị MB Capital
A13: SSISCA | B13: Quỹ Đầu tư Lợi thế Cạnh tranh Bền vững SSI
A14: VCBBCF | B14: Quỹ Đầu tư Cổ Phiếu Hàng Đầu VCBF
... A52: VCBMGF | B52: Quỹ Đầu Tư Cổ phiếu Tăng trưởng VCBF
A53: AM33
A54: AM34
A55: AM35
A56: AM36 | B56: Tổng công ty cổ phần bảo hiểm Petrolimex - PJICO EQUITY PORTFOLIO 04
A57: AM37
A58: AM38
A59: AM39
A60: AM40
A61: AM41
A62: AM42
A63: AM43
A64: AM44
A65: AM45
A66: AM46
A67: AM47
A68: AM48
... A70: AM50
A71: VMPF | B71: Quỹ Đầu Tư Cổ Phiếu Hiệu Suất Thị Trường Việt Nam VinaCapital (VinaCapital-VMPF)
A72: ENF
A73: EVESG
A74: UVDIF
A75: VDEF
A76: VCBAIF
