Workbook
Name addlogo: INDEX(LogoFMS!$C$3:$C$76,MATCH(LogoFMS!$D$1,LogoFMS!$A$3:$A$76,0))

Sheet TONGQUAN
A1: Kỳ báo cáo: | C1: Tại ngày 31 tháng 12 năm 2024 / As at 31 Dec 2024
C2: Quý IV năm 2024 / Quarter IV 2024
A4: Thông tin chung:
C5: Tên Công ty quản lý quỹ: | D5: Công ty Cổ phần Quản lý Quỹ Đầu tư Dragon Capital Việt Nam
C6: Fund Management Company: | D6: Dragon Capital Vietfund Management Joint Stock Company
C7: Tên ngân hàng giám sát: | D7: Ngân hàng TNHH Một thành viên Standard Chartered (Việt Nam)
C8: Supervising bank: | D8: Standard Chartered Bank (Vietnam) Limited
C9: Tên Quỹ: | D9: Quỹ Đầu tư Trái phiếu DC
C10: Fund name: | D10: DC Bond Fund (DCBF)
C11: Ngày lập báo cáo: | D11: Ngày 07 tháng 01 năm 2025
C12: Reporting Date: | D12: 07 Jan 2025
A14: Người ký báo cáo:
C16: Đại diện có thẩm quyền của Ngân hàng giám sát | F16: Đại diện có thẩm quyền của Công ty quản lý Quỹ
C17: Authorised Representative of Supervisory Bank | F17: Authorised Representative of Fund Management Company
C19: Ngân hàng TNHH MTV Standard Chartered (Việt Nam) | F19: =D5 -> Công ty Cổ phần Quản lý Quỹ Đầu tư Dragon Capital Việt Nam
C20: Vũ Quang Phan | F20: Lê Hoàng Anh
C21: Phó phòng Dịch vụ nghiệp vụ giám sát Quỹ | F21: Quyền Giám đốc nghiệp vụ hỗ trợ đầu tư

Sheet BCTaiSan_06027
A1: Phụ lục XXVI. Mẫu báo cáo về hoạt động của Quỹ Appendix XXVI. Report on Fund's Operation
A2: (Ban hành kèm theo Thông tư số 98/2020/TT-BTC ngày 16 tháng 11 năm 2020 của Bộ trưởng Bộ Tài Chính về hướng dẫn hoạt động và quản lý quỹ đầu tư chứng khoán) (Issued in association with Circular 98/2020/TT-BTC dated 16 November 2020 of the Minister of Finance on guiding the operation and management of the securities investment funds)
A3: BÁO CÁO HOẠT ĐỘNG ĐẦU TƯ CỦA QUỸ MỞ REPORT ON OPEN ENDED FUND'S INVESTMENT ACTIVITIES
A5: Tại ngày 31 tháng 12 năm 2024 / As at 31 Dec 2024
A7: Tên Công ty quản lý quỹ: | C7: Công ty Cổ phần Quản lý Quỹ Đầu tư Dragon Capital Việt Nam
A8: Fund Management Company: | C8: Dragon Capital Vietfund Management Joint Stock Company
A9: Tên ngân hàng giám sát: | C9: Ngân hàng TNHH Một thành viên Standard Chartered (Việt Nam)
A10: Supervising bank: | C10: Standard Chartered Bank (Vietnam) Limited
A11: Tên Quỹ: | C11: Quỹ Đầu tư Trái phiếu DC
A12: Fund name: | C12: DC Bond Fund (DCBF)
A13: Ngày lập báo cáo: | C13: Ngày 07 tháng 01 năm 2025
A14: Reporting Date: | C14: 07 Jan 2025
A16: A. | B16: BÁO CÁO CHUNG VỀ HOẠT ĐỘNG ĐẦU TƯ CỦA QUỸ/GENERAL INFORMATION ON FUND'S INVESTMENT ACTIVITIES
A17: I | B17: BÁO CÁO VỀ TÀI SẢN / ASSET REPORT
A18: STT No | B18: Nội dung Indicator | C18: Mã chỉ tiêu Code | D18: Ngày 31 tháng 12 năm 2024 As at 31 Dec 2024 | E18: Ngày 30 tháng 09 năm 2024 As at 30 Sep 2024 | F18: %/cùng kỳ năm trước %/against last year
A19: I | B19: TÀI SẢN ASSETS | C19: 2200
A20: I.1 | B20: Tiền và các khoản tương đương tiền Cash and Cash Equivalents | C20: 2201 | D20: 260940922040 | E20: 156172164816 | F20: 3.7632083
B21: Tiền Cash | C21: 2202
A22: ... | B22: ... | C22: ... | D22: ... | E22: ... | F22: ...
B23: Tiền gửi ngân hàng Cash at bank | C23: 2203 | D23: 260940922040 | E23: 156172164816 | F23: 3.7632083
A24: ... | B24: ... | C24: ... | D24: ... | E24: ... | F24: ...
B25: Tiền gửi của nhà đầu tư cho hoạt động mua chứng chỉ quỹ Cash at bank for Fund's subscription | C25: 2203.1 | D25: 9923142711 | E25: 9525444010 | F25: 62.736741
B26: Tiền phải trả cho Nhà đầu tư về cổ tức và mua lại chứng chỉ quỹ Cash at bank for Fund's dividend payment and redemption | C26: 2203.2 | D26: 4391073 | E26: 4391073 | F26: 0.41283769
B27: Tiền gửi ngân hàng cho hoạt động của Quỹ Cash at bank for Fund's operation | C27: 2203.3 | D27: 2213388256 | E27: 842329733 | F27: 0.049849731
B28: Tiền gửi ký quỹ cho hoạt động đầu tư chứng khoán phái sinh Margin account for trading derivatives | C28: 2203.4 | D28: 0 | E28: 0
B29: Tiền, tương đương tiền Cash, cash equivalents | C29: 2203.5 | D29: 248800000000 | E29: 145800000000 | F29: 10.044409
A30: I.2 | B30: Các khoản đầu tư (kê chi tiết) Investments | C30: 2205 | D30: 1383107257612 | E30: 1360106253896 | F30: 3.3522179
A31: ... | B31: ... | C31: ... | D31: ... | E31: ... | F31: ...
B32: Cổ phiếu, chứng chỉ quỹ niêm yết Listed Shares, fund certificates | C32: 2205.1 | D32: 0 | E32: 0
B33: Cổ phiếu, chứng chỉ quỹ chưa niêm yết Unlisted Shares, fund certifictes | C33: 2205.2 | D33: 0 | E33: 0
B34: Trái phiếu Bonds | C34: 2205.3 | D34: 956884352009 | E34: 939006253896 | F34: 2.5341574
B35: Công cụ thị trường tiền tệ Money market instruments | C35: 2205.4 | D35: 265122905603 | E35: 265000000000 | F35: 7.5749402
B36: Hợp đồng tiền gửi có kỳ hạn trên ba (03) tháng Deposits with term over three (03) months | C36: 2205.5 | D36: 161100000000 | E36: 156100000000
B37: Quyền mua chứng khoán Investment - Rights | C37: 2205.6 | D37: 0 | E37: 0
B38: Hợp đồng tương lai chỉ số Index future contracts | C38: 2205.7 | D38: 0 | E38: 0
B39: Đầu tư khác Other investments | C39: 2205.8 | D39: 0 | E39: 0
B40: Hợp đồng mua lại đảo ngược Reverse repo contracts | C40: 2205.9 | D40: 0 | E40: 0
A41: I.3 | B41: Thu từ cho thuê bất động sản đầu tư (không áp dụng) Receivables from rental of investment property (not applicable) | C41: 2220 | D41: 0 | E41: 0
A42: ... | B42: ... | C42: ... | D42: ... | E42: ... | F42: ...
A43: I.4 | B43: Cổ tức, trái tức được nhận Dividend, Coupon receivables | C43: 2206 | D43: 30288039815 | E43: 15619405291 | F43: 2.2453645
A44: ... | B44: ... | C44: ... | D44: ... | E44: ... | F44: ...
B45: Phải thu cổ tức Dividend receivables | C45: 2206.1 | D45: 0 | E45: 0
B46: Phải thu trái tức Coupon receivables | C46: 2206.2 | D46: 30288039815 | E46: 15619405291 | F46: 2.2453645
A47: I.5 | B47: Lãi được nhận Interest receivables | C47: 2207 | D47: 13444436440 | E47: 6671668631 | F47: 8.1848376
A48: ... | B48: ... | C48: ... | D48: ... | E48: ... | F48: ...
B49: Phải thu lãi tiền gửi Interest receivable from bank deposits | C49: 2207.1 | D49: 3842326851 | E49: 1169257672 | F49: 133.56672
B50: Phải thu lãi công cụ thị trường tiền tệ Interest receivable from Money market instruments | C50: 2207.2 | D50: 9602109589 | E50: 5502410959 | F50: 5.9498684
B51: Phải thu lãi hợp đồng mua lại đảo ngược Interest receivable from reverse repo contracts | C51: 2207.3 | D51: 0 | E51: 0
A52: I.6 | B52: Tiền bán bất động sản chờ thu (không áp dụng) Real Estate Proceeds Receivables (not applicale) | C52: 2221 | D52: 0 | E52: 0
A53: ... | B53: ... | C53: ... | D53: ... | E53: ... | F53: ...
A54: I.7 | B54: Tiền bán chứng khoán chờ thu Securities Trading Receivables | C54: 2208 | D54: 0 | E54: 0
A55: ... | B55: ... | C55: ... | D55: ... | E55: ... | F55: ...
A56: I.8 | B56: Các khoản phải thu khác Other Receivables | C56: 2210 | D56: 0 | E56: 0
A57: ... | B57: ... | C57: ... | D57: ... | E57: ... | F57: ...
B58: Dự phòng giảm giá tài sản nhận thế chấp Impairment of devaluation of pledged assets | C58: 2210.1 | D58: 0 | E58: 0
B59: Dự phòng nợ phải thu khó đòi Provision for doubtful debt | C59: 2210.2 | D59: 0 | E59: 0
B60: Các khoản phải thu khác Other Receivables | C60: 2210.3 | D60: 0 | E60: 0
A61: I.9 | B61: Các tài sản khác Other Assets | C61: 2211 | D61: 0 | E61: 36583558
A62: ... | B62: ... | C62: ... | D62: ... | E62: ... | F62: ...
A63: I.10 | B63: TỔNG TÀI SẢN TOTAL ASSETS | C63: 2212 | D63: 1687780655907 | E63: 1538606076192 | F63: 3.3954831
A64: II | B64: NỢ LIABILITIES | C64: 2213
A65: II.1 | B65: Tiền phải thanh toán mua bất động sản (không áp dụng) Real Estate Trading Payables (not applicable) | C65: 2222 | D65: 0 | E65: 0
A66: ... | B66: ... | C66: ... | D66: ... | E66: ... | F66: ...
A67: II.2 | B67: Tiền phải thanh toán mua chứng khoán Securities Trading Payables | C67: 2214 | D67: 0 | E67: 0 | F67: 0
A68: ... | B68: ... | C68: ... | D68: ... | E68: ... | F68: ...
A69: II.3 | B69: Các khoản phải trả khác Other Payables | C69: 2215 | D69: 39206607425 | E69: 53030897719 | F69: 29.483669
A70: ... | B70: ... | C70: ... | D70: ... | E70: ... | F70: ...
B71: Phải trả nhà đầu tư Payables to investors | C71: 2215.1 | D71: 36492948218 | E71: 50683818264 | F71: 73.772542
B72: Phải trả cho nhà đầu tư chờ mua chứng chỉ quỹ Subscription Pending allotment | C72: 2215.1.1 | D72: 9923142711 | E72: 9525444010 | F72: 62.736741
B73: Phải trả nhà đầu tư trên tài sản giữ hộ Payables to investors for investment bought on behalf | C73: 2215.1.2 | D73: 0 | E73: 0
B74: Phải trả nhà đầu tư trên cổ tức đã thu Payables to investors for collected dividend | C74: 2215.1.3 | D74: 0 | E74: 0
B75: Phải trả cho Nhà đầu tư về mua lại chứng chỉ quỹ Redemption payable to investors | C75: 2215.1.4 | D75: 26569805507 | E75: 41158374254 | F75: 78.959941
B76: Thuế và các khoản phải nộp Nhà nước Tax payables and obligations to the State Budget | C76: 2215.2 | D76: 137193084 | E76: 159790129 | F76: 25.899923
B77: Phải trả phí phát hành, mua lại chứng chỉ quỹ cho Đại lý phân phối và Công ty quản lý quỹ Subscription and Redemption fee payable to distributors and Fund Management Company | C77: 2215.3 | D77: 405658375 | E77: 297211309 | F77: 36.680523
B78: Phải trả thu nhập cho nhà đầu tư Income payable to investors | C78: 2215.4 | D78: 0 | E78: 0
B79: Phải trả thù lao Ban đại diện quỹ Remuneration Payable to Fund's Board of Representatives | C79: 2215.5 | D79: 12000000 | E79: 10491803 | F79: 1
B80: Phải trả phí quản lý cho công ty quản lý quỹ Management fee payable | C80: 2215.6 | D80: 1650065860 | E80: 1435279293 | F80: 3.7948065
B81: Phải trả phí quản trị quỹ Fund Administration fee payable | C81: 2215.7 | D81: 45376811 | E81: 39470179 | F81: 3.7948064
B82: Phải trả phí giám sát Supervisory service fee payable | C82: 2215.8 | D82: 60502415 | E82: 52626908 | F82: 3.6587038
B83: Phí giao dịch Transaction fee | C83: 2215.9 | D83: 192537125 | E83: 192537125 | F83: 0.96675477
B84: Phải trả phí môi giới Brokerage fee payable | C84: 2215.9.1 | D84: 192537125 | E84: 192537125 | F84: 0.96675477
B85: Phải trả phí phát hành thanh toán bù trừ chứng khoán Clearing Settlement fee payable | C85: 2215.9.2 | D85: 0 | E85: 0
B86: Trích trước phí lưu ký tài sản Quỹ mở Accrued expense for Custodian fee | C86: 2215.10 | D86: 49976921 | E86: 50292643 | F86: 2.9956348
B87: Phí lưu ký - bảo quản tài sản Custodian service - Safe Custody Fee | C87: 2215.10.1 | D87: 48126921 | E87: 47842643 | F87: 3.2013653
B88: Phí lưu ký - giao dịch chứng khoán Custodian service - Transaction fee | C88: 2215.10.2 | D88: 1100000 | E88: 1700000 | F88: 1.2222222
B89: Phí lưu ký cho chứng khoán cơ sở, phí quản lý vị thế và tài sản phái sinh trả cho VSDC Custodian service - Depository fee, Position and Margin management fee paid to VSDC | C89: 2215.10.3 | D89: 750000 | E89: 750000 | F89: 1
B90: Phải trả phí kiểm toán Audit fee payable | C90: 2215.11 | D90: 74480000 | E90: 39421164 | F90: 0.95
B91: Phải trả phí họp đại hội thường niên General meeting expense payable | C91: 2215.12 | D91: 39618616 | E91: 22344148
B92: Phải trả phí báo cáo thường niên Annual report fee payable | C92: 2215.13 | D92: 0 | E92: 0
B93: Phải trả phí dịch vụ đại lý chuyển nhượng Transfer Agency fee payable | C93: 2215.14 | D93: 11000000 | E93: 11000000 | F93: 1
B94: Dự chi phí tính giá trị tài sản ròng tham chiếu (iNAV) cho HOSE Service fee payable to HOSE for calculating iNAV | C94: 2215.15 | D94: 0 | E94: 0
B95: Dự chi phí cấp quyền sử dụng chỉ số cho HOSE Authorising index service fee payable to HOSE | C95: 2215.16 | D95: 0 | E95: 0
B96: Phải trả khác Other payables | C96: 2215.17 | D96: 35250000 | E96: 36614754 | F96: 0.92298629
B97: Phải trả phí báo giá Price feed fee payable | C97: 2215.17.1 | D97: 35250000 | E97: 23500000 | F97: 1.5
B98: Trích trước phí công tác, họp của ban đại diện Accrued expense for Fund's Board of Representatives travelling, meeting | C98: 2215.17.2 | D98: 0 | E98: 0
B99: Trích trước phí quản lý thường niên trả UBCKNN Accrued expense for Annual Management Fee pay to SSC | C99: 2215.17.3 | D99: 0 | E99: 13114754 | F99: 0
B100: Phải trả khác Other payables | C100: 2215.17.4 | D100: 0 | E100: 0 | F100: 0
B101: Vay ngắn hạn - hợp đồng repo Short-term loans - Repo contracts | C101: 2215.18 | D101: 0 | E101: 0
B102: Gốc hợp đồng repo Principal of repo contracts | C102: 2215.18.1 | D102: 0 | E102: 0
B103: Trích trước lãi vay ngắn hạn Accrued Interest Expense | C103: 2215.18.2 | D103: 0 | E103: 0
...

Sheet BCKetQuaHoatDong_06028
A1: Phụ lục XXVI. Mẫu báo cáo về hoạt động của Quỹ Appendix XXVI. Report on Fund's Operation
A2: (Ban hành kèm theo Thông tư số 98/2020/TT-BTC ngày 16 tháng 11 năm 2020 của Bộ trưởng Bộ Tài Chính về hướng dẫn hoạt động và quản lý quỹ đầu tư chứng khoán) (Issued in association with Circular 98/2020/TT-BTC dated 16 November 2020 of the Minister of Finance on guiding the operation and management of the securities investment funds)
A3: BÁO CÁO HOẠT ĐỘNG ĐẦU TƯ CỦA QUỸ MỞ REPORT ON OPEN ENDED FUND'S INVESTMENT ACTIVITIES
A5: Quý IV năm 2024 / Quarter IV 2024
A7: Tên Công ty quản lý quỹ: | C7: Công ty Cổ phần Quản lý Quỹ Đầu tư Dragon Capital Việt Nam
A8: Fund Management Company: | C8: Dragon Capital Vietfund Management Joint Stock Company
A9: Tên ngân hàng giám sát: | C9: Ngân hàng TNHH Một thành viên Standard Chartered (Việt Nam)
A10: Supervising bank: | C10: Standard Chartered Bank (Vietnam) Limited
A11: Tên Quỹ: | C11: Quỹ Đầu tư Trái phiếu DC
A12: Fund name: | C12: DC Bond Fund (DCBF)
A13: Ngày lập báo cáo: | C13: Ngày 07 tháng 01 năm 2025
A14: Reporting Date: | C14: 07 Jan 2025
A16: A. | B16: BÁO CÁO CHUNG VỀ HOẠT ĐỘNG ĐẦU TƯ CỦA QUỸ/GENERAL INFORMATION ON FUND'S INVESTMENT ACTIVITIES
A17: II | B17: BÁO CÁO KẾT QUẢ HOẠT ĐỘNG / PROFIT AND LOSS REPORT
A18: STT No | B18: Nội dung Indicator | C18: Mã chỉ tiêu Code | D18: Quý IV năm 2024 Quarter IV 2024 | E18: Quý III năm 2024 Quarter III 2024 | F18: Lũy kế từ đầu năm Accumulated from beginning of year
A19: I | B19: Thu nhập từ hoạt động đầu tư Income from Investment Activities | C19: 2220 | D19: 31084786669 | E19: 26893035688 | F19: 94422054315
A20: 1 | B20: Thu từ bất động sản cho thuê (không áp dụng) Income from rental property (not applicable) | C20: 2223 | D20: 0 | E20: 0 | F20: 0
A21: ... | B21: ... | C21: ... | D21: ... | E21: … | F21: …
A22: 2 | B22: Cổ tức, trái tức được nhận Dividend income, interest income from bonds | C22: 2221 | D22: 21436650554 | E22: 18333400700 | F22: 64672633442
A23: ... | B23: ... | C23: ... | D23: ... | E23: … | F23: …
B24: Cổ tức được nhận Dividends income | C24: 2221.1 | D24: 0 | E24: 0 | F24: 0
B25: Trái tức được nhận Interest income from bonds | C25: 2221.2 | D25: 21436650554 | E25: 18333400700 | F25: 64672633442
A26: 3 | B26: Lãi được nhận Interest income | C26: 2222 | D26: 9648136115 | E26: 8559634988 | F26: 29749420873
A27: ... | B27: ... | C27: ... | D27: ... | E27: ... | F27: ...
B28: Lãi tiền gửi ngân hàng Interest income from bank deposits | C28: 2222.1 | D28: 4691725157 | E28: 3231087044 | F28: 13238023615
B29: Lãi công cụ thị trường tiền tệ Interest income from Money market instruments | C29: 2222.2 | D29: 4956410958 | E29: 5328547944 | F29: 16511397258
B30: Lãi hợp đồng mua lại đảo ngược Interest income from reverse repo contracts | C30: 2222.3 | D30: 0 | E30: 0 | F30: 0
A31: 4 | B31: Các khoản thu nhập khác Other incomes | C31: 2223 | D31: 0 | E31: 0 | F31: 0
A32: ... | B32: ... | C32: ... | D32: ... | E32: ... | F32: ...
B33: Thu nhập khác về đầu tư Other investment incomes | C33: 2223.1 | D33: 0 | E33: 0 | F33: 0
B34: Thu nhập khác Other incomes | C34: 2223.2 | D34: 0 | E34: 0 | F34: 0
B35: Chi phí dự phòng nợ phải thu khó đòi về cổ tức, tiền lãi và xử lý tổn thất nợ phải thu khó đòi về cổ tức, tiền lãi Provision expense for bad debts from dividends, interest income and written off bad debts from dividends, interest income | C35: 2223.3 | D35: 0 | E35: 0 | F35: 0
A36: II | B36: Chi phí Expenses | C36: 2224 | D36: 5704744487 | E36: 5247439042 | F36: 17785928645
A37: 1 | B37: Chi phí quản lý trả cho Công ty quản lý quỹ Management Fee paid to Fund Management Company | C37: 2225 | D37: 4801176409 | E37: 4315110065 | F37: 14826392925
A38: ... | B38: ... | C38: ... | D38: ... | E38: ... | F38: ...
A39: 2 | B39: Chi phí lưu ký, giám sát trả cho Ngân hàng Giám sát/VSDC Custody fee, Supervising fee paid to Supervising Bank/VSDC | C39: 2226 | D39: 326579992 | E39: 313273976 | F39: 1048321067
A40: ... | B40: ... | C40: ... | D40: ... | E40: ... | F40: ...
B41: Chi phí dịch vụ lưu ký - bảo quản tài sản Custodian service - Safe Custody Fee | C41: 2226.1 | D41: 140237335 | E41: 143837005 | F41: 474411221
B42: Chi phí dịch vụ lưu ký - giao dịch chứng khoán Custodian service - Transaction fee | C42: 2226.2 | D42: 6200000 | E42: 8500000 | F42: 19500000
B43: Chi phí dịch vụ lưu ký cho chứng khoán cơ sở, phí quản lý vị thế và tài sản phái sinh trả cho VSDC Custodian service - Depository fee, Position and Margin management fee paid to VSDC | C43: 2226.3 | D43: 4099523 | E43: 2716268 | F43: 10775439
B44: Chi phí giám sát Supervisory fee | C44: 2226.4 | D44: 176043134 | E44: 158220703 | F44: 543634407
A45: 3 | B45: Chi phí quản trị quỹ và các chi phí khác mà công ty quản lý quỹ trả cho tổ chức cung cấp dịch vụ có liên quan Fund Administration Fee, and other fees paid to relevant Fund's service providers | C45: 2227 | D45: 165032352 | E45: 151665523 | F45: 539725800
A46: ... | B46: ... | C46: ... | D46: ... | E46: ... | F46: ...
B47: Chi phí quản trị Quỹ Fund Administration Fee | C47: 2227.1 | D47: 132032352 | E47: 118665523 | F47: 407725800
B48: Chi phí dịch vụ Đại lý Chuyển nhượng Transfer Agency Fee | C48: 2227.2 | D48: 33000000 | E48: 33000000 | F48: 132000000
A49: 4 | B49: Chi phí dịch vụ quản lý bất động sản (không áp dụng) Real Estate Management Service fee (not applicable) | D49: 0 | E49: 0 | F49: 0
A50: ... | B50: ... | C50: ... | D50: ... | E50: ... | F50: ...
A51: 5 | B51: Chi phí dịch vụ định giá bất động sản (không áp dụng) Real estate valuation service fees (not applicable) | D51: 0 | E51: 0 | F51: 0
A52: ... | B52: ... | C52: ... | D52: ... | E52: ... | F52: ...
A53: 6 | B53: Chi phí kiểm toán trả cho tổ chức kiểm toán Audit fee | C53: 2228 | D53: 35058836 | E53: 35058836 | F53: 145957528
A54: ... | B54: ... | C54: ... | D54: ... | E54: ... | F54: ...
A55: 7 | B55: Chi phí dịch vụ tư vấn pháp lý, dịch vụ báo giá và các dịch vụ hợp lý khác, thù lao trả cho ban đại diện quỹ Legal consultancy expenses, price feed fee, other valid expenses, remuneration paid to Fund's Board of Representatives | C55: 2229 | D55: 77441757 | E55: 53941755 | F55: 238700000
A56: ... | B56: ... | C56: ... | D56: ... | E56: ... | F56: ...
B57: Thù lao Ban đại diện Quỹ Remuneration of Fund's Board of Representatives | C57: 2229.1 | D57: 19508197 | E57: 19508196 | F57: 78000000
B58: Chi phí cung cấp báo giá chứng khoán Price feed fee | C58: 2229.2 | D58: 47000000 | E58: 23500000 | F58: 117500000
B59: Chi phí dịch vụ tư vấn pháp lý Legal consultancy expenses | C59: 2229.3 | D59: 10933560 | E59: 10933559 | F59: 43200000
A60: 8 | B60: Chi phí dự thảo, in ấn, gửi bản cáo bạch, bản cáo bạch tóm tắt, báo cáo tài chính, xác nhận giao dịch, sao kê tài khoản và các tài liệu khác cho nhà đầu tư; chi phí công bố thông tin của quỹ; chi phí tổ chức họp đại hội nhà đầu tư, ban đại diện quỹ Fee for drafting, printing, distribution of prospectus, summarised prospectus, financial statements, transaction confirmations, account statements and other documents to investors; information disclosure fee; fee for organising annual general meeting, board of representatives meeting | C60: 2230 | D60: 42924466 | E60: 46889959 | F60: 142737439
A61: ... | B61: ... | C61: ... | D61: ... | E61: ... | F61: ...
B62: Chi phí họp Đại hội Quỹ Meeting expenses | C62: 2230.1 | D62: 42924466 | E62: 46889959 | F62: 142737439
B63: Chi phí báo cáo thường niên Annual report expenses | C63: 2230.2 | D63: 0 | E63: 0 | F63: 0
B64: Chi phí họp, công tác của Ban đại diện Fund's Board of Representatives meeting, travelling expenses | C64: 2230.3 | D64: 0 | E64: 0 | F64: 0
B65: Chi phí công bố thông tin của Quỹ Expenses of information disclosure of the Fund | C65: 2230.4 | D65: 0 | E65: 0 | F65: 0
B66: Chi phí thiết kế, in ấn, gửi thư… Designing, printing, posting... expenses | C66: 2230.5 | D66: 0 | E66: 0 | F66: 0
A67: 9 | B67: Chi phí liên quan đến thực hiện các giao dịch tài sản của Quỹ Expenses related to execution of Fund’s asset transactions | C67: 2231 | D67: 243539829 | E67: 313483432 | F67: 770495036
A68: ... | B68: ... | C68: ... | D68: ... | E68: ... | F68: ...
B69: Chi phí môi giới Brokerage fee | C69: 2231.1 | D69: 241089279 | E69: 309729513 | F69: 758459498
B70: Chi phí thanh toán bù trừ Clearing settlement fee | C70: 2231.2 | D70: 2450550 | E70: 453919 | F70: 3735538
B71: Chi phí khác Other Expenses | C71: 2231.3 | D71: 0 | E71: 3300000 | F71: 8300000
A72: 10 | B72: Các loại chi phí khác Other expenses | C72: 2232 | D72: 12990846 | E72: 18015496 | F72: 73598850
A73: ... | B73: ... | C73: ... | D73: ... | E73: ... | F73: ...
B74: Chi phí thiết lập Quỹ Set up Expenses | C74: 2232.1 | D74: 0 | E74: 0 | F74: 0
B75: Phí niêm yết, đăng ký chứng khoán Listing, registration fees | C75: 2232.2 | D75: 0 | E75: 0 | F75: 0
B76: Phí quản lý thường niên trả cho UBCKNN Annual management fee paid to SSC | C76: 2232.3 | D76: 1885246 | E76: 1885246 | F76: 7500000
B77: Phí ngân hàng Bank charges | C77: 2232.4 | D77: 11105600 | E77: 14583250 | F77: 63451850
B78: Chi phí lãi vay Borrowing expense | C78: 2232.5 | D78: 0 | E78: 0 | F78: 0
B79: Chi phí khác Other Expenses | C79: 2232.6 | D79: 0 | E79: 1547000 | F79: 1547000
B80: Phí thực hiện quyền trả cho VSDC Fee paid to VSDC for getting the list of investors | C80: 2232.7 | D80: 0 | E80: 0 | F80: 1100000
A81: III | B81: Thu nhập ròng từ hoạt động đầu tư (= I - II) Net Income from Investment Activities (= I - II) | C81: 2233 | D81: 25380042182 | E81: 21645596646 | F81: 76636125670
A82: IV | B82: Lãi / (lỗ) từ hoạt động đầu tư Gain / (Loss) from Investment Activities | C82: 2234 | D82: 2295059007 | E82: -350655931 | F82: 5087561936
A83: 1 | B83: Lãi (lỗ) thực tế phát sinh từ hoạt động đầu tư hoặc chuyển nhượng bất động sản Realised Gain / (Loss) from disposal of investment or real estate transfer | C83: 2235 | D83: 2605392376 | E83: 1770599471 | F83: 6377328833
A84: 2 | B84: Thay đổi về giá trị của các khoản đầu tư trong kỳ Unrealised Gain / (Loss) due to market price | C84: 2236 | D84: -310333369 | E84: -2121255402 | F84: -1289766897
A85: V | B85: Thay đổi của giá trị tài sản ròng của Quỹ do các hoạt động đầu tư trong kỳ (III + IV) Change of Net Asset Value of the Fund due to investment activities during the period (= III + IV) | C85: 2237 | D85: 27675101189 | E85: 21294940715 | F85: 81723687606
A86: VI | B86: Giá trị tài sản ròng đầu kỳ Net Asset Value at the beginning of period | C86: 2238 | D86: 1485575178473 | E86: 1344758330774 | F86: 451596260409
A87: VII | B87: Thay đổi giá trị tài sản ròng của Quỹ trong kỳ, Trong đó Change of Net Asset Value of the Fund during the period, of which | C87: 2239 | D87: 162998870009 | E87: 140816847699 | F87: 1196977788073
A88: 1 | B88: Thay đổi giá trị tài sản ròng của Quỹ do các hoạt động đầu tư của Quỹ trong kỳ Change of Net Asset Value due to investment activities during the period | C88: 2239.1 | D88: 27675101189 | E88: 21294940715 | F88: 81723687606
A89: 2 | B89: Thay đổi giá trị tài sản ròng của Quỹ do việc chi trả lợi tức/ cổ tức của Quỹ cho các nhà đầu tư trong kỳ Change of Net Asset Value due to dividends payment to investors during the period | C89: 2239.2 | D89: 0 | E89: 0 | F89: 0
A90: 3 | B90: Thay đổi giá trị tài sản ròng do phát hành thêm/mua lại chứng chỉ quỹ Change of Net Asset Value due to subscription/redemption during the period | C90: 2239.3 | D90: 135323768820 | E90: 119521906984 | F90: 1115254100467
B91: Thay đổi giá trị tài sản ròng do phát hành thêm Chứng chỉ Quỹ Change of Net Asset Value due to subscription during the period | C91: 2239.3.1 | D91: 512421664397 | E91: 426233716431 | F91: 2142176039473
B92: Thay đổi giá trị tài sản ròng do mua lại Chứng chỉ Quỹ Change of Net Asset Value due to redemption during the period | C92: 2239.3.2 | D92: -377097895577 | E92: -306711809447 | F92: -1026921939006
A93: VIII | B93: Giá trị tài sản ròng cuối kỳ Net Asset Value at the end of period | C93: 2243 | D93: 1648574048482 | E93: 1485575178473 | F93: 1648574048482
A94: IX | B94: Lợi nhuận bình quân năm (chỉ áp dụng đối với báo cáo năm) Average annual profit (only applicable to annual report) | C94: 2244 | D94: 0 | E94: 0 | F94: 0
B95: Tỷ suất lợi nhuận bình quân năm (chỉ áp dụng đối với báo cáo năm) Average annual rate of return (only applicable to annual report) | C95: 2245 | D95: 0 | E95: 0 | F95: 0
A97: Đại diện có thẩm quyền của Ngân hàng giám sát | E97: Đại diện có thẩm quyền của Công ty quản lý Quỹ
A98: Authorised Representative of Supervisory Bank | E98: Authorised Representative of Fund Management Company
A105: Ngân hàng TNHH MTV Standard Chartered (Việt Nam) | E105: Công ty Cổ phần Quản lý Quỹ Đầu tư Dragon Capital Việt Nam
A106: Vũ Quang Phan | E106: Lê Hoàng Anh
A107: Phó phòng Dịch vụ nghiệp vụ giám sát Quỹ | E107: Quyền Giám đốc nghiệp vụ hỗ trợ đầu tư

Sheet BCDanhMucDauTu_06029
A1: Phụ lục XXVI. Mẫu báo cáo về hoạt động của Quỹ Appendix XXVI. Report on Fund's Operation
A2: (Ban hành kèm theo Thông tư số 98/2020/TT-BTC ngày 16 tháng 11 năm 2020 của Bộ trưởng Bộ Tài Chính về hướng dẫn hoạt động và quản lý quỹ đầu tư chứng khoán) (Issued in association with Circular 98/2020/TT-BTC dated 16 November 2020 of the Minister of Finance on guiding the operation and management of the securities investment funds)
A3: BÁO CÁO HOẠT ĐỘNG ĐẦU TƯ CỦA QUỸ MỞ REPORT ON OPEN ENDED FUND'S INVESTMENT ACTIVITIES
A5: =TONGQUAN!C1 -> Tại ngày 31 tháng 12 năm 2024 / As at 31 Dec 2024
A7: Tên Công ty quản lý quỹ: | C7: =TONGQUAN!D5 -> Công ty Cổ phần Quản lý Quỹ Đầu tư Dragon Capital Việt Nam
A8: Fund Management Company: | C8: =TONGQUAN!D6 -> Dragon Capital Vietfund Management Joint Stock Company
A9: Tên ngân hàng giám sát: | C9: =TONGQUAN!D7 -> Ngân hàng TNHH Một thành viên Standard Chartered (Việt Nam)
A10: Supervising bank: | C10: =TONGQUAN!D8 -> Standard Chartered Bank (Vietnam) Limited
A11: Tên Quỹ: | C11: =TONGQUAN!D9 -> Quỹ Đầu tư Trái phiếu DC
A12: Fund name: | C12: =TONGQUAN!D10 -> DC Bond Fund (DCBF)
A13: Ngày lập báo cáo: | C13: =TONGQUAN!D11 -> Ngày 07 tháng 01 năm 2025
A14: Reporting Date: | C14: =TONGQUAN!D12 -> 07 Jan 2025
A16: A. | B16: BÁO CÁO CHUNG VỀ HOẠT ĐỘNG ĐẦU TƯ CỦA QUỸ/GENERAL INFORMATION ON FUND'S INVESTMENT ACTIVITIES
A17: III | B17: BÁO CÁO DANH MỤC ĐẦU TƯ / INVESTMENT PORTFOLIO REPORT
A18: STT No. | B18: Loại Category | C18: Mã chỉ tiêu Code | D18: Số Lượng Quantity | E18: Giá thị trường hoặc giá trị hợp lý tại ngày báo cáo Market price | F18: Tổng giá trị (Đồng) Value (VND) | G18: Tỷ lệ % Tổng giá trị tài sản của Quỹ % of total asset
A19: I | B19: BẤT ĐỘNG SẢN ĐẦU TƯ (KHÔNG ÁP DỤNG) REAL ESTATE INVESTMENT (NOT APPLICABLE)
B21: TỔNG TOTAL | C21: 2264
A22: II | B22: CỔ PHIẾU NIÊM YẾT, ĐĂNG KÝ GIAO DỊCH, CHỨNG CHỈ QUỸ NIÊM YẾT SHARES LISTED, SHARES REGISTERED FOR TRADING, LISTED FUND CERTIFICATES | C22: 2246
B24: TỔNG TOTAL | C24: 2247
A25: III | B25: CỔ PHIẾU CHƯA NIÊM YẾT, ĐĂNG KÝ GIAO DỊCH, CHỨNG CHỈ QUỸ KHÔNG NIÊM YẾT SHARES UNLISTED, UNREGISTERED FOR TRADING, UNLISTED FUND CERTIFICATES | C25: 2248
B27: TỔNG TOTAL | C27: 2249 | F27: 0 | G27: 0
A28: IV | B28: TRÁI PHIẾU BONDS | C28: 2251
A30: 1 | B30: Trái phiếu niêm yết Listed bonds | C30: 2251.1 | F30: 803804814079 | G30: 0.47624957
A31: 1.1 | B31: BAF122029 | C31: 2251.1.1 | D31: 390000 | E31: 100539.32 | F31: 39210336750 | G31: 0.023231891
A32: 1.2 | B32: BAF123020 | C32: 2251.1.2 | D32: 452357 | E32: 100750.69 | F32: 45575278067 | G32: 0.027003081
A33: 1.3 | B33: CII124021 | C33: 2251.1.3 | D33: 993 | E33: 100055449 | F33: 99355060857 | G33: 0.058867283
A34: 1.4 | B34: HDB124006 | C34: 2251.1.4 | D34: 100000 | E34: 100571.29 | F34: 10057128800 | G34: 0.005958789
A35: 1.5 | B35: HDB124018 | C35: 2251.1.5 | D35: 1000000 | E35: 99787.479 | F35: 99787479000 | G35: 0.059123488
A36: 1.6 | B36: MML121021 | C36: 2251.1.6 | D36: 400230 | E36: 99943.096 | F36: 40000225312 | G36: 0.023699896
A37: 1.7 | B37: MSN123008 | C37: 2251.1.7 | D37: 500000 | E37: 99645.297 | F37: 49822648500 | G37: 0.029519623
A38: 1.8 | B38: MSN123009 | C38: 2251.1.8 | D38: 250000 | E38: 99644.332 | F38: 24911083000 | G38: 0.014759669
A39: 1.9 | B39: TNG122017 | C39: 2251.1.9 | D39: 1100000 | E39: 101016.37 | F39: 111118009200 | G39: 0.06583676
A40: 1.10 | B40: VBA122001 | C40: 2251.1.10 | D40: 220480 | E40: 98098.34 | F40: 21628722003 | G40: 0.012814889
A41: 1.11 | B41: VIC123028 | C41: 2251.1.11 | D41: 380000 | E41: 99662.45 | F41: 37871731000 | G41: 0.022438775
A42: 1.12 | B42: VND122014 | C42: 2251.1.12 | D42: 654430 | E42: 100317.73 | F42: 65650929426 | G42: 0.038897785
... A44: 1.14 | B44: VRE12007 | C44: 2251.1.14 | D44: 200000 | E44: 100190.6 | F44: 20038120800 | G44: 0.011872467
A45: 2 | B45: Trái phiếu chưa niêm yết Unlisted Bonds | C45: 2251.2 | F45: 153079537930 | G45: 0.090698716
A46: 2.1 | B46: CII12403 | C46: 2251.2.1 | D46: 360 | E46: 99965873 | F46: 35987714280 | G46: 0.021322507
A47: 2.2 | B47: KBC12401 | C47: 2251.2.2 | D47: 75 | E47: 999709240 | F47: 74978193000 | G47: 0.044424133
A48: 2.3 | B48: KDH12101 | C48: 2251.2.3 | D48: 35 | E48: 1003246590 | F48: 35113630650 | G48: 0.020804617
A49: 2.4 | B49: KDH12202 | C49: 2251.2.4 | D49: 7 | E49: 1000000000 | F49: 7000000000 | G49: 0.0041474584
B50: TỔNG TOTAL | C50: 2252 | F50: 956884352009 | G50: 0.56694829
A51: V | B51: CÁC LOẠI CHỨNG KHOÁN KHÁC OTHER SECURITIES | C51: 2253
A53: 1 | B53: Quyền mua chứng khoán Investment - Rights | C53: 2253.1 | F53: 0 | G53: 0
A54: 2 | B54: Chi tiết loại hợp đồng phái sinh(*) Index future contracts | C54: 2253.2 | F54: 0 | G54: 0
B55: TỔNG TOTAL | C55: 2254 | F55: 0 | G55: 0
B56: TỔNG CÁC LOẠI CHỨNG KHOÁN TOTAL TYPES OF SECURITIES | C56: 2255 | F56: 956884352009 | G56: 0.56694829
A57: VI | B57: CÁC TÀI SẢN KHÁC OTHER ASSETS | C57: 2256
A59: 1 | B59: Cổ tức được nhận Dividend receivables | C59: 2256.1 | F59: 0 | G59: 0
A60: 2 | B60: Lãi trái phiếu được nhận Coupon receivables | C60: 2256.2 | F60: 30288039815 | G60: 0.017945483
A61: 3 | B61: Lãi tiền gửi và công cụ thị trường tiền tệ được nhận Interest receivables from bank deposits and Money market instruments | C61: 2256.3 | F61: 13444436440 | G61: 0.0079657486
A62: 4 | B62: Tiền bán chứng khoán chờ thu Outstanding Settlement of sales transactions | C62: 2256.4 | F62: 0 | G62: 0
A63: 5 | B63: Phải thu cho khoản cổ phiếu hạn chế chờ mua Receivable from AP/Investors on securities on hold of buying | C63: 2256.5 | F63: 0 | G63: 0
A64: 6 | B64: Phải thu khác Other receivables | C64: 2256.6 | F64: 0 | G64: 0
A65: 7 | B65: Tài sản khác Other assets | C65: 2256.7 | F65: 0 | G65: 0
B66: TỔNG TOTAL | C66: 2257 | F66: 43732476255 | G66: 0.025911232
A67: VII | B67: TIỀN CASH | C67: 2258
A68: 1 | B68: Tiền, tương đương tiền Cash, Cash Equivalent | C68: 2259 | F68: 260940922040 | G68: 0.15460594
A70: 1.1 | B70: Tiền gửi ngân hàng Cash at Bank | C70: 2259.1 | F70: 12140922040 | G70: 0.0071934241
A71: 1.2 | B71: Các khoản tương đương tiền Cash Equivalents | C71: 2259.2 | F71: 248800000000 | G71: 0.14741252
A72: 2 | B72: Tiền gửi ngân hàng có kỳ hạn trên 3 tháng Deposits with term over three (03) months | C72: 2260 | F72: 161100000000 | G72: 0.095450792
A74: 3 | B74: Công cụ thị trường tiền tệ Money market instruments | C74: 2261.1 | F74: 265122905603 | G74: 0.15708374
B75: TỔNG TOTAL | C75: 2262 | F75: 687163827643 | G75: 0.40714048
A76: VIII | B76: Tổng giá trị danh mục Total value of portfolio | C76: 2263 | F76: 1687780655907 | G76: 1
A78: Đại diện có thẩm quyền của Ngân hàng giám sát | E78: Đại diện có thẩm quyền của Công ty quản lý Quỹ
A79: Authorised Representative of Supervisory Bank | E79: Authorised Representative of Fund Management Company
A88: Ngân hàng TNHH MTV Standard Chartered (Việt Nam) | E88: Công ty Cổ phần Quản lý Quỹ Đầu tư Dragon Capital Việt Nam
A89: Vũ Quang Phan | E89: Lê Hoàng Anh
A90: Phó phòng Dịch vụ nghiệp vụ giám sát Quỹ | E90: Quyền Giám đốc nghiệp vụ hỗ trợ đầu tư

Sheet BCHoatDongVay_06026
A1: Phụ lục XXVI. Mẫu báo cáo về hoạt động của Quỹ Appendix XXVI. Report on Fund's Operation
A2: (Ban hành kèm theo Thông tư số 98/2020/TT-BTC ngày 16 tháng 11 năm 2020 của Bộ trưởng Bộ Tài Chính về hướng dẫn hoạt động và quản lý quỹ đầu tư chứng khoán) (Issued in association with Circular 98/2020/TT-BTC dated 16 November 2020 of the Minister of Finance on guiding the operation and management of the securities investment funds)
A3: BÁO CÁO HOẠT ĐỘNG ĐẦU TƯ CỦA QUỸ MỞ REPORT ON OPEN ENDED FUND'S INVESTMENT ACTIVITIES
A5: =TONGQUAN!C2 -> Quý IV năm 2024 / Quarter IV 2024
A7: Tên Công ty quản lý quỹ: | G7: =TONGQUAN!D5 -> Công ty Cổ phần Quản lý Quỹ Đầu tư Dragon Capital Việt Nam
A8: Fund Management Company: | G8: =TONGQUAN!D6 -> Dragon Capital Vietfund Management Joint Stock Company
A9: Tên ngân hàng giám sát: | G9: =TONGQUAN!D7 -> Ngân hàng TNHH Một thành viên Standard Chartered (Việt Nam)
A10: Supervising bank: | G10: =TONGQUAN!D8 -> Standard Chartered Bank (Vietnam) Limited
A11: Tên Quỹ: | G11: =TONGQUAN!D9 -> Quỹ Đầu tư Trái phiếu DC
A12: Fund name: | G12: =TONGQUAN!D10 -> DC Bond Fund (DCBF)
A13: Ngày lập báo cáo: | G13: =TONGQUAN!D11 -> Ngày 07 tháng 01 năm 2025
A14: Reporting Date: | G14: =TONGQUAN!D12 -> 07 Jan 2025
A15: A. | B15: BÁO CÁO CHUNG VỀ HOẠT ĐỘNG ĐẦU TƯ CỦA QUỸ/GENERAL INFORMATION ON FUND'S INVESTMENT ACTIVITIES
A16: IV | B16: BÁO CÁO HOẠT ĐỘNG VAY, GIAO DỊCH MUA BÁN LẠI / REPORT ON BORROWING OPERATION, REPO/REVERSE REPO TRANSACTIONS
A17: STT No. | B17: Nội dung hoạt động (nên chi tiết theo mục tiêu và đối tác) Description | C17: Đối tác Counterparty | D17: Mục tiêu/ Tài sản đảm bảo Collateral | E17: Kỳ hạn Term | F17: Giá trị khoản vay hoặc khoản cho vay Amount | G17: Thời điểm giao dịch As at transaction date | I17: Thời điểm báo cáo As at reporting date
G18: Ngày tháng năm Date | H18: Tỷ lệ giá trị hợp đồng/giá trị tài sản ròng của quỹ/công ty (%) Balance/NAV (%) | I18: Ngày tháng năm Date | J18: Tỷ lệ giá trị hợp đồng/ giá trị tài sản ròng của quỹ/ công ty (%) Balance/NAV (%)
A19: 1 | B19: Các khoản vay tiền (nêu chi tiết từng hợp đồng)
A20: ... | B20: ... | C20: ... | D20: ... | E20: ... | F20: ... | G20: ... | H20: ... | I20: ... | J20: ...
A21: I | B21: Tổng giá trị các khoản vay tiền/giá trị tài sản ròng | F21: 0 | H21: 0 | J21: 0
A22: 2 | B22: Hợp đồng Repo (nêu chi tiết từng hợp đồng)
A23: ... | B23: ... | C23: ... | D23: ... | E23: ... | F23: ... | G23: ... | H23: ... | I23: ... | J23: ...
A24: II | B24: Tổng giá trị các hợp đồng Repo/giá trị tài sản ròng | F24: 0 | H24: 0 | J24: 0
A25: A | B25: Tổng giá trị các khoản vay/giá trị tài sản ròng (=I+II) | F25: 0 | H25: 0 | J25: 0
A26: 3 | B26: Cho vay chứng khoán (nêu chi tiết từng hợp đồng)
A27: ... | B27: ... | C27: ... | D27: ... | E27: ... | F27: ... | G27: ... | H27: ... | I27: ... | J27: ...
A28: III | B28: Tổng giá trị các hợp đồng/giá trị tài sản ròng | F28: 0 | H28: 0 | J28: 0
A29: 4 | B29: Hợp đồng Reverse Repo (nêu chi tiết từng hợp đồng)
A30: ... | B30: ... | C30: ... | D30: ... | E30: ... | F30: ... | G30: ... | H30: ... | I30: ... | J30: ...
A31: IV | B31: Tổng giá trị các hợp đồng/ giá trị tài sản ròng | F31: 0 | H31: 0 | J31: 0
A32: B | B32: Tổng giá trị các khoản cho vay/giá trị tài sản ròng (=III + IV) | F32: 0 | H32: 0 | J32: 0
A33: Đại diện có thẩm quyền của Ngân hàng giám sát | I33: Đại diện có thẩm quyền của Công ty quản lý Quỹ
A34: Authorised Representative of Supervisory Bank | I34: Authorised Representative of Fund Management Company
A40: Ngân hàng TNHH MTV Standard Chartered (Việt Nam) | I40: Công ty Cổ phần Quản lý Quỹ Đầu tư Dragon Capital Việt Nam
A41: Vũ Quang Phan | I41: Lê Hoàng Anh
A42: Phó phòng Dịch vụ nghiệp vụ giám sát Quỹ | I42: Quyền Giám đốc nghiệp vụ hỗ trợ đầu tư

Sheet Khac_06030
A1: Phụ lục XXVI. Mẫu báo cáo về hoạt động của Quỹ Appendix XXVI. Report on Fund's Operation
A2: (Ban hành kèm theo Thông tư số 98/2020/TT-BTC ngày 16 tháng 11 năm 2020 của Bộ trưởng Bộ Tài Chính về hướng dẫn hoạt động và quản lý quỹ đầu tư chứng khoán) (Issued in association with Circular 98/2020/TT-BTC dated 16 November 2020 of the Minister of Finance on guiding the operation and management of the securities investment funds)
A3: BÁO CÁO HOẠT ĐỘNG ĐẦU TƯ CỦA QUỸ MỞ REPORT ON OPEN ENDED FUND'S INVESTMENT ACTIVITIES
A5: Quý IV năm 2024 / Quarter IV 2024
A7: Tên Công ty quản lý quỹ: | C7: Công ty Cổ phần Quản lý Quỹ Đầu tư Dragon Capital Việt Nam
A8: Fund Management Company: | C8: Dragon Capital Vietfund Management Joint Stock Company
A9: Tên ngân hàng giám sát: | C9: Ngân hàng TNHH Một thành viên Standard Chartered (Việt Nam)
A10: Supervising bank: | C10: Standard Chartered Bank (Vietnam) Limited
A11: Tên Quỹ: | C11: Quỹ Đầu tư Trái phiếu DC
A12: Fund name: | C12: DC Bond Fund (DCBF)
A13: Ngày lập báo cáo: | C13: Ngày 07 tháng 01 năm 2025
A14: Reporting Date: | C14: 07 Jan 2025
A16: A. | B16: BÁO CÁO CHUNG VỀ HOẠT ĐỘNG ĐẦU TƯ CỦA QUỸ/GENERAL INFORMATION ON FUND'S INVESTMENT ACTIVITIES
A17: V | B17: MỘT SỐ CHỈ TIÊU KHÁC / OTHER INDICATORS
A18: STT No | B18: Chỉ tiêu Indicators | C18: Mã chỉ tiêu Code | D18: Quý IV năm 2024 Quarter IV 2024 | E18: Quý III năm 2024 Quarter III 2024
A19: I | B19: CÁC CHỈ TIÊU VỀ HIỆU QUẢ HOẠT ĐỘNG INVESTMENT PERFORMANCE INDICATORS | C19: 2264
A20: 1 | B20: Tỷ lệ giá dịch vụ quản lý quỹ trả cho công ty quản lý quỹ/Giá trị tài sản ròng trung bình trong kỳ (%) Management fee paid to the fund management company/Average NAV (%) | C20: 2265 | D20: 0.012067296 | E20: 0.012067621
A21: 2 | B21: Tỷ lệ giá dịch vụ lưu ký, giám sát trả cho Ngân hàng Giám sát/Giá trị tài sản ròng trung bình trong kỳ (%) Custody and supervising fees paid to the Supervisory Bank/Average NAV (%) | C21: 2266 | D21: 0.00081052371 | E21: 0.00086850456
A22: 3 | B22: Tỷ lệ chi phí dịch vụ quản trị quỹ, và các chi phí khác mà công ty quản lý quỹ trả cho tổ chức cung cấp dịch vụ có liên quan/Giá trị tài sản ròng của quỹ trung bình trong kỳ (%) Fund admin fee, and other fees paid to relating services providers by the fund management company/Average NAV (%) | C22: 22661 | D22: 0.00042509673 | E22: 0.00043174356
A23: 4 | B23: Chi phí kiểm toán trả cho tổ chức kiểm toán (nếu phát sinh)/Giá trị tài sản ròng trung bình trong kỳ (%) Auditing fee paid to auditing organizations (if any)/Average NAV (%) | C23: 2267 | D23: 8.8117019e-05 | E23: 9.8045414e-05
A24: 5 | B24: Chi phí trả cho tổ chức quản lý bất động sản/ Giá trị tài sản ròng trung bình trong kỳ (%) (không áp dụng) Fee paid to Real Estate management organisation/ Average NAV (%) (not applicable) | C24: 2286
A25: 6 | B25: Chi phí trả cho doanh nghiệp thẩm định giá bất động sản/Giá trị tài sản ròng trung bình trong kỳ (%) (không áp dụng) Fee paid to Real Estate valuation service provider/ Average NAV (%) (not applicable)
A26: 7 | B26: Chi phí dịch vụ tư vấn pháp lý, dịch vụ báo giá và các dịch vụ hợp lý khác, thù lao trả cho ban đại diện quỹ/Giá trị tài sản ròng trung bình trong kỳ (%) Legal consultancy, price quotation and other appropriate service fees; remunerations paid to the Board of Representatives/Average NAV (%) | C26: 2268 | D26: 0.00019464242 | E26: 0.00015085332
A27: 8 | B27: Tỷ lệ chi phí /Giá trị tài sản ròng trung bình trong kỳ (%) Expense/Average NAV (%) | C27: 2269 | D27: 0.013651615 | E27: 0.013723292
A28: 9 | B28: Tốc độ vòng quay danh mục trong kỳ (%)/Portfolio turnover rate (%) | C28: 2270 | D28: 1.7853931 | E28: 1.7217115
A29: 10 | B29: Tỷ lệ thu nhập (tính cả thu nhập từ lãi, cổ tức, trái tức, chênh lệch giá)/ Giá trị tài sản ròng (không áp dụng) Income (including interest income, dividend, coupon income and unrealised gain)/ Average NAV (%) (not applicable) | C29: 2287
A30: II | B30: CÁC CHỈ TIÊU KHÁC OTHER INDICATORS | C30: 2272
A31: 1 | B31: Quy mô quỹ đầu kỳ (tính theo mệnh giá chứng chỉ quỹ) Fund scale at the beginning of the period (based on par value of fund certificate) | C31: 2273 | D31: 557399216300 | E31: 512141120400
B32: Tổng giá trị chứng chỉ quỹ đang lưu hành đầu kỳ Total value of outstanding Fund Certificate at the beginning of period | C32: 2274 | D32: 557399216300 | E32: 512141120400
B33: Tổng số lượng chứng chỉ quỹ đang lưu hành đầu kỳ Total number of outstanding Fund Certificate at the beginning of period | C33: 2275 | D33: 55739922 | E33: 51214112
A34: 2 | B34: Thay đổi quy mô quỹ trong kỳ (tính theo mệnh giá chứng chỉ quỹ) Change of Fund scale during the period (based on par value of fund certificate) | C34: 2276 | D34: 50479299800 | E34: 45258095900
B35: Thay đổi số lượng chứng chỉ quỹ trong kỳ Change of Number of Fund Certificates during the period | C35: 22761 | D35: 5047930 | E35: 4525809.6
B36: Thay đổi giá trị vốn trong kỳ (theo mệnh giá) Change in capital amount during the period (based on par value) | C36: 22762 | D36: 50479299800 | E36: 45258095900
B37: Số lượng chứng chỉ quỹ phát hành thêm trong kỳ Number of Fund Certificates subscribed during the period | C37: 2277 | D37: 19074809 | E37: 16096108
B38: Giá trị vốn huy động thêm trong kỳ (theo mệnh giá) Net subscription amount during the period (based on par value) | C38: 2278 | D38: 190748086600 | E38: 160961080900
B39: Số lượng chứng chỉ quỹ mua lại trong kỳ Number of Fund Certificates redeemed during the period | C39: 22781 | D39: -14026879 | E39: -11570298
B40: Giá trị vốn phải thanh toán trong kỳ khi đáp ứng lệnh của nhà đầu tư (theo mệnh giá) Net redemption amount during the period (based on par value) | C40: 22782 | D40: -140268786800 | E40: -115702985000
A41: 3 | B41: Quy mô quỹ cuối kỳ (tính theo mệnh giá chứng chỉ quỹ) Fund scale at the end of the period (based on par value) | C41: 2279 | D41: 607878516100 | E41: 557399216300
B42: Tổng giá trị thị trường của quỹ đang lưu hành cuối kỳ (theo mệnh giá) Total value of outstanding Fund Certificate at the end of the period (based on par value) | C42: 2280 | D42: 607878516100 | E42: 557399216300
B43: Tổng số lượng chứng chỉ quỹ đang lưu hành cuối kỳ Total number of outstanding Fund Certificate at the end of the period | C43: 2281 | D43: 60787852 | E43: 55739922
A44: 4 | B44: Tỷ lệ nắm giữ chứng chỉ quỹ của công ty quản lý quỹ và người có liên quan cuối kỳ Fund Management Company and related parties' ownership ratio at the end of the period | C44: 2282 | D44: 6.8947493e-05 | E44: 7.519153e-05
A45: 5 | B45: Tỷ lệ nắm giữ chứng chỉ quỹ của 10 nhà đầu tư lớn nhất cuối kỳ Top 10 investors' ownership ratio at the end of the period | C45: 2283 | D45: 0.2831 | E45: 0.284
A46: 6 | B46: Tỷ lệ nắm giữ chứng chỉ quỹ của nhà đầu tư nước ngoài cuối kỳ Foreign investors' ownership ratio at the end of the period (***) | C46: 2284 | D46: 0.0081 | E46: 0.0078
A47: 7 | B47: Số nhà đầu tư tham gia vào quỹ, kể cả giao dịch ký danh Number of investors of the Fund at the end of the period | C47: 22841 | D47: 11859 | E47: 11566
A48: 8 | B48: Giá trị tài sản ròng trên một đơn vị quỹ cuối kỳ Net asset value per Fund Certificate at the end of period | C48: 2285 | D48: 27120.12 | E48: 26651.9
A49: 9 | B49: Giá trị thị trường trên một chứng chỉ quỹ/cổ phiếu cuối kỳ (không áp dụng) Market price per fund certificates at the end of period (not applicable) | C49: 2288
A50: Ghi chú: Note:
A51: (*) Các chỉ tiêu từ 1 đến 7 của "Chỉ tiêu về hiệu quả hoạt động" đã được điều chỉnh để phản ánh số liệu trên cơ sở hoạt động tròn năm bằng cách nhân các chỉ tiêu này với 12 (đối với báo cáo tháng), 4 (đối với báo cáo quý), 2 (đối với báo cáo bán niên), 1 (đối với báo cáo năm). All Indicator starting from number 1 to 7 of "Investment performance indicators" are annualized to reflect a rate that is based on a full year operation by multiplying these indicators with 12 (monthly report) or 4 (quarterly report) or 2 (semi-annual report) or 1 (annual report). (**) Không tính đến giá trị cam kết của các hợp đồng tương lai chỉ số. Excluding the committed value of the Index Futures contracts.
A52: (***) Hiện tại Công ty Cổ phần Quản lý Quỹ Đầu tư Dragon Capital Việt Nam ("DCVFM") đang làm thủ tục cập nhật lên trên hệ thống Đại lý chuyển nhượng (“VSD”) từ hình thức Nhà đầu tư trong nước thành hình thức doanh nghiệp thành lập trong nước có vốn đầu tư nước ngoài. Vì vậy, chỉ tiêu “Tỷ lệ sở hữu nước ngoài” được trình bày ở trên vẫn tính toán dựa trên báo cáo từ VSD với dữ liệu DCVFM là nhà đầu tư trong nước. Dragon Capital Vietfund Management Joint Stock Company ("DCVFM") is updating Company's information from Local coporation to Foreign Direct Investment corporation in Vietnam Securites Depository ("VSD") system. Therefore, above Foreign Investors' Ownership Ratio is still calculated based on VSD's report which records DCVFM is Local coporation.
A53: Đại diện có thẩm quyền của Ngân hàng giám sát | D53: Đại diện có thẩm quyền của Công ty quản lý Quỹ
A54: Authorised Representative of Supervisory Bank | D54: Authorised Representative of Fund Management Company
A64: Ngân hàng TNHH MTV Standard Chartered (Việt Nam) | D64: Công ty Cổ phần Quản lý Quỹ Đầu tư Dragon Capital Việt Nam
A65: Vũ Quang Phan | D65: Lê Hoàng Anh
A66: Phó phòng Dịch vụ nghiệp vụ giám sát Quỹ | D66: Quyền Giám đốc nghiệp vụ hỗ trợ đầu tư

Sheet BCThuNhap_06203
A1: Mẫu số B01 - QM Báo cáo thu nhập Template B01 - QM Statement of Comprehensive Income
A2: (Ban hành kèm theo Thông tư 198/2012/TT-BTC ngày 15 tháng 11 năm 2012 về chế độ kế toán áp dụng đối với quỹ mở) (Issued in association with Circular 198/2012/TT-BTC dated 15 Nov 2012 on the Accounting Policies for Open-Ended Fund)
A3: BÁO CÁO THU NHẬP STATEMENT OF COMPREHENSIVE INCOME
A5: =TONGQUAN!C2 -> Quý IV năm 2024 / Quarter IV 2024
A7: Tên Công ty quản lý quỹ: | D7: =TONGQUAN!D5 -> Công ty Cổ phần Quản lý Quỹ Đầu tư Dragon Capital Việt Nam
A8: Fund Management Company: | D8: =TONGQUAN!D6 -> Dragon Capital Vietfund Management Joint Stock Company
A9: Tên ngân hàng giám sát: | D9: =TONGQUAN!D7 -> Ngân hàng TNHH Một thành viên Standard Chartered (Việt Nam)
A10: Supervising bank: | D10: =TONGQUAN!D8 -> Standard Chartered Bank (Vietnam) Limited
A11: Tên Quỹ: | D11: =TONGQUAN!D9 -> Quỹ Đầu tư Trái phiếu DC
A12: Fund name: | D12: =TONGQUAN!D10 -> DC Bond Fund (DCBF)
A13: Ngày lập báo cáo: | D13: =TONGQUAN!D11 -> Ngày 07 tháng 01 năm 2025
A14: Reporting Date: | D14: =TONGQUAN!D12 -> 07 Jan 2025
A16: Chỉ tiêu Indicator | B16: Mã số Code | C16: Thuyết minh Note | D16: Năm 2024 Year 2024 | F16: Năm 2023 Year 2023
D17: =BCKetQuaHoatDong_06028!D18 -> Quý IV năm 2024 Quarter IV 2024 | E17: Số lũy kế Year-to-date | F17: Quý IV năm 2023 Quarter IV 2023 | G17: Số lũy kế Year-to-date
A18: I. THU NHẬP, DOANH THU HOẠT ĐỘNG ĐẦU TƯ Investment income | B18: 01 | D18: 33379845676 | E18: 99509616251 | F18: 12330419193 | G18: 41092208650
A19: 1.1. Cổ tức được chia Dividend income | B19: 02 | D19: 0 | E19: 0 | F19: 0 | G19: 0
A20: 1.2. Tiền lãi được nhận Interest income | B20: 03 | D20: 31084786669 | E20: 94422054315 | F20: 10074642133 | G20: 37966620921
A21: Lãi tiền gửi ngân hàng Interest income from bank deposits | B21: 03.1 | D21: 4691725157 | E21: 13238023615 | F21: 128065761 | G21: 3206997455
A22: Lãi công cụ thị trường tiền tệ Interest income from Money market instruments | B22: 03.2 | D22: 4956410958 | E22: 16511397258 | F22: 970410958 | G22: 1909726027
A23: Lãi trái phiếu Interest income from bonds | B23: 03.3 | D23: 21436650554 | E23: 64672633442 | F23: 8976165414 | G23: 32849897439
A24: Tiền lãi hợp đồng mua lại đảo ngược được nhận Reverse repo contract interest received | B24: 03.4 | D24: 0 | E24: 0 | F24: 0 | G24: 0
A25: 1.3. Lãi (lỗ) bán các khoản đầu tư Realized gain (losses) from disposal investments | B25: 04 | D25: 2605392376 | E25: 6377328833 | F25: 1242797289 | G25: 2062879766
A26: 1.4. Chênh lệch tăng, giảm đánh giá lại các khoản đầu tư chưa thực hiện Unrealized gain (losses) from investment revaluation | B26: 05 | D26: -310333369 | E26: -1289766897 | F26: 1012979771 | G26: 1062707963
A27: 1.5. Doanh thu khác Other income | B27: 06 | D27: 0 | E27: 0 | F27: 0 | G27: 0
A28: 1.6. Chênh lệch lãi, lỗ tỷ giá hối đoái đã và chưa thực hiện Realized and unrealized gain (losses) from foreign exchange | B28: 07 | D28: 0 | E28: 0 | F28: 0 | G28: 0
A29: 1.7. Doanh thu khác về đầu tư Other investment income | B29: 08 | D29: 0 | E29: 0 | F29: 0 | G29: 0
... A77: VIII. LỢI NHUẬN KẾ TOÁN SAU THUẾ TNDN PROFIT AFTER TAX (41=30-40) | B77: 41 | D77: 27675101189 | E77: 81723687606 | F77: 10755690676 | G77: 34890488461
A80: Người lập: | B80: Người duyệt:
A93: _______________________________________________ | B93: ___________________________________________ | F93: _____________________________
A94: Vương Thị Trâm Anh | B94: Ninh Thị Tuệ Minh | F94: Lê Hoàng Anh
A95: Kế toán Quỹ | B95: Trưởng phòng Kế toán Quỹ | F95: Quyền Giám đốc nghiệp vụ hỗ trợ đầu tư

Sheet BCTinhHinhTaiChinh_06105
A1: Mẫu số B02 - QM. Báo cáo tình hình tài chính Template B02 - QM. Statement of Financial Position
A2: (Ban hành kèm theo Thông tư 198/2012/TT-BTC ngày 15 tháng 11 năm 2012 về chế độ kế toán áp dụng đối với quỹ mở) (Issued in association with Circular 198/2012/TT-BTC dated 15 Nov 2012 on the Accounting Policies for Open-Ended Fund)
A3: BÁO CÁO TÌNH HÌNH TÀI CHÍNH STATEMENT OF FINANCIAL POSITION
A5: =TONGQUAN!C1 -> Tại ngày 31 tháng 12 năm 2024 / As at 31 Dec 2024
A7: Tên Công ty quản lý quỹ: | C7: =TONGQUAN!D5 -> Công ty Cổ phần Quản lý Quỹ Đầu tư Dragon Capital Việt Nam
A8: Fund Management Company: | C8: =TONGQUAN!D6 -> Dragon Capital Vietfund Management Joint Stock Company
A9: Tên ngân hàng giám sát: | C9: =TONGQUAN!D7 -> Ngân hàng TNHH Một thành viên Standard Chartered (Việt Nam)
A10: Supervising bank: | C10: =TONGQUAN!D8 -> Standard Chartered Bank (Vietnam) Limited
A11: Tên Quỹ: | C11: =TONGQUAN!D9 -> Quỹ Đầu tư Trái phiếu DC
A12: Fund name: | C12: =TONGQUAN!D10 -> DC Bond Fund (DCBF)
A13: Ngày lập báo cáo: | C13: =TONGQUAN!D11 -> Ngày 07 tháng 01 năm 2025
A14: Reporting Date: | C14: =TONGQUAN!D12 -> 07 Jan 2025
A16: STT No. | B16: Chỉ tiêu Indicator | C16: Mã số Code | D16: Thuyết minh Note | E16: =BCTaiSan_06027!D18 -> Ngày 31 tháng 12 năm 2024 As at 31 Dec 2024 | F16: =BCTaiSan_06027!E18 -> Ngày 30 tháng 09 năm 2024 As at 30 Sep 2024
A17: I | B17: I. TÀI SẢN ASSETS | C17: I
A18: 1 | B18: 1.Tiền gửi ngân hàng và tương đương tiền Cash at bank and cash equivalent | C18: 110 | E18: 260940922040 | F18: 156172164816
A19: 1.1 | B19: 1.1. Tiền gửi ngân hàng Cash at bank | C19: 111 | E19: 12140922040 | F19: 10372164816
B20: Tiền gửi của nhà đầu tư cho hoạt động mua chứng chỉ quỹ Cash at bank for Fund's subscription | C20: 111.1 | E20: 9923142711 | F20: 9525444010
B21: Tiền phải trả cho Nhà đầu tư về cổ tức và mua lại chứng chỉ quỹ Cash at bank for Fund's dividend payment and redemption | C21: 111.2 | E21: 4391073 | F21: 4391073
B22: Tiền gửi ngân hàng cho hoạt động của Quỹ Cash at bank for Fund's operation | C22: 111.3 | E22: 2213388256 | F22: 842329733
B23: Tiền gửi ký quỹ cho hoạt động đầu tư chứng khoán phái sinh Margin account for trading derivatives | C23: 111.4 | E23: 0 | F23: 0
A24: 1.2 | B24: 1.2. Tiền gửi có kỳ hạn không quá ba (03) tháng Deposit with term up to three (03) months | C24: 112 | E24: 248800000000 | F24: 145800000000
A25: 2 | B25: 2. Các khoản đầu tư thuần Net Investments | C25: 120 | E25: 1383107257612 | F25: 1360106253896
A26: 2.1 | B26: 2.1. Các khoản đầu tư Investments | C26: 121 | E26: 1383107257612 | F26: 1360106253896
B27: Cổ phiếu, chứng chỉ quỹ niêm yết Listed Shares, fund certificates | C27: 121.1 | E27: 0 | F27: 0
B28: Cổ phiếu, chứng chỉ quỹ chưa niêm yết Unlisted Shares, fund certifictes | C28: 121.2 | E28: 0 | F28: 0
B29: Trái phiếu niêm yết Listed Bonds | C29: 121.3 | E29: 803804814079 | F29: 796657988636
B30: Trái phiếu chưa niêm yết Unlisted Bonds | C30: 121.4 | E30: 153079537930 | F30: 142348265260
B31: Công cụ thị trường tiền tệ Money market instruments | C31: 121.5 | E31: 265122905603 | F31: 265000000000
B32: Hợp đồng tiền gửi có kỳ hạn trên ba (03) tháng Deposits with term over three (03) months | C32: 121.6 | E32: 161100000000 | F32: 156100000000
B33: Quyền mua chứng khoán Investment - Rights | C33: 121.7 | E33: 0 | F33: 0
B34: Hợp đồng tương lai chỉ số Index future contracts | C34: 121.8 | E34: 0 | F34: 0
B35: Đầu tư khác Other Investments | C35: 121.9 | E35: 0 | F35: 0
B36: Hợp đồng mua lại đảo ngược Reverse repo contracts | C36: 121.10 | E36: 0 | F36: 0
A37: 2.2 | B37: 2.2. Dự phòng giảm giá tài sản nhận thế chấp Impairment of devaluation of pledged assets | C37: 122 | E37: 0 | F37: 0
A38: 3 | B38: 3. Các khoản phải thu Receivables | C38: 130 | E38: 43732476255 | F38: 22327657480
A39: 3.1 | B39: 3.1 Phải thu về bán các khoản đầu tư Receivables from investments sold but not yet settled | C39: 131 | E39: 0 | F39: 0
B40: Trong đó: Phải thu khó đòi về bán các khoản đầu tư In which: Overdue receivables from selling investments | C40: 132 | E40: 0 | F40: 0
A41: 3.2 | B41: 3.2. Phải thu và dự thu cổ tức, tiền lãi các khoản đầu tư Dividend and interest receivables | C41: 133 | E41: 43732476255 | F41: 22291073922
A42: 3.2.1 | B42: 3.2.1. Phải thu cổ tức, tiền lãi đến ngày nhận Dividend and interest receivables on or after payment date | C42: 134 | E42: 0 | F42: 0
B43: Phải thu cổ tức Dividend receivables | C43: 134.1 | E43: 0 | F43: 0
B44: Phải thu trái tức Coupon receivables | C44: 134.2 | E44: 0 | F44: 0
B45: Phải thu lãi tiền gửi có kỳ hạn không quá ba (03) tháng Interest receivables from deposit with term up to three (03) months | C45: 134.3 | E45: 0 | F45: 0
B46: Phải thu lãi tiền gửi có kỳ hạn trên 3 tháng Interest receivables from deposit with term more than three (03) months | C46: 134.4 | E46: 0 | F46: 0
B47: Phải thu lãi Công cụ thị trường tiền tệ Interest receivables from Money market instruments | C47: 134.5 | E47: 0 | F47: 0
B48: Trong đó: Phải thu khó đòi về cổ tức, tiền lãi đến ngày nhận nhưng chưa nhận được In which: Overdue receivables from dividend, interest income | C48: 135 | E48: 0 | F48: 0
A49: 3.2.2 | B49: 3.2.2.Dự thu cổ tức, tiền lãi chưa đến ngày nhận Dividend and interest receivables before payment date | C49: 136 | E49: 43732476255 | F49: 22291073922
B50: Dự thu cổ tức Dividend receivables | C50: 136.1 | E50: 0 | F50: 0
B51: Dự thu lãi trái phiếu Interest accrual from bonds | C51: 136.2 | E51: 30288039815 | F51: 15619405291
B52: Dự thu lãi tiền gửi có kỳ hạn không quá ba (03) tháng Interest accrual from deposits with term up to three (03) months | C52: 136.3 | E52: 592969865 | F52: 339010274
B53: Dự thu lãi tiền gửi có kỳ hạn trên 3 tháng Interest accrual from deposit with term more than three (03) months | C53: 136.4 | E53: 3249356986 | F53: 830247398
B54: Dự thu lãi Công cụ thị trường tiền tệ Interest accrual from Money market instruments | C54: 136.5 | E54: 9602109589 | F54: 5502410959
B55: Dự thu lãi hợp đồng mua lại đảo ngược Interest receivables from reverse repo contracts | C55: 136.6 | E55: 0 | F55: 0
A56: 3.3 | B56: 3.3. Các khoản phải thu khác Other receivables | C56: 137 | E56: 0 | F56: 36583558
B57: Phải thu cho khoản cổ phiếu hạn chế chờ mua Receivable from AP/Investors on securities on hold of buying | C57: 137.1 | E57: 0 | F57: 0
B58: Các tài sản khác Other assets | C58: 137.2 | E58: 0 | F58: 36583558
B59: Các khoản khác Others | C59: 137.3 | E59: 0 | F59: 0
A60: 3.4 | B60: 3.4. Dự phòng nợ phải thu khó đòi Provision for doubtful debt | C60: 138 | E60: 0 | F60: 0
B61: TỔNG TÀI SẢN TOTAL ASSETS | C61: 100 | E61: 1687780655907 | F61: 1538606076192
A62: II | B62: II. NỢ PHẢI TRẢ TOTAL LIABILITIES | C62: II
A63: 1 | B63: 1. Vay ngắn hạn Short-term loans | C63: 311 | E63: 0 | F63: 0
B64: Gốc hợp đồng repo Repo contracts - Principal | C64: 311.1 | E64: 0 | F64: 0
B65: Vay ngắn hạn Short-term loans | C65: 311.2 | E65: 0 | F65: 0
A66: 2 | B66: 2. Phải trả về mua các khoản đầu tư Payables for securities bought but not yet settled | C66: 312 | E66: 0 | F66: 0
A67: 3 | B67: 3. Phải trả phí cho các Đại lý phân phối, Công ty quản lý quỹ về mua bán Chứng chỉ quỹ Subscription and Redemption fee payable to distributors and fund management company | C67: 313 | E67: 405658375 | F67: 297211309
B68: Phải trả phí cho các Đại lý phân phối về mua bán Chứng chỉ quỹ Subscription and Redemption fee payable to distributors | C68: 313.1 | E68: 0 | F68: 0
B69: Phải trả phí cho Công ty quản lý quỹ về mua bán Chứng chỉ quỹ Subscription and Redemption fee payable to fund management company | C69: 313.2 | E69: 405658375 | F69: 297211309
A70: 4 | B70: 4. Thuế và các khoản phải nộp Nhà nước Tax payables and obligations to the State Budget | C70: 314 | E70: 137193084 | F70: 159790129
A71: 5 | B71: 5.Phải trả thu nhập cho Nhà đầu tư Profit distribution payables | C71: 315 | E71: 0 | F71: 0
A72: 6 | B72: 6. Chi phí phải trả Expense Accruals | C72: 316 | E72: 318635741 | F72: 264794240
B73: Phí giao dịch Transaction fee | C73: 316.1 | E73: 192537125 | F73: 192537125
B74: Phải trả phí môi giới Brokerage fee payables | C74: 316.1.1 | E74: 192537125 | F74: 192537125
B75: Phải trả phí giao dịch thanh toán bù trừ chứng khoán Clearing Settlement Fee payables | C75: 316.1.2 | E75: 0 | F75: 0
B76: Trích trước phí kiểm toán Accrued expense for audit fee | C76: 316.2 | E76: 74480000 | F76: 39421164
B77: Trích trước phí họp đại hội thường niên Accrued expense for Annual General meeting | C77: 316.3 | E77: 39618616 | F77: 22344148
B78: Trích trước phí báo cáo thường niên Accrued expense for Annual report | C78: 316.4 | E78: 0 | F78: 0
B79: Trích trước thù lao ban đại diện quỹ Accrued expense for Remuneration Payable to Fund's Board of Representatives | C79: 316.5 | E79: 12000000 | F79: 10491803
B80: Trích trước phí quản lý niêm yết hàng năm tại SGDCK Accrued expense for annual listing fee at HOSE | C80: 316.6 | E80: 0 | F80: 0
B81: Trích trước lãi vay ngắn hạn của hợp đồng vay và hợp đồng repo Accrued Interest Expense of short-term loan contracts and repo contracts | C81: 316.7 | E81: 0 | F81: 0
A82: 7 | B82: 7. Phải trả cho Nhà đầu tư về mua Chứng chỉ quỹ Subscription payables to investors | C82: 317 | E82: 9923142711 | F82: 9525444010
B83: Phải trả cho nhà đầu tư chờ mua chứng chỉ quỹ Subscription Pending allotment | C83: 317.1 | E83: 9923142711 | F83: 9525444010
B84: Phải trả nhà đầu tư trên tài sản giữ hộ Payables to investors for investment bought on behalf | C84: 317.2 | E84: 0 | F84: 0
A85: 8 | B85: 8. Phải trả cho Nhà đầu tư về mua lại Chứng chỉ quỹ Redemption payables to investors | C85: 318 | E85: 26569805507 | F85: 41158374254
A86: 9 | B86: 9. Phải trả dịch vụ quản lý Quỹ mở Fund management related service expense payable | C86: 319 | E86: 1816922007 | F86: 1588669023
B87: Trích trước phải trả phí quản lý Accrued expense for Management fee | C87: 319.1 | E87: 1650065860 | F87: 1435279293
B88: Trích trước phí lưu ký tài sản Quỹ mở Accrued expense for Custodian fee | C88: 319.2 | E88: 49976921 | F88: 50292643
B89: Phí dịch vụ lưu ký - bảo quản tài sản Custodian service - Safe Custody Fee | C89: 319.2.1 | E89: 48126921 | F89: 47842643
B90: Phí dịch vụ lưu ký - giao dịch chứng khoán Custodian service - Transaction fee | C90: 319.2.2 | E90: 1100000 | F90: 1700000
B91: Phí dịch vụ lưu ký cho chứng khoán cơ sở, phí quản lý vị thế và tài sản phái sinh trả cho VSDC Custodian service - Depository fee, Position and Margin management fee paid to VSDC | C91: 319.2.3 | E91: 750000 | F91: 750000
B92: Trích trước phí quản trị quỹ Accrued expense for Fund administration fee | C92: 319.3 | E92: 45376811 | F92: 39470179
B93: Trích trước phí giám sát Accrued expense for Supervising fee | C93: 319.4 | E93: 60502415 | F93: 52626908
B94: Trích trước phí dịch vụ đại lý chuyển nhượng Accrued expense for Tranfer agency fee | C94: 319.5 | E94: 11000000 | F94: 11000000
B95: Dự chi phí cung cấp dịch vụ tính giá trị tài sản ròng tham chiếu (iNAV) cho HOSE Accrued expense for payable to HOSE for iNAV calculation | C95: 319.6 | E95: 0 | F95: 0
B96: Dự chi phí cấp quyền sử dụng chỉ số cho HOSE Accrued expense for payable to HOSE for Index usage | C96: 319.7 | E96: 0 | F96: 0
A97: 10 | B97: 10. Phải trả, phải nộp khác Other payables | C97: 320 | E97: 35250000 | F97: 36614754
B98: Phải trả phí báo giá Price feed fee payable | C98: 320.1 | E98: 35250000 | F98: 23500000
B99: Trích trước phí công tác, họp của ban đại diện Accrued expense for Fund's Board of Representatives travelling, meeting | C99: 320.2 | E99: 0 | F99: 0
B100: Trích trước phí quản lý thường niên trả cho UBCKNN Accrued expense for Annual Fee paid to SSC | C100: 320.3 | E100: 0 | F100: 13114754
B101: Phí Ngân hàng S2B S2B Bank charge | C101: 320.4 | E101: 0 | F101: 0
B102: Phải trả khác Other payables | C102: 320.5 | E102: 0 | F102: 0
B103: TỔNG NỢ PHẢI TRẢ TOTAL LIABILITIES | C103: 300 | E103: 39206607425 | F103: 53030897719
...

Sheet BCLCGT_06262
A1: Mẫu số B05 - QM. Báo cáo lưu chuyển tiền tệ Template B05 - QM. Cash flow statement
A2: (Ban hành kèm theo Thông tư 198/2012/TT-BTC ngày 15 tháng 11 năm 2012 về chế độ kế toán áp dụng đối với quỹ mở) (Issued in association with Circular 198/2012/TT-BTC dated 15 Nov 2012 on the Accounting Policies for Open-Ended Fund)
A3: BÁO CÁO LƯU CHUYỂN TIỀN TỆ CASH FLOW STATEMENT
A4: =TONGQUAN!C2 -> Quý IV năm 2024 / Quarter IV 2024
A7: Tên Công ty quản lý quỹ: | B7: =TONGQUAN!D5 -> Công ty Cổ phần Quản lý Quỹ Đầu tư Dragon Capital Việt Nam
A8: Fund Management Company: | B8: =TONGQUAN!D6 -> Dragon Capital Vietfund Management Joint Stock Company
A9: Tên ngân hàng giám sát: | B9: =TONGQUAN!D7 -> Ngân hàng TNHH Một thành viên Standard Chartered (Việt Nam)
A10: Supervising bank: | B10: =TONGQUAN!D8 -> Standard Chartered Bank (Vietnam) Limited
A11: Tên Quỹ: | B11: =TONGQUAN!D9 -> Quỹ Đầu tư Trái phiếu DC
A12: Fund name: | B12: =TONGQUAN!D10 -> DC Bond Fund (DCBF)
A13: Ngày lập báo cáo: | B13: =TONGQUAN!D11 -> Ngày 07 tháng 01 năm 2025
A14: Reporting Date: | B14: =TONGQUAN!D12 -> 07 Jan 2025
A17: Chỉ tiêu Indicator | B17: Mã số Code | C17: Thuyết minh Note | D17: =BCKetQuaHoatDong_06028!D18 -> Quý IV năm 2024 Quarter IV 2024 | E17: =BCKetQuaHoatDong_06028!E18 -> Quý III năm 2024 Quarter III 2024
A18: I. Lưu chuyển tiền từ hoạt động đầu tư Cash flow from investing activities | B18: I
A19: 1. Lợi nhuận trước Thuế thu nhập doanh nghiệp Profit before income tax | B19: 01 | D19: 27675101189 | E19: 21294940715
A20: 2. Điều chỉnh cho các khoản tăng giá trị tài sản ròng từ các hoạt động đầu tư Adjustment for NAV increase from investing activities | B20: 02 | D20: 361301919 | E20: 2103653951
A21: (- Lãi) hoặc (+ lỗ) chênh lệch tỷ giá hối đoái/ đánh giá lại các khoản đầu tư chưa thực hiện Unreliased (Gain) or Loss from FX valuation/Investment revaluation | B21: 03 | D21: 310333369 | E21: 2121255402
A22: (+) Chi phí trích trước Increase of Accrued Expenses | B22: 04 | D22: 50968550 | E22: -17601451
A23: 3. Lợi nhuận từ hoạt động đầu tư trước thay đổi vốn lưu động Profit from investing activities before changes in working capital | B23: 05 | D23: 28036403108 | E23: 23398594666
A24: (-) Tăng, (+) giảm đầu tư (Increase), Decrease Investments | B24: 20 | D24: -23311337085 | E24: -394164813916
A25: (-) Tăng, (+) giảm phải thu bán chứng khoán đầu tư (Increase), Decrease in Receivables from investments sold but not yet settled | B25: 06 | D25: 0 | E25: 0
A26: (-) Tăng, (+) giảm dự thu phải thu tiền lãi các khoản đầu tư (Increase), Decrease in Dividend and interest receivables | B26: 07 | D26: -21441402333 | E26: 998881763
A27: (-) Tăng, (+) giảm các khoản phải thu khác (Increase), Decrease in other receivables | B27: 08 | D27: 36583558 | E27: 10933561
A28: (+) Tăng, (-) giảm vay ngắn hạn Increase, (Decrease) in Short-term Loans | B28: 09 | D28: 0 | E28: 0
A29: (+) Tăng, (-) giảm phải trả cho người bán (Decrease), Increase in payables for securities purchased but not yet settled | B29: 10 | D29: 0 | E29: 0
A30: (+) Tăng, (-) giảm phải trả các Đại lý phân phối Chứng chỉ quỹ, Công ty Quản lý Quỹ (Decrease)/increase in subscription and redemption fee payable to distributors and Fund Management Company | B30: 11 | D30: 108447066 | E30: 16555281
... A38: Lưu chuyển tiền thuần từ hoạt động đầu tư (1+2+3) Net Cash flow from Investing activities | B38: 19 | D38: -30555011596 | E38: -327012635669
A39: II. Lưu chuyển tiền từ hoạt động tài chính Cash flow from financing activities | B39: II
A40: 1. Tiền thu từ phát hành Chứng chỉ quỹ mở Receipts from subscriptions | B40: 31 | D40: 512421664397 | E40: 426233716431
A41: 2. Tiền chi mua lại Chứng chỉ quỹ mở Payments for redemptions | B41: 32 | D41: -377097895577 | E41: -306711809447
A42: 3. Tiền vay gốc Principal of borrowings | B42: 33 | D42: 0 | E42: 0
A43: 4. Tiền chi trả nợ gốc vay Payment of Principal borrowings | B43: 34 | D43: 0 | E43: 0
A44: 5. Tiền chi trả cổ tức, tiền lãi cho nhà đầu tư Dividend, profit distribution paid to investors | B44: 35 | D44: 0 | E44: 0
A45: Lưu chuyển tiền thuần từ hoạt động tài chính (1-2+3-4-5) Net cash outflows from financing activities | B45: 30 | D45: 135323768820 | E45: 119521906984
A46: III. Tăng/giảm tiền thuần trong kỳ Net Increase/Decrease in cash and cash equivalent for the period | B46: 40 | D46: 104768757224 | E46: -207490728685
A47: IV. Tiền và các khoản tương đương tiền đầu kỳ Cash and cash equivalents at the beginning of period | B47: 50 | D47: 156172164816 | E47: 363662893501
A48: Tiền gửi ngân hàng đầu kỳ: Cash at bank of the beginning of period: | B48: 51 | D48: 156172164816 | E48: 363662893501
A49: -Tiền gửi ngân hàng và tương đương tiền cho hoạt động của Quỹ Cash at bank and cash equivalent for Fund's operation | B49: 52 | D49: 146642329733 | E49: 360560914263
A50: Tiền gửi không kỳ hạn Demand deposit | B50: 52.1 | D50: 842329733 | E50: 460914263
A51: Tiền gửi có kỳ hạn không quá ba (03) tháng Deposit with term up to three (03) months | B51: 52.2 | D51: 145800000000 | E51: 360100000000
... A64: Khác Others | B64: 80 | D64: 0 | E64: 0
A67: Người lập: | C67: Người duyệt:
A75: _______________________________ | B75: _______________________________________
A76: Vương Thị Trâm Anh | B76: Ninh Thị Tuệ Minh | E76: Lê Hoàng Anh
A77: Kế toán Quỹ | B77: Trưởng phòng Kế toán Quỹ | E77: Quyền Giám đốc nghiệp vụ hỗ trợ đầu tư

Sheet LogoFMS
D1: VFMVFB
A2: FUNDCODE | B2: FUNDNAME | C2: LOGO
A3: VFMVSF | B3: Quỹ Đầu Tư Cổ Phiếu Việt Nam Chọn Lọc
A4: VFMVF1 | B4: Quỹ Đầu tư Chứng khoán Năng động DC
A5: VFMVF4 | B5: Quỹ Đầu tư Doanh nghiệp Hàng đầu DC
A6: VFMVFA | B6: Quỹ Đầu tư Năng Động Việt Nam
A7: VFMVFB | B7: Quỹ Đầu tư Trái phiếu DC
A8: VFMVFC | B8: Quỹ Đầu tư Trái phiếu Gia tăng Thu nhập Cố định DC
A9: TCEF1 | B9: Quỹ Đầu tư Cổ phiếu Techcom
A10: TCBF | B10: Quỹ Đầu tư Cổ phiếu Techcom
A11: MBEF1 | B11: Quỹ Đầu tư JAPAN ASIA MB CAPITAL
A12: MBVF | B12: Quỹ Đầu tư Giá trị MB Capital
A13: SSISCA | B13: Quỹ Đầu tư Lợi thế Cạnh tranh Bền vững SSI
A14: VCBBCF | B14: Quỹ Đầu tư Cổ Phiếu Hàng Đầu VCBF
... A52: VCBMGF | B52: Quỹ Đầu Tư Cổ phiếu Tăng trưởng VCBF
A53: AM33
A54: AM34
A55: AM35
A56: AM36 | B56: Tổng công ty cổ phần bảo hiểm Petrolimex - PJICO EQUITY PORTFOLIO 04
A57: AM37
A58: AM38
A59: AM39
A60: AM40
A61: AM41
A62: AM42
A63: AM43
A64: AM44
A65: AM45
A66: AM46
A67: AM47
A68: AM48
... A70: AM50
A71: VMPF | B71: Quỹ Đầu Tư Cổ Phiếu Hiệu Suất Thị Trường Việt Nam VinaCapital (VinaCapital-VMPF)
A72: ENF
A73: EVESG
A74: UVDIF
A75: VDEF
A76: VCBAIF
