Workbook
Name addlogo: INDEX(#REF!,MATCH(#REF!,#REF!,0))

Sheet TONGQUAN
A1: Kỳ báo cáo: | C1: Tại ngày 31 tháng 03 năm 2021 / As at 31 Mar 2021
C2: Quý I năm 2021 / Quarter I 2021
A4: Thông tin chung:
C5: Tên Công ty quản lý quỹ: | D5: Công ty Cổ phần Quản lý Quỹ Đầu tư Dragon Capital Việt Nam
C6: Fund Management Company: | D6: Dragon Capital Vietfund Management Joint Stock Company
C7: Tên ngân hàng giám sát: | D7: Ngân hàng TNHH Một thành viên Standard Chartered (Việt Nam)
C8: Supervising bank: | D8: Standard Chartered Bank (Vietnam) Limited
C9: Tên Quỹ: | D9: Quỹ Đầu tư Chứng khoán Việt Nam
C10: Fund name: | D10: Vietnam Securities Investment Fund(VFMVF1)
C11: Ngày lập báo cáo: | D11: Ngày 06 tháng 04 năm 2021
C12: Reporting Date: | D12: 06 Apr 2021
A14: Người ký báo cáo:
C16: Đại diện có thẩm quyền của Ngân hàng giám sát | F16: Đại diện có thẩm quyền của Công ty quản lý Quỹ
C17: Authorised Representative of Supervisory Bank | F17: Authorised Representative of Fund Management Company
C19: Ngân hàng TNHH MTV Standard Chartered (Việt Nam) | F19: Công ty Cổ phần Quản lý Quỹ Đầu tư Dragon Capital Việt Nam
C20: Vũ Hương Giang | F20: Nguyễn Minh Đăng Khánh
C21: Trưởng phòng Dịch vụ Quản trị và Giám sát Quỹ | F21: Giám đốc điều hành Nghiệp vụ hỗ trợ đầu tư
B34: STT | C34: Nội dung | D34: Tên sheet
B35: A | C35: BÁO CÁO CHUNG VỀ HOẠT ĐỘNG ĐẦU TƯ CỦA QUỸ
B36: A.I | C36: Báo cáo về tài sản | D36: 06027
B37: A.II | C37: Báo cáo kết quả hoạt động | D37: 06028
B38: A.III | C38: Báo cáo danh mục đầu tư | D38: 06029
B39: A.IV | C39: Báo cáo hoạt động vay, giao dịch mua bán lại | D39: 06026
B40: A.V | C40: Một số chỉ tiêu khác | D40: 06030
B41: A.VI | C41: Thống kê phí giao dịch | D41: 06031
B42: 5 | C42: Báo cáo thay đổi giá trị tài sản ròng, giao dịch chứng chỉ quỹ | D42: 06129
B43: 6 | C43: Báo cáo thu nhập giữa niên độ | D43: 06203
B44: 7 | C44: Báo cáo tình hình tài chính giữa niên độ | D44: 06105
B45: 8 | C45: Báo cáo thay đổi giá trị tài sản ròng, giao dịch chứng chỉ quỹ giữa niên độ | D45: 06107
B46: 9 | C46: Báo cáo danh mục đầu tư | D46: 06108
B47: 10 | C47: Báo cáo lưu chuyển tiền tệ | D47: 06262
B48: 11 | C48: Báo cáo thu nhập | D48: 06104
B49: 12 | C49: Báo cáo về tài sản của quỹ | D49: 06126
B50: A.VII | C50: Thống kê giao dịch của Quỹ đầu tư bất động sản với người có liên quan | D50: không có
B51: A.VIII | C51: Thống kê giao dịch bất động sản của Quỹ đầu tư bất động sản | D51: không có
B52: B | C52: BÁO CÁO TÌNH HÌNH TỰ DOANH ĐẦU TƯ GIÁN TIẾP RA NƯỚC NGOÀI CỦA QUỸ | D52: Không có

Sheet BCthunhap
A1: Mẫu số B01g - QM. Báo cáo thu nhập Template B01g - QM. Statement of Comprehensive Income
A2: (Ban hành kèm theo Thông tư 198/2012/TT-BTC ngày 15 tháng 11 năm 2012 về chế độ kế toán áp dụng đối với quỹ mở) (Issued in association with Circular 198/2012/TT-BTC dated 15 Nov 2012 on the Accounting Policies for Open-Ended Fund)
A3: BÁO CÁO THU NHẬP STATEMENT OF COMPREHENSIVE INCOME
A5: Quý I năm 2021 / Quarter I 2021
A7: Tên Công ty quản lý quỹ: | D7: Công ty Cổ phần Quản lý Quỹ Đầu tư Dragon Capital Việt Nam
A8: Fund Management Company: | D8: Dragon Capital Vietfund Management Joint Stock Company
A9: Tên ngân hàng giám sát: | D9: Ngân hàng TNHH Một thành viên Standard Chartered (Việt Nam)
A10: Supervising bank: | D10: Standard Chartered Bank (Vietnam) Limited
A11: Tên Quỹ: | D11: Quỹ Đầu tư Chứng khoán Việt Nam
A12: Fund name: | D12: Vietnam Securities Investment Fund(VFMVF1)
A13: Ngày lập báo cáo: | D13: Ngày 06 tháng 04 năm 2021
A14: Reporting Date: | D14: 06 Apr 2021
A16: Chỉ tiêu Indicator | B16: Mã số Code | C16: Thuyết minh Note | D16: Năm 2021 Year 2021 | F16: Năm 2020 Year 2020
D17: Quý I năm 2021 Quarter I 2021 | E17: Số lũy kế Year-to-date | F17: Quý I năm 2020 Quarter I 2020 | G17: Số lũy kế Year-to-date
A18: I. THU NHẬP, DOANH THU HOẠT ĐỘNG ĐẦU TƯ Investment income | B18: 01 | D18: 54506351329 | E18: 54506351329 | F18: -213949429922 | G18: -213949429922
A19: 1.1. Cổ tức được chia Dividend income | B19: 02 | D19: 537421400 | E19: 537421400 | F19: 224360000 | G19: 224360000
A20: 1.2. Tiền lãi được nhận Interest income | B20: 03 | D20: 1168478112 | E20: 1168478112 | F20: 3179346128 | G20: 3179346128
A21: Lãi tiền gửi ngân hàng Interest income from bank deposits | B21: 03.1 | D21: 15943864 | E21: 15943864 | F21: 122743388 | G21: 122743388
A22: Lãi chứng chỉ tiền gửi Interest income from Certificates of Deposit | B22: 03.2 | D22: 1067054795 | E22: 1067054795 | F22: 1458493151 | G22: 1458493151
A23: Lãi trái phiếu Interest income from bonds | B23: 03.3 | D23: 85479453 | E23: 85479453 | F23: 1598109589 | G23: 1598109589
A24: Tiền lãi hợp đồng mua lại đảo ngược được nhận Reverse repo contract interest received | B24: 03.4 | D24: 0 | E24: 0 | F24: 0 | G24: 0
A25: 1.3. Lãi (lỗ) bán các khoản đầu tư Realized gain (losses) from disposal investments | B25: 04 | D25: 12680230736 | E25: 12680230736 | F25: 7643535882 | G25: 7643535882
A26: 1.4. Chênh lệch tăng, giảm đánh giá lại các khoản đầu tư chưa thực hiện Unrealized gain (losses) from investment revaluation | B26: 05 | D26: 40120221081 | E26: 40120221081 | F26: -224996671932 | G26: -224996671932
A27: 1.5. Doanh thu khác Other income | B27: 06 | D27: 0 | E27: 0 | F27: 0 | G27: 0
A28: 1.6. Chênh lệch lãi, lỗ tỷ giá hối đoái đã và chưa thực hiện Realized and unrealized gain (losses) from foreign exchange | B28: 07 | D28: 0 | E28: 0 | F28: 0 | G28: 0
A29: 1.7. Doanh thu khác về đầu tư Other investment income | B29: 08 | D29: 0 | E29: 0 | F29: 0 | G29: 0
... A77: VIII. LỢI NHUẬN KẾ TOÁN SAU THUẾ TNDN PROFIT AFTER TAX (41=30-40) | B77: 41 | D77: 51099476926 | E77: 51099476926 | F77: -218624918757 | G77: -218624918757
A80: Người lập: | B80: Người duyệt:
A93: _______________________________________________ | B93: ___________________________________________ | F93: _____________________________
A94: Mai Thùy Sâm | B94: Phạm Thanh Dũng | F94: Nguyễn Minh Đăng Khánh
A95: Kế toán Quỹ | B95: Kế toán Trưởng | F95: Giám đốc điều hành Nghiệp vụ hỗ trợ đầu tư

Sheet BCtinhhinhtaichinh
A1: Mẫu số B02g - QM. Báo cáo tình hình tài chính Template B02g - QM. Statement of Financial Position
A2: (Ban hành kèm theo Thông tư 198/2012/TT-BTC ngày 15 tháng 11 năm 2012 về chế độ kế toán áp dụng đối với quỹ mở) (Issued in association with Circular 198/2012/TT-BTC dated 15 Nov 2012 on the Accounting Policies for Open-Ended Fund)
A3: BÁO CÁO TÌNH HÌNH TÀI CHÍNH STATEMENT OF FINANCIAL POSITION
A5: Tại ngày 31 tháng 03 năm 2021 / As at 31 Mar 2021
A7: Tên Công ty quản lý quỹ: | C7: Công ty Cổ phần Quản lý Quỹ Đầu tư Dragon Capital Việt Nam
A8: Fund Management Company: | C8: Dragon Capital Vietfund Management Joint Stock Company
A9: Tên ngân hàng giám sát: | C9: Ngân hàng TNHH Một thành viên Standard Chartered (Việt Nam)
A10: Supervising bank: | C10: Standard Chartered Bank (Vietnam) Limited
A11: Tên Quỹ: | C11: Quỹ Đầu tư Chứng khoán Việt Nam
A12: Fund name: | C12: Vietnam Securities Investment Fund(VFMVF1)
A13: Ngày lập báo cáo: | C13: Ngày 06 tháng 04 năm 2021
A14: Reporting Date: | C14: 06 Apr 2021
A16: STT No. | B16: Chỉ tiêu Indicator | C16: Mã số Code | D16: Thuyết minh Note | E16: Ngày 31 tháng 03 năm 2021 As at 31 Mar 2021 | F16: Ngày 31 tháng 12 năm 2020 As at 31 Dec 2020
A17: I | B17: I. TÀI SẢN ASSETS | C17: I
A18: 1 | B18: 1.Tiền gửi ngân hàng và tương đương tiền Cash at bank and cash equivalent | C18: 110 | E18: 13601078113 | F18: 46497927740
A19: 1.1 | B19: 1.1. Tiền gửi ngân hàng Cash at bank | C19: 111 | E19: 13601078113 | F19: 46497927740
B20: Tiền gửi của nhà đầu tư cho hoạt động mua chứng chỉ quỹ Cash at bank for Fund's subscription | C20: 111.1 | E20: 0 | F20: 0
B21: Tiền phải trả cho Nhà đầu tư về mua lại Chứng chỉ quỹ Cash at bank for Fund's redemption | C21: 111.2 | E21: 125123389 | F21: 226700815
B22: Tiền gửi ngân hàng cho hoạt động của Quỹ Cash at bank for Fund's operation | C22: 111.3 | E22: 13475839515 | F22: 41972659771
B23: Tiền gửi ký quỹ cho hoạt động đầu tư chứng khoán phái sinh Margin account for trading derivatives | C23: 111.4 | E23: 115209 | F23: 4298567154
A24: 1.2 | B24: 1.2. Tiền gửi có kỳ hạn dưới ba (03) tháng Deposit with term less than three (03) months | C24: 112 | E24: 0 | F24: 0
A25: 2 | B25: 2. Các khoản đầu tư thuần Net Investments | C25: 120 | E25: 607539056450 | F25: 493298290900
A26: 2.1 | B26: 2.1. Các khoản đầu tư Investments | C26: 121 | E26: 607539056450 | F26: 493298290900
B27: Cổ phiếu niêm yết Listed Shares | C27: 121.1 | E27: 542545631850 | F27: 448298290900
B28: Cổ phiếu chưa niêm yết Unlisted Shares | C28: 121.2 | E28: 0 | F28: 0
B29: Trái phiếu niêm yết Listed Bonds | C29: 121.3 | E29: 0 | F29: 0
B30: Trái phiếu chưa niêm yết Unlisted Bonds | C30: 121.4 | E30: 19993424600 | F30: 0
B31: Chứng chỉ tiền gửi Certificates of Deposit | C31: 121.5 | E31: 45000000000 | F31: 45000000000
B32: Hợp đồng tiền gửi có kỳ hạn trên ba (03) tháng Deposits with term over three (03) months | C32: 121.6 | E32: 0 | F32: 0
B33: Quyền mua chứng khoán Investment - Rights | C33: 121.7 | E33: 0 | F33: 0
B34: Hợp đồng tương lai chỉ số Index future contracts | C34: 121.8 | E34: 0 | F34: 0
B35: Đầu tư khác Other Investments | C35: 121.9 | E35: 0 | F35: 0
B36: Hợp đồng mua lại đảo ngược Reverse repo contracts | C36: 121.10 | E36: 0 | F36: 0
A37: 2.2 | B37: 2.2. Dự phòng giảm giá tài sản nhận thế chấp Impairment of devaluation of pledged assets | C37: 122 | E37: 0 | F37: 0
A38: 3 | B38: 3. Các khoản phải thu Receivables | C38: 130 | E38: 1360117932 | F38: 2234411093
A39: 3.1 | B39: 3.1 Phải thu về bán các khoản đầu tư Receivables from investments sold but not yet settled | C39: 131 | E39: 5286600 | F39: 154710
B40: Trong đó: Phải thu khó đòi về bán các khoản đầu tư In which: Overdue receivables from selling investments | C40: 132 | E40: 0 | F40: 0
A41: 3.2 | B41: 3.2. Phải thu và dự thu cổ tức, tiền lãi các khoản đầu tư Dividend and interest receivables | C41: 133 | E41: 2221231332 | F41: 3100656383
A42: 3.2.1 | B42: 3.2.1. Phải thu cổ tức, tiền lãi đến ngày nhận Dividend and interest receivables on or after payment date | C42: 134 | E42: 866400000 | F42: 866400000
B43: Phải thu cổ tức Dividend receivables | C43: 134.1 | E43: 866400000 | F43: 866400000
B44: Phải thu trái tức Coupon receivables | C44: 134.2 | E44: 0 | F44: 0
B45: Phải thu lãi tiền gửi có kỳ hạn dưới 3 tháng Interest receivables from deposit with term less than three (03) months | C45: 134.3 | E45: 0 | F45: 0
B46: Phải thu lãi tiền gửi có kỳ hạn trên 3 tháng Interest receivables from deposit with term more than three (03) months | C46: 134.4 | E46: 0 | F46: 0
B47: Phải thu lãi chứng chỉ tiền gửi Interest receivables from Certificates of Deposit | C47: 134.5 | E47: 0 | F47: 0
B48: Trong đó: Phải thu khó đòi về cổ tức, tiền lãi đến ngày nhận nhưng chưa nhận được In which: Overdue receivables from dividend, interest income | C48: 135 | E48: 866400000 | F48: 866400000
A49: 3.2.2 | B49: 3.2.2.Dự thu cổ tức, tiền lãi chưa đến ngày nhận Dividend and interest receivables before payment date | C49: 136 | E49: 1354831332 | F49: 2234256383
B50: Dự thu cổ tức Dividend receivables | C50: 136.1 | E50: 116146400 | F50: 1743092000
B51: Dự thu lãi trái phiếu Interest accrual from bonds | C51: 136.2 | E51: 92054795 | F51: 0
B52: Dự thu lãi tiền gửi có kỳ hạn dưới 3 tháng Interest accrual from deposits with term less than three (03) months | C52: 136.3 | E52: 0 | F52: 0
B53: Dự thu lãi tiền gửi có kỳ hạn trên 3 tháng Interest accrual from deposit with term more than three (03) months | C53: 136.4 | E53: 0 | F53: 0
B54: Dự thu lãi chứng chỉ tiền gửi Interest accrual from Certificates of Deposit | C54: 136.5 | E54: 1146630137 | F54: 491164383
B55: Dự thu lãi hợp đồng mua lại đảo ngược Interest receivables from reverse repo contracts | C55: 136.6 | E55: 0 | F55: 0
A56: 3.3 | B56: 3.3. Các khoản phải thu khác Other receivables | C56: 137 | E56: 0 | F56: 0
B57: Phải thu cho khoản cổ phiếu hạn chế chờ mua Receivable from AP/Investors on securities on hold of buying | C57: 137.1 | E57: 0 | F57: 0
B58: Các tài sản khác Other assets | C58: 137.2 | E58: 0 | F58: 0
B59: Các khoản khác Others | C59: 137.3 | E59: 0 | F59: 0
A60: 3.4 | B60: 3.4. Dự phòng nợ phải thu khó đòi Provision for doubtful debt | C60: 138 | E60: -866400000 | F60: -866400000
B61: TỔNG TÀI SẢN TOTAL ASSETS | C61: 100 | E61: 622500252495 | F61: 542030629733
A62: II | B62: II. NỢ PHẢI TRẢ TOTAL LIABILITIES | C62: II
A63: 1 | B63: 1. Vay ngắn hạn Short-term loans | C63: 311 | E63: 0 | F63: 0
B64: Gốc hợp đồng repo Repo contracts - Principal | C64: 311.1 | E64: 0 | F64: 0
B65: Vay ngắn hạn Short-term loans | C65: 311.2 | E65: 0 | F65: 0
A66: 2 | B66: 2. Phải trả về mua các khoản đầu tư Payables for securities bought but not yet settled | C66: 312 | E66: 0 | F66: 0
A67: 3 | B67: 3. Phải trả phí cho các Đại lý phân phối, Công ty quản lý quỹ về mua bán Chứng chỉ quỹ Subscription and Redemption fee payable to distributors and fund management company | C67: 313 | E67: 191702692 | F67: 101250229
B68: Phải trả phí cho các Đại lý phân phối về mua bán Chứng chỉ quỹ Subscription and Redemption fee payable to distributors | C68: 313.1 | E68: 113282552 | F68: 81218453
B69: Phải trả phí cho Công ty quản lý quỹ về mua bán Chứng chỉ quỹ Subscription and Redemption fee payable to fund management company | C69: 313.2 | E69: 78420140 | F69: 20031776
A70: 4 | B70: 4. Thuế và các khoản phải nộp Nhà nước Tax payables and obligations to the State Budget | C70: 314 | E70: 16590610 | F70: 14880057
A71: 5 | B71: 5.Phải trả thu nhập cho Nhà đầu tư Profit distribution payables | C71: 315 | E71: 39925000 | F71: 39925000
A72: 6 | B72: 6. Chi phí phải trả Expense Accruals | C72: 316 | E72: 179080726 | F72: 147135520
B73: Phí giao dịch Transaction fee | C73: 316.1 | E73: 25135520 | F73: 25135520
B74: Phải trả phí môi giới Brokerage fee payables | C74: 316.1.1 | E74: 25135520 | F74: 25135520
B75: Phải trả phí giao dịch thanh toán bù trừ chứng khoán Clearing Settlement Fee payables | C75: 316.1.2 | E75: 0 | F75: 0
B76: Trích trước phí kiểm toán Accrued expense for audit fee | C76: 316.2 | E76: 132753425 | F76: 88000000
B77: Trích trước phí họp đại hội thường niên Accrued expense for Annual General meeting | C77: 316.3 | E77: 0 | F77: 0
B78: Trích trước phí báo cáo thường niên Accrued expense for Annual report | C78: 316.4 | E78: 0 | F78: 0
B79: Trích trước thù lao ban đại diện quỹ Accrued expense for Remuneration Payable to Fund's Board of Representatives | C79: 316.5 | E79: 21191781 | F79: 34000000
B80: Trích trước phí quản lý niêm yết hàng năm tại SGDCK Accrued expense for annual listing fee at HOSE | C80: 316.6 | E80: 0 | F80: 0
B81: Trích trước lãi vay ngắn hạn của hợp đồng vay và hợp đồng repo Accrued Interest Expense of short-term loan contracts and repo contracts | C81: 316.7 | E81: 0 | F81: 0
A82: 7 | B82: 7. Phải trả cho Nhà đầu tư về mua Chứng chỉ quỹ Subscription payables to investors | C82: 317 | E82: 996717820 | F82: 1048216969
B83: Phải trả cho nhà đầu tư chờ mua chứng chỉ quỹ Subscription Pending allotment | C83: 317.1 | E83: 996717820 | F83: 1048216969
B84: Phải trả nhà đầu tư trên tài sản giữ hộ Payables to investors for investment bought on behalf | C84: 317.2 | E84: 0 | F84: 0
A85: 8 | B85: 8. Phải trả cho Nhà đầu tư về mua lại Chứng chỉ quỹ Redemption payables to investors | C85: 318 | E85: 1717984810 | F85: 2159786082
A86: 9 | B86: 9. Phải trả dịch vụ quản lý Quỹ mở Fund management related service expense payable | C86: 319 | E86: 1099824378 | F86: 930719668
B87: Trích trước phải trả phí quản lý Accrued expense for Management fee | C87: 319.1 | E87: 1018736148 | F87: 850637160
B88: Trích trước phí lưu ký tài sản Quỹ mở Accrued expense for Custodian fee | C88: 319.2 | E88: 30421440 | F88: 31782292
B89: Phí dịch vụ lưu ký - bảo quản tài sản Custodian service - Safe Custody Fee | C89: 319.2.1 | E89: 26121440 | F89: 26182292
B90: Phí dịch vụ lưu ký - giao dịch chứng khoán Custodian service - Transaction fee | C90: 319.2.2 | E90: 4300000 | F90: 5600000
B91: Phí dịch vụ lưu ký cho chứng khoán cơ sở, phí quản lý vị thế và tài sản phái sinh trả cho VSD Custodian service - Depository fee, Position and Margin management fee paid to VSD | C91: 319.2.3 | E91: 0 | F91: 0
B92: Trích trước phí quản trị quỹ Accrued expense for Fund administration fee | C92: 319.3 | E92: 14366790 | F92: 12000216
B93: Trích trước phí giám sát Accrued expense for Supervising fee | C93: 319.4 | E93: 25300000 | F93: 25300000
B94: Trích trước phí dịch vụ đại lý chuyển nhượng Accrued expense for Tranfer agency fee | C94: 319.5 | E94: 11000000 | F94: 11000000
B95: Dự chi phí cung cấp dịch vụ tính giá trị tài sản ròng tham chiếu (iNAV) cho HOSE Accrued expense for payable to HOSE for iNAV calculation | C95: 319.6 | E95: 0 | F95: 0
B96: Dự chi phí cấp quyền sử dụng chỉ số cho HOSE Accrued expense for payable to HOSE for Index usage | C96: 319.7 | E96: 0 | F96: 0
A97: 10 | B97: 10. Phải trả, phải nộp khác Other payables | C97: 320 | E97: 193782966 | F97: 263732966
B98: Phải trả phí báo giá Price feed fee payable | C98: 320.1 | E98: 17300000 | F98: 87250000
B99: Trích trước phí công tác, họp của ban đại diện Accrued expense for Fund's Board of Representatives travelling, meeting | C99: 320.2 | E99: 0 | F99: 0
B100: Trích trước phí quản lý thường niên trả cho UBCKNN Accrued expense for Annual Fee paid to SSC | C100: 320.3 | E100: 0 | F100: 0
B101: Phí Ngân hàng S2B S2B Bank charge | C101: 320.4 | E101: 0 | F101: 0
B102: Phải trả khác Other payables | C102: 320.5 | E102: 176482966 | F102: 176482966
B103: TỔNG NỢ PHẢI TRẢ TOTAL LIABILITIES | C103: 300 | E103: 4435609002 | F103: 4705646491
...

Sheet BCLCGT_06262
A1: Mẫu số B05g - QM. Báo cáo lưu chuyển tiền tệ Template B05g - QM. Cash flow statement
A2: (Ban hành kèm theo Thông tư 198/2012/TT-BTC ngày 15 tháng 11 năm 2012 về chế độ kế toán áp dụng đối với quỹ mở) (Issued in association with Circular 198/2012/TT-BTC dated 15 Nov 2012 on the Accounting Policies for Open-Ended Fund)
A3: BÁO CÁO LƯU CHUYỂN TIỀN TỆ CASH FLOW STATEMENT
A4: =TONGQUAN!C2 -> Quý I năm 2021 / Quarter I 2021
A7: Tên Công ty quản lý quỹ: | B7: =TONGQUAN!D5 -> Công ty Cổ phần Quản lý Quỹ Đầu tư Dragon Capital Việt Nam
A8: Fund Management Company: | B8: =TONGQUAN!D6 -> Dragon Capital Vietfund Management Joint Stock Company
A9: Tên ngân hàng giám sát: | B9: =TONGQUAN!D7 -> Ngân hàng TNHH Một thành viên Standard Chartered (Việt Nam)
A10: Supervising bank: | B10: =TONGQUAN!D8 -> Standard Chartered Bank (Vietnam) Limited
A11: Tên Quỹ: | B11: =TONGQUAN!D9 -> Quỹ Đầu tư Chứng khoán Việt Nam
A12: Fund name: | B12: =TONGQUAN!D10 -> Vietnam Securities Investment Fund(VFMVF1)
A13: Ngày lập báo cáo: | B13: =TONGQUAN!D11 -> Ngày 06 tháng 04 năm 2021
A14: Reporting Date: | B14: =TONGQUAN!D12 -> 06 Apr 2021
A17: Chỉ tiêu Indicator | B17: Mã số Code | C17: Thuyết minh Note | D17: =BCKetQuaHoatDong_06028!D18 -> Quý I năm 2021 Quarter I 2021 | E17: =BCKetQuaHoatDong_06028!E18 -> Quý IV năm 2020 Quarter IV 2020
A18: I. Lưu chuyển tiền từ hoạt động đầu tư Cash flow from investing activities | B18: I
A19: 1. Lợi nhuận trước Thuế thu nhập doanh nghiệp Profit before income tax | B19: 01 | D19: 51099476926 | E19: 105496617758
A20: 2. Điều chỉnh cho các khoản tăng giá trị tài sản ròng từ các hoạt động đầu tư Adjustment for NAV increase from investing activities | B20: 02 | D20: -40145417656 | E20: -91650711613
A21: (- Lãi) hoặc (+ lỗ) chênh lệch tỷ giá hối đoái/ đánh giá lại các khoản đầu tư chưa thực hiện Unreliased (Gain) or Loss from FX valuation/Investment revaluation | B21: 03 | D21: -40120221081 | E21: -91783584564
A22: (+) Chi phí trích trước Increase of Accrued Expenses | B22: 04 | D22: -25196575 | E22: 132872951
A23: 3. Lợi nhuận từ hoạt động đầu tư trước thay đổi vốn lưu động Profit from investing activities before changes in working capital | B23: 05 | D23: 10954059270 | E23: 13845906145
A24: (-) Tăng, (+) giảm đầu tư (Increase), Decrease Investments | B24: 20 | D24: -74120544469 | E24: 13091328814
A25: (-) Tăng, (+) giảm phải thu bán chứng khoán đầu tư (Increase), Decrease in Receivables from investments sold but not yet settled | B25: 06 | D25: -5131890 | E25: -154710
A26: (-) Tăng, (+) giảm dự thu phải thu tiền lãi các khoản đầu tư (Increase), Decrease in Dividend and interest receivables | B26: 07 | D26: 879425051 | E26: 1076265850
A27: (-) Tăng, (+) giảm các khoản phải thu khác (Increase), Decrease in other receivables | B27: 08 | D27: 0 | E27: 0
A28: (+) Tăng, (-) giảm vay ngắn hạn Increase, (Decrease) in Short-term Loans | B28: 09 | D28: 0 | E28: 0
A29: (+) Tăng, (-) giảm phải trả cho người bán (Decrease), Increase in payables for securities purchased but not yet settled | B29: 10 | D29: 0 | E29: 0
A30: (+) Tăng, (-) giảm phải trả các Đại lý phân phối Chứng chỉ quỹ, Công ty Quản lý Quỹ (Decrease)/increase in subscription and redemption fee payable to distributors and Fund Management Company | B30: 11 | D30: 90452463 | E30: 25401432
... A38: Lưu chuyển tiền thuần từ hoạt động đầu tư (1+2+3) Net Cash flow from Investing activities | B38: 19 | D38: -62537032952 | E38: 30381356521
A39: II. Lưu chuyển tiền từ hoạt động tài chính Cash flow from financing activities | B39: II
A40: 1. Tiền thu từ phát hành Chứng chỉ quỹ mở Receipts from subscriptions | B40: 31 | D40: 80184192529 | E40: 34023099739
A41: 2. Tiền chi mua lại Chứng chỉ quỹ mở Payments for redemptions | B41: 32 | D41: -50544009204 | E41: -23948774545
A42: 3. Tiền vay gốc Principal of borrowings | B42: 33 | D42: 0 | E42: 0
A43: 4. Tiền chi trả nợ gốc vay Payment of Principal borrowings | B43: 34 | D43: 0 | E43: 0
A44: 5. Tiền chi trả cổ tức, tiền lãi cho nhà đầu tư Dividend, profit distribution paid to investors | B44: 35 | D44: 0 | E44: 0
A45: Lưu chuyển tiền thuần từ hoạt động tài chính (1-2+3-4-5) Net cash outflows from financing activities | B45: 30 | D45: 29640183325 | E45: 10074325194
A46: III. Tăng/giảm tiền thuần trong kỳ Net Increase/Decrease in cash and cash equivalent for the period | B46: 40 | D46: -32896849627 | E46: 40455681715
A47: IV. Tiền và các khoản tương đương tiền đầu kỳ Cash and cash equivalents at the beginning of period | B47: 50 | D47: 46497927740 | E47: 6042246025
A48: Tiền gửi ngân hàng đầu kỳ: Cash at bank of the beginning of period: | B48: 51 | D48: 46497927740 | E48: 6042246025
A49: -Tiền gửi ngân hàng và tương đương tiền cho hoạt động của Quỹ Cash at bank and cash equivalent for Fund's operation | B49: 52 | D49: 46271226925 | E49: 5913952195
A50: Tiền gửi không kỳ hạn Demand deposit | B50: 52.1 | D50: 41972659771 | E50: 5913837097
A51: Tiền gửi có kỳ hạn dưới ba (03) tháng Deposits with term under three (03) months | B51: 52.2 | D51: 0 | E51: 0
... A64: Khác Others | B64: 80 | D64: 0 | E64: 0
A67: Người lập: | C67: Người duyệt:
A78: _______________________________ | B78: _______________________________________ | E78: ______________________
A79: Mai Thùy Sâm | B79: Phạm Thanh Dũng | E79: Nguyễn Minh Đăng Khánh
A80: Kế toán Quỹ | B80: Kế toán Trưởng | E80: Giám đốc điều hành Nghiệp vụ hỗ trợ đầu tư

Sheet BCTaiSan_06027
A1: Phụ lục XXVI. Mẫu báo cáo về hoạt động của Quỹ Appendix XXVI. Report on Fund's Operation
A2: (Ban hành kèm theo Thông tư số 98/2020/TT-BTC ngày 16 tháng 11 năm 2020 của Bộ trưởng Bộ Tài Chính về hướng dẫn hoạt động và quản lý quỹ đầu tư chứng khoán) (Issued in association with Circular 98/2020/TT-BTC dated 16 November 2020 of the Minister of Finance on guiding the operation and management of the securities investment funds)
A3: BÁO CÁO VỀ HOẠT ĐỘNG ĐẦU TƯ REPORT ON INVESTMENT ACTIVITIES
A5: Tại ngày 31 tháng 03 năm 2021 / As at 31 Mar 2021
A7: Tên Công ty quản lý quỹ: | C7: Công ty Cổ phần Quản lý Quỹ Đầu tư Dragon Capital Việt Nam
A8: Fund Management Company: | C8: Dragon Capital Vietfund Management Joint Stock Company
A9: Tên ngân hàng giám sát: | C9: Ngân hàng TNHH Một thành viên Standard Chartered (Việt Nam)
A10: Supervising bank: | C10: Standard Chartered Bank (Vietnam) Limited
A11: Tên Quỹ: | C11: Quỹ Đầu tư Chứng khoán Việt Nam
A12: Fund name: | C12: Vietnam Securities Investment Fund(VFMVF1)
A13: Ngày lập báo cáo: | C13: Ngày 06 tháng 04 năm 2021
A14: Reporting Date: | C14: 06 Apr 2021
A16: A. | B16: BÁO CÁO CHUNG VỀ HOẠT ĐỘNG ĐẦU TƯ CỦA QUỸ/GENERAL INFORMATION ON FUND'S INVESTMENT ACTIVITIES
A17: I | B17: BÁO CÁO VỀ TÀI SẢN / ASSET REPORT
A18: STT No | B18: Nội dung Indicator | C18: Mã chỉ tiêu Code | D18: Ngày 31 tháng 03 năm 2021 As at 31 Mar 2021 | E18: Ngày 31 tháng 12 năm 2020 As at 31 Dec 2020 | F18: %/cùng kỳ năm trước %/against last year
A19: I | B19: TÀI SẢN ASSETS
A20: I.1 | B20: Tiền và các khoản tương đương tiền Cash and Cash Equivalents | D20: 13601078113 | E20: 46497927740 | F20: 0.27671132
B21: Tiền gửi ngân hàng Cash at bank | D21: 13601078113 | E21: 46497927740 | F21: 0.27671132
B22: Tiền gửi của nhà đầu tư cho hoạt động mua chứng chỉ quỹ Cash at bank for Fund's subscription | D22: 0 | E22: 0 | F22: 0
B23: Tiền phải trả cho Nhà đầu tư về mua lại chứng chỉ quỹ Cash at bank for Fund's redemption | D23: 125123389 | E23: 226700815 | F23: 1.0328178
B24: Tiền gửi ngân hàng cho hoạt động của Quỹ Cash at bank for Fund's operation | D24: 13475839515 | E24: 41972659771 | F24: 1.1854925
B25: Tiền gửi ký quỹ cho hoạt động đầu tư chứng khoán phái sinh Margin account for trading derivatives | D25: 115209 | E25: 4298567154 | F25: 3.0593377e-06
B26: Tiền, tương đương tiền Cash, cash equivalents | D26: 0 | E26: 0
A27: I.2 | B27: Các khoản đầu tư (kê chi tiết) Investments | D27: 607539056450 | E27: 493298290900 | F27: 1.1950766
B28: Cổ phiếu niêm yết Listed shares | D28: 542545631850 | E28: 448298290900 | F28: 1.3972894
B29: Cổ phiếu chưa niêm yết Unlisted shares | D29: 0 | E29: 0
B30: Trái phiếu Bonds | D30: 19993424600 | E30: 0 | F30: 0.33275844
B31: Chứng chỉ tiền gửi Certificates of Deposit | D31: 45000000000 | E31: 45000000000 | F31: 0.75
B32: Hợp đồng tiền gửi có kỳ hạn trên ba (03) tháng Deposits with term over three (03) months | D32: 0 | E32: 0
B33: Quyền mua chứng khoán Investment - Rights | D33: 0 | E33: 0
B34: Hợp đồng tương lai chỉ số Index future contracts | D34: 0 | E34: 0
B35: Đầu tư khác Other investments | D35: 0 | E35: 0
B36: Hợp đồng mua lại đảo ngược Reverse repo contracts | D36: 0 | E36: 0
A37: I.3 | B37: Thu từ cho thuê bất động sản đầu tư (không áp dụng) Receivables from rental of investment property (not applicable)
A38: I.4 | B38: Cổ tức, trái tức được nhận Dividend, Coupon receivables | D38: 1074601195 | E38: 2609492000 | F38: 0.30411377
B39: Phải thu cổ tức Dividend receivables | D39: 982546400 | E39: 2609492000 | F39: 0.81098296
B40: Phải thu trái tức Coupon receivables | D40: 92054795 | E40: 0 | F40: 0.039644615
A41: I.5 | B41: Lãi được nhận Interest receivables | D41: 1146630137 | E41: 491164383 | F41: 0.97053742
B42: Phải thu lãi tiền gửi Interest receivable from bank deposits | D42: 0 | E42: 0
B43: Phải thu lãi chứng chỉ tiền gửi Interest receivable from Certificates of Deposit | D43: 1146630137 | E43: 491164383 | F43: 0.97053742
B44: Phải thu lãi hợp đồng mua lại đảo ngược Interest receivable from reverse repo contracts | D44: 0 | E44: 0
A45: I.6 | B45: Tiền bán bất động sản chờ thu (không áp dụng) Real Estate Proceeds Receivables (not applicale)
A46: I.7 | B46: Tiền bán chứng khoán chờ thu Securities Trading Receivables | D46: 5286600 | E46: 154710
A47: I.8 | B47: Các khoản phải thu khác Other Receivables | D47: -866400000 | E47: -866400000 | F47: 1
B48: Dự phòng giảm giá tài sản nhận thế chấp Impairment of devaluation of pledged assets | D48: 0 | E48: 0
B49: Dự phòng nợ phải thu khó đòi Provision for doubtful debt | D49: -866400000 | E49: -866400000 | F49: 1
B50: Các khoản phải thu khác Other Receivables | D50: 0 | E50: 0
A51: I.9 | B51: Các tài sản khác Other Assets | D51: 0 | E51: 0
A52: I.10 | B52: TỔNG TÀI SẢN TOTAL ASSETS | D52: 622500252495 | E52: 542030629733 | F52: 1.1088958
A53: II | B53: NỢ LIABILITIES
A54: II.1 | B54: Tiền phải thanh toán mua bất động sản (không áp dụng) Real Estate Trading Payables (not applicable)
A55: II.2 | B55: Tiền phải thanh toán mua chứng khoán Securities Trading Payables | D55: 0 | E55: 0
A56: II.3 | B56: Các khoản phải trả khác Other Payables | D56: 4435609002 | E56: 4705646491 | F56: 1.7318616
B57: Phải trả nhà đầu tư Payables to investors | D57: 2714702630 | E57: 3208003051 | F57: 6.0863968
B58: Phải trả cho nhà đầu tư chờ mua chứng chỉ quỹ Subscription Pending allotment | D58: 996717820 | E58: 1048216969 | F58: 17.95888
B59: Phải trả nhà đầu tư trên tài sản giữ hộ Payables to investors for investment bought on behalf | D59: 0 | E59: 0
B60: Phải trả nhà đầu tư trên cổ tức đã thu Payables to investors for collected dividend | D60: 0 | E60: 0
B61: Phải trả cho Nhà đầu tư về mua lại chứng chỉ quỹ Redemption payable to investors | D61: 1717984810 | E61: 2159786082 | F61: 4.3991349
B62: Thuế và các khoản phải nộp Nhà nước Tax payables and obligations to the State Budget | D62: 16590610 | E62: 14880057 | F62: 1.4772678
B63: Phải trả phí phát hành, mua lại chứng chỉ quỹ cho Đại lý phân phối và Công ty quản lý quỹ Subscription and Redemption fee payable to distributors and Fund Management Company | D63: 191702692 | E63: 101250229 | F63: 0.42588883
B64: Phải trả thu nhập cho nhà đầu tư Income payable to investors | D64: 39925000 | E64: 39925000 | F64: 1
B65: Phải trả thù lao Ban đại diện quỹ Remuneration Payable to Fund's Board of Representatives | D65: 21191781 | E65: 34000000 | F65: 0.9983517
B66: Phải trả phí quản lý cho công ty quản lý quỹ Management fee payable | D66: 1018736148 | E66: 850637160 | F66: 0.90999219
B67: Phải trả phí quản trị quỹ Fund Administration fee payable | D67: 14366790 | E67: 12000216 | F67: 0.90999212
B68: Phải trả phí giám sát Supervisory service fee payable | D68: 25300000 | E68: 25300000 | F68: 0.9480887
B69: Phí giao dịch Transaction fee | D69: 25135520 | E69: 25135520 | F69: 1
B70: Phải trả phí môi giới Brokerage fee payable | D70: 25135520 | E70: 25135520 | F70: 1
B71: Phải trả phí phát hành thanh toán bù trừ chứng khoán Clearing Settlement fee payable | D71: 0 | E71: 0
B72: Trích trước phí lưu ký tài sản Quỹ mở Accrued expense for Custodian fee | D72: 30421440 | E72: 31782292 | F72: 0.61927258
B73: Phí lưu ký - bảo quản tài sản Custodian service - Safe Custody Fee | D73: 26121440 | E73: 26182292 | F73: 0.86711688
B74: Phí lưu ký - giao dịch chứng khoán Custodian service - Transaction fee | D74: 4300000 | E74: 5600000 | F74: 0.22631579
B75: Phí lưu ký cho chứng khoán cơ sở, phí quản lý vị thế và tài sản phái sinh trả cho VSD Custodian service - Depository fee, Position and Margin management fee paid to VSD | D75: 0 | E75: 0
B76: Phải trả phí kiểm toán Audit fee payable | D76: 132753425 | E76: 88000000 | F76: 0.99719334
B77: Phải trả phí họp đại hội thường niên General meeting expense payable | D77: 0 | E77: 0 | F77: 0
B78: Phải trả phí báo cáo thường niên Annual report fee payable | D78: 0 | E78: 0
B79: Phải trả phí dịch vụ đại lý chuyển nhượng Transfer Agency fee payable | D79: 11000000 | E79: 11000000 | F79: 1
B80: Dự chi phí tính giá trị tài sản ròng tham chiếu (iNAV) cho HOSE Service fee payable to HOSE for calculating iNAV | D80: 0 | E80: 0
B81: Dự chi phí cấp quyền sử dụng chỉ số cho HOSE Authorising index service fee payable to HOSE | D81: 0 | E81: 0
B82: Phải trả khác Other payables | D82: 193782966 | E82: 263732966 | F82: 1.0980265
B83: Phải trả phí báo giá Price feed fee payable | D83: 17300000 | E83: 87250000
B84: Trích trước phí công tác, họp của ban đại diện Accrued expense for Fund's Board of Representatives travelling, meeting | D84: 0 | E84: 0
B85: Trích trước phí quản lý thường niên trả UBCKNN Accrued expense for Annual Management Fee pay to SSC | D85: 0 | E85: 0
B86: Phải trả khác Other payables | D86: 176482966 | E86: 176482966 | F86: 1
B87: Vay ngắn hạn - hợp đồng repo Short-term loans - Repo contracts | D87: 0 | E87: 0
B88: Gốc hợp đồng repo Principal of repo contracts | D88: 0 | E88: 0
B89: Trích trước lãi vay ngắn hạn Accrued Interest Expense | D89: 0 | E89: 0
B90: Gốc vay ngắn hạn Principal of Short-term loans | D90: 0 | E90: 0
A91: II.4 | B91: TỔNG NỢ TOTAL LIABILITIES | D91: 4435609002 | E91: 4705646491 | F91: 1.7318616
B92: Tài sản ròng của Quỹ ( = I.10 - II.4) Net Asset Value ( = I.10 - II.4) | D92: 618064643493 | E92: 537324983242 | F92: 1.1060406
B93: Tổng số chứng chỉ quỹ đang lưu hành Total Outstanding Fund Certificates | D93: 11065093 | E93: 10529255 | F93: 0.58938263
B94: Giá trị tài sản ròng trên một chứng chỉ quỹ Net Asset Value per Fund Certificate | D94: 55857.15 | E94: 51031.62 | F94: 1.8766089
A96: Đại diện có thẩm quyền của Ngân hàng giám sát | E96: Đại diện có thẩm quyền của Công ty quản lý Quỹ
A97: Authorised Representative of Supervisory Bank | E97: Authorised Representative of Fund Management Company
A105: Ngân hàng TNHH MTV Standard Chartered (Việt Nam) | E105: Công ty Cổ phần Quản lý Quỹ Đầu tư Dragon Capital Việt Nam
A106: Vũ Hương Giang | E106: Nguyễn Minh Đăng Khánh
A107: Trưởng phòng Dịch vụ Quản trị và Giám sát Quỹ | E107: Giám đốc điều hành Nghiệp vụ hỗ trợ đầu tư

Sheet BCKetQuaHoatDong_06028
A1: Phụ lục XXVI. Mẫu báo cáo về hoạt động của Quỹ Appendix XXVI. Report on Fund's Operation
A2: (Ban hành kèm theo Thông tư số 98/2020/TT-BTC ngày 16 tháng 11 năm 2020 của Bộ trưởng Bộ Tài Chính về hướng dẫn hoạt động và quản lý quỹ đầu tư chứng khoán) (Issued in association with Circular 98/2020/TT-BTC dated 16 November 2020 of the Minister of Finance on guiding the operation and management of the securities investment funds)
A3: BÁO CÁO VỀ HOẠT ĐỘNG ĐẦU TƯ REPORT ON INVESTMENT ACTIVITIES
A5: Quý I năm 2021 / Quarter I 2021
A7: Tên Công ty quản lý quỹ: | C7: Công ty Cổ phần Quản lý Quỹ Đầu tư Dragon Capital Việt Nam
A8: Fund Management Company: | C8: Dragon Capital Vietfund Management Joint Stock Company
A9: Tên ngân hàng giám sát: | C9: Ngân hàng TNHH Một thành viên Standard Chartered (Việt Nam)
A10: Supervising bank: | C10: Standard Chartered Bank (Vietnam) Limited
A11: Tên Quỹ: | C11: Quỹ Đầu tư Chứng khoán Việt Nam
A12: Fund name: | C12: Vietnam Securities Investment Fund(VFMVF1)
A13: Ngày lập báo cáo: | C13: Ngày 06 tháng 04 năm 2021
A14: Reporting Date: | C14: 06 Apr 2021
A16: A. | B16: BÁO CÁO CHUNG VỀ HOẠT ĐỘNG ĐẦU TƯ CỦA QUỸ/GENERAL INFORMATION ON FUND'S INVESTMENT ACTIVITIES
A17: II | B17: BÁO CÁO KẾT QUẢ HOẠT ĐỘNG / PROFIT AND LOSS REPORT
A18: STT No | B18: Nội dung Indicator | C18: Mã chỉ tiêu Code | D18: Quý I năm 2021 Quarter I 2021 | E18: Quý IV năm 2020 Quarter IV 2020 | F18: Lũy kế từ đầu năm Accumulated from beginning of year
A19: I | B19: Thu nhập từ hoạt động đầu tư Income from Investment Activities | D19: 1705899512 | E19: 4597693474 | F19: 1705899512
A20: 1 | B20: Thu từ bất động sản cho thuê (không áp dụng) Income from rental property (not applicable)
A21: 2 | B21: Cổ tức, trái tức được nhận Dividend income, interest income from bonds | D21: 622900853 | E21: 3507772455 | F21: 622900853
B22: Cổ tức được nhận Dividends income | D22: 537421400 | E22: 3269073834 | F22: 537421400
B23: Trái tức được nhận Interest income from bonds | D23: 85479453 | E23: 238698621 | F23: 85479453
A24: 3 | B24: Lãi được nhận Interest income | D24: 1082998659 | E24: 1089921019 | F24: 1082998659
B25: Lãi tiền gửi ngân hàng Interest income from bank deposits | D25: 15943864 | E25: 6208691 | F25: 15943864
B26: Lãi chứng chỉ tiền gửi Interest income from Certificates of Deposit | D26: 1067054795 | E26: 1083712328 | F26: 1067054795
B27: Lãi hợp đồng mua lại đảo ngược Interest income from reverse repo contracts | D27: 0 | E27: 0 | F27: 0
A28: 4 | B28: Các khoản thu nhập khác Other incomes | D28: 0 | E28: 0 | F28: 0
B29: Thu nhập khác về đầu tư Other investment incomes | D29: 0 | E29: 0 | F29: 0
B30: Thu nhập khác Other incomes | D30: 0 | E30: 0 | F30: 0
B31: Chi phí dự phòng nợ phải thu khó đòi về cổ tức, tiền lãi và xử lý tổn thất nợ phải thu khó đòi về cổ tức, tiền lãi Provision expense for bad debts from dividends, interest income and written off bad debts from dividends, interest income | D31: 0 | E31: 0 | F31: 0
A32: II | B32: Chi phí Expenses | D32: 3406874403 | E32: 2945744176 | F32: 3406874403
A33: 1 | B33: Chi phí quản lý trả cho Công ty quản lý quỹ Management Fee paid to Fund Management Company | D33: 2795129033 | E33: 2304253594 | F33: 2795129033
A34: 2 | B34: Chi phí lưu ký, giám sát trả cho Ngân hàng Giám sát/VSD Custody fee, Supervising fee paid to Supervising Bank/VSD | D34: 175762183 | E34: 168146038 | F34: 175762183
B35: Chi phí dịch vụ lưu ký - bảo quản tài sản Custodian service - Safe Custody Fee | D35: 80779680 | E35: 71150162 | F35: 80779680
B36: Chi phí dịch vụ lưu ký - giao dịch chứng khoán Custodian service - Transaction fee | D36: 9900000 | E36: 11100000 | F36: 9900000
B37: Chi phí dịch vụ lưu ký cho chứng khoán cơ sở, phí quản lý vị thế và tài sản phái sinh trả cho VSD Custodian service - Depository fee, Position and Margin management fee paid to VSD | D37: 9182503 | E37: 9995876 | F37: 9182503
B38: Chi phí giám sát Supervisory fee | D38: 75900000 | E38: 75900000 | F38: 75900000
A39: 3 | B39: Chi phí quản trị quỹ và các chi phí khác mà công ty quản lý quỹ trả cho tổ chức cung cấp dịch vụ có liên quan Fund Administration Fee, and other fees paid to relevant Fund's service providers | D39: 72418485 | E39: 65499930 | F39: 72418485
B40: Chi phí quản trị Quỹ Fund Administration Fee | D40: 39418485 | E40: 32499930 | F40: 39418485
B41: Chi phí dịch vụ Đại lý Chuyển nhượng Transfer Agency Fee | D41: 33000000 | E41: 33000000 | F41: 33000000
A42: 4 | B42: Chi phí dịch vụ quản lý bất động sản (không áp dụng) Real Estate Management Service fee (not applicable)
A43: 5 | B43: Chi phí dịch vụ định giá bất động sản (không áp dụng) Real estate valuation service fees (not applicable)
A44: 6 | B44: Chi phí kiểm toán trả cho tổ chức kiểm toán Audit fee | D44: 44753425 | E44: 45622951 | F44: 44753425
A45: 7 | B45: Chi phí dịch vụ tư vấn pháp lý, dịch vụ báo giá và các dịch vụ hợp lý khác, thù lao trả cho ban đại diện quỹ Legal consultancy expenses, price feed fee, other valid expenses, remuneration paid to Fund's Board of Representatives | D45: 72491781 | E45: 175123224 | F45: 72491781
B46: Thù lao Ban đại diện Quỹ Remuneration of Fund's Board of Representatives | D46: 55191781 | E46: 55273224 | F46: 55191781
B47: Chi phí cung cấp báo giá chứng khoán Price feed fee | D47: 17300000 | E47: 119850000 | F47: 17300000
B48: Chi phí dịch vụ tư vấn pháp lý Legal consultancy expenses | D48: 0 | E48: 0 | F48: 0
A49: 8 | B49: Chi phí dự thảo, in ấn, gửi bản cáo bạch, bản cáo bạch tóm tắt, báo cáo tài chính, xác nhận giao dịch, sao kê tài khoản và các tài liệu khác cho nhà đầu tư; chi phí công bố thông tin của quỹ; chi phí tổ chức họp đại hội nhà đầu tư, ban đại diện quỹ Fee for drafting, printing, distribution of prospectus, summarised prospectus, financial statements, transaction confirmations, account statements and other documents to investors; information disclosure fee; fee for organising annual general meeting, board of representatives meeting | D49: 0 | E49: 0 | F49: 0
B50: Chi phí họp Đại hội Quỹ Meeting expenses | D50: 0 | E50: 0 | F50: 0
B51: Chi phí báo cáo thường niên Annual report expenses | D51: 0 | E51: 0 | F51: 0
B52: Chi phí họp, công tác của Ban đại diện Fund's Board of Representatives meeting, travelling expenses | D52: 0 | E52: 0 | F52: 0
B53: Chi phí công bố thông tin của Quỹ Expenses of information disclosure of the Fund | D53: 0 | E53: 0 | F53: 0
B54: Chi phí thiết kế, in ấn, gửi thư… Designing, printing, posting... expenses | D54: 0 | E54: 0 | F54: 0
A55: 9 | B55: Chi phí liên quan đến thực hiện các giao dịch tài sản của Quỹ Expenses related to execution of Fund’s asset transactions | D55: 242215137 | E55: 178009810 | F55: 242215137
B56: Chi phí môi giới Brokerage fee | D56: 241561759 | E56: 176906958 | F56: 241561759
B57: Chi phí thanh toán bù trừ Clearing settlement fee | D57: 653378 | E57: 1102852 | F57: 653378
B58: Chi phí khác Other Expenses | D58: 0 | E58: 0 | F58: 0
A59: 10 | B59: Các loại chi phí khác Other expenses | D59: 4104359 | E59: 9088629 | F59: 4104359
B60: Chi phí thiết lập Quỹ Set up Expenses | D60: 0 | E60: 0 | F60: 0
B61: Phí niêm yết, đăng ký chứng khoán Listing, registration fees | D61: 0 | E61: 0 | F61: 0
B62: Phí quản lý thường niên trả cho UBCKNN Annual management fee paid to SSC | D62: 0 | E62: 6739726 | F62: 0
B63: Phí ngân hàng Bank charges | D63: 4104359 | E63: 2348903 | F63: 4104359
B64: Chi phí lãi vay Borrowing expense | D64: 0 | E64: 0 | F64: 0
B65: Chi phí khác Other Expenses | D65: 0 | E65: 0 | F65: 0
B66: Phí thực hiện quyền trả cho VSD Fee paid to VSD for getting the list of investors | D66: 0 | E66: 0 | F66: 0
A67: III | B67: Thu nhập ròng từ hoạt động đầu tư (= I - II) Net Income from Investment Activities (= I - II) | D67: -1700974891 | E67: 1651949298 | F67: -1700974891
A68: IV | B68: Lãi / (lỗ) từ hoạt động đầu tư Gain / (Loss) from Investment Activities | D68: 52800451817 | E68: 103844668460 | F68: 52800451817
A69: 1 | B69: Lãi (lỗ) thực tế phát sinh từ hoạt động đầu tư hoặc chuyển nhượng bất động sản Realised Gain / (Loss) from disposal of investment or real estate transfer | D69: 12680230736 | E69: 12061083896 | F69: 12680230736
A70: 2 | B70: Thay đổi về giá trị của các khoản đầu tư trong kỳ Unrealised Gain / (Loss) due to market price | D70: 40120221081 | E70: 91783584564 | F70: 40120221081
A71: V | B71: Thay đổi của giá trị tài sản ròng của Quỹ do các hoạt động đầu tư trong kỳ (III + IV) Change of Net Asset Value of the Fund due to investment activities during the period (= III + IV) | D71: 51099476926 | E71: 105496617758 | F71: 51099476926
A72: VI | B72: Giá trị tài sản ròng đầu kỳ Net Asset Value at the beginning of period | D72: 537324983242 | E72: 421754040290 | F72: 537324983242
A73: VII | B73: Thay đổi giá trị tài sản ròng của Quỹ trong kỳ Change of Net Asset Value of the Fund during the period | D73: 80739660251 | E73: 115570942952 | F73: 80739660251
B74: Trong đó: Of which:
A75: 1 | B75: Thay đổi giá trị tài sản ròng của Quỹ do các hoạt động đầu tư của Quỹ trong kỳ Change of Net Asset Value due to investment activities during the period | D75: 51099476926 | E75: 105496617758 | F75: 51099476926
A76: 2 | B76: Thay đổi giá trị tài sản ròng của Quỹ do việc chi trả lợi tức/ cổ tức của Quỹ cho các nhà đầu tư trong kỳ Change of Net Asset Value due to dividends payment to investors during the period | D76: 0 | E76: 0 | F76: 0
A77: 3 | B77: Thay đổi giá trị tài sản ròng do phát hành thêm/mua lại chứng chỉ quỹ Change of Net Asset Value due to subscription/redemption during the period | D77: 29640183325 | E77: 10074325194 | F77: 29640183325
B78: Thay đổi giá trị tài sản ròng do phát hành thêm Chứng chỉ Quỹ Change of Net Asset Value due to subscription during the period | D78: 80184192529 | E78: 34023099739 | F78: 80184192529
B79: Thay đổi giá trị tài sản ròng do mua lại Chứng chỉ Quỹ Change of Net Asset Value due to redemption during the period | D79: -50544009204 | E79: -23948774545 | F79: -50544009204
A80: VIII | B80: Giá trị tài sản ròng cuối kỳ Net Asset Value at the end of period | D80: 618064643493 | E80: 537324983242 | F80: 618064643493
A81: IX | B81: Lợi nhuận bình quân năm (chỉ áp dụng đối với báo cáo năm) Average annual profit (only applicable to annual report) | D81: 0 | E81: 0 | F81: 0
B82: Tỷ suất lợi nhuận bình quân năm (chỉ áp dụng đối với báo cáo năm) Average annual rate of return (only applicable to annual report) | D82: 0 | E82: 0 | F82: 0
A85: Đại diện có thẩm quyền của Ngân hàng giám sát | D85: Đại diện có thẩm quyền của Công ty quản lý Quỹ
A86: Authorised Representative of Supervisory Bank | D86: Authorised Representative of Fund Management Company
A94: Ngân hàng TNHH MTV Standard Chartered (Việt Nam) | D94: Công ty Cổ phần Quản lý Quỹ Đầu tư Dragon Capital Việt Nam
A95: Vũ Hương Giang | D95: Nguyễn Minh Đăng Khánh
A96: Trưởng phòng Dịch vụ Quản trị và Giám sát Quỹ | D96: Giám đốc điều hành Nghiệp vụ hỗ trợ đầu tư

Sheet BCDanhMucDauTu_06029
A1: Phụ lục XXVI. Mẫu báo cáo về hoạt động của Quỹ Appendix XXVI. Report on Fund's Operation
A2: (Ban hành kèm theo Thông tư số 98/2020/TT-BTC ngày 16 tháng 11 năm 2020 của Bộ trưởng Bộ Tài Chính về hướng dẫn hoạt động và quản lý quỹ đầu tư chứng khoán) (Issued in association with Circular 98/2020/TT-BTC dated 16 November 2020 of the Minister of Finance on guiding the operation and management of the securities investment funds)
A3: BÁO CÁO VỀ HOẠT ĐỘNG ĐẦU TƯ REPORT ON INVESTMENT ACTIVITIES
A5: Tại ngày 31 tháng 03 năm 2021 / As at 31 Mar 2021
A7: Tên Công ty quản lý quỹ: | C7: Công ty Cổ phần Quản lý Quỹ Đầu tư Dragon Capital Việt Nam
A8: Fund Management Company: | C8: Dragon Capital Vietfund Management Joint Stock Company
A9: Tên ngân hàng giám sát: | C9: Ngân hàng TNHH Một thành viên Standard Chartered (Việt Nam)
A10: Supervising bank: | C10: Standard Chartered Bank (Vietnam) Limited
A11: Tên Quỹ: | C11: Quỹ Đầu tư Chứng khoán Việt Nam
A12: Fund name: | C12: Vietnam Securities Investment Fund(VFMVF1)
A13: Ngày lập báo cáo: | C13: Ngày 06 tháng 04 năm 2021
A14: Reporting Date: | C14: 06 Apr 2021
A16: A. | B16: BÁO CÁO CHUNG VỀ HOẠT ĐỘNG ĐẦU TƯ CỦA QUỸ/GENERAL INFORMATION ON FUND'S INVESTMENT ACTIVITIES
A17: III | B17: BÁO CÁO DANH MỤC ĐẦU TƯ / INVESTMENT PORTFOLIO REPORT
A18: STT No. | B18: Loại Category | C18: Mã chỉ tiêu Code | D18: Số Lượng Quantity | E18: Giá thị trường hoặc giá trị hợp lý tại ngày báo cáo Market price | F18: Tổng giá trị (Đồng) Value (VND) | G18: Tỷ lệ % Tổng giá trị tài sản của Quỹ % of total asset
A19: I | B19: BẤT ĐỘNG SẢN ĐẦU TƯ (KHÔNG ÁP DỤNG) REAL ESTATE INVESTMENT (NOT APPLICABLE)
A20: II | B20: CỔ PHIẾU NIÊM YẾT, ĐĂNG KÝ GIAO DỊCH, CHỨNG CHỈ QUỸ NIÊM YẾT LISTED SHARES, TRADING REGISTRATION SHARED, LISTED FUND CERTIFICATES
A21: 1 | B21: ACB | D21: 375314 | E21: 33300 | F21: 12497956200 | G21: 0.02007703
A22: 2 | B22: ASM | D22: 413100 | E22: 15150 | F22: 6258465000 | G22: 0.010053755
A23: 3 | B23: BID | D23: 191820 | E23: 42950 | F23: 8238669000 | G23: 0.013234804
A24: 4 | B24: CTG | D24: 266290 | E24: 40150 | F24: 10691543500 | G24: 0.017175163
A25: 5 | B25: CTR | D25: 86500 | E25: 93800 | F25: 8113700000 | G25: 0.013034051
A26: 6 | B26: DHC | D26: 171410 | E26: 83500 | F26: 14312735000 | G26: 0.022992336
A27: 7 | B27: DPM | D27: 300000 | E27: 19850 | F27: 5955000000 | G27: 0.0095662612
A28: 8 | B28: DRC | D28: 164810 | E28: 28800 | F28: 4746528000 | G28: 0.0076249415
A29: 9 | B29: DXG | D29: 246993 | E29: 24000 | F29: 5927832000 | G29: 0.0095226178
A30: 10 | B30: FPT | D30: 520305 | E30: 77700 | F30: 40427698500 | G30: 0.064944068
A31: 11 | B31: GAS | D31: 62360 | E31: 89700 | F31: 5593692000 | G31: 0.008985847
A32: 12 | B32: GIL | D32: 92300 | E32: 71800 | F32: 6627140000 | G32: 0.010646004
... A60: 40 | B60: VRE | D60: 164070 | E60: 32700 | F60: 5365089000 | G60: 0.0086186134
B61: TỔNG TOTAL | F61: 542545631850 | G61: 0.87155889
A62: III | B62: CỔ PHIẾU CHƯA NIÊM YẾT, ĐĂNG KÝ GIAO DỊCH, CHỨNG CHỈ QUỸ KHÔNG NIÊM YẾT UNLISTED SHARES, TRADING REGISTRATION, UNLISTED FUND CERTIFICATES
B63: TỔNG TOTAL | F63: 0 | G63: 0
B64: TỔNG CÁC LOẠI CỔ PHIẾU TOTAL SHARES | F64: 542545631850 | G64: 0.87155889
A65: IV | B65: TRÁI PHIẾU BONDS
A66: 1 | B66: Trái phiếu niêm yết Listed bonds | F66: 0 | G66: 0
A67: 2 | B67: Trái phiếu chưa niêm yết Unlisted Bonds | F67: 19993424600 | G67: 0.032117938
A68: 2.1 | B68: DAT XANH GROUP JSC 12% 18 Mar 2023 | D68: 200 | E68: 99967123 | F68: 19993424600 | G68: 0.032117938
B69: TỔNG TOTAL | F69: 19993424600 | G69: 0.032117938
A70: V | B70: CÁC LOẠI CHỨNG KHOÁN KHÁC OTHER SECURITIES
A71: 1 | B71: Quyền mua chứng khoán Investment - Rights | F71: 0 | G71: 0
A72: 2 | B72: Chi tiết loại hợp đồng phái sinh(*) Index future contracts | F72: 0 | G72: 0
B73: TỔNG TOTAL | F73: 0 | G73: 0
B74: TỔNG CÁC LOẠI CHỨNG KHOÁN TOTAL TYPES OF SECURITIES | F74: 562539056450 | G74: 0.90367683
A75: VI | B75: CÁC TÀI SẢN KHÁC OTHER ASSETS
A76: 1 | B76: Cổ tức được nhận Dividend receivables | F76: 982546400 | G76: 0.0015783872
A77: 2 | B77: Lãi trái phiếu được nhận Coupon receivables | F77: 92054795 | G77: 0.00014787913
A78: 3 | B78: Lãi tiền gửi và chứng chỉ tiền gửi được nhận Interest receivables from bank deposits and certificates of deposit | F78: 1146630137 | G78: 0.0018419754
A79: 4 | B79: Tiền bán chứng khoán chờ thu Outstanding Settlement of sales transactions | F79: 5286600 | G79: 8.4925267e-06
A80: 5 | B80: Phải thu cho khoản cổ phiếu hạn chế chờ mua Receivable from AP/Investors on securities on hold of buying | F80: 0 | G80: 0
A81: 6 | B81: Phải thu khác Other receivables | F81: 0 | G81: 0
A82: 7 | B82: Tài sản khác Other assets | F82: -866400000 | G82: -0.0013918067
B83: TỔNG TOTAL | F83: 1360117932 | G83: 0.0021849275
A84: VII | B84: TIỀN CASH
A85: 1 | B85: Tiền, tương đương tiền Cash, Cash Equivalents | F85: 13601078113 | G85: 0.021849113
A86: 1.1 | B86: Tiền gửi ngân hàng Cash at Bank | F86: 13601078113 | G86: 0.021849113
A87: 1.2 | B87: Các khoản tương đương tiền Cash Equivalents | F87: 0 | G87: 0
A88: 2 | B88: Tiền gửi ngân hàng có kỳ hạn trên 3 tháng Deposits with term over three (03) months | F88: 0 | G88: 0
A89: 3 | B89: Chứng chỉ tiền gửi Certificates of deposit | F89: 45000000000 | G89: 0.072289127
A90: 4 | B90: Công cụ chuyển nhượng… Transferable instruments… | F90: 0 | G90: 0
B91: TỔNG TOTAL | F91: 58601078113 | G91: 0.09413824
A92: VII | B92: Tổng giá trị danh mục Total value of portfolio | F92: 622500252495 | G92: 1
A94: Đại diện có thẩm quyền của Ngân hàng giám sát | E94: Đại diện có thẩm quyền của Công ty quản lý Quỹ
A95: Authorised Representative of Supervisory Bank | E95: Authorised Representative of Fund Management Company
A104: Ngân hàng TNHH MTV Standard Chartered (Việt Nam) | E104: Công ty Cổ phần Quản lý Quỹ Đầu tư Dragon Capital Việt Nam
A105: Vũ Hương Giang | E105: Nguyễn Minh Đăng Khánh
A106: Trưởng phòng Dịch vụ Quản trị và Giám sát Quỹ | E106: Giám đốc điều hành Nghiệp vụ hỗ trợ đầu tư

Sheet Khac_06030
A1: Phụ lục XXVI. Mẫu báo cáo về hoạt động của Quỹ Appendix XXVI. Report on Fund's Operation
A2: (Ban hành kèm theo Thông tư số 98/2020/TT-BTC ngày 16 tháng 11 năm 2020 của Bộ trưởng Bộ Tài Chính về hướng dẫn hoạt động và quản lý quỹ đầu tư chứng khoán) (Issued in association with Circular 98/2020/TT-BTC dated 16 November 2020 of the Minister of Finance on guiding the operation and management of the securities investment funds)
A3: BÁO CÁO VỀ HOẠT ĐỘNG ĐẦU TƯ REPORT ON INVESTMENT ACTIVITIES
A5: =TONGQUAN!C2 -> Quý I năm 2021 / Quarter I 2021
A7: Tên Công ty quản lý quỹ: | C7: =TONGQUAN!D5 -> Công ty Cổ phần Quản lý Quỹ Đầu tư Dragon Capital Việt Nam
A8: Fund Management Company: | C8: =TONGQUAN!D6 -> Dragon Capital Vietfund Management Joint Stock Company
A9: Tên ngân hàng giám sát: | C9: =TONGQUAN!D7 -> Ngân hàng TNHH Một thành viên Standard Chartered (Việt Nam)
A10: Supervising bank: | C10: =TONGQUAN!D8 -> Standard Chartered Bank (Vietnam) Limited
A11: Tên Quỹ: | C11: =TONGQUAN!D9 -> Quỹ Đầu tư Chứng khoán Việt Nam
A12: Fund name: | C12: =TONGQUAN!D10 -> Vietnam Securities Investment Fund(VFMVF1)
A13: Ngày lập báo cáo: | C13: =TONGQUAN!D11 -> Ngày 06 tháng 04 năm 2021
A14: Reporting Date: | C14: =TONGQUAN!D12 -> 06 Apr 2021
A16: A. | B16: BÁO CÁO CHUNG VỀ HOẠT ĐỘNG ĐẦU TƯ CỦA QUỸ/GENERAL INFORMATION ON FUND'S INVESTMENT ACTIVITIES
A17: V | B17: MỘT SỐ CHỈ TIÊU KHÁC / OTHER INDICATORS
A18: STT No | B18: Chỉ tiêu Indicators | C18: Mã chỉ tiêu Code | D18: =BCKetQuaHoatDong_06028!D18 -> Quý I năm 2021 Quarter I 2021 | E18: =BCKetQuaHoatDong_06028!E18 -> Quý IV năm 2020 Quarter IV 2020
A19: I | B19: CÁC CHỈ TIÊU VỀ HIỆU QUẢ HOẠT ĐỘNG INVESTMENT PERFORMANCE INDICATORS
A20: 1 | B20: Tỷ lệ giá dịch vụ quản lý quỹ trả cho công ty quản lý quỹ/Giá trị tài sản ròng trung bình trong kỳ (%) Management fee paid to the fund management company/Average NAV (%) | D20: 0.019235165 | E20: 0.019606145
A21: 2 | B21: Tỷ lệ giá dịch vụ lưu ký, giám sát trả cho Ngân hàng Giám sát/Giá trị tài sản ròng trung bình trong kỳ (%) Custody and supervising fees paid to the Supervisory Bank/Average NAV (%) | D21: 0.0011463469 | E21: 0.0013456484
A22: 3 | B22: Tỷ lệ chi phí dịch vụ quản trị quỹ, và các chi phí khác mà công ty quản lý quỹ trả cho tổ chức cung cấp dịch vụ có liên quan/Giá trị tài sản ròng của quỹ trung bình trong kỳ (%) Fund admin fee, and other fees paid to relating services providers by the fund management company/Average NAV (%) | D22: 0.00056155134 | E22: 0.00064236929
A23: 4 | B23: Chi phí kiểm toán trả cho tổ chức kiểm toán (nếu phát sinh)/Giá trị tài sản ròng trung bình trong kỳ (%) Auditing fee paid to auditing organizations (if any)/Average NAV (%) | D23: 0.00030797845 | E23: 0.00038819087
A24: 5 | B24: Chi phí trả cho tổ chức quản lý bất động sản/ Giá trị tài sản ròng trung bình trong kỳ (%) (không áp dụng) Fee paid to Real Estate management organisation/ Average NAV (%) (not applicable)
A25: 6 | B25: Chi phí trả cho doanh nghiệp thẩm định giá bất động sản/Giá trị tài sản ròng trung bình trong kỳ (%) (không áp dụng) Fee paid to Real Estate valuation service provider/ Average NAV (%) (not applicable)
A26: 7 | B26: Chi phí dịch vụ tư vấn pháp lý, dịch vụ báo giá và các dịch vụ hợp lý khác, thù lao trả cho ban đại diện quỹ/Giá trị tài sản ròng trung bình trong kỳ (%) Legal consultancy, price quotation and other appropriate service fees; remunerations paid to the Board of Representatives/Average NAV (%) | D26: 0.00049886475 | E26: 0.0014900666
A27: 8 | B27: Tỷ lệ chi phí /Giá trị tài sản ròng trung bình trong kỳ (%) Expense/Average NAV (%) | D27: 0.023444997 | E27: 0.02506438
A28: 9 | B28: Tốc độ vòng quay danh mục trong kỳ (%) = (Tổng giá trị mua vào + tổng giá trị bán ra) x 100%/ (2 x Giá trị tài sản ròng trung bình trong kỳ) Portfolio turnover rate (%) = (Total value of purchase transactions + total value of sales transactions) x 100%/ (2 x Average NAV) (**) | D28: 0.80284592 | E28: 0.62106722
A29: 10 | B29: Tỷ lệ thu nhập (tính cả thu nhập từ lãi, cổ tức, trái tức, chênh lệch giá)/ Giá trị tài sản ròng (không áp dụng) Income (including interest income, dividend, coupon income and unrealised gain)/ Average NAV (%) (not applicable)
A30: II | B30: CÁC CHỈ TIÊU KHÁC OTHER INDICATORS
A31: 1 | B31: Quy mô quỹ đầu kỳ (tính theo mệnh giá chứng chỉ quỹ) Fund scale at the beginning of the period (based on par value of fund certificate) | D31: 105292552100 | E31: 103117010400
B32: Tổng giá trị chứng chỉ quỹ đang lưu hành đầu kỳ Total value of outstanding Fund Certificate at the beginning of period | D32: 105292552100 | E32: 103117010400
B33: Tổng số lượng chứng chỉ quỹ đang lưu hành đầu kỳ Total number of outstanding Fund Certificate at the beginning of period | D33: 10529255 | E33: 10311701
A34: 2 | B34: Thay đổi quy mô quỹ trong kỳ (tính theo mệnh giá chứng chỉ quỹ) Change of Fund scale during the period (based on par value of fund certificate) | D34: 5358375000 | E34: 2175541700
B35: Thay đổi số lượng chứng chỉ quỹ trong kỳ Change of Number of Fund Certificates during the period | D35: 535837.5 | E35: 217554.17
B36: Thay đổi giá trị vốn trong kỳ (theo mệnh giá) Change in capital amount during the period (based on par value) | D36: 5358375000 | E36: 2175541700
B37: Số lượng chứng chỉ quỹ phát hành thêm trong kỳ Number of Fund Certificates subscribed during the period | D37: 1470523.2 | E37: 728312.03
B38: Giá trị vốn huy động thêm trong kỳ (theo mệnh giá) Net subscription amount during the period (based on par value) | D38: 14705232400 | E38: 7283120300
B39: Số lượng chứng chỉ quỹ mua lại trong kỳ (theo mệnh giá) Number of Fund Certificates redeemed during the period | D39: -934685.74 | E39: -510757.86
B40: Giá trị vốn phải thanh toán trong kỳ khi đáp ứng lệnh của nhà đầu tư (theo mệnh giá) Net redemption amount during the period (based on par value) | D40: -9346857400 | E40: -5107578600
A41: 3 | B41: Quy mô quỹ cuối kỳ (tính theo mệnh giá chứng chỉ quỹ) Fund scale at the end of the period (based on par value) | D41: 110650927100 | E41: 105292552100
B42: Tổng giá trị thị trường của quỹ đang lưu hành cuối kỳ (theo mệnh giá) Total value of outstanding Fund Certificate at the end of the period (based on par value) | D42: 110650927100 | E42: 105292552100
B43: Tổng số lượng chứng chỉ quỹ đang lưu hành cuối kỳ Total number of outstanding Fund Certificate at the end of the period | D43: 11065093 | E43: 10529255
A44: 4 | B44: Tỷ lệ nắm giữ chứng chỉ quỹ của công ty quản lý quỹ và người có liên quan cuối kỳ Fund Management Company and related parties' ownership ratio at the end of the period | D44: 0.0010020738 | E44: 0.0026836694
A45: 5 | B45: Tỷ lệ nắm giữ chứng chỉ quỹ của 10 nhà đầu tư lớn nhất cuối kỳ Top 10 investors' ownership ratio at the end of the period | D45: 0.5429 | E45: 0.5365
A46: 6 | B46: Tỷ lệ nắm giữ chứng chỉ quỹ của nhà đầu tư nước ngoài cuối kỳ Foreign investors' ownership ratio at the end of the period | D46: 0.3649 | E46: 0.3835
A47: 7 | B47: Giá trị tài sản ròng trên một đơn vị quỹ cuối kỳ Net asset value per Fund Certificate at the end of period | D47: 55857.15 | E47: 51031.62
A48: 8 | B48: Giá trị thị trường trên một chứng chỉ quỹ/cổ phiếu cuối kỳ (không áp dụng) Market price per fund certificates at the end of period (not applicable)
A49: 9 | B49: Số nhà đầu tư tham gia vào quỹ, kể cả giao dịch ký danh Number of investors of the Fund at the end of the period | D49: 3295 | E49: 3042
A50: Ghi chú / Notes:
A51: Các chỉ tiêu từ 1 đến 10 của "Chỉ tiêu về hiệu quả hoạt động" đã được điều chỉnh để phản ánh số liệu trên cơ sở hoạt động tròn năm bằng cách nhân các chỉ tiêu này với 12 (đối với báo cáo tháng), 4 (đối với báo cáo quý), 2 (đối với báo cáo bán niên), 1 (đối với báo cáo năm). All Indicator starting from number 1 to 10 of "Investment performance indicators" are annualized to reflect a rate that is based on a full year operation by multiplying these indicators with 12 (monthly report) or 4 (quarterly report) or 2 (semi-annual report) or 1 (annual report).
A52: (**) Không tính đến giá trị cam kết của các hợp đồng tương lai chỉ số. Excluding the committed value of the Index Futures contracts.
A54: =TONGQUAN!C16 -> Đại diện có thẩm quyền của Ngân hàng giám sát | D54: =TONGQUAN!F16 -> Đại diện có thẩm quyền của Công ty quản lý Quỹ
A55: =TONGQUAN!C17 -> Authorised Representative of Supervisory Bank | D55: =TONGQUAN!F17 -> Authorised Representative of Fund Management Company
A65: =TONGQUAN!C19 -> Ngân hàng TNHH MTV Standard Chartered (Việt Nam) | D65: =TONGQUAN!F19 -> Công ty Cổ phần Quản lý Quỹ Đầu tư Dragon Capital Việt Nam
A66: =TONGQUAN!C20 -> Vũ Hương Giang | D66: =TONGQUAN!F20 -> Nguyễn Minh Đăng Khánh
A67: =TONGQUAN!C21 -> Trưởng phòng Dịch vụ Quản trị và Giám sát Quỹ | D67: =TONGQUAN!F21 -> Giám đốc điều hành Nghiệp vụ hỗ trợ đầu tư

Sheet BCHoatDongVay_06026
A1: Phụ lục XXVI. Mẫu báo cáo về hoạt động của Quỹ Appendix XXVI. Report on Fund's Operation
A2: (Ban hành kèm theo Thông tư số 98/2020/TT-BTC ngày 16 tháng 11 năm 2020 của Bộ trưởng Bộ Tài Chính về hướng dẫn hoạt động và quản lý quỹ đầu tư chứng khoán) (Issued in association with Circular 98/2020/TT-BTC dated 16 November 2020 of the Minister of Finance on guiding the operation and management of the securities investment funds)
A3: BÁO CÁO VỀ HOẠT ĐỘNG ĐẦU TƯ REPORT ON INVESTMENT ACTIVITIES
A5: Quý I năm 2021 / Quarter I 2021
A7: Tên Công ty quản lý quỹ: | G7: Công ty Cổ phần Quản lý Quỹ Đầu tư Dragon Capital Việt Nam
A8: Fund Management Company: | G8: Dragon Capital Vietfund Management Joint Stock Company
A9: Tên ngân hàng giám sát: | G9: Ngân hàng TNHH Một thành viên Standard Chartered (Việt Nam)
A10: Supervising bank: | G10: Standard Chartered Bank (Vietnam) Limited
A11: Tên Quỹ: | G11: Quỹ Đầu tư Chứng khoán Việt Nam
A12: Fund name: | G12: Vietnam Securities Investment Fund(VFMVF1)
A13: Ngày lập báo cáo: | G13: Ngày 06 tháng 04 năm 2021
A14: Reporting Date: | G14: 06 Apr 2021
A16: A. | B16: BÁO CÁO CHUNG VỀ HOẠT ĐỘNG ĐẦU TƯ CỦA QUỸ/GENERAL INFORMATION ON FUND'S INVESTMENT ACTIVITIES
A17: IV | B17: BÁO CÁO HOẠT ĐỘNG VAY, GIAO DỊCH MUA BÁN LẠI / REPORT ON BORROWING OPERATION, REPO/REVERSE REPO TRANSACTIONS
A18: STT No. | B18: Nội dung hoạt động (nêu chi tiết theo mục tiêu và đối tác) Description | C18: Mã chỉ tiêu Code | D18: Đối tác Counterparty | E18: Mục tiêu/Tài sản đảm bảo Collateral | F18: Kỳ hạn Term | G18: Giá trị khoản vay hoặc khoản cho vay Amount | H18: Thời điểm giao dịch As at transaction date | J18: Thời điểm báo cáo As at reporting date
H19: Ngày tháng năm Date | I19: Tỷ lệ giá trị hợp đồng/giá trị tài sản ròng của quỹ Balance/NAV | J19: Ngày tháng năm Date | K19: Tỷ lệ giá trị hợp đồng/giá trị tài sản ròng của quỹ Balance/NAV
A20: 1 | B20: Các khoản vay tiền (nêu chi tiết từng hợp đồng) Borrowings (detail by each contract)
A21: I | B21: Tổng giá trị các khoản vay tiền/giá trị tài sản ròng Borrowings/NAV
A22: 2 | B22: Hợp đồng Repo (nêu chi tiết từng hợp đồng) Repo contract (detail by each contract)
A23: II | B23: Tổng giá trị các hợp đồng Repo/giá trị tài sản ròng Total value of Repo contracts/NAV
A24: A | B24: Tổng giá trị các khoản vay/giá trị tài sản ròng (=I+II) Total Borrowings, Repo/NAV (=I+II)
A25: 3 | B25: Cho vay chứng khoán (nêu chi tiết từng hợp đồng) Securities lending (detail by each contract)
A26: III | B26: Tổng giá trị các hợp đồng/giá trị tài sản ròng Total contract value/NAV
A27: 4 | B27: Hợp đồng Reverse Repo (nêu chi tiết từng hợp đồng) Reverse Repo contract (Detail by each contract)
A28: IV | B28: Tổng giá trị các hợp đồng/giá trị tài sản ròng Total contract value/NAV
A29: B | B29: Tổng giá trị các khoản cho vay/giá trị tài sản ròng (=III + IV) Total Loans/NAV (=III + IV)
A34: Đại diện có thẩm quyền của Ngân hàng giám sát | I34: Đại diện có thẩm quyền của Công ty quản lý Quỹ
A35: Authorised Representative of Supervisory Bank | I35: Authorised Representative of Fund Management Company
A45: Ngân hàng TNHH MTV Standard Chartered (Việt Nam) | I45: Công ty Cổ phần Quản lý Quỹ Đầu tư Dragon Capital Việt Nam
A46: Vũ Hương Giang | I46: Nguyễn Minh Đăng Khánh
A47: Trưởng phòng Dịch vụ Quản trị và Giám sát Quỹ | I47: Giám đốc điều hành Nghiệp vụ hỗ trợ đầu tư
