Workbook
Name addlogo: INDEX(#REF!,MATCH(#REF!,#REF!,0))

Sheet TONGQUAN
A1: Kỳ báo cáo: | C1: Tại ngày 30 tháng 09 năm 2022 / As at 30 Sep 2022
C2: Quý III năm 2022 / Quarter III 2022
A4: Thông tin chung:
C5: Tên Công ty quản lý quỹ: | D5: Công ty Cổ phần Quản lý Quỹ Đầu tư Dragon Capital Việt Nam
C6: Fund Management Company: | D6: Dragon Capital Vietfund Management Joint Stock Company
C7: Tên ngân hàng giám sát: | D7: Ngân hàng TNHH Một thành viên Standard Chartered (Việt Nam)
C8: Supervising bank: | D8: Standard Chartered Bank (Vietnam) Limited
C9: Tên Quỹ: | D9: Quỹ Đầu tư Trái phiếu Gia tăng Thu nhập Cố định DC
C10: Fund name: | D10: DC Income Plus Bond Fund(VFMVFC)
C11: Ngày lập báo cáo: | D11: Ngày 05 tháng 10 năm 2022
C12: Reporting Date: | D12: 05 Oct 2022
A14: Người ký báo cáo:
C16: Đại diện có thẩm quyền của Ngân hàng giám sát | F16: Đại diện có thẩm quyền của Công ty quản lý Quỹ
C17: Authorised Representative of Supervisory Bank | F17: Authorised Representative of Fund Management Company
C19: Ngân hàng TNHH MTV Standard Chartered (Việt Nam) | F19: =D5 -> Công ty Cổ phần Quản lý Quỹ Đầu tư Dragon Capital Việt Nam
C20: Trịnh Hoài Nam | F20: Nguyễn Minh Đăng Khánh
C21: Phó phòng Dịch vụ Quản trị và Giám sát Quỹ | F21: Giám đốc điều hành Nghiệp vụ hỗ trợ đầu tư
B34: STT | C34: Nội dung | D34: Tên sheet
B35: A | C35: BÁO CÁO CHUNG VỀ HOẠT ĐỘNG ĐẦU TƯ CỦA QUỸ
B36: A.I | C36: Báo cáo về tài sản | D36: 06027
B37: A.II | C37: Báo cáo kết quả hoạt động | D37: 06028
B38: A.III | C38: Báo cáo danh mục đầu tư | D38: 06029
B39: A.IV | C39: Báo cáo hoạt động vay, giao dịch mua bán lại | D39: 06026
B40: A.V | C40: Một số chỉ tiêu khác | D40: 06030
B41: A.VI | C41: Thống kê phí giao dịch | D41: 06031
B42: 5 | C42: Báo cáo thay đổi giá trị tài sản ròng, giao dịch chứng chỉ quỹ | D42: 06129
B43: 6 | C43: Báo cáo thu nhập giữa niên độ | D43: 06203
B44: 7 | C44: Báo cáo tình hình tài chính giữa niên độ | D44: 06105
B45: 8 | C45: Báo cáo thay đổi giá trị tài sản ròng, giao dịch chứng chỉ quỹ giữa niên độ | D45: 06107
B46: 9 | C46: Báo cáo danh mục đầu tư | D46: 06108
B47: 10 | C47: Báo cáo lưu chuyển tiền tệ | D47: 06262
B48: 11 | C48: Báo cáo thu nhập | D48: 06104
B49: 12 | C49: Báo cáo về tài sản của quỹ | D49: 06126
B50: A.VII | C50: Thống kê giao dịch của Quỹ đầu tư bất động sản với người có liên quan | D50: không có
B51: A.VIII | C51: Thống kê giao dịch bất động sản của Quỹ đầu tư bất động sản | D51: không có
B52: B | C52: BÁO CÁO TÌNH HÌNH TỰ DOANH ĐẦU TƯ GIÁN TIẾP RA NƯỚC NGOÀI CỦA QUỸ | D52: Không có

Sheet BCthunhap
A1: Mẫu số B01g - QM. Báo cáo thu nhập Template B01g - QM. Statement of Comprehensive Income
A2: (Ban hành kèm theo Thông tư 198/2012/TT-BTC ngày 15 tháng 11 năm 2012 về chế độ kế toán áp dụng đối với quỹ mở) (Issued in association with Circular 198/2012/TT-BTC dated 15 Nov 2012 on the Accounting Policies for Open-Ended Fund)
A3: BÁO CÁO THU NHẬP STATEMENT OF COMPREHENSIVE INCOME
A5: =TONGQUAN!C2 -> Quý III năm 2022 / Quarter III 2022
A7: Tên Công ty quản lý quỹ: | D7: =TONGQUAN!D5 -> Công ty Cổ phần Quản lý Quỹ Đầu tư Dragon Capital Việt Nam
A8: Fund Management Company: | D8: =TONGQUAN!D6 -> Dragon Capital Vietfund Management Joint Stock Company
A9: Tên ngân hàng giám sát: | D9: =TONGQUAN!D7 -> Ngân hàng TNHH Một thành viên Standard Chartered (Việt Nam)
A10: Supervising bank: | D10: =TONGQUAN!D8 -> Standard Chartered Bank (Vietnam) Limited
A11: Tên Quỹ: | D11: =TONGQUAN!D9 -> Quỹ Đầu tư Trái phiếu Gia tăng Thu nhập Cố định DC
A12: Fund name: | D12: =TONGQUAN!D10 -> DC Income Plus Bond Fund(VFMVFC)
A13: Ngày lập báo cáo: | D13: =TONGQUAN!D11 -> Ngày 05 tháng 10 năm 2022
A14: Reporting Date: | D14: =TONGQUAN!D12 -> 05 Oct 2022
A16: Chỉ tiêu Indicator | B16: Mã số Code | C16: Thuyết minh Note | D16: Năm 2022 Year 2022 | F16: Năm 2021 Year 2021
D17: =BCKetQuaHoatDong_06028!D18 -> Quý III năm 2022 Quarter III 2022 | E17: Số lũy kế Year-to-date | F17: Quý III năm 2021 Quarter III 2021 | G17: Số lũy kế Year-to-date
A18: I. THU NHẬP, DOANH THU HOẠT ĐỘNG ĐẦU TƯ Investment income | B18: 01 | D18: 12115899732 | E18: 23528831260 | F18: 4156664698 | G18: 5750628763
A19: 1.1. Cổ tức được chia Dividend income | B19: 02 | D19: 0 | E19: 0 | F19: 17000 | G19: 212000
A20: 1.2. Tiền lãi được nhận Interest income | B20: 03 | D20: 12859723014 | E20: 24194718123 | F20: 4195213657 | G20: 5772572637
A21: Lãi tiền gửi ngân hàng Interest income from bank deposits | B21: 03.1 | D21: 1372469591 | E21: 2683328986 | F21: 642653249 | G21: 1153190312
A22: Lãi chứng chỉ tiền gửi Interest income from Certificates of Deposit | B22: 03.2 | D22: 1395767124 | E22: 3846643836 | F22: 1643397260 | G22: 2082547945
A23: Lãi trái phiếu Interest income from bonds | B23: 03.3 | D23: 10091486299 | E23: 17664745301 | F23: 1909163148 | G23: 2536834380
A24: Tiền lãi hợp đồng mua lại đảo ngược được nhận Reverse repo contract interest received | B24: 03.4 | D24: 0 | E24: 0 | F24: 0 | G24: 0
A25: 1.3. Lãi (lỗ) bán các khoản đầu tư Realized gain (losses) from disposal investments | B25: 04 | D25: 128662233 | E25: 484419112 | F25: -38705479 | G25: -11222836
A26: 1.4. Chênh lệch tăng, giảm đánh giá lại các khoản đầu tư chưa thực hiện Unrealized gain (losses) from investment revaluation | B26: 05 | D26: -872485515 | E26: -1150305975 | F26: 139520 | G26: -10933038
A27: 1.5. Doanh thu khác Other income | B27: 06 | D27: 0 | E27: 0 | F27: 0 | G27: 0
A28: 1.6. Chênh lệch lãi, lỗ tỷ giá hối đoái đã và chưa thực hiện Realized and unrealized gain (losses) from foreign exchange | B28: 07 | D28: 0 | E28: 0 | F28: 0 | G28: 0
A29: 1.7. Doanh thu khác về đầu tư Other investment income | B29: 08 | D29: 0 | E29: 0 | F29: 0 | G29: 0
... A77: VIII. LỢI NHUẬN KẾ TOÁN SAU THUẾ TNDN PROFIT AFTER TAX (41=30-40) | B77: 41 | D77: 9608133266 | E77: 18568973122 | F77: 3151009049 | G77: 3798671370
A80: Người lập: | B80: Người duyệt:
A93: _______________________________________________ | B93: _____________________________________ | F93: _________________________________________________
A94: Nguyễn Kiều Trúc Ly | B94: Ninh Thị Tuệ Minh | F94: Nguyễn Minh Đăng Khánh
A95: Kế toán Quỹ | B95: Trưởng phòng Kế toán Quỹ | F95: Giám đốc điều hành Nghiệp vụ hỗ trợ đầu tư

Sheet BCtinhhinhtaichinh
A1: Mẫu số B02g - QM. Báo cáo tình hình tài chính Template B02g - QM. Statement of Financial Position
A2: (Ban hành kèm theo Thông tư 198/2012/TT-BTC ngày 15 tháng 11 năm 2012 về chế độ kế toán áp dụng đối với quỹ mở) (Issued in association with Circular 198/2012/TT-BTC dated 15 Nov 2012 on the Accounting Policies for Open-Ended Fund)
A3: BÁO CÁO TÌNH HÌNH TÀI CHÍNH STATEMENT OF FINANCIAL POSITION
A5: =TONGQUAN!C1 -> Tại ngày 30 tháng 09 năm 2022 / As at 30 Sep 2022
A7: Tên Công ty quản lý quỹ: | C7: =TONGQUAN!D5 -> Công ty Cổ phần Quản lý Quỹ Đầu tư Dragon Capital Việt Nam
A8: Fund Management Company: | C8: =TONGQUAN!D6 -> Dragon Capital Vietfund Management Joint Stock Company
A9: Tên ngân hàng giám sát: | C9: =TONGQUAN!D7 -> Ngân hàng TNHH Một thành viên Standard Chartered (Việt Nam)
A10: Supervising bank: | C10: =TONGQUAN!D8 -> Standard Chartered Bank (Vietnam) Limited
A11: Tên Quỹ: | C11: =TONGQUAN!D9 -> Quỹ Đầu tư Trái phiếu Gia tăng Thu nhập Cố định DC
A12: Fund name: | C12: =TONGQUAN!D10 -> DC Income Plus Bond Fund(VFMVFC)
A13: Ngày lập báo cáo: | C13: =TONGQUAN!D11 -> Ngày 05 tháng 10 năm 2022
A14: Reporting Date: | C14: =TONGQUAN!D12 -> 05 Oct 2022
A16: STT No. | B16: Chỉ tiêu Indicator | C16: Mã số Code | D16: Thuyết minh Note | E16: =BCTaiSan_06027!D18 -> Ngày 30 tháng 09 năm 2022 As at 30 Sep 2022 | F16: =BCTaiSan_06027!E18 -> Ngày 30 tháng 06 năm 2022 As at 30 Jun 2022
A17: I | B17: I. TÀI SẢN ASSETS | C17: I
A18: 1 | B18: 1.Tiền gửi ngân hàng và tương đương tiền Cash at bank and cash equivalent | C18: 110 | E18: 147951287500 | F18: 69607440580
A19: 1.1 | B19: 1.1. Tiền gửi ngân hàng Cash at bank | C19: 111 | E19: 78951287500 | F19: 8607440580
B20: Tiền gửi của nhà đầu tư cho hoạt động mua chứng chỉ quỹ Cash at bank for Fund's subscription | C20: 111.1 | E20: 0 | F20: 0
B21: Tiền phải trả cho Nhà đầu tư về mua lại Chứng chỉ quỹ Cash at bank for Fund's redemption | C21: 111.2 | E21: 50120632 | F21: 11385290
B22: Tiền gửi ngân hàng cho hoạt động của Quỹ Cash at bank for Fund's operation | C22: 111.3 | E22: 78901166868 | F22: 8596055290
B23: Tiền gửi ký quỹ cho hoạt động đầu tư chứng khoán phái sinh Margin account for trading derivatives | C23: 111.4 | E23: 0 | F23: 0
A24: 1.2 | B24: 1.2. Tiền gửi có kỳ hạn dưới ba (03) tháng Deposit with term less than three (03) months | C24: 112 | E24: 69000000000 | F24: 61000000000
A25: 2 | B25: 2. Các khoản đầu tư thuần Net Investments | C25: 120 | E25: 895944472888 | F25: 294518928855
A26: 2.1 | B26: 2.1. Các khoản đầu tư Investments | C26: 121 | E26: 895944472888 | F26: 294518928855
B27: Cổ phiếu niêm yết Listed Shares | C27: 121.1 | E27: 0 | F27: 0
B28: Cổ phiếu chưa niêm yết Unlisted Shares | C28: 121.2 | E28: 0 | F28: 0
B29: Trái phiếu niêm yết Listed Bonds | C29: 121.3 | E29: 576115043700 | F29: 203377325500
B30: Trái phiếu chưa niêm yết Unlisted Bonds | C30: 121.4 | E30: 99082914650 | F30: 31003554040
B31: Chứng chỉ tiền gửi Certificates of Deposit | C31: 121.5 | E31: 190146514538 | F31: 50538049315
B32: Hợp đồng tiền gửi có kỳ hạn trên ba (03) tháng Deposits with term over three (03) months | C32: 121.6 | E32: 30600000000 | F32: 9600000000
B33: Quyền mua chứng khoán Investment - Rights | C33: 121.7 | E33: 0 | F33: 0
B34: Hợp đồng tương lai chỉ số Index future contracts | C34: 121.8 | E34: 0 | F34: 0
B35: Đầu tư khác Other Investments | C35: 121.9 | E35: 0 | F35: 0
B36: Hợp đồng mua lại đảo ngược Reverse repo contracts | C36: 121.10 | E36: 0 | F36: 0
A37: 2.2 | B37: 2.2. Dự phòng giảm giá tài sản nhận thế chấp Impairment of devaluation of pledged assets | C37: 122 | E37: 0 | F37: 0
A38: 3 | B38: 3. Các khoản phải thu Receivables | C38: 130 | E38: 26686447536 | F38: 6275483056
A39: 3.1 | B39: 3.1 Phải thu về bán các khoản đầu tư Receivables from investments sold but not yet settled | C39: 131 | E39: 0 | F39: 0
B40: Trong đó: Phải thu khó đòi về bán các khoản đầu tư In which: Overdue receivables from selling investments | C40: 132 | E40: 0 | F40: 0
A41: 3.2 | B41: 3.2. Phải thu và dự thu cổ tức, tiền lãi các khoản đầu tư Dividend and interest receivables | C41: 133 | E41: 26686337536 | F41: 6275470956
A42: 3.2.1 | B42: 3.2.1. Phải thu cổ tức, tiền lãi đến ngày nhận Dividend and interest receivables on or after payment date | C42: 134 | E42: 0 | F42: 0
B43: Phải thu cổ tức Dividend receivables | C43: 134.1 | E43: 0 | F43: 0
B44: Phải thu trái tức Coupon receivables | C44: 134.2 | E44: 0 | F44: 0
B45: Phải thu lãi tiền gửi có kỳ hạn dưới 3 tháng Interest receivables from deposit with term less than three (03) months | C45: 134.3 | E45: 0 | F45: 0
B46: Phải thu lãi tiền gửi có kỳ hạn trên 3 tháng Interest receivables from deposit with term more than three (03) months | C46: 134.4 | E46: 0 | F46: 0
B47: Phải thu lãi chứng chỉ tiền gửi Interest receivables from Certificates of Deposit | C47: 134.5 | E47: 0 | F47: 0
B48: Trong đó: Phải thu khó đòi về cổ tức, tiền lãi đến ngày nhận nhưng chưa nhận được In which: Overdue receivables from dividend, interest income | C48: 135 | E48: 0 | F48: 0
A49: 3.2.2 | B49: 3.2.2.Dự thu cổ tức, tiền lãi chưa đến ngày nhận Dividend and interest receivables before payment date | C49: 136 | E49: 26686337536 | F49: 6275470956
B50: Dự thu cổ tức Dividend receivables | C50: 136.1 | E50: 0 | F50: 0
B51: Dự thu lãi trái phiếu Interest accrual from bonds | C51: 136.2 | E51: 19742010958 | F51: 5447342740
B52: Dự thu lãi tiền gửi có kỳ hạn dưới 3 tháng Interest accrual from deposits with term less than three (03) months | C52: 136.3 | E52: 53671233 | F52: 114169861
B53: Dự thu lãi tiền gửi có kỳ hạn trên 3 tháng Interest accrual from deposit with term more than three (03) months | C53: 136.4 | E53: 395340275 | F53: 3519999
B54: Dự thu lãi chứng chỉ tiền gửi Interest accrual from Certificates of Deposit | C54: 136.5 | E54: 6495315070 | F54: 710438356
B55: Dự thu lãi hợp đồng mua lại đảo ngược Interest receivables from reverse repo contracts | C55: 136.6 | E55: 0 | F55: 0
A56: 3.3 | B56: 3.3. Các khoản phải thu khác Other receivables | C56: 137 | E56: 110000 | F56: 12100
B57: Phải thu cho khoản cổ phiếu hạn chế chờ mua Receivable from AP/Investors on securities on hold of buying | C57: 137.1 | E57: 0 | F57: 0
B58: Các tài sản khác Other assets | C58: 137.2 | E58: 0 | F58: 0
B59: Các khoản khác Others | C59: 137.3 | E59: 110000 | F59: 12100
A60: 3.4 | B60: 3.4. Dự phòng nợ phải thu khó đòi Provision for doubtful debt | C60: 138 | E60: 0 | F60: 0
B61: TỔNG TÀI SẢN TOTAL ASSETS | C61: 100 | E61: 1070582207924 | F61: 370401852491
A62: II | B62: II. NỢ PHẢI TRẢ TOTAL LIABILITIES | C62: II
A63: 1 | B63: 1. Vay ngắn hạn Short-term loans | C63: 311 | E63: 0 | F63: 0
B64: Gốc hợp đồng repo Repo contracts - Principal | C64: 311.1 | E64: 0 | F64: 0
B65: Vay ngắn hạn Short-term loans | C65: 311.2 | E65: 0 | F65: 0
A66: 2 | B66: 2. Phải trả về mua các khoản đầu tư Payables for securities bought but not yet settled | C66: 312 | E66: 18794840000 | F66: 0
A67: 3 | B67: 3. Phải trả phí cho các Đại lý phân phối, Công ty quản lý quỹ về mua bán Chứng chỉ quỹ Subscription and Redemption fee payable to distributors and fund management company | C67: 313 | E67: 198646364 | F67: 23552296
B68: Phải trả phí cho các Đại lý phân phối về mua bán Chứng chỉ quỹ Subscription and Redemption fee payable to distributors | C68: 313.1 | E68: 0 | F68: 0
B69: Phải trả phí cho Công ty quản lý quỹ về mua bán Chứng chỉ quỹ Subscription and Redemption fee payable to fund management company | C69: 313.2 | E69: 198646364 | F69: 23552296
A70: 4 | B70: 4. Thuế và các khoản phải nộp Nhà nước Tax payables and obligations to the State Budget | C70: 314 | E70: 212217997 | F70: 10671744
A71: 5 | B71: 5.Phải trả thu nhập cho Nhà đầu tư Profit distribution payables | C71: 315 | E71: 0 | F71: 0
A72: 6 | B72: 6. Chi phí phải trả Expense Accruals | C72: 316 | E72: 38816264 | F72: 58114545
B73: Phí giao dịch Transaction fee | C73: 316.1 | E73: 3758968 | F73: 0
B74: Phải trả phí môi giới Brokerage fee payables | C74: 316.1.1 | E74: 3758968 | F74: 0
B75: Phải trả phí giao dịch thanh toán bù trừ chứng khoán Clearing Settlement Fee payables | C75: 316.1.2 | E75: 0 | F75: 0
B76: Trích trước phí kiểm toán Accrued expense for audit fee | C76: 316.2 | E76: 24199232 | F76: 48398464
B77: Trích trước phí họp đại hội thường niên Accrued expense for Annual General meeting | C77: 316.3 | E77: 0 | F77: 0
B78: Trích trước phí báo cáo thường niên Accrued expense for Annual report | C78: 316.4 | E78: 0 | F78: 0
B79: Trích trước thù lao ban đại diện quỹ Accrued expense for Remuneration Payable to Fund's Board of Representatives | C79: 316.5 | E79: 10858064 | F79: 9716081
B80: Trích trước phí quản lý niêm yết hàng năm tại SGDCK Accrued expense for annual listing fee at HOSE | C80: 316.6 | E80: 0 | F80: 0
B81: Trích trước lãi vay ngắn hạn của hợp đồng vay và hợp đồng repo Accrued Interest Expense of short-term loan contracts and repo contracts | C81: 316.7 | E81: 0 | F81: 0
A82: 7 | B82: 7. Phải trả cho Nhà đầu tư về mua Chứng chỉ quỹ Subscription payables to investors | C82: 317 | E82: 28138885128 | F82: 8533790040
B83: Phải trả cho nhà đầu tư chờ mua chứng chỉ quỹ Subscription Pending allotment | C83: 317.1 | E83: 28138885128 | F83: 8533790040
B84: Phải trả nhà đầu tư trên tài sản giữ hộ Payables to investors for investment bought on behalf | C84: 317.2 | E84: 0 | F84: 0
A85: 8 | B85: 8. Phải trả cho Nhà đầu tư về mua lại Chứng chỉ quỹ Redemption payables to investors | C85: 318 | E85: 50120632 | F85: 0
A86: 9 | B86: 9. Phải trả dịch vụ quản lý Quỹ mở Fund management related service expense payable | C86: 319 | E86: 1031315411 | F86: 413195766
B87: Trích trước phải trả phí quản lý Accrued expense for Management fee | C87: 319.1 | E87: 914114480 | F87: 332335935
B88: Trích trước phí lưu ký tài sản Quỹ mở Accrued expense for Custodian fee | C88: 319.2 | E88: 38838101 | F88: 14447331
B89: Phí dịch vụ lưu ký - bảo quản tài sản Custodian service - Safe Custody Fee | C89: 319.2.1 | E89: 38088101 | F89: 13847331
B90: Phí dịch vụ lưu ký - giao dịch chứng khoán Custodian service - Transaction fee | C90: 319.2.2 | E90: 750000 | F90: 600000
B91: Phí dịch vụ lưu ký cho chứng khoán cơ sở, phí quản lý vị thế và tài sản phái sinh trả cho VSD Custodian service - Depository fee, Position and Margin management fee paid to VSD | C91: 319.2.3 | E91: 0 | F91: 0
B92: Trích trước phí quản trị quỹ Accrued expense for Fund administration fee | C92: 319.3 | E92: 40024682 | F92: 37262500
B93: Trích trước phí giám sát Accrued expense for Supervising fee | C93: 319.4 | E93: 25138148 | F93: 18150000
B94: Trích trước phí dịch vụ đại lý chuyển nhượng Accrued expense for Tranfer agency fee | C94: 319.5 | E94: 13200000 | F94: 11000000
B95: Dự chi phí cung cấp dịch vụ tính giá trị tài sản ròng tham chiếu (iNAV) cho HOSE Accrued expense for payable to HOSE for iNAV calculation | C95: 319.6 | E95: 0 | F95: 0
B96: Dự chi phí cấp quyền sử dụng chỉ số cho HOSE Accrued expense for payable to HOSE for Index usage | C96: 319.7 | E96: 0 | F96: 0
A97: 10 | B97: 10. Phải trả, phải nộp khác Other payables | C97: 320 | E97: 5000000 | F97: 5000000
B98: Phải trả phí báo giá Price feed fee payable | C98: 320.1 | E98: 0 | F98: 0
B99: Trích trước phí công tác, họp của ban đại diện Accrued expense for Fund's Board of Representatives travelling, meeting | C99: 320.2 | E99: 0 | F99: 0
B100: Trích trước phí quản lý thường niên trả cho UBCKNN Accrued expense for Annual Fee paid to SSC | C100: 320.3 | E100: 5000000 | F100: 5000000
B101: Phí Ngân hàng S2B S2B Bank charge | C101: 320.4 | E101: 0 | F101: 0
B102: Phải trả khác Other payables | C102: 320.5 | E102: 0 | F102: 0
B103: TỔNG NỢ PHẢI TRẢ TOTAL LIABILITIES | C103: 300 | E103: 48469841796 | F103: 9044324391
...

Sheet BCLCTT_06262
A1: Mẫu số B05g - QM. Báo cáo lưu chuyển tiền tệ Template B05g - QM. Cash flow statement
A2: (Ban hành kèm theo Thông tư 198/2012/TT-BTC ngày 15 tháng 11 năm 2012 về chế độ kế toán áp dụng đối với quỹ mở) (Issued in association with Circular 198/2012/TT-BTC dated 15 Nov 2012 on the Accounting Policies for Open-Ended Fund)
A3: BÁO CÁO LƯU CHUYỂN TIỀN TỆ CASH FLOW STATEMENT
A4: =TONGQUAN!C2 -> Quý III năm 2022 / Quarter III 2022
A7: Tên Công ty quản lý quỹ: | B7: =TONGQUAN!D5 -> Công ty Cổ phần Quản lý Quỹ Đầu tư Dragon Capital Việt Nam
A8: Fund Management Company: | B8: =TONGQUAN!D6 -> Dragon Capital Vietfund Management Joint Stock Company
A9: Tên ngân hàng giám sát: | B9: =TONGQUAN!D7 -> Ngân hàng TNHH Một thành viên Standard Chartered (Việt Nam)
A10: Supervising bank: | B10: =TONGQUAN!D8 -> Standard Chartered Bank (Vietnam) Limited
A11: Tên Quỹ: | B11: =TONGQUAN!D9 -> Quỹ Đầu tư Trái phiếu Gia tăng Thu nhập Cố định DC
A12: Fund name: | B12: =TONGQUAN!D10 -> DC Income Plus Bond Fund(VFMVFC)
A13: Ngày lập báo cáo: | B13: =TONGQUAN!D11 -> Ngày 05 tháng 10 năm 2022
A14: Reporting Date: | B14: =TONGQUAN!D12 -> 05 Oct 2022
A17: Chỉ tiêu Indicator | B17: Mã số Code | C17: Thuyết minh Note | D17: =BCKetQuaHoatDong_06028!D18 -> Quý III năm 2022 Quarter III 2022 | E17: =BCKetQuaHoatDong_06028!E18 -> Quý II năm 2022 Quarter II 2022
A18: I. Lưu chuyển tiền từ hoạt động đầu tư Cash flow from investing activities | B18: I
A19: 1. Lợi nhuận trước Thuế thu nhập doanh nghiệp Profit before income tax | B19: 01 | D19: 9608133266 | E19: 4627253459
A20: 2. Điều chỉnh cho các khoản tăng giá trị tài sản ròng từ các hoạt động đầu tư Adjustment for NAV increase from investing activities | B20: 02 | D20: 848286283 | E20: 66583055
A21: (- Lãi) hoặc (+ lỗ) chênh lệch tỷ giá hối đoái/ đánh giá lại các khoản đầu tư chưa thực hiện Unreliased (Gain) or Loss from FX valuation/Investment revaluation | B21: 03 | D21: 872485515 | E21: 85239386
A22: (+) Chi phí trích trước Increase of Accrued Expenses | B22: 04 | D22: -24199232 | E22: -18656331
A23: 3. Lợi nhuận từ hoạt động đầu tư trước thay đổi vốn lưu động Profit from investing activities before changes in working capital | B23: 05 | D23: 10456419549 | E23: 4693836514
A24: (-) Tăng, (+) giảm đầu tư (Increase), Decrease Investments | B24: 20 | D24: -602298029548 | E24: -34954774026
A25: (-) Tăng, (+) giảm phải thu bán chứng khoán đầu tư (Increase), Decrease in Receivables from investments sold but not yet settled | B25: 06 | D25: 0 | E25: 0
A26: (-) Tăng, (+) giảm dự thu phải thu tiền lãi các khoản đầu tư (Increase), Decrease in Dividend and interest receivables | B26: 07 | D26: -20410866580 | E26: -39370962
A27: (-) Tăng, (+) giảm các khoản phải thu khác (Increase), Decrease in other receivables | B27: 08 | D27: -97900 | E27: -12100
A28: (+) Tăng, (-) giảm vay ngắn hạn Increase, (Decrease) in Short-term Loans | B28: 09 | D28: 0 | E28: 0
A29: (+) Tăng, (-) giảm phải trả cho người bán (Decrease), Increase in payables for securities purchased but not yet settled | B29: 10 | D29: 18794840000 | E29: 0
A30: (+) Tăng, (-) giảm phải trả các Đại lý phân phối Chứng chỉ quỹ, Công ty Quản lý Quỹ (Decrease)/increase in subscription and redemption fee payable to distributors and Fund Management Company | B30: 11 | D30: 175094068 | E30: 13777608
... A38: Lưu chuyển tiền thuần từ hoạt động đầu tư (1+2+3) Net Cash flow from Investing activities | B38: 19 | D38: -572802857842 | E38: -21907816170
A39: II. Lưu chuyển tiền từ hoạt động tài chính Cash flow from financing activities | B39: II
A40: 1. Tiền thu từ phát hành Chứng chỉ quỹ mở Receipts from subscriptions | B40: 31 | D40: 961853905123 | E40: 98241194677
A41: 2. Tiền chi mua lại Chứng chỉ quỹ mở Payments for redemptions | B41: 32 | D41: -310707200361 | E41: -21675506517
A42: 3. Tiền vay gốc Principal of borrowings | B42: 33 | D42: 0 | E42: 0
A43: 4. Tiền chi trả nợ gốc vay Payment of Principal borrowings | B43: 34 | D43: 0 | E43: 0
A44: 5. Tiền chi trả cổ tức, tiền lãi cho nhà đầu tư Dividend, profit distribution paid to investors | B44: 35 | D44: 0 | E44: 0
A45: Lưu chuyển tiền thuần từ hoạt động tài chính (1-2+3-4-5) Net cash outflows from financing activities | B45: 30 | D45: 651146704762 | E45: 76565688160
A46: III. Tăng/giảm tiền thuần trong kỳ Net Increase/Decrease in cash and cash equivalent for the period | B46: 40 | D46: 78343846920 | E46: 54657871990
A47: IV. Tiền và các khoản tương đương tiền đầu kỳ Cash and cash equivalents at the beginning of period | B47: 50 | D47: 69607440580 | E47: 14949568590
A48: Tiền gửi ngân hàng đầu kỳ: Cash at bank of the beginning of period: | B48: 51 | D48: 69607440580 | E48: 14949568590
A49: -Tiền gửi ngân hàng và tương đương tiền cho hoạt động của Quỹ Cash at bank and cash equivalent for Fund's operation | B49: 52 | D49: 69596055290 | E49: 14949468680
A50: Tiền gửi không kỳ hạn Demand deposit | B50: 52.1 | D50: 8596055290 | E50: 449468680
A51: Tiền gửi có kỳ hạn dưới ba (03) tháng Deposits with term under three (03) months | B51: 52.2 | D51: 61000000000 | E51: 14500000000
... A64: Khác Others | B64: 80 | D64: 0 | E64: 0
A67: Người lập: | C67: Người duyệt:
A78: ____________________________________ __________________________ _____________________________________________
A79: Nguyễn Kiều Trúc Ly | B79: Ninh Thị Tuệ Minh Nguyễn Minh Đăng Khánh
A80: Kế toán Quỹ | B80: Trưởng phòng Kế toán Quỹ Giám đốc điều hành Nghiệp vụ hỗ trợ đầu tư

Sheet BCTaiSan_06027
A1: Phụ lục XXVI. Mẫu báo cáo về hoạt động của Quỹ Appendix XXVI. Report on Fund's Operation
A2: (Ban hành kèm theo Thông tư số 98/2020/TT-BTC ngày 16 tháng 11 năm 2020 của Bộ trưởng Bộ Tài Chính về hướng dẫn hoạt động và quản lý quỹ đầu tư chứng khoán) (Issued in association with Circular 98/2020/TT-BTC dated 16 November 2020 of the Minister of Finance on guiding the operation and management of the securities investment funds)
A3: BÁO CÁO VỀ HOẠT ĐỘNG ĐẦU TƯ REPORT ON INVESTMENT ACTIVITIES
A5: =TONGQUAN!C1 -> Tại ngày 30 tháng 09 năm 2022 / As at 30 Sep 2022
A7: Tên Công ty quản lý quỹ: | C7: =TONGQUAN!D5 -> Công ty Cổ phần Quản lý Quỹ Đầu tư Dragon Capital Việt Nam
A8: Fund Management Company: | C8: =TONGQUAN!D6 -> Dragon Capital Vietfund Management Joint Stock Company
A9: Tên ngân hàng giám sát: | C9: =TONGQUAN!D7 -> Ngân hàng TNHH Một thành viên Standard Chartered (Việt Nam)
A10: Supervising bank: | C10: =TONGQUAN!D8 -> Standard Chartered Bank (Vietnam) Limited
A11: Tên Quỹ: | C11: =TONGQUAN!D9 -> Quỹ Đầu tư Trái phiếu Gia tăng Thu nhập Cố định DC
A12: Fund name: | C12: =TONGQUAN!D10 -> DC Income Plus Bond Fund(VFMVFC)
A13: Ngày lập báo cáo: | C13: =TONGQUAN!D11 -> Ngày 05 tháng 10 năm 2022
A14: Reporting Date: | C14: =TONGQUAN!D12 -> 05 Oct 2022
A16: A. | B16: BÁO CÁO CHUNG VỀ HOẠT ĐỘNG ĐẦU TƯ CỦA QUỸ/GENERAL INFORMATION ON FUND'S INVESTMENT ACTIVITIES
A17: I | B17: BÁO CÁO VỀ TÀI SẢN / ASSET REPORT
A18: STT No | B18: Nội dung Indicator | C18: Mã chỉ tiêu Code | D18: Ngày 30 tháng 09 năm 2022 As at 30 Sep 2022 | E18: Ngày 30 tháng 06 năm 2022 As at 30 Jun 2022 | F18: %/cùng kỳ năm trước %/against last year
A19: I | B19: TÀI SẢN ASSETS
A20: I.1 | B20: Tiền và các khoản tương đương tiền Cash and Cash Equivalents | D20: 147951287500 | E20: 69607440580 | F20: 6.8331915
B21: Tiền gửi ngân hàng Cash at bank | D21: 78951287500 | E21: 8607440580 | F21: 224.38438
B22: Tiền gửi của nhà đầu tư cho hoạt động mua chứng chỉ quỹ Cash at bank for Fund's subscription | D22: 0 | E22: 0
B23: Tiền phải trả cho Nhà đầu tư về mua lại chứng chỉ quỹ Cash at bank for Fund's redemption | D23: 50120632 | E23: 11385290
B24: Tiền gửi ngân hàng cho hoạt động của Quỹ Cash at bank for Fund's operation | D24: 78901166868 | E24: 8596055290 | F24: 224.24194
B25: Tiền gửi ký quỹ cho hoạt động đầu tư chứng khoán phái sinh Margin account for trading derivatives | D25: 0 | E25: 0
B26: Tiền, tương đương tiền Cash, cash equivalents | D26: 69000000000 | E26: 61000000000 | F26: 3.2394366
A27: I.2 | B27: Các khoản đầu tư (kê chi tiết) Investments | D27: 895944472888 | E27: 294518928855 | F27: 4.5095859
B28: Cổ phiếu niêm yết Listed shares | D28: 0 | E28: 0 | F28: 0
B29: Cổ phiếu chưa niêm yết Unlisted shares | D29: 0 | E29: 0
B30: Trái phiếu Bonds | D30: 675197958350 | E30: 234380879540 | F30: 8.6391257
B31: Chứng chỉ tiền gửi Certificates of Deposit | D31: 190146514538 | E31: 50538049315 | F31: 2.361536
B32: Hợp đồng tiền gửi có kỳ hạn trên ba (03) tháng Deposits with term over three (03) months | D32: 30600000000 | E32: 9600000000 | F32: 0.765
B33: Quyền mua chứng khoán Investment - Rights | D33: 0 | E33: 0
B34: Hợp đồng tương lai chỉ số Index future contracts | D34: 0 | E34: 0
B35: Đầu tư khác Other investments | D35: 0 | E35: 0
B36: Hợp đồng mua lại đảo ngược Reverse repo contracts | D36: 0 | E36: 0
A37: I.3 | B37: Thu từ cho thuê bất động sản đầu tư (không áp dụng) Receivables from rental of investment property (not applicable)
A38: I.4 | B38: Cổ tức, trái tức được nhận Dividend, Coupon receivables | D38: 19742010958 | E38: 5447342740 | F38: 14.664087
B39: Phải thu cổ tức Dividend receivables | D39: 0 | E39: 0
B40: Phải thu trái tức Coupon receivables | D40: 19742010958 | E40: 5447342740 | F40: 14.664087
A41: I.5 | B41: Lãi được nhận Interest receivables | D41: 6944326578 | E41: 828128216 | F41: 1.5203021
B42: Phải thu lãi tiền gửi Interest receivable from bank deposits | D42: 449011508 | E42: 117689860 | F42: 0.58034276
B43: Phải thu lãi chứng chỉ tiền gửi Interest receivable from Certificates of Deposit | D43: 6495315070 | E43: 710438356 | F43: 1.7119842
B44: Phải thu lãi hợp đồng mua lại đảo ngược Interest receivable from reverse repo contracts | D44: 0 | E44: 0
A45: I.6 | B45: Tiền bán bất động sản chờ thu (không áp dụng) Real Estate Proceeds Receivables (not applicale)
A46: I.7 | B46: Tiền bán chứng khoán chờ thu Securities Trading Receivables | D46: 0 | E46: 0
A47: I.8 | B47: Các khoản phải thu khác Other Receivables | D47: 110000 | E47: 12100
B48: Dự phòng giảm giá tài sản nhận thế chấp Impairment of devaluation of pledged assets | D48: 0 | E48: 0
B49: Dự phòng nợ phải thu khó đòi Provision for doubtful debt | D49: 0 | E49: 0
B50: Các khoản phải thu khác Other Receivables | D50: 110000 | E50: 12100
A51: I.9 | B51: Các tài sản khác Other Assets | D51: 0 | E51: 0 | F51: 0
A52: I.10 | B52: TỔNG TÀI SẢN TOTAL ASSETS | D52: 1070582207924 | E52: 370401852491 | F52: 3.875531
A53: II | B53: NỢ LIABILITIES
A54: II.1 | B54: Tiền phải thanh toán mua bất động sản (không áp dụng) Real Estate Trading Payables (not applicable)
A55: II.2 | B55: Tiền phải thanh toán mua chứng khoán Securities Trading Payables | D55: 18794840000 | E55: 0
A56: II.3 | B56: Các khoản phải trả khác Other Payables | D56: 29675001796 | E56: 9044324391 | F56: 67.261647
B57: Phải trả nhà đầu tư Payables to investors | D57: 28189005760 | E57: 8533790040 | F57: 2236.0156
B58: Phải trả cho nhà đầu tư chờ mua chứng chỉ quỹ Subscription Pending allotment | D58: 28138885128 | E58: 8533790040 | F58: 2232.0399
B59: Phải trả nhà đầu tư trên tài sản giữ hộ Payables to investors for investment bought on behalf | D59: 0 | E59: 0
B60: Phải trả nhà đầu tư trên cổ tức đã thu Payables to investors for collected dividend | D60: 0 | E60: 0
B61: Phải trả cho Nhà đầu tư về mua lại chứng chỉ quỹ Redemption payable to investors | D61: 50120632 | E61: 0
B62: Thuế và các khoản phải nộp Nhà nước Tax payables and obligations to the State Budget | D62: 212217997 | E62: 10671744 | F62: 216.49905
B63: Phải trả phí phát hành, mua lại chứng chỉ quỹ cho Đại lý phân phối và Công ty quản lý quỹ Subscription and Redemption fee payable to distributors and Fund Management Company | D63: 198646364 | E63: 23552296 | F63: 68.209983
B64: Phải trả thu nhập cho nhà đầu tư Income payable to investors | D64: 0 | E64: 0
B65: Phải trả thù lao Ban đại diện quỹ Remuneration Payable to Fund's Board of Representatives | D65: 10858064 | E65: 9716081 | F65: 0.75881995
B66: Phải trả phí quản lý cho công ty quản lý quỹ Management fee payable | D66: 914114480 | E66: 332335935 | F66: 3.8889506
B67: Phải trả phí quản trị quỹ Fund Administration fee payable | D67: 40024682 | E67: 37262500 | F67: 1.0741277
B68: Phải trả phí giám sát Supervisory service fee payable | D68: 25138148 | E68: 18150000 | F68: 1.3850219
B69: Phí giao dịch Transaction fee | D69: 3758968 | E69: 0
B70: Phải trả phí môi giới Brokerage fee payable | D70: 3758968 | E70: 0
B71: Phải trả phí phát hành thanh toán bù trừ chứng khoán Clearing Settlement fee payable | D71: 0 | E71: 0
B72: Trích trước phí lưu ký tài sản Quỹ mở Accrued expense for Custodian fee | D72: 38838101 | E72: 14447331 | F72: 3.2500503
B73: Phí lưu ký - bảo quản tài sản Custodian service - Safe Custody Fee | D73: 38088101 | E73: 13847331 | F73: 3.3120088
B74: Phí lưu ký - giao dịch chứng khoán Custodian service - Transaction fee | D74: 750000 | E74: 600000 | F74: 1.6666667
B75: Phí lưu ký cho chứng khoán cơ sở, phí quản lý vị thế và tài sản phái sinh trả cho VSD Custodian service - Depository fee, Position and Margin management fee paid to VSD | D75: 0 | E75: 0
B76: Phải trả phí kiểm toán Audit fee payable | D76: 24199232 | E76: 48398464 | F76: 0.34603513
B77: Phải trả phí họp đại hội thường niên General meeting expense payable | D77: 0 | E77: 0
B78: Phải trả phí báo cáo thường niên Annual report fee payable | D78: 0 | E78: 0
B79: Phải trả phí dịch vụ đại lý chuyển nhượng Transfer Agency fee payable | D79: 13200000 | E79: 11000000 | F79: 1.2
B80: Dự chi phí tính giá trị tài sản ròng tham chiếu (iNAV) cho HOSE Service fee payable to HOSE for calculating iNAV | D80: 0 | E80: 0
B81: Dự chi phí cấp quyền sử dụng chỉ số cho HOSE Authorising index service fee payable to HOSE | D81: 0 | E81: 0
B82: Phải trả khác Other payables | D82: 5000000 | E82: 5000000 | F82: 0.1849834
B83: Phải trả phí báo giá Price feed fee payable | D83: 0 | E83: 0 | F83: 0
B84: Trích trước phí công tác, họp của ban đại diện Accrued expense for Fund's Board of Representatives travelling, meeting | D84: 0 | E84: 0
B85: Trích trước phí quản lý thường niên trả UBCKNN Accrued expense for Annual Management Fee pay to SSC | D85: 5000000 | E85: 5000000 | F85: 0.66849817
B86: Phải trả khác Other payables | D86: 0 | E86: 0
B87: Vay ngắn hạn - hợp đồng repo Short-term loans - Repo contracts | D87: 0 | E87: 0
B88: Gốc hợp đồng repo Principal of repo contracts | D88: 0 | E88: 0
B89: Trích trước lãi vay ngắn hạn Accrued Interest Expense | D89: 0 | E89: 0
B90: Gốc vay ngắn hạn Principal of Short-term loans | D90: 0 | E90: 0
A91: II.4 | B91: TỔNG NỢ TOTAL LIABILITIES | D91: 48469841796 | E91: 9044324391 | F91: 109.86221
B92: Tài sản ròng của Quỹ ( = I.10 - II.4) Net Asset Value ( = I.10 - II.4) | D92: 1022112366128 | E92: 361357528100 | F92: 3.705988
B93: Tổng số chứng chỉ quỹ đang lưu hành Total Outstanding Fund Certificates | D93: 1.0102596e+08 | E93: 36261654 | F93: 3.4678683
B94: Giá trị tài sản ròng trên một chứng chỉ quỹ Net Asset Value per Fund Certificate | D94: 10117.32 | E94: 9965.27 | F94: 1.0686651
A96: Đại diện có thẩm quyền của Ngân hàng giám sát | D96: Đại diện có thẩm quyền của Công ty quản lý Quỹ
A97: Authorised Representative of Supervisory Bank | D97: Authorised Representative of Fund Management Company
A105: Ngân hàng TNHH MTV Standard Chartered (Việt Nam) | D105: Công ty Cổ phần Quản lý Quỹ Đầu tư Dragon Capital Việt Nam
A106: Trịnh Hoài Nam | D106: Nguyễn Minh Đăng Khánh
A107: Phó phòng Dịch vụ Quản trị và Giám sát Quỹ | D107: Giám đốc điều hành Nghiệp vụ hỗ trợ đầu tư

Sheet BCKetQuaHoatDong_06028
A1: Phụ lục XXVI. Mẫu báo cáo về hoạt động của Quỹ Appendix XXVI. Report on Fund's Operation
A2: (Ban hành kèm theo Thông tư số 98/2020/TT-BTC ngày 16 tháng 11 năm 2020 của Bộ trưởng Bộ Tài Chính về hướng dẫn hoạt động và quản lý quỹ đầu tư chứng khoán) (Issued in association with Circular 98/2020/TT-BTC dated 16 November 2020 of the Minister of Finance on guiding the operation and management of the securities investment funds)
A3: BÁO CÁO VỀ HOẠT ĐỘNG ĐẦU TƯ REPORT ON INVESTMENT ACTIVITIES
A5: =TONGQUAN!C2 -> Quý III năm 2022 / Quarter III 2022
A7: Tên Công ty quản lý quỹ: | C7: =TONGQUAN!D5 -> Công ty Cổ phần Quản lý Quỹ Đầu tư Dragon Capital Việt Nam
A8: Fund Management Company: | C8: =TONGQUAN!D6 -> Dragon Capital Vietfund Management Joint Stock Company
A9: Tên ngân hàng giám sát: | C9: =TONGQUAN!D7 -> Ngân hàng TNHH Một thành viên Standard Chartered (Việt Nam)
A10: Supervising bank: | C10: =TONGQUAN!D8 -> Standard Chartered Bank (Vietnam) Limited
A11: Tên Quỹ: | C11: =TONGQUAN!D9 -> Quỹ Đầu tư Trái phiếu Gia tăng Thu nhập Cố định DC
A12: Fund name: | C12: =TONGQUAN!D10 -> DC Income Plus Bond Fund(VFMVFC)
A13: Ngày lập báo cáo: | C13: =TONGQUAN!D11 -> Ngày 05 tháng 10 năm 2022
A14: Reporting Date: | C14: =TONGQUAN!D12 -> 05 Oct 2022
A16: A. | B16: BÁO CÁO CHUNG VỀ HOẠT ĐỘNG ĐẦU TƯ CỦA QUỸ/GENERAL INFORMATION ON FUND'S INVESTMENT ACTIVITIES
A17: II | B17: BÁO CÁO KẾT QUẢ HOẠT ĐỘNG / PROFIT AND LOSS REPORT
A18: STT No | B18: Nội dung Indicator | C18: Mã chỉ tiêu Code | D18: Quý III năm 2022 Quarter III 2022 | E18: Quý II năm 2022 Quarter II 2022 | F18: Lũy kế từ đầu năm Accumulated from beginning of year
A19: I | B19: Thu nhập từ hoạt động đầu tư Income from Investment Activities | D19: 12859723014 | E19: 6148459931 | F19: 24194718123
A20: 1 | B20: Thu từ bất động sản cho thuê (không áp dụng) Income from rental property (not applicable)
A21: 2 | B21: Cổ tức, trái tức được nhận Dividend income, interest income from bonds | D21: 10091486299 | E21: 4489323424 | F21: 17664745301
B22: Cổ tức được nhận Dividends income | D22: 0 | E22: 0 | F22: 0
B23: Trái tức được nhận Interest income from bonds | D23: 10091486299 | E23: 4489323424 | F23: 17664745301
A24: 3 | B24: Lãi được nhận Interest income | D24: 2768236715 | E24: 1659136507 | F24: 6529972822
B25: Lãi tiền gửi ngân hàng Interest income from bank deposits | D25: 1372469591 | E25: 669355686 | F25: 2683328986
B26: Lãi chứng chỉ tiền gửi Interest income from Certificates of Deposit | D26: 1395767124 | E26: 989780821 | F26: 3846643836
B27: Lãi hợp đồng mua lại đảo ngược Interest income from reverse repo contracts | D27: 0 | E27: 0 | F27: 0
A28: 4 | B28: Các khoản thu nhập khác Other incomes | D28: 0 | E28: 0 | F28: 0
B29: Thu nhập khác về đầu tư Other investment incomes | D29: 0 | E29: 0 | F29: 0
B30: Thu nhập khác Other incomes | D30: 0 | E30: 0 | F30: 0
B31: Chi phí dự phòng nợ phải thu khó đòi về cổ tức, tiền lãi và xử lý tổn thất nợ phải thu khó đòi về cổ tức, tiền lãi Provision expense for bad debts from dividends, interest income and written off bad debts from dividends, interest income | D31: 0 | E31: 0 | F31: 0
A32: II | B32: Chi phí Expenses | D32: 2507766466 | E32: 1315919034 | F32: 4959858138
A33: 1 | B33: Chi phí quản lý trả cho Công ty quản lý quỹ Management Fee paid to Fund Management Company | D33: 1978054608 | E33: 921012824 | F33: 3713556681
A34: 2 | B34: Chi phí lưu ký, giám sát trả cho Ngân hàng Giám sát/VSD Custody fee, Supervising fee paid to Supervising Bank/VSD | D34: 149497260 | E34: 95106858 | F34: 337622865
B35: Chi phí dịch vụ lưu ký - bảo quản tài sản Custodian service - Safe Custody Fee | D35: 82418938 | E35: 38375536 | F35: 155651573
B36: Chi phí dịch vụ lưu ký - giao dịch chứng khoán Custodian service - Transaction fee | D36: 3300000 | E36: 1650000 | F36: 8200000
B37: Chi phí dịch vụ lưu ký cho chứng khoán cơ sở, phí quản lý vị thế và tài sản phái sinh trả cho VSD Custodian service - Depository fee, Position and Margin management fee paid to VSD | D37: 944348 | E37: 631322 | F37: 2037318
B38: Chi phí giám sát Supervisory fee | D38: 62833974 | E38: 54450000 | F38: 171733974
A39: 3 | B39: Chi phí quản trị quỹ và các chi phí khác mà công ty quản lý quỹ trả cho tổ chức cung cấp dịch vụ có liên quan Fund Administration Fee, and other fees paid to relevant Fund's service providers | D39: 154190599 | E39: 144787500 | F39: 443765599
B40: Chi phí quản trị Quỹ Fund Administration Fee | D40: 114590599 | E40: 111787500 | F40: 338165599
B41: Chi phí dịch vụ Đại lý Chuyển nhượng Transfer Agency Fee | D41: 39600000 | E41: 33000000 | F41: 105600000
A42: 4 | B42: Chi phí dịch vụ quản lý bất động sản (không áp dụng) Real Estate Management Service fee (not applicable)
A43: 5 | B43: Chi phí dịch vụ định giá bất động sản (không áp dụng) Real estate valuation service fees (not applicable)
A44: 6 | B44: Chi phí kiểm toán trả cho tổ chức kiểm toán Audit fee | D44: 29800768 | E44: 27359875 | F44: 80215438
A45: 7 | B45: Chi phí dịch vụ tư vấn pháp lý, dịch vụ báo giá và các dịch vụ hợp lý khác, thù lao trả cho ban đại diện quỹ Legal consultancy expenses, price feed fee, other valid expenses, remuneration paid to Fund's Board of Representatives | D45: 64375316 | E45: 51463569 | F45: 145058063
B46: Thù lao Ban đại diện Quỹ Remuneration of Fund's Board of Representatives | D46: 19141983 | E46: 22496903 | F46: 70858064
B47: Chi phí cung cấp báo giá chứng khoán Price feed fee | D47: 45233333 | E47: 28966666 | F47: 74199999
B48: Chi phí dịch vụ tư vấn pháp lý Legal consultancy expenses | D48: 0 | E48: 0 | F48: 0
A49: 8 | B49: Chi phí dự thảo, in ấn, gửi bản cáo bạch, bản cáo bạch tóm tắt, báo cáo tài chính, xác nhận giao dịch, sao kê tài khoản và các tài liệu khác cho nhà đầu tư; chi phí công bố thông tin của quỹ; chi phí tổ chức họp đại hội nhà đầu tư, ban đại diện quỹ Fee for drafting, printing, distribution of prospectus, summarised prospectus, financial statements, transaction confirmations, account statements and other documents to investors; information disclosure fee; fee for organising annual general meeting, board of representatives meeting | D49: 0 | E49: 0 | F49: 0
B50: Chi phí họp Đại hội Quỹ Meeting expenses | D50: 0 | E50: 0 | F50: 0
B51: Chi phí báo cáo thường niên Annual report expenses | D51: 0 | E51: 0 | F51: 0
B52: Chi phí họp, công tác của Ban đại diện Fund's Board of Representatives meeting, travelling expenses | D52: 0 | E52: 0 | F52: 0
B53: Chi phí công bố thông tin của Quỹ Expenses of information disclosure of the Fund | D53: 0 | E53: 0 | F53: 0
B54: Chi phí thiết kế, in ấn, gửi thư… Designing, printing, posting... expenses | D54: 0 | E54: 0 | F54: 0
A55: 9 | B55: Chi phí liên quan đến thực hiện các giao dịch tài sản của Quỹ Expenses related to execution of Fund’s asset transactions | D55: 89589215 | E55: 37874858 | F55: 138255696
B56: Chi phí môi giới Brokerage fee | D56: 74439215 | E56: 34814858 | F56: 119943696
B57: Chi phí thanh toán bù trừ Clearing settlement fee | D57: 150000 | E57: 60000 | F57: 312000
B58: Chi phí khác Other Expenses | D58: 15000000 | E58: 3000000 | F58: 18000000
A59: 10 | B59: Các loại chi phí khác Other expenses | D59: 42258700 | E59: 38313550 | F59: 101383796
B60: Chi phí thiết lập Quỹ Set up Expenses | D60: 0 | E60: 0 | F60: 0
B61: Phí niêm yết, đăng ký chứng khoán Listing, registration fees | D61: 0 | E61: 0 | F61: 0
B62: Phí quản lý thường niên trả cho UBCKNN Annual management fee paid to SSC | D62: 0 | E62: 0 | F62: 0
B63: Phí ngân hàng Bank charges | D63: 42258700 | E63: 38313550 | F63: 100283796
B64: Chi phí lãi vay Borrowing expense | D64: 0 | E64: 0 | F64: 0
B65: Chi phí khác Other Expenses | D65: 0 | E65: 0 | F65: 0
B66: Phí thực hiện quyền trả cho VSD Fee paid to VSD for getting the list of investors | D66: 0 | E66: 0 | F66: 1100000
A67: III | B67: Thu nhập ròng từ hoạt động đầu tư (= I - II) Net Income from Investment Activities (= I - II) | D67: 10351956548 | E67: 4832540897 | F67: 19234859985
A68: IV | B68: Lãi / (lỗ) từ hoạt động đầu tư Gain / (Loss) from Investment Activities | D68: -743823282 | E68: -205287438 | F68: -665886863
A69: 1 | B69: Lãi (lỗ) thực tế phát sinh từ hoạt động đầu tư hoặc chuyển nhượng bất động sản Realised Gain / (Loss) from disposal of investment or real estate transfer | D69: 128662233 | E69: -120048052 | F69: 484419112
A70: 2 | B70: Thay đổi về giá trị của các khoản đầu tư trong kỳ Unrealised Gain / (Loss) due to market price | D70: -872485515 | E70: -85239386 | F70: -1150305975
A71: V | B71: Thay đổi của giá trị tài sản ròng của Quỹ do các hoạt động đầu tư trong kỳ (III + IV) Change of Net Asset Value of the Fund due to investment activities during the period (= III + IV) | D71: 9608133266 | E71: 4627253459 | F71: 18568973122
A72: VI | B72: Giá trị tài sản ròng đầu kỳ Net Asset Value at the beginning of period | D72: 361357528100 | E72: 280164586481 | F72: 271332225925
A73: VII | B73: Thay đổi giá trị tài sản ròng của Quỹ trong kỳ Change of Net Asset Value of the Fund during the period | D73: 660754838028 | E73: 81192941619 | F73: 750780140203
B74: Trong đó: Of which:
A75: 1 | B75: Thay đổi giá trị tài sản ròng của Quỹ do các hoạt động đầu tư của Quỹ trong kỳ Change of Net Asset Value due to investment activities during the period | D75: 9608133266 | E75: 4627253459 | F75: 18568973122
A76: 2 | B76: Thay đổi giá trị tài sản ròng của Quỹ do việc chi trả lợi tức/ cổ tức của Quỹ cho các nhà đầu tư trong kỳ Change of Net Asset Value due to dividends payment to investors during the period | D76: 0 | E76: 0 | F76: 0
A77: 3 | B77: Thay đổi giá trị tài sản ròng do phát hành thêm/mua lại chứng chỉ quỹ Change of Net Asset Value due to subscription/redemption during the period | D77: =SUM(D78:D79) -> 651146704762 | E77: =SUM(E78:E79) -> 76565688160 | F77: =SUM(F78:F79) -> 732211167081
B78: Thay đổi giá trị tài sản ròng do phát hành thêm Chứng chỉ Quỹ Change of Net Asset Value due to subscription during the period | D78: 961853905123 | E78: 98241194677 | F78: 1075704446847
B79: Thay đổi giá trị tài sản ròng do mua lại Chứng chỉ Quỹ Change of Net Asset Value due to redemption during the period | D79: -310707200361 | E79: -21675506517 | F79: -343493279766
A80: VIII | B80: Giá trị tài sản ròng cuối kỳ Net Asset Value at the end of period | D80: 1022112366128 | E80: 361357528100 | F80: 1022112366128
A81: IX | B81: Lợi nhuận bình quân năm (chỉ áp dụng đối với báo cáo năm) Average annual profit (only applicable to annual report) | D81: 0 | E81: 0 | F81: 0
B82: Tỷ suất lợi nhuận bình quân năm (chỉ áp dụng đối với báo cáo năm) Average annual rate of return (only applicable to annual report) | D82: 0 | E82: 0 | F82: 0
A85: =TONGQUAN!C16 -> Đại diện có thẩm quyền của Ngân hàng giám sát | D85: =TONGQUAN!F16 -> Đại diện có thẩm quyền của Công ty quản lý Quỹ
A86: =TONGQUAN!C17 -> Authorised Representative of Supervisory Bank | D86: =TONGQUAN!F17 -> Authorised Representative of Fund Management Company
A94: =TONGQUAN!C19 -> Ngân hàng TNHH MTV Standard Chartered (Việt Nam) | D94: =TONGQUAN!F19 -> Công ty Cổ phần Quản lý Quỹ Đầu tư Dragon Capital Việt Nam
A95: =TONGQUAN!C20 -> Trịnh Hoài Nam | D95: =TONGQUAN!F20 -> Nguyễn Minh Đăng Khánh
A96: =TONGQUAN!C21 -> Phó phòng Dịch vụ Quản trị và Giám sát Quỹ | D96: =TONGQUAN!F21 -> Giám đốc điều hành Nghiệp vụ hỗ trợ đầu tư

Sheet BCDanhMucDauTu_06029
A1: Phụ lục số 03. Mẫu báo cáo hoạt động đầu tư của quỹ mở Appendix 03. Report on Open ended Fund's Investment Activities
A2: (Ban hành kèm theo Thông tư số 91/2019/TT-BTC ngày 31 tháng 12 năm 2019 của Bộ trưởng Bộ Tài chính sửa đổi, bổ sung một số Thông tư quy định về chế độ báo cáo và thủ tục hành chính áp dụng với công ty quản lý quỹ, quỹ đầu tư chứng khoán và công ty đầu tư chứng khoán) (Issued in association with Circular 91/2019/TT-BTC dated 31 December 2019 of the Minister of Finance on amending and supplementing several Circulars on the reporting regime and administrative procedures applicable to fund management company, investment fund and investment company)
A3: BÁO CÁO HOẠT ĐỘNG ĐẦU TƯ CỦA QUỸ MỞ REPORT ON OPEN ENDED FUND'S INVESTMENT ACTIVITIES
A5: =TONGQUAN!C1 -> Tại ngày 30 tháng 09 năm 2022 / As at 30 Sep 2022
A7: Tên Công ty quản lý quỹ: | C7: =TONGQUAN!D5 -> Công ty Cổ phần Quản lý Quỹ Đầu tư Dragon Capital Việt Nam
A8: Fund Management Company: | C8: =TONGQUAN!D6 -> Dragon Capital Vietfund Management Joint Stock Company
A9: Tên ngân hàng giám sát: | C9: =TONGQUAN!D7 -> Ngân hàng TNHH Một thành viên Standard Chartered (Việt Nam)
A10: Supervising bank: | C10: =TONGQUAN!D8 -> Standard Chartered Bank (Vietnam) Limited
A11: Tên Quỹ: | C11: =TONGQUAN!D9 -> Quỹ Đầu tư Trái phiếu Gia tăng Thu nhập Cố định DC
A12: Fund name: | C12: =TONGQUAN!D10 -> DC Income Plus Bond Fund(VFMVFC)
A13: Ngày lập báo cáo: | C13: =TONGQUAN!D11 -> Ngày 05 tháng 10 năm 2022
A14: Reporting Date: | C14: =TONGQUAN!D12 -> 05 Oct 2022
A17: III | B17: BÁO CÁO DANH MỤC ĐẦU TƯ / INVESTMENT PORTFOLIO REPORT
A18: STT No. | B18: Loại Category | C18: Mã chỉ tiêu Code | D18: Số Lượng Quantity | E18: Giá thị trường hoặc giá trị hợp lý tại ngày báo cáo Market price | F18: Tổng giá trị (Đồng) Value (VND) | G18: Tỷ lệ % Tổng giá trị tài sản của Quỹ % of total asset
A19: I | B19: BẤT ĐỘNG SẢN ĐẦU TƯ (KHÔNG ÁP DỤNG) REAL ESTATE INVESTMENT (NOT APPLICABLE)
A20: II | B20: CỔ PHIẾU NIÊM YẾT, ĐĂNG KÝ GIAO DỊCH, CHỨNG CHỈ QUỸ NIÊM YẾT SHARES LISTED, SHARES REGISTERED FOR TRADING, LISTED FUND CERTIFICATES
B21: TỔNG TOTAL
A22: III | B22: CỔ PHIẾU CHƯA NIÊM YẾT, ĐĂNG KÝ GIAO DỊCH, CHỨNG CHỈ QUỸ KHÔNG NIÊM YẾT SHARES UNLISTED, UNREGISTERED FOR TRADING, UNLISTED FUND CERTIFICATES
B23: TỔNG TOTAL | D23: 0 | F23: 0 | G23: 0
B24: TỔNG CÁC LOẠI CỔ PHIẾU TOTAL SHARES
A25: IV | B25: TRÁI PHIẾU BONDS
A26: 1 | B26: Trái phiếu niêm yết Listed bonds | F26: 576115043700 | G26: 0.53813247
A27: 1.1 | B27: BCG122006 | D27: 200000 | E27: 99924 | F27: 19984800000 | G27: 0.018667226
A28: 1.2 | B28: CII121029 | D28: 1070000 | E28: 99785 | F28: 106769950000 | G28: 0.099730735
A29: 1.3 | B29: KBC121020 | D29: 1170000 | E29: 101073 | F29: 118255410000 | G29: 0.11045897
A30: 1.4 | B30: MSN12003 | D30: 1300000 | E30: 100129 | F30: 130167700000 | G30: 0.1215859
A31: 1.5 | B31: MSN121015 | D31: 100000 | E31: 100199 | F31: 10019900000 | G31: 0.0093592999
A32: 1.6 | B32: TNG119007 | D32: 15 | E32: 1001464780 | F32: 15021971700 | G32: 0.014031591
A33: 1.7 | B33: TNG122017 | D33: 159200 | E33: 100360 | F33: 15977312000 | G33: 0.014923947
A34: 1.8 | B34: VND122013 | D34: 1400000 | E34: 99932 | F34: 139904800000 | G34: 0.13068104
A35: 1.9 | B35: VND122014 | D35: 200000 | E35: 100066 | F35: 20013200000 | G35: 0.018693754
A36: 2 | B36: Trái phiếu chưa niêm yết Unlisted Bonds | F36: 99082914650 | G36: 0.092550496
A37: 2.1 | B37: DAT XANH GROUP JSC 12% 18 Mar 2023 | D37: 280 | E37: 100285698 | F37: 28079995440 | G37: 0.026228715
A38: 2.2 | B38: KDH TRADING & INV JSC 12% 14/06/2025 | D38: 10 | E38: 1000000000 | F38: 10000000000 | G38: 0.0093407119
A39: 2.3 | B39: KDH TRADING & INV JSC 12% 23/08/2025 | D39: 40 | E39: 1000000000 | F39: 40000000000 | G39: 0.037362848
A40: 2.4 | B40: PDR BOND 12 PCT 02 DEC 2023 | D40: 210 | E40: 100013901 | F40: 21002919210 | G40: 0.019618222
B41: TỔNG TOTAL | F41: 675197958350 | G41: 0.63068296
A42: V | B42: CÁC LOẠI CHỨNG KHOÁN KHÁC OTHER SECURITIES
A43: 1 | B43: Quyền mua chứng khoán Investment - Rights | D43: 0 | F43: 0 | G43: 0
A44: 2 | B44: Chi tiết loại hợp đồng phái sinh(*) Index future contracts | D44: 0 | F44: 0 | G44: 0
B45: TỔNG TOTAL | F45: 0 | G45: 0
B46: TỔNG CÁC LOẠI CHỨNG KHOÁN TOTAL TYPES OF SECURITIES | F46: 675197958350 | G46: 0.63068296
A47: VI | B47: CÁC TÀI SẢN KHÁC OTHER ASSETS
A48: 1 | B48: Cổ tức được nhận Dividend receivables | F48: 0 | G48: 0
A49: 2 | B49: Lãi trái phiếu được nhận Coupon receivables | F49: 19742010958 | G49: 0.018440444
A50: 3 | B50: Lãi tiền gửi và chứng chỉ tiền gửi được nhận Interest receivables from bank deposits and certificates of deposit | F50: 6944326578 | G50: 0.0064864954
A51: 4 | B51: Tiền bán chứng khoán chờ thu Outstanding Settlement of sales transactions | F51: 0 | G51: 0
A52: 5 | B52: Phải thu cho khoản cổ phiếu hạn chế chờ mua Receivable from AP/Investors on securities on hold of buying | F52: 0 | G52: 0
A53: 6 | B53: Phải thu khác Other receivables | F53: 110000 | G53: 1.0274783e-07
A54: 7 | B54: Tài sản khác Other assets | F54: 0 | G54: 0
B55: TỔNG TOTAL | F55: 26686447536 | G55: 0.024927042
A56: VII | B56: TIỀN CASH
A57: 1 | B57: Tiền, tương đương tiền Cash, Cash Equivalents | F57: =SUM(F58:F59) -> 147951287500 | G57: =SUM(G58:G59) -> 0.13819704
A58: 1.1 | B58: Tiền gửi ngân hàng Cash at Bank | F58: 78951287500 | G58: 0.073746123
A59: 1.2 | B59: Các khoản tương đương tiền Cash Equivalents | F59: 69000000000 | G59: 0.064450912
A60: 2 | B60: Tiền gửi ngân hàng có kỳ hạn trên 3 tháng Deposits with term over three (03) months | F60: 30600000000 | G60: 0.028582579
A61: 3 | B61: Chứng chỉ tiền gửi Certificates of deposit | F61: 190146514538 | G61: 0.17761038
A62: 4 | B62: Công cụ chuyển nhượng… Transferable instruments… | F62: 0 | G62: 0
B63: TỔNG TOTAL | F63: =SUM(F62,F61,F60,F57) -> 368697802038 | G63: =SUM(G62,G61,G60,G57) -> 0.34439
A64: VIII | B64: Tổng giá trị danh mục Total value of portfolio | F64: 1070582207924 | G64: 1
A66: Đại diện có thẩm quyền của Ngân hàng giám sát | E66: Đại diện có thẩm quyền của Công ty quản lý Quỹ
A67: Authorised Representative of Supervisory Bank | E67: Authorised Representative of Fund Management Company
A76: Ngân hàng TNHH MTV Standard Chartered (Việt Nam) | E76: Công ty Cổ phần Quản lý Quỹ Đầu tư Dragon Capital Việt Nam
A77: Trịnh Hoài Nam | E77: Nguyễn Minh Đăng Khánh
A78: Phó phòng Dịch vụ Quản trị và Giám sát Quỹ | E78: Giám đốc điều hành Nghiệp vụ hỗ trợ đầu tư

Sheet BCHoatDongVay_06026
A1: Phụ lục XXVI. Mẫu báo cáo về hoạt động của Quỹ Appendix XXVI. Report on Fund's Operation
A2: (Ban hành kèm theo Thông tư số 98/2020/TT-BTC ngày 16 tháng 11 năm 2020 của Bộ trưởng Bộ Tài Chính về hướng dẫn hoạt động và quản lý quỹ đầu tư chứng khoán) (Issued in association with Circular 98/2020/TT-BTC dated 16 November 2020 of the Minister of Finance on guiding the operation and management of the securities investment funds)
A3: BÁO CÁO VỀ HOẠT ĐỘNG ĐẦU TƯ REPORT ON INVESTMENT ACTIVITIES
A5: =TONGQUAN!C2 -> Quý III năm 2022 / Quarter III 2022
A7: Tên Công ty quản lý quỹ: | G7: =TONGQUAN!D5 -> Công ty Cổ phần Quản lý Quỹ Đầu tư Dragon Capital Việt Nam
A8: Fund Management Company: | G8: =TONGQUAN!D6 -> Dragon Capital Vietfund Management Joint Stock Company
A9: Tên ngân hàng giám sát: | G9: =TONGQUAN!D7 -> Ngân hàng TNHH Một thành viên Standard Chartered (Việt Nam)
A10: Supervising bank: | G10: =TONGQUAN!D8 -> Standard Chartered Bank (Vietnam) Limited
A11: Tên Quỹ: | G11: =TONGQUAN!D9 -> Quỹ Đầu tư Trái phiếu Gia tăng Thu nhập Cố định DC
A12: Fund name: | G12: =TONGQUAN!D10 -> DC Income Plus Bond Fund(VFMVFC)
A13: Ngày lập báo cáo: | G13: =TONGQUAN!D11 -> Ngày 05 tháng 10 năm 2022
A14: Reporting Date: | G14: =TONGQUAN!D12 -> 05 Oct 2022
A15: A. | B15: BÁO CÁO CHUNG VỀ HOẠT ĐỘNG ĐẦU TƯ CỦA QUỸ/GENERAL INFORMATION ON FUND'S INVESTMENT ACTIVITIES
A16: IV | B16: BÁO CÁO HOẠT ĐỘNG VAY, GIAO DỊCH MUA BÁN LẠI / REPORT ON BORROWING OPERATION, REPO/REVERSE REPO TRANSACTIONS
A17: STT No. | B17: Nội dung hoạt động (nêu chi tiết theo mục tiêu và đối tác) Description | C17: Mã chỉ tiêu Code | D17: Đối tác Counterparty | E17: Mục tiêu/Tài sản đảm bảo Collateral | F17: Kỳ hạn Term | G17: Giá trị khoản vay hoặc khoản cho vay Amount | H17: Thời điểm giao dịch As at transaction date | J17: Thời điểm báo cáo As at reporting date
H18: Ngày tháng năm Date | I18: Tỷ lệ giá trị hợp đồng/giá trị tài sản ròng của quỹ Balance/NAV | J18: Ngày tháng năm Date | K18: Tỷ lệ giá trị hợp đồng/giá trị tài sản ròng của quỹ Balance/NAV
A19: 1 | B19: Các khoản vay tiền (nêu chi tiết từng hợp đồng) Borrowings (detail by each contract)
A20: I | B20: Tổng giá trị các khoản vay tiền/giá trị tài sản ròng Borrowings/NAV
A21: 2 | B21: Hợp đồng Repo (nêu chi tiết từng hợp đồng) Repo contract (detail by each contract)
A22: II | B22: Tổng giá trị các hợp đồng Repo/giá trị tài sản ròng Total value of Repo contracts/NAV
A23: A | B23: Tổng giá trị các khoản vay/giá trị tài sản ròng (=I+II) Total Borrowings, Repo/NAV (=I+II)
A24: 3 | B24: Cho vay chứng khoán (nêu chi tiết từng hợp đồng) Securities lending (detail by each contract)
A25: III | B25: Tổng giá trị các hợp đồng/giá trị tài sản ròng Total contract value/NAV
A26: 4 | B26: Hợp đồng Reverse Repo (nêu chi tiết từng hợp đồng) Reverse Repo contract (Detail by each contract)
A27: IV | B27: Tổng giá trị các hợp đồng/giá trị tài sản ròng Total contract value/NAV
A28: B | B28: Tổng giá trị các khoản cho vay/giá trị tài sản ròng (=III + IV) Total Loans/NAV (=III + IV)
A33: Đại diện có thẩm quyền của Ngân hàng giám sát | I33: Đại diện có thẩm quyền của Công ty quản lý Quỹ
A34: Authorised Representative of Supervisory Bank | I34: Authorised Representative of Fund Management Company
A44: Ngân hàng TNHH MTV Standard Chartered (Việt Nam) | I44: =TONGQUAN!F19 -> Công ty Cổ phần Quản lý Quỹ Đầu tư Dragon Capital Việt Nam
A45: =TONGQUAN!C20 -> Trịnh Hoài Nam | I45: =TONGQUAN!F20 -> Nguyễn Minh Đăng Khánh
A46: =TONGQUAN!C21 -> Phó phòng Dịch vụ Quản trị và Giám sát Quỹ | I46: =TONGQUAN!F21 -> Giám đốc điều hành Nghiệp vụ hỗ trợ đầu tư

Sheet Khac_06030
A1: Phụ lục XXVI. Mẫu báo cáo về hoạt động của Quỹ Appendix XXVI. Report on Fund's Operation
A2: (Ban hành kèm theo Thông tư số 98/2020/TT-BTC ngày 16 tháng 11 năm 2020 của Bộ trưởng Bộ Tài chính về hướng dẫn hoạt động và quản lý quỹ đầu tư chứng khoán) (Issued in association with Circular 98/2020/TT-BTC dated 16 November 2020 of the Minister of Finance on guiding the operation and management of the securities investment funds)
A3: BÁO CÁO VỀ HOẠT ĐỘNG ĐẦU TƯ REPORT ON INVESTMENT ACTIVITIES
A5: =TONGQUAN!C2 -> Quý III năm 2022 / Quarter III 2022
A7: Tên Công ty quản lý quỹ: | C7: =TONGQUAN!D5 -> Công ty Cổ phần Quản lý Quỹ Đầu tư Dragon Capital Việt Nam
A8: Fund Management Company: | C8: =TONGQUAN!D6 -> Dragon Capital Vietfund Management Joint Stock Company
A9: Tên ngân hàng giám sát: | C9: =TONGQUAN!D7 -> Ngân hàng TNHH Một thành viên Standard Chartered (Việt Nam)
A10: Supervising bank: | C10: =TONGQUAN!D8 -> Standard Chartered Bank (Vietnam) Limited
A11: Tên Quỹ: | C11: =TONGQUAN!D9 -> Quỹ Đầu tư Trái phiếu Gia tăng Thu nhập Cố định DC
A12: Fund name: | C12: =TONGQUAN!D10 -> DC Income Plus Bond Fund(VFMVFC)
A13: Ngày lập báo cáo: | C13: =TONGQUAN!D11 -> Ngày 05 tháng 10 năm 2022
A14: Reporting Date: | C14: =TONGQUAN!D12 -> 05 Oct 2022
A16: A. | B16: BÁO CÁO CHUNG VỀ HOẠT ĐỘNG ĐẦU TƯ CỦA QUỸ/GENERAL INFORMATION ON FUND'S INVESTMENT ACTIVITIES
A17: V | B17: MỘT SỐ CHỈ TIÊU KHÁC / OTHER INDICATORS
A18: STT No | B18: Chỉ tiêu Indicators | C18: Mã chỉ tiêu Code | D18: =BCKetQuaHoatDong_06028!D18 -> Quý III năm 2022 Quarter III 2022 | E18: =BCKetQuaHoatDong_06028!E18 -> Quý II năm 2022 Quarter II 2022
A19: I | B19: CÁC CHỈ TIÊU VỀ HIỆU QUẢ HOẠT ĐỘNG INVESTMENT PERFORMANCE INDICATORS
A20: 1 | B20: Tỷ lệ giá dịch vụ quản lý quỹ trả cho công ty quản lý quỹ/Giá trị tài sản ròng trung bình trong kỳ (%) Management fee paid to the fund management company/Average NAV (%) | D20: 0.012099482 | E20: 0.011968038
A21: 2 | B21: Tỷ lệ giá dịch vụ lưu ký, giám sát trả cho Ngân hàng Giám sát/Giá trị tài sản ròng trung bình trong kỳ (%) Custody and supervising fees paid to the Supervisory Bank/Average NAV (%) | D21: 0.00090867726 | E21: 0.0012276559
A22: 3 | B22: Tỷ lệ chi phí dịch vụ quản trị quỹ, và các chi phí khác mà công ty quản lý quỹ trả cho tổ chức cung cấp dịch vụ có liên quan/Giá trị tài sản ròng của quỹ trung bình trong kỳ (%) Fund admin fee, and other fees paid to relating services providers by the fund management company/Average NAV (%) | D22: 0.00094893864 | E22: 0.0018896349
A23: 4 | B23: Chi phí kiểm toán trả cho tổ chức kiểm toán (nếu phát sinh)/Giá trị tài sản ròng trung bình trong kỳ (%) Auditing fee paid to auditing organizations (if any)/Average NAV (%) | D23: 0.0001822871 | E23: 0.00035552602
A24: 5 | B24: Chi phí trả cho tổ chức quản lý bất động sản/ Giá trị tài sản ròng trung bình trong kỳ (%) (không áp dụng) Fee paid to Real Estate management organisation/ Average NAV (%) (not applicable)
A25: 6 | B25: Chi phí trả cho doanh nghiệp thẩm định giá bất động sản/Giá trị tài sản ròng trung bình trong kỳ (%) (không áp dụng) Fee paid to Real Estate valuation service provider/ Average NAV (%) (not applicable)
A26: 7 | B26: Chi phí dịch vụ tư vấn pháp lý, dịch vụ báo giá và các dịch vụ hợp lý khác, thù lao trả cho ban đại diện quỹ/Giá trị tài sản ròng trung bình trong kỳ (%) Legal consultancy, price quotation and other appropriate service fees; remunerations paid to the Board of Representatives/Average NAV (%) | D26: 0.00039377475 | E26: 0.00066873981
A27: 8 | B27: Tỷ lệ chi phí /Giá trị tài sản ròng trung bình trong kỳ (%) Expense/Average NAV (%) | D27: 0.015339655 | E27: 0.01709962
A28: 9 | B28: Tốc độ vòng quay danh mục trong kỳ (%) = (Tổng giá trị mua vào + tổng giá trị bán ra) x 100%/ (2 x Giá trị tài sản ròng trung bình trong kỳ) Portfolio turnover rate (%) = (Total value of purchase transactions + total value of sales transactions) x 100%/ (2 x Average NAV) (**) | D28: 2.0773447 | E28: 1.3649621
A29: 10 | B29: Tỷ lệ thu nhập (tính cả thu nhập từ lãi, cổ tức, trái tức, chênh lệch giá)/ Giá trị tài sản ròng (không áp dụng) Income (including interest income, dividend, coupon income and unrealised gain)/ Average NAV (%) (not applicable)
A30: II | B30: CÁC CHỈ TIÊU KHÁC OTHER INDICATORS
A31: 1 | B31: Quy mô quỹ đầu kỳ (tính theo mệnh giá chứng chỉ quỹ) Fund scale at the beginning of the period (based on par value of fund certificate) | D31: 362616543400 | E31: 285398566800
B32: Tổng giá trị chứng chỉ quỹ đang lưu hành đầu kỳ Total value of outstanding Fund Certificate at the beginning of period | D32: 362616543400 | E32: 285398566800
B33: Tổng số lượng chứng chỉ quỹ đang lưu hành đầu kỳ Total number of outstanding Fund Certificate at the beginning of period | D33: 36261654 | E33: 28539857
A34: 2 | B34: Thay đổi quy mô quỹ trong kỳ (tính theo mệnh giá chứng chỉ quỹ) Change of Fund scale during the period (based on par value of fund certificate) | D34: 647643049800 | E34: 77217976600
B35: Thay đổi số lượng chứng chỉ quỹ trong kỳ Change of Number of Fund Certificates during the period | D35: 64764305 | E35: 7721797.7
B36: Thay đổi giá trị vốn trong kỳ (theo mệnh giá) Change in capital amount during the period (based on par value) | D36: 647643049800 | E36: 77217976600
B37: Số lượng chứng chỉ quỹ phát hành thêm trong kỳ Number of Fund Certificates subscribed during the period | D37: 95583679 | E37: 9909715.7
B38: Giá trị vốn huy động thêm trong kỳ (theo mệnh giá) Net subscription amount during the period (based on par value) | D38: 955836791500 | E38: 99097156700
B39: Số lượng chứng chỉ quỹ mua lại trong kỳ (theo mệnh giá) Number of Fund Certificates redeemed during the period | D39: -30819374 | E39: -2187918
B40: Giá trị vốn phải thanh toán trong kỳ khi đáp ứng lệnh của nhà đầu tư (theo mệnh giá) Net redemption amount during the period (based on par value) | D40: -308193741700 | E40: -21879180100
A41: 3 | B41: Quy mô quỹ cuối kỳ (tính theo mệnh giá chứng chỉ quỹ) Fund scale at the end of the period (based on par value) | D41: 1010259593200 | E41: 362616543400
B42: Tổng giá trị thị trường của quỹ đang lưu hành cuối kỳ (theo mệnh giá) Total value of outstanding Fund Certificate at the end of the period (based on par value) | D42: 1010259593200 | E42: 362616543400
B43: Tổng số lượng chứng chỉ quỹ đang lưu hành cuối kỳ Total number of outstanding Fund Certificate at the end of the period | D43: 1.0102596e+08 | E43: 36261654
A44: 4 | B44: Tỷ lệ nắm giữ chứng chỉ quỹ của công ty quản lý quỹ và người có liên quan cuối kỳ Fund Management Company and related parties' ownership ratio at the end of the period | D44: 0.26714057 | E44: 0.73722791
A45: 5 | B45: Tỷ lệ nắm giữ chứng chỉ quỹ của 10 nhà đầu tư lớn nhất cuối kỳ Top 10 investors' ownership ratio at the end of the period | D45: 0.4081 | E45: 0.8061
A46: 6 | B46: Tỷ lệ nắm giữ chứng chỉ quỹ của nhà đầu tư nước ngoài cuối kỳ Foreign investors' ownership ratio at the end of the period | D46: 0.0009 | E46: 0.0025
A47: 7 | B47: Giá trị tài sản ròng trên một đơn vị quỹ cuối kỳ Net asset value per Fund Certificate at the end of period | D47: 10117.32 | E47: 9965.27
A48: 8 | B48: Giá trị thị trường trên một chứng chỉ quỹ/cổ phiếu cuối kỳ (không áp dụng) Market price per fund certificates at the end of period (not applicable)
A49: 9 | B49: Số nhà đầu tư tham gia vào quỹ, kể cả giao dịch ký danh Number of investors of the Fund at the end of the period | D49: 14545 | E49: 8924
A50: Ghi chú / Notes:
A51: Các chỉ tiêu từ 1 đến 10 của "Chỉ tiêu về hiệu quả hoạt động" đã được điều chỉnh để phản ánh số liệu trên cơ sở hoạt động tròn năm bằng cách nhân các chỉ tiêu này với 12 (đối với báo cáo tháng), 4 (đối với báo cáo quý), 2 (đối với báo cáo bán niên), 1 (đối với báo cáo năm). All Indicator starting from number 1 to 710 of "Investment performance indicators" are annualized to reflect a rate that is based on a full year operation by multiplying these indicators with 12 (monthly report) or 4 (quarterly report) or 2 (semi-annual report) or 1 (annual report).
A52: (**) Không tính đến giá trị cam kết của các hợp đồng tương lai chỉ số. Excluding the committed value of the Index Futures contracts.
A54: =TONGQUAN!C16 -> Đại diện có thẩm quyền của Ngân hàng giám sát | D54: =TONGQUAN!F16 -> Đại diện có thẩm quyền của Công ty quản lý Quỹ
A55: =TONGQUAN!C17 -> Authorised Representative of Supervisory Bank | D55: =TONGQUAN!F17 -> Authorised Representative of Fund Management Company
A65: =TONGQUAN!C19 -> Ngân hàng TNHH MTV Standard Chartered (Việt Nam) | D65: =TONGQUAN!F19 -> Công ty Cổ phần Quản lý Quỹ Đầu tư Dragon Capital Việt Nam
A66: =TONGQUAN!C20 -> Trịnh Hoài Nam | D66: =TONGQUAN!F20 -> Nguyễn Minh Đăng Khánh
A67: =TONGQUAN!C21 -> Phó phòng Dịch vụ Quản trị và Giám sát Quỹ | D67: =TONGQUAN!F21 -> Giám đốc điều hành Nghiệp vụ hỗ trợ đầu tư
