Workbook
Name addlogo: INDEX(LogoFMS!$C$3:$C$39,MATCH(LogoFMS!$D$1,LogoFMS!$A$3:$A$39,0))

Sheet Tong quat
A1: Kỳ báo cáo: | C1: Tại ngày 31 tháng 10 năm 2019 / As at 31 Oct 2019
C2: Tháng 10 năm 2019 / Oct 2019
A4: Thông tin chung:
C5: Tên Công ty quản lý quỹ: | D5: Công ty Cổ phần Quản lý Quỹ Đầu tư Việt Nam
C6: Fund Management Company: | D6: Vietnam Investment Fund Management Joint Stock Company
C7: Tên ngân hàng giám sát: | D7: Ngân hàng TNHH Một thành viên Standard Chartered (Việt Nam)
C8: Supervising bank: | D8: Standard Chartered Bank (Vietnam) Limited
C9: Tên Quỹ: | D9: Quỹ Đầu tư Chứng khoán Việt Nam
C10: Fund name: | D10: Vietnam Securities Investment Fund(VFMVF1)
C11: Ngày lập báo cáo: | D11: Ngày 04 tháng 11 năm 2019
C12: Reporting Date: | D12: 04 Nov 2019
A14: Người ký báo cáo:
C16: Đại diện có thẩm quyền của Ngân hàng giám sát | F16: Đại diện có thẩm quyền của Công ty quản lý Quỹ
C17: Authorised Representative of Supervisory Bank | F17: Authorised Representative of Fund Management Company
C19: Ngân hàng TNHH MTV Standard Chartered (Việt Nam) | F19: =D5 -> Công ty Cổ phần Quản lý Quỹ Đầu tư Việt Nam
C20: Vũ Hương Giang | F20: Trần Thanh Tân
C21: Phó phòng Nghiệp vụ Dịch vụ Chứng khoán | F21: Tổng Giám đốc
B34: STT | C34: Nội dung | D34: Tên sheet
B35: 1 | C35: Báo cáo về tài sản của quỹ | D35: 06027
B36: 2 | C36: Báo cáo kết quả hoạt động | D36: 06028
B37: 3 | C37: Báo cáo danh mục đầu tư của quỹ | D37: 06029
B38: 4 | C38: Một số chỉ tiêu khác | D38: 06030
B39: 5 | C39: Báo cáo thay đổi giá trị tài sản ròng, giao dịch chứng chỉ quỹ | D39: 06129
B40: 6 | C40: Báo cáo thu nhập giữa niên độ | D40: 06203
B41: 7 | C41: Báo cáo tình hình tài chính giữa niên độ | D41: 06105
B42: 8 | C42: Báo cáo thay đổi giá trị tài sản ròng, giao dịch chứng chỉ quỹ giữa niên độ | D42: 06107
B43: 9 | C43: Báo cáo danh mục đầu tư | D43: 06108
B44: 10 | C44: Báo cáo lưu chuyển tiền tệ | D44: 06262
B45: 11 | C45: Báo cáo thu nhập | D45: 06104
B46: 12 | C46: Báo cáo về tài sản của quỹ | D46: 06126
B48: Thống kê các Thuyết minh BCTC
D50: Có trình bày Y/N/O | E50: Nguyên nhân không trình bày
B51: 1/ | C51: Tiền gửi Ngân hàng | D51: Y
B52: 2/ | C52: Các khoản đầu tư | D52: Y
B53: 3/ | C53: Các khoản dự phòng | D53: O | E53: Chỉ có VF1 trình bày, các Quỹ khác không có khoản mục này không phải trình bày
B54: 4/ | C54: Vay ngắn hạn | D54: N | E54: Không có số dư không trình bày
B55: 5/ | C55: Phải trả mua các khoản đầu tư | D55: N | E55: Không có số dư không trình bày
B56: 6/ | C56: Phải trả các Đại lý phân phối, Công ty Quản lý quỹ về phí phát hành và mua lại Chứng chỉ quỹ | D56: N | E56: Trên báo cáo chính đã chi tiết theo từng khoản mục
B57: 7/ | C57: Thuế và các khoản phải nộp Nhà nước | D57: N | E57: Không bắt buộc, Quỹ chỉ có khoản mục thuế từ hoạt động mua bán CCQ và Thù lao BDD
B58: 8/ | C58: Phải trả thu nhập cho Nhà đầu tư | D58: N | E58: Quỹ nào có chia cổ tức mới trình bày
B59: 9/ | C59: Chi phí phải trả | D59: N | E59: Trên báo cáo chính đã chi tiết theo từng khoản mục
B60: 10/ | C60: Phải trả dịch vụ quản lý quỹ | D60: N | E60: Trên báo cáo chính đã chi tiết theo từng khoản mục
B61: 11/ | C61: Phải trả, phải nộp khác | D61: Y | E61: Chi tiết theo nature khoản mục của từng quỹ
B62: 12/ | C62: Tình hình biến động vốn chủ sở hữu | D62: Y
B63: 13/ | C63: Lợi nhuận chưa phân phối | D63: Y
B64: 14/ | C64: Lãi, lỗ bán các khoản đầu tư | D64: Y | E64: Tính toán lại dựa trên Báo cáo Sale and Purchase Report, checking với cân đối
B65: 15/ | C65: Chênh lệch đánh giá lại các khoản đầu tư | D65: Y | E65: Dựa trên báo cáo Portfolio Valuation
B66: 16/ | C66: Doanh thu hoạt động đầu tư | D66: Y
B67: 17/ | C67: Chi phí giao dịch mua các khoản đầu tư | D67: N | E67: Hệ thống ko support nhặt số liệu báo cáo này
B68: 18/ | C68: Chi phí giao dịch bán các khoản đầu tư | D68: N | E68: Hệ thống ko support nhặt số liệu báo cáo này
B69: 19/ | C69: Chi phí đầu tư | D69: N | E69: Trên báo cáo chính đã chi tiết theo từng khoản mục
B70: 20/ | C70: Chi phí quản lý Quỹ mở | D70: N | E70: Trên báo cáo chính đã chi tiết theo từng khoản mục
B71: 21/ | C71: Thuyết minh về giá trị tài sản ròng | D71: Y | E71: Thống kê theo từng kỳ NAV
B72: 22/ | C72: Thuyết minh về danh mục các khoản đầu tư | D72: N | E72: Báo cáo theo thông tư 183 đã có thông tin
B73: 23/ | C73: Thuyết minh về các Tài khoản loại 0 | D73: N | E73: Không có
B74: 24/ | C74: Những thông tin khác | D74: N | E74: Không bắt buộc trình bày

Sheet BCthunhap
A1: Mẫu số B01g - QM. Báo cáo thu nhập Template B01g - QM. Statement of Comprehensive Income
A2: (Ban hành kèm theo Thông tư 198/2012/TT-BTC ngày 15 tháng 11 năm 2012 về chế độ kế toán áp dụng đối với quỹ mở) (Issued in association with Circular 198/2012/TT-BTC dated 15 Nov 2012 on the Accounting Policies for Open-Ended Fund)
A3: BÁO CÁO THU NHẬP STATEMENT OF COMPREHENSIVE INCOME
A5: ='Tong quat'!C2 -> Tháng 10 năm 2019 / Oct 2019
A7: Tên Công ty quản lý quỹ: | D7: ='Tong quat'!D5 -> Công ty Cổ phần Quản lý Quỹ Đầu tư Việt Nam
A8: Fund Management Company: | D8: ='Tong quat'!D6 -> Vietnam Investment Fund Management Joint Stock Company
A9: Tên ngân hàng giám sát: | D9: ='Tong quat'!D7 -> Ngân hàng TNHH Một thành viên Standard Chartered (Việt Nam)
A10: Supervising bank: | D10: ='Tong quat'!D8 -> Standard Chartered Bank (Vietnam) Limited
A11: Tên Quỹ: | D11: ='Tong quat'!D9 -> Quỹ Đầu tư Chứng khoán Việt Nam
A12: Fund name: | D12: ='Tong quat'!D10 -> Vietnam Securities Investment Fund(VFMVF1)
A13: Ngày lập báo cáo: | D13: ='Tong quat'!D11 -> Ngày 04 tháng 11 năm 2019
A14: Reporting Date: | D14: ='Tong quat'!D12 -> 04 Nov 2019
A16: Chỉ tiêu Indicator | B16: Mã số Code | C16: Thuyết minh Note | D16: Năm 2019 Year 2019 | F16: Năm 2018 Year 2018
D17: =BCKetQuaHoatDong_06028!D18 -> Tháng 10 năm 2019 Oct 2019 | E17: Số lũy kế Year-to-date | F17: Tháng 10 năm 2018 Oct 2018 | G17: Số lũy kế Year-to-date
A18: I. THU NHẬP, DOANH THU HOẠT ĐỘNG ĐẦU TƯ Investment income | B18: 01 | D18: 5814905582 | E18: 139819108198 | F18: -126850262450 | G18: -132972932936
A19: 1.1. Cổ tức được chia Dividend income | B19: 02 | D19: 643830000 | E19: 12039311000 | F19: 1294826000 | G19: 13105518700
A20: 1.2. Tiền lãi được nhận Interest income | B20: 03 | D20: 979821780 | E20: 14568393858 | F20: 1360904100 | G20: 10950463254
A21: Lãi tiền gửi ngân hàng Interest income from bank deposits | B21: 03.1 | D21: 4993012 | E21: 262591347 | F21: 28479156 | G21: 1446833402
A22: Lãi chứng chỉ tiền gửi Interest income from Certificates of Deposit | B22: 03.2 | D22: 278150685 | E22: 6629817922 | F22: 1061174944 | G22: 7981129852
A23: Lãi trái phiếu Interest income from bonds | B23: 03.3 | D23: 696678083 | E23: 7675984589 | F23: 271250000 | G23: 1522500000
A24: Tiền lãi hợp đồng reverse repo Reverse repo contract interest received | B24: 03.4 | D24: 0 | E24: 0 | F24: 0 | G24: 0
A25: 1.3. Lãi (lỗ) bán các khoản đầu tư Realized gain (losses) from disposal investments | B25: 04 | D25: 994411335 | E25: 3783608640 | F25: -13376297276 | G25: 67758632292
A26: 1.4. Chênh lệch tăng, giảm đánh giá lại các khoản đầu tư chưa thực hiện Unrealized gain (losses) from investment revaluation | B26: 05 | D26: 3196842467 | E26: 109427794700 | F26: -116129695274 | G26: -227643547182
A27: 1.5. Doanh thu khác Other income | B27: 06 | D27: 0 | E27: 0 | F27: 0 | G27: 2856000000
A28: 1.6. Chênh lệch lãi, lỗ tỷ giá hối đoái đã và chưa thực hiện Realized and unrealized gain (losses) from foreign exchange | B28: 07 | D28: 0 | E28: 0 | F28: 0 | G28: 0
A29: 1.7. Doanh thu khác về đầu tư Other investment income | B29: 08 | D29: 0 | E29: 0 | F29: 0 | G29: 0
... A77: VIII. LỢI NHUẬN KẾ TOÁN SAU THUẾ TNDN PROFIT AFTER TAX (41=30-40) | B77: 41 | D77: 4194581295 | E77: 120697289535 | F77: -129547781095 | G77: -159977099676
A80: Người lập: | B80: Người duyệt:
A93: ____________________________________________ | B93: ____________________________________________ | F93: _____________________________________
A94: Bà Mai Thùy Sâm | B94: Ông Nguyễn Minh Đăng Khánh | F94: Ông Trần Thanh Tân
A95: Kế toán Quỹ | B95: Phó Tổng Giám đốc kiêm Giám đốc Tài chính | F95: Tổng Giám đốc

Sheet BCtinhhinhtaichinh
A1: Mẫu số B02g - QM. Báo cáo tình hình tài chính Template B02g - QM. Statement of Financial Position
A2: (Ban hành kèm theo Thông tư 198/2012/TT-BTC ngày 15 tháng 11 năm 2012 về chế độ kế toán áp dụng đối với quỹ mở) (Issued in association with Circular 198/2012/TT-BTC dated 15 Nov 2012 on the Accounting Policies for Open-Ended Fund)
A3: BÁO CÁO TÌNH HÌNH TÀI CHÍNH STATEMENT OF FINANCIAL POSITION
A5: ='Tong quat'!C1 -> Tại ngày 31 tháng 10 năm 2019 / As at 31 Oct 2019
A7: Tên Công ty quản lý quỹ: | C7: ='Tong quat'!D5 -> Công ty Cổ phần Quản lý Quỹ Đầu tư Việt Nam
A8: Fund Management Company: | C8: ='Tong quat'!D6 -> Vietnam Investment Fund Management Joint Stock Company
A9: Tên ngân hàng giám sát: | C9: ='Tong quat'!D7 -> Ngân hàng TNHH Một thành viên Standard Chartered (Việt Nam)
A10: Supervising bank: | C10: ='Tong quat'!D8 -> Standard Chartered Bank (Vietnam) Limited
A11: Tên Quỹ: | C11: ='Tong quat'!D9 -> Quỹ Đầu tư Chứng khoán Việt Nam
A12: Fund name: | C12: ='Tong quat'!D10 -> Vietnam Securities Investment Fund(VFMVF1)
A13: Ngày lập báo cáo: | C13: ='Tong quat'!D11 -> Ngày 04 tháng 11 năm 2019
A14: Reporting Date: | C14: ='Tong quat'!D12 -> 04 Nov 2019
A16: STT No. | B16: Chỉ tiêu Indicator | C16: Mã số Code | D16: Thuyết minh Note | E16: =BCTaiSan_06027!D18 -> Ngày 31 tháng 10 năm 2019 As at 31 Oct 2019 | F16: =BCTaiSan_06027!E18 -> Ngày 30 tháng 09 năm 2019 As at 30 Sep 2019
A17: I | B17: I. TÀI SẢN ASSETS | C17: I
A18: 1 | B18: 1.Tiền gửi ngân hàng và tương đương tiền Cash at bank and cash equivalent | C18: 110 | E18: 49227230731 | F18: 4858023375
A19: 1.1 | B19: 1.1. Tiền gửi ngân hàng Cash at bank | C19: 111 | E19: 49227230731 | F19: 4858023375
B20: Tiền gửi của nhà đầu tư cho hoạt động mua chứng chỉ quỹ Cash at bank for Fund's subscription | C20: 111.1 | E20: 59000000 | F20: 41000000
B21: Tiền phải trả cho Nhà đầu tư về mua lại Chứng chỉ quỹ Cash at bank for Fund's redemption | C21: 111.2 | E21: 0 | F21: 0
B22: Tiền gửi ngân hàng cho hoạt động của Quỹ Cash at bank for Fund's operation | C22: 111.3 | E22: 49168230731 | F22: 4817023375
B23: Tiền gửi ký quỹ cho hoạt động đầu tư chứng khoán phái sinh Margin account for trading derivatives | C23: 111.4 | E23: 0 | F23: 0
A24: 1.2 | B24: 1.2. Tiền gửi có kỳ hạn dưới ba (03) tháng Deposits with term less than three (03) months | C24: 112 | E24: 0 | F24: 0
A25: 2 | B25: 2. Các khoản đầu tư thuần Net Investments | C25: 120 | E25: 808973695750 | F25: 864628088050
A26: 2.1 | B26: 2.1. Các khoản đầu tư Investments | C26: 121 | E26: 808973695750 | F26: 864628088050
B27: Cổ phiếu niêm yết Listed Shares | C27: 121.1 | E27: 713837895750 | F27: 739131288050
B28: Cổ phiếu chưa niêm yết Unlisted Shares | C28: 121.2 | E28: 0 | F28: 0
B29: Trái phiếu niêm yết Listed Bonds | C29: 121.3 | E29: 60135800000 | F29: 90496800000
B30: Trái phiếu chưa niêm yết Unlisted Bonds | C30: 121.4 | E30: 0 | F30: 0
B31: Chứng chỉ tiền gửi Certificates of Deposit | C31: 121.5 | E31: 35000000000 | F31: 35000000000
B32: Hợp đồng tiền gửi có kỳ hạn trên ba (03) tháng Deposits with term over three (03) months | C32: 121.6 | E32: 0 | F32: 0
B33: Quyền mua chứng khoán Investment - Rights | C33: 121.7 | E33: 0 | F33: 0
B34: Hợp đồng tương lai chỉ số Index future contracts | C34: 121.8 | E34: 0 | F34: 0
B35: Đầu tư khác Other Investments | C35: 121.9 | E35: 0 | F35: 0
B36: Hợp đồng reverse repo Reverse repo contracts | C36: 121.10 | E36: 0 | F36: 0
A37: 2.2 | B37: 2.2. Dự phòng giảm giá tài sản nhận thế chấp Impairment of devaluation of pledged assets | C37: 122 | E37: 0 | F37: 0
A38: 3 | B38: 3. Các khoản phải thu Receivables | C38: 130 | E38: 3618099315 | F38: 3532149315
A39: 3.1 | B39: 3.1 Phải thu về bán các khoản đầu tư Receivables from investments sold but not yet settled | C39: 131 | E39: 0 | F39: 0
B40: Trong đó: Phải thu khó đòi về bán các khoản đầu tư In which: Overdue receivables from selling investments | C40: 132 | E40: 0 | F40: 0
A41: 3.2 | B41: 3.2. Phải thu và dự thu cổ tức, tiền lãi các khoản đầu tư Dividend and interest receivables | C41: 133 | E41: 4484499315 | F41: 4398549315
A42: 3.2.1 | B42: 3.2.1. Phải thu cổ tức, tiền lãi đến ngày nhận Dividend and interest receivables on or after payment date | C42: 134 | E42: 866400000 | F42: 866400000
B43: Phải thu cổ tức Dividend receivables | C43: 134.1 | E43: 866400000 | F43: 866400000
B44: Phải thu trái tức Coupon receivables | C44: 134.2 | E44: 0 | F44: 0
B45: Phải thu lãi tiền gửi có kỳ hạn dưới 3 tháng Interest receivables from deposit with term less than three (03) months | C45: 134.3 | E45: 0 | F45: 0
B46: Phải thu lãi tiền gửi có kỳ hạn trên 3 tháng Interest receivables from deposit with term more than three (03) months | C46: 134.4 | E46: 0 | F46: 0
B47: Phải thu lãi chứng chỉ tiền gửi Interest receivables from Certificates of Deposit | C47: 134.5 | E47: 0 | F47: 0
B48: Trong đó: Phải thu khó đòi về cổ tức, tiền lãi đến ngày nhận nhưng chưa nhận được In which: Overdue receivables from dividend, interest income | C48: 135 | E48: 866400000 | F48: 866400000
A49: 3.2.2 | B49: 3.2.2.Dự thu cổ tức, tiền lãi chưa đến ngày nhận Dividend and interest receivables before payment date | C49: 136 | E49: 3618099315 | F49: 3532149315
B50: Dự thu cổ tức Dividend receivables | C50: 136.1 | E50: 553750000 | F50: 300000
B51: Dự thu lãi trái phiếu Interest accrual from bonds | C51: 136.2 | E51: 2842294521 | F51: 3111643836
B52: Dự thu lãi tiền gửi có kỳ hạn dưới 3 tháng Interest accrual from deposits with term less than three (03) months | C52: 136.3 | E52: 0 | F52: 0
B53: Dự thu lãi tiền gửi có kỳ hạn trên 3 tháng Interest accrual from deposit with term more than three (03) months | C53: 136.4 | E53: 0 | F53: 0
B54: Dự thu lãi chứng chỉ tiền gửi Interest accrual from Certificates of Deposit | C54: 136.5 | E54: 222054794 | F54: 420205479
B55: Dự thu lãi hợp đồng reverse repo Interest receivables from reverse repo contracts | C55: 136.6 | E55: 0 | F55: 0
A56: 3.3 | B56: 3.3. Các khoản phải thu khác Other receivables | C56: 137 | E56: 0 | F56: 0
B57: Phải thu cho cổ phiếu hạn chế Receivable from AP/Investors on restricted securities | C57: 137.1 | E57: 0 | F57: 0
B58: Các tài sản khác Other assets | C58: 137.2 | E58: 0 | F58: 0
B59: Các khoản khác Others | C59: 137.3 | E59: 0 | F59: 0
A60: 3.4 | B60: 3.4. Dự phòng nợ phải thu khó đòi Provision for doubtful debt | C60: 138 | E60: -866400000 | F60: -866400000
B61: TỔNG TÀI SẢN TOTAL ASSETS | C61: 100 | E61: 861819025796 | F61: 873018260740
A62: II | B62: II. NỢ PHẢI TRẢ TOTAL LIABILITIES | C62: II
A63: 1 | B63: 1. Vay ngắn hạn Short-term loans | C63: 311 | E63: 0 | F63: 0
B64: Giá trị hợp đồng repo Repo contract | C64: 311.1 | E64: 0 | F64: 0
B65: Vay ngắn hạn Short-term loans | C65: 311.2 | E65: 0 | F65: 0
A66: 2 | B66: 2. Phải trả về mua các khoản đầu tư Payables for securities bought but not yet settled | C66: 312 | E66: 0 | F66: 0
A67: 3 | B67: 3. Phải trả phí cho các Đại lý phân phối, Công ty quản lý quỹ về mua bán Chứng chỉ quỹ Subscription and Redemption fee payable to distributors and fund management company | C67: 313 | E67: 141529333 | F67: 230586386
B68: Phải trả phí cho các Đại lý phân phối về mua bán Chứng chỉ quỹ Subscription and Redemption fee payable to distributors | C68: 313.1 | E68: 9943530 | F68: 8681648
B69: Phải trả phí cho Công ty quản lý quỹ về mua bán Chứng chỉ quỹ Subscription and Redemption fee payable to fund management company | C69: 313.2 | E69: 131585803 | F69: 221904738
A70: 4 | B70: 4. Thuế và các khoản phải nộp Nhà nước Tax payables and obligations to the State Budget | C70: 314 | E70: 19973039 | F70: 31875408
A71: 5 | B71: 5.Phải trả thu nhập cho Nhà đầu tư Profit distribution payables | C71: 315 | E71: 39925000 | F71: 39925000
A72: 6 | B72: 6. Chi phí phải trả Expense Accruals | C72: 316 | E72: 172726693 | F72: 155867800
B73: Phí giao dịch Transaction fee | C73: 316.1 | E73: 25135520 | F73: 25135520
B74: Phải trả phí môi giới Brokerage fee payables | C74: 316.1.1 | E74: 25135520 | F74: 25135520
B75: Phải trả phí giao dịch thanh toán bù trừ chứng khoán Clearing Settlement Fee payables | C75: 316.1.2 | E75: 0 | F75: 0
B76: Trích trước phí kiểm toán Accrued expense for audit fee | C76: 316.2 | E76: 57667085 | F76: 42252021
B77: Trích trước phí họp đại hội thường niên Accrued expense for Annual General meeting | C77: 316.3 | E77: 35802742 | F77: 35802742
B78: Trích trước phí báo cáo thường niên Accrued expense for Annual report | C78: 316.4 | E78: 22962500 | F78: 22962500
B79: Trích trước thù lao ban đại diện quỹ Accrued expense for Remuneration Payable to Fund's Board of Representatives | C79: 316.5 | E79: 31158846 | F79: 29715017
B80: Trích trước phí quản lý niêm yết hàng năm tại SGDCK Accrued expense for annual listing fee at HOSE | C80: 316.6 | E80: 0 | F80: 0
B81: Trích trước lãi vay ngắn hạn của hợp đồng vay và hợp đồng repo Accrued Interest Expense of short-term loan contracts and repo contracts | C81: 316.7 | E81: 0 | F81: 0
A82: 7 | B82: 7. Phải trả cho Nhà đầu tư về mua Chứng chỉ quỹ Subscription payables to investors | C82: 317 | E82: 133500000 | F82: 204500000
B83: Phải trả cho nhà đầu tư chờ mua chứng chỉ quỹ Subscription Pending allotment | C83: 317.1 | E83: 133500000 | F83: 204500000
B84: Phải trả nhà đầu tư trên tài sản giữ hộ Payables to investors for investment bought on behalf | C84: 317.2 | E84: 0 | F84: 0
A85: 8 | B85: 8. Phải trả cho Nhà đầu tư về mua lại Chứng chỉ quỹ Redemption payables to investors | C85: 318 | E85: 2783368745 | F85: 197494098
A86: 9 | B86: 9. Phải trả dịch vụ quản lý Quỹ mở Fund management related service expense payable | C86: 319 | E86: 1528361298 | F86: 1499341132
B87: Trích trước phải trả phí quản lý Accrued expense for Management fee | C87: 319.1 | E87: 1424409624 | F87: 1398127063
B88: Trích trước phí lưu ký tài sản Quỹ mở Accrued expense for Custodian fee | C88: 319.2 | E88: 40723323 | F88: 38949411
B89: Phí dịch vụ lưu ký - bảo quản tài sản Custodian service - Safe Custody Fee | C89: 319.2.1 | E89: 36523323 | F89: 35849411
B90: Phí dịch vụ lưu ký - giao dịch chứng khoán Custodian service - Transaction fee | C90: 319.2.2 | E90: 4200000 | F90: 3100000
B91: Phí dịch vụ lưu ký cho chứng khoán cơ sở, phí quản lý vị thế và tài sản phái sinh trả cho VSD Custodian service - Depository fee, Position and Margin management fee paid to VSD | C91: 319.2.3 | E91: 0 | F91: 0
B92: Trích trước phí quản trị quỹ Accrued expense for Fund administration fee | C92: 319.3 | E92: 20087827 | F92: 19717177
B93: Trích trước phí giám sát Accrued expense for Supervising fee | C93: 319.4 | E93: 32140524 | F93: 31547481
B94: Trích trước phí dịch vụ đại lý chuyển nhượng Accrued expense for Tranfer agency fee | C94: 319.5 | E94: 11000000 | F94: 11000000
B95: Dự chi phí cung cấp dịch vụ tính giá trị tài sản ròng tham chiếu (iNAV) cho HOSE Accrued expense for payable to HOSE for iNAV calculation | C95: 319.6 | E95: 0 | F95: 0
B96: Dự chi phí cấp quyền sử dụng chỉ số cho HOSE Accrued expense for payable to HOSE for Index usage | C96: 319.7 | E96: 0 | F96: 0
A97: 10 | B97: 10. Phải trả, phải nộp khác Other payables | C97: 320 | E97: 176482966 | F97: 176482966
B98: Phải trả phí báo giá Price feed fee payable | C98: 320.1 | E98: 0 | F98: 0
B99: Trích trước phí công tác, họp của ban đại diện Accrued expense for Fund's Board of Representatives travelling, meeting | C99: 320.2 | E99: 0 | F99: 0
B100: Trích trước phí quản lý thường niên trả cho UBCKNN Accrued expense for Annual Fee paid to SSC | C100: 320.3 | E100: 0 | F100: 0
B101: Phí Ngân hàng S2B S2B Bank charge | C101: 320.4 | E101: 0 | F101: 0
B102: Phải trả khác Other payables | C102: 320.5 | E102: 176482966 | F102: 176482966
B103: TỔNG NỢ PHẢI TRẢ TOTAL LIABILITIES | C103: 300 | E103: 4995867074 | F103: 2536072790
...

Sheet BCTaiSan_06027
A1: Phụ lục 34. Mẫu báo cáo định kỳ về hoạt động đầu tư của quỹ Appendix 34. Periodical Report on Fund's Investment Activities
A2: (Ban hành kèm theo Thông tư 183/2011/TT-BTC ngày 16 tháng 12 năm 2011 hướng dẫn về việc thành lập và quản lý quỹ mở) (Issued in association with Circular 183/2011/TT-BTC dated 16 December 2011 guiding establishment and management of the Open-Ended Fund)
A3: BÁO CÁO ĐỊNH KỲ VỀ HOẠT ĐỘNG ĐẦU TƯ CỦA QUỸ PERIODICAL REPORT ON FUND'S INVESTMENT ACTIVITIES
A5: ='Tong quat'!C1 -> Tại ngày 31 tháng 10 năm 2019 / As at 31 Oct 2019
A7: Tên Công ty quản lý quỹ: | C7: ='Tong quat'!D5 -> Công ty Cổ phần Quản lý Quỹ Đầu tư Việt Nam
A8: Fund Management Company: | C8: ='Tong quat'!D6 -> Vietnam Investment Fund Management Joint Stock Company
A9: Tên ngân hàng giám sát: | C9: ='Tong quat'!D7 -> Ngân hàng TNHH Một thành viên Standard Chartered (Việt Nam)
A10: Supervising bank: | C10: ='Tong quat'!D8 -> Standard Chartered Bank (Vietnam) Limited
A11: Tên Quỹ: | C11: ='Tong quat'!D9 -> Quỹ Đầu tư Chứng khoán Việt Nam
A12: Fund name: | C12: ='Tong quat'!D10 -> Vietnam Securities Investment Fund(VFMVF1)
A13: Ngày lập báo cáo: | C13: ='Tong quat'!D11 -> Ngày 04 tháng 11 năm 2019
A14: Reporting Date: | C14: ='Tong quat'!D12 -> 04 Nov 2019
A17: I | B17: BÁO CÁO TÀI SẢN CỦA QUỸ / ASSET REPORT
A18: STT No | B18: Nội dung Indicator | C18: Mã chỉ tiêu Code | D18: Ngày 31 tháng 10 năm 2019 As at 31 Oct 2019 | E18: Ngày 30 tháng 09 năm 2019 As at 30 Sep 2019 | F18: %/cùng kỳ năm trước %/against last year
A19: I | B19: TÀI SẢN ASSETS | C19: 2200
A20: I.1 | B20: Tiền và các khoản tương đương tiền Cash and Cash Equivalents | C20: 2201 | D20: 49227230731 | E20: 4858023375 | F20: 0.7580963
B21: Tiền Cash | C21: 2202 | D21: 0 | E21: 0
B22: Tiền gửi ngân hàng Cash at bank | C22: 2203 | D22: 49227230731 | E22: 4858023375 | F22: 0.7580963
B23: Tiền gửi của nhà đầu tư cho hoạt động mua chứng chỉ quỹ Cash at bank for Fund's subscription | C23: 2203.1 | D23: 59000000 | E23: 41000000 | F23: 7.375
B24: Tiền phải trả cho Nhà đầu tư về mua lại chứng chỉ quỹ Cash at bank for Fund's redemption | C24: 2203.2 | D24: 0 | E24: 0 | F24: 0
B25: Tiền gửi ngân hàng cho hoạt động của Quỹ Cash at bank for Fund's operation | C25: 2203.3 | D25: 49168230731 | E25: 4817023375 | F25: 0.80521008
B26: Tiền gửi ký quỹ cho hoạt động đầu tư chứng khoán phái sinh Margin account for trading derivatives | C26: 2203.4 | D26: 0 | E26: 0
B27: Các khoản tương đương tiền Cash Equivalents | C27: 2204 | D27: 0 | E27: 0
A28: I.2 | B28: Các khoản đầu tư (kê chi tiết) Investments | C28: 2205 | D28: 808973695750 | E28: 864628088050 | F28: 0.75480467
B29: Cổ phiếu niêm yết Listed shares | C29: 2205.1 | D29: 713837895750 | E29: 739131288050 | F29: 0.7830447
B30: Cổ phiếu chưa niêm yết Unlisted shares | C30: 2205.2 | D30: 0 | E30: 0
B31: Trái phiếu Bonds | C31: 2205.3 | D31: 60135800000 | E31: 90496800000 | F31: 1.9947325
B32: Chứng chỉ tiền gửi Certificates of Deposit | C32: 2205.4 | D32: 35000000000 | E32: 35000000000 | F32: 0.26923077
B33: Hợp đồng tiền gửi có kỳ hạn trên ba (03) tháng Deposits with term over three (03) months | C33: 2205.5 | D33: 0 | E33: 0
B34: Quyền mua chứng khoán Investment - Rights | C34: 2205.6 | D34: 0 | E34: 0
B35: Hợp đồng tương lai chỉ số Index future contracts | C35: 2205.7 | D35: 0 | E35: 0
B36: Đầu tư khác Other investments | C36: 2205.8 | D36: 0 | E36: 0
B37: Hợp đồng reverse repo Reverse repo contracts | C37: 2205.9 | D37: 0 | E37: 0
A38: I.3 | B38: Phải thu cổ tức, trái tức Dividend, Coupon receivables | C38: 2206 | D38: 4262444521 | E38: 3978343836 | F38: 2.0552797
B39: Phải thu cổ tức Dividend receivables | C39: 2206.1 | D39: 1420150000 | E39: 866700000 | F39: 1.0206626
B40: Phải thu trái tức Coupon receivables | C40: 2206.2 | D40: 2842294521 | E40: 3111643836 | F40: 4.1645341
A41: I.4 | B41: Lãi được nhận Interest receivables | C41: 2207 | D41: 222054794 | E41: 420205479 | F41: 0.074580606
B42: Phải thu lãi tiền gửi Interest receivable from bank deposits | C42: 2207.1 | D42: 0 | E42: 0
B43: Phải thu lãi chứng chỉ tiền gửi Interest receivable from Certificates of Deposit | C43: 2207.2 | D43: 222054794 | E43: 420205479 | F43: 0.074580606
B44: Phải thu lãi hợp đồng reverse repo Interest receivable from reverse repo contracts | C44: 2207.3 | D44: 0 | E44: 0
A45: I.5 | B45: Tiền bán chứng khoán chờ thu Securities Trading Receivables | C45: 2208 | D45: 0 | E45: 0 | F45: 0
A46: I.6 | B46: Các khoản phải thu khác Other Receivables | C46: 2210 | D46: -866400000 | E46: -866400000 | F46: 1
B47: Dự phòng giảm giá tài sản nhận thế chấp Impairment of devaluation of pledged assets | C47: 2210.1 | D47: 0 | E47: 0
B48: Dự phòng nợ phải thu khó đòi Provision for doubtful debt | C48: 2210.2 | D48: -866400000 | E48: -866400000 | F48: 1
B49: Các khoản phải thu khác Other Receivables | C49: 2210.3 | D49: 0 | E49: 0
A50: I.7 | B50: Các tài sản khác Other Assets | C50: 2211 | D50: 0 | E50: 0
A51: I.8 | B51: TỔNG TÀI SẢN TOTAL ASSETS | C51: 2212 | D51: 861819025796 | E51: 873018260740 | F51: 0.69426611
A52: II | B52: NỢ LIABILITIES | C52: 2213
A53: II.1 | B53: Tiền phải thanh toán mua chứng khoán Securities Trading Payables | C53: 2214 | D53: 0 | E53: 0 | F53: 0
A54: II.2 | B54: Các khoản phải trả khác Other Payables | C54: 2215 | D54: 4995867074 | E54: 2536072790 | F54: 0.13813576
B55: Phải trả nhà đầu tư Payables to investors | C55: 2215.1 | D55: 2916868745 | E55: 401994098 | F55: 0.089805404
B56: Phải trả cho nhà đầu tư chờ mua chứng chỉ quỹ Subscription Pending allotment | C56: 2215.1.1 | D56: 133500000 | E56: 204500000 | F56: 1.9208633
B57: Phải trả nhà đầu tư trên tài sản giữ hộ Payables to investors for investment bought on behalf | C57: 2215.1.2 | D57: 0 | E57: 0
B58: Phải trả nhà đầu tư trên cổ tức đã thu Payables to investors for collected dividend | C58: 2215.1.3 | D58: 0 | E58: 0
B59: Phải trả cho Nhà đầu tư về mua lại chứng chỉ quỹ Redemption payable to investors | C59: 2215.1.4 | D59: 2783368745 | E59: 197494098 | F59: 0.08587893
B60: Thuế và các khoản phải nộp Nhà nước Tax payables and obligations to the State Budget | C60: 2215.2 | D60: 19973039 | E60: 31875408 | F60: 0.62414103
B61: Phải trả phí phát hành, mua lại chứng chỉ quỹ cho Đại lý phân phối và Công ty quản lý quỹ Subscription and Redemption fee payable to distributors and Fund Management Company | C61: 2215.3 | D61: 141529333 | E61: 230586386 | F61: 0.17982995
B62: Phải trả thu nhập cho nhà đầu tư Income payable to investors | C62: 2215.4 | D62: 39925000 | E62: 39925000 | F62: 1
B63: Phải trả thù lao Ban đại diện quỹ Remuneration Payable to Fund's Board of Representatives | C63: 2215.5 | D63: 31158846 | E63: 29715017 | F63: 1
B64: Phải trả phí quản lý cho công ty quản lý quỹ Management fee payable | C64: 2215.6 | D64: 1424409624 | E64: 1398127063 | F64: 0.67922707
B65: Phải trả phí quản trị quỹ Fund Administration fee payable | C65: 2215.7 | D65: 20087827 | E65: 19717177 | F65: 0.6792271
B66: Phải trả phí giám sát Supervisory service fee payable | C66: 2215.8 | D66: 32140524 | E66: 31547481 | F66: 0.67922703
B67: Phí giao dịch Transaction fee | C67: 2215.9 | D67: 25135520 | E67: 25135520 | F67: 0.14083078
B68: Phải trả phí môi giới Brokerage fee payable | C68: 2215.9.1 | D68: 25135520 | E68: 25135520 | F68: 0.14083078
B69: Phải trả phí phát hành thanh toán bù trừ chứng khoán Clearing Settlement fee payable | C69: 2215.9.2 | D69: 0 | E69: 0
B70: Trích trước phí lưu ký tài sản Quỹ mở Accrued expense for Custodian fee | C70: 2215.10 | D70: 40723323 | E70: 38949411 | F70: 0.71422483
B71: Phí lưu ký - bảo quản tài sản Custodian service - Safe Custody Fee | C71: 2215.10.1 | D71: 36523323 | E71: 35849411 | F71: 0.84903383
B72: Phí lưu ký - giao dịch chứng khoán Custodian service - Transaction fee | C72: 2215.10.2 | D72: 4200000 | E72: 3100000 | F72: 0.3
B73: Phí dịch vụ lưu ký cho chứng khoán cơ sở, phí quản lý vị thế và tài sản phái sinh trả cho VSD Custodian service - Depository fee, Position and Margin management fee paid to VSD | C73: 2215.10.3 | D73: 0 | E73: 0
B74: Phải trả phí kiểm toán Audit fee payable | C74: 2215.11 | D74: 57667085 | E74: 42252021 | F74: 1
B75: Phải trả phí họp đại hội thường niên General meeting expense payable | C75: 2215.12 | D75: 35802742 | E75: 35802742 | F75: 1.7540277
B76: Phải trả phí báo cáo thường niên Annual report fee payable | C76: 2215.13 | D76: 22962500 | E76: 22962500 | F76: 0.7681278
B77: Phải trả phí dịch vụ đại lý chuyển nhượng Transfer Agency fee payable | C77: 2215.14 | D77: 11000000 | E77: 11000000 | F77: 0.25
B78: Dự chi phí tính giá trị tài sản ròng tham chiếu (iNAV) cho HOSE Service fee payable to HOSE for calculating iNAV | C78: 2215.15 | D78: 0 | E78: 0
B79: Dự chi phí cấp quyền sử dụng chỉ số cho HOSE Authorising index service fee payable to HOSE | C79: 2215.16 | D79: 0 | E79: 0
B80: Phải trả khác Other payables | C80: 2215.17 | D80: 176482966 | E80: 176482966 | F80: 0.75129091
B81: Phải trả phí báo giá Price feed fee payable | C81: 2215.17.1 | D81: 0 | E81: 0 | F81: 0
B82: Trích trước phí công tác, họp của ban đại diện Accrued expense for Fund's Board of Representatives travelling, meeting | C82: 2215.17.2 | D82: 0 | E82: 0 | F82: 0
B83: Trích trước phí quản lý thường niên trả UBCKNN Accrued expense for Annual Management Fee pay to SSC | C83: 2215.17.3 | D83: 0 | E83: 0 | F83: 0
B84: Phải trả khác Other payables | C84: 2215.17.4 | D84: 176482966 | E84: 176482966 | F84: 1
B85: Vay ngắn hạn - hợp đồng repo Short-term loans - Repo contracts | C85: 2215.18 | D85: 0 | E85: 0
B86: Gốc hợp đồng repo Principal of repo contracts | C86: 2215.18.1 | D86: 0 | E86: 0
B87: Trích trước lãi vay ngắn hạn Accrued Interest Expense | C87: 2215.18.2 | D87: 0 | E87: 0
B88: Gốc vay ngắn hạn Principal of Short-term loans | C88: 2215.18.3 | D88: 0 | E88: 0
A89: II.3 | B89: TỔNG NỢ TOTAL LIABILITIES | C89: 2216 | D89: 4995867074 | E89: 2536072790 | F89: 0.13166475
B90: Tài sản ròng của Quỹ ( = I.8 - II.3) Net Asset Value ( = I.8 - II.3) | C90: 2217 | D90: 856823158722 | E90: 870482187950 | F90: 0.71200531
B91: Tổng số đơn vị quỹ Total Outstanding Fund Certificates | C91: 2218 | D91: 20570963 | E91: 21001834 | F91: 0.64141772
B92: Giá trị tài sản ròng trên một đơn vị quỹ Net Asset Value per Fund Certificate | C92: 2219 | D92: 41652.06 | E92: 41447.91 | F92: 1.1100494
A94: Đại diện có thẩm quyền của Ngân hàng giám sát | E94: Đại diện có thẩm quyền của Công ty quản lý Quỹ
A95: Authorised Representative of Supervisory Bank | E95: Authorised Representative of Fund Management Company
A103: Ngân hàng TNHH MTV Standard Chartered (Việt Nam) | E103: Công ty Cổ phần Quản lý Quỹ Đầu tư Việt Nam
A104: Vũ Hương Giang | E104: Trần Thanh Tân
A105: Phó phòng Nghiệp vụ Dịch vụ Chứng khoán | E105: Tổng Giám đốc

Sheet BCKetQuaHoatDong_06028
A1: Phụ lục 34. Mẫu báo cáo định kỳ về hoạt động đầu tư của quỹ Appendix 34. Periodical Report on Fund's Investment Activities
A2: (Ban hành kèm theo Thông tư 183/2011/TT-BTC ngày 16 tháng 12 năm 2011 hướng dẫn về việc thành lập và quản lý quỹ mở) (Issued in association with Circular 183/2011/TT-BTC dated 16 December 2011 guiding establishment and management of the Open-Ended Fund)
A3: BÁO CÁO ĐỊNH KỲ VỀ HOẠT ĐỘNG ĐẦU TƯ CỦA QUỸ PERIODICAL REPORT ON FUND'S INVESTMENT ACTIVITIES
A5: ='Tong quat'!C2 -> Tháng 10 năm 2019 / Oct 2019
A7: Tên Công ty quản lý quỹ: | C7: ='Tong quat'!D5 -> Công ty Cổ phần Quản lý Quỹ Đầu tư Việt Nam
A8: Fund Management Company: | C8: ='Tong quat'!D6 -> Vietnam Investment Fund Management Joint Stock Company
A9: Tên ngân hàng giám sát: | C9: ='Tong quat'!D7 -> Ngân hàng TNHH Một thành viên Standard Chartered (Việt Nam)
A10: Supervising bank: | C10: ='Tong quat'!D8 -> Standard Chartered Bank (Vietnam) Limited
A11: Tên Quỹ: | C11: ='Tong quat'!D9 -> Quỹ Đầu tư Chứng khoán Việt Nam
A12: Fund name: | C12: ='Tong quat'!D10 -> Vietnam Securities Investment Fund(VFMVF1)
A13: Ngày lập báo cáo: | C13: ='Tong quat'!D11 -> Ngày 04 tháng 11 năm 2019
A14: Reporting Date: | C14: ='Tong quat'!D12 -> 04 Nov 2019
A17: II | B17: BÁO CÁO KẾT QUẢ HOẠT ĐỘNG / PROFIT AND LOSS REPORT
A18: STT No | B18: Nội dung Indicator | C18: Mã chỉ tiêu Code | D18: Tháng 10 năm 2019 Oct 2019 | E18: Tháng 09 năm 2019 Sep 2019 | F18: Lũy kế từ đầu năm Accumulated from beginning of year
A19: I | B19: Thu nhập từ hoạt động đầu tư Income from Investment Activities | C19: 2220 | D19: 1623651780 | E19: 1713413162 | F19: 26607704858
A20: 1 | B20: Cổ tức, trái tức được nhận Dividend income, interest income from bonds | C20: 2221 | D20: 1340508083 | E20: 1447416001 | F20: 19715295589
B21: Cổ tức được nhận Dividends income | C21: 2221.1 | D21: 643830000 | E21: 677216000 | F21: 12039311000
B22: Trái tức được nhận Interest income from bonds | C22: 2221.2 | D22: 696678083 | E22: 770200001 | F22: 7675984589
A23: 2 | B23: Lãi được nhận Interest income | C23: 2222 | D23: 283143697 | E23: 265997161 | F23: 6892409269
B24: Lãi tiền gửi ngân hàng Interest income from bank deposits | C24: 2222.1 | D24: 4993012 | E24: 3024274 | F24: 262591347
B25: Lãi chứng chỉ tiền gửi Interest income from Certificates of Deposit | C25: 2222.2 | D25: 278150685 | E25: 262972887 | F25: 6629817922
B26: Lãi hợp đồng mua reverse repo Interest income from reverse repo contracts | C26: 2222.3 | D26: 0 | E26: 0 | F26: 0
A27: 3 | B27: Các khoản thu nhập khác Other income | C27: 2223 | D27: 0 | E27: 0 | F27: 0
B28: Thu nhập khác về đầu tư Other investment income | C28: 2223.1 | D28: 0 | E28: 0 | F28: 0
B29: Thu nhập khác Other income | C29: 2223.2 | D29: 0 | E29: 0 | F29: 0
B30: Chi phí dự phòng nợ phải thu khó đòi về cổ tức, tiền lãi và xử lý tổn thất nợ phải thu khó đòi về cổ tức, tiền lãi Provision expense for bad debts from dividends, interest income and written off bad debts from dividends, interest income | C30: 2223.3 | D30: 0 | E30: 0 | F30: 0
A31: II | B31: Chi phí Expenses | C31: 2224 | D31: 1620324287 | E31: 1581657071 | F31: 19121818663
A32: 1 | B32: Phí quản lý trả cho Công ty quản lý quỹ Management Fee paid to Fund Management Company | C32: 2225 | D32: 1424409624 | E32: 1398127063 | F32: 16116239884
A33: 2 | B33: Phí lưu ký, giám sát trả cho Ngân hàng Giám sát/VSD Custody fee, Supervising fee paid to Supervising Bank/VSD | C33: 2226 | D33: 78454753 | E33: 76875896 | F33: 858500405
B34: Phí dịch vụ lưu ký - bảo quản tài sản Custodian service - Safe Custody Fee | C34: 2226.1 | D34: 36523323 | E34: 35849411 | F34: 366340048
B35: Phí dịch vụ lưu ký - giao dịch chứng khoán Custodian service - Transaction fee | C35: 2226.2 | D35: 4515000 | E35: 2900000 | F35: 63015000
B36: Phí dịch vụ lưu ký cho chứng khoán cơ sở, phí quản lý vị thế và tài sản phái sinh trả cho VSD Custodian service - Depository fee, Position and Margin management fee paid to VSD | C36: 2226.3 | D36: 5275906 | E36: 6579004 | F36: 65496873
B37: Phí giám sát Supervisory fee | C37: 2226.4 | D37: 32140524 | E37: 31547481 | F37: 363648484
A38: 3 | B38: Chi phí dịch vụ quản trị quỹ, chi phí dịch vụ đại lý chuyển nhượng và các chi phí khác mà công ty quản lý quỹ trả cho tổ chức cung cấp dịch vụ có liên quan Fund Administration Fee, Transfer Agency Fee and other fees paid to relevant Fund's service providers | C38: 2227 | D38: 31087827 | E38: 30717177 | F38: 337280301
B39: Chi phí quản trị Quỹ Fund Administration Fee | C39: 2227.1 | D39: 20087827 | E39: 19717177 | F39: 227280301
B40: Chi phí dịch vụ Đại lý Chuyển nhượng Transfer Agency Fee | C40: 2227.2 | D40: 11000000 | E40: 11000000 | F40: 110000000
A41: 4 | B41: Chi phí kiểm toán trả cho tổ chức kiểm toán Audit fee | C41: 2228 | D41: 15415064 | E41: 14917805 | F41: 154805349
A42: 5 | B42: Chi phí dịch vụ tư vấn pháp lý, dịch vụ báo giá và các dịch vụ hợp lý khác, thù lao trả cho ban đại diện quỹ Legal consultancy expenses, price feed fee, other valid expenses, remuneration paid to Fund's Board of Representatives | C42: 2229 | D42: 18443829 | E42: 18397255 | F42: 196223846
B43: Thù lao Ban đại diện Quỹ Remuneration of Fund's Board of Representatives | C43: 2229.1 | D43: 18443829 | E43: 18397255 | F43: 184158846
B44: Chi phí cung cấp báo giá chứng khoán Price feed fee | C44: 2229.2 | D44: 0 | E44: 0 | F44: 12065000
B45: Chi phí dịch vụ tư vấn pháp lý Legal consultancy expenses | C45: 2229.3 | D45: 0 | E45: 0 | F45: 0
A46: 6 | B46: Chi phí dự thảo, in ấn, gửi bản cáo bạch, bản cáo bạch tóm tắt, báo cáo tài chính, xác nhận giao dịch, sao kê tài khoản và các tài liệu khác cho nhà đầu tư; chi phí công bố thông tin của quỹ; chi phí tổ chức họp đại hội nhà đầu tư, ban đại diện quỹ Fee for drafting, printing, distribution of prospectus, summarised prospectus, financial statements, transaction confirmations, account statements and other documents to investors; information disclosure fee; fee for organising annual general meeting, board of representatives meeting | C46: 2230 | D46: 0 | E46: 0 | F46: -20282951
B47: Chi phí họp Đại hội Quỹ Meeting expenses | C47: 2230.1 | D47: 0 | E47: 0 | F47: 0
B48: Chi phí báo cáo thường niên Annual report expenses | C48: 2230.2 | D48: 0 | E48: 0 | F48: 0
B49: Chi phí họp, công tác của Ban đại diện Fund's Board of Representatives meeting, travelling expenses | C49: 2230.3 | D49: 0 | E49: 0 | F49: -20282951
B50: Chi phí công bố thông tin của Quỹ Expenses of information disclosure of the Fund | C50: 2230.4 | D50: 0 | E50: 0 | F50: 0
B51: Phí thiết kế, in ấn, gửi thư… Designing, printing, posting... expenses | C51: 2230.5 | D51: 0 | E51: 0 | F51: 0
A52: 7 | B52: Chi phí liên quan đến thực hiện các giao dịch tài sản của Quỹ Expenses related to execution of Fund’s asset transactions | C52: 2231 | D52: 50886173 | E52: 41373482 | F52: 1459846284
B53: Chi phí môi giới Brokerage fee | C53: 2231.1 | D53: 50492233 | E53: 40939302 | F53: 1453147719
B54: Chi phí thanh toán bù trừ Clearing settlement fee | C54: 2231.2 | D54: 393940 | E54: 434180 | F54: 6698565
B55: Chi phí khác Other Expenses | C55: 2231.3 | D55: 0 | E55: 0 | F55: 0
A56: 8 | B56: Các loại phí, chi phí khác Other fees, expenses | C56: 2232 | D56: 1627017 | E56: 1248393 | F56: 19205545
B57: Chi phí thiết lập Quỹ Set up Expenses | C57: 2232.1 | D57: 0 | E57: 0 | F57: 0
B58: Phí niêm yết, đăng ký chứng khoán Listing, registration fees | C58: 2232.2 | D58: 0 | E58: 0 | F58: 0
B59: Phí quản lý thường niên trả cho UBCKNN Annual management fee paid to SSC | C59: 2232.3 | D59: 0 | E59: 0 | F59: 0
B60: Phí ngân hàng Bank charges | C60: 2232.4 | D60: 1627017 | E60: 1248393 | F60: 18105545
B61: Chi phí lãi vay Borrowing expense | C61: 2232.5 | D61: 0 | E61: 0 | F61: 0
B62: Chi phí khác Other Expenses | C62: 2232.6 | D62: 0 | E62: 0 | F62: 0
B63: Phí thực hiện quyền trả cho VSD Fee paid to VSD for getting the list of investors | C63: 2232.7 | D63: 0 | E63: 0 | F63: 1100000
A64: III | B64: Thu nhập ròng từ hoạt động đầu tư (= I - II) Net Income from Investment Activities (= I - II) | C64: 2233 | D64: 3327493 | E64: 131756091 | F64: 7485886195
A65: IV | B65: Lãi / (lỗ) từ hoạt động đầu tư Gain / (Loss) from Investment Activities | C65: 2234 | D65: 4191253802 | E65: 18624167959 | F65: 113211403340
A66: 1 | B66: Lãi (lỗ) thực tế phát sinh từ hoạt động đầu tư Realised Gain / (Loss) from disposal of investment | C66: 2235 | D66: 994411335 | E66: 930156138 | F66: 3783608640
A67: 2 | B67: Thay đổi về giá trị của các khoản đầu tư trong kỳ Unrealised Gain / (Loss) due to market price | C67: 2236 | D67: 3196842467 | E67: 17694011821 | F67: 109427794700
A68: V | B68: Thay đổi của giá trị tài sản ròng của Quỹ do các hoạt động đầu tư trong kỳ (III + IV) Change of Net Asset Value of the Fund due to investment activities during the period (= III + IV) | C68: 2237 | D68: 4194581295 | E68: 18755924050 | F68: 120697289535
A69: VI | B69: Giá trị tài sản ròng đầu kỳ Net Asset Value at the beginning of period | C69: 2238 | D69: 870482187950 | E69: 882204395196 | F69: 1089016862195
A70: VII | B70: Thay đổi giá trị tài sản ròng của Quỹ trong kỳ Change of Net Asset Value of the Fund during the period | C70: 2239 | D70: -13659029228 | E70: -11722207246 | F70: -232193703473
B71: Trong đó: Of which: | C71: 2240
A72: 1 | B72: Thay đổi giá trị tài sản ròng của Quỹ do các hoạt động liên quan đến đầu tư của Quỹ trong kỳ Change of Net Asset Value due to investment related activities during the period | C72: 2239.1 | D72: 4194581295 | E72: 18755924050 | F72: 120697289535
A73: 2 | B73: Thay đổi giá trị tài sản ròng của Quỹ do việc phân phối thu nhập của Quỹ cho các nhà đầu tư trong kỳ Change of Net Asset Value due to profit distribution to investors during the period | C73: 2239.2 | D73: 0 | E73: 0 | F73: 0
A74: 3 | B74: Thay đổi giá trị tài sản ròng do phát hành thêm Chứng chỉ Quỹ Change of Net Asset Value due to subscription during the period | C74: 2239.3 | D74: 2119427539 | E74: 1397279179 | F74: 46408385911
A75: 4 | B75: Thay đổi giá trị tài sản ròng do mua lại Chứng chỉ Quỹ Change of Net Asset Value due to redemption during the period | C75: 2239.4 | D75: -19973038062 | E75: -31875410475 | F75: -399299378919
A76: VIII | B76: Giá trị tài sản ròng cuối kỳ Net Asset Value at the end of period | C76: 2243 | D76: 856823158722 | E76: 870482187950 | F76: 856823158722
A77: IX | B77: Lợi nhuận bình quân năm (chỉ áp dụng đối với báo cáo năm) Average annual profit (only applicable to annual report) | C77: 2244 | D77: 0 | E77: 0 | F77: 0
B78: Tỷ suất lợi nhuận bình quân năm (chỉ áp dụng đối với báo cáo năm) Average annual rate of return (only applicable to annual report) | C78: 2245 | D78: 0 | E78: 0 | F78: 0
A81: ='Tong quat'!C16 -> Đại diện có thẩm quyền của Ngân hàng giám sát | D81: ='Tong quat'!F16 -> Đại diện có thẩm quyền của Công ty quản lý Quỹ
A82: ='Tong quat'!C17 -> Authorised Representative of Supervisory Bank | D82: ='Tong quat'!F17 -> Authorised Representative of Fund Management Company
A90: ='Tong quat'!C19 -> Ngân hàng TNHH MTV Standard Chartered (Việt Nam) | D90: ='Tong quat'!F19 -> Công ty Cổ phần Quản lý Quỹ Đầu tư Việt Nam
A91: ='Tong quat'!C20 -> Vũ Hương Giang | D91: ='Tong quat'!F20 -> Trần Thanh Tân
A92: ='Tong quat'!C21 -> Phó phòng Nghiệp vụ Dịch vụ Chứng khoán | D92: ='Tong quat'!F21 -> Tổng Giám đốc

Sheet BCDanhMucDauTu_06029
A1: Phụ lục 34. Mẫu báo cáo định kỳ về hoạt động đầu tư của quỹ Appendix 34. Periodical Report on Fund's Investment Activities
A2: (Ban hành kèm theo Thông tư 183/2011/TT-BTC ngày 16 tháng 12 năm 2011 hướng dẫn về việc thành lập và quản lý quỹ mở) (Issued in association with Circular 183/2011/TT-BTC dated 16 December 2011 guiding establishment and management of the Open-Ended Fund)
A3: BÁO CÁO ĐỊNH KỲ VỀ HOẠT ĐỘNG ĐẦU TƯ CỦA QUỸ PERIODICAL REPORT ON FUND'S INVESTMENT ACTIVITIES
A5: ='Tong quat'!C1 -> Tại ngày 31 tháng 10 năm 2019 / As at 31 Oct 2019
A7: Tên Công ty quản lý quỹ: | C7: ='Tong quat'!D5 -> Công ty Cổ phần Quản lý Quỹ Đầu tư Việt Nam
A8: Fund Management Company: | C8: ='Tong quat'!D6 -> Vietnam Investment Fund Management Joint Stock Company
A9: Tên ngân hàng giám sát: | C9: ='Tong quat'!D7 -> Ngân hàng TNHH Một thành viên Standard Chartered (Việt Nam)
A10: Supervising bank: | C10: ='Tong quat'!D8 -> Standard Chartered Bank (Vietnam) Limited
A11: Tên Quỹ: | C11: ='Tong quat'!D9 -> Quỹ Đầu tư Chứng khoán Việt Nam
A12: Fund name: | C12: ='Tong quat'!D10 -> Vietnam Securities Investment Fund(VFMVF1)
A13: Ngày lập báo cáo: | C13: ='Tong quat'!D11 -> Ngày 04 tháng 11 năm 2019
A14: Reporting Date: | C14: ='Tong quat'!D12 -> 04 Nov 2019
A17: III | B17: BÁO CÁO VỀ TÌNH HÌNH DANH MỤC ĐẦU TƯ CỦA QUỸ / INVESTMENT PORTFOLIO REPORT
A18: STT No. | B18: Loại Category | C18: Mã chỉ tiêu Code | D18: Số Lượng Quantity | E18: Giá thị trường hoặc giá trị hợp lý tại ngày báo cáo Market price | F18: Tổng giá trị (Đồng) Value (VND) | G18: Tỷ lệ % Tổng giá trị tài sản của Quỹ % of total asset
A19: I | B19: CỔ PHIẾU NIÊM YẾT LISTED SHARES | C19: 2246
A20: 1 | B20: ACB | C20: 2246.1 | D20: 764357 | E20: 24100 | F20: 18421003700 | G20: 0.021374561
A21: 2 | B21: ACV | C21: 2246.2 | D21: 136800 | E21: 80000 | F21: 10944000000 | G21: 0.012698722
A22: 3 | B22: BID | C22: 2246.3 | D22: 985890 | E22: 40600 | F22: 40027134000 | G22: 0.046444941
A23: 4 | B23: BVH | C23: 2246.4 | D23: 114600 | E23: 72100 | F23: 8262660000 | G23: 0.0095874653
A24: 5 | B24: CTD | C24: 2246.5 | D24: 100 | E24: 79000 | F24: 7900000 | G24: 9.1666577e-06
A25: 6 | B25: CTG | C25: 2246.6 | D25: 494900 | E25: 22000 | F25: 10887800000 | G25: 0.012633511
A26: 7 | B26: DPM | C26: 2246.7 | D26: 100 | E26: 13650 | F26: 1365000 | G26: 1.5838592e-06
A27: 8 | B27: DXG | C27: 2246.8 | D27: 547153 | E27: 15450 | F27: 8453513850 | G27: 0.00980892
A28: 9 | B28: EIB | C28: 2246.9 | D28: 100 | E28: 16500 | F28: 1650000 | G28: 1.9145551e-06
A29: 10 | B29: FPT | C29: 2246.10 | D29: 1084142 | E29: 57900 | F29: 62771821800 | G29: 0.072836431
A30: 11 | B30: GAS | C30: 2246.11 | D30: 256150 | E30: 103500 | F30: 26511525000 | G30: 0.030762288
A31: 12 | B31: GMD | C31: 2246.12 | D31: 100 | E31: 26700 | F31: 2670000 | G31: 3.0980982e-06
... A63: 44 | B63: VRE | C63: 2246.44 | D63: 285970 | E63: 33200 | F63: 9494204000 | G63: 0.011016471
B64: TỔNG TOTAL | C64: 2247 | D64: 15715365 | F64: 713837895750 | G64: 0.82829211
A65: II | B65: CỔ PHIẾU CHƯA NIÊM YẾT UNLISTED SHARES | C65: 2248
B66: TỔNG TOTAL | C66: 2249 | D66: 0 | F66: 0 | G66: 0
B67: TỔNG CÁC LOẠI CỔ PHIẾU TOTAL | C67: 2250 | D67: 15715365 | F67: 713837895750 | G67: 0.82829211
A68: III | B68: TRÁI PHIẾU BONDS | C68: 2251
A69: 1 | B69: Trái phiếu niêm yết Listed bonds | C69: 2251.1 | D69: 600000 | F69: 60135800000 | G69: 0.069777759
A70: 1.1 | B70: KBC11806 | C70: 2251.1.1 | D70: 500000 | E70: 100000 | F70: 50000000000 | G70: 0.058016821
A71: 1.2 | B71: VIC11814 | C71: 2251.1.2 | D71: 100000 | E71: 101358 | F71: 10135800000 | G71: 0.011760938
A72: 2 | B72: Trái phiếu chưa niêm yết Unlisted Bonds | C72: 2251.2 | D72: 0 | F72: 0 | G72: 0
B73: TỔNG TOTAL | C73: 2252 | D73: 600000 | F73: 60135800000 | G73: 0.069777759
A74: IV | B74: CÁC LOẠI CHỨNG KHOÁN KHÁC OTHER SECURITIES | C74: 2253
A75: 1 | B75: Quyền mua chứng khoán Investment - Rights | C75: 2253.1 | D75: 0 | F75: 0 | G75: 0
A76: 2 | B76: Chi tiết loại hợp đồng phái sinh (*) Index future contracts | C76: 2253.2 | D76: 0 | F76: 0 | G76: 0
B77: TỔNG TOTAL | C77: 2254 | F77: 0 | G77: 0
B78: TỔNG CÁC LOẠI CHỨNG KHOÁN TOTAL TYPES OF SECURITIES | C78: 2255 | F78: 773973695750 | G78: 0.89806986
A79: V | B79: CÁC TÀI SẢN KHÁC OTHER ASSETS | C79: 2256
A80: 1 | B80: Cổ tức được nhận Dividend receivables | C80: 2256.1 | F80: 1420150000 | G80: 0.0016478518
A81: 2 | B81: Lãi trái phiếu được nhận Coupon receivables | C81: 2256.2 | F81: 2842294521 | G81: 0.0032980178
A82: 3 | B82: Lãi tiền gửi và chứng chỉ tiền gửi được nhận Interest receivables from bank deposits and certificates of deposit | C82: 2256.3 | F82: 222054794 | G82: 0.00025765826
A83: 4 | B83: Tiền bán chứng khoán chờ thu Outstanding Settlement of sales transactions | C83: 2256.4 | F83: 0 | G83: 0
A84: 5 | B84: Phải thu cho cổ phiếu hạn chế Receivable from AP/Investors on restricted securities | C84: 2256.5 | F84: 0 | G84: 0
A85: 6 | B85: Phải thu khác Other receivables | C85: 2256.6 | F85: 0 | G85: 0
A86: 7 | B86: Tài sản khác Other assets | C86: 2256.7 | F86: -866400000 | G86: -0.0010053155
B87: TỔNG TOTAL | C87: 2257 | F87: 3618099315 | G87: 0.0041982124
A88: VI | B88: TIỀN CASH | C88: 2258
A89: 1 | B89: Tiền gửi Ngân hàng Cash at bank | C89: 2259 | F89: 49227230731 | G89: 0.057120148
A90: 1.1 | B90: Tiền gửi ngân hàng Cash at Bank | C90: 2259.1 | F90: 49227230731 | G90: 0.057120148
A91: 1.2 | B91: Các khoản tương đương tiền Cash Equivalents | C91: 2259.2 | F91: 0 | G91: 0
A92: 1.3 | B92: Tiền gửi có kỳ hạn trên 3 tháng Deposits with term over three (03) months | C92: 2259.3 | F92: 0 | G92: 0
A93: 2 | B93: Chứng chỉ tiền gửi Certificates of deposit | C93: 2260 | F93: 35000000000 | G93: 0.040611775
A94: 3 | B94: Công cụ chuyển nhượng… Transferable instruments… | C94: 2261 | F94: 0 | G94: 0
B95: TỔNG TOTAL | C95: 2262 | F95: 84227230731 | G95: 0.097731923
A96: VII | B96: Tổng giá trị danh mục Total value of portfolio | C96: 2263 | F96: 861819025796 | G96: 1
A98: Đại diện có thẩm quyền của Ngân hàng giám sát | E98: Đại diện có thẩm quyền của Công ty quản lý Quỹ
A99: Authorised Representative of Supervisory Bank | E99: Authorised Representative of Fund Management Company
A108: Ngân hàng TNHH MTV Standard Chartered (Việt Nam) | E108: Công ty Cổ phần Quản lý Quỹ Đầu tư Việt Nam
A109: Vũ Hương Giang | E109: Trần Thanh Tân
A110: Phó phòng Nghiệp vụ Dịch vụ Chứng khoán | E110: Tổng Giám đốc

Sheet Khac_06030
A1: Phụ lục 34. Mẫu báo cáo định kỳ về hoạt động đầu tư của quỹ Appendix 34. Periodical Report on Fund's Investment Activities
A2: (Ban hành kèm theo Thông tư 183/2011/TT-BTC ngày 16 tháng 12 năm 2011 hướng dẫn về việc thành lập và quản lý quỹ mở) (Issued in association with Circular 183/2011/TT-BTC dated 16 December 2011 guiding establishment and management of the Open-Ended Fund)
A3: BÁO CÁO ĐỊNH KỲ VỀ HOẠT ĐỘNG ĐẦU TƯ CỦA QUỸ PERIODICAL REPORT ON FUND'S INVESTMENT ACTIVITIES
A5: ='Tong quat'!C2 -> Tháng 10 năm 2019 / Oct 2019
A7: Tên Công ty quản lý quỹ: | C7: ='Tong quat'!D5 -> Công ty Cổ phần Quản lý Quỹ Đầu tư Việt Nam
A8: Fund Management Company: | C8: ='Tong quat'!D6 -> Vietnam Investment Fund Management Joint Stock Company
A9: Tên ngân hàng giám sát: | C9: ='Tong quat'!D7 -> Ngân hàng TNHH Một thành viên Standard Chartered (Việt Nam)
A10: Supervising bank: | C10: ='Tong quat'!D8 -> Standard Chartered Bank (Vietnam) Limited
A11: Tên Quỹ: | C11: ='Tong quat'!D9 -> Quỹ Đầu tư Chứng khoán Việt Nam
A12: Fund name: | C12: ='Tong quat'!D10 -> Vietnam Securities Investment Fund(VFMVF1)
A13: Ngày lập báo cáo: | C13: ='Tong quat'!D11 -> Ngày 04 tháng 11 năm 2019
A14: Reporting Date: | C14: ='Tong quat'!D12 -> 04 Nov 2019
A17: IV | B17: MỘT SỐ CHỈ TIÊU KHÁC / OTHER INDICATORS
A18: STT No | B18: Chỉ tiêu Indicators | C18: Mã chỉ tiêu Code | D18: =BCKetQuaHoatDong_06028!D18 -> Tháng 10 năm 2019 Oct 2019 | E18: =BCKetQuaHoatDong_06028!E18 -> Tháng 09 năm 2019 Sep 2019
A19: I | B19: CÁC CHỈ TIÊU VỀ HIỆU QUẢ HOẠT ĐỘNG INVESTMENT PERFORMANCE INDICATORS | C19: 2264
A20: 1 | B20: Tỷ lệ phí quản lý trả cho công ty quản lý quỹ/Giá trị tài sản ròng trung bình trong kỳ (%) Management fee paid to the fund management company/Average NAV (%) | C20: 2265 | D20: 0.019875975 | E20: 0.019234916
A21: 2 | B21: Tỷ lệ phí lưu ký, giám sát trả cho Ngân hàng Giám sát/Giá trị tài sản ròng trung bình trong kỳ (%) Custody and supervising fees paid to the Supervisory Bank/Average NAV (%) | C21: 2266 | D21: 0.0010211254 | E21: 0.00096711869
A22: 3 | B22: Tỷ lệ chi phí dịch vụ quản trị quỹ, chi phí dịch vụ đại lý chuyển nhượng và các chi phí khác mà công ty quản lý quỹ trả cho tổ chức cung cấp dịch vụ có liên quan/Giá trị tài sản ròng của quỹ trung bình trong kỳ (%) Fund admin fee, transfer agency fee and other fees paid to relating services providers by the fund management company/Average NAV (%) | C22: 22661 | D22: 0.00050741347 | E22: 0.00051310709
A23: 4 | B23: Chi phí kiểm toán trả cho tổ chức kiểm toán (nếu phát sinh)/Giá trị tài sản ròng trung bình trong kỳ (%) Auditing fee paid to auditing organizations (if any)/Average NAV (%) | C23: 2267 | D23: 0.00021509924 | E23: 0.00020523365
A24: 5 | B24: Chi phí dịch vụ tư vấn pháp lý, dịch vụ báo giá và các dịch vụ hợp lý khác, thù lao trả cho ban đại diện quỹ/Giá trị tài sản ròng trung bình trong kỳ (%) Legal consultancy, price quotation and other appropriate service fees; remunerations paid to the Board of Representatives/Average NAV (%) | C24: 2268 | D24: 0.00025736212 | E24: 0.00025310264
A25: 6 | B25: Tỷ lệ chi phí hoạt động/Giá trị tài sản ròng trung bình trong kỳ (%) Operating expense/Average NAV (%) | C25: 2269 | D25: 0.022609735 | E25: 0.021190653
A26: 7 | B26: Tốc độ vòng quay danh mục trong kỳ (%) = (Tổng giá trị danh mục mua vào + tổng giá trị danh mục bán ra)/2/Giá trị tài sản ròng trung bình trong kỳ Portfolio turnover rate (%) = (Total value of purchase transactions + total value of sales transactions)/2/Average NAV (**) | C26: 2270 | D26: 0.034794841 | E26: 0.053838463
A27: II | B27: CÁC CHỈ TIÊU KHÁC OTHER INDICATORS | C27: 2272
A28: 1 | B28: Quy mô quỹ đầu kỳ (tính theo mệnh giá chứng chỉ quỹ) Fund scale at the beginning of the period (based on par value of fund certificate) | C28: 2273 | D28: 210018339800 | E28: 217450991500
B29: Tổng giá trị chứng chỉ quỹ đang lưu hành đầu kỳ Total value of outstanding Fund Certificate at the beginning of period | C29: 2274 | D29: 210018339800 | E29: 217450991500
B30: Tổng số lượng đơn vị quỹ đang lưu hành đầu kỳ Total number of outstanding Fund Certificate at the beginning of period | C30: 2275 | D30: 21001834 | E30: 21745099
A31: 2 | B31: Thay đổi quy mô quỹ trong kỳ (tính theo mệnh giá chứng chỉ quỹ) Change of Fund scale during the period (based on par value of fund certificate) | C31: 2276 | D31: -4308706200 | E31: -7432651700
B32: Thay đổi số lượng chứng chỉ quỹ trong kỳ Change of Number of Fund Certificates during the period | C32: 2276.1 | D32: -430870.62 | E32: -743265.17
B33: Thay đổi giá trị vốn trong kỳ (theo mệnh giá) Change in capital amount during the period (based on par value) | C33: 2276.2 | D33: -4308706200 | E33: -7432651700
B34: Số lượng đơn vị quỹ phát hành thêm trong kỳ Number of Fund Certificates subscribed during the period | C34: 2277 | D34: 51294.48 | E34: 34291.67
B35: Giá trị vốn huy động thêm trong kỳ (theo mệnh giá) Net subscription amount during the period (based on par value) | C35: 2278 | D35: 512944800 | E35: 342916700
B36: Số lượng đơn vị quỹ mua lại trong kỳ Number of Fund Certificates redeemed during the period | C36: 22781 | D36: -482165.1 | E36: -777556.84
B37: Giá trị vốn phải thanh toán trong kỳ khi đáp ứng lệnh của nhà đầu tư (theo mệnh giá) Net redemption amount during the period (based on par value) | C37: 22782 | D37: -4821651000 | E37: -7775568400
A38: 3 | B38: Quy mô quỹ cuối kỳ (tính theo mệnh giá chứng chỉ quỹ) Fund scale at the end of the period (based on par value) | C38: 2279 | D38: 205709633600 | E38: 210018339800
B39: Tổng giá trị chứng chỉ quỹ đang lưu hành cuối kỳ Total value of outstanding Fund Certificate at the end of the period | C39: 2280 | D39: 205709633600 | E39: 210018339800
B40: Tổng số lượng đơn vị quỹ đang lưu hành cuối kỳ Total number of outstanding Fund Certificate at the end of the period | C40: 2281 | D40: 20570963 | E40: 21001834
A41: 4 | B41: Tỷ lệ nắm giữ chứng chỉ quỹ của công ty quản lý quỹ và người có liên quan cuối kỳ Fund Management Company and related parties' ownership ratio at the end of the period | C41: 2282 | D41: 0.056885501 | E41: 0.055696662
A42: 5 | B42: Tỷ lệ nắm giữ chứng chỉ quỹ của 10 nhà đầu tư lớn nhất cuối kỳ Top 10 investors' ownership ratio at the end of the period | C42: 2283 | D42: 0.696 | E42: 0.6825
A43: 6 | B43: Tỷ lệ nắm giữ chứng chỉ quỹ của nhà đầu tư nước ngoài cuối kỳ Foreign investors' ownership ratio at the end of the period | C43: 2284 | D43: 0.5881 | E43: 0.576
A44: 7 | B44: Số nhà đầu tư tham gia vào quỹ, kể cả giao dịch ký danh Number of investors of the Fund at the end of the period | C44: 22841 | D44: 3170 | E44: 3184
A45: 8 | B45: Giá trị tài sản ròng trên một đơn vị quỹ cuối kỳ Net asset value per Fund Certificate at the end of period | C45: 2285 | D45: 41652.06 | E45: 41447.91
A46: Ghi chú / Notes:
A47: Các chỉ tiêu từ 1 đến 6 của "Chỉ tiêu về hiệu quả hoạt động" đã được điều chỉnh để phản ánh số liệu trên cơ sở hoạt động tròn năm bằng cách nhân các chỉ tiêu này với 12 (đối với báo cáo tháng), 4 (đối với báo cáo quý), 2 (đối với báo cáo bán niên), 1 (đối với báo cáo năm). All Indicator starting from number 1 to 6 of "Investment performance indicators" are annualized to reflect a rate that is based on a full year operation by multiplying these indicators with 12 (monthly report) or 4 (quarterly report) or 2 (semi-annual report) or 1 (annual report).
A48: (**) Không tính đến giá trị cam kết của các hợp đồng tương lai chỉ số. Excluding the committed value of the Index Futures contracts.
A50: ='Tong quat'!C16 -> Đại diện có thẩm quyền của Ngân hàng giám sát | D50: ='Tong quat'!F16 -> Đại diện có thẩm quyền của Công ty quản lý Quỹ
A51: ='Tong quat'!C17 -> Authorised Representative of Supervisory Bank | D51: ='Tong quat'!F17 -> Authorised Representative of Fund Management Company
A61: ='Tong quat'!C19 -> Ngân hàng TNHH MTV Standard Chartered (Việt Nam) | D61: ='Tong quat'!F19 -> Công ty Cổ phần Quản lý Quỹ Đầu tư Việt Nam
A62: ='Tong quat'!C20 -> Vũ Hương Giang | D62: ='Tong quat'!F20 -> Trần Thanh Tân
A63: ='Tong quat'!C21 -> Phó phòng Nghiệp vụ Dịch vụ Chứng khoán | D63: ='Tong quat'!F21 -> Tổng Giám đốc

Sheet GiaTriTaiSanRong_06129
A1: Phụ lục 26. Mẫu báo cáo thay đổi giá trị tài sản ròng, giao dịch chứng chỉ quỹ Appendix 26. Report on change of Net Asset Value, trading of Fund Certificate
A2: (Ban hành kèm theo Thông tư 183/2011/TT-BTC ngày 16 tháng 12 năm 2011 hướng dẫn về việc thành lập và quản lý quỹ mở) (Issued in association with Circular 183/2011/TT-BTC dated 16 December 2011 guiding establishment and management of the Open-Ended Fund)
A3: BÁO CÁO THAY ĐỔI GIÁ TRỊ TÀI SẢN RÒNG, GIAO DỊCH CHỨNG CHỈ QUỸ REPORT ON CHANGE OF NET ASSET VALUE, TRADING OF FUND CERTIFICATE
A5: ='Tong quat'!C2 -> Tháng 10 năm 2019 / Oct 2019
A7: Tên Công ty quản lý quỹ: | D7: ='Tong quat'!D5 -> Công ty Cổ phần Quản lý Quỹ Đầu tư Việt Nam
A8: Fund Management Company: | D8: ='Tong quat'!D6 -> Vietnam Investment Fund Management Joint Stock Company
A9: Tên ngân hàng giám sát: | D9: ='Tong quat'!D7 -> Ngân hàng TNHH Một thành viên Standard Chartered (Việt Nam)
A10: Supervising bank: | D10: ='Tong quat'!D8 -> Standard Chartered Bank (Vietnam) Limited
A11: Tên Quỹ: | D11: ='Tong quat'!D9 -> Quỹ Đầu tư Chứng khoán Việt Nam
A12: Fund name: | D12: ='Tong quat'!D10 -> Vietnam Securities Investment Fund(VFMVF1)
A13: Ngày lập báo cáo: | D13: ='Tong quat'!D11 -> Ngày 04 tháng 11 năm 2019
A14: Reporting Date: | D14: ='Tong quat'!D12 -> 04 Nov 2019
A18: STT No | C18: Nội dung Item | D18: Mã số Code | E18: =BCKetQuaHoatDong_06028!D18 -> Tháng 10 năm 2019 Oct 2019 | F18: =BCKetQuaHoatDong_06028!E18 -> Tháng 09 năm 2019 Sep 2019
A19: I | C19: I. Giá trị tài sản ròng của Quỹ mở (NAV) đầu kỳ Net Asset Value (NAV) at the beginning of period | D19: 4060 | E19: 870482187950 | F19: 882204395196
A20: II | C20: II. Thay đổi NAV so với kỳ trước (= II.1 + II.2), trong đó: Change of NAV during the period (= II.1 + II.2), of which: | D20: 4061 | E20: 4194581295 | F20: 18755924050
B21: II.1 | C21: II.1 Thay đổi NAV do biến động thị trường và hoạt động giao dịch của Quỹ mở trong kỳ Changes of NAV due to market fluctuation and the fund's investment during the period | D21: 4062 | E21: 4194581295 | F21: 18755924050
B22: II.2 | C22: II.2 Thay đổi NAV do phân chia Lợi nhuận/Tài sản của Quỹ mở cho Nhà đầu tư trong kỳ Change of NAV due to profit/asset distribution to investors during the period | D22: 4063 | E22: 0 | F22: 0
A23: III | C23: III. Thay đổi NAV do mua lại, phát hành thêm Chứng chỉ quỹ (= III.1 + III.2) Change of NAV due to redemption, subscription of Fund Certificate (= III.1 + III.2) | D23: 4064 | E23: -17853610523 | F23: -30478131296
B24: III.1 | C24: III.1 Khoản thu từ việc phát hành bổ sung Chứng chỉ quỹ Increase from Subscription of Fund Certificate | D24: 4065 | E24: 2119427539 | F24: 1397279179
B25: III.2 | C25: III.2 Khoản thanh toán từ việc mua lại Chứng chỉ quỹ Decrease from Redemption of Fund Certificate | D25: 4066 | E25: -19973038062 | F25: -31875410475
A26: IV | C26: IV. Giá trị tài sản ròng của Quỹ mở cuối kỳ (= I + II + III) NAV at the end of period (= I + II + III) | D26: 4067 | E26: 856823158722 | F26: 870482187950
A27: V | C27: V. Giá trị tài sản ròng trên một đơn vị quỹ cuối kỳ NAV per unit at the end of period | D27: 4067.1 | E27: 41652.06 | F27: 41447.91
A30: ='Tong quat'!C16 -> Đại diện có thẩm quyền của Ngân hàng giám sát | E30: ='Tong quat'!F16 -> Đại diện có thẩm quyền của Công ty quản lý Quỹ
A31: ='Tong quat'!C17 -> Authorised Representative of Supervisory Bank | E31: ='Tong quat'!F17 -> Authorised Representative of Fund Management Company
A41: ='Tong quat'!C19 -> Ngân hàng TNHH MTV Standard Chartered (Việt Nam) | E41: ='Tong quat'!F19 -> Công ty Cổ phần Quản lý Quỹ Đầu tư Việt Nam
A42: ='Tong quat'!C20 -> Vũ Hương Giang | E42: ='Tong quat'!F20 -> Trần Thanh Tân
A43: ='Tong quat'!C21 -> Phó phòng Nghiệp vụ Dịch vụ Chứng khoán | E43: ='Tong quat'!F21 -> Tổng Giám đốc

Sheet BCHoatDongVay_06026
A1: Phụ lục 31: Mẫu Báo cáo hoạt động vay, giao dịch mua bán lại của quỹ Appendix 31: Report on borrowing operation, repo/reverse repo transactions of the fund
A2: (Ban hành kèm theo Thông tư 183/2011/TT-BTC ngày 16 tháng 12 năm 2011 hướng dẫn về việc thành lập và quản lý quỹ mở) (Issued in association with Circular 183/2011/TT-BTC dated 16 December 2011 guiding establishment and management of the Open-Ended Fund)
A3: BÁO CÁO HOẠT ĐỘNG VAY, GIAO DỊCH MUA BÁN LẠI CỦA QUỸ REPORT ON BORROWING OPERATION, REPO/REVERSE REPO TRANSACTIONS OF THE FUND
A5: Tháng 10 năm 2019/Oct 2019
A7: Tên Công ty quản lý quỹ: | G7: Công ty Cổ phần Quản lý Quỹ Đầu tư Việt Nam
A8: Fund Management Company: | G8: Vietnam Investment Fund Management Joint Stock Company
A9: Tên ngân hàng giám sát: | G9: Ngân hàng TNHH một thành viên Standard Chartered (Việt Nam)
A10: Supervising bank: | G10: Standard Chartered Bank (Vietnam) Ltd.
A11: Tên Quỹ: | G11: Quỹ đầu tư Chứng khoán Việt Nam
A12: Fund name: | G12: Vietnam Securities Investment Fund (VFMVF1)
A13: Ngày lập báo cáo: | G13: Ngày 04 tháng 11 năm 2019
A14: Reporting Date: | G14: 43773
A16: STT No. | B16: Nội dung hoạt động (nêu chi tiết theo mục tiêu và đối tác) Description | C16: Mã chỉ tiêu Code | D16: Đối tác Counterparty | E16: Mục tiêu/Tài sản đảm bảo Collateral | F16: Kỳ hạn Term | G16: Giá trị khoản vay hoặc khoản cho vay Amount | H16: Thời điểm giao dịch As at transaction date | J16: Thời điểm báo cáo As at reporting date
H17: Ngày tháng năm Date | I17: Tỷ lệ giá trị hợp đồng/giá trị tài sản ròng của quỹ Balance/NAV | J17: Ngày tháng năm Date | K17: Tỷ lệ giá trị hợp đồng/giá trị tài sản ròng của quỹ Balance/NAV
A18: 1.1 | B18: Vay tiền (nêu chi tiết từng hợp đồng) Borrowings (detail by each contract) | C18: 2287
A19: I | B19: Tỷ lệ tiền vay từ các hợp đồng/giá trị tài sản ròng Borrowings/NAV | C19: 2288
A20: 1.2 | B20: Hợp đồng Repo (nêu chi tiết từng hợp đồng) Repo (detail by each contract) | C20: 2289
A21: II | B21: Tổng giá trị các hợp đồng Repo/giá trị tài sản ròng Repo/NAV | C21: 2290
A22: A | B22: Tổng giá trị các khoản vay/giá trị tài sản ròng (=I+II) Total Borrowings, Repo/NAV | C22: 2291
A23: 2.1 | B23: Cho vay chứng khoán (nêu chi tiết từng hợp đồng) Margin (detail by each contract) | C23: 2292
A24: I | B24: Tổng giá trị các hợp đồng/giá trị tài sản ròng của quỹ Total Margin/NAV | C24: 2293
A25: 2.2 | B25: Hợp đồng Reverse Repo (nêu chi tiết từng hợp đồng) Reverse Repo (Detail by each contract) | C25: 2295
A26: II | B26: Tổng giá trị các hợp đồng/giá trị tài sản ròng của quỹ Reverse Repo/NAV | C26: 2296
A27: B | B27: Tổng giá trị các khoản cho vay/giá trị tài sản ròng (=III + IV) Total Loans/NAV | C27: 2297
A32: Đại diện có thẩm quyền của Ngân hàng giám sát | I32: Đại diện có thẩm quyền của Công ty quản lý Quỹ
A33: Authorised Representative of Supervisory Bank | I33: Authorised Representative of Fund Management Company
A43: Ngân hàng TNHH MTV Standard Chartered (Việt Nam) | I43: Công ty Cổ phần Quản lý Quỹ đầu tư Việt Nam
A44: Vũ Hương Giang | I44: Trần Thanh Tân
A45: Phó Phòng Nghiệp vụ Dịch vụ Chứng khoán | I45: Tổng Giám đốc

Sheet LogoFMS
D1: VFMVF1
A2: FUNDCODE | B2: FUNDNAME | C2: LOGO
A3: VFMVEI | B3: Quỹ Đầu tư Cổ phiếu Việt Nam
A4: VFMVF1 | B4: Quỹ Đầu tư Chứng khoán Việt Nam
A5: VFMVF4 | B5: Quỹ Đầu tư Doanh nghiệp hàng đầu Việt Nam
A6: VFMVFA | B6: Quỹ Đầu tư Năng Động Việt Nam
A7: VFMVFB | B7: Quỹ Đầu tư Trái phiếu Việt Nam
A8: VFMVFC | B8: Quỹ đầu tư Định Hướng Bảo Toàn Vốn Việt Nam
A9: TCEF1 | B9: Quỹ Đầu tư Cổ phiếu Techcom
A10: TCBF | B10: Quỹ Đầu tư Cổ phiếu Techcom
A11: MBEF1 | B11: Quỹ Đầu tư JAPAN ASIA MB CAPITAL
A12: MBVF | B12: Quỹ Đầu tư Giá trị MB Capital
A13: SSISCA | B13: Quỹ Đầu tư Lợi thế Cạnh tranh Bền vững SSI
A14: VCBBCF | B14: Quỹ Đầu tư Cổ Phiếu Hàng Đầu VCBF
... A39: MAGEF | B39: Quỹ đầu tư cổ phiếu tăng trưởng Mira asset Việt Nam
