Workbook
Name addlogo: INDEX(LogoFMS!$C$3:$C$76,MATCH(LogoFMS!$D$1,LogoFMS!$A$3:$A$76,0))

Sheet TONGQUAN
A1: Kỳ báo cáo: | C1: Tại ngày 31 tháng 12 năm 2024 / As at 31 Dec 2024
C2: Tháng 12 năm 2024 / Dec 2024
A4: Thông tin chung:
C5: Tên Công ty quản lý quỹ: | D5: Công ty Cổ phần Quản lý Quỹ Đầu tư Dragon Capital Việt Nam
C6: Fund Management Company: | D6: Dragon Capital Vietfund Management Joint Stock Company
C7: Tên ngân hàng giám sát: | D7: Ngân hàng TNHH Một thành viên Standard Chartered (Việt Nam)
C8: Supervising bank: | D8: Standard Chartered Bank (Vietnam) Limited
C9: Tên Quỹ: | D9: Quỹ Đầu tư Chứng khoán Năng động DC
C10: Fund name: | D10: DC Dynamic Securities Fund (DCDS)
C11: Ngày lập báo cáo: | D11: Ngày 02 tháng 01 năm 2025
C12: Reporting Date: | D12: 02 Jan 2025
A14: Người ký báo cáo:
C16: Đại diện có thẩm quyền của Ngân hàng giám sát | F16: Đại diện có thẩm quyền của Công ty quản lý Quỹ
C17: Authorised Representative of Supervisory Bank | F17: Authorised Representative of Fund Management Company
C19: Ngân hàng TNHH MTV Standard Chartered (Việt Nam) | F19: =D5 -> Công ty Cổ phần Quản lý Quỹ Đầu tư Dragon Capital Việt Nam
C20: Vũ Quang Phan | F20: Lê Hoàng Anh
C21: Phó phòng Dịch vụ nghiệp vụ giám sát Quỹ | F21: Quyền Giám đốc nghiệp vụ hỗ trợ đầu tư

Sheet BCTaiSan_06027
A1: Phụ lục XXVI. Mẫu báo cáo về hoạt động của Quỹ Appendix XXVI. Report on Fund's Operation
A2: (Ban hành kèm theo Thông tư số 98/2020/TT-BTC ngày 16 tháng 11 năm 2020 của Bộ trưởng Bộ Tài Chính về hướng dẫn hoạt động và quản lý quỹ đầu tư chứng khoán) (Issued in association with Circular 98/2020/TT-BTC dated 16 November 2020 of the Minister of Finance on guiding the operation and management of the securities investment funds)
A3: BÁO CÁO HOẠT ĐỘNG ĐẦU TƯ CỦA QUỸ MỞ REPORT ON OPEN ENDED FUND'S INVESTMENT ACTIVITIES
A5: =TONGQUAN!C1 -> Tại ngày 31 tháng 12 năm 2024 / As at 31 Dec 2024
A7: Tên Công ty quản lý quỹ: | C7: =TONGQUAN!D5 -> Công ty Cổ phần Quản lý Quỹ Đầu tư Dragon Capital Việt Nam
A8: Fund Management Company: | C8: =TONGQUAN!D6 -> Dragon Capital Vietfund Management Joint Stock Company
A9: Tên ngân hàng giám sát: | C9: =TONGQUAN!D7 -> Ngân hàng TNHH Một thành viên Standard Chartered (Việt Nam)
A10: Supervising bank: | C10: =TONGQUAN!D8 -> Standard Chartered Bank (Vietnam) Limited
A11: Tên Quỹ: | C11: =TONGQUAN!D9 -> Quỹ Đầu tư Chứng khoán Năng động DC
A12: Fund name: | C12: =TONGQUAN!D10 -> DC Dynamic Securities Fund (DCDS)
A13: Ngày lập báo cáo: | C13: =TONGQUAN!D11 -> Ngày 02 tháng 01 năm 2025
A14: Reporting Date: | C14: =TONGQUAN!D12 -> 02 Jan 2025
A16: A. | B16: BÁO CÁO CHUNG VỀ HOẠT ĐỘNG ĐẦU TƯ CỦA QUỸ/GENERAL INFORMATION ON FUND'S INVESTMENT ACTIVITIES
A17: I | B17: BÁO CÁO VỀ TÀI SẢN / ASSET REPORT
A18: STT No | B18: Nội dung Indicator | C18: Mã chỉ tiêu Code | D18: Ngày 31 tháng 12 năm 2024 As at 31 Dec 2024 | E18: Ngày 30 tháng 11 năm 2024 As at 30 Nov 2024 | F18: %/cùng kỳ năm trước %/against last year
A19: I | B19: TÀI SẢN ASSETS | C19: 2200
A20: I.1 | B20: Tiền và các khoản tương đương tiền Cash and Cash Equivalents | C20: 2201 | D20: 133059118550 | E20: 104882199495 | F20: 2.2236303
B21: Tiền Cash | C21: 2202
A22: ... | B22: ... | C22: ... | D22: ... | E22: ... | F22: ...
B23: Tiền gửi ngân hàng Cash at bank | C23: 2203 | D23: 133059118550 | E23: 104882199495 | F23: 2.2236303
A24: ... | B24: ... | C24: ... | D24: ... | E24: ... | F24: ...
B25: Tiền gửi của nhà đầu tư cho hoạt động mua chứng chỉ quỹ Cash at bank for Fund's subscription | C25: 2203.1 | D25: 4222973819 | E25: 13538887098 | F25: 2.9158115
B26: Tiền phải trả cho Nhà đầu tư về cổ tức và mua lại chứng chỉ quỹ Cash at bank for Fund's dividend payment and redemption | C26: 2203.2 | D26: 183572977 | E26: 169629402 | F26: 1.3492917
B27: Tiền gửi ngân hàng cho hoạt động của Quỹ Cash at bank for Fund's operation | C27: 2203.3 | D27: 128652571754 | E27: 91173682995 | F27: 2.2084635
B28: Tiền gửi ký quỹ cho hoạt động đầu tư chứng khoán phái sinh Margin account for trading derivatives | C28: 2203.4 | D28: 0 | E28: 0
B29: Tiền, tương đương tiền Cash, cash equivalents | C29: 2203.5 | D29: 0 | E29: 0
A30: I.2 | B30: Các khoản đầu tư (kê chi tiết) Investments | C30: 2205 | D30: 2779933654900 | E30: 2781782932900 | F30: 1.8922994
A31: ... | B31: ... | C31: ... | D31: ... | E31: ... | F31: ...
B32: Cổ phiếu, chứng chỉ quỹ niêm yết Listed Shares, fund certificates | C32: 2205.1 | D32: 2779933654900 | E32: 2781782932900 | F32: 1.9147962
B33: Cổ phiếu, chứng chỉ quỹ chưa niêm yết Unlisted Shares, fund certifictes | C33: 2205.2 | D33: 0 | E33: 0
B34: Trái phiếu Bonds | C34: 2205.3 | D34: 0 | E34: 0 | F34: 0
B35: Công cụ thị trường tiền tệ Money market instruments | C35: 2205.4 | D35: 0 | E35: 0
B36: Hợp đồng tiền gửi có kỳ hạn trên ba (03) tháng Deposits with term over three (03) months | C36: 2205.5 | D36: 0 | E36: 0
B37: Quyền mua chứng khoán Investment - Rights | C37: 2205.6 | D37: 0 | E37: 0 | F37: 0
B38: Hợp đồng tương lai chỉ số Index future contracts | C38: 2205.7 | D38: 0 | E38: 0
B39: Đầu tư khác Other investments | C39: 2205.8 | D39: 0 | E39: 0
B40: Hợp đồng mua lại đảo ngược Reverse repo contracts | C40: 2205.9 | D40: 0 | E40: 0
A41: I.3 | B41: Thu từ cho thuê bất động sản đầu tư (không áp dụng) Receivables from rental of investment property (not applicable) | C41: 2220 | D41: 0 | E41: 0
A42: ... | B42: ... | C42: ... | D42: ... | E42: ... | F42: ...
A43: I.4 | B43: Cổ tức, trái tức được nhận Dividend, Coupon receivables | C43: 2206 | D43: 1534400000 | E43: 7772558982 | F43: 0.5202472
A44: ... | B44: ... | C44: ... | D44: ... | E44: ... | F44: ...
B45: Phải thu cổ tức Dividend receivables | C45: 2206.1 | D45: 1534400000 | E45: 7772558982 | F45: 0.53639097
B46: Phải thu trái tức Coupon receivables | C46: 2206.2 | D46: 0 | E46: 0 | F46: 0
A47: I.5 | B47: Lãi được nhận Interest receivables | C47: 2207 | D47: 0 | E47: 0
A48: ... | B48: ... | C48: ... | D48: ... | E48: ... | F48: ...
B49: Phải thu lãi tiền gửi Interest receivable from bank deposits | C49: 2207.1 | D49: 0 | E49: 0
B50: Phải thu lãi công cụ thị trường tiền tệ Interest receivable from Money market instruments | C50: 2207.2 | D50: 0 | E50: 0
B51: Phải thu lãi hợp đồng mua lại đảo ngược Interest receivable from reverse repo contracts | C51: 2207.3 | D51: 0 | E51: 0
A52: I.6 | B52: Tiền bán bất động sản chờ thu (không áp dụng) Real Estate Proceeds Receivables (not applicale) | C52: 2221 | D52: 0 | E52: 0
A53: ... | B53: ... | C53: ... | D53: ... | E53: ... | F53: ...
A54: I.7 | B54: Tiền bán chứng khoán chờ thu Securities Trading Receivables | C54: 2208 | D54: 117900715000 | E54: 26154990000 | F54: 4.1262937
A55: ... | B55: ... | C55: ... | D55: ... | E55: ... | F55: ...
A56: I.8 | B56: Các khoản phải thu khác Other Receivables | C56: 2210 | D56: -866400000 | E56: -866400000 | F56: 1
A57: ... | B57: ... | C57: ... | D57: ... | E57: ... | F57: ...
B58: Dự phòng giảm giá tài sản nhận thế chấp Impairment of devaluation of pledged assets | C58: 2210.1 | D58: 0 | E58: 0
B59: Dự phòng nợ phải thu khó đòi Provision for doubtful debt | C59: 2210.2 | D59: -866400000 | E59: -866400000 | F59: 1
B60: Các khoản phải thu khác Other Receivables | C60: 2210.3 | D60: 0 | E60: 0
A61: I.9 | B61: Các tài sản khác Other Assets | C61: 2211 | D61: 0 | E61: 12283629
A62: ... | B62: ... | C62: ... | D62: ... | E62: ... | F62: ...
A63: I.10 | B63: TỔNG TÀI SẢN TOTAL ASSETS | C63: 2212 | D63: 3031561488450 | E63: 2919738565006 | F63: 1.9438423
A64: II | B64: NỢ LIABILITIES | C64: 2213
A65: II.1 | B65: Tiền phải thanh toán mua bất động sản (không áp dụng) Real Estate Trading Payables (not applicable) | C65: 2222 | D65: 0 | E65: 0
A66: ... | B66: ... | C66: ... | D66: ... | E66: ... | F66: ...
A67: II.2 | B67: Tiền phải thanh toán mua chứng khoán Securities Trading Payables | C67: 2214 | D67: 124365310000 | E67: 88280153300 | F67: 2.8467802
A68: ... | B68: ... | C68: ... | D68: ... | E68: ... | F68: ...
A69: II.3 | B69: Các khoản phải trả khác Other Payables | C69: 2215 | D69: 42654086153 | E69: 28603373790 | F69: 4.5014952
A70: ... | B70: ... | C70: ... | D70: ... | E70: ... | F70: ...
B71: Phải trả nhà đầu tư Payables to investors | C71: 2215.1 | D71: 36341325300 | E71: 23168884536 | F71: 5.9801843
B72: Phải trả cho nhà đầu tư chờ mua chứng chỉ quỹ Subscription Pending allotment | C72: 2215.1.1 | D72: 4222973819 | E72: 13538887098 | F72: 2.9158115
B73: Phải trả nhà đầu tư trên tài sản giữ hộ Payables to investors for investment bought on behalf | C73: 2215.1.2 | D73: 0 | E73: 0
B74: Phải trả nhà đầu tư trên cổ tức đã thu Payables to investors for collected dividend | C74: 2215.1.3 | D74: 0 | E74: 0
B75: Phải trả cho Nhà đầu tư về mua lại chứng chỉ quỹ Redemption payable to investors | C75: 2215.1.4 | D75: 32118351481 | E75: 9629997438 | F75: 6.9390232
B76: Thuế và các khoản phải nộp Nhà nước Tax payables and obligations to the State Budget | C76: 2215.2 | D76: 178195905 | E76: 46065096 | F76: 7.3231664
B77: Phải trả phí phát hành, mua lại chứng chỉ quỹ cho Đại lý phân phối và Công ty quản lý quỹ Subscription and Redemption fee payable to distributors and Fund Management Company | C77: 2215.3 | D77: 452294040 | E77: 286462921 | F77: 2.1453107
B78: Phải trả thu nhập cho nhà đầu tư Income payable to investors | C78: 2215.4 | D78: 39925000 | E78: 39925000 | F78: 1
B79: Phải trả thù lao Ban đại diện quỹ Remuneration Payable to Fund's Board of Representatives | C79: 2215.5 | D79: 22265027 | E79: 21248634 | F79: 0.92770946
B80: Phải trả phí quản lý cho công ty quản lý quỹ Management fee payable | C80: 2215.6 | D80: 4673049304 | E80: 4259301281 | F80: 1.908897
B81: Phải trả phí quản trị quỹ Fund Administration fee payable | C81: 2215.7 | D81: 65901975 | E81: 60067069 | F81: 1.9088968
B82: Phải trả phí giám sát Supervisory service fee payable | C82: 2215.8 | D82: 105443164 | E82: 96107312 | F82: 1.908897
B83: Phí giao dịch Transaction fee | C83: 2215.9 | D83: 265462170 | E83: 134872004 | F83: 1.9881155
B84: Phải trả phí môi giới Brokerage fee payable | C84: 2215.9.1 | D84: 265462170 | E84: 134872004 | F84: 1.9881155
B85: Phải trả phí phát hành thanh toán bù trừ chứng khoán Clearing Settlement fee payable | C85: 2215.9.2 | D85: 0 | E85: 0
B86: Trích trước phí lưu ký tài sản Quỹ mở Accrued expense for Custodian fee | C86: 2215.10 | D86: 165357422 | E86: 162370281 | F86: 1.5701053
B87: Phí lưu ký - bảo quản tài sản Custodian service - Safe Custody Fee | C87: 2215.10.1 | D87: 95857422 | E87: 87370281 | F87: 1.9088969
B88: Phí lưu ký - giao dịch chứng khoán Custodian service - Transaction fee | C88: 2215.10.2 | D88: 58500000 | E88: 64000000 | F88: 1.3265306
B89: Phí lưu ký cho chứng khoán cơ sở, phí quản lý vị thế và tài sản phái sinh trả cho VSDC Custodian service - Depository fee, Position and Margin management fee paid to VSDC | C89: 2215.10.3 | D89: 11000000 | E89: 11000000 | F89: 1
B90: Phải trả phí kiểm toán Audit fee payable | C90: 2215.11 | D90: 102480000 | E90: 85430000 | F90: 1
B91: Phải trả phí họp đại hội thường niên General meeting expense payable | C91: 2215.12 | D91: 45003880 | E91: 38391936
B92: Phải trả phí báo cáo thường niên Annual report fee payable | C92: 2215.13 | D92: 0 | E92: 0
B93: Phải trả phí dịch vụ đại lý chuyển nhượng Transfer Agency fee payable | C93: 2215.14 | D93: 13200000 | E93: 13200000 | F93: 1
B94: Dự chi phí tính giá trị tài sản ròng tham chiếu (iNAV) cho HOSE Service fee payable to HOSE for calculating iNAV | C94: 2215.15 | D94: 0 | E94: 0
B95: Dự chi phí cấp quyền sử dụng chỉ số cho HOSE Authorising index service fee payable to HOSE | C95: 2215.16 | D95: 0 | E95: 0
B96: Phải trả khác Other payables | C96: 2215.17 | D96: 184182966 | E96: 191047720 | F96: 0.88902456
B97: Phải trả phí báo giá Price feed fee payable | C97: 2215.17.1 | D97: 0 | E97: 0 | F97: 0
B98: Trích trước phí công tác, họp của ban đại diện Accrued expense for Fund's Board of Representatives travelling, meeting | C98: 2215.17.2 | D98: 0 | E98: 0
B99: Trích trước phí quản lý thường niên trả UBCKNN Accrued expense for Annual Management Fee pay to SSC | C99: 2215.17.3 | D99: 0 | E99: 6864754
B100: Phải trả khác Other payables | C100: 2215.17.4 | D100: 184182966 | E100: 184182966 | F100: 1.0027698
B101: Vay ngắn hạn - hợp đồng repo Short-term loans - Repo contracts | C101: 2215.18 | D101: 0 | E101: 0
B102: Gốc hợp đồng repo Principal of repo contracts | C102: 2215.18.1 | D102: 0 | E102: 0
B103: Trích trước lãi vay ngắn hạn Accrued Interest Expense | C103: 2215.18.2 | D103: 0 | E103: 0
...

Sheet BCKetQuaHoatDong_06028
A1: Phụ lục XXVI. Mẫu báo cáo về hoạt động của Quỹ Appendix XXVI. Report on Fund's Operation
A2: (Ban hành kèm theo Thông tư số 98/2020/TT-BTC ngày 16 tháng 11 năm 2020 của Bộ trưởng Bộ Tài Chính về hướng dẫn hoạt động và quản lý quỹ đầu tư chứng khoán) (Issued in association with Circular 98/2020/TT-BTC dated 16 November 2020 of the Minister of Finance on guiding the operation and management of the securities investment funds)
A3: BÁO CÁO HOẠT ĐỘNG ĐẦU TƯ CỦA QUỸ MỞ REPORT ON OPEN ENDED FUND'S INVESTMENT ACTIVITIES
A5: Tháng 12 năm 2024 / Dec 2024
A7: Tên Công ty quản lý quỹ: | C7: Công ty Cổ phần Quản lý Quỹ Đầu tư Dragon Capital Việt Nam
A8: Fund Management Company: | C8: Dragon Capital Vietfund Management Joint Stock Company
A9: Tên ngân hàng giám sát: | C9: Ngân hàng TNHH Một thành viên Standard Chartered (Việt Nam)
A10: Supervising bank: | C10: Standard Chartered Bank (Vietnam) Limited
A11: Tên Quỹ: | C11: Quỹ Đầu tư Chứng khoán Năng động DC
A12: Fund name: | C12: DC Dynamic Securities Fund (DCDS)
A13: Ngày lập báo cáo: | C13: Ngày 02 tháng 01 năm 2025
A14: Reporting Date: | C14: 02 Jan 2025
A16: A. | B16: BÁO CÁO CHUNG VỀ HOẠT ĐỘNG ĐẦU TƯ CỦA QUỸ/GENERAL INFORMATION ON FUND'S INVESTMENT ACTIVITIES
A17: II | B17: BÁO CÁO KẾT QUẢ HOẠT ĐỘNG / PROFIT AND LOSS REPORT
A18: STT No | B18: Nội dung Indicator | C18: Mã chỉ tiêu Code | D18: Tháng 12 năm 2024 Dec 2024 | E18: Tháng 11 năm 2024 Nov 2024 | F18: Lũy kế từ đầu năm Accumulated from beginning of year
A19: I | B19: Thu nhập từ hoạt động đầu tư Income from Investment Activities | C19: 2220 | D19: 4307598232 | E19: 7162755167 | F19: 41776161931
A20: 1 | B20: Thu từ bất động sản cho thuê (không áp dụng) Income from rental property (not applicable) | C20: 2223 | D20: 0 | E20: 0 | F20: 0
A21: ... | B21: ... | C21: ... | D21: ... | E21: … | F21: …
A22: 2 | B22: Cổ tức, trái tức được nhận Dividend income, interest income from bonds | C22: 2221 | D22: 4287321000 | E22: 7126024582 | F22: 41509953444
A23: ... | B23: ... | C23: ... | D23: ... | E23: … | F23: …
B24: Cổ tức được nhận Dividends income | C24: 2221.1 | D24: 4287321000 | E24: 7126024582 | F24: 41465569882
B25: Trái tức được nhận Interest income from bonds | C25: 2221.2 | D25: 0 | E25: 0 | F25: 44383562
A26: 3 | B26: Lãi được nhận Interest income | C26: 2222 | D26: 20277232 | E26: 36730585 | F26: 266208487
A27: ... | B27: ... | C27: ... | D27: ... | E27: ... | F27: ...
B28: Lãi tiền gửi ngân hàng Interest income from bank deposits | C28: 2222.1 | D28: 20277232 | E28: 36730585 | F28: 266208487
B29: Lãi công cụ thị trường tiền tệ Interest income from Money market instruments | C29: 2222.2 | D29: 0 | E29: 0 | F29: 0
B30: Lãi hợp đồng mua lại đảo ngược Interest income from reverse repo contracts | C30: 2222.3 | D30: 0 | E30: 0 | F30: 0
A31: 4 | B31: Các khoản thu nhập khác Other incomes | C31: 2223 | D31: 0 | E31: 0 | F31: 0
A32: ... | B32: ... | C32: ... | D32: ... | E32: ... | F32: ...
B33: Thu nhập khác về đầu tư Other investment incomes | C33: 2223.1 | D33: 0 | E33: 0 | F33: 0
B34: Thu nhập khác Other incomes | C34: 2223.2 | D34: 0 | E34: 0 | F34: 0
B35: Chi phí dự phòng nợ phải thu khó đòi về cổ tức, tiền lãi và xử lý tổn thất nợ phải thu khó đòi về cổ tức, tiền lãi Provision expense for bad debts from dividends, interest income and written off bad debts from dividends, interest income | C35: 2223.3 | D35: 0 | E35: 0 | F35: 0
A36: II | B36: Chi phí Expenses | C36: 2224 | D36: 6793005997 | E36: 6898866088 | F36: 66747490096
A37: 1 | B37: Chi phí quản lý trả cho Công ty quản lý quỹ Management Fee paid to Fund Management Company | C37: 2225 | D37: 4673049304 | E37: 4259301281 | F37: 41186711622
A38: ... | B38: ... | C38: ... | D38: ... | E38: ... | F38: ...
A39: 2 | B39: Chi phí lưu ký, giám sát trả cho Ngân hàng Giám sát/VSDC Custody fee, Supervising fee paid to Supervising Bank/VSDC | C39: 2226 | D39: 272168709 | E39: 259406085 | F39: 2518707531
A40: ... | B40: ... | C40: ... | D40: ... | E40: ... | F40: ...
B41: Chi phí dịch vụ lưu ký - bảo quản tài sản Custodian service - Safe Custody Fee | C41: 2226.1 | D41: 95857422 | E41: 87370281 | F41: 844855620
B42: Chi phí dịch vụ lưu ký - giao dịch chứng khoán Custodian service - Transaction fee | C42: 2226.2 | D42: 53300000 | E42: 60300000 | F42: 594330000
B43: Chi phí dịch vụ lưu ký cho chứng khoán cơ sở, phí quản lý vị thế và tài sản phái sinh trả cho VSDC Custodian service - Depository fee, Position and Margin management fee paid to VSDC | C43: 2226.3 | D43: 17568123 | E43: 15628492 | F43: 150180722
B44: Chi phí giám sát Supervisory fee | C44: 2226.4 | D44: 105443164 | E44: 96107312 | F44: 929341189
A45: 3 | B45: Chi phí quản trị quỹ và các chi phí khác mà công ty quản lý quỹ trả cho tổ chức cung cấp dịch vụ có liên quan Fund Administration Fee, and other fees paid to relevant Fund's service providers | C45: 2227 | D45: 79101975 | E45: 73267069 | F45: 739238242
A46: ... | B46: ... | C46: ... | D46: ... | E46: ... | F46: ...
B47: Chi phí quản trị Quỹ Fund Administration Fee | C47: 2227.1 | D47: 65901975 | E47: 60067069 | F47: 580838242
B48: Chi phí dịch vụ Đại lý Chuyển nhượng Transfer Agency Fee | C48: 2227.2 | D48: 13200000 | E48: 13200000 | F48: 158400000
A49: 4 | B49: Chi phí dịch vụ quản lý bất động sản (không áp dụng) Real Estate Management Service fee (not applicable) | D49: 0 | E49: 0 | F49: 0
A50: ... | B50: ... | C50: ... | D50: ... | E50: ... | F50: ...
A51: 5 | B51: Chi phí dịch vụ định giá bất động sản (không áp dụng) Real estate valuation service fees (not applicable) | D51: 0 | E51: 0 | F51: 0
A52: ... | B52: ... | C52: ... | D52: ... | E52: ... | F52: ...
A53: 6 | B53: Chi phí kiểm toán trả cho tổ chức kiểm toán Audit fee | C53: 2228 | D53: 17050000 | E53: 16500000 | F53: 199789475
A54: ... | B54: ... | C54: ... | D54: ... | E54: ... | F54: ...
A55: 7 | B55: Chi phí dịch vụ tư vấn pháp lý, dịch vụ báo giá và các dịch vụ hợp lý khác, thù lao trả cho ban đại diện quỹ Legal consultancy expenses, price feed fee, other valid expenses, remuneration paid to Fund's Board of Representatives | C55: 2229 | D55: 16657058 | E55: 16506831 | F55: 244465027
A56: ... | B56: ... | C56: ... | D56: ... | E56: ... | F56: ...
B57: Thù lao Ban đại diện Quỹ Remuneration of Fund's Board of Representatives | C57: 2229.1 | D57: 13016393 | E57: 12983607 | F57: 154265027
B58: Chi phí cung cấp báo giá chứng khoán Price feed fee | C58: 2229.2 | D58: 0 | E58: 0 | F58: 47000000
B59: Chi phí dịch vụ tư vấn pháp lý Legal consultancy expenses | C59: 2229.3 | D59: 3640665 | E59: 3523224 | F59: 43200000
A60: 8 | B60: Chi phí dự thảo, in ấn, gửi bản cáo bạch, bản cáo bạch tóm tắt, báo cáo tài chính, xác nhận giao dịch, sao kê tài khoản và các tài liệu khác cho nhà đầu tư; chi phí công bố thông tin của quỹ; chi phí tổ chức họp đại hội nhà đầu tư, ban đại diện quỹ Fee for drafting, printing, distribution of prospectus, summarised prospectus, financial statements, transaction confirmations, account statements and other documents to investors; information disclosure fee; fee for organising annual general meeting, board of representatives meeting | C60: 2230 | D60: 15254908 | E60: 14762781 | F60: 149108024
A61: ... | B61: ... | C61: ... | D61: ... | E61: ... | F61: ...
B62: Chi phí họp Đại hội Quỹ Meeting expenses | C62: 2230.1 | D62: 15254908 | E62: 14762781 | F62: 149108024
B63: Chi phí báo cáo thường niên Annual report expenses | C63: 2230.2 | D63: 0 | E63: 0 | F63: 0
B64: Chi phí họp, công tác của Ban đại diện Fund's Board of Representatives meeting, travelling expenses | C64: 2230.3 | D64: 0 | E64: 0 | F64: 0
B65: Chi phí công bố thông tin của Quỹ Expenses of information disclosure of the Fund | C65: 2230.4 | D65: 0 | E65: 0 | F65: 0
B66: Chi phí thiết kế, in ấn, gửi thư… Designing, printing, posting... expenses | C66: 2230.5 | D66: 0 | E66: 0 | F66: 0
A67: 9 | B67: Chi phí liên quan đến thực hiện các giao dịch tài sản của Quỹ Expenses related to execution of Fund’s asset transactions | C67: 2231 | D67: 1711293647 | E67: 2250724237 | F67: 21597362875
A68: ... | B68: ... | C68: ... | D68: ... | E68: ... | F68: ...
B69: Chi phí môi giới Brokerage fee | C69: 2231.1 | D69: 1703877192 | E69: 2243287045 | F69: 21531902091
B70: Chi phí thanh toán bù trừ Clearing settlement fee | C70: 2231.2 | D70: 7416455 | E70: 7437192 | F70: 65460784
B71: Chi phí khác Other Expenses | C71: 2231.3 | D71: 0 | E71: 0 | F71: 0
A72: 10 | B72: Các loại chi phí khác Other expenses | C72: 2232 | D72: 8430396 | E72: 8397804 | F72: 112107300
A73: ... | B73: ... | C73: ... | D73: ... | E73: ... | F73: ...
B74: Chi phí thiết lập Quỹ Set up Expenses | C74: 2232.1 | D74: 0 | E74: 0 | F74: 0
B75: Phí niêm yết, đăng ký chứng khoán Listing, registration fees | C75: 2232.2 | D75: 0 | E75: 0 | F75: 0
B76: Phí quản lý thường niên trả cho UBCKNN Annual management fee paid to SSC | C76: 2232.3 | D76: 635246 | E76: 614754 | F76: 7500000
B77: Phí ngân hàng Bank charges | C77: 2232.4 | D77: 7795150 | E77: 7783050 | F77: 99685300
B78: Chi phí lãi vay Borrowing expense | C78: 2232.5 | D78: 0 | E78: 0 | F78: 0
B79: Chi phí khác Other Expenses | C79: 2232.6 | D79: 0 | E79: 0 | F79: 3822000
B80: Phí thực hiện quyền trả cho VSDC Fee paid to VSDC for getting the list of investors | C80: 2232.7 | D80: 0 | E80: 0 | F80: 1100000
A81: III | B81: Thu nhập ròng từ hoạt động đầu tư (= I - II) Net Income from Investment Activities (= I - II) | C81: 2233 | D81: -2485407765 | E81: 263889079 | F81: -24971328165
A82: IV | B82: Lãi / (lỗ) từ hoạt động đầu tư Gain / (Loss) from Investment Activities | C82: 2234 | D82: 77583245200 | E82: -25154594500 | F82: 431049851405
A83: 1 | B83: Lãi (lỗ) thực tế phát sinh từ hoạt động đầu tư hoặc chuyển nhượng bất động sản Realised Gain / (Loss) from disposal of investment or real estate transfer | C83: 2235 | D83: 22894490122 | E83: 6419020674 | F83: 344517649497
A84: 2 | B84: Thay đổi về giá trị của các khoản đầu tư trong kỳ Unrealised Gain / (Loss) due to market price | C84: 2236 | D84: 54688755078 | E84: -31573615174 | F84: 86532201908
A85: V | B85: Thay đổi của giá trị tài sản ròng của Quỹ do các hoạt động đầu tư trong kỳ (III + IV) Change of Net Asset Value of the Fund due to investment activities during the period (= III + IV) | C85: 2237 | D85: 75097837435 | E85: -24890705421 | F85: 406078523240
A86: VI | B86: Giá trị tài sản ròng đầu kỳ Net Asset Value at the beginning of period | C86: 2238 | D86: 2802855037916 | E86: 2613534019879 | F86: 1506409920896
A87: VII | B87: Thay đổi giá trị tài sản ròng của Quỹ trong kỳ, Trong đó Change of Net Asset Value of the Fund during the period, of which | C87: 2239 | D87: 61687054381 | E87: 189321018037 | F87: 1358132171401
A88: 1 | B88: Thay đổi giá trị tài sản ròng của Quỹ do các hoạt động đầu tư của Quỹ trong kỳ Change of Net Asset Value due to investment activities during the period | C88: 2239.1 | D88: 75097837435 | E88: -24890705421 | F88: 406078523240
A89: 2 | B89: Thay đổi giá trị tài sản ròng của Quỹ do việc chi trả lợi tức/ cổ tức của Quỹ cho các nhà đầu tư trong kỳ Change of Net Asset Value due to dividends payment to investors during the period | C89: 2239.2 | D89: 0 | E89: 0 | F89: 0
A90: 3 | B90: Thay đổi giá trị tài sản ròng do phát hành thêm/mua lại chứng chỉ quỹ Change of Net Asset Value due to subscription/redemption during the period | C90: 2239.3 | D90: -13410783054 | E90: 214211723458 | F90: 952053648161
B91: Thay đổi giá trị tài sản ròng do phát hành thêm Chứng chỉ Quỹ Change of Net Asset Value due to subscription during the period | C91: 2239.3.1 | D91: 165650263367 | E91: 260948152018 | F91: 2232213231885
B92: Thay đổi giá trị tài sản ròng do mua lại Chứng chỉ Quỹ Change of Net Asset Value due to redemption during the period | C92: 2239.3.2 | D92: -179061046421 | E92: -46736428560 | F92: -1280159583724
A93: VIII | B93: Giá trị tài sản ròng cuối kỳ Net Asset Value at the end of period | C93: 2243 | D93: 2864542092297 | E93: 2802855037916 | F93: 2864542092297
A94: IX | B94: Lợi nhuận bình quân năm (chỉ áp dụng đối với báo cáo năm) Average annual profit (only applicable to annual report) | C94: 2244 | D94: 0 | E94: 0 | F94: 0
B95: Tỷ suất lợi nhuận bình quân năm (chỉ áp dụng đối với báo cáo năm) Average annual rate of return (only applicable to annual report) | C95: 2245 | D95: 0 | E95: 0 | F95: 0
A97: Đại diện có thẩm quyền của Ngân hàng giám sát | E97: Đại diện có thẩm quyền của Công ty quản lý Quỹ
A98: Authorised Representative of Supervisory Bank | E98: Authorised Representative of Fund Management Company
A105: Ngân hàng TNHH MTV Standard Chartered (Việt Nam) | E105: Công ty Cổ phần Quản lý Quỹ Đầu tư Dragon Capital Việt Nam
A106: Vũ Quang Phan | E106: Lê Hoàng Anh
A107: Phó phòng Dịch vụ nghiệp vụ giám sát Quỹ | E107: Quyền Giám đốc nghiệp vụ hỗ trợ đầu tư

Sheet BCDanhMucDauTu_06029
A1: Phụ lục XXVI. Mẫu báo cáo về hoạt động của Quỹ Appendix XXVI. Report on Fund's Operation
A2: (Ban hành kèm theo Thông tư số 98/2020/TT-BTC ngày 16 tháng 11 năm 2020 của Bộ trưởng Bộ Tài Chính về hướng dẫn hoạt động và quản lý quỹ đầu tư chứng khoán) (Issued in association with Circular 98/2020/TT-BTC dated 16 November 2020 of the Minister of Finance on guiding the operation and management of the securities investment funds)
A3: BÁO CÁO HOẠT ĐỘNG ĐẦU TƯ CỦA QUỸ MỞ REPORT ON OPEN ENDED FUND'S INVESTMENT ACTIVITIES
A5: =TONGQUAN!C1 -> Tại ngày 31 tháng 12 năm 2024 / As at 31 Dec 2024
A7: Tên Công ty quản lý quỹ: | C7: =TONGQUAN!D5 -> Công ty Cổ phần Quản lý Quỹ Đầu tư Dragon Capital Việt Nam
A8: Fund Management Company: | C8: =TONGQUAN!D6 -> Dragon Capital Vietfund Management Joint Stock Company
A9: Tên ngân hàng giám sát: | C9: =TONGQUAN!D7 -> Ngân hàng TNHH Một thành viên Standard Chartered (Việt Nam)
A10: Supervising bank: | C10: =TONGQUAN!D8 -> Standard Chartered Bank (Vietnam) Limited
A11: Tên Quỹ: | C11: =TONGQUAN!D9 -> Quỹ Đầu tư Chứng khoán Năng động DC
A12: Fund name: | C12: =TONGQUAN!D10 -> DC Dynamic Securities Fund (DCDS)
A13: Ngày lập báo cáo: | C13: =TONGQUAN!D11 -> Ngày 02 tháng 01 năm 2025
A14: Reporting Date: | C14: =TONGQUAN!D12 -> 02 Jan 2025
A16: A. | B16: BÁO CÁO CHUNG VỀ HOẠT ĐỘNG ĐẦU TƯ CỦA QUỸ/GENERAL INFORMATION ON FUND'S INVESTMENT ACTIVITIES
A17: III | B17: BÁO CÁO DANH MỤC ĐẦU TƯ / INVESTMENT PORTFOLIO REPORT
A18: STT No. | B18: Loại Category | C18: Mã chỉ tiêu Code | D18: Số Lượng Quantity | E18: Giá thị trường hoặc giá trị hợp lý tại ngày báo cáo Market price | F18: Tổng giá trị (Đồng) Value (VND) | G18: Tỷ lệ % Tổng giá trị tài sản của Quỹ % of total asset
A19: I | B19: BẤT ĐỘNG SẢN ĐẦU TƯ (KHÔNG ÁP DỤNG) REAL ESTATE INVESTMENT (NOT APPLICABLE)
B21: TỔNG TOTAL | C21: 2264
A22: II | B22: CỔ PHIẾU NIÊM YẾT, ĐĂNG KÝ GIAO DỊCH, CHỨNG CHỈ QUỸ NIÊM YẾT SHARES LISTED, SHARES REGISTERED FOR TRADING, LISTED FUND CERTIFICATES | C22: 2246
A24: 1 | B24: ACB | C24: 2246.1 | D24: 3417535 | E24: 25800 | F24: 88172403000 | G24: 0.029084814
A25: 2 | B25: ACV | C25: 2246.2 | D25: 234000 | E25: 125900 | F25: 29460600000 | G25: 0.0097179622
A26: 3 | B26: BAF | C26: 2246.3 | D26: 100100 | E26: 28100 | F26: 2812810000 | G26: 0.00092784198
A27: 4 | B27: BID | C27: 2246.4 | D27: 113740 | E27: 37550 | F27: 4270937000 | G27: 0.0014088241
A28: 5 | B28: BWE | C28: 2246.5 | D28: 415100 | E28: 47500 | F28: 19717250000 | G28: 0.0065039914
A29: 6 | B29: CMG | C29: 2246.6 | D29: 324180 | E29: 49250 | F29: 15965865000 | G29: 0.0052665483
A30: 7 | B30: CSV | C30: 2246.7 | D30: 318800 | E30: 45700 | F30: 14569160000 | G30: 0.004805827
A31: 8 | B31: CTD | C31: 2246.8 | D31: 668000 | E31: 68700 | F31: 45891600000 | G31: 0.015137941
A32: 9 | B32: CTG | C32: 2246.9 | D32: 4498626 | E32: 37800 | F32: 170048062800 | G32: 0.056092566
A33: 10 | B33: CTR | C33: 2246.10 | D33: 419400 | E33: 124500 | F33: 52215300000 | G33: 0.017223896
A34: 11 | B34: DGC | C34: 2246.11 | D34: 765700 | E34: 116600 | F34: 89280620000 | G34: 0.029450374
A35: 12 | B35: DXG | C35: 2246.12 | D35: 2138800 | E35: 15600 | F35: 33365280000 | G35: 0.011005972
... A74: 51 | B74: VPB | C74: 2246.51 | D74: 5426000 | E74: 19200 | F74: 104179200000 | G74: 0.034364865
B75: TỔNG TOTAL | C75: 2247 | F75: 2779933654900 | G75: 0.91699729
A76: III | B76: CỔ PHIẾU CHƯA NIÊM YẾT, ĐĂNG KÝ GIAO DỊCH, CHỨNG CHỈ QUỸ KHÔNG NIÊM YẾT SHARES UNLISTED, UNREGISTERED FOR TRADING, UNLISTED FUND CERTIFICATES | C76: 2248
B78: TỔNG TOTAL | C78: 2249 | F78: 0 | G78: 0
A79: IV | B79: TRÁI PHIẾU BONDS | C79: 2251
A81: 1 | B81: Trái phiếu niêm yết Listed bonds | C81: 2251.1 | F81: 0 | G81: 0
A82: 2 | B82: Trái phiếu chưa niêm yết Unlisted Bonds | C82: 2251.2 | F82: 0 | G82: 0
B83: TỔNG TOTAL | C83: 2252 | F83: 0 | G83: 0
A84: V | B84: CÁC LOẠI CHỨNG KHOÁN KHÁC OTHER SECURITIES | C84: 2253
A86: 1 | B86: Quyền mua chứng khoán Investment - Rights | C86: 2253.1 | F86: 0 | G86: 0
A87: 2 | B87: Chi tiết loại hợp đồng phái sinh(*) Index future contracts | C87: 2253.2 | F87: 0 | G87: 0
B88: TỔNG TOTAL | C88: 2254 | F88: 0 | G88: 0
B89: TỔNG CÁC LOẠI CHỨNG KHOÁN TOTAL TYPES OF SECURITIES | C89: 2255 | F89: 2779933654900 | G89: 0.91699729
A90: VI | B90: CÁC TÀI SẢN KHÁC OTHER ASSETS | C90: 2256
A92: 1 | B92: Cổ tức được nhận Dividend receivables | C92: 2256.1 | F92: 1534400000 | G92: 0.0005061418
A93: 2 | B93: Lãi trái phiếu được nhận Coupon receivables | C93: 2256.2 | F93: 0 | G93: 0
A94: 3 | B94: Lãi tiền gửi và công cụ thị trường tiền tệ được nhận Interest receivables from bank deposits and Money market instruments | C94: 2256.3 | F94: 0 | G94: 0
A95: 4 | B95: Tiền bán chứng khoán chờ thu Outstanding Settlement of sales transactions | C95: 2256.4 | F95: 117900715000 | G95: 0.038891085
A96: 5 | B96: Phải thu cho khoản cổ phiếu hạn chế chờ mua Receivable from AP/Investors on securities on hold of buying | C96: 2256.5 | F96: 0 | G96: 0
A97: 6 | B97: Phải thu khác Other receivables | C97: 2256.6 | F97: -866400000 | G97: -0.00028579331
A98: 7 | B98: Tài sản khác Other assets | C98: 2256.7 | F98: 0 | G98: 0
B99: TỔNG TOTAL | C99: 2257 | F99: 118568715000 | G99: 0.039111433
A100: VII | B100: TIỀN CASH | C100: 2258
A101: 1 | B101: Tiền, tương đương tiền Cash, Cash Equivalent | C101: 2259 | F101: 133059118550 | G101: 0.043891281
A103: 1.1 | B103: Tiền gửi ngân hàng Cash at Bank | C103: 2259.1 | F103: 133059118550 | G103: 0.043891281
A104: 1.2 | B104: Các khoản tương đương tiền Cash Equivalents | C104: 2259.2 | F104: 0 | G104: 0
A105: 2 | B105: Tiền gửi ngân hàng có kỳ hạn trên 3 tháng Deposits with term over three (03) months | C105: 2260 | F105: 0 | G105: 0
A107: 3 | B107: Công cụ thị trường tiền tệ Money market instruments | C107: 2261.1 | F107: 0 | G107: 0
B108: TỔNG TOTAL | C108: 2262 | F108: 133059118550 | G108: 0.043891281
A109: VIII | B109: Tổng giá trị danh mục Total value of portfolio | C109: 2263 | F109: 3031561488450 | G109: 1
A111: Đại diện có thẩm quyền của Ngân hàng giám sát | E111: Đại diện có thẩm quyền của Công ty quản lý Quỹ
A112: Authorised Representative of Supervisory Bank | E112: Authorised Representative of Fund Management Company
A121: Ngân hàng TNHH MTV Standard Chartered (Việt Nam) | E121: Công ty Cổ phần Quản lý Quỹ Đầu tư Dragon Capital Việt Nam
A122: Vũ Quang Phan | E122: Lê Hoàng Anh
A123: Phó phòng Dịch vụ nghiệp vụ giám sát Quỹ | E123: Quyền Giám đốc nghiệp vụ hỗ trợ đầu tư

Sheet BCHoatDongVay_06026
A1: Phụ lục XXVI. Mẫu báo cáo về hoạt động của Quỹ Appendix XXVI. Report on Fund's Operation
A2: (Ban hành kèm theo Thông tư số 98/2020/TT-BTC ngày 16 tháng 11 năm 2020 của Bộ trưởng Bộ Tài Chính về hướng dẫn hoạt động và quản lý quỹ đầu tư chứng khoán) (Issued in association with Circular 98/2020/TT-BTC dated 16 November 2020 of the Minister of Finance on guiding the operation and management of the securities investment funds)
A3: BÁO CÁO HOẠT ĐỘNG ĐẦU TƯ CỦA QUỸ MỞ REPORT ON OPEN ENDED FUND'S INVESTMENT ACTIVITIES
A5: =TONGQUAN!C2 -> Tháng 12 năm 2024 / Dec 2024
A7: Tên Công ty quản lý quỹ: | G7: =TONGQUAN!D5 -> Công ty Cổ phần Quản lý Quỹ Đầu tư Dragon Capital Việt Nam
A8: Fund Management Company: | G8: =TONGQUAN!D6 -> Dragon Capital Vietfund Management Joint Stock Company
A9: Tên ngân hàng giám sát: | G9: =TONGQUAN!D7 -> Ngân hàng TNHH Một thành viên Standard Chartered (Việt Nam)
A10: Supervising bank: | G10: =TONGQUAN!D8 -> Standard Chartered Bank (Vietnam) Limited
A11: Tên Quỹ: | G11: =TONGQUAN!D9 -> Quỹ Đầu tư Chứng khoán Năng động DC
A12: Fund name: | G12: =TONGQUAN!D10 -> DC Dynamic Securities Fund (DCDS)
A13: Ngày lập báo cáo: | G13: =TONGQUAN!D11 -> Ngày 02 tháng 01 năm 2025
A14: Reporting Date: | G14: =TONGQUAN!D12 -> 02 Jan 2025
A15: A. | B15: BÁO CÁO CHUNG VỀ HOẠT ĐỘNG ĐẦU TƯ CỦA QUỸ/GENERAL INFORMATION ON FUND'S INVESTMENT ACTIVITIES
A16: IV | B16: BÁO CÁO HOẠT ĐỘNG VAY, GIAO DỊCH MUA BÁN LẠI / REPORT ON BORROWING OPERATION, REPO/REVERSE REPO TRANSACTIONS
A17: STT No. | B17: Nội dung hoạt động (nên chi tiết theo mục tiêu và đối tác) Description | C17: Đối tác Counterparty | D17: Mục tiêu/ Tài sản đảm bảo Collateral | E17: Kỳ hạn Term | F17: Giá trị khoản vay hoặc khoản cho vay Amount | G17: Thời điểm giao dịch As at transaction date | I17: Thời điểm báo cáo As at reporting date
G18: Ngày tháng năm Date | H18: Tỷ lệ giá trị hợp đồng/giá trị tài sản ròng của quỹ/công ty (%) Balance/NAV (%) | I18: Ngày tháng năm Date | J18: Tỷ lệ giá trị hợp đồng/ giá trị tài sản ròng của quỹ/ công ty (%) Balance/NAV (%)
A19: 1 | B19: Các khoản vay tiền (nêu chi tiết từng hợp đồng)
A20: ... | B20: ... | C20: ... | D20: ... | E20: ... | F20: ... | G20: ... | H20: ... | I20: ... | J20: ...
A21: I | B21: Tổng giá trị các khoản vay tiền/giá trị tài sản ròng | F21: 0 | H21: 0 | J21: 0
A22: 2 | B22: Hợp đồng Repo (nêu chi tiết từng hợp đồng)
A23: ... | B23: ... | C23: ... | D23: ... | E23: ... | F23: ... | G23: ... | H23: ... | I23: ... | J23: ...
A24: II | B24: Tổng giá trị các hợp đồng Repo/giá trị tài sản ròng | F24: 0 | H24: 0 | J24: 0
A25: A | B25: Tổng giá trị các khoản vay/giá trị tài sản ròng (=I+II) | F25: 0 | H25: 0 | J25: 0
A26: 3 | B26: Cho vay chứng khoán (nêu chi tiết từng hợp đồng)
A27: ... | B27: ... | C27: ... | D27: ... | E27: ... | F27: ... | G27: ... | H27: ... | I27: ... | J27: ...
A28: III | B28: Tổng giá trị các hợp đồng/giá trị tài sản ròng | F28: 0 | H28: 0 | J28: 0
A29: 4 | B29: Hợp đồng Reverse Repo (nêu chi tiết từng hợp đồng)
A30: ... | B30: ... | C30: ... | D30: ... | E30: ... | F30: ... | G30: ... | H30: ... | I30: ... | J30: ...
A31: IV | B31: Tổng giá trị các hợp đồng/ giá trị tài sản ròng | F31: 0 | H31: 0 | J31: 0
A32: B | B32: Tổng giá trị các khoản cho vay/giá trị tài sản ròng (=III + IV) | F32: 0 | H32: 0 | J32: 0
A33: Đại diện có thẩm quyền của Ngân hàng giám sát | I33: Đại diện có thẩm quyền của Công ty quản lý Quỹ
A34: Authorised Representative of Supervisory Bank | I34: Authorised Representative of Fund Management Company
A43: Ngân hàng TNHH MTV Standard Chartered (Việt Nam) | I43: Công ty Cổ phần Quản lý Quỹ Đầu tư Dragon Capital Việt Nam
A44: Vũ Quang Phan | I44: Lê Hoàng Anh
A45: Phó phòng Dịch vụ nghiệp vụ giám sát Quỹ | I45: Quyền Giám đốc nghiệp vụ hỗ trợ đầu tư

Sheet Khac_06030
A1: Phụ lục XXVI. Mẫu báo cáo về hoạt động của Quỹ Appendix XXVI. Report on Fund's Operation
A2: (Ban hành kèm theo Thông tư số 98/2020/TT-BTC ngày 16 tháng 11 năm 2020 của Bộ trưởng Bộ Tài Chính về hướng dẫn hoạt động và quản lý quỹ đầu tư chứng khoán) (Issued in association with Circular 98/2020/TT-BTC dated 16 November 2020 of the Minister of Finance on guiding the operation and management of the securities investment funds)
A3: BÁO CÁO HOẠT ĐỘNG ĐẦU TƯ CỦA QUỸ MỞ REPORT ON OPEN ENDED FUND'S INVESTMENT ACTIVITIES
A5: Tháng 12 năm 2024 / Dec 2024
A7: Tên Công ty quản lý quỹ: | C7: Công ty Cổ phần Quản lý Quỹ Đầu tư Dragon Capital Việt Nam
A8: Fund Management Company: | C8: Dragon Capital Vietfund Management Joint Stock Company
A9: Tên ngân hàng giám sát: | C9: Ngân hàng TNHH Một thành viên Standard Chartered (Việt Nam)
A10: Supervising bank: | C10: Standard Chartered Bank (Vietnam) Limited
A11: Tên Quỹ: | C11: Quỹ Đầu tư Chứng khoán Năng động DC
A12: Fund name: | C12: DC Dynamic Securities Fund (DCDS)
A13: Ngày lập báo cáo: | C13: Ngày 02 tháng 01 năm 2025
A14: Reporting Date: | C14: 02 Jan 2025
A16: A. | B16: BÁO CÁO CHUNG VỀ HOẠT ĐỘNG ĐẦU TƯ CỦA QUỸ/GENERAL INFORMATION ON FUND'S INVESTMENT ACTIVITIES
A17: V | B17: MỘT SỐ CHỈ TIÊU KHÁC / OTHER INDICATORS
A18: STT No | B18: Chỉ tiêu Indicators | C18: Mã chỉ tiêu Code | D18: Tháng 12 năm 2024 Dec 2024 | E18: Tháng 11 năm 2024 Nov 2024
A19: I | B19: CÁC CHỈ TIÊU VỀ HIỆU QUẢ HOẠT ĐỘNG INVESTMENT PERFORMANCE INDICATORS | C19: 2264
A20: 1 | B20: Tỷ lệ giá dịch vụ quản lý quỹ trả cho công ty quản lý quỹ/Giá trị tài sản ròng trung bình trong kỳ (%) Management fee paid to the fund management company/Average NAV (%) | C20: 2265 | D20: 0.019821653 | E20: 0.019182343
A21: 2 | B21: Tỷ lệ giá dịch vụ lưu ký, giám sát trả cho Ngân hàng Giám sát/Giá trị tài sản ròng trung bình trong kỳ (%) Custody and supervising fees paid to the Supervisory Bank/Average NAV (%) | C21: 2266 | D21: 0.0010799382 | E21: 0.0010978855
A22: 3 | B22: Tỷ lệ chi phí dịch vụ quản trị quỹ, và các chi phí khác mà công ty quản lý quỹ trả cho tổ chức cung cấp dịch vụ có liên quan/Giá trị tài sản ròng của quỹ trung bình trong kỳ (%) Fund admin fee, and other fees paid to relating services providers by the fund management company/Average NAV (%) | C22: 22661 | D22: 0.00041004515 | E22: 0.00040035325
A23: 4 | B23: Chi phí kiểm toán trả cho tổ chức kiểm toán (nếu phát sinh)/Giá trị tài sản ròng trung bình trong kỳ (%) Auditing fee paid to auditing organizations (if any)/Average NAV (%) | C23: 2267 | D23: 7.2320913e-05 | E23: 7.4309994e-05
A24: 5 | B24: Chi phí trả cho tổ chức quản lý bất động sản/ Giá trị tài sản ròng trung bình trong kỳ (%) (không áp dụng) Fee paid to Real Estate management organisation/ Average NAV (%) (not applicable) | C24: 2286
A25: 6 | B25: Chi phí trả cho doanh nghiệp thẩm định giá bất động sản/Giá trị tài sản ròng trung bình trong kỳ (%) (không áp dụng) Fee paid to Real Estate valuation service provider/ Average NAV (%) (not applicable)
A26: 7 | B26: Chi phí dịch vụ tư vấn pháp lý, dịch vụ báo giá và các dịch vụ hợp lý khác, thù lao trả cho ban đại diện quỹ/Giá trị tài sản ròng trung bình trong kỳ (%) Legal consultancy, price quotation and other appropriate service fees; remunerations paid to the Board of Representatives/Average NAV (%) | C26: 2268 | D26: 7.0654172e-05 | E26: 7.4340758e-05
A27: 8 | B27: Tỷ lệ chi phí /Giá trị tài sản ròng trung bình trong kỳ (%) Expense/Average NAV (%) | C27: 2269 | D27: 0.021207415 | E27: 0.021282431
A28: 9 | B28: Tốc độ vòng quay danh mục trong kỳ (%)/Portfolio turnover rate (%) | C28: 2270 | D28: 3.8097458 | E28: 3.8866299
A29: 10 | B29: Tỷ lệ thu nhập (tính cả thu nhập từ lãi, cổ tức, trái tức, chênh lệch giá)/ Giá trị tài sản ròng (không áp dụng) Income (including interest income, dividend, coupon income and unrealised gain)/ Average NAV (%) (not applicable) | C29: 2287
A30: II | B30: CÁC CHỈ TIÊU KHÁC OTHER INDICATORS | C30: 2272
A31: 1 | B31: Quy mô quỹ đầu kỳ (tính theo mệnh giá chứng chỉ quỹ) Fund scale at the beginning of the period (based on par value of fund certificate) | C31: 2273 | D31: 353378237300 | E31: 325939036600
B32: Tổng giá trị chứng chỉ quỹ đang lưu hành đầu kỳ Total value of outstanding Fund Certificate at the beginning of period | C32: 2274 | D32: 353378237300 | E32: 325939036600
B33: Tổng số lượng chứng chỉ quỹ đang lưu hành đầu kỳ Total number of outstanding Fund Certificate at the beginning of period | C33: 2275 | D33: 35337824 | E33: 32593904
A34: 2 | B34: Thay đổi quy mô quỹ trong kỳ (tính theo mệnh giá chứng chỉ quỹ) Change of Fund scale during the period (based on par value of fund certificate) | C34: 2276 | D34: -1640346600 | E34: 27439200700
B35: Thay đổi số lượng chứng chỉ quỹ trong kỳ Change of Number of Fund Certificates during the period | C35: 22761 | D35: -164034.66 | E35: 2743920.1
B36: Thay đổi giá trị vốn trong kỳ (theo mệnh giá) Change in capital amount during the period (based on par value) | C36: 22762 | D36: -1640346600 | E36: 27439200700
B37: Số lượng chứng chỉ quỹ phát hành thêm trong kỳ Number of Fund Certificates subscribed during the period | C37: 2277 | D37: 2049801.8 | E37: 3340287.4
B38: Giá trị vốn huy động thêm trong kỳ (theo mệnh giá) Net subscription amount during the period (based on par value) | C38: 2278 | D38: 20498017900 | E38: 33402874200
B39: Số lượng chứng chỉ quỹ mua lại trong kỳ Number of Fund Certificates redeemed during the period | C39: 22781 | D39: -2213836.5 | E39: -596367.35
B40: Giá trị vốn phải thanh toán trong kỳ khi đáp ứng lệnh của nhà đầu tư (theo mệnh giá) Net redemption amount during the period (based on par value) | C40: 22782 | D40: -22138364500 | E40: -5963673500
A41: 3 | B41: Quy mô quỹ cuối kỳ (tính theo mệnh giá chứng chỉ quỹ) Fund scale at the end of the period (based on par value) | C41: 2279 | D41: 351737890700 | E41: 353378237300
B42: Tổng giá trị thị trường của quỹ đang lưu hành cuối kỳ (theo mệnh giá) Total value of outstanding Fund Certificate at the end of the period (based on par value) | C42: 2280 | D42: 351737890700 | E42: 353378237300
B43: Tổng số lượng chứng chỉ quỹ đang lưu hành cuối kỳ Total number of outstanding Fund Certificate at the end of the period | C43: 2281 | D43: 35173789 | E43: 35337824
A44: 4 | B44: Tỷ lệ nắm giữ chứng chỉ quỹ của công ty quản lý quỹ và người có liên quan cuối kỳ Fund Management Company and related parties' ownership ratio at the end of the period | C44: 2282 | D44: 0.083227078 | E44: 0.06331922
A45: 5 | B45: Tỷ lệ nắm giữ chứng chỉ quỹ của 10 nhà đầu tư lớn nhất cuối kỳ Top 10 investors' ownership ratio at the end of the period | C45: 2283 | D45: 0.2286 | E45: 0.2045
A46: 6 | B46: Tỷ lệ nắm giữ chứng chỉ quỹ của nhà đầu tư nước ngoài cuối kỳ Foreign investors' ownership ratio at the end of the period | C46: 2284 | D46: 0.1892 | E46: 0.168
A47: 7 | B47: Số nhà đầu tư tham gia vào quỹ, kể cả giao dịch ký danh Number of investors of the Fund at the end of the period | C47: 22841 | D47: 34156 | E47: 34747
A48: 8 | B48: Giá trị tài sản ròng trên một đơn vị quỹ cuối kỳ Net asset value per Fund Certificate at the end of period | C48: 2285 | D48: 81439.67 | E48: 79316
A49: 9 | B49: Giá trị thị trường trên một chứng chỉ quỹ/cổ phiếu cuối kỳ (không áp dụng) Market price per fund certificates at the end of period (not applicable) | C49: 2288
A50: Ghi chú: Note:
A51: (*) Các chỉ tiêu từ 1 đến 7 của "Chỉ tiêu về hiệu quả hoạt động" đã được điều chỉnh để phản ánh số liệu trên cơ sở hoạt động tròn năm bằng cách nhân các chỉ tiêu này với 12 (đối với báo cáo tháng), 4 (đối với báo cáo quý), 2 (đối với báo cáo bán niên), 1 (đối với báo cáo năm). All Indicator starting from number 1 to 7 of "Investment performance indicators" are annualized to reflect a rate that is based on a full year operation by multiplying these indicators with 12 (monthly report) or 4 (quarterly report) or 2 (semi-annual report) or 1 (annual report). (**) Không tính đến giá trị cam kết của các hợp đồng tương lai chỉ số. Excluding the committed value of the Index Futures contracts.
A52: Đại diện có thẩm quyền của Ngân hàng giám sát | D52: Đại diện có thẩm quyền của Công ty quản lý Quỹ
A53: Authorised Representative of Supervisory Bank | D53: Authorised Representative of Fund Management Company
A63: Ngân hàng TNHH MTV Standard Chartered (Việt Nam) | D63: Công ty Cổ phần Quản lý Quỹ Đầu tư Dragon Capital Việt Nam
A64: Vũ Quang Phan | D64: Lê Hoàng Anh
A65: Phó phòng Dịch vụ nghiệp vụ giám sát Quỹ | D65: Quyền Giám đốc nghiệp vụ hỗ trợ đầu tư

Sheet LogoFMS
D1: VFMVF1
A2: FUNDCODE | B2: FUNDNAME | C2: LOGO
A3: VFMVSF | B3: Quỹ Đầu Tư Cổ Phiếu Việt Nam Chọn Lọc
A4: VFMVF1 | B4: Quỹ Đầu tư Chứng khoán Năng động DC
A5: VFMVF4 | B5: Quỹ Đầu tư Doanh nghiệp Hàng đầu DC
A6: VFMVFA | B6: Quỹ Đầu tư Năng Động Việt Nam
A7: VFMVFB | B7: Quỹ Đầu tư Trái phiếu DC
A8: VFMVFC | B8: Quỹ Đầu tư Trái phiếu Gia tăng Thu nhập Cố định DC
A9: TCEF1 | B9: Quỹ Đầu tư Cổ phiếu Techcom
A10: TCBF | B10: Quỹ Đầu tư Cổ phiếu Techcom
A11: MBEF1 | B11: Quỹ Đầu tư JAPAN ASIA MB CAPITAL
A12: MBVF | B12: Quỹ Đầu tư Giá trị MB Capital
A13: SSISCA | B13: Quỹ Đầu tư Lợi thế Cạnh tranh Bền vững SSI
A14: VCBBCF | B14: Quỹ Đầu tư Cổ Phiếu Hàng Đầu VCBF
... A52: VCBMGF | B52: Quỹ Đầu Tư Cổ phiếu Tăng trưởng VCBF
A53: AM33
A54: AM34
A55: AM35
A56: AM36 | B56: Tổng công ty cổ phần bảo hiểm Petrolimex - PJICO EQUITY PORTFOLIO 04
A57: AM37
A58: AM38
A59: AM39
A60: AM40
A61: AM41
A62: AM42
A63: AM43
A64: AM44
A65: AM45
A66: AM46
A67: AM47
A68: AM48
... A70: AM50
A71: VMPF | B71: Quỹ Đầu Tư Cổ Phiếu Hiệu Suất Thị Trường Việt Nam VinaCapital (VinaCapital-VMPF)
A72: ENF
A73: EVESG
A74: UVDIF
A75: VDEF
A76: VCBAIF
